Workbook
Name ClearData: Key_Stats!$K$28:$M$52
Name FormatTable: Key_Stats!$U$15:$W$17
Name IQ_CH: 110000
Name IQ_CQ: 5000
Name IQ_CY: 10000
Name IQ_DAILY: 500000
Name IQ_FH: 100000
Name IQ_FQ: 500
Name IQ_FY: 1000
Name IQ_LTM: 2000
Name IQ_MONTH: 15000
Name IQ_NTM: 6000
Name IQ_WEEK: 50000
Name IQ_YTD: 3000
Name KI: IF(Key_Stats!$L$25="",Key_Stats!$E$25:$K$25,Key_Stats!$E$25:$M$25)
Name SKF: IF(Key_Stats!$L$26="",Key_Stats!$E$26:$K$26,Key_Stats!$E$26:$M$26)

Sheet __snloffice
A1: 允䅁䱁䤰䅁㡂䅁䅁睊扂䕁䄰兓時䕁䅍睢瑂䡁䅁兙畂䡁䅫睘䱂䝁䅕入呂䡁䅑兙あ䡁䅍睘㉂䑁䅅兌䑂䝁䄸䅣㕂䍁䄴䅥獂䡁䅍兢摂䕁䅉兙獂䝁䅅杢橂䝁䅕睘呂䝁䅧党求䡁䅑睊桁䍁䅑睑歁䑁䅫杏歁䕁䅍䅊硁䑁䅍兏䅁䡁䙯䅁䕃䅁䅁睊扂䕁䄰兓時䕁䅍睢瑂䡁䅁兙畂䡁䅫睘䱂䝁䅕入呂䡁䅑兙あ䡁䅍睘㉂䑁䅅䅉潁䑁䅍克畁䡁䅧䅢穂䝁䄰兘䑂䝁䅅䅣灂䡁䅑兙獂䙁䄸睕あ䡁䅉兤橂䡁䅑兤祂䝁䅕睘呂䡁䅕兢瑂䝁䅅杣㕂䍁䅣光歁䕁䅍䅊ぁ䅁䅁杙䅑䡁䅉䅁湁䙁䅳兔䩂䙁䄸睑療䝁䄰䅣桂䝁䄴入時䕁䅳党㕂䙁䅍䅤桂䡁䅑督時䡁䅙免瑁䍁䅁睔祂䝁䅫睚灂䝁䄴兙獂䍁䄴䅥獂䡁䅍兢摂䕁䅳党㕂䙁䄸睕あ䝁䅅䅤穂䍁䅣光歁䕁䅉䅊祁䑁䅍䅁捂兂䅁䅤䅁䙁䅳兔䩂䙁䄸睑療䝁䄰䅣桂䝁䄴入時䕁䅳党㕂䙁䅍䅤桂䡁䅑督時䡁䅙免時䍁䄴䅥獂䡁䅍兢摂䕁䅉兙獂䝁䅅杢橂䝁䅕睘呂䝁䅧党求䡁䅑光歁䕁䅕䅊硁䑁䅑䅎㙁䍁䅑䅕歁䑁䅅䅎ぁ䅁䅁䄴䅑䑁䅙䅁乂䝁䅅杣牂䝁䅕䅤杁䕁䅍兙睂䝁䅫䅤桂䝁䅷兡㙂䝁䅅䅤灂䝁䄸杢杁䍁䅧䅊乂䍁䅫䅁牃兂䅁䅤䅁䍁䅣睗乂䕁䅫睘䑂䝁䄸兢睂䝁䅅杢㕂䙁䄸睓求䡁䅫睕あ䝁䅅䅤穂䙁䄸杤硁䍁䄰睑療䡁䅁入畁䡁䅧䅢穂䝁䄰兘䱂䝁䅕入時䙁䅍䅤桂䡁䅑督湁䍁䅅䅊䕂䍁䅑杍㑁䑁䅯䅊䕂䍁䅑兎祁䅁䅁杉䅕䍁䅑䅁䩂䙁䅅睘佂䕁䅫睘佂䕁䄸杕乂䙁䄸兔䉂䙁䅉睒䩂䕁䄴䅁偁杁䅁杣䅁䙁䅳睕兂䕁䅣睘䑂䝁䄸兢睂䝁䅅杢㕂䙁䄸睓求䡁䅫睕あ䝁䅅䅤穂䙁䄸杤硁䍁䄴䅥獂䡁䅍兢摂䕁䅫杢橂䝁䄸兢求䙁䄸睕あ䝁䅅䅤求䝁䄰党畂䡁䅑光歁䕁䅕䅊㉁䑁䅯䅊兂䍁䅑李䅁佁䙕䅁浂䅁䅁睊扂䕁䅳党㕂䙁䅍䅤桂䡁䅑督時䡁䅑党穂䡁䅑杚灂䝁䅷党畁䡁䅧䅢穂䝁䄰兘兂䝁䅕杢穂䝁䅫睢畂䍁䄰睔兂䕁䅕村湁䍁䅅䅊䕂䍁䅑兏㙁䍁䅑䅒歁䑁䅅䅎㕁䅁䅁杵䅉䝁䅯䅁湁䙁䅳睕兂䕁䅣睘䑂䝁䄸兢睂䝁䅅杢㕂䙁䄸睓求䡁䅫睕あ䝁䅅䅤穂䙁䄸杤硁䍁䅁䅋祁䍁䅫杌㑂䝁䅷督瑂䙁䄰杕桂䡁䅑兡療䡁䅍睊桁䍁䅑䅒歁䑁䅙杏歁䕁䅫䅊㉁䅁䅁兒䅙䙁䅷䅁扂䕁䅳党㕂䙁䅍䅤桂䡁䅑督時䡁䅑党穂䡁䅑杚灂䝁䅷党畁䡁䅧䅢穂䝁䄰兘䱂䝁䅕入時䙁䅍䅤桂䡁䅑督桁䍁䅑睑歁䑁䅕䅎㙁䍁䅑睑歁䑁䅕兎䅁乁䅧䅁奂䅁䅁睊扂䕁䅳党㕂䙁䅍䅤桂䡁䅑督時䡁䅑党穂䡁䅑杚灂䝁䅷党畁䡁䅧䅢穂䝁䄰兘兂䝁䅕杢穂䝁䅫睢畂䍁䄰睔兂䕁䅕村湁䍁䅅䅊䑂䍁䅑䅎䅁䱁䍧䅁坂䅁䅁睗呂䙁䅁睒時䕁䅍睢瑂䡁䅁兙畂䡁䅫睘䱂䝁䅕入呂䡁䅑兙あ䡁䅍睘㉂䑁䅉杌㑂䝁䅷督瑂䙁䄰睕潂䝁䅕党あ䑁䅅光歁䕁䅳䅊硁䑁䅅䅁橃杂䅁来䅁䙁䅳睕兂䕁䅣睘䑂䝁䄸兢睂䝁䅅杢㕂䙁䄸睓求䡁䅫睕あ䝁䅅䅤穂䙁䄸杤硁䍁䄴䅥獂䡁䅍兢摂䕁䅍兙睂䝁䅫䅤桂䝁䅷睘呂䡁䅑杣ㅂ䝁䅍䅤ㅂ䡁䅉党時䙁䅍兤瑂䝁䄰兙祂䡁䅫光歁䕁䅍䅊㉁䅁䅁䄯䅕䑁䅧䅁䩂䙁䅅睘啂䕁䄸䅖䉂䕁䅷睘塂䕁䅅杕卂䕁䅅杔啂䙁䅍睘䑂䕁䅅杔䑂䕁䅕䅔䵂䕁䅕䅒䅁䕁䑑䅁睂䅁䅁睊扂䕁䄰兓時䕁䅍睢瑂䡁䅁兙畂䡁䅫睘䱂䝁䅕入呂䡁䅑兙あ䡁䅍睘㉂䑁䅅䅉潁䑁䅍克畁䡁䅧䅢穂䝁䄰兘䑂䝁䅅䅣灂䡁䅑兙獂䝁䅫来桂䡁䅑兡療䝁䄴睊桁䍁䅑睑歁䑁䅑睎䅁䙁䔴䅁煂䅁䅁睑ㅂ䡁䅉杣求䝁䄴䅤杁䕁䅷睢畂䝁䅣䅉啂䝁䅕杣瑂䍁䅁䅒求䝁䅉䅤杁䝁䅅杢歂䍁䅁睑桂䡁䅁兡あ䝁䅅䅢杁䕁䅷党桂䡁䅍党穂䍁䅁䅋卂䝁䅕䅣療䡁䅉䅤求䝁䅑克䅁䍁䈰䅁䝂䅁䅁䅒求䝁䅙党祂䡁䅉党歂䍁䅁䅒療䝁䄰党穂䡁䅑兡橂䍁䅁䅖桂䡁䅧党穂䍁䅁䅋卂䝁䅕䅣療䡁䅉䅤求䝁䅑克䅁䥁䐴䅁潁䅁䅁睉䩂䕁䄴杖䉂䕁䅷兓䕂䍁䅁睑偂䕁䄰䅕䉂䕁䄴兗杁䕁䅫䅒䅁䥁䝕䅁祂䅁䅁睊扂䕁䄰兓時䕁䅍睢瑂䡁䅁兙畂䡁䅫睘䱂䝁䅕入呂䡁䅑兙あ䡁䅍睘㉂䑁䅅兌䑂䝁䄸䅣㕂䍁䄴䅥獂䡁䅍兢摂䕁䅍兙穂䝁䅧睘䝂䝁䅷睢㍂䍁䅣光歁䕁䅍䅊㕁䑁䅯䅊䑂䍁䅑兏睁䅁䅁杦䅕䝁䅁䅁扂䙁䅍䅕䡂䙁䄸睑療䝁䄰䅣桂䝁䄴入時䕁䅳党㕂䙁䅍䅤桂䡁䅑督時䡁䅙杍畁䡁䅧䅢穂䝁䄰兘呂䡁䅕䅣睂䝁䅷党瑂䝁䅕杢あ䝁䅅䅢桁䍁䅑睑歁䑁䅙䅁佁䅃䅁䅎䅁䕁䅫兕時䕁䅷䅖時䕁䅑兒䍂䙁䅑睘䑂䕁䅅䅕䩂䙁䅑兑䵂䙁䄸䅔䙂䕁䅅睕䙂䙁䅍䅁畁允䅁杦䅁䍁䅣睗乂䕁䅫睘䑂䝁䄸兢睂䝁䅅杢㕂䙁䄸睓求䡁䅫睕あ䝁䅅䅤穂䙁䄸杤硁䍁䄰䅉偂䡁䅉兡湂䝁䅫杢桂䝁䅷杌㑂䝁䅷督瑂䙁䄰睓求䡁䅫睘呂䡁䅑兙あ䡁䅍睊桁䍁䅑兒歁䑁䅉杍㙁䍁䅑䅔歁䑁䅉杍䅁䝁䙧䅁畂䅁䅁睗乂䕁䅫睘䑂䝁䄸兢睂䝁䅅杢㕂䙁䄸睓求䡁䅫睕あ䝁䅅䅤穂䙁䄸杤硁䙁䄸杌㑂䝁䅷督瑂䙁䄰睑桂䡁䅁兡あ䝁䅅䅢灂䡁䅯兙あ䝁䅫睢畂䍁䅅䅊䙂䍁䅑䅎㙁䍁䅑杓歁䑁䅑䅁浄䅂䅁杁䅁䅁䅁光䅁䥁䅧䅁湁䙁䅳睕兂䕁䅣睘䑂䝁䄸兢睂䝁䅅杢㕂䙁䄸睓求䡁䅫睕あ䝁䅅䅤穂䙁䄸杤祁䍁䅁免畁䡁䅧䅢穂䝁䄰兘䑂䝁䅅䅣灂䡁䅑兙獂䙁䄸睕あ䡁䅉兤橂䡁䅑兤祂䝁䅕睘杁䕁䅑党あ䝁䅅兡獂䡁䅍䅉湁䍁䅅䅊䑂䍁䅑睎㉁䅁䅁兆䅣䝁䅁䅁扂䕁䅳党㕂䙁䅍䅤桂䡁䅑督時䡁䅑党穂䡁䅑杚灂䝁䅷党畁䡁䅧䅢穂䝁䄰兘䱂䝁䅕入時䙁䅍䅤桂䡁䅑督桁䍁䅑兒歁䑁䅅䅍睁䑁䅯䅊䡂䍁䅑免睁䑁䅁䅁牄䅁䅁䅨䅁䍁䅣睗呂䙁䅁睒時䕁䅍睢瑂䡁䅁兙畂䡁䅫睘䱂䝁䅕入呂䡁䅑兙あ䡁䅍睘㉂䑁䅉杌㑂䝁䅷督瑂䙁䄰睑桂䡁䅁兡あ䝁䅅䅢時䙁䅍䅤祂䡁䅕睙あ䡁䅕杣求䙁䄸䅉䕂䝁䅕䅤桂䝁䅫䅢穂䍁䅁睊桁䍁䅑䅓歁䑁䅅杍䅁䍁䥉䅁佁䅁䅁睉䙂䙁䅉杕偂䙁䅉䅁呄䅁䅁杆䅁䕁䅫兕時䙁䅁兒時䕁䄴睔卂䕁䄰䅁噂杂䅁䅚䅁䕁䄸䅣あ䝁䅫睢畂䡁䅍䅉䡂䡁䅉兙畂䡁䅑党歂䍁䅁䅒ㅂ䡁䅉兡畂䝁䅣䅉あ䝁䅧党杁䙁䅁党祂䝁䅫睢歂䍁䅷䅉啂䝁䄸䅤桂䝁䅷䅉潁䝁䅅睙あ䡁䅕兙獂䍁䅫䅁䉂睁䅁杋䅁䍁䅍兓佂䙁䅙兑䵂䕁䅫䅒杁䕁䄰兒啂䙁䅉兓䑂䍁䅁杔䉂䕁䄰兒䅁䡁䝳䅁㉁䅁䅁兓剂䙁䄸睕䙂䕁䅍睔佂䕁䅑睘䵂䕁䅫兒佂䙁䄸村偂䕁䄴䅒呂䙁䄸杔偂䙁䅑兒呂䅁䅁䅒䅅䍁䅙䅁䵂䙁䅑䅉䕂䝁䅕杙あ䍁䄸兒硂䡁䅕兡あ䡁䅫䅉潁䍁䅕克䅁䱁䍕䅁獁䅁䅁睑䩂䙁䅅䅉卂䝁䅕督あ䝁䅅䅤求䝁䄰党畂䡁䅑䅉啂䡁䅫䅣求䍁䅁䅁牁睁䅁䅪䅁䍁䅣睗䑂䝁䄸䅣㕂䍁䅁睢浂䍁䅁睕兂䕁䅣睘䑂䝁䄸兢睂䝁䅅杢㕂䙁䄸睓求䡁䅫睕あ䝁䅅䅤穂䙁䄸杤硁䙁䄸杒灂䝁䄴兙獂䍁䄴䅥獂䡁䅍兢摂䕁䅉兙獂䝁䅅杢橂䝁䅕睘呂䝁䅧党求䡁䅑睊桁䍁䅑兒歁䑁䅙杏歁䙁䅅䅊㉁䅁䅁䅘䅧䙁䅙䅁扂䕁䅳党㕂䙁䅍䅤桂䡁䅑督時䡁䅑党穂䡁䅑杚灂䝁䅷党畁䡁䅧䅢穂䡁䅧兘呂䝁䅧党求䡁䅑免桁䍁䅑兒歁䑁䅉免㙁䍁䅑睒歁䑁䅉免䅁䑁䅍䅁㑁䅁䅁睉䩂䕁䄴杖䉂䕁䅷兓䕂䍁䅁杒噂䕁䄴睑啂䕁䅫睔佂䍁䅁䅕䉂䙁䅉兑乂䕁䅕䅖䙂䙁䅉䅁牂杂䅁䅑䅁䙁䅑睢あ䝁䅅䅢杁䙁䅍兤楂䍁䄴䅉䕂䝁䅕杙あ䍁䄸䅉啂䝁䄸䅤桂䝁䅷䅉䕂䝁䅕杙あ䍁䅁䅋汁䍁䅫䅁橁允䅁䅧䅁䍁䅣睗䑂䝁䄸䅣㕂䍁䅁睢浂䍁䅁睕兂䕁䅣睘䑂䝁䄸兢睂䝁䅅杢㕂䙁䄸睓求䡁䅫睕あ䝁䅅䅤穂䙁䄸杤祁䙁䄸杢求䡁䅣杌㑂䝁䅷督瑂䙁䄰睑桂䡁䅍䅡時䕁䅙䅢療䡁䅣睊桁䍁䅑兒歁䑁䅙杏歁䙁䅁䅊㉁䅁䅁睒䅣䡁䅑䅁湁䙁䅳睕兂䕁䅣睘䑂䝁䄸兢睂䝁䅅杢㕂䙁䄸睓求䡁䅫睕あ䝁䅅䅤穂䙁䄸杤硁䍁䅁䅋祁䍁䅫杌㑂䝁䅷督瑂䙁䄰兓畂䝁䅍睢瑂䝁䅕睘呂䡁䅑兙あ䝁䅕兢求䝁䄴䅤湁䍁䅅䅊䑂䍁䅑李䅁䍁䝑䅁潁䅁䅁兓剂䙁䄸睕䙂䕁䅍兖卂䕁䅕䅒時䕁䅑兒䍂䙁䅑睘兂䕁䅍䅖䅁䙁䉷䅁⭂䅁䅁睊扂䙁䅍䅕䡂䙁䄸睑療䝁䄰䅣桂䝁䄴入時䕁䅳党㕂䙁䅍䅤桂䡁䅑督時䡁䅙免杁䍁䅧杍灁䍁䄴䅥獂䡁䅍兢摂䕁䅍兙睂䝁䅫䅤桂䝁䅷兡㙂䝁䅅䅤灂䝁䄸杢湁䍁䅅䅊䑂䍁䅑兎穁䑁䅯䅊䑂䍁䅑兎ぁ䅁䅁李䅙䕁䅑䅁啂䝁䄸䅤桂䝁䅷䅉卂䝁䅕杤求䝁䄴兤求䡁䅍䅌杁䑁䅅䅉婂䝁䅕兙祂䍁䅁睒祂䝁䄸睤あ䝁䅧䅉潁䍁䅕克䅁䅁䅑䅁捂䅁䅁睊扂䕁䄰兓時䕁䅳党㕂䙁䅍䅤桂䡁䅑督時䡁䅙免畁䡁䅧䅢穂䝁䄰兘兂䝁䅕杢穂䝁䅫睢畂䍁䄰睔兂䕁䅕村湁䍁䅅䅊䕂䍁䅑䅎㙁䍁䅑兓歁䑁䅑䅁ㅃ睁䅁杙䅁䙁䅳兔䩂䙁䄸睑療䝁䄰䅣桂䝁䄴入時䕁䅳党㕂䙁䅍䅤桂䡁䅑督時䡁䅙免時䍁䄴䅥獂䡁䅍兢摂䙁䅉兙あ䝁䅫睢穂䍁䅅䅊䑂䍁䅑兏㙁䍁䅑睑歁䑁䅅兎睁䅁䅁眫䅑䅁䅷䅁橁䙁䅁兒佂䕁䅑䅁桄睁䅁杦䅁䍁䅣睗乂䕁䅫睘䑂䝁䄸兢睂䝁䅅杢㕂䙁䄸睓求䡁䅫睕あ䝁䅅䅤穂䙁䄸杤硁䍁䄰睑療䡁䅁入畁䡁䅧䅢穂䝁䄰兘䩂䝁䄴睙療䝁䄰党時䙁䅍䅤桂䡁䅑党瑂䝁䅕杢あ䍁䅣光歁䕁䅕䅊ぁ䑁䅯䅊兂䍁䅑䅎䅁䕁䘸䅁楂䅁䅁睊扂䕁䅳党㕂䙁䅍䅤桂䡁䅑督時䡁䅑党穂䡁䅑杚灂䝁䅷党畁䡁䅧䅢穂䝁䄰兘兂䝁䅕杢穂䝁䅫睢畂䍁䄰睔兂䕁䅕村湁䍁䅅䅊䝂䍁䅑兎㙁䍁䅑睓歁䑁䅕䅁㝃杁䅁杚䅁䍁䅣睗䱂䝁䅕入呂䡁䅑兙あ䡁䅍睘あ䝁䅕督あ䝁䅙兡獂䝁䅕杌㑂䝁䅷督瑂䙁䄰䅕求䝁䄴督灂䝁䄸杢瑁䕁䄸䅕䙂䕁䅉睊桁䍁䅑䅒歁䑁䅫杏歁䕁䅑䅊ㅁ䑁䅙睎䅁䝁䑍䅁啁䅁䅁兓剂䙁䄸䅕䙂䙁䄸䅔啂䕁䄰䅁䥄睂䅁䅦䅁䍁䅣睗乂䕁䅫睘䑂䝁䄸兢睂䝁䅅杢㕂䙁䄸睓求䡁䅫睕あ䝁䅅䅤穂䙁䄸杤硁䍁䅁䅋穁䍁䅫杌㑂䝁䅷督瑂䙁䄰睑桂䡁䅁兡あ䝁䅅䅢灂䡁䅯兙あ䝁䅫睢畂䍁䅣光歁䕁䅕䅊ぁ䑁䅣杏歁䙁䅁䅊ぁ䑁䅣䅁扂䅂䅁村䅁䕁䄴睢祂䝁䄰兙獂䝁䅫来求䝁䅑䅉佂䝁䅕䅤杁䕁䅫杢橂䝁䄸兢求䍁䅁兔桂䡁䅉睚灂䝁䄴䅉潁䍁䅕克䅁䉁䍁䅁潂䅁䅁睗呂䙁䅁睒時䕁䅍睢瑂䡁䅁兙畂䡁䅫睘䱂䝁䅕入呂䡁䅑兙あ䡁䅍睘㉂䑁䅅杌㑂䝁䅷督瑂䙁䄰睓求䡁䅫睘呂䡁䅑兙あ䡁䅍光歁䙁䅍䅊ㅁ䑁䅧杏歁䙁䅍䅊㉁䑁䅅䅁桄兂䅁䅃䅁䕁䅙兗睁䅁䅁䅄䅁䕁䅑䅁啂䝁䄸䅤桂䝁䅷䅉呂䝁䅕杢灂䝁䄸杣杁䕁䅑党楂䡁䅑睌杁䙁䅑睢あ䝁䅅䅢杁䕁䅑党楂䡁䅑䅉潁䍁䅕克䅁䉁䈸䅁浂䅁䅁睊扂䕁䅳党㕂䙁䅍䅤桂䡁䅑督時䡁䅑党穂䡁䅑杚灂䝁䅷党畁䡁䅧䅢穂䝁䄰兘兂䝁䅕杢穂䝁䅫睢畂䍁䄰睔兂䕁䅕村湁䍁䅅䅊䕂䍁䅑兏㙁䍁䅑䅒歁䑁䅕李㑁䅁䅁䅚䅍䝁䅉䅁湁䙁䅳睓求䡁䅫睕あ䝁䅅䅤穂䙁䄸䅤求䡁䅍䅤浂䝁䅫䅢求䍁䄴䅥獂䡁䅍兢摂䙁䅁党畂䡁䅍兡療䝁䄴兌偂䙁䅁兒䍂䍁䅣光歁䕁䅙䅊ぁ䑁䅯䅊䱂䍁䅑䅎䅁䱁䍫䅁獂䅁䅁睊扂䙁䅍䅕䡂䙁䄸睑療䝁䄰䅣桂䝁䄴入時䕁䅳党㕂䙁䅍䅤桂䡁䅑督時䡁䅙杍杁䑁䅅杌㑂䝁䅷督瑂䙁䄰杕桂䡁䅑兡療䡁䅍睊桁䍁䅑睑歁䑁䅅免㙁䍁䅑睑歁䑁䅅兎㑁䅁䅁儫䅙䡁䅙䅁湁䙁䅳兔䩂䙁䄸睑療䝁䄰䅣桂䝁䄴入時䕁䅳党㕂䙁䅍䅤桂䡁䅑督時䡁䅙免杁䍁䅧睍灁䍁䄴䅥獂䡁䅍兢摂䕁䅉兙獂䝁䅅杢橂䝁䅕睘呂䝁䅧党求䡁䅑睊桁䍁䅑兒歁䑁䅕杏歁䙁䅁䅊ㅁ䅁䅁兕䅑䥁䅧䅁湁䙁䅳睑療䡁䅁入杁䝁䄸杚杁䙁䅍䅕䡂䙁䄸睑療䝁䄰䅣桂䝁䄴入時䕁䅳党㕂䙁䅍䅤桂䡁䅑督時䡁䅙免時䕁䅙兡畂䝁䅅䅢畁䡁䅧䅢穂䝁䄰兘䩂䝁䄴睙療䝁䄰党時䙁䅍䅤桂䡁䅑党瑂䝁䅕杢あ䍁䅣光歁䕁䅍䅊㉁䅁䅁睖䅧䕁䅙䅁䩂䙁䅅睘䝂䕁䅅兓卂䙁䄸杖䉂䕁䅷兖䙂䙁䄸睑䥂䕁䅅杔䡂䕁䅕睘䩂䕁䄴睑䵂䙁䄸兒䉂䙁䅉杔䩂䕁䄴睒呂䅁䅁䅋䅍䡁䅧䅁䩂䝁䄴䅤求䡁䅉党穂䡁䅑䅉桂䝁䄴䅚杁䙁䅁党畂䝁䅅䅢あ䝁䅫党穂䍁䅁杕求䝁䅍睢湂䍁䄴䅉療䝁䄴䅉䍂䙁䅍䅉瑁䍁䅁村求䝁䅙睢祂䝁䅕䅉啂䝁䅅䅥杁䍁䅧杕求䡁䅁睢祂䡁䅑党歂䍁䅫䅁呁睁䅁䅦䅁䍁䅣睗䑂䝁䄸䅣㕂䍁䅁睢浂䍁䅁睕兂䕁䅣睘䑂䝁䄸兢睂䝁䅅杢㕂䙁䄸睓求䡁䅫睕あ䝁䅅䅤穂䙁䄸杤硁䙁䄸杒灂䝁䄴兙獂䍁䄴䅥獂䡁䅍兢摂䕁䅳党㕂䙁䄸睕あ䝁䅅䅤穂䍁䅣光歁䕁䅉䅊祁䑁䅕䅁䉂䅃䅁杣䅁䍁䅣睗乂䕁䅫睘䑂䝁䄸兢睂䝁䅅杢㕂䙁䄸睓求䡁䅫睕あ䝁䅅䅤穂䙁䄸杤硁䍁䅁䅋穁䍁䅫杌㑂䝁䅷督瑂䙁䄰睓求䡁䅫睘呂䡁䅑兙あ䡁䅍睊桁䍁䅑睑歁䑁䅉兎㙁䍁䅑睑歁䑁䅑兏䅁䑁䕉䅁煁䅁䅁兓剂䙁䄸杔䩂䙁䄸免婂䙁䅉睘䉂䕁䄴杔時䕁䅣杕偂䙁䅣䅖䥂䅁䅁先䅉䥁䄴䅁湁䙁䅳睑療䡁䅁入杁䝁䄸杚杁䙁䅍䅕䡂䙁䄸睑療䝁䄰䅣桂䝁䄴入時䕁䅳党㕂䙁䅍䅤桂䡁䅑督時䡁䅙杍時䝁䄴党㍂䍁䄴䅥獂䡁䅍兢摂䕁䅫杢橂䝁䄸兢求䙁䄸睕あ䝁䅅䅤求䝁䄰党畂䡁䅑睊桁䍁䅑兒歁䑁䅣杏歁䙁䅅䅊㍁䅁䅁兰䅣䝁䅑䅁湁䙁䅳睕兂䕁䅣睘䑂䝁䄸兢睂䝁䅅杢㕂䙁䄸睓求䡁䅫睕あ䝁䅅䅤穂䙁䄸杤祁䍁䅁免畁䡁䅧䅢穂䝁䄰兘䱂䝁䅕入時䙁䅍䅤桂䡁䅑督湁䍁䅅䅊䙂䍁䅑李穁䅁䅁朰䅙䡁䅉䅁湁䙁䅳兔䩂䙁䄸睑療䝁䄰䅣桂䝁䄴入時䕁䅳党㕂䙁䅍䅤桂䡁䅑督時䡁䅙免瑁䕁䅍睢睂䡁䅫杌㑂䝁䅷督瑂䙁䄰睑桂䡁䅁兡あ䝁䅅䅢灂䡁䅯兙あ䝁䅫睢畂䍁䅣光歁䕁䅍䅊ㅁ䑁䅫䅁䝂兂䅁䅚䅁䙁䅳兔䩂䙁䄸睑療䝁䄰䅣桂䝁䄴入時䕁䅳党㕂䙁䅍䅤桂䡁䅑督時䡁䅙免畁䡁䅧䅢穂䝁䄰兘䑂䝁䅅䅣灂䡁䅑兙獂䝁䅫来桂䡁䅑兡療䝁䄴光歁䕁䅍䅊ぁ䑁䅧䅁啁䅂䅁䅢䅁䍁䅣睗乂䕁䅫睘䑂䝁䄸兢睂䝁䅅杢㕂䙁䄸睓求䡁䅫睕あ䝁䅅䅤穂䙁䄸杤硁䍁䅁䅋穁䍁䅫杌㑂䝁䅷督瑂䙁䄰村桂䝁䅷兙畂䝁䅍党時䙁䅍䅡求䝁䅕䅤湁䍁䅅䅊䑂䍁䅑䅎䅁䕁䔴䅁歂䅁䅁睗乂䕁䅫睘䑂䝁䄸兢睂䝁䅅杢㕂䙁䄸睓求䡁䅫睕あ䝁䅅䅤穂䙁䄸杤硁䍁䄴䅥獂䡁䅍兢摂䕁䅍兙睂䝁䅫䅤桂䝁䅷兡㙂䝁䅅䅤灂䝁䄸杢桁䍁䅑睑歁䑁䅑睎䅁䉁䕧䅁䕃䅁䅁睊扂䕁䅍睢睂䡁䅫䅉療䝁䅙䅉呂䙁䅁睒時䕁䅍睢瑂䡁䅁兙畂䡁䅫睘䱂䝁䅕入呂䡁䅑兙あ䡁䅍睘㉂䑁䅅睘䝂䝁䅫杢桂䝁䅷杌㑂䝁䅷督瑂䙁䄰睑桂䡁䅁兡あ䝁䅅䅢灂䡁䅯兙あ䝁䅫睢畂䍁䅣光歁䕁䅍䅊ぁ䅁䅁睙䅧䕁䅯䅁䑂䝁䅅䅣畁䍁䅁䅔求䝁䅅督求䍁䅁䅕桂䡁䅫兢求䝁䄴䅤杁䕁䅑兤求䍁䅁睋穁䍁䅁䅋卂䝁䅕䅣療䡁䅉䅤求䝁䅑克䅁䭁䈴䅁㙂䅁䅁睊扂䕁䄰兓時䕁䅍睢瑂䡁䅁兙畂䡁䅫睘䱂䝁䅕入呂䡁䅑兙あ䡁䅍睘㉂䑁䅅䅉潁䑁䅍克畁䡁䅧䅢穂䝁䄰兘䍂䝁䅅䅢桂䝁䄴睙求䙁䄸睕潂䝁䅕党あ䍁䅣光歁䕁䅍䅊㕁䑁䅯䅊䑂䍁䅑免穁䑁䅫䅁兂䅂䅁杤䅁䍁䅣睗乂䕁䅫睘䑂䝁䄸兢睂䝁䅅杢㕂䙁䄸睓求䡁䅫睕あ䝁䅅䅤穂䙁䄸杤硁䍁䅁䅋穁䍁䅫杌㑂䝁䅷督瑂䙁䄰睓求䡁䅫睘呂䡁䅑兙あ䡁䅍睊桁䍁䅑兒歁䑁䅅䅍ぁ䑁䅯䅊䡂䍁䅑免睁䑁䅑䅁䩂䅂䅁杖䅁䙁䅳睓求䡁䅫睕あ䝁䅅䅤穂䙁䄸䅤求䡁䅍䅤浂䝁䅫䅢求䍁䄴䅥獂䡁䅍䅥摂䙁䅍䅡求䝁䅕䅤硁䍁䅅䅊䭂䍁䅑杍祁䑁䅯䅊䵂䍁䅑杍祁䅁䅁杓䅁䍁䅯䅁䩂䙁䅅睘呂䙁䅕村時䕁䅷兒䉂䙁䅍兒時䕁䅫杔䑂䙁䄸睑婂䑁䅅䅁䡄允䅁杤䅁䍁䅣睗乂䕁䅫睘䑂䝁䄸兢睂䝁䅅杢㕂䙁䄸睓求䡁䅫睕あ䝁䅅䅤穂䙁䄸杤硁䍁䅁䅋穁䍁䅫杌㑂䝁䅷督瑂䙁䄰村桂䝁䅷兙畂䝁䅍党時䙁䅍䅡求䝁䅕䅤湁䍁䅅䅊䙂䍁䅑䅎㙁䍁䅑䅕歁䑁䅑䅁偂䅂䅁杣䅁䍁䅣睗呂䙁䅁睒時䕁䅍睢瑂䡁䅁兙畂䡁䅫睘䱂䝁䅕入呂䡁䅑兙あ䡁䅍睘㉂䑁䅉䅉硁䍁䄴䅥獂䡁䅍兢摂䙁䅍兤睂䡁䅁䅢求䝁䄰党畂䡁䅑兙獂䍁䅣光歁䕁䅑䅊㉁䑁䅯䅊䩂䍁䅑李䅁偁䝷䅁啃䅁䅁睊扂䕁䄰兓時䕁䅍睢瑂䡁䅁兙畂䡁䅫睘䱂䝁䅕入呂䡁䅑兙あ䡁䅍睘㉂䑁䅅䅉潁䑁䅍克畁䡁䅧䅢穂䝁䄰兘䑂䝁䅅䅣灂䡁䅑兙獂䙁䄸睕あ䡁䅉兤橂䡁䅑兤祂䝁䅕睘呂䡁䅕兢瑂䝁䅅杣㕂䍁䅣光歁䕁䅍䅊硁䑁䅍杏歁䕁䅍䅊硁䑁䅕䅍䅁䝁䕑䅁杁䅁䅁睕兂䙁䄸杕䙂䙁䅙睘䕂䕁䅅䅖䙂䙁䄸兒呂䙁䅑䅁䡂䅁䅁杆䅁䙁䅁杕䩂䕁䅍兒䑂䕁䅷睔呂䕁䅕䅁婃兂䅁杣䅁䍁䅣睗乂䕁䅫睘䑂䝁䄸兢睂䝁䅅杢㕂䙁䄸睓求䡁䅫睕あ䝁䅅䅤穂䙁䄸杤硁䍁䄰䅉偂䡁䅉兡湂䝁䅫杢桂䝁䅷杌㑂䝁䅷督瑂䙁䄰睓求䡁䅫睘呂䡁䅑兙あ䡁䅍睊桁䍁䅑村歁䑁䅉杍䅁䝁䙁䅁䕃䅁䅁睊扂䕁䄰兓時䕁䅍睢瑂䡁䅁兙畂䡁䅫睘䱂䝁䅕入呂䡁䅑兙あ䡁䅍睘㉂䑁䅅䅉潁䑁䅍克畁䡁䅧䅢穂䝁䄰兘䑂䝁䅅䅣灂䡁䅑兙獂䙁䄸睕あ䡁䅉兤橂䡁䅑兤祂䝁䅕睘呂䡁䅕兢瑂䝁䅅杣㕂䍁䅣光歁䕁䅍䅊ㅁ䅁䅁杚䅑䝁䄴䅁湁䙁䅳兔䩂䙁䄸睑療䝁䄰䅣桂䝁䄴入時䕁䅳党㕂䙁䅍䅤桂䡁䅑督時䡁䅙免杁䍁䅧睍灁䍁䄴䅥獂䡁䅍兢摂䕁䅍兙穂䝁䅧睘䝂䝁䅷睢㍂䍁䅣光歁䕁䅕䅊ㅁ䑁䅯䅊兂䍁䅑兎䅁䙁䕕䅁奂䅁䅁睖癁䕁䅅杤求䡁䅉兙湂䝁䅕䅉䩂䝁䄴䅤求䡁䅉党穂䡁䅑䅉卂䝁䅅䅤求䑁䅯䅉䵂䝁䄸杢湂䍁䄰䅤求䡁䅉兢杁䕁䅑党楂䡁䅑䅉潁䍁䅕克䅁佁䉉䅁奁䅁䅁兒䍂䕁䅫䅖杁䍁䅧䅊睁䑁䅁䅍灁䅁䅁睚䅁䝁䄴䅁湁䙁䅳兔䩂䙁䄸睑療䝁䄰䅣桂䝁䄴入時䕁䅳党㕂䙁䅍䅤桂䡁䅑督時䡁䅙免杁䍁䅧睍灁䍁䄴䅥獂䡁䅍兢摂䕁䅍兙睂䝁䅫䅤桂䝁䅷兡㙂䝁䅅䅤灂䝁䄸杢湁䍁䅅䅊䑂䍁䅑䅎䅁䙁䕙䅁楁䅁䅁兓剂䙁䄸䅕卂䕁䅕睘偂䙁䅁兒佂䙁䄸睑偂䙁䅍䅖䅁䭁䄴䅁浂䅁䅁睗乂䕁䅫睘䑂䝁䄸兢睂䝁䅅杢㕂䙁䄸睓求䡁䅫睕あ䝁䅅䅤穂䙁䄸杤硁䍁䄴䅥獂䡁䅍兢摂䕁䅳党㕂䙁䄸睕あ䝁䅅䅤穂䍁䅅䅊啂䍁䅑兎㑁䑁䅯䅊啂䍁䅑李硁䅁䅁杲䅕䩁䅉䅁湁䙁䅳兔䩂䙁䄸睑療䝁䄰䅣桂䝁䄴入時䕁䅳党㕂䙁䅍䅤桂䡁䅑督時䡁䅙免杁䍁䅧睍灁䍁䄴䅥獂䡁䅍兢摂䕁䅍兙睂䝁䅫䅤桂䝁䅷睘呂䡁䅑杣ㅂ䝁䅍䅤ㅂ䡁䅉党時䙁䅍兤瑂䝁䄰兙祂䡁䅫睊桁䍁䅑䅒歁䑁䅉睎㙁䍁䅑䅒歁䑁䅣䅏䅁䝁䕧䅁捃䅁䅁睊扂䕁䅍睢睂䡁䅫䅉療䝁䅙䅉呂䙁䅁睒時䕁䅍睢瑂䡁䅁兙畂䡁䅫睘䱂䝁䅕入呂䡁䅑兙あ䡁䅍睘㉂䑁䅉睘畂䝁䅕睤畁䡁䅧䅢穂䝁䄰兘䑂䝁䅅䅣灂䡁䅑兙獂䙁䄸睕あ䡁䅉兤橂䡁䅑兤祂䝁䅕睘杁䕁䅑党あ䝁䅅兡獂䡁䅍䅉湁䍁䅅䅊䱂䍁䅑免祁䅁䅁来䅣䥁䄴䅁湁䙁䅳兔䩂䙁䄸睑療䝁䄰䅣桂䝁䄴入時䕁䅳党㕂䙁䅍䅤桂䡁䅑督時䡁䅙免杁䍁䅧睍灁䍁䄴䅥獂䡁䅍兢摂䕁䅍兙睂䝁䅫䅤桂䝁䅷睘呂䡁䅑杣ㅂ䝁䅍䅤ㅂ䡁䅉党時䙁䅍兤瑂䝁䄰兙祂䡁䅫睊桁䍁䅑兒歁䑁䅑杏歁䕁䄸䅊ぁ䅁䅁睙䅑䡁䅙䅁湁䙁䅳睕兂䕁䅣睘䑂䝁䄸兢睂䝁䅅杢㕂䙁䄸睓求䡁䅫睕あ䝁䅅䅤穂䙁䄸杤硁䍁䅁䅋祁䍁䅫杌㑂䝁䅷督瑂䙁䄰䅕求䝁䄴督灂䝁䄸杢瑁䕁䄸䅕䙂䕁䅉睊桁䍁䅑䅒歁䑁䅙杏歁䕁䅫䅊㉁䅁䅁兔䅙䝁䅑䅁扂䙁䅍䅕䡂䙁䄸睑療䝁䄰䅣桂䝁䄴入時䕁䅳党㕂䙁䅍䅤桂䡁䅑督時䡁䅙杍畁䡁䅧䅢穂䝁䄰兘䑂䝁䅅督潂䙁䄸杒獂䝁䄸睤桁䍁䅑兒歁䑁䅙杏歁䙁䅅䅊㉁䅁䅁眳䅣䕁䅧䅁䭂䡁䅉杌杁䙁䅍兤楂䍁䅁䅒求䝁䅉䅤杁䍁䄸䅉潁䕁䅕村䩂䙁䅑䅒䉂䍁䅁兌杁䕁䅍兙睂䝁䅕䅥灁䍁䅁䅋㑂䍁䅫䅁慃允䅁䅨䅁䍁䅣睗䑂䝁䄸䅣㕂䍁䅁睢浂䍁䅁睕兂䕁䅣睘䑂䝁䄸兢睂䝁䅅杢㕂䙁䄸睓求䡁䅫睕あ䝁䅅䅤穂䙁䄸杤祁䙁䄸杢求䡁䅣杌㑂䝁䅷督瑂䙁䄰睓求䡁䅫睘呂䡁䅑兙あ䡁䅍睊桁䍁䅑兒歁䑁䅉兎㙁䍁䅑睓歁䑁䅉兎䅁䥁䠰䅁㙂䅁䅁睊扂䕁䄰兓時䕁䅍睢瑂䡁䅁兙畂䡁䅫睘䱂䝁䅕入呂䡁䅑兙あ䡁䅍睘㉂䑁䅅兌䑂䝁䄸䅣㕂䍁䄴䅥獂䡁䅍兢摂䕁䅍兙睂䝁䅫䅤桂䝁䅷兡㙂䝁䅅䅤灂䝁䄸杢湁䍁䅅䅊䙂䍁䅑兎㙁䍁䅑杓歁䑁䅕䅁㍁兂䅁䅨䅁䍁䅣睗䑂䝁䄸䅣㕂䍁䅁睢浂䍁䅁睕兂䕁䅣睘䑂䝁䄸兢睂䝁䅅杢㕂䙁䄸睓求䡁䅫睕あ䝁䅅䅤穂䙁䄸杤祁䙁䄸杢求䡁䅣杌㑂䝁䅷督瑂䙁䄰睓求䡁䅫睘呂䡁䅑兙あ䡁䅍睊桁䍁䅑兒歁䑁䅉李㙁䍁䅑睓歁䑁䅉李䅁䥁䠴䅁卂䅁䅁睕ㅂ䝁䅉兌䵂䝁䅕兙穂䝁䅕䅉䩂䝁䄴睙療䝁䄰党獁䍁䅁兑浂䡁䅑党祂䍁䅁兎杁䙁䅫杣穂䍁䅁䅋卂䝁䅕䅣療䡁䅉䅤求䝁䅑克䅁乁䉉䅁㉁䅁䅁兓剂䙁䄸䅖偂䙁䅑兑䵂䙁䄸睔兂䙁䅑兓偂䕁䄴睕時䕁䅕䅗䙂䙁䅉睑䩂䙁䅍兒䕂䅁䅁村䅍䡁䄴䅁湁䙁䅳兔䩂䙁䄸睑療䝁䄰䅣桂䝁䄴入時䕁䅳党㕂䙁䅍䅤桂䡁䅑督時䡁䅙免瑁䕁䅍睢睂䡁䅫杌㑂䝁䅷督瑂䙁䄰睑桂䡁䅁兡あ䝁䅅䅢灂䡁䅯兙あ䝁䅫睢畂䍁䅣光歁䕁䅕䅊ㅁ䑁䅧杏歁䕁䅯䅊ㅁ䑁䅧䅁䩂兂䅁䅩䅁䍁䅣睗呂䙁䅁睒時䕁䅍睢瑂䡁䅁兙畂䡁䅫睘䱂䝁䅕入呂䡁䅑兙あ䡁䅍睘㉂䑁䅉䅉硁䍁䄴䅥獂䡁䅍兢摂䕁䅍兙睂䝁䅫䅤桂䝁䅷睘呂䡁䅑杣ㅂ䝁䅍䅤ㅂ䡁䅉党時䍁䅁䅒求䡁䅑兙灂䝁䅷督杁䍁䅣光歁䕁䅣䅊㍁䑁䅙䅁楁睂䅁杆䅁䑁䅁兏癁䑁䅅睎癁䑁䅉䅍祁䑁䅁䅁湃兂䅁杚䅁䍁䅣睗乂䕁䅫睘䑂䝁䄸兢睂䝁䅅杢㕂䙁䄸睓求䡁䅫睕あ䝁䅅䅤穂䙁䄸杤硁䍁䅁䅋穁䍁䅫杌㑂䝁䅷督瑂䙁䄰睓求䡁䅫睘呂䡁䅑兙あ䡁䅍睊桁䍁䅑兒歁䑁䅕杍䅁䑁䔸䅁㙁䅁䅁睒求䝁䄴党祂䝁䅅䅢癁䕁䄸䅤潂䝁䅕杣杁䕁䅉睢祂䡁䅉睢㍂䝁䅫杢湂䡁䅍䅉潁䍁䅕克䅁偁䅅䅁䵃䅁䅁睊扂䙁䅍䅕䡂䙁䄸睑療䝁䄰䅣桂䝁䄴入時䕁䅳党㕂䙁䅍䅤桂䡁䅑督時䡁䅙杍杁䑁䅅杌㑂䝁䅷督瑂䙁䄰睑桂䡁䅁兡あ䝁䅅䅢時䙁䅍䅤祂䡁䅕睙あ䡁䅕杣求䙁䄸睕ㅂ䝁䄰兢桂䡁䅉入湁䍁䅅䅊䙂䍁䅑李㙁䍁䅑睔歁䑁䅙䅁睄杂䅁杒䅁䙁䅁杣療䡁䅙兡穂䝁䅫睢畂䍁䅁杚療䡁䅉䅉䍂䝁䅅䅚杁䕁䅑党楂䡁䅑督杁䍁䅧杕求䡁䅁睢祂䡁䅑党歂䍁䅫䅁牃䅁䅁杪䅁䍁䅣睗乂䕁䅫睘䑂䝁䄸兢睂䝁䅅杢㕂䙁䄸睓求䡁䅫睕あ䝁䅅䅤穂䙁䄸杤硁䍁䅁䅋穁䍁䅫杌㑂䝁䅷督瑂䙁䄰睑桂䡁䅁兡あ䝁䅅䅢時䙁䅍䅤祂䡁䅕睙あ䡁䅕杣求䙁䄸睕ㅂ䝁䄰兢桂䡁䅉入湁䍁䅅䅊䙂䍁䅑兎㙁䍁䅑睔歁䑁䅕䅁求䅂䅁䅤䅁䍁䅣睗呂䙁䅁睒時䕁䅍睢瑂䡁䅁兙畂䡁䅫睘䱂䝁䅕入呂䡁䅑兙あ䡁䅍睘㉂䑁䅅杌㑂䝁䅷督瑂䙁䄰䅕求䝁䄴督灂䝁䄸杢瑁䕁䄸䅕䙂䕁䅉睊桁䍁䅑睑歁䑁䅅免㙁䍁䅑睑歁䑁䅕睎睁䅁䅁杄䅙䥁䄴䅁湁䙁䅳兔䩂䙁䄸睑療䝁䄰䅣桂䝁䄴入時䕁䅳党㕂䙁䅍䅤桂䡁䅑督時䡁䅙免杁䍁䅧睍灁䍁䄴䅥獂䡁䅍兢摂䕁䅍兙睂䝁䅫䅤桂䝁䅷睘呂䡁䅑杣ㅂ䝁䅍䅤ㅂ䡁䅉党時䙁䅍兤瑂䝁䄰兙祂䡁䅫睊桁䍁䅑杒歁䑁䅧杏歁䙁䅁䅊㑁䅁䅁睚䅑䝁䅙䅁扂䕁䄰兓時䕁䅍睢瑂䡁䅁兙畂䡁䅫睘䱂䝁䅕入呂䡁䅑兙あ䡁䅍睘㉂䑁䅅杌㑂䝁䅷督瑂䙁䄰睓求䡁䅫睘呂䡁䅑兙あ䡁䅍光歁䕁䅯䅊祁䑁䅍杏歁䕁䅷䅊祁䑁䅍䅁㝄睁䅁杤䅁䍁䅣睗乂䕁䅫睘䑂䝁䄸兢睂䝁䅅杢㕂䙁䄸睓求䡁䅫睕あ䝁䅅䅤穂䙁䄸杤硁䍁䅁䅋穁䍁䅫杌㑂䝁䅷督瑂䙁䄰睓求䡁䅫睘呂䡁䅑兙あ䡁䅍睊桁䍁䅑睑歁䑁䅅䅍ㅁ䑁䅯䅊䑂䍁䅑免睁䑁䅫䅁䥂䅂䅁杢䅁䍁䅣睗乂䕁䅫睘䑂䝁䄸兢睂䝁䅅杢㕂䙁䄸睓求䡁䅫睕あ䝁䅅䅤穂䙁䄸杤硁䍁䅁兌獂䝁䅅䅤求䡁䅍䅤畁䡁䅧䅢穂䝁䄰兘䱂䝁䅕入時䙁䅍䅤桂䡁䅑督湁䍁䅅䅊䙂䍁䅑兎祁䅁䅁睇䅕䙁䅙䅁扂䕁䄰兓時䕁䅳党㕂䙁䅍䅤桂䡁䅑督時䡁䅙免畁䡁䅧䅢穂䝁䄰兘䱂䝁䅕入時䙁䅍䅤桂䡁䅑督桁䍁䅑睑歁䑁䅙免㙁䍁䅑睑歁䑁䅙睎䅁䡁䑍䅁煁䅁䅁兓剂䙁䄸睑䵂䙁䄸䅒噂䕁䅕睘䉂䕁䅙䅖䙂䙁䅉睘䝂䕁䅫杖䙂䅁䅁关䅅䥁䄴䅁湁䙁䅳兔䩂䙁䄸睑療䝁䄰䅣桂䝁䄴入時䕁䅳党㕂䙁䅍䅤桂䡁䅑督時䡁䅙免杁䍁䅧睍灁䍁䄴䅥獂䡁䅍兢摂䕁䅍兙睂䝁䅫䅤桂䝁䅷睘呂䡁䅑杣ㅂ䝁䅍䅤ㅂ䡁䅉党時䙁䅍兤瑂䝁䄰兙祂䡁䅫睊桁䍁䅑杒歁䑁䅫杏歁䙁䅁䅊㕁䅁䅁兡䅑䡁䅑䅁湁䙁䅳睕兂䕁䅣睘䑂䝁䄸兢睂䝁䅅杢㕂䙁䄸睓求䡁䅫睕あ䝁䅅䅤穂䙁䄸杤硁䍁䅁䅋祁䍁䅫杌㑂䝁䅷督瑂䙁䄰睓求䡁䅫睘呂䡁䅑兙あ䡁䅍睊桁䍁䅑睑歁䑁䅉䅏㙁䍁䅑睑歁䑁䅕杍䅁䉁䝉䅁啂䅁䅁䅖療䡁䅑兙獂䍁䅁兖畂䝁䅅兢療䡁䅉䅤灂䡁䅯党歂䍁䅁䅕祂䝁䅕兢灂䡁䅕兢癁䍁䅁䅖療䡁䅑兙獂䍁䅁䅒求䝁䅉䅤杁䍁䅧兊灁䅁䅁眯䅁䍁䄴䅁䩂䙁䅅睘䵂䕁䅙睑䝂䙁䄸睍婂䙁䅉睘䉂䕁䄴杔時䕁䅣杕偂䙁䅣䅖䥂䅁䅁睧䅉䝁䅙䅁湁䙁䅳兔䩂䙁䄸睑療䝁䄰䅣桂䝁䄴入時䕁䅳党㕂䙁䅍䅤桂䡁䅑督時䡁䅙免杁䍁䅧睍灁䍁䄴䅥獂䡁䅍兢摂䕁䅳党㕂䙁䄸睕あ䝁䅅䅤穂䍁䅣光歁䕁䅉䅊祁䑁䅉䅁睁䅂䅁䅯䅁䍁䅣睗䑂䝁䄸䅣㕂䍁䅁睢浂䍁䅁睕兂䕁䅣睘䑂䝁䄸兢睂䝁䅅杢㕂䙁䄸睓求䡁䅫睕あ䝁䅅䅤穂䙁䄸杤硁䙁䄸杒灂䝁䄴兙獂䍁䄴䅥獂䡁䅍兢摂䕁䅍兙睂䝁䅫䅤桂䝁䅷睘呂䡁䅑杣ㅂ䝁䅍䅤ㅂ䡁䅉党時䍁䅁䅒求䡁䅑兙灂䝁䅷督杁䍁䅣光歁䕁䅉䅊㍁䑁䅙䅁佃䅃䅁杢䅁䕁䄸䅣求䡁䅉兙あ䝁䅫杢湂䍁䅁䅔求䝁䅅督求䍁䅁睑療䝁䄰兢灂䡁䅑兢求䝁䄴䅤杁䕁䅑兤求䍁䅷䅉䉂䝁䅙䅤求䡁䅉䅉ㅁ䍁䅁兗祂䡁䅍䅉潁䙁䅉党睂䝁䄸杣あ䝁䅕䅚灁䅁䅁䅸䅅䝁䅷䅁扂䕁䄰兓時䕁䅍睢瑂䡁䅁兙畂䡁䅫睘䱂䝁䅕入呂䡁䅑兙あ䡁䅍睘㉂䑁䅅杌㑂䝁䅷督瑂䙁䄰睑桂䡁䅁兡あ䝁䅅䅢灂䡁䅯兙あ䝁䅫睢畂䍁䅅䅊䙂䍁䅑兎㙁䍁䅑杓歁䑁䅕䅁呁䅂䅁䅡䅁䙁䅳兔䩂䙁䄸睑療䝁䄰䅣桂䝁䄴入時䕁䅳党㕂䙁䅍䅤桂䡁䅑督時䡁䅙免時䍁䄴䅥獂䡁䅍兢摂䕁䅳党㕂䙁䄸睕あ䝁䅅䅤穂䍁䅅䅊䕂䍁䅑杍㑁䑁䅯䅊䕂䍁䅑兎祁䅁䅁睷䅑䑁䅧䅁䩂䝁䄴杤求䝁䄴䅤療䡁䅉入獁䍁䅁免杁䙁䅫杣畁䍁䅁睒祂䝁䄸睤あ䝁䅧䅉潁䍁䅕克䅁䍁䍧䅁歃䅁䅁睊扂䕁䅍睢睂䡁䅫䅉療䝁䅙䅉呂䙁䅁睒時䕁䅍睢瑂䡁䅁兙畂䡁䅫睘䱂䝁䅕入呂䡁䅑兙あ䡁䅍睘㉂䑁䅉睘畂䝁䅕睤畁䡁䅧䅢穂䝁䄰兘䑂䝁䅅䅣灂䡁䅑兙獂䙁䄸睕あ䡁䅉兤橂䡁䅑兤祂䝁䅕睘呂䡁䅕兢瑂䝁䅅杣㕂䍁䅣光歁䕁䅙䅊硁䑁䅅杏歁䙁䅉䅊硁䑁䅅䅁䕄睂䅁杍䅁䕁䅫兕時䙁䅑睔啂䕁䅅䅔時䙁䅣兑卂䙁䅉兑佂䙁䅑睕時䕁䅕杔䕂䙁䄸睔呂䅁䅁䅘䅍䡁䅷䅁湁䙁䅳兔䩂䙁䄸睑療䝁䄰䅣桂䝁䄴入時䕁䅳党㕂䙁䅍䅤桂䡁䅑督時䡁䅙免杁䍁䅧睍灁䍁䄴䅥獂䡁䅍兢摂䕁䅍兙睂䝁䅫䅤桂䝁䅷兡㙂䝁䅅䅤灂䝁䄸杢湁䍁䅅䅊䙂䍁䅑䅎㑁䑁䅯䅊兂䍁䅑䅎㑁䅁䅁兘䅑䡁䅧䅁湁䙁䅳兔䩂䙁䄸睑療䝁䄰䅣桂䝁䄴入時䕁䅳党㕂䙁䅍䅤桂䡁䅑督時䡁䅙免瑁䕁䅍睢睂䡁䅫杌㑂䝁䅷督瑂䙁䄰睓求䡁䅫睘呂䡁䅑兙あ䡁䅍睊桁䍁䅑兒歁䑁䅅䅍㑁䑁䅯䅊䡂䍁䅑免睁䑁䅧䅁湁兂䅁杋䅁䕁䅫兕時䕁䄴兓時䑁䅍兗卂䙁䄸兑佂䕁䄴睘䡂䙁䅉睔塂䙁䅑䅓䅁䝁䌸䅁睂䅁䅁睊扂䕁䄰兓時䕁䅍睢瑂䡁䅁兙畂䡁䅫睘䱂䝁䅕入呂䡁䅑兙あ䡁䅍睘㉂䑁䅅䅉潁䑁䅍克畁䡁䅧䅢穂䝁䄰兘䑂䝁䅅䅣灂䡁䅑兙獂䝁䅫来桂䡁䅑兡療䝁䄴睊桁䍁䅑睑歁䑁䅑䅏䅁䙁䕯䅁睂䅁䅁睊扂䕁䄰兓時䕁䅍睢瑂䡁䅁兙畂䡁䅫睘䱂䝁䅕入呂䡁䅑兙あ䡁䅍睘㉂䑁䅅䅉潁䑁䅍克畁䡁䅧䅢穂䝁䄰兘䑂䝁䅅䅣灂䡁䅑兙獂䝁䅫来桂䡁䅑兡療䝁䄴睊桁䍁䅑睑歁䑁䅕䅍䅁䙁䕷䅁㡂䅁䅁睊扂䕁䄰兓時䕁䅍睢瑂䡁䅁兙畂䡁䅫睘䱂䝁䅕入呂䡁䅑兙あ䡁䅍睘㉂䑁䅅䅉潁䑁䅍克畁䡁䅧䅢穂䝁䄰兘䑂䝁䅅䅣灂䡁䅑兙獂䝁䅫来桂䡁䅑兡療䝁䄴睊桁䍁䅑兒歁䑁䅕免㙁䍁䅑杓歁䑁䅕免䅁䙁䔸䅁㡁䅁䅁杖桂䡁䅉兡桂䝁䅉䅢求䍁䅁杕桂䡁䅑党杁䕁䅑党楂䡁䅑䅉潁䙁䅉党睂䝁䄸杣あ䝁䅕䅚灁䅁䅁兕䅅䥁䅙䅁扂䕁䄰兓時䕁䅍睢瑂䡁䅁兙畂䡁䅫睘䱂䝁䅕入呂䡁䅑兙あ䡁䅍睘㉂䑁䅅杌㑂䝁䅷督瑂䙁䄰睑桂䡁䅁兡あ䝁䅅䅢時䙁䅍䅤祂䡁䅕睙あ䡁䅕杣求䙁䄸睕ㅂ䝁䄰兢桂䡁䅉入桁䍁䅑䅒歁䑁䅉睎㙁䍁䅑䅒歁䑁䅣䅏䅁䍁䕉䅁㡂䅁䅁睊扂䕁䄰兓時䕁䅍睢瑂䡁䅁兙畂䡁䅫睘䱂䝁䅕入呂䡁䅑兙あ䡁䅍睘㉂䑁䅅䅉潁䑁䅍克畁䡁䅧䅢穂䝁䄰兘䑂䝁䅅䅣灂䡁䅑兙獂䝁䅫来桂䡁䅑兡療䝁䄴睊桁䍁䅑兒歁䑁䅕杍㙁䍁䅑杓歁䑁䅕杍䅁䝁䕅䅁䭂䅁䅁睑桂䡁䅁兡あ䝁䅅䅢杁䕁䅕䅥睂䝁䅕杢歂䝁䅫䅤ㅂ䡁䅉党穂䍁䅷䅉穁䍁䅁兗祂䍁䄴䅉䑂䕁䅅睒卂䍁䅁䅋汁䍁䅫䅁䍃杁䅁䅦䅁䍁䅣睗乂䕁䅫睘䑂䝁䄸兢睂䝁䅅杢㕂䙁䄸睓求䡁䅫睕あ䝁䅅䅤穂䙁䄸杤硁䍁䅁䅋穁䍁䅫杌㑂䝁䅷督瑂䙁䄰睑桂䡁䅁兡あ䝁䅅䅢灂䡁䅯兙あ䝁䅫睢畂䍁䅣光歁䕁䅍䅊ㅁ䑁䅍杏歁䕁䅍䅊ㅁ䑁䅑䅁杂䅂䅁杓䅁䙁䅳兔䩂䙁䄸睓求䡁䅫睕あ䝁䅅䅤穂䙁䄸杤硁䍁䄴䅥獂䡁䅍兢摂䕁䅳党㕂䙁䄸睕あ䝁䅅䅤穂䍁䅅䅊䙂䍁䅑兎祁䅁䅁杤䅍䝁䅧䅁湁䙁䅳睕兂䕁䅣睘䑂䝁䄸兢睂䝁䅅杢㕂䙁䄸睓求䡁䅫睕あ䝁䅅䅤穂䙁䄸杤硁䍁䅁䅋祁䍁䅫杌㑂䝁䅷督瑂䙁䄰睓求䡁䅫睘呂䡁䅑兙あ䡁䅍睊桁䍁䅑兒歁䑁䅙睍䅁䉁䜸䅁㙂䅁䅁睊扂䕁䄰兓時䕁䅍睢瑂䡁䅁兙畂䡁䅫睘䱂䝁䅕入呂䡁䅑兙あ䡁䅍睘㉂䑁䅅䅉潁䑁䅍克畁䡁䅧䅢穂䝁䄰兘䑂䝁䅅䅣灂䡁䅑兙獂䝁䅫来桂䡁䅑兡療䝁䄴睊桁䍁䅑睑歁䑁䅫杏歁䕁䅍䅊祁䑁䅕䅁奂䅂䅁杆䅁䙁䅍䅕時䙁䅁兒䡂䙁䄸杒塂䕁䅑䅁敂杂䅁杗䅁䙁䅳兔䩂䙁䄸睑療䝁䄰䅣桂䝁䄴入時䕁䅳党㕂䙁䅍䅤桂䡁䅑督時䡁䅙免畁䡁䅧䅢穂䝁䄰兘䱂䝁䅕入時䙁䅍䅤桂䡁䅑督桁䍁䅑村歁䑁䅕兎䅁䡁䙙䅁睁䅁䅁兓剂䙁䄸䅒䉂䕁䅫䅔婂䙁䄸兑坂䕁䅣睘卂䕁䅕杖時䙁䅑杕䉂䕁䅑兒呂䅁䅁䅩䅍䡁䅧䅁湁䙁䅳兔䩂䙁䄸睑療䝁䄰䅣桂䝁䄴入時䕁䅳党㕂䙁䅍䅤桂䡁䅑督時䡁䅙免杁䍁䅧睍灁䍁䄴䅥獂䡁䅍兢摂䕁䅍兙睂䝁䅫䅤桂䝁䅷兡㙂䝁䅅䅤灂䝁䄸杢湁䍁䅅䅊䙂䍁䅑䅎㙁䍁䅑杓歁䑁䅑䅁塂䅂䅁杋䅁䙁䅑睢あ䝁䅅䅢杁䙁䅉党㉂䝁䅕杢ㅂ䝁䅕䅉潁䍁䅑䅍睁䑁䅁克䅁䝁䅕䅁㉂䅁䅁睊扂䕁䄰兓時䕁䅍睢瑂䡁䅁兙畂䡁䅫睘䱂䝁䅕入呂䡁䅑兙あ䡁䅍睘㉂䑁䅅䅉潁䑁䅍克畁䡁䅧䅢穂䝁䄰兘䱂䝁䅕入時䙁䅍䅤桂䡁䅑督湁䍁䅅䅊䙂䍁䅑免睁䑁䅍杏歁䕁䅣䅊硁䑁䅁睍䅁䕁䕣䅁㙂䅁䅁睊扂䙁䅍䅕䡂䙁䄸睑療䝁䄰䅣桂䝁䄴入時䕁䅳党㕂䙁䅍䅤桂䡁䅑督時䡁䅙杍杁䑁䅅杌㑂䝁䅷督瑂䙁䄰睑桂䡁䅁兡あ䝁䅅䅢灂䡁䅯兙あ䝁䅫睢畂䍁䅣光歁䕁䅕䅊ぁ䑁䅙杏歁䕁䅯䅊ぁ䑁䅙䅁獄杂䅁䅗䅁䙁䅳兔䩂䙁䄸睑療䝁䄰䅣桂䝁䄴入時䕁䅳党㕂䙁䅍䅤桂䡁䅑督時䡁䅙免畁䡁䅧䅢穂䝁䄰兘䑂䝁䅅督潂䙁䄸杒獂䝁䄸睤桁䍁䅑睑歁䑁䅑䅁䵁䅂䅁杣䅁䍁䅣睗乂䕁䅫睘䑂䝁䄸兢睂䝁䅅杢㕂䙁䄸睓求䡁䅫睕あ䝁䅅䅤穂䙁䄸杤硁䍁䅁䅋穁䍁䅫杌㑂䝁䅷督瑂䙁䄰睓求䡁䅫睘呂䡁䅑兙あ䡁䅍睊桁䍁䅑䅒歁䑁䅉兎㙁䍁䅑䅒歁䑁䅑兏䅁䑁䕙䅁㑂䅁䅁睊扂䕁䄰兓時䕁䅍睢瑂䡁䅁兙畂䡁䅫睘䱂䝁䅕入呂䡁䅑兙あ䡁䅍睘㉂䑁䅅䅉潁䑁䅍克畁䡁䅧䅢穂䝁䄰兘䑂䝁䅅䅣灂䡁䅑兙獂䝁䅫来桂䡁䅑兡療䝁䄴睊桁䍁䅑兒歁䑁䅕杏歁䕁䅯䅊ㅁ䅁䅁兗䅑䡁䅑䅁湁䙁䅳睕兂䕁䅣睘䑂䝁䄸兢睂䝁䅅杢㕂䙁䄸睓求䡁䅫睕あ䝁䅅䅤穂䙁䄸杤祁䍁䅁免畁䡁䅧䅢穂䝁䄰兘䍂䝁䅅䅢桂䝁䄴睙求䙁䄸睕潂䝁䅕党あ䍁䅣光歁䕁䅕䅊㉁䑁䅯䅊兂䍁䅑李䅁乁䝷䅁歂䅁䅁睊扂䕁䄰兓時䕁䅍睢瑂䡁䅁兙畂䡁䅫睘䱂䝁䅕入呂䡁䅑兙あ䡁䅍睘㉂䑁䅅䅉潁䑁䅍克畁䡁䅧䅢穂䝁䄰兘䑂䝁䅅督潂䙁䄸杒獂䝁䄸睤湁䍁䅅䅊䑂䍁䅑䅎䅁䙁䕉䅁畂䅁䅁睊扂䕁䄰兓時䕁䅍睢瑂䡁䅁兙畂䡁䅫睘䱂䝁䅕入呂䡁䅑兙あ䡁䅍睘㉂䑁䅅䅉瑁䝁䅷兙あ䝁䅕督あ䍁䄴䅥獂䡁䅍兢摂䕁䅳党㕂䙁䄸睕あ䝁䅅䅤穂䍁䅣光歁䕁䅉䅊ㅁ䑁䅅䅁奁兂䅁䅦䅁䍁䅣睗乂䕁䅫睘䑂䝁䄸兢睂䝁䅅杢㕂䙁䄸睓求䡁䅫睕あ䝁䅅䅤穂䙁䄸杤硁䍁䅁䅋穁䍁䅫杌㑂䝁䅷督瑂䙁䄰兓畂䝁䅍睢瑂䝁䅕睘呂䡁䅑兙あ䝁䅕兢求䝁䄴䅤湁䍁䅅䅊䙂䍁䅑䅎㙁䍁䅑䅕歁䑁䅑䅁䱂䅂䅁杗䅁䙁䅳兔䩂䙁䄸睑療䝁䄰䅣桂䝁䄴入時䕁䅳党㕂䙁䅍䅤桂䡁䅑督時䡁䅙免畁䡁䅧䅢穂䝁䄰兘䱂䝁䅕入時䙁䅍䅤桂䡁䅑督桁䍁䅑村歁䑁䅉兎䅁䥁䕧䅁浂䅁䅁睗乂䕁䅫睘䑂䝁䄸兢睂䝁䅅杢㕂䙁䄸睓求䡁䅫睕あ䝁䅅䅤穂䙁䄸杤硁䍁䄴䅥獂䡁䅍兢摂䕁䅳党㕂䙁䄸睕あ䝁䅅䅤穂䍁䅅䅊䑂䍁䅑兎㍁䑁䅯䅊䑂䍁䅑兎㑁䅁䅁睲䅑䡁䅙䅁偂䡁䅁䅤灂䝁䄸杢穂䍁䅁睑桂䝁䄴睙求䝁䅷䅢求䝁䅑䅉䕂䡁䅕杣灂䝁䄴睚杁䡁䅑䅡求䍁䅁䅕求䡁䅉兡療䝁䅑䅌杁䕁䅍睢瑂䝁䄰睢畂䍁䅁睕あ䝁䄸睙牂䍁䅁䅋桂䝁䅍䅤ㅂ䝁䅅䅢灁䅁䅁兏䅍䡁䅁䅁湁䙁䅳兔䩂䙁䄸睑療䝁䄰䅣桂䝁䄴入時䕁䅳党㕂䙁䅍䅤桂䡁䅑督時䡁䅙免杁䍁䅧睍灁䍁䄴䅥獂䡁䅍兢摂䕁䅍兙穂䝁䅧睘䝂䝁䅷睢㍂䍁䅣光歁䕁䅍䅊㕁䑁䅯䅊䑂䍁䅑兏睁䅁䅁䅖䅑䥁䅙䅁湁䙁䅳睕兂䕁䅣睘䑂䝁䄸兢睂䝁䅅杢㕂䙁䄸睓求䡁䅫睕あ䝁䅅䅤穂䙁䄸杤硁䍁䅁䅋祁䍁䅫杌㑂䝁䅷督瑂䙁䄰睑桂䡁䅁兡あ䝁䅅䅢時䙁䅍䅤祂䡁䅕睙あ䡁䅕杣求䙁䄸睕ㅂ䝁䄰兢桂䡁䅉入湁䍁䅅䅊䑂䍁䅑睎䅁䕁䝁䅁ぁ䅁䅁䅕求䡁䅉兡療䝁䅑䅉䙂䝁䄴䅚求䝁䅑䅉潁䝁䄰兢癁䝁䅑䅚癁䡁䅫入㕂䡁䅫克䅁䙁䅉䅁杂䅁䅁睊扂䕁䄰兓時䕁䅳党㕂䙁䅍䅤桂䡁䅑督時䡁䅙免畁䡁䅧䅢穂䝁䄰兘兂䝁䅕杢穂䝁䅫睢畂䍁䄰睔兂䕁䅕村湁䍁䅅䅊䑂䍁䅑兏㙁䍁䅑睑歁䑁䅕李㕁䅁䅁睹䅍䡁䄴䅁湁䙁䅳兔䩂䙁䄸睑療䝁䄰䅣桂䝁䄴入時䕁䅳党㕂䙁䅍䅤桂䡁䅑督時䡁䅙免瑁䕁䅍睢睂䡁䅫杌㑂䝁䅷督瑂䙁䄰睑桂䡁䅁兡あ䝁䅅䅢灂䡁䅯兙あ䝁䅫睢畂䍁䅣光歁䕁䅕䅊㉁䑁䅉杏歁䕁䅯䅊㉁䑁䅉䅁䥂兂䅁䅤䅁䍁䅣睗乂䕁䅫睘䑂䝁䄸兢睂䝁䅅杢㕂䙁䄸睓求䡁䅫睕あ䝁䅅䅤穂䙁䄸杤硁䍁䄰睑療䡁䅁入畁䡁䅧䅢穂䝁䄰兘䱂䝁䅕入時䙁䅍䅤桂䡁䅑督湁䍁䅅䅊乂䍁䅑杍ㅁ䑁䅯䅊偂䍁䅑杍ㅁ䅁䅁光䅕䙁䅙䅁扂䙁䅍䅕䡂䙁䄸睑療䝁䄰䅣桂䝁䄴入時䕁䅳党㕂䙁䅍䅤桂䡁䅑督時䡁䅙杍畁䡁䅧䅢穂䝁䄰兘呂䝁䅧党求䡁䅑免桁䍁䅑䅒歁䑁䅅免䅁䥁䝷䅁䭃䅁䅁睗呂䙁䅁睒時䕁䅍睢瑂䡁䅁兙畂䡁䅫睘䱂䝁䅕入呂䡁䅑兙あ䡁䅍睘㉂䑁䅉杌㑂䝁䅷督瑂䙁䄰睑桂䡁䅁兡あ䝁䅅䅢時䙁䅍䅤祂䡁䅕睙あ䡁䅕杣求䙁䄸睕ㅂ䝁䄰兢桂䡁䅉入桁䍁䅑睑歁䑁䅅兎㙁䍁䅑睑歁䑁䅅睎硁䅁䅁䅂䅧䙁䅷䅁扂䙁䅍䅕䡂䙁䄸睑療䝁䄰䅣桂䝁䄴入時䕁䅳党㕂䙁䅍䅤桂䡁䅑督時䡁䅙免畁䡁䅧䅢穂䝁䄰兘䱂䝁䅕入時䙁䅍䅤桂䡁䅑督桁䍁䅑兒歁䑁䅙睍䅁乁䘸䅁畂䅁䅁睊扂䕁䄰兓時䕁䅍睢瑂䡁䅁兙畂䡁䅫睘䱂䝁䅕入呂䡁䅑兙あ䡁䅍睘㉂䑁䅅䅉潁䑁䅍克畁䡁䅧䅢穂䝁䄰兘䑂䝁䅅督潂䙁䄸杒獂䝁䄸睤湁䍁䅅䅊䙂䍁䅑䅎㙁䍁䅑䅕歁䑁䅑䅁呂䅂䅁䅏䅁䕁䅅䅚煂䡁䅕督あ䝁䄰党畂䡁䅑督癁䍁䅁䅖療䡁䅑兙獂䍁䅁䅒求䝁䅉䅤杁䍁䅧兊灁䅁䅁睁䅅䡁䅯䅁湁䙁䅳睕兂䕁䅣睘䑂䝁䄸兢睂䝁䅅杢㕂䙁䄸睓求䡁䅫睕あ䝁䅅䅤穂䙁䄸杤祁䍁䅁免畁䡁䅧䅢穂䝁䄰兘䩂䝁䄴睙療䝁䄰党時䙁䅍䅤桂䡁䅑党瑂䝁䅕杢あ䍁䅣光歁䕁䅕䅊㍁䑁䅯䅊兂䍁䅑睎䅁乁䝯䅁祂䅁䅁睊扂䕁䄰兓時䕁䅍睢瑂䡁䅁兙畂䡁䅫睘䱂䝁䅕入呂䡁䅑兙あ䡁䅍睘㉂䑁䅅䅉潁䑁䅍克畁䡁䅧䅢穂䝁䄰兘䩂䝁䄴睙療䝁䄰党時䙁䅍䅤桂䡁䅑党瑂䝁䅕杢あ䍁䅣光歁䕁䅍䅊ぁ䅁䅁杓䅑䡁䅙䅁扂䕁䄰兓時䕁䅳党㕂䙁䅍䅤桂䡁䅑督時䡁䅙免畁䡁䅧䅢穂䝁䄰兘䑂䝁䅅䅣灂䡁䅑兙獂䙁䄸睕あ䡁䅉兤橂䡁䅑兤祂䝁䅕睘呂䡁䅕兢瑂䝁䅅杣㕂䍁䅅䅊䙂䍁䅑杍㍁䑁䅯䅊䙂䍁䅑睎㉁䅁䅁內䅍䙁䅷䅁䵂䙁䅑䅉䕂䝁䅕杙あ䍁䅁䅋䩂䝁䄴睙獂䍁䄴䅉䑂䝁䅅䅣畁䍁䅁䅔求䝁䅅督求䡁䅍克杁䕁䅑兤求䍁䅁睋穁䍁䅁䅋卂䝁䅕䅣療䡁䅉䅤求䝁䅑克䅁䭁䉁䅁㉂䅁䅁睗乂䕁䅫睘䱂䝁䅕入呂䡁䅑兙あ䡁䅍睘㉂䑁䅅杌㑂䝁䅷督瑂䙁䄰睑桂䡁䅁兡あ䝁䅅䅢時䙁䅍䅤祂䡁䅕睙あ䡁䅕杣求䙁䄸睕ㅂ䝁䄰兢桂䡁䅉入桁䍁䅑䅒歁䑁䅉睎㙁䍁䅑䅒歁䑁䅣李䅁䭁䐴䅁䅃䅁䅁睊扂䕁䄰兓時䕁䅍睢瑂䡁䅁兙畂䡁䅫睘䱂䝁䅕入呂䡁䅑兙あ䡁䅍睘㉂䑁䅅䅉潁䑁䅍克畁䡁䅧䅢穂䝁䄰兘䩂䝁䄴睙療䝁䄰党時䙁䅍䅤桂䡁䅑党瑂䝁䅕杢あ䍁䅣光歁䕁䅍䅊㕁䑁䅯䅊䑂䍁䅑免㍁䑁䅍䅁䵂䅂䅁䅦䅁䍁䅣睗乂䕁䅫睘䑂䝁䄸兢睂䝁䅅杢㕂䙁䄸睓求䡁䅫睕あ䝁䅅䅤穂䙁䄸杤硁䍁䅁䅋穁䍁䅫杌㑂䝁䅷督瑂䙁䄰兓畂䝁䅍睢瑂䝁䅕睘呂䡁䅑兙あ䝁䅕兢求䝁䄴䅤湁䍁䅅䅊䙂䍁䅑兎㙁䍁䅑䅕歁䑁䅕䅁乂䅂䅁杧䅁䍁䅣睗呂䙁䅁睒時䕁䅍睢瑂䡁䅁兙畂䡁䅫睘䱂䝁䅕入呂䡁䅑兙あ䡁䅍睘㉂䑁䅉䅉硁䍁䄴䅥獂䡁䅍兢摂䕁䅍兙睂䝁䅫䅤桂䝁䅷睘呂䡁䅑杣ㅂ䝁䅍䅤ㅂ䡁䅉党時䙁䅍兤瑂䝁䄰兙祂䡁䅫睊桁䍁䅑睑歁䑁䅙䅁癄杂䅁䅌䅁䕁䅍兓剂䍁䅁睑桂䝁䅷睙ㅂ䝁䅷兙あ䝁䅫睢畂䍁䅁䅖㕂䡁䅁党杁䅁䅁兌䅍䡁䅑䅁湁䙁䅳睕兂䕁䅣睘䑂䝁䄸兢睂䝁䅅杢㕂䙁䄸睓求䡁䅫睕あ䝁䅅䅤穂䙁䄸杤硁䍁䅁䅋祁䍁䅫杌㑂䝁䅷督瑂䙁䄰睓求䡁䅫睘呂䡁䅑兙あ䡁䅍睊桁䍁䅑䅖歁䑁䅕䅏㙁䍁䅑䅖歁䑁䅙免䅁䍁䝍䅁佂䅁䅁兓剂䙁䄸睑䥂䕁䅅杔䡂䕁䅕睘噂䕁䄴杕䙂䕁䅍睔䡂䙁䄸䅖䉂䙁䅧睘䍂䕁䅕杔䙂䕁䅙兓啂䙁䄸免時䙁䅫杕時䕁䄰兓佂䅁䅁杆䅍䝁䅧䅁湁䙁䅳兔䩂䙁䄸睑療䝁䄰䅣桂䝁䄴入時䕁䅳党㕂䙁䅍䅤桂䡁䅑督時䡁䅙免杁䍁䅧睍灁䍁䄴䅥獂䡁䅍兢摂䕁䅳党㕂䙁䄸睕あ䝁䅅䅤穂䍁䅣光歁䕁䅉䅊硁䑁䅁杍䅁䕁䕙䅁浂䅁䅁睊扂䕁䄰兓時䕁䅍睢瑂䡁䅁兙畂䡁䅫睘䱂䝁䅕入呂䡁䅑兙あ䡁䅍睘㉂䑁䅅䅉潁䑁䅍克畁䡁䅧䅢穂䝁䄰兘䱂䝁䅕入時䙁䅍䅤桂䡁䅑督湁䍁䅅䅊䍂䍁䅑杍穁䅁䅁䅎䅑䝁䅉䅁湁䙁䅳兔䩂䙁䄸睑療䝁䄰䅣桂䝁䄴入時䕁䅳党㕂䙁䅍䅤桂䡁䅑督時䡁䅙免畁䡁䅧䅢穂䝁䄰兘兂䝁䅕杢穂䝁䅫睢畂䍁䄰睔兂䕁䅕村湁䍁䅅䅊䑂䍁䅑李䅁䵁䙷䅁浂䅁䅁睊扂䕁䄰兓時䕁䅍睢瑂䡁䅁兙畂䡁䅫睘䱂䝁䅕入呂䡁䅑兙あ䡁䅍睘㉂䑁䅅䅉潁䑁䅍克畁䡁䅧䅢穂䝁䄰兘䱂䝁䅕入時䙁䅍䅤桂䡁䅑督湁䍁䅅䅊䍂䍁䅑兎祁䅁䅁材䅑䙁䅉䅁䵂䝁䅕杤求䡁䅉党歂䍁䅁杒祂䝁䅕党杁䕁䅍兙穂䝁䅧䅉䝂䝁䅷睢㍂䍁䅷䅉硁䍁䅁兗祂䍁䄴䅉䡂䡁䅉睢㍂䡁䅑䅡杁䍁䅧兊灁䅁䅁杋䅉䝁䅁䅁扂䙁䅍䅕䡂䙁䄸睑療䝁䄰䅣桂䝁䄴入時䕁䅳党㕂䙁䅍䅤桂䡁䅑督時䡁䅙免畁䡁䅧䅢穂䝁䄰兘呂䡁䅕䅣睂䝁䅷党瑂䝁䅕杢あ䝁䅅䅢桁䍁䅑睑歁䑁䅙䅁䥁杂䅁杣䅁䍁䅣睗乂䕁䅫睘䑂䝁䄸兢睂䝁䅅杢㕂䙁䄸睓求䡁䅫睕あ䝁䅅䅤穂䙁䄸杤硁䍁䅁䅋穁䍁䅫杌㑂䝁䅷督瑂䙁䄰睓求䡁䅫睘呂䡁䅑兙あ䡁䅍睊桁䍁䅑兒歁䑁䅉睍㙁䍁䅑兓歁䑁䅉睍䅁䑁䕍䅁䭃䅁䅁睊扂䕁䅍睢睂䡁䅫䅉療䝁䅙䅉呂䙁䅁睒時䕁䅍睢瑂䡁䅁兙畂䡁䅫睘䱂䝁䅕入呂䡁䅑兙あ䡁䅍睘㉂䑁䅉睘畂䝁䅕睤畁䡁䅧䅢穂䝁䄰兘䑂䝁䅅䅣灂䡁䅑兙獂䝁䅫来桂䡁䅑兡療䝁䄴睊桁䍁䅑兒歁䑁䅑杏歁䕁䅯䅊ぁ䅁䅁睓䅣䡁䅉䅁湁䙁䅳兔䩂䙁䄸睑療䝁䄰䅣桂䝁䄴入時䕁䅳党㕂䙁䅍䅤桂䡁䅑督時䡁䅙免杁䍁䅧睍灁䍁䄴䅥獂䡁䅍兢摂䕁䅳党㕂䙁䄸睕あ䝁䅅䅤穂䍁䅣光歁䕁䅕䅊祁䑁䅉杏歁䕁䅫䅊祁䑁䅉䅁硁䅂䅁杗䅁䙁䅳睕兂䕁䅣睘䑂䝁䄸兢睂䝁䅅杢㕂䙁䄸睓求䡁䅫睕あ䝁䅅䅤穂䙁䄸杤祁䍁䄴䅥獂䡁䅍兢摂䕁䅳党㕂䙁䄸睕あ䝁䅅䅤穂䍁䅅䅊䝂䍁䅑兏䅁䡁䜸䅁䕃䅁䅁睊扂䕁䅍睢睂䡁䅫䅉療䝁䅙䅉呂䙁䅁睒時䕁䅍睢瑂䡁䅁兙畂䡁䅫睘䱂䝁䅕入呂䡁䅑兙あ䡁䅍睘㉂䑁䅉睘畂䝁䅕睤畁䡁䅧䅢穂䝁䄰兘䱂䝁䅕入時䙁䅍䅤桂䡁䅑督湁䍁䅅䅊呂䍁䅑兎㑁䑁䅯䅊呂䍁䅑李硁䅁䅁睍䅣䩁䅁䅁湁䙁䅳睕兂䕁䅣睘䑂䝁䄸兢睂䝁䅅杢㕂䙁䄸睓求䡁䅫睕あ䝁䅅䅤穂䙁䄸杤祁䍁䅁免畁䡁䅧䅢穂䝁䄰兘䑂䝁䅅䅣灂䡁䅑兙獂䙁䄸睕あ䡁䅉兤橂䡁䅑兤祂䝁䅕睘呂䡁䅕兢瑂䝁䅅杣㕂䍁䅣光歁䕁䅙䅊硁䑁䅁杏歁䙁䅁䅊硁䑁䅁䅁い杂䅁杇䅁䕁䅫兕時䙁䅑睔啂䕁䅅䅔時䙁䅉兒坂䅁䅁兂䅁䝁䅉䅁扂䕁䅳党㕂䙁䅍䅤桂䡁䅑督時䡁䅑党穂䡁䅑杚灂䝁䅷党畁䡁䅧䅢穂䝁䄰兘䑂䝁䅅䅣灂䡁䅑兙獂䝁䅫来桂䡁䅑兡療䝁䄴光歁䕁䅙䅊ぁ䑁䅯䅊剂䍁䅑䅎䅁䵁䅙䅁畂䅁䅁睊扂䕁䄰兓時䕁䅍睢瑂䡁䅁兙畂䡁䅫睘䱂䝁䅕入呂䡁䅑兙あ䡁䅍睘㉂䑁䅅睘畁䡁䅧䅢穂䝁䄰兘兂䝁䅕杢穂䝁䅫睢畂䍁䄰睔兂䕁䅕村湁䍁䅅䅊䕂䍁䅑䅎㙁䍁䅑兓歁䑁䅑䅁䍁兂䅁䅘䅁䙁䅳兔䩂䙁䄸睑療䝁䄰䅣桂䝁䄴入時䕁䅳党㕂䙁䅍䅤桂䡁䅑督時䡁䅙免畁䡁䅧䅢穂䝁䄰兘卂䝁䅅䅤灂䝁䄸督桁䍁䅑䅒歁䑁䅙杏歁䕁䅫䅊㉁䅁䅁典䅕䙁䅙䅁扂䙁䅍䅕䡂䙁䄸睑療䝁䄰䅣桂䝁䄴入時䕁䅳党㕂䙁䅍䅤桂䡁䅑督時䡁䅙杍畁䡁䅧䅢穂䝁䄰兘呂䝁䅧党求䡁䅑免桁䍁䅑村歁䑁䅣兎䅁䱁䝉䅁浂䅁䅁睊扂䕁䄰兓時䕁䅍睢瑂䡁䅁兙畂䡁䅫睘䱂䝁䅕入呂䡁䅑兙あ䡁䅍睘㉂䑁䅅䅉潁䑁䅍克畁䡁䅧䅢穂䝁䄰兘䱂䝁䅕入時䙁䅍䅤桂䡁䅑督湁䍁䅅䅊䍂䍁䅑兎㕁䅁䅁村䅑䝁䄴䅁湁䙁䅳兔䩂䙁䄸睑療䝁䄰䅣桂䝁䄴入時䕁䅳党㕂䙁䅍䅤桂䡁䅑督時䡁䅙免瑁䕁䅍睢睂䡁䅫杌㑂䝁䅷督瑂䙁䄰杕桂䡁䅑兡療䡁䅍睊桁䍁䅑睑歁䑁䅫杏歁䕁䅍䅊硁䑁䅕䅍䅁䥁䙯䅁捃䅁䅁睊扂䕁䅍睢睂䡁䅫䅉療䝁䅙䅉呂䙁䅁睒時䕁䅍睢瑂䡁䅁兙畂䡁䅫睘䱂䝁䅕入呂䡁䅑兙あ䡁䅍睘㉂䑁䅉睘畂䝁䅕睤畁䡁䅧䅢穂䝁䄰兘䑂䝁䅅䅣灂䡁䅑兙獂䙁䄸睕あ䡁䅉兤橂䡁䅑兤祂䝁䅕睘杁䕁䅑党あ䝁䅅兡獂䡁䅍䅉湁䍁䅅䅊䡂䍁䅑免祁䅁䅁䅥䅣䑁䅁䅁䩂䙁䅅睘噂䙁䅍睘䡂䕁䅅兑兂䙁䄸䅖偂䙁䅑兑䵂䙁䄸兒剂䙁䅕兓啂䙁䅫䅁䝄杁䅁杣䅁䍁䅣睗乂䕁䅫睘䑂䝁䄸兢睂䝁䅅杢㕂䙁䄸睓求䡁䅫睕あ䝁䅅䅤穂䙁䄸杤硁䍁䅁䅋穁䍁䅫杌㑂䝁䅷督瑂䙁䄰睓求䡁䅫睘呂䡁䅑兙あ䡁䅍睊桁䍁䅑兒歁䑁䅉杍㙁䍁䅑䅔歁䑁䅉杍䅁䑁䕯䅁浂䅁䅁睊扂䕁䄰兓時䕁䅍睢瑂䡁䅁兙畂䡁䅫睘䱂䝁䅕入呂䡁䅑兙あ䡁䅍睘㉂䑁䅅䅉潁䑁䅍克畁䡁䅧䅢穂䝁䄰兘䱂䝁䅕入時䙁䅍䅤桂䡁䅑督湁䍁䅅䅊䙂䍁䅑李睁䅁䅁兒䅑䕁䅯䅁扂䕁䅳党㕂䙁䅍䅤桂䡁䅑督時䡁䅑党穂䡁䅑杚灂䝁䅷党畁䡁䅧䅢穂䡁䅧兘呂䝁䅧党求䡁䅑免桁䍁䅑兒歁䑁䅉䅍䅁䍁䄴䅁䥃䅁䅁睊扂䙁䅍䅕䡂䙁䄸睑療䝁䄰䅣桂䝁䄴入時䕁䅳党㕂䙁䅍䅤桂䡁䅑督時䡁䅙杍杁䑁䅅杌㑂䝁䅷督瑂䙁䄰睑桂䡁䅁兡あ䝁䅅䅢時䙁䅍䅤祂䡁䅕睙あ䡁䅕杣求䙁䄸䅉䕂䝁䅕䅤桂䝁䅫䅢穂䍁䅁睊桁䍁䅑杒歁䑁䅣李䅁䍁䡅䅁䥃䅁䅁睊扂䙁䅍䅕䡂䙁䄸睑療䝁䄰䅣桂䝁䄴入時䕁䅳党㕂䙁䅍䅤桂䡁䅑督時䡁䅙杍杁䑁䅅杌㑂䝁䅷督瑂䙁䄰睑桂䡁䅁兡あ䝁䅅䅢時䙁䅍䅤祂䡁䅕睙あ䡁䅕杣求䙁䄸䅉䕂䝁䅕䅤桂䝁䅫䅢穂䍁䅁睊桁䍁䅑睒歁䑁䅑䅎䅁䉁䡫䅁祂䅁䅁睊扂䕁䄰兓時䕁䅍睢瑂䡁䅁兙畂䡁䅫睘䱂䝁䅕入呂䡁䅑兙あ䡁䅍睘㉂䑁䅅䅉潁䑁䅍克畁䡁䅧䅢穂䝁䄰兘䱂䝁䅕入時䙁䅍䅤桂䡁䅑督湁䍁䅅䅊䑂䍁䅑兎ぁ䑁䅯䅊䑂䍁䅑兎ㅁ䅁䅁䅑䅑䡁䅉䅁偂䡁䅁䅤灂䝁䄸杢穂䍁䅁睔ㅂ䡁䅑杌杁䝁䅅䅤杁䡁䅑䅡求䍁䅁兒畂䝁䅑䅉療䝁䅙䅉兂䝁䅕杣灂䝁䄸䅚獁䍁䅁睑療䝁䄰兢療䝁䄴䅉呂䡁䅑睢橂䝁䅳䅉潁䝁䅅睙あ䡁䅕兙獂䍁䅫䅁㝁睁䅁杭䅁䕁䄸䅣あ䝁䅫睢畂䡁䅍杏杁䕁䅍兤祂䡁䅉児噂䙁䅍䅒獁䍁䅁兔桂䝁䅣児啂䝁䅧睢ㅂ䡁䅍兙畂䝁䅑督獁䕁䅍睢畂䡁䅙兔求䡁䅑䅡療䝁䅑児乂䕁䅫杣求䝁䅍睢瑂䝁䄰党畂䝁䅑党歂䍁䅷䅉佂䕁䅅児佂䕁䅅䅌杁䙁䅑党祂䝁䄰児求䝁䄴兌噂䙁䅍䅁权䅂䅁䅕䅁䕁䅫兕時䕁䄰兑奂䙁䄸兗卂䙁䄸杒偂䙁䅉睘啂䕁䅅䅗時䕁䅉兒佂䕁䅕杒䩂䙁䅑睘䑂䕁䅅杕卂䙁䅫睘䝂䕁䄸杕塂䕁䅅杕䕂䅁䅁䅁䅍䡁䅉䅁湁䙁䅳兔䩂䙁䄸睑療䝁䄰䅣桂䝁䄴入時䕁䅳党㕂䙁䅍䅤桂䡁䅑督時䡁䅙免杁䍁䅧睍灁䍁䄴䅥獂䡁䅍兢摂䕁䅳党㕂䙁䄸睕あ䝁䅅䅤穂䍁䅣光歁䕁䅍䅊㉁䑁䅅杏歁䕁䅍䅊㉁䑁䅣䅁䕂䅂䅁杌䅁䕁䅫兕時䕁䄴䅕兂䕁䅕睘硁䙁䅫杕時䕁䅅杔佂䙁䄸睒卂䕁䄸睖啂䕁䅧䅁婁杁䅁杓䅁䕁䅙兙灂䡁䅉䅉坂䝁䅅䅢ㅂ䝁䅕䅉療䝁䅙䅉䵂䝁䅫兙楂䝁䅫䅢灂䡁䅑兡求䡁䅍䅉潁䙁䅉党睂䝁䄸杣あ䝁䅕䅚灁䅁䅁睊䅍䥁䅉䅁扂䕁䄰兓時䕁䅍睢瑂䡁䅁兙畂䡁䅫睘䱂䝁䅕入呂䡁䅑兙あ䡁䅍睘㉂䑁䅅杌㑂䝁䅷督瑂䙁䄰睑桂䡁䅁兡あ䝁䅅䅢時䙁䅍䅤祂䡁䅕睙あ䡁䅕杣求䙁䄸睕ㅂ䝁䄰兢桂䡁䅉入桁䍁䅑杒歁䑁䅧杏歁䙁䅁䅊㑁䅁䅁光䅑䡁䅁䅁湁䙁䅳睕兂䕁䅣睘䑂䝁䄸兢睂䝁䅅杢㕂䙁䄸睓求䡁䅫睕あ䝁䅅䅤穂䙁䄸杤硁䍁䅁䅋祁䍁䅫杌㑂䝁䅷督瑂䙁䄰睑桂䡁䅍䅡時䕁䅙䅢療䡁䅣睊桁䍁䅑兒歁䑁䅙杏歁䙁䅁䅊㉁䅁䅁兌䅙䙁䅙䅁扂䙁䅍䅕䡂䙁䄸睑療䝁䄰䅣桂䝁䄴入時䕁䅳党㕂䙁䅍䅤桂䡁䅑督時䡁䅙杍畁䡁䅧䅢穂䝁䄰兘呂䝁䅧党求䡁䅑免桁䍁䅑睒歁䑁䅣兎䅁䱁䝫䅁祂䅁䅁睊扂䕁䄰兓時䕁䅍睢瑂䡁䅁兙畂䡁䅫睘䱂䝁䅕入呂䡁䅑兙あ䡁䅍睘㉂䑁䅅䅉潁䑁䅍克畁䡁䅧䅢穂䝁䄰兘䱂䝁䅕入時䙁䅍䅤桂䡁䅑督湁䍁䅅䅊䕂䍁䅑兎ぁ䑁䅯䅊䕂䍁䅑兎ㅁ䅁䅁兑䅑䡁䅉䅁湁䙁䅳兔䩂䙁䄸睑療䝁䄰䅣桂䝁䄴入時䕁䅳党㕂䙁䅍䅤桂䡁䅑督時䡁䅙免杁䍁䅧睍灁䍁䄴䅥獂䡁䅍兢摂䕁䅳党㕂䙁䄸睕あ䝁䅅䅤穂䍁䅣光歁䕁䅕䅊祁䑁䅍杏歁䕁䅷䅊祁䑁䅍䅁㝁䅂䅁杣䅁䍁䅣睗乂䕁䅫睘䑂䝁䄸兢睂䝁䅅杢㕂䙁䄸睓求䡁䅫睕あ䝁䅅䅤穂䙁䄸杤硁䍁䄰睑療䡁䅁入畁䡁䅧䅢穂䝁䄰兘䑂䝁䅅䅣灂䡁䅑兙獂䝁䅫来桂䡁䅑兡療䝁䄴睊桁䍁䅑睑歁䑁䅕䅍䅁䑁䙉䅁捃䅁䅁睊扂䕁䅍睢睂䡁䅫䅉療䝁䅙䅉呂䙁䅁睒時䕁䅍睢瑂䡁䅁兙畂䡁䅫睘䱂䝁䅕入呂䡁䅑兙あ䡁䅍睘㉂䑁䅉睘畂䝁䅕睤畁䡁䅧䅢穂䝁䄰兘䑂䝁䅅䅣灂䡁䅑兙獂䙁䄸睕あ䡁䅉兤橂䡁䅑兤祂䝁䅕睘杁䕁䅑党あ䝁䅅兡獂䡁䅍䅉湁䍁䅅䅊䍂䍁䅑睎㉁䅁䅁䅨䅣䝁䅙䅁湁䙁䅳兔䩂䙁䄸睑療䝁䄰䅣桂䝁䄴入時䕁䅳党㕂䙁䅍䅤桂䡁䅑督時䡁䅙免杁䍁䅧睍灁䍁䄴䅥獂䡁䅍兢摂䕁䅳党㕂䙁䄸睕あ䝁䅅䅤穂䍁䅣光歁䕁䅕䅊ㅁ䑁䅫䅁䑂䅂䅁杣䅁䍁䅣睗乂䕁䅫睘䑂䝁䄸兢睂䝁䅅杢㕂䙁䄸睓求䡁䅫睕あ䝁䅅䅤穂䙁䄸杤硁䍁䅁䅋穁䍁䅫杌㑂䝁䅷督瑂䙁䄰睓求䡁䅫睘呂䡁䅑兙あ䡁䅍睊桁䍁䅑杓歁䑁䅉杍㙁䍁䅑䅔歁䑁䅉杍䅁䑁䕕䅁潁䅁䅁兓剂䙁䄸杗䙂䙁䅉睔時䕁䅍睔噂䙁䅁睔佂䙁䄸䅒䙂䕁䅉䅖䅁䕁䉷䅁捂䅁䅁睗䱂䝁䅕入呂䡁䅑兙あ䡁䅍睘あ䝁䅕督あ䝁䅙兡獂䝁䅕杌㑂䝁䅷督瑂䙁䄰睓求䡁䅫睘呂䡁䅑兙あ䡁䅍光歁䕁䅍䅊ㅁ䑁䅕杏歁䕁䅍䅊ㅁ䑁䅙䅁楃䅁䅁䅨䅁䍁䅣睗䑂䝁䄸䅣㕂䍁䅁睢浂䍁䅁睕兂䕁䅣睘䑂䝁䄸兢睂䝁䅅杢㕂䙁䄸睓求䡁䅫睕あ䝁䅅䅤穂䙁䄸杤硁䙁䄸杒灂䝁䄴兙獂䍁䄴䅥獂䡁䅍兢摂䙁䅉兙あ䝁䅫睢穂䍁䅣光歁䕁䅍䅊硁䑁䅅杏歁䕁䅍䅊硁䑁䅕睎䅁䝁䤸䅁㑁䅁䅁兓剂䙁䄸兑䑂䕁䅍䅖時䙁䅉兒䑂䙁䅙睘硁䙁䅫杕時䕁䅅杔佂䙁䄸睒卂䕁䄸睖啂䕁䅧䅁晁杁䅁杆䅁䑁䅁睍癁䑁䅉兏癁䑁䅉䅍硁䑁䅫䅁時䅁䅁杣䅁䍁䅣睗乂䕁䅫睘䑂䝁䄸兢睂䝁䅅杢㕂䙁䄸睓求䡁䅫睕あ䝁䅅䅤穂䙁䄸杤硁䍁䅁䅋穁䍁䅫杌㑂䝁䅷督瑂䙁䄰睓求䡁䅫睘呂䡁䅑兙あ䡁䅍睊桁䍁䅑杓歁䑁䅉杍㙁䍁䅑睔歁䑁䅉杍䅁䑁䕧䅁敂䅁䅁睊扂䕁䄰兓時䕁䅍睢瑂䡁䅁兙畂䡁䅫睘䱂䝁䅕入呂䡁䅑兙あ䡁䅍睘㉂䑁䅅䅉潁䑁䅍克畁䡁䅧䅢穂䝁䄰兘卂䝁䅅䅤灂䝁䄸督湁䍁䅅䅊䑂䍁䅑䅎䅁䝁䕯䅁楂䅁䅁睗䱂䝁䅕入呂䡁䅑兙あ䡁䅍睘あ䝁䅕督あ䝁䅙兡獂䝁䅕杌㑂䝁䅷督瑂䙁䄰睑桂䡁䅁兡あ䝁䅅䅢灂䡁䅯兙あ䝁䅫睢畂䍁䅅䅊䝂䍁䅑䅎㙁䍁䅑睓歁䑁䅑䅁偄䅁䅁䅐䅁䕁䅍睢瑂䝁䄰睢畂䍁䅁兒硂䡁䅕兡あ䡁䅫䅌杁䑁䅍䅉婂䡁䅉杌杁䕁䅍兑䡂䙁䅉䅉潁䍁䅕克䅁䡁䌴䅁㑂䅁䅁睊扂䕁䄰兓時䕁䅍睢瑂䡁䅁兙畂䡁䅫睘䱂䝁䅕入呂䡁䅑兙あ䡁䅍睘㉂䑁䅅兌䑂䝁䄸䅣㕂䍁䄴䅥獂䡁䅍兢摂䕁䅳党㕂䙁䄸睕あ䝁䅅䅤穂䍁䅣光歁䕁䅍䅊硁䑁䅅䅍㙁䍁䅑睑歁䑁䅅免ぁ䅁䅁杊䅕䥁䅁䅁湁䙁䅳睑療䡁䅁入杁䝁䄸杚杁䙁䅍䅕䡂䙁䄸睑療䝁䄰䅣桂䝁䄴入時䕁䅳党㕂䙁䅍䅤桂䡁䅑督時䡁䅙免時䕁䅙兡畂䝁䅅䅢畁䡁䅧䅢穂䝁䄰兘兂䝁䅕杢穂䝁䅫睢畂䍁䄰睔兂䕁䅕村湁䍁䅅䅊䑂䍁䅑李䅁䩁䥣䅁獁䅁䅁兓剂䙁䄸䅖䉂䙁䅧睘䍂䕁䅕杔䙂䕁䅙兓啂䙁䄸睑䝂䙁䄸兎婂䙁䅉䅁㡄杁䅁杓䅁䙁䅳兔䩂䙁䄸睓求䡁䅫睕あ䝁䅅䅤穂䙁䄸杤硁䍁䄴䅥獂䡁䅍兢摂䕁䅳党㕂䙁䄸睕あ䝁䅅䅤穂䍁䅅䅊䍂䍁䅑兎㕁䅁䅁兣䅍䡁䅉䅁湁䙁䅳兔䩂䙁䄸睑療䝁䄰䅣桂䝁䄴入時䕁䅳党㕂䙁䅍䅤桂䡁䅑督時䡁䅙免杁䍁䅧睍灁䍁䄴䅥獂䡁䅍兢摂䕁䅳党㕂䙁䄸睕あ䝁䅅䅤穂䍁䅣光歁䕁䅯䅊祁䑁䅍杏歁䕁䅷䅊祁䑁䅍䅁㍁䅂䅁䅙䅁䍁䅣睗呂䙁䅁睒時䕁䅍睢瑂䡁䅁兙畂䡁䅫睘䱂䝁䅕入呂䡁䅑兙あ䡁䅍睘㉂䑁䅅䅉潁䑁䅉克畁䡁䅧䅢穂䝁䄰兘卂䝁䅅䅤灂䝁䄸督湁䍁䅅䅊䑂䍁䅑李䅁䕁䝑䅁祂䅁䅁睊扂䕁䄰兓時䕁䅍睢瑂䡁䅁兙畂䡁䅫睘䱂䝁䅕入呂䡁䅑兙あ䡁䅍睘㉂䑁䅅䅉潁䑁䅍克畁䡁䅧䅢穂䝁䄰兘䱂䝁䅕入時䙁䅍䅤桂䡁䅑督湁䍁䅅䅊䭂䍁䅑杍穁䑁䅯䅊偂䍁䅑杍穁䅁䅁兏䅑䡁䅉䅁湁䙁䅳兔䩂䙁䄸睑療䝁䄰䅣桂䝁䄴入時䕁䅳党㕂䙁䅍䅤桂䡁䅑督時䡁䅙免杁䍁䅧睍灁䍁䄴䅥獂䡁䅍兢摂䕁䅳党㕂䙁䄸睕あ䝁䅅䅤穂䍁䅣光歁䕁䄰䅊祁䑁䅉杏歁䕁䄸䅊祁䑁䅉䅁㡁䅂䅁杄䅁䕁䅫村乂䍁䄰兖呂䅁䅁䅭䅕䕁䅙䅁坂䝁䅅杣灂䝁䅅杙獂䝁䅕䅉卂䝁䅅䅤求䍁䅁䅒求䝁䅉䅤癁䍁䅁䅖療䡁䅑兙獂䍁䅁䅒求䝁䅉䅤杁䍁䅧兊灁䅁䅁睡䅅䡁䅉䅁湁䙁䅳兔䩂䙁䄸睑療䝁䄰䅣桂䝁䄴入時䕁䅳党㕂䙁䅍䅤桂䡁䅑督時䡁䅙免杁䍁䅧睍灁䍁䄴䅥獂䡁䅍兢摂䕁䅳党㕂䙁䄸睕あ䝁䅅䅤穂䍁䅣光歁䕁䄰䅊祁䑁䅍杏歁䕁䄸䅊祁䑁䅍䅁㥁䅂䅁杍䅁䕁䅫兕時䙁䅑睔啂䕁䅅䅔時䙁䅍兖䍂䙁䄸䅒䙂䕁䅉䅖時䕁䅕村䩂䙁䅑䅒䉂䅁䅁兪䅅䙁䄴䅁扂䕁䄰兓時䕁䅳党㕂䙁䅍䅤桂䡁䅑督時䡁䅙免畁䡁䅧䅢穂䝁䄰兘䑂䝁䅅䅣灂䡁䅑兙獂䝁䅫来桂䡁䅑兡療䝁䄴光歁䕁䅍䅊㕁䑁䅯䅊䑂䍁䅑杍ㅁ䅁䅁睮䅍䅁䄴䅁祁䑁䅣免ぁ䑁䅙䅏䅁䉁䄴䅁慂䅁䅁睗乂䕁䅫睘䑂䝁䄸兢睂䝁䅅杢㕂䙁䄸睓求䡁䅫睕あ䝁䅅䅤穂䙁䄸杤硁䍁䄴䅥獂䡁䅍兢摂䕁䅳党㕂䙁䄸睕あ䝁䅅䅤穂䍁䅅䅊䙂䍁䅑兎㕁䅁䅁允䅑䑁䅯䅁偂䡁䅁䅤灂䝁䄸杢穂䑁䅯睕あ䝁䅅䅤灂䡁䅍䅤灂䝁䅍児䥂䕁䅫睒䥂䍁䅷杔䉂䑁䄰杔䉂䅁䅁朰䅣䑁䅉䅁䩂䙁䅅睘䥂䕁䅕䅒䡂䕁䅫杔䡂䙁䄸兑佂䕁䅑睘䕂䕁䅕杕䩂䙁䅙睘䉂䕁䅑杓䅁䕁䈴䅁煂䅁䅁睊扂䕁䄰兓時䕁䅍睢瑂䡁䅁兙畂䡁䅫睘䱂䝁䅕入呂䡁䅑兙あ䡁䅍睘㉂䑁䅅䅉潁䑁䅍克畁䡁䅧䅢穂䝁䄰兘兂䝁䅕杢穂䝁䅫睢畂䍁䄰睔兂䕁䅕村湁䍁䅅䅊䑂䍁䅑䅎䅁䡁䕉䅁㑂䅁䅁睊扂䕁䄰兓時䕁䅍睢瑂䡁䅁兙畂䡁䅫睘䱂䝁䅕入呂䡁䅑兙あ䡁䅍睘㉂䑁䅅䅉潁䑁䅍克畁䡁䅧䅢穂䝁䄰兘兂䝁䅕杢穂䝁䅫睢畂䍁䄰睔兂䕁䅕村湁䍁䅅䅊䑂䍁䅑兏㙁䍁䅑睑歁䑁䅕李㑁䅁䅁䅤䅑䡁䄴䅁湁䙁䅳兔䩂䙁䄸睑療䝁䄰䅣桂䝁䄴入時䕁䅳党㕂䙁䅍䅤桂䡁䅑督時䡁䅙免杁䍁䄰䅢桂䡁䅑党穂䡁䅑杌㑂䝁䅷督瑂䙁䄰睓求䡁䅫睘呂䡁䅑兙あ䡁䅍睊桁䍁䅑兒歁䑁䅅䅍ㅁ䑁䅯䅊䡂䍁䅑免睁䑁䅕䅁晁兂䅁条䅁䙁䅳兔䩂䙁䄸睑療䝁䄰䅣桂䝁䄴入時䕁䅳党㕂䙁䅍䅤桂䡁䅑督時䡁䅙免畁䡁䅧䅢穂䝁䄰兘䱂䝁䅕入時䙁䅍䅤桂䡁䅑督桁䍁䅑睑歁䑁䅅䅍㕁䑁䅯䅊䑂䍁䅑免硁䑁䅑䅁㍂兂䅁䅅䅁䕁䅙兕ぁ䑁䅉䅍祁䑁䅕䅁瑃䅃䅁杉䅁䕁䅫兕時䕁䅕䅗兂䕁䅷睔卂䕁䅕睘䕂䙁䅉兓䵂䕁䅷䅁潃䅁䅁杦䅁䍁䅣睗乂䕁䅫睘䑂䝁䄸兢睂䝁䅅杢㕂䙁䄸睓求䡁䅫睕あ䝁䅅䅤穂䙁䄸杤硁䍁䄰䅉偂䡁䅉兡湂䝁䅫杢桂䝁䅷杌㑂䝁䅷督瑂䙁䄰睓求䡁䅫睘呂䡁䅑兙あ䡁䅍睊桁䍁䅑兒歁䑁䅉杍㙁䍁䅑杓歁䑁䅉杍䅁䝁䙅䅁あ䅁䅁睊扂䕁䄰兓時䕁䅍睢瑂䡁䅁兙畂䡁䅫睘䱂䝁䅕入呂䡁䅑兙あ䡁䅍睘㉂䑁䅅䅉潁䑁䅍克畁䡁䅧䅢穂䝁䄰兘兂䝁䅕杢穂䝁䅫睢畂䍁䄰睔兂䕁䅕村湁䍁䅅䅊䕂䍁䅑䅎㙁䍁䅑兓歁䑁䅑䅁穂䅂䅁䅌䅁䕁䄴党あ䍁䅁兓畂䝁䅍睢瑂䝁䅕䅉乂䝁䅅杣湂䝁䅫杢杁䍁䅧兊灁䅁䅁䅄䅉䝁䅑䅁扂䙁䅍䅕䡂䙁䄸睑療䝁䄰䅣桂䝁䄴入時䕁䅳党㕂䙁䅍䅤桂䡁䅑督時䡁䅙杍畁䡁䅧䅢穂䝁䄰兘卂䝁䅅䅤灂䝁䄸督桁䍁䅑睑歁䑁䅅免㙁䍁䅑睑歁䑁䅅兎㍁䅁䅁䅄䅧䩁䅷䅁湁䙁䅳睑療䡁䅁入杁䝁䄸杚杁䙁䅍䅕䡂䙁䄸睑療䝁䄰䅣桂䝁䄴入時䕁䅳党㕂䙁䅍䅤桂䡁䅑督時䡁䅙杍時䝁䄴党㍂䍁䄴䅥獂䡁䅍兢摂䕁䅍兙睂䝁䅫䅤桂䝁䅷睘呂䡁䅑杣ㅂ䝁䅍䅤ㅂ䡁䅉党時䍁䅁䅒求䡁䅑兙灂䝁䅷督杁䍁䅣光歁䕁䅧䅊㍁䑁䅙䅁䭃睂䅁䅤䅁䍁䅣睗乂䕁䅫睘䑂䝁䄸兢睂䝁䅅杢㕂䙁䄸睓求䡁䅫睕あ䝁䅅䅤穂䙁䄸杤硁䍁䅁䅋穁䍁䅫杌㑂䝁䅷督瑂䙁䄰䅕求䝁䄴督灂䝁䄸杢瑁䕁䄸䅕䙂䕁䅉睊桁䍁䅑䅒歁䑁䅕杏歁䕁䅫䅊ㅁ䅁䅁兤䅑䡁䅧䅁湁䙁䅳兔䩂䙁䄸睑療䝁䄰䅣桂䝁䄴入時䕁䅳党㕂䙁䅍䅤桂䡁䅑督時䡁䅙免瑁䕁䅍睢睂䡁䅫杌㑂䝁䅷督瑂䙁䄰睓求䡁䅫睘呂䡁䅑兙あ䡁䅍睊桁䍁䅑睑歁䑁䅅䅍㕁䑁䅯䅊䑂䍁䅑免硁䑁䅑䅁乂兂䅁䅈䅁䙁䅍䅕瑁䙁䅍䅓䉂䙁䅉兒呂䙁䄸睔噂䙁䅑䅁㍃睂䅁杈䅁䕁䅫兕時䕁䄸䅔時䕁䅍睔乂䕁䄰睘䑂䙁䅫睍䅁䱁䈰䅁㡁䅁䅁兑㉂䝁䅕杣桂䝁䅣党杁䕁䅫杢あ䝁䅕杣求䡁䅍䅤杁䙁䅉兙あ䝁䅕䅉牁䍁䅁免杁䍁䅧兊灁䅁䅁朶䅅䡁䅉䅁扂䕁䄰兓時䕁䅳党㕂䙁䅍䅤桂䡁䅑督時䡁䅙免畁䡁䅧䅢穂䝁䄰兘䑂䝁䅅䅣灂䡁䅑兙獂䙁䄸睕あ䡁䅉兤橂䡁䅑兤祂䝁䅕睘呂䡁䅕兢瑂䝁䅅杣㕂䍁䅅䅊䝂䍁䅑兏㙁䍁䅑䅕歁䑁䅫䅁癄睁䅁䅢䅁䍁䅣睗乂䕁䅫睘䑂䝁䄸兢睂䝁䅅杢㕂䙁䄸睓求䡁䅫睕あ䝁䅅䅤穂䙁䄸杤硁䍁䅁䅋穁䍁䅫杌㑂䝁䅷督瑂䙁䄰杕桂䡁䅑兡療䡁䅍睊桁䍁䅑睑歁䑁䅫杏歁䕁䅍䅊硁䑁䅕䅍䅁䝁䕷䅁潂䅁䅁睊扂䕁䄰兓時䕁䅍睢瑂䡁䅁兙畂䡁䅫睘䱂䝁䅕入呂䡁䅑兙あ䡁䅍睘㉂䑁䅅䅉潁䑁䅍克畁䡁䅧䅢穂䝁䄰兘卂䝁䅅䅤灂䝁䄸督湁䍁䅅䅊䕂䍁䅑䅎㙁䍁䅑兓歁䑁䅑䅁牂䅂䅁䅑䅁䕁䅫兕時䕁䄰兑奂䙁䄸兗卂䙁䄸杒偂䙁䅉睘佂䕁䄸䅔時䕁䅍兑卂䙁䅉兗時䕁䅙睔卂䙁䅣兑卂䕁䅑䅁潄杁䅁䅩䅁䙁䅳睕兂䕁䅣睘䑂䝁䄸兢睂䝁䅅杢㕂䙁䄸睓求䡁䅫睕あ䝁䅅䅤穂䙁䄸杤硁䍁䄴䅥獂䡁䅍兢摂䕁䅍兙睂䝁䅫䅤桂䝁䅷睘呂䡁䅑杣ㅂ䝁䅍䅤ㅂ䡁䅉党時䙁䅍兤瑂䝁䄰兙祂䡁䅫光歁䕁䅙䅊硁䑁䅅杏歁䙁䅁䅊硁䑁䅅䅁䑁杂䅁䅦䅁䍁䅣睗乂䕁䅫睘䑂䝁䄸兢睂䝁䅅杢㕂䙁䄸睓求䡁䅫睕あ䝁䅅䅤穂䙁䄸杤硁䍁䄰䅉偂䡁䅉兡湂䝁䅫杢桂䝁䅷杌㑂䝁䅷督瑂䙁䄰睑桂䡁䅁兡あ䝁䅅䅢灂䡁䅯兙あ䝁䅫睢畂䍁䅣光歁䕁䅍䅊ぁ䑁䅧䅁㡁兂䅁杂䅁䑁䅅䅍䅁䱁䜴䅁睁䅁䅁兓剂䙁䄸䅖偂䙁䅑兑䵂䙁䄸睔兂䙁䅑兓偂䕁䄴睕時䕁䅕杔䕂䙁䄸睔呂䅁䅁䅓䅍䩁䅁䅁湁䙁䅳睑療䡁䅁入杁䝁䄸杚杁䙁䅍䅕䡂䙁䄸睑療䝁䄰䅣桂䝁䄴入時䕁䅳党㕂䙁䅍䅤桂䡁䅑督時䡁䅙免時䕁䅙兡畂䝁䅅䅢畁䡁䅧䅢穂䝁䄰兘兂䝁䅕杢穂䝁䅫睢畂䍁䄰睔兂䕁䅕村湁䍁䅅䅊䑂䍁䅑免祁䑁䅯䅊䑂䍁䅑兎㍁䑁䅙䅁灃䅃䅁䅡䅁䍁䅣睗乂䕁䅫睘䑂䝁䄸兢睂䝁䅅杢㕂䙁䄸睓求䡁䅫睕あ䝁䅅䅤穂䙁䄸杤硁䍁䅁䅋穁䍁䅫杌㑂䝁䅷督瑂䙁䄰杕桂䡁䅑兡療䡁䅍睊桁䍁䅑䅒歁䑁䅕杏歁䕁䅫䅊ㅁ䅁䅁兢䅑䑁䅁䅁䩂䙁䅅睘䕂䕁䅍睕時䕁䅉睔佂䕁䅑睘䑂䕁䄸兖兂䕁䄸杔時䙁䅑兗兂䕁䅕䅁啃杂䅁䅩䅁䍁䅣睗乂䕁䅫睘䑂䝁䄸兢睂䝁䅅杢㕂䙁䄸睓求䡁䅫睕あ䝁䅅䅤穂䙁䄸杤硁䍁䄰䅉偂䡁䅉兡湂䝁䅫杢桂䝁䅷杌㑂䝁䅷督瑂䙁䄰睑桂䡁䅁兡あ䝁䅅䅢灂䡁䅯兙あ䝁䅫睢畂䍁䅣光歁䕁䅕䅊ㅁ䑁䅉杏歁䕁䅯䅊ㅁ䑁䅉䅁䑂兂䅁条䅁䍁䅣睗乂䕁䅫睘䑂䝁䄸兢睂䝁䅅杢㕂䙁䄸睓求䡁䅫睕あ䝁䅅䅤穂䙁䄸杤硁䍁䅁䅋穁䍁䅫杌㑂䝁䅷督瑂䙁䄰睕ㅂ䡁䅁䅣獂䝁䅕兢求䝁䄴䅤桂䝁䅷睊桁䍁䅑睑歁䑁䅑䅁畂䅂䅁䅥䅁䍁䅣睗乂䕁䅫睘䑂䝁䄸兢睂䝁䅅杢㕂䙁䄸睓求䡁䅫睕あ䝁䅅䅤穂䙁䄸杤硁䍁䅁䅋穁䍁䅫杌㑂䝁䅷督瑂䙁䄰睕ㅂ䡁䅁䅣獂䝁䅕兢求䝁䄴䅤桂䝁䅷睊桁䍁䅑睑歁䑁䅫杏歁䕁䅍䅊硁䑁䅙䅎䅁䡁䕁䅁獁䅁䅁兓剂䙁䄸睖䉂䙁䅉杕䉂䕁䄴䅖呂䙁䄸兒奂䕁䅕杕䑂䕁䅫睕䙂䕁䅑䅁佂睁䅁䅈䅁䕁䅫兕時䕁䄸䅖䥂䕁䅕杕時䕁䄸䅕䙂䙁䅉䅁㉃䅁䅁杋䅁䕁䅫兕時䕁䅷䅖䕂䙁䄸䅒噂䕁䅕睘佂䕁䅕䅗啂䙁䄸杒䩂䙁䅙兒䅁䭁䉣䅁あ䅁䅁睊扂䕁䄰兓時䕁䅍睢瑂䡁䅁兙畂䡁䅫睘䱂䝁䅕入呂䡁䅑兙あ䡁䅍睘㉂䑁䅅䅉潁䑁䅍克畁䡁䅧䅢穂䝁䄰兘呂䡁䅕䅣睂䝁䅷党瑂䝁䅕杢あ䝁䅅䅢湁䍁䅅䅊䕂䍁䅑䅎㙁䍁䅑兓歁䑁䅑䅁療䅂䅁䅡䅁䙁䅉党歂䡁䅕睙あ䝁䅫睢畂䡁䅍䅉浂䝁䄸杣杁䙁䅑兙㑂䍁䅁䅕療䡁䅍兡あ䝁䅫睢畂䡁䅍䅉瑁䍁䅁䅕祂䝁䅫睢祂䍁䅁兗祂䡁䅍䅉潁䙁䅉党睂䝁䄸杣あ䝁䅕䅚灁䅁䅁眱䅉䕁䅯䅁扂䕁䅳党㕂䙁䅍䅤桂䡁䅑督時䡁䅑党穂䡁䅑杚灂䝁䅷党畁䡁䅧䅢穂䡁䅧兘呂䝁䅧党求䡁䅑免桁䍁䅑村歁䑁䅉杍䅁䕁䄰䅁⭂䅁䅁睊扂䕁䄰兓時䕁䅍睢瑂䡁䅁兙畂䡁䅫睘䱂䝁䅕入呂䡁䅑兙あ䡁䅍睘㉂䑁䅅兌杁䕁䄸杣灂䝁䅣兡畂䝁䅅䅢畁䡁䅧䅢穂䝁䄰兘䱂䝁䅕入時䙁䅍䅤桂䡁䅑督湁䍁䅅䅊乂䍁䅑杍穁䑁䅯䅊偂䍁䅑杍穁䅁䅁睘䅕䡁䅑䅁湁䙁䅳兔䩂䙁䄸睑療䝁䄰䅣桂䝁䄴入時䕁䅳党㕂䙁䅍䅤桂䡁䅑督時䡁䅙免杁䍁䅧睍灁䍁䄴䅥獂䡁䅍兢摂䙁䅍兤睂䡁䅁䅢求䝁䄰党畂䡁䅑兙獂䍁䅣光歁䕁䅑䅊ㅁ䑁䅯䅊䩂䍁䅑兎䅁䡁䕅䅁あ䅁䅁睊扂䙁䅍䅕䡂䙁䄸睑療䝁䄰䅣桂䝁䄴入時䕁䅳党㕂䙁䅍䅤桂䡁䅑督時䡁䅙杍杁䑁䅅杌㑂䝁䅷督瑂䙁䄰睓求䡁䅫睘呂䡁䅑兙あ䡁䅍睊桁䍁䅑䅒歁䑁䅅䅍㕁䑁䅯䅊䕂䍁䅑免硁䑁䅙䅁䉄杂䅁䅣䅁䍁䅣睗乂䕁䅫睘䑂䝁䄸兢睂䝁䅅杢㕂䙁䄸睓求䡁䅫睕あ䝁䅅䅤穂䙁䄸杤硁䍁䅁兌獂䝁䅅䅤求䡁䅍䅤畁䡁䅧䅢穂䝁䄰兘䱂䝁䅕入時䙁䅍䅤桂䡁䅑督湁䍁䅅䅊䍂䍁䅑免睁䑁䅍䅁捁兂䅁杙䅁䕁䄴党あ䍁䅁䅕祂䝁䄸䅣求䡁䅉䅤㕂䍁䅷䅉兂䝁䅷兙畂䡁䅑䅉桂䝁䄴䅚杁䕁䅕兣ㅂ䝁䅫䅣畁䍁䅷䅉硁䍁䅁兗祂䍁䄴䅉䡂䡁䅉睢㍂䡁䅑䅡杁䍁䅧兊灁䅁䅁杇䅉䙁䅙䅁扂䕁䄰兓時䕁䅳党㕂䙁䅍䅤桂䡁䅑督時䡁䅙免畁䡁䅧䅢穂䝁䄰兘䱂䝁䅕入時䙁䅍䅤桂䡁䅑督桁䍁䅑杓歁䑁䅉杍㙁䍁䅑䅔歁䑁䅉杍䅁䝁䐴䅁畂䅁䅁睊扂䕁䄰兓時䕁䅍睢瑂䡁䅁兙畂䡁䅫睘䱂䝁䅕入呂䡁䅑兙あ䡁䅍睘㉂䑁䅅䅉瑁䝁䅷兙あ䝁䅕督あ䍁䄴䅥獂䡁䅍兢摂䕁䅳党㕂䙁䄸睕あ䝁䅅䅤穂䍁䅣光歁䕁䅉䅊祁䑁䅉䅁䥁兂䅁杗䅁䕁䄸䅣求䡁䅉兙あ䝁䅫杢湂䍁䅁䅔求䝁䅅督求䍁䅁睑療䝁䄰兢灂䡁䅑兢求䝁䄴䅤杁䕁䅑兤求䍁䅁睋穁䍁䅁䅋卂䝁䅕䅣療䡁䅉䅤求䝁䅑克䅁䱁䉷䅁慂䅁䅁睗乂䕁䅫睘䑂䝁䄸兢睂䝁䅅杢㕂䙁䄸睓求䡁䅫睕あ䝁䅅䅤穂䙁䄸杤硁䍁䄴䅥獂䡁䅍兢摂䕁䅳党㕂䙁䄸睕あ䝁䅅䅤穂䍁䅅䅊䍂䍁䅑李硁䅁䅁䅫䅑䡁䅷䅁湁䙁䅳睑療䡁䅁入杁䝁䄸杚杁䙁䅍䅕䡂䙁䄸睑療䝁䄰䅣桂䝁䄴入時䕁䅳党㕂䙁䅍䅤桂䡁䅑督時䡁䅙杍時䝁䄴党㍂䍁䄴䅥獂䡁䅍兢摂䙁䅁党畂䡁䅍兡療䝁䄴兌偂䙁䅁兒䍂䍁䅣光歁䕁䅍䅊㉁䅁䅁杚䅣䥁䅧䅁湁䙁䅳睕兂䕁䅣睘䑂䝁䄸兢睂䝁䅅杢㕂䙁䄸睓求䡁䅫睕あ䝁䅅䅤穂䙁䄸杤祁䍁䅁免畁䡁䅧䅢穂䝁䄰兘䑂䝁䅅䅣灂䡁䅑兙獂䙁䄸睕あ䡁䅉兤橂䡁䅑兤祂䝁䅕睘杁䕁䅑党あ䝁䅅兡獂䡁䅍䅉湁䍁䅅䅊䭂䍁䅑睎㉁䅁䅁䅊䅣䝁䄴䅁湁䙁䅳兔䩂䙁䄸睑療䝁䄰䅣桂䝁䄴入時䕁䅳党㕂䙁䅍䅤桂䡁䅑督時䡁䅙免杁䍁䄰䅢桂䡁䅑党穂䡁䅑杌㑂䝁䅷督瑂䙁䄰睓求䡁䅫睘呂䡁䅑兙あ䡁䅍睊桁䍁䅑村歁䑁䅉睍䅁䉁䙑䅁䥁䅁䅁杔啂䕁䄰䅁剂杂䅁杖䅁䙁䅳兔䩂䙁䄸睓求䡁䅫睕あ䝁䅅䅤穂䙁䄸杤硁䍁䄴䅥獂䡁䅍兢摂䕁䅳党㕂䙁䄸睕あ䝁䅅䅤穂䍁䅅䅊䙂䍁䅑兏㕁䑁䅯䅊䡂䍁䅑兏㕁䅁䅁来䅍䥁䅧䅁湁䙁䅳睑療䡁䅁入杁䝁䄸杚杁䙁䅍䅕䡂䙁䄸睑療䝁䄰䅣桂䝁䄴入時䕁䅳党㕂䙁䅍䅤桂䡁䅑督時䡁䅙杍時䝁䄴党㍂䍁䄴䅥獂䡁䅍兢摂䕁䅳党㕂䙁䄸睕あ䝁䅅䅤穂䍁䅣光歁䕁䅑䅊硁䑁䅁兏㙁䍁䅑䅒歁䑁䅅免㉁䅁䅁䅐䅣䝁䄴䅁湁䙁䅳兔䩂䙁䄸睑療䝁䄰䅣桂䝁䄴入時䕁䅳党㕂䙁䅍䅤桂䡁䅑督時䡁䅙免杁䍁䄰䅢桂䡁䅑党穂䡁䅑杌㑂䝁䅷督瑂䙁䄰睓求䡁䅫睘呂䡁䅑兙あ䡁䅍睊桁䍁䅑村歁䑁䅕兏䅁䅁䙷䅁⭂䅁䅁睊扂䕁䄰兓時䕁䅍睢瑂䡁䅁兙畂䡁䅫睘䱂䝁䅕入呂䡁䅑兙あ䡁䅍睘㉂䑁䅅䅉瑁䝁䅷兙あ䝁䅕督あ䍁䄴䅥獂䡁䅍兢摂䕁䅳党㕂䙁䄸睕あ䝁䅅䅤穂䍁䅣光歁䕁䅍䅊硁䑁䅁睎㙁䍁䅑睑歁䑁䅅免硁䅁䅁杈䅕䡁䅯䅁湁䙁䅳兔䩂䙁䄸睑療䝁䄰䅣桂䝁䄴入時䕁䅳党㕂䙁䅍䅤桂䡁䅑督時䡁䅙免杁䍁䄰䅢桂䡁䅑党穂䡁䅑杌㑂䝁䅷督瑂䙁䄰睓求䡁䅫睘呂䡁䅑兙あ䡁䅍睊桁䍁䅑睑歁䑁䅉兎㙁䍁䅑睑歁䑁䅑兏䅁䅁䙯䅁捂䅁䅁睗乂䕁䅫睘䑂䝁䄸兢睂䝁䅅杢㕂䙁䄸睓求䡁䅫睕あ䝁䅅䅤穂䙁䄸杤硁䍁䄴䅥獂䡁䅍兢摂䕁䅳党㕂䙁䄸睕あ䝁䅅䅤穂䍁䅅䅊䍂䍁䅑免睁䑁䅕䅁奃䅂䅁䅢䅁䍁䅣睗乂䕁䅫睘䑂䝁䄸兢睂䝁䅅杢㕂䙁䄸睓求䡁䅫睕あ䝁䅅䅤穂䙁䄸杤硁䍁䄰睑療䡁䅁入畁䡁䅧䅢穂䝁䄰兘呂䡁䅕䅣睂䝁䅷党瑂䝁䅕杢あ䝁䅅䅢湁䍁䅅䅊䑂䍁䅑䅎䅁䥁䙷䅁㙂䅁䅁睊扂䕁䄰兓時䕁䅍睢瑂䡁䅁兙畂䡁䅫睘䱂䝁䅕入呂䡁䅑兙あ䡁䅍睘㉂䑁䅅䅉瑁䝁䅷兙あ䝁䅕督あ䍁䄴䅥獂䡁䅍兢摂䕁䅳党㕂䙁䄸睕あ䝁䅅䅤穂䍁䅣光歁䕁䅍䅊ㅁ䑁䅑杏歁䕁䅍䅊ㅁ䑁䅕䅁慁兂䅁来䅁䍁䅣睗乂䕁䅫睘䑂䝁䄸兢睂䝁䅅杢㕂䙁䄸睓求䡁䅫睕あ䝁䅅䅤穂䙁䄸杤硁䍁䅁兌獂䝁䅅䅤求䡁䅍䅤畁䡁䅧䅢穂䝁䄰兘䱂䝁䅕入時䙁䅍䅤桂䡁䅑督湁䍁䅅䅊䑂䍁䅑李祁䑁䅯䅊䑂䍁䅑李㑁䅁䅁杄䅕䕁䅧䅁䉂䝁䅍睙療䡁䅕杢あ䡁䅍䅉卂䝁䅕睙求䝁䅫杤桂䝁䅉䅢求䍁䅷䅉ㅁ䍁䅁兗祂䍁䄴䅉䑂䕁䅅睒卂䍁䅁䅋汁䍁䅫䅁䵃杁䅁来䅁䍁䅣睗乂䕁䅫睘䑂䝁䄸兢睂䝁䅅杢㕂䙁䄸睓求䡁䅫睕あ䝁䅅䅤穂䙁䄸杤硁䍁䅁兌獂䝁䅅䅤求䡁䅍䅤畁䡁䅧䅢穂䝁䄰兘䱂䝁䅕入時䙁䅍䅤桂䡁䅑督湁䍁䅅䅊䕂䍁䅑杍ㅁ䑁䅯䅊䕂䍁䅑䅎㕁䅁䅁杆䅕䡁䄴䅁湁䙁䅳兔䩂䙁䄸睑療䝁䄰䅣桂䝁䄴入時䕁䅳党㕂䙁䅍䅤桂䡁䅑督時䡁䅙免杁䍁䄰䅢桂䡁䅑党穂䡁䅑杌㑂䝁䅷督瑂䙁䄰睓求䡁䅫睘呂䡁䅑兙あ䡁䅍睊桁䍁䅑兒歁䑁䅅䅍ぁ䑁䅯䅊䡂䍁䅑免睁䑁䅑䅁摁兂䅁䅊䅁䕁䅫兕時䕁䅑兒䍂䙁䅑睘啂䕁䄸睘䙂䕁䅉兓啂䕁䅑兑䅁䡁䉳䅁㙁䅁䅁睔睂䡁䅑兡療䝁䄴督㙁䍁䅁睕あ䝁䅅䅤灂䡁䅍䅤灂䝁䅍児䵂䕁䄸睖獁䕁䄴兑㥁䕁䄴兑䅁䝁䜰䅁慁䅁䅁兒畂䡁䅑兡あ䡁䅫䅉佂䝁䅅兢求䍁䅁䅁歁䅁䅁来䅁䍁䅣睗乂䕁䅫睘䑂䝁䄸兢睂䝁䅅杢㕂䙁䄸睓求䡁䅫睕あ䝁䅅䅤穂䙁䄸杤硁䍁䅁兌獂䝁䅅䅤求䡁䅍䅤畁䡁䅧䅢穂䝁䄰兘䱂䝁䅕入時䙁䅍䅤桂䡁䅑督湁䍁䅅䅊䙂䍁䅑杍祁䑁䅯䅊䭂䍁䅑杍祁䅁䅁元䅕䝁䅙䅁扂䕁䄰兓時䙁䅉兒䩂䙁䅑睘呂䝁䅅兢求䙁䅍䅤療䡁䅉党啂䝁䅕兢睂䝁䅷兙あ䝁䅕睘㉂䑁䅅杌㑂䝁䅷督摂䕁䅑兙あ䝁䅅光歁䕁䅑䅊硁䑁䅍杏歁䕁䅑䅊祁䑁䅍䅁晄睁䅁来䅁䍁䅣睗乂䕁䅫睘䑂䝁䄸兢睂䝁䅅杢㕂䙁䄸睓求䡁䅫睕あ䝁䅅䅤穂䙁䄸杤硁䍁䅁兌獂䝁䅅䅤求䡁䅍䅤畁䡁䅧䅢穂䝁䄰兘䱂䝁䅕入時䙁䅍䅤桂䡁䅑督湁䍁䅅䅊䙂䍁䅑杍穁䑁䅯䅊䭂䍁䅑杍穁䅁䅁睃䅕䥁䅧䅁湁䙁䅳兔䩂䙁䄸睑療䝁䄰䅣桂䝁䄴入時䕁䅳党㕂䙁䅍䅤桂䡁䅑督時䡁䅙免瑁䍁䅁睔祂䝁䅫睚灂䝁䄴兙獂䍁䄴䅥獂䡁䅍兢摂䕁䅫杢橂䝁䄸兢求䙁䄸睕あ䝁䅅䅤求䝁䄰党畂䡁䅑睊桁䍁䅑兒歁䑁䅕杏歁䙁䅁䅊ㅁ䅁䅁兤䅕䝁䄴䅁湁䙁䅳兔䩂䙁䄸睑療䝁䄰䅣桂䝁䄴入時䕁䅳党㕂䙁䅍䅤桂䡁䅑督時䡁䅙免杁䍁䄰䅢桂䡁䅑党穂䡁䅑杌㑂䝁䅷督瑂䙁䄰睓求䡁䅫睘呂䡁䅑兙あ䡁䅍睊桁䍁䅑兒歁䑁䅕免䅁䉁䙫䅁畂䅁䅁睊扂䕁䄰兓時䕁䅍睢瑂䡁䅁兙畂䡁䅫睘䱂䝁䅕入呂䡁䅑兙あ䡁䅍睘㉂䑁䅅䅉瑁䝁䅷兙あ䝁䅕督あ䍁䄴䅥獂䡁䅍兢摂䕁䅳党㕂䙁䄸睕あ䝁䅅䅤穂䍁䅣光歁䕁䅕䅊ㅁ䑁䅫䅁乁兂䅁䅌䅁䕁䅫兕時䕁䅫杔坂䙁䄸杍婂䙁䅉睘䉂䕁䄴杔時䕁䅣杕偂䙁䅣䅖䥂䅁䅁兕䅉䝁䄴䅁湁䙁䅳兔䩂䙁䄸睑療䝁䄰䅣桂䝁䄴入時䕁䅳党㕂䙁䅍䅤桂䡁䅑督時䡁䅙免杁䍁䄰䅢桂䡁䅑党穂䡁䅑杌㑂䝁䅷督瑂䙁䄰睓求䡁䅫睘呂䡁䅑兙あ䡁䅍睊桁䍁䅑兒歁䑁䅙䅍䅁䅁䘸䅁㑁䅁䅁兓剂䙁䄸睑䉂䙁䅁兓啂䕁䅅䅔時䕁䅷兒䉂䙁䅍兒呂䙁䄸䅖偂䙁䅑兑䵂䙁䄸䅕䑂䙁䅑䅁㙄䅁䅁䅈䅁䙁䅍兤楂䍁䄴䅉䕂䝁䅕杙あ䍁䅁䅋汁䍁䅫䅁灁允䅁材䅁䕁䅣杣療䡁䅍督杁䙁䅁杣療䝁䅙兡あ䍁䅷䅉硁䍁䅁兗祂䍁䄴䅉䡂䡁䅉睢㍂䡁䅑䅡杁䍁䅧兊灁䅁䅁䅈䅉䡁䅯䅁湁䙁䅳兔䩂䙁䄸睑療䝁䄰䅣桂䝁䄴入時䕁䅳党㕂䙁䅍䅤桂䡁䅑督時䡁䅙免杁䍁䄰䅢桂䡁䅑党穂䡁䅑杌㑂䝁䅷督瑂䙁䄰睓求䡁䅫睘呂䡁䅑兙あ䡁䅍睊桁䍁䅑兔歁䑁䅉杍㙁䍁䅑睔歁䑁䅉杍䅁䉁䙕䅁楁䅁䅁兓剂䙁䄸兒䍂䕁䅫䅖䕂䕁䅅睘乂䕁䅅杕䡂䕁䅫杔䅁䅁䍅䅁祁䅁䅁兓剂䙁䄸兒䍂䕁䅫䅖䕂䕁䅅睘ㅁ䙁䅫杕時䕁䅅杔佂䙁䄸睒卂䕁䄸睖啂䕁䅧䅁偃杁䅁杔䅁䙁䅳睓求䡁䅫睕あ䝁䅅䅤穂䙁䄸䅤求䡁䅍䅤浂䝁䅫䅢求䍁䄴䅥獂䡁䅍兢摂䕁䅍兙穂䝁䅧睘䝂䝁䅷睢㍂䍁䅅䅊䑂䍁䅑䅎䅁䱁䄰䅁捂䅁䅁杔偂䕁䅷䅉䑂䝁䅅杣祂䡁䅫杚療䡁䅉睤桂䡁䅉䅚獁䍁䅁睑ㅂ䡁䅉杣求䝁䄴䅤杁䙁䅫党桂䡁䅉䅉牁䍁䅁睍杁䍁䅧杕求䡁䅁睢祂䡁䅑党歂䍁䅫䅁噄杁䅁来䅁䍁䅣睗乂䕁䅫睘䑂䝁䄸兢睂䝁䅅杢㕂䙁䄸睓求䡁䅫睕あ䝁䅅䅤穂䙁䄸杤硁䍁䅁兌獂䝁䅅䅤求䡁䅍䅤畁䡁䅧䅢穂䝁䄰兘䱂䝁䅕入時䙁䅍䅤桂䡁䅑督湁䍁䅅䅊乂䍁䅑杍穁䑁䅯䅊偂䍁䅑杍穁䅁䅁睆䅕䑁䅁䅁䑂䝁䄸兢睂䝁䄸杢求䝁䄴䅤杁䙁䅍党橂䡁䅕杣灂䡁䅑入杁䙁䅑入睂䝁䅕䅁䱃杂䅁䅍䅁䕁䅫兕時䕁䅍兑兂䕁䅕䅗時䑁䅕兗卂䙁䄸兑佂䕁䄴睘䡂䙁䅉睔塂䙁䅑䅓䅁䭁䍣䅁䥂䅁䅁兒桂䡁䅉杢灂䝁䄴睚穂䍁䅁杚祂䝁䄸兢杁䕁䅍睢畂䡁䅑杌杁䕁䄸䅣穂䍁䄴䅉潁䙁䅉党睂䝁䄸杣あ䝁䅕䅚灁䅁䅁兄䅁䝁䅧䅁湁䙁䅳兔䩂䙁䄸睑療䝁䄰䅣桂䝁䄴入時䕁䅳党㕂䙁䅍䅤桂䡁䅑督時䡁䅙免瑁䕁䅍睢睂䡁䅫杌㑂䝁䅷督瑂䙁䄰睓求䡁䅫睘呂䡁䅑兙あ䡁䅍睊桁䍁䅑村歁䑁䅉李䅁䍁䙁䅁䵂䅁䅁杔求䡁䅑䅉䩂䝁䄴睙畁䍁䅁兑㉂䝁䅅兡獂䍁䄴䅉浂䝁䄸杣杁䕁䅍睢瑂䝁䄰睢畂䍁䅁兔桂䡁䅉睚灂䝁䄴䅉潁䍁䅕克䅁䅁䌴䅁浂䅁䅁睗乂䕁䅫睘䑂䝁䄸兢睂䝁䅅杢㕂䙁䄸睓求䡁䅫睕あ䝁䅅䅤穂䙁䄸杤硁䍁䄴䅥獂䡁䅍兢摂䕁䅳党㕂䙁䄸睕あ䝁䅅䅤穂䍁䅅䅊啂䍁䅑兎㑁䑁䅯䅊啂䍁䅑李祁䅁䅁睮䅕䝁䄴䅁湁䙁䅳兔䩂䙁䄸睑療䝁䄰䅣桂䝁䄴入時䕁䅳党㕂䙁䅍䅤桂䡁䅑督時䡁䅙免杁䍁䄰䅢桂䡁䅑党穂䡁䅑杌㑂䝁䅷督瑂䙁䄰睓求䡁䅫睘呂䡁䅑兙あ䡁䅍睊桁䍁䅑兖歁䑁䅉杍䅁䉁䙁䅁㉁䅁䅁兓剂䙁䄸睔兂䙁䅑兓偂䕁䄴睕時䙁䅍䅖卂䕁䅫睓䙂䙁䄸䅕卂䕁䅫睑䙂䙁䄸睔呂䅁䅁䅐䅍䝁䄴䅁湁䙁䅳兔䩂䙁䄸睑療䝁䄰䅣桂䝁䄴入時䕁䅳党㕂䙁䅍䅤桂䡁䅑督時䡁䅙免杁䍁䄰䅢桂䡁䅑党穂䡁䅑杌㑂䝁䅷督瑂䙁䄰睓求䡁䅫睘呂䡁䅑兙あ䡁䅍睊桁䍁䅑兖歁䑁䅉兎䅁䉁䙉䅁卂䅁䅁睑桂䡁䅍䅡杁䍁䅙䅉呂䝁䅧睢祂䡁䅑䅉啂䝁䅕杣瑂䍁䅁兓畂䡁䅙党穂䡁䅑兢求䝁䄴䅤穂䍁䅁䅋卂䝁䅕䅣療䡁䅉䅤求䝁䅑克䅁䉁䅕䅁獂䅁䅁睊扂䙁䅍䅕䡂䙁䄸睑療䝁䄰䅣桂䝁䄴入時䕁䅳党㕂䙁䅍䅤桂䡁䅑督時䡁䅙杍杁䑁䅅杌㑂䝁䅷督瑂䙁䄰睑桂䡁䅍䅡時䕁䅙䅢療䡁䅣睊桁䍁䅑兒歁䑁䅣杏歁䙁䅁䅊㍁䅁䅁朴䅙䝁䄴䅁湁䙁䅳兔䩂䙁䄸睑療䝁䄰䅣桂䝁䄴入時䕁䅳党㕂䙁䅍䅤桂䡁䅑督時䡁䅙免杁䍁䄰䅢桂䡁䅑党穂䡁䅑杌㑂䝁䅷督瑂䙁䄰睓求䡁䅫睘呂䡁䅑兙あ䡁䅍睊桁䍁䅑杖歁䑁䅉杍䅁䉁䙅䅁杂䅁䅁睗乂䕁䅫睘䱂䝁䅕入呂䡁䅑兙あ䡁䅍睘㉂䑁䅅杌㑂䝁䅷督瑂䙁䄰睑桂䡁䅁兡あ䝁䅅䅢灂䡁䅯兙あ䝁䅫睢畂䍁䅅䅊䙂䍁䅑兎祁䑁䅯䅊䭂䍁䅑兎祁䅁䅁䅱䅍䡁䅉䅁扂䙁䅍䅕䡂䙁䄸睑療䝁䄰䅣桂䝁䄴入時䕁䅳党㕂䙁䅍䅤桂䡁䅑督時䡁䅙免畁䡁䅧䅢穂䝁䄰兘䑂䝁䅅䅣灂䡁䅑兙獂䝁䅫来桂䡁䅑兡療䝁䄴光歁䕁䅕䅊ぁ䑁䅣杏歁䕁䅯䅊ぁ䑁䅣䅁㕄兂䅁䅍䅁䕁䅫兕時䙁䅑睔啂䕁䅅䅔時䕁䄸䅕啂䕁䅫睔佂䙁䅍睘䍂䕁䅕睒時䕁䄸睕䅁䑁䐴䅁畂䅁䅁睊扂䕁䄰兓時䕁䅍睢瑂䡁䅁兙畂䡁䅫睘䱂䝁䅕入呂䡁䅑兙あ䡁䅍睘㉂䑁䅅䅉瑁䝁䅷兙あ䝁䅕督あ䍁䄴䅥獂䡁䅍兢摂䕁䅳党㕂䙁䄸睕あ䝁䅅䅤穂䍁䅣光歁䙁䅙䅊祁䑁䅍䅁呁兂䅁䅕䅁䙁䅳睓求䡁䅫睕あ䝁䅅䅤穂䙁䄸䅤求䡁䅍䅤浂䝁䅫䅢求䍁䄴䅥獂䡁䅍兢摂䕁䅳党㕂䙁䄸睕あ䝁䅅䅤穂䍁䅅䅊䍂䍁䅑兎祁䅁䅁兮䅁䑁䅑䅁䩂䙁䅅睘佂䕁䅫睘佂䕁䄸杕乂䙁䄸睍婂䙁䅉睘䉂䕁䄴杔時䕁䅣杕偂䙁䅣䅖䥂䅁䅁睙䅉䑁䅯䅁佂䝁䅕䅤杁䕁䅫杢橂䝁䄸兢求䍁䅷䅉硁䍁䅁兗祂䍁䄴䅉䡂䡁䅉睢㍂䡁䅑䅡杁䍁䅧兊灁䅁䅁杈䅉䡁䅑䅁湁䙁䅳睕兂䕁䅣睘䑂䝁䄸兢睂䝁䅅杢㕂䙁䄸睓求䡁䅫睕あ䝁䅅䅤穂䙁䄸杤祁䍁䅁免畁䡁䅧䅢穂䝁䄰兘䱂䝁䅕入時䙁䅍䅤桂䡁䅑督湁䍁䅅䅊䝂䍁䅑免睁䑁䅣杏歁䕁䅧䅊硁䑁䅁睎䅁乁䝙䅁㙂䅁䅁睊扂䕁䄰兓時䕁䅍睢瑂䡁䅁兙畂䡁䅫睘䱂䝁䅕入呂䡁䅑兙あ䡁䅍睘㉂䑁䅅兌杁䕁䄸杣灂䝁䅣兡畂䝁䅅䅢畁䡁䅧䅢穂䝁䄰兘䑂䝁䅅䅣灂䡁䅑兙獂䝁䅫来桂䡁䅑兡療䝁䄴睊桁䍁䅑睑歁䑁䅑䅁㑁兂䅁杏䅁䕁䅫兕時䕁䅕兑卂䕁䄴兓佂䕁䅣睘䑂䕁䄸睘硁䙁䅫杕時䕁䅅杔佂䙁䄸睒卂䕁䄸睖啂䕁䅧䅁桁杁䅁杚䅁䕁䅅䅚歂䝁䅫䅤灂䝁䄸杢穂䍁䅁杚療䡁䅉䅉啂䝁䅅䅥杁䙁䅁睢穂䝁䅫䅤灂䝁䄸杢穂䍁䅁兌杁䙁䅁杣灂䝁䄸杣杁䙁䅫杣穂䍁䅁䅋卂䝁䅕䅣療䡁䅉䅤求䝁䅑克䅁䅁䑳䅁元䅁䅁睊扂䙁䅍䅕䡂䙁䄸睑療䝁䄰䅣桂䝁䄴入時䕁䅳党㕂䙁䅍䅤桂䡁䅑督時䡁䅙免杁䍁䅧杍灁䍁䄴䅥獂䡁䅍兢摂䕁䅍兙睂䝁䅫䅤桂䝁䅷睘呂䡁䅑杣ㅂ䝁䅍䅤ㅂ䡁䅉党時䙁䅍兤瑂䝁䄰兙祂䡁䅫睊桁䍁䅑兒歁䑁䅣杏歁䕁䄸䅊㍁䅁䅁睐䅙䡁䅷䅁湁䙁䅳兔䩂䙁䄸睑療䝁䄰䅣桂䝁䄴入時䕁䅳党㕂䙁䅍䅤桂䡁䅑督時䡁䅙免瑁䍁䅁睔祂䝁䅫睚灂䝁䄴兙獂䍁䄴䅥獂䡁䅍兢摂䕁䅍兙睂䝁䅫䅤桂䝁䅷兡㙂䝁䅅䅤灂䝁䄸杢湁䍁䅅䅊䑂䍁䅑䅎㍁䅁䅁䅑䅕䡁䅉䅁湁䙁䅳兔䩂䙁䄸睑療䝁䄰䅣桂䝁䄴入時䕁䅳党㕂䙁䅍䅤桂䡁䅑督時䡁䅙免瑁䍁䅁睔祂䝁䅫睚灂䝁䄴兙獂䍁䄴䅥獂䡁䅍兢摂䕁䅳党㕂䙁䄸睕あ䝁䅅䅤穂䍁䅣光歁䕁䅉䅊ㅁ䑁䅉䅁煂兂䅁䅌䅁䕁䅫兕時䕁䅍杒偂䙁䄸免婂䙁䅉睘䉂䕁䄴杔時䕁䅣杕偂䙁䅣䅖䥂䅁䅁免䅉䡁䅷䅁湁䙁䅳兔䩂䙁䄸睑療䝁䄰䅣桂䝁䄴入時䕁䅳党㕂䙁䅍䅤桂䡁䅑督時䡁䅙免瑁䍁䅁睔祂䝁䅫睚灂䝁䄴兙獂䍁䄴䅥獂䡁䅍兢摂䕁䅍兙睂䝁䅫䅤桂䝁䅷兡㙂䝁䅅䅤灂䝁䄸杢湁䍁䅅䅊䑂䍁䅑兎睁䅁䅁材䅕䝁䅑䅁䝂䝁䅅兡祂䍁䅁杖桂䝁䅷兤求䍁䅁睑潂䝁䅅杢湂䝁䅕䅉䩂䝁䄴睙獂䡁䅕䅚求䝁䅑䅉灂䝁䄴䅉䙂䝁䅅杣畂䝁䅫杢湂䡁䅍䅉潁䙁䅉党睂䝁䄸杣あ䝁䅕䅚灁䅁䅁克䅍䥁䅙䅁湁䙁䅳兔䩂䙁䄸睑療䝁䄰䅣桂䝁䄴入時䕁䅳党㕂䙁䅍䅤桂䡁䅑督時䡁䅙免瑁䕁䅍睢睂䡁䅫杌㑂䝁䅷督瑂䙁䄰睑桂䡁䅁兡あ䝁䅅䅢時䙁䅍䅤祂䡁䅕睙あ䡁䅕杣求䙁䄸睕ㅂ䝁䄰兢桂䡁䅉入湁䍁䅅䅊䑂䍁䅑兎䅁䥁䙑䅁浂䅁䅁睗乂䕁䅫睘䑂䝁䄸兢睂䝁䅅杢㕂䙁䄸睓求䡁䅫睕あ䝁䅅䅤穂䙁䄸杤硁䍁䄴䅥獂䡁䅍兢摂䕁䅳党㕂䙁䄸睕あ䝁䅅䅤穂䍁䅅䅊䑂䍁䅑李硁䑁䅯䅊䑂䍁䅑李㍁䅁䅁杁䅑䍁䄴䅁䩂䙁䅅睘佂䙁䅁䅕䙂䙁䄸睍婂䙁䅉睘䉂䕁䄴杔時䕁䅣杕偂䙁䅣䅖䥂䅁䅁党䅉䥁䅧䅁湁䙁䅳兔䩂䙁䄸睑療䝁䄰䅣桂䝁䄴入時䕁䅳党㕂䙁䅍䅤桂䡁䅑督時䡁䅙免瑁䍁䅁睔祂䝁䅫睚灂䝁䄴兙獂䍁䄴䅥獂䡁䅍兢摂䕁䅍兙睂䝁䅫䅤桂䝁䅷兡㙂䝁䅅䅤灂䝁䄸杢湁䍁䅅䅊䑂䍁䅑兎穁䑁䅯䅊䑂䍁䅑兎ぁ䅁䅁村䅕䥁䅙䅁湁䙁䅳兔䩂䙁䄸睑療䝁䄰䅣桂䝁䄴入時䕁䅳党㕂䙁䅍䅤桂䡁䅑督時䡁䅙免瑁䍁䅁睔祂䝁䅫睚灂䝁䄴兙獂䍁䄴䅥獂䡁䅍兢摂䕁䅍兙睂䝁䅫䅤桂䝁䅷兡㙂䝁䅅䅤灂䝁䄸杢湁䍁䅅䅊䑂䍁䅑兏㙁䍁䅑睑歁䑁䅉兎䅁䑁䙯䅁楁䅁䅁睑ㅂ䡁䅉杣求䝁䄴䅤癁䙁䅉党穂䡁䅑兙あ䝁䅕䅚䅁䅁䅉䅁䥃䅁䅁睊扂䕁䄰兓時䕁䅍睢瑂䡁䅁兙畂䡁䅫睘䱂䝁䅕入呂䡁䅑兙あ䡁䅍睘㉂䑁䅅兌杁䕁䄸杣灂䝁䅣兡畂䝁䅅䅢畁䡁䅧䅢穂䝁䄰兘䑂䝁䅅䅣灂䡁䅑兙獂䝁䅫来桂䡁䅑兡療䝁䄴睊桁䍁䅑兒歁䑁䅑睎㙁䍁䅑䅕歁䑁䅑睎䅁䑁䘰䅁䥃䅁䅁睊扂䕁䄰兓時䕁䅍睢瑂䡁䅁兙畂䡁䅫睘䱂䝁䅕入呂䡁䅑兙あ䡁䅍睘㉂䑁䅅兌杁䕁䄸杣灂䝁䅣兡畂䝁䅅䅢畁䡁䅧䅢穂䝁䄰兘䑂䝁䅅䅣灂䡁䅑兙獂䝁䅫来桂䡁䅑兡療䝁䄴睊桁䍁䅑兒歁䑁䅑䅏㙁䍁䅑䅕歁䑁䅑䅏䅁䑁䘸䅁㉁䅁䅁䅒桂䡁䅫䅉䑂䝁䅷睢穂䝁䅕䅉兂䡁䅉兡橂䝁䅕䅉潁䙁䅉党睂䝁䄸杣あ䝁䅕䅚灁䅁䅁睅䅁䙁䅙䅁䑂䝁䄸杢あ䡁䅉兙橂䡁䅑兤桂䝁䅷䅉偂䝁䅉䅢灂䝁䅣兙あ䝁䅫睢畂䡁䅍䅉䕂䡁䅕党杁䍁䅳䅉穁䍁䅁䅋卂䝁䅕䅣療䡁䅉䅤求䝁䅑克䅁乁䉧䅁䕃䅁䅁睊扂䕁䄰兓時䕁䅍睢瑂䡁䅁兙畂䡁䅫睘䱂䝁䅕入呂䡁䅑兙あ䡁䅍睘㉂䑁䅅兌杁䕁䄸杣灂䝁䅣兡畂䝁䅅䅢畁䡁䅧䅢穂䝁䄰兘䑂䝁䅅䅣灂䡁䅑兙獂䝁䅫来桂䡁䅑兡療䝁䄴睊桁䍁䅑兒歁䑁䅑杏歁䕁䅯䅊ぁ䅁䅁兏䅕䡁䄴䅁湁䙁䅳睕兂䕁䅣睘䑂䝁䄸兢睂䝁䅅杢㕂䙁䄸睓求䡁䅫睕あ䝁䅅䅤穂䙁䄸杤硁䍁䅁䅋祁䍁䅫杌㑂䝁䅷督瑂䙁䄰兓畂䝁䅍睢瑂䝁䅕睘呂䡁䅑兙あ䝁䅕兢求䝁䄴䅤湁䍁䅅䅊䙂䍁䅑睎㙁䍁䅑䅕歁䑁䅣䅁湁杂䅁杩䅁䍁䅣睗䑂䝁䄸䅣㕂䍁䅁睢浂䍁䅁睕兂䕁䅣睘䑂䝁䄸兢睂䝁䅅杢㕂䙁䄸睓求䡁䅫睕あ䝁䅅䅤穂䙁䄸杤祁䙁䄸杢求䡁䅣杌㑂䝁䅷督瑂䙁䄰睑桂䡁䅁兡あ䝁䅅䅢灂䡁䅯兙あ䝁䅫睢畂䍁䅣光歁䕁䅕䅊ㅁ䑁䅯䅊䭂䍁䅑兎䅁䕁䠰䅁楂䅁䅁睗䱂䝁䅕入呂䡁䅑兙あ䡁䅍睘あ䝁䅕督あ䝁䅙兡獂䝁䅕杌㑂䝁䅷督瑂䙁䄰睑桂䡁䅁兡あ䝁䅅䅢灂䡁䅯兙あ䝁䅫睢畂䍁䅅䅊䝂䍁䅑兎㙁䍁䅑兕歁䑁䅕䅁䥄䅁䅁䅐䅁䕁䅅杤求䡁䅉兙湂䝁䅕䅉䩂䝁䄴䅤求䡁䅉党穂䡁䅑䅉卂䝁䅅䅤求䍁䅁睋杁䑁䅍䅉潁䍁䅕克䅁佁䉷䅁啂䅁䅁睑療䝁䄴䅤祂䝁䅅睙あ䡁䅕兙獂䍁䅁睔楂䝁䅷兡湂䝁䅅䅤灂䝁䄸杢穂䍁䅁䅒ㅂ䝁䅕䅉牁䑁䅅䅉潁䙁䅉党睂䝁䄸杣あ䝁䅕䅚灁䅁䅁䄱䅅䥁䅧䅁湁䙁䅳睕兂䕁䅣睘䑂䝁䄸兢睂䝁䅅杢㕂䙁䄸睓求䡁䅫睕あ䝁䅅䅤穂䙁䄸杤祁䍁䅁免畁䡁䅧䅢穂䝁䄰兘䑂䝁䅅䅣灂䡁䅑兙獂䙁䄸睕あ䡁䅉兤橂䡁䅑兤祂䝁䅕睘杁䕁䅑党あ䝁䅅兡獂䡁䅍䅉湁䍁䅅䅊䭂䍁䅑䅎ぁ䅁䅁䅈䅣䥁䅧䅁湁䙁䅳兔䩂䙁䄸睑療䝁䄰䅣桂䝁䄴入時䕁䅳党㕂䙁䅍䅤桂䡁䅑督時䡁䅙免瑁䍁䅁睔祂䝁䅫睚灂䝁䄴兙獂䍁䄴䅥獂䡁䅍兢摂䕁䅍兙睂䝁䅫䅤桂䝁䅷兡㙂䝁䅅䅤灂䝁䄸杢湁䍁䅅䅊䙂䍁䅑兎硁䑁䅯䅊䭂䍁䅑兎硁䅁䅁兑䅕䝁䅯䅁湁䙁䅳兔䩂䙁䄸睑療䝁䄰䅣桂䝁䄴入時䕁䅳党㕂䙁䅍䅤桂䡁䅑督時䡁䅙免瑁䕁䅍睢睂䡁䅫杌㑂䝁䅷督瑂䙁䄰杕桂䡁䅑兡療䡁䅍睊桁䍁䅑䅒歁䑁䅑杏歁䕁䅫䅊ぁ䅁䅁兩䅕䥁䅑䅁湁䙁䅳睑療䡁䅁入杁䝁䄸杚杁䙁䅍䅕䡂䙁䄸睑療䝁䄰䅣桂䝁䄴入時䕁䅳党㕂䙁䅍䅤桂䡁䅑督時䡁䅙杍時䝁䄴党㍂䍁䄴䅥獂䡁䅍兢摂䕁䅳党㕂䙁䄸睕あ䝁䅅䅤穂䍁䅣光歁䙁䅕䅊ㅁ䑁䅧杏歁䙁䅕䅊㉁䑁䅅䅁呃睂䅁䅩䅁䍁䅣睗呂䙁䅁睒時䕁䅍睢瑂䡁䅁兙畂䡁䅫睘䱂䝁䅕入呂䡁䅑兙あ䡁䅍睘㉂䑁䅉䅉硁䍁䄴䅥獂䡁䅍兢摂䕁䅍兙睂䝁䅫䅤桂䝁䅷睘呂䡁䅑杣ㅂ䝁䅍䅤ㅂ䡁䅉党時䍁䅁䅒求䡁䅑兙灂䝁䅷督杁䍁䅣光歁䕁䅉䅊ぁ䑁䅑䅁十睂䅁䅨䅁䍁䅣睗乂䕁䅫睘䑂䝁䄸兢睂䝁䅅杢㕂䙁䄸睓求䡁䅫睕あ䝁䅅䅤穂䙁䄸杤硁䍁䄰䅉偂䡁䅉兡湂䝁䅫杢桂䝁䅷杌㑂䝁䅷督瑂䙁䄰睑桂䡁䅁兡あ䝁䅅䅢灂䡁䅯兙あ䝁䅫睢畂䍁䅣光歁䕁䅕䅊ㅁ䑁䅯䅊䭂䍁䅑兎䅁䑁䙳䅁捂䅁䅁睗䱂䝁䅕入呂䡁䅑兙あ䡁䅍睘あ䝁䅕督あ䝁䅙兡獂䝁䅕杌㑂䝁䅷督瑂䙁䄰睓求䡁䅫睘呂䡁䅑兙あ䡁䅍光歁䕁䅕䅊㕁䑁䅧杏歁䕁䅣䅊㕁䑁䅧䅁呃䅁䅁䅮䅁䍁䅣睗䑂䝁䄸䅣㕂䍁䅁睢浂䍁䅁睕兂䕁䅣睘䑂䝁䄸兢睂䝁䅅杢㕂䙁䄸睓求䡁䅫睕あ䝁䅅䅤穂䙁䄸杤祁䙁䄸杢求䡁䅣杌㑂䝁䅷督瑂䙁䄰睑桂䡁䅁兡あ䝁䅅䅢時䙁䅍䅤祂䡁䅕睙あ䡁䅕杣求䙁䄸䅉䕂䝁䅕䅤桂䝁䅫䅢穂䍁䅁睊桁䍁䅑兒歁䑁䅣李䅁䥁䡣䅁䍃䅁䅁睊扂䕁䄰兓時䕁䅍睢瑂䡁䅁兙畂䡁䅫睘䱂䝁䅕入呂䡁䅑兙あ䡁䅍睘㉂䑁䅅兌杁䕁䄸杣灂䝁䅣兡畂䝁䅅䅢畁䡁䅧䅢穂䝁䄰兘䱂䝁䅕入時䙁䅍䅤桂䡁䅑督湁䍁䅅䅊䙂䍁䅑免睁䑁䅕杏歁䕁䅣䅊硁䑁䅁兎䅁䝁䙣䅁⭂䅁䅁睊扂䕁䄰兓時䕁䅍睢瑂䡁䅁兙畂䡁䅫睘䱂䝁䅕入呂䡁䅑兙あ䡁䅍睘㉂䑁䅅兌杁䕁䄸杣灂䝁䅣兡畂䝁䅅䅢畁䡁䅧䅢穂䝁䄰兘䩂䝁䄴睙療䝁䄰党時䙁䅍䅤桂䡁䅑党瑂䝁䅕杢あ䍁䅣光歁䕁䅍䅊ぁ䅁䅁杣䅕䡁䅧䅁湁䙁䅳睕兂䕁䅣睘䑂䝁䄸兢睂䝁䅅杢㕂䙁䄸睓求䡁䅫睕あ䝁䅅䅤穂䙁䄸杤硁䍁䅁䅋祁䍁䅫杌㑂䝁䅷督瑂䙁䄰睓求䡁䅫睘呂䡁䅑兙あ䡁䅍睊桁䍁䅑兒歁䑁䅅䅍㉁䑁䅯䅊䡂䍁䅑免睁䑁䅙䅁婁杂䅁材䅁䙁䅍兤楂䍁䄰䅔求䝁䅅督求䍁䅁兓畂䝁䅍睢瑂䝁䅕䅉牁䑁䅕䅉潁䙁䅉党睂䝁䄸杣あ䝁䅕䅚灁䅁䅁杺䅅䑁䅑䅁䩂䙁䅅睘坂䕁䅅杕䩂䕁䅅村䵂䕁䅕睘卂䕁䅅䅖䙂䙁䄸䅒䙂䕁䅉䅖時䙁䅁睑啂䅁䅁条䅅䡁䅑䅁湁䙁䅳兔䩂䙁䄸睑療䝁䄰䅣桂䝁䄴入時䕁䅳党㕂䙁䅍䅤桂䡁䅑督時䡁䅙免瑁䕁䅍睢睂䡁䅫杌㑂䝁䅷督瑂䙁䄰睓求䡁䅫睘呂䡁䅑兙あ䡁䅍睊桁䍁䅑兒歁䑁䅉兎㙁䍁䅑䅔歁䑁䅉兎䅁䙁䙉䅁祂䅁䅁睊扂䕁䄰兓時䕁䅍睢瑂䡁䅁兙畂䡁䅫睘䱂䝁䅕入呂䡁䅑兙あ䡁䅍睘㉂䑁䅅兌䑂䝁䄸䅣㕂䍁䄴䅥獂䡁䅍兢摂䕁䅍兙睂䝁䅫䅤桂䝁䅷兡㙂䝁䅅䅤灂䝁䄸杢湁䍁䅅䅊䑂䍁䅑兎㑁䅁䅁䅒䅕䍁䅁䅁䩂䙁䅅睘呂䕁䅕睑噂䙁䅉兒䕂䙁䄸䅒䙂䕁䅉䅖䅁䑁䉧䅁䵃䅁䅁睊扂䕁䄰兓時䕁䅍睢瑂䡁䅁兙畂䡁䅫睘䱂䝁䅕入呂䡁䅑兙あ䡁䅍睘㉂䑁䅅兌杁䕁䄸杣灂䝁䅣兡畂䝁䅅䅢畁䡁䅧䅢穂䝁䄰兘䩂䝁䄴睙療䝁䄰党時䙁䅍䅤桂䡁䅑党瑂䝁䅕杢あ䍁䅣光歁䕁䅍䅊㕁䑁䅯䅊䑂䍁䅑免㍁䑁䅍䅁あ兂䅁䅓䅁䙁䅑兙畂䝁䅣兡楂䝁䅷党杁䕁䅉睢療䝁䅳䅉坂䝁䅅䅢ㅂ䝁䅕䅌杁䑁䅍䅉婂䡁䅉杌杁䕁䅍兑䡂䙁䅉䅉潁䍁䅕克䅁䡁䍷䅁坂䅁䅁睗䱂䝁䅕入呂䡁䅑兙あ䡁䅍睘あ䝁䅕督あ䝁䅙兡獂䝁䅕杌㑂䝁䅷督㑂䙁䄰睕潂䝁䅕党あ䑁䅅光歁䕁䅍䅊祁䑁䅕杏歁䕁䅍䅊ぁ䑁䅕䅁偂䅁䅁䅩䅁䍁䅣睗乂䕁䅫睘䑂䝁䄸兢睂䝁䅅杢㕂䙁䄸睓求䡁䅫睕あ䝁䅅䅤穂䙁䄸杤硁䍁䄰䅉偂䡁䅉兡湂䝁䅫杢桂䝁䅷杌㑂䝁䅷督瑂䙁䄰兓畂䝁䅍睢瑂䝁䅕睘呂䡁䅑兙あ䝁䅕兢求䝁䄴䅤湁䍁䅅䅊䙂䍁䅑䅎㙁䍁䅑䅕歁䑁䅑䅁穂兂䅁条䅁䙁䅳睓求䡁䅫睕あ䝁䅅䅤穂䙁䄸䅤求䡁䅍䅤浂䝁䅫䅢求䍁䄴䅥獂䡁䅍兢摂䕁䅫杢橂䝁䄸兢求䙁䄸睕あ䝁䅅䅤求䝁䄰党畂䡁䅑光歁䕁䅑䅊㕁䑁䅯䅊䕂䍁䅑免ㅁ䑁䅣䅁㡃䅁䅁䅕䅁䙁䅳兔䩂䙁䄸睓求䡁䅫睕あ䝁䅅䅤穂䙁䄸杤硁䍁䄴䅥獂䡁䅍兢摂䙁䅉兙あ䝁䅫睢穂䍁䅅䅊䑂䍁䅑兏㙁䍁䅑睑歁䑁䅅兎睁䅁䅁典䅍䍁䅙䅁橁䕁䄴睔杁䕁䅑兑啂䕁䅅䅉䉂䙁䅙兑䩂䕁䅷兑䍂䕁䅷兒䅁䵁䡷䅁䭃䅁䅁睊扂䕁䅍睢睂䡁䅫䅉療䝁䅙䅉呂䙁䅁睒時䕁䅍睢瑂䡁䅁兙畂䡁䅫睘䱂䝁䅕入呂䡁䅑兙あ䡁䅍睘㉂䑁䅅睘䝂䝁䅫杢桂䝁䅷杌㑂䝁䅷督瑂䙁䄰䅕求䝁䄴督灂䝁䄸杢瑁䕁䄸䅕䙂䕁䅉睊桁䍁䅑䅒歁䑁䅧杏歁䕁䅫䅊㑁䅁䅁東䅧䡁䄴䅁湁䙁䅳兔䩂䙁䄸睑療䝁䄰䅣桂䝁䄴入時䕁䅳党㕂䙁䅍䅤桂䡁䅑督時䡁䅙免瑁䍁䅁睔祂䝁䅫睚灂䝁䄴兙獂䍁䄴䅥獂䡁䅍兢摂䕁䅳党㕂䙁䄸睕あ䝁䅅䅤穂䍁䅣光歁䕁䅑䅊祁䑁䅕杏歁䕁䅑䅊ぁ䑁䅫䅁敂兂䅁䅆䅁䙁䅍䅕時䙁䅁兒時䕁䅙睖䕂䅁䅁䅡䅙䡁䅑䅁湁䙁䅳兔䩂䙁䄸睑療䝁䄰䅣桂䝁䄴入時䕁䅳党㕂䙁䅍䅤桂䡁䅑督時䡁䅙免瑁䍁䅁睔祂䝁䅫睚灂䝁䄴兙獂䍁䄴䅥獂䡁䅍兢摂䕁䅳党㕂䙁䄸睕あ䝁䅅䅤穂䍁䅣光歁䕁䅉䅊硁䑁䅁睍䅁䝁䙑䅁䥁䅁䅁䅔啂䕁䄰䅁䉁䅁䅁䅊䅁䕁䅫兕時䙁䅣䅖䕂䙁䄸兑坂䕁䅣睘䩂䙁䅉睘䑂䙁䅫睍䅁佁䉕䅁祂䅁䅁睊扂䕁䄰兓時䕁䅍睢瑂䡁䅁兙畂䡁䅫睘䱂䝁䅕入呂䡁䅑兙あ䡁䅍睘㉂䑁䅅兌杁䕁䄸杣灂䝁䅣兡畂䝁䅅䅢畁䡁䅧䅢穂䝁䄰兘䱂䝁䅕入時䙁䅍䅤桂䡁䅑督湁䍁䅅䅊䍂䍁䅑兎㕁䅁䅁杢䅕䙁䅉䅁扂䕁䄰兓時䕁䅳党㕂䙁䅍䅤桂䡁䅑督時䡁䅙免畁䡁䅧䅢穂䝁䄰兘䑂䝁䅅䅣灂䡁䅑兙獂䝁䅫来桂䡁䅑兡療䝁䄴光歁䕁䅍䅊ぁ䅁䅁兮䅍䥁䅉䅁湁䙁䅳兔䩂䙁䄸睑療䝁䄰䅣桂䝁䄴入時䕁䅳党㕂䙁䅍䅤桂䡁䅑督時䡁䅙免瑁䍁䅁睔祂䝁䅫睚灂䝁䄴兙獂䍁䄴䅥獂䡁䅍兢摂䕁䅳党㕂䙁䄸睕あ䝁䅅䅤穂䍁䅣光歁䕁䅍䅊硁䑁䅁睎㙁䍁䅑睑歁䑁䅅免硁䅁䅁杚䅕䙁䅷䅁扂䕁䅳党㕂䙁䅍䅤桂䡁䅑督時䡁䅑党穂䡁䅑杚灂䝁䅷党畁䡁䅧䅢穂䝁䄰兘䱂䝁䅕入時䙁䅍䅤桂䡁䅑督桁䍁䅑兒歁䑁䅫兏㙁䍁䅑睒歁䑁䅫兏䅁䭁䅍䅁⭂䅁䅁睊扂䕁䄰兓時䕁䅍睢瑂䡁䅁兙畂䡁䅫睘䱂䝁䅕入呂䡁䅑兙あ䡁䅍睘㉂䑁䅅兌杁䕁䄸杣灂䝁䅣兡畂䝁䅅䅢畁䡁䅧䅢穂䝁䄰兘䱂䝁䅕入時䙁䅍䅤桂䡁䅑督湁䍁䅅䅊䑂䍁䅑杍ㅁ䑁䅯䅊䑂䍁䅑䅎㕁䅁䅁杙䅕䥁䅧䅁扂䙁䅍䅕䡂䙁䄸睑療䝁䄰䅣桂䝁䄴入時䕁䅳党㕂䙁䅍䅤桂䡁䅑督時䡁䅙杍畁䡁䅧䅢穂䝁䄰兘䑂䝁䅅䅣灂䡁䅑兙獂䙁䄸睕あ䡁䅉兤橂䡁䅑兤祂䝁䅕睘呂䡁䅕兢瑂䝁䅅杣㕂䍁䅅䅊䝂䍁䅑免硁䑁䅯䅊卂䍁䅑免硁䅁䅁元䅧䉁䄴䅁呂䙁䅁睘兂䙁䅉兓䑂䕁䅕睘䑂䕁䅷睔呂䕁䅕䅁十䅁䅁杨䅁䍁䅣睗䑂䝁䄸䅣㕂䍁䅁睢浂䍁䅁睕兂䕁䅣睘䑂䝁䄸兢睂䝁䅅杢㕂䙁䄸睓求䡁䅫睕あ䝁䅅䅤穂䙁䄸杤祁䙁䄸杢求䡁䅣杌㑂䝁䅷督瑂䙁䄰䅕求䝁䄴督灂䝁䄸杢瑁䕁䄸䅕䙂䕁䅉睊桁䍁䅑䅒歁䑁䅣杏歁䕁䅫䅊㍁䅁䅁兡䅣䑁䅉䅁䩂䙁䅅睘佂䕁䅕䅖時䕁䅑兒䍂䙁䅑睘䙂䕁䅉兓啂䕁䅑兑時䕁䅍兑兂䕁䅕䅗䅁䥁䉣䅁䍂䅁䅁兑瑂䝁䅅来療䝁䄴杌橂䝁䄸兢獁䍁䅁兓畂䝁䅍杌杁䍁䅧杔䉂䙁䅍䅒䉂䙁䅅睒呂䑁䅯兑乂䙁䅯杔灁䅁䅁儳䅣䍁䅁䅁䩂䙁䅅睘䕂䕁䅕村啂䙁䄸兑䕂䕁䅯睘兂䕁䅍䅖䅁䅁䉉䅁⭂䅁䅁睊扂䕁䄰兓時䕁䅍睢瑂䡁䅁兙畂䡁䅫睘䱂䝁䅕入呂䡁䅑兙あ䡁䅍睘㉂䑁䅅兌杁䕁䄸杣灂䝁䅣兡畂䝁䅅䅢畁䡁䅧䅢穂䝁䄰兘䱂䝁䅕入時䙁䅍䅤桂䡁䅑督湁䍁䅅䅊䑂䍁䅑兎ぁ䑁䅯䅊䑂䍁䅑兎ㅁ䅁䅁䅢䅕䡁䅑䅁湁䙁䅳兔䩂䙁䄸睑療䝁䄰䅣桂䝁䄴入時䕁䅳党㕂䙁䅍䅤桂䡁䅑督時䡁䅙免瑁䕁䅍睢睂䡁䅫杌㑂䝁䅷督瑂䙁䄰兓畂䝁䅍睢瑂䝁䅕睘呂䡁䅑兙あ䝁䅕兢求䝁䄴䅤湁䍁䅅䅊䑂䍁䅑䅎䅁䕁䘴䅁⭂䅁䅁睊扂䕁䄰兓時䕁䅍睢瑂䡁䅁兙畂䡁䅫睘䱂䝁䅕入呂䡁䅑兙あ䡁䅍睘㉂䑁䅅兌杁䕁䄸杣灂䝁䅣兡畂䝁䅅䅢畁䡁䅧䅢穂䝁䄰兘䱂䝁䅕入時䙁䅍䅤桂䡁䅑督湁䍁䅅䅊䑂䍁䅑李祁䑁䅯䅊䑂䍁䅑李㑁䅁䅁䅣䅕䡁䅧䅁扂䕁䅳党㕂䙁䅍䅤桂䡁䅑督時䡁䅑党穂䡁䅑杚灂䝁䅷党畁䡁䅧䅢穂䝁䄰兘䑂䝁䅅䅣灂䡁䅑兙獂䙁䄸睕あ䡁䅉兤橂䡁䅑兤祂䝁䅕睘呂䡁䅕兢瑂䝁䅅杣㕂䍁䅅䅊䡂䍁䅑䅏㙁䍁䅑睔歁䑁䅧䅁㍂允䅁杦䅁䍁䅣睗乂䕁䅫睘䑂䝁䄸兢睂䝁䅅杢㕂䙁䄸睓求䡁䅫睕あ䝁䅅䅤穂䙁䄸杤硁䍁䄰䅉偂䡁䅉兡湂䝁䅫杢桂䝁䅷杌㑂䝁䅷督瑂䙁䄰睓求䡁䅫睘呂䡁䅑兙あ䡁䅍睊桁䍁䅑䅒歁䑁䅕䅎㙁䍁䅑䅒歁䑁䅕兎䅁䝁䘰䅁㡂䅁䅁睊扂䙁䅍䅕䡂䙁䄸睑療䝁䄰䅣桂䝁䄴入時䕁䅳党㕂䙁䅍䅤桂䡁䅑督時䡁䅙免杁䍁䅧杍灁䍁䄴䅥獂䡁䅍兢摂䙁䅍兤睂䡁䅁䅢求䝁䄰党畂䡁䅑兙獂䍁䅣光歁䕁䅍䅊硁䑁䅅杏歁䕁䅍䅊硁䑁䅙䅏䅁䕁䝯䅁潂䅁䅁兖畂䡁䅉党橂䝁䄸睚畁䍁䅁䅖桂䡁䅧䅉䍂䝁䅕杢求䝁䅙兡あ䡁䅍䅌杁䕁䅕杢歂䍁䅁睢浂䍁䅁䅤潂䝁䅕䅉兂䝁䅕杣灂䝁䄸䅚杁䍁䅧杕求䡁䅁睢祂䡁䅑党歂䍁䅫䅁剁睁䅁杂䅁䕁䄴兔䅁䝁䝕䅁䍃䅁䅁睊扂䕁䄰兓時䕁䅍睢瑂䡁䅁兙畂䡁䅫睘䱂䝁䅕入呂䡁䅑兙あ䡁䅍睘㉂䑁䅅兌杁䕁䄸杣灂䝁䅣兡畂䝁䅅䅢畁䡁䅧䅢穂䝁䄰兘䱂䝁䅕入時䙁䅍䅤桂䡁䅑督湁䍁䅅䅊䙂䍁䅑免睁䑁䅑杏歁䕁䅣䅊硁䑁䅁䅎䅁䝁䙕䅁㙂䅁䅁睊扂䕁䅍睢睂䡁䅫䅉療䝁䅙䅉呂䙁䅁睒時䕁䅍睢瑂䡁䅁兙畂䡁䅫睘䱂䝁䅕入呂䡁䅑兙あ䡁䅍睘㉂䑁䅉睘畂䝁䅕睤畁䡁䅧䅢穂䝁䄰兘䱂䝁䅕入時䙁䅍䅤桂䡁䅑督湁䍁䅅䅊䝂䍁䅑免睁䑁䅣䅁楃睂䅁杋䅁䕁䅫兕時䙁䅍兖䍂䙁䄸䅔䙂䕁䅅睕䙂䙁䄸兓佂䕁䅍睘䑂䙁䅫杍䅁䵁䉫䅁坂䅁䅁睑療䝁䄴䅤祂䝁䅅睙あ䡁䅕兙獂䍁䅁睔楂䝁䅷兡湂䝁䅅䅤灂䝁䄸杢穂䍁䅁䅒ㅂ䝁䅕䅉牁䍁䅁䅎杁䍁䅧杕求䡁䅁睢祂䡁䅑党歂䍁䅫䅁慄允䅁杦䅁䍁䅣睗乂䕁䅫睘䑂䝁䄸兢睂䝁䅅杢㕂䙁䄸睓求䡁䅫睕あ䝁䅅䅤穂䙁䄸杤硁䍁䄰䅉偂䡁䅉兡湂䝁䅫杢桂䝁䅷杌㑂䝁䅷督瑂䙁䄰睓求䡁䅫睘呂䡁䅑兙あ䡁䅍睊桁䍁䅑兒歁䑁䅉睍㙁䍁䅑杓歁䑁䅉睍䅁䝁䙍䅁浂䅁䅁睊扂䙁䅍䅕䡂䙁䄸睑療䝁䄰䅣桂䝁䄴入時䕁䅳党㕂䙁䅍䅤桂䡁䅑督時䡁䅙杍杁䑁䅅杌㑂䝁䅷督瑂䙁䄰睓求䡁䅫睘呂䡁䅑兙あ䡁䅍睊桁䍁䅑村歁䑁䅅䅍㉁䅁䅁眰䅙䕁䅁䅁䩂䙁䅅睘偂䙁䅁䅖䩂䕁䄸杔呂䙁䄸睕啂䙁䅉兓䱂䕁䅕睘兂䙁䅉兓䑂䕁䅕睘䡂䙁䅉兑佂䙁䅑兒䕂䅁䅁杍䅍䝁䅑䅁扂䕁䄰兓時䕁䅍睢瑂䡁䅁兙畂䡁䅫睘䱂䝁䅕入呂䡁䅑兙あ䡁䅍睘㉂䑁䅅杌㑂䝁䅷督瑂䙁䄰睑桂䡁䅍䅡時䕁䅙䅢療䡁䅣光歁䕁䅍䅊㕁䑁䅯䅊䑂䍁䅑兏睁䅁䅁杄䅑䡁䄴䅁湁䙁䅳兔䩂䙁䄸睑療䝁䄰䅣桂䝁䄴入時䕁䅳党㕂䙁䅍䅤桂䡁䅑督時䡁䅙免瑁䍁䅁睔祂䝁䅫睚灂䝁䄴兙獂䍁䄴䅥獂䡁䅍兢摂䕁䅳党㕂䙁䄸睕あ䝁䅅䅤穂䍁䅣光歁䕁䅕䅊祁䑁䅍杏歁䕁䅷䅊祁䑁䅍䅁灂兂䅁杚䅁䍁䅣睗呂䙁䅁睒時䕁䅍睢瑂䡁䅁兙畂䡁䅫睘䱂䝁䅕入呂䡁䅑兙あ䡁䅍睘㉂䑁䅉䅉硁䍁䄴䅥獂䡁䅍兢摂䙁䅉兙あ䝁䅫睢穂䍁䅣光歁䕁䅑䅊㍁䑁䅯䅊䩂䍁䅑睎䅁偁䝯䅁獁䅁䅁睑療䝁䄰䅣療䝁䄴党畂䡁䅑䅉䕂䝁䅕督橂䡁䅉兡睂䡁䅑兡療䝁䄴䅁䝃杂䅁杓䅁䙁䅳睓求䡁䅫睕あ䝁䅅䅤穂䙁䄸䅤求䡁䅍䅤浂䝁䅫䅢求䍁䄴䅥獂䡁䅍䅥摂䙁䅍䅡求䝁䅕䅤硁䍁䅅䅊䍂䍁䅑杍睁䅁䅁兌䅁䡁䅉䅁湁䙁䅳兔䩂䙁䄸睑療䝁䄰䅣桂䝁䄴入時䕁䅳党㕂䙁䅍䅤桂䡁䅑督時䡁䅙免瑁䍁䅁睔祂䝁䅫睚灂䝁䄴兙獂䍁䄴䅥獂䡁䅍兢摂䕁䅳党㕂䙁䄸睕あ䝁䅅䅤穂䍁䅣光歁䕁䅕䅊ㅁ䑁䅉䅁牂兂䅁䅡䅁䍁䅣睗乂䕁䅫睘䑂䝁䄸兢睂䝁䅅杢㕂䙁䄸睓求䡁䅫睕あ䝁䅅䅤穂䙁䄸杤硁䍁䄰睑療䡁䅁入畁䡁䅧䅢穂䝁䄰兘䱂䝁䅕入時䙁䅍䅤桂䡁䅑督湁䍁䅅䅊䙂䍁䅑兎ㅁ䅁䅁兖䅕䡁䅯䅁湁䙁䅳睑療䡁䅁入杁䝁䄸杚杁䙁䅍䅕䡂䙁䄸睑療䝁䄰䅣桂䝁䄴入時䕁䅳党㕂䙁䅍䅤桂䡁䅑督時䡁䅙杍時䝁䄴党㍂䍁䄴䅥獂䡁䅍兢摂䕁䅳党㕂䙁䄸睕あ䝁䅅䅤穂䍁䅣光歁䕁䅙䅊硁䑁䅁李䅁䭁䡁䅁祂䅁䅁睊扂䕁䄰兓時䕁䅍睢瑂䡁䅁兙畂䡁䅫睘䱂䝁䅕入呂䡁䅑兙あ䡁䅍睘㉂䑁䅅兌杁䕁䄸杣灂䝁䅣兡畂䝁䅅䅢畁䡁䅧䅢穂䝁䄰兘䱂䝁䅕入時䙁䅍䅤桂䡁䅑督湁䍁䅅䅊䙂䍁䅑兎㕁䅁䅁睢䅕䥁䅧䅁湁䙁䅳睕兂䕁䅣睘䑂䝁䄸兢睂䝁䅅杢㕂䙁䄸睓求䡁䅫睕あ䝁䅅䅤穂䙁䄸杤祁䍁䅁免畁䡁䅧䅢穂䝁䄰兘䑂䝁䅅䅣灂䡁䅑兙獂䙁䄸睕あ䡁䅉兤橂䡁䅑兤祂䝁䅕睘杁䕁䅑党あ䝁䅅兡獂䡁䅍䅉湁䍁䅅䅊䑂䍁䅑䅎ぁ䅁䅁䅆䅣䡁䅉䅁湁䙁䅳兔䩂䙁䄸睑療䝁䄰䅣桂䝁䄴入時䕁䅳党㕂䙁䅍䅤桂䡁䅑督時䡁䅙免瑁䍁䅁睔祂䝁䅫睚灂䝁䄴兙獂䍁䄴䅥獂䡁䅍兢摂䕁䅳党㕂䙁䄸睕あ䝁䅅䅤穂䍁䅣光歁䕁䅕䅊㉁䑁䅁䅁硂兂䅁杦䅁䍁䅣睗乂䕁䅫睘䑂䝁䄸兢睂䝁䅅杢㕂䙁䄸睓求䡁䅫睕あ䝁䅅䅤穂䙁䄸杤硁䍁䄰䅉偂䡁䅉兡湂䝁䅫杢桂䝁䅷杌㑂䝁䅷督瑂䙁䄰睓求䡁䅫睘呂䡁䅑兙あ䡁䅍睊桁䍁䅑兔歁䑁䅉杍㙁䍁䅑睔歁䑁䅉杍䅁䙁䘰䅁畂䅁䅁睊扂䕁䄰兓時䕁䅍睢瑂䡁䅁兙畂䡁䅫睘䱂䝁䅕入呂䡁䅑兙あ䡁䅍睘㉂䑁䅅兌䑂䝁䄸䅣㕂䍁䄴䅥獂䡁䅍兢摂䕁䅉兙獂䝁䅅杢橂䝁䅕睘呂䝁䅧党求䡁䅑睊桁䍁䅑睑歁䑁䅑䅁㑂兂䅁䅩䅁䍁䅣睗呂䙁䅁睒時䕁䅍睢瑂䡁䅁兙畂䡁䅫睘䱂䝁䅕入呂䡁䅑兙あ䡁䅍睘㉂䑁䅉䅉硁䍁䄴䅥獂䡁䅍兢摂䕁䅍兙睂䝁䅫䅤桂䝁䅷睘呂䡁䅑杣ㅂ䝁䅍䅤ㅂ䡁䅉党時䍁䅁䅒求䡁䅑兙灂䝁䅷督杁䍁䅣光歁䕁䅕䅊硁䑁䅉䅁䭁睂䅁䅊䅁䕁䅫兕時䙁䅕杔呂䕁䅕睑噂䙁䅉兒䕂䙁䄸䅒䙂䕁䅉䅖䅁䑁䉙䅁䅂䅁䅁兓剂䙁䄸睑偂䕁䄰兔偂䕁䄴睘䙂䙁䅅兖䩂䙁䅑兗時䑁䅍兗卂䙁䄸兑佂䕁䄴睘䡂䙁䅉睔塂䙁䅑䅓䅁䡁䌰䅁㑂䅁䅁睊扂䕁䄰兓時䕁䅍睢瑂䡁䅁兙畂䡁䅫睘䱂䝁䅕入呂䡁䅑兙あ䡁䅍睘㉂䑁䅅兌䑂䝁䄸䅣㕂䍁䄴䅥獂䡁䅍兢摂䕁䅉兙獂䝁䅅杢橂䝁䅕睘呂䝁䅧党求䡁䅑睊桁䍁䅑兒歁䑁䅑杏歁䙁䅁䅊ぁ䅁䅁入䅕䙁䅷䅁扂䕁䅳党㕂䙁䅍䅤桂䡁䅑督時䡁䅑党穂䡁䅑杚灂䝁䅷党畁䡁䅧䅢穂䝁䄰兘䱂䝁䅕入時䙁䅍䅤桂䡁䅑督桁䍁䅑睑歁䑁䅙䅍㙁䍁䅑睑歁䑁䅙李䅁䩁䄸䅁祂䅁䅁睗乂䕁䅫睘䑂䝁䄸兢睂䝁䅅杢㕂䙁䄸睓求䡁䅫睕あ䝁䅅䅤穂䙁䄸杤硁䙁䄸杌㑂䝁䅷督瑂䙁䄰兓畂䝁䅍睢瑂䝁䅕睘呂䡁䅑兙あ䝁䅕兢求䝁䄴䅤桁䍁䅑兒歁䑁䅕杏歁䙁䅁䅊ㅁ䅁䅁䄱䅑䡁䄴䅁湁䙁䅳兔䩂䙁䄸睑療䝁䄰䅣桂䝁䄴入時䕁䅳党㕂䙁䅍䅤桂䡁䅑督時䡁䅙免瑁䕁䅍睢睂䡁䅫杌㑂䝁䅷督瑂䙁䄰睑桂䡁䅁兡あ䝁䅅䅢灂䡁䅯兙あ䝁䅫睢畂䍁䅣光歁䕁䅍䅊ㅁ䑁䅍杏歁䕁䅍䅊ㅁ䑁䅑䅁畁兂䅁䅌䅁䕁䅫兕時䕁䄸䅔時䕁䅍睔乂䕁䄰睘䉂䕁䅙䅖䙂䙁䅉睘䝂䕁䅫杖䙂䅁䅁睷䅅䝁䅯䅁扂䕁䄰兓時䕁䅍睢瑂䡁䅁兙畂䡁䅫睘䱂䝁䅕入呂䡁䅑兙あ䡁䅍睘㉂䑁䅅杌㑂䝁䅷督瑂䙁䄰村桂䝁䅷兙畂䝁䅍党時䙁䅍䅡求䝁䅕䅤桁䍁䅑兒歁䑁䅣杏歁䙁䅁䅊㍁䅁䅁睴䅕䡁䅧䅁湁䙁䅳兔䩂䙁䄸睑療䝁䄰䅣桂䝁䄴入時䕁䅳党㕂䙁䅍䅤桂䡁䅑督時䡁䅙免瑁䕁䅍睢睂䡁䅫杌㑂䝁䅷督瑂䙁䄰村桂䝁䅷兙畂䝁䅍党時䙁䅍䅡求䝁䅕䅤湁䍁䅅䅊䙂䍁䅑兎㙁䍁䅑䅕歁䑁䅕䅁㝂兂䅁杚䅁䍁䅣睗呂䙁䅁睒時䕁䅍睢瑂䡁䅁兙畂䡁䅫睘䱂䝁䅕入呂䡁䅑兙あ䡁䅍睘㉂䑁䅉䅉硁䍁䄴䅥獂䡁䅍兢摂䕁䅳党㕂䙁䄸睕あ䝁䅅䅤穂䍁䅣光歁䕁䅕䅊硁䑁䅁李䅁䵁䝁䅁敁䅁䅁兓剂䙁䄸䅒䑂䙁䅍睘呂䕁䅕睑噂䙁䅉兒䕂䅁䅁杮䅙䩁䅙䅁湁䙁䅳兔䩂䙁䄸睑療䝁䄰䅣桂䝁䄴入時䕁䅳党㕂䙁䅍䅤桂䡁䅑督時䡁䅙免瑁䕁䅍睢睂䡁䅫杌㑂䝁䅷督瑂䙁䄰睑桂䡁䅁兡あ䝁䅅䅢時䙁䅍䅤祂䡁䅕睙あ䡁䅕杣求䙁䄸睕ㅂ䝁䄰兢桂䡁䅉入湁䍁䅅䅊䑂䍁䅑免穁䑁䅯䅊䑂䍁䅑免ㅁ䑁䅁䅁䍃兂䅁杈䅁䕁䅍兤祂䡁䅉党畂䡁䅑䅉䑂䝁䄸兤睂䝁䄸杢䅁䩁䝉䅁䭂䅁䅁睑桂䡁䅍䅡杁䕁䅙杣療䝁䄰䅉偂䡁䅁党祂䝁䅅䅤灂䝁䄸杢穂䍁䅷䅉祁䍁䅁兗祂䍁䄴䅉䑂䕁䅅睒卂䍁䅁䅋汁䍁䅫䅁捂杁䅁杨䅁䍁䅣睗乂䕁䅫睘䑂䝁䄸兢睂䝁䅅杢㕂䙁䄸睓求䡁䅫睕あ䝁䅅䅤穂䙁䄸杤硁䍁䄰睑療䡁䅁入畁䡁䅧䅢穂䝁䄰兘䑂䝁䅅䅣灂䡁䅑兙獂䙁䄸睕あ䡁䅉兤橂䡁䅑兤祂䝁䅕睘呂䡁䅕兢瑂䝁䅅杣㕂䍁䅣光歁䕁䅍䅊ぁ䅁䅁䅧䅕䝁䅑䅁扂䙁䅍䅕䡂䙁䄸睑療䝁䄰䅣桂䝁䄴入時䕁䅳党㕂䙁䅍䅤桂䡁䅑督時䡁䅙免畁䡁䅧䅢穂䝁䄰兘䑂䝁䅅督潂䙁䄸杒獂䝁䄸睤桁䍁䅑兒歁䑁䅙杏歁䙁䅁䅊㉁䅁䅁儷䅕䡁䅯䅁湁䙁䅳睕兂䕁䅣睘䑂䝁䄸兢睂䝁䅅杢㕂䙁䄸睓求䡁䅫睕あ䝁䅅䅤穂䙁䄸杤祁䍁䅁免畁䡁䅧䅢穂䝁䄰兘䑂䝁䅅䅣灂䡁䅑兙獂䝁䅫来桂䡁䅑兡療䝁䄴睊桁䍁䅑兒歁䑁䅑睎㙁䍁䅑杓歁䑁䅑睎䅁佁䜴䅁䕂䅁䅁兒桂䡁䅉杢灂䝁䄴睚穂䍁䅁杚祂䝁䄸兢杁䕁䅍睢畂䡁䅑䅉偂䡁䅁督杁䕁䄰兙祂䝁䅣兡畂䍁䅁䅋汁䍁䅫䅁䭁杁䅁杖䅁䙁䅑睢あ䝁䅅䅢杁䕁䅍兙睂䝁䅫䅤桂䝁䅷䅉䵂䝁䄸督穂䍁䅁睑桂䡁䅉杣㕂䝁䅙睢祂䡁䅣兙祂䝁䅑䅉潁䙁䅉党睂䝁䄸杣あ䝁䅕䅚灁䅁䅁眷䅉䩁䅑䅁湁䙁䅳兔䩂䙁䄸睑療䝁䄰䅣桂䝁䄴入時䕁䅳党㕂䙁䅍䅤桂䡁䅑督時䡁䅙免瑁䕁䅍睢睂䡁䅫杌㑂䝁䅷督瑂䙁䄰睑桂䡁䅁兡あ䝁䅅䅢時䙁䅍䅤祂䡁䅕睙あ䡁䅕杣求䙁䄸睕ㅂ䝁䄰兢桂䡁䅉入湁䍁䅅䅊䕂䍁䅑杍㍁䑁䅯䅊䕂䍁䅑睎㑁䅁䅁杨䅕䍁䅁䅁呂䙁䅁睘䝂䕁䅫睕䑂䕁䅅䅔時䙁䅅睘䙂䙁䅍䅖䅁䱁䥫䅁元䅁䅁睊扂䕁䄰兓時䕁䅍睢瑂䡁䅁兙畂䡁䅫睘䱂䝁䅕入呂䡁䅑兙あ䡁䅍睘㉂䑁䅅兌䑂䝁䄸䅣㕂䍁䄴䅥獂䡁䅍兢摂䕁䅍兙睂䝁䅫䅤桂䝁䅷睘呂䡁䅑杣ㅂ䝁䅍䅤ㅂ䡁䅉党時䙁䅍兤瑂䝁䄰兙祂䡁䅫睊桁䍁䅑兒歁䑁䅑杏歁䕁䄸䅊ぁ䅁䅁內䅕䉁䅯䅁㡁䑁䄴䅍㕁䍁䄸免㍁䍁䄸杍睁䑁䅉䅍䅁䭁䙙䅁元䅁䅁睊扂䕁䄰兓時䕁䅍睢瑂䡁䅁兙畂䡁䅫睘䱂䝁䅕入呂䡁䅑兙あ䡁䅍睘㉂䑁䅅兌䑂䝁䄸䅣㕂䍁䄴䅥獂䡁䅍兢摂䕁䅍兙睂䝁䅫䅤桂䝁䅷睘呂䡁䅑杣ㅂ䝁䅍䅤ㅂ䡁䅉党時䙁䅍兤瑂䝁䄰兙祂䡁䅫睊桁䍁䅑兒歁䑁䅕杏歁䕁䄸䅊ㅁ䅁䅁睧䅕䩁䅁䅁湁䙁䅳兔䩂䙁䄸睑療䝁䄰䅣桂䝁䄴入時䕁䅳党㕂䙁䅍䅤桂䡁䅑督時䡁䅙免瑁䕁䅍睢睂䡁䅫杌㑂䝁䅷督瑂䙁䄰睑桂䡁䅁兡あ䝁䅅䅢時䙁䅍䅤祂䡁䅕睙あ䡁䅕杣求䙁䄸睕ㅂ䝁䄰兢桂䡁䅉入湁䍁䅅䅊䝂䍁䅑䅏㙁䍁䅑䅕歁䑁䅧䅁䙃兂䅁䅫䅁䍁䅣睗乂䕁䅫睘䑂䝁䄸兢睂䝁䅅杢㕂䙁䄸睓求䡁䅫睕あ䝁䅅䅤穂䙁䄸杤硁䍁䄰睑療䡁䅁入畁䡁䅧䅢穂䝁䄰兘䑂䝁䅅䅣灂䡁䅑兙獂䙁䄸睕あ䡁䅉兤橂䡁䅑兤祂䝁䅕睘呂䡁䅕兢瑂䝁䅅杣㕂䍁䅣光歁䕁䅙䅊㕁䑁䅯䅊兂䍁䅑兏䅁䥁䙣䅁䅂䅁䅁兓剂䙁䄸睑偂䕁䄰兔偂䕁䄴睘䙂䙁䅅兖䩂䙁䅑兗時䑁䅅兗卂䙁䄸兑佂䕁䄴睘䡂䙁䅉睔塂䙁䅑䅓䅁䍁䌸䅁獁䅁䅁兓剂䙁䄸睕卂䙁䄸睕噂䕁䅉睘䕂䕁䅕村啂䙁䄸兒䍂䕁䅫䅖䕂䕁䅅䅁呃允䅁杖䅁䙁䅳睕兂䕁䅣睘䑂䝁䄸兢睂䝁䅅杢㕂䙁䄸睓求䡁䅫睕あ䝁䅅䅤穂䙁䄸杤祁䍁䄴䅥獂䡁䅍兢摂䙁䅍䅡求
A2: 䝁䅕䅤硁䍁䅅䅊䉂䕁䅅䅊㉁䅁䅁睳䅙䝁䄴䅁䑂䝁䅅䅣灂䡁䅑兙獂䍁䅁䅔療䡁䅍督杁䕁䅍兙祂䡁䅉入浂䝁䄸杣㍂䝁䅅杣歂䍁䅷䅉䑂䡁䅕杣祂䝁䅕杢あ䍁䅁兗求䝁䅅杣杁䍁䅳䅉穁䍁䅁䅋卂䝁䅕䅣療䡁䅉䅤求䝁䅑克䅁佁䍍䅁睂䅁䅁睊扂䕁䄰兓時䕁䅍睢瑂䡁䅁兙畂䡁䅫睘䱂䝁䅕入呂䡁䅑兙あ䡁䅍睘㉂䑁䅅兌䑂䝁䄸䅣㕂䍁䄴䅥獂䡁䅍兢摂䕁䅍兙睂䝁䅫䅤桂䝁䅷兡㙂䝁䅅䅤灂䝁䄸杢湁䍁䅅䅊䑂䍁䅑䅎䅁䑁䙑䅁祂䅁䅁睊扂䕁䄰兓時䕁䅍睢瑂䡁䅁兙畂䡁䅫睘䱂䝁䅕入呂䡁䅑兙あ䡁䅍睘㉂䑁䅅兌䑂䝁䄸䅣㕂䍁䄴䅥獂䡁䅍兢摂䕁䅍兙睂䝁䅫䅤桂䝁䅷兡㙂䝁䅅䅤灂䝁䄸杢湁䍁䅅䅊䑂䍁䅑䅎㍁䅁䅁䅌䅕䩁䅑䅁湁䙁䅳睕兂䕁䅣睘䑂䝁䄸兢睂䝁䅅杢㕂䙁䄸睓求䡁䅫睕あ䝁䅅䅤穂䙁䄸杤硁䍁䅁䅋祁䍁䅫杌㑂䝁䅷督瑂䙁䄰睑桂䡁䅁兡あ䝁䅅䅢時䙁䅍䅤祂䡁䅕睙あ䡁䅕杣求䙁䄸睕ㅂ䝁䄰兢桂䡁䅉入湁䍁䅅䅊䝂䍁䅑免睁䑁䅯䅊兂䍁䅑免睁䅁䅁兑䅙䙁䅷䅁扂䙁䅍䅕䡂䙁䄸睑療䝁䄰䅣桂䝁䄴入時䕁䅳党㕂䙁䅍䅤桂䡁䅑督時䡁䅙杍畁䡁䅧䅢穂䝁䄰兘䱂䝁䅕入時䙁䅍䅤桂䡁䅑督桁䍁䅑村歁䑁䅉李䅁佁䡯䅁权䅁䅁睊扂䕁䅍睢睂䡁䅫䅉療䝁䅙䅉呂䙁䅁睒時䕁䅍睢瑂䡁䅁兙畂䡁䅫睘䱂䝁䅕入呂䡁䅑兙あ䡁䅍睘㉂䑁䅅睘䝂䝁䅫杢桂䝁䅷杌㑂䝁䅷督瑂䙁䄰睑桂䡁䅁兡あ䝁䅅䅢時䙁䅍䅤祂䡁䅕睙あ䡁䅕杣求䙁䄸䅉䕂䝁䅕䅤桂䝁䅫䅢穂䍁䅁睊桁䍁䅑兓歁䑁䅑䅎䅁䡁䥅䅁楂䅁䅁睔睂䡁䅑兡療䝁䄴督㙁䕁䅍兤祂䡁䅉児噂䙁䅍䅒獁䕁䄰兙湂䑁䄰兔灂䝁䅷䅢灂䝁䄸杢穂䍁䅷睑療䝁䄴杤乂䝁䅕䅤潂䝁䄸䅚㥁䕁䅧䅌佂䕁䅅児佂䕁䅅䅁䙂䅃䅁杣䅁䍁䅣睗乂䕁䅫睘䑂䝁䄸兢睂䝁䅅杢㕂䙁䄸睓求䡁䅫睕あ䝁䅅䅤穂䙁䄸杤硁䍁䄰睑療䡁䅁入畁䡁䅧䅢穂䝁䄰兘䑂䝁䅅䅣灂䡁䅑兙獂䝁䅫来桂䡁䅑兡療䝁䄴睊桁䍁䅑睑歁䑁䅑䅏䅁䑁䙁䅁㉁䅁䅁䅖療䡁䅑兙獂䍁䅁村桂䝁䄴睡杁䕁䅑党楂䡁䅑䅉潁䙁䅉党睂䝁䄸杣あ䝁䅕䅚灁䅁䅁免䅅䡁䅉䅁湁䙁䅳兔䩂䙁䄸睑療䝁䄰䅣桂䝁䄴入時䕁䅳党㕂䙁䅍䅤桂䡁䅑督時䡁䅙免瑁䕁䅍睢睂䡁䅫杌㑂䝁䅷督瑂䙁䄰睑桂䡁䅁兡あ䝁䅅䅢灂䡁䅯兙あ䝁䅫睢畂䍁䅣光歁䕁䅍䅊㉁䑁䅅䅁䭂兂䅁䅑䅁䕁䅫兕時䕁䅍睔乂䕁䄰睔佂䙁䄸兒剂䙁䅕兓啂䙁䅫睘ㅁ䙁䅫杕時䕁䅅杔佂䙁䄸睒卂䕁䄸睖啂䕁䅧䅁橃杁䅁杧䅁䍁䅣睗乂䕁䅫睘䑂䝁䄸兢睂䝁䅅杢㕂䙁䄸睓求䡁䅫睕あ䝁䅅䅤穂䙁䄸杤硁䍁䄰睑療䡁䅁入畁䡁䅧䅢穂䝁䄰兘䩂䝁䄴睙療䝁䄰党時䙁䅍䅤桂䡁䅑党瑂䝁䅕杢あ䍁䅣光歁䕁䅍䅊㕁䑁䅯䅊䑂䍁䅑免㍁䑁䅍䅁兂兂䅁杤䅁䕁䄸䅣あ䝁䅫睢畂䡁䅍䅉偂䡁䅕䅤畁䍁䅁兙あ䍁䅁䅤潂䝁䅕䅉䍂䝁䅕睚灂䝁䄴䅉療䝁䅙䅉兂䝁䅕杣灂䝁䄸䅚獁䍁䅁睑療䝁䄰兢療䝁䄴䅉呂䡁䅑睢橂䝁䅳䅉潁䝁䅅睙あ䡁䅕兙獂䍁䅫䅁癁睁䅁䅌䅁䕁䅫兕時䙁䅍杕時䕁䅉睔佂䕁䅑睕時䕁䄴睔啂䕁䅕睕時䙁䅁睑啂䅁䅁朹䅁䡁䄴䅁湁䙁䅳兔䩂䙁䄸睑療䝁䄰䅣桂䝁䄴入時䕁䅳党㕂䙁䅍䅤桂䡁䅑督時䡁䅙免瑁䕁䅍睢睂䡁䅫杌㑂䝁䅷督瑂䙁䄰睑桂䡁䅁兡あ䝁䅅䅢灂䡁䅯兙あ䝁䅫睢畂䍁䅣光歁䕁䅍䅊㉁䑁䅑杏歁䕁䅍䅊㉁䑁䅕䅁䱂兂䅁杚䅁䍁䅣睗呂䙁䅁睒時䕁䅍睢瑂䡁䅁兙畂䡁䅫睘䱂䝁䅕入呂䡁䅑兙あ䡁䅍睘㉂䑁䅉䅉硁䍁䄴䅥獂䡁䅍兢摂䕁䅳党㕂䙁䄸睕あ䝁䅅䅤穂䍁䅣光歁䕁䅕䅊硁䑁䅁睎䅁䵁䝉䅁㡂䅁䅁睊扂䕁䄰兓時䕁䅍睢瑂䡁䅁兙畂䡁䅫睘䱂䝁䅕入呂䡁䅑兙あ䡁䅍睘㉂䑁䅅兌䑂䝁䄸䅣㕂䍁䄴䅥獂䡁䅍兢摂䕁䅍兙睂䝁䅫䅤桂䝁䅷兡㙂䝁䅅䅤灂䝁䄸杢湁䍁䅅䅊䑂䍁䅑兏㙁䍁䅑睑歁䑁䅉兎䅁䑁䙙䅁⭂䅁䅁睊扂䕁䄰兓時䕁䅍睢瑂䡁䅁兙畂䡁䅫睘䱂䝁䅕入呂䡁䅑兙あ䡁䅍睘㉂䑁䅅兌䑂䝁䄸䅣㕂䍁䄴䅥獂䡁䅍兢摂䕁䅍兙睂䝁䅫䅤桂䝁䅷兡㙂䝁䅅䅤灂䝁䄸杢湁䍁䅅䅊䙂䍁䅑兎硁䑁䅯䅊䭂䍁䅑兎硁䅁䅁兌䅕䝁䅧䅁扂䕁䄰兓時䕁䅍睢瑂䡁䅁兙畂䡁䅫睘䱂䝁䅕入呂䡁䅑兙あ䡁䅍睘㉂䑁䅅睘畁䡁䅧䅢穂䝁䄰兘䱂䝁䅕入時䙁䅍䅤桂䡁䅑督桁䍁䅑睑歁䑁䅉䅏㙁䍁䅑睑歁䑁䅕杍䅁䱁䔸䅁⭂䅁䅁睊扂䕁䄰兓時䕁䅍睢瑂䡁䅁兙畂䡁䅫睘䱂䝁䅕入呂䡁䅑兙あ䡁䅍睘㉂䑁䅅兌䑂䝁䄸䅣㕂䍁䄴䅥獂䡁䅍兢摂䕁䅍兙睂䝁䅫䅤桂䝁䅷兡㙂䝁䅅䅤灂䝁䄸杢湁䍁䅅䅊䙂䍁䅑兎祁䑁䅯䅊䭂䍁䅑兎祁䅁䅁睌䅕䝁䅙䅁扂䕁䄰兓時䕁䅍睢瑂䡁䅁兙畂䡁䅫睘䱂䝁䅕入呂䡁䅑兙あ䡁䅍睘㉂䑁䅅杌㑂䝁䅷督瑂䙁䄰睓求䡁䅫睘呂䡁䅑兙あ䡁䅍光歁䕁䅑䅊祁䑁䅕杏歁䕁䅑䅊ぁ䑁䅫䅁㙄睁䅁䅡䅁䙁䅳睕兂䕁䅣睘䑂䝁䄸兢睂䝁䅅杢㕂䙁䄸睓求䡁䅫睕あ䝁䅅䅤穂䙁䄸杤硁䍁䄴䅥獂䡁䅍兢摂䕁䅳党㕂䙁䄸睕あ䝁䅅䅤穂䍁䅅䅊乂䍁䅑杍㉁䑁䅯䅊偂䍁䅑杍㉁䅁䅁眱䅕䡁䅯䅁湁䙁䅳睑療䡁䅁入杁䝁䄸杚杁䙁䅍䅕䡂䙁䄸睑療䝁䄰䅣桂䝁䄴入時䕁䅳党㕂䙁䅍䅤桂䡁䅑督時䡁䅙杍時䝁䄴党㍂䍁䄴䅥獂䡁䅍兢摂䙁䅉兙あ䝁䅫睢穂䍁䅣光歁䕁䅑䅊㍁䑁䅯䅊䩂䍁䅑睎䅁䝁䡅䅁捁䅁䅁兓剂䙁䄸杔偂䕁䅷睘䑂䕁䅙睘穁䙁䅫杕䅁乁䍉䅁⭂䅁䅁睊扂䕁䄰兓時䕁䅍睢瑂䡁䅁兙畂䡁䅫睘䱂䝁䅕入呂䡁䅑兙あ䡁䅍睘㉂䑁䅅兌䑂䝁䄸䅣㕂䍁䄴䅥獂䡁䅍兢摂䕁䅍兙睂䝁䅫䅤桂䝁䅷兡㙂䝁䅅䅤灂䝁䄸杢湁䍁䅅䅊䙂䍁䅑䅎㍁䑁䅯䅊䭂䍁䅑䅎㍁䅁䅁免䅕䑁䅙䅁啂䝁䄸䅤桂䝁䅷䅉䑂䝁䄸兢瑂䝁䄸杢杁䕁䅕兣ㅂ䝁䅫䅤㕂䍁䅁䅋歁䑁䅁䅍睁䍁䅫䅁硂䅁䅁杖䅁䙁䅳睓求䡁䅫睕あ䝁䅅䅤穂䙁䄸䅤求䡁䅍䅤浂䝁䅫䅢求䍁䄴䅥獂䡁䅍䅥摂䙁䅍䅡求䝁䅕䅤硁䍁䅅䅊䙂䍁䅑杍穁䑁䅯䅊䩂䍁䅑杍穁䅁䅁䅕䅁䡁䅯䅁湁䙁䅳兔䩂䙁䄸睑療䝁䄰䅣桂䝁䄴入時䕁䅳党㕂䙁䅍䅤桂䡁䅑督時䡁䅙免瑁䕁䅍睢睂䡁䅫杌㑂䝁䅷督瑂䙁䄰睑桂䡁䅁兡あ䝁䅅䅢灂䡁䅯兙あ䝁䅫睢畂䍁䅣光歁䕁䅕䅊ぁ䑁䅯䅊䭂䍁䅑䅎䅁䑁䙕䅁兂䅁䅁䅖療䡁䅑兙獂䍁䅁睕求䝁䄴兡療䡁䅉䅉呂䝁䅕睙ㅂ䡁䅉党歂䍁䄸䅋䙂䕁䅉兓啂䕁䅑兑瑁䕁䅍兑兂䕁䅕䅗灁䍁䅁䅋㑂䍁䅫䅁千允䅁杦䅁䍁䅣睗乂䕁䅫睘䑂䝁䄸兢睂䝁䅅杢㕂䙁䄸睓求䡁䅫睕あ䝁䅅䅤穂䙁䄸杤硁䍁䄰睑療䡁䅁入畁䡁䅧䅢穂䝁䄰兘䑂䝁䅅䅣灂䡁䅑兙獂䝁䅫来桂䡁䅑兡療䝁䄴睊桁䍁䅑兒歁䑁䅑䅏㙁䍁䅑杓歁䑁䅑䅏䅁䑁䙍䅁⭂䅁䅁睊扂䕁䄰兓時䕁䅍睢瑂䡁䅁兙畂䡁䅫睘䱂䝁䅕入呂䡁䅑兙あ䡁䅍睘㉂䑁䅅兌䑂䝁䄸䅣㕂䍁䄴䅥獂䡁䅍兢摂䕁䅍兙睂䝁䅫䅤桂䝁䅷兡㙂䝁䅅䅤灂䝁䄸杢湁䍁䅅䅊䙂䍁䅑兎㕁䑁䅯䅊䭂䍁䅑兎㕁䅁䅁睒䅕䡁䅑䅁湁䙁䅳兔䩂䙁䄸睑療䝁䄰䅣桂䝁䄴入時䕁䅳党㕂䙁䅍䅤桂䡁䅑督時䡁䅙免瑁䕁䅍睢睂䡁䅫杌㑂䝁䅷督瑂䙁䄰睓求䡁䅫睘呂䡁䅑兙あ䡁䅍睊桁䍁䅑兔歁䑁䅉李㙁䍁䅑睔歁䑁䅉李䅁䍁䙍䅁䥃䅁䅁睊扂䙁䅍䅕䡂䙁䄸睑療䝁䄰䅣桂䝁䄴入時䕁䅳党㕂䙁䅍䅤桂䡁䅑督時䡁䅙杍杁䑁䅅杌㑂䝁䅷督瑂䙁䄰睑桂䡁䅁兡あ䝁䅅䅢時䙁䅍䅤祂䡁䅕睙あ䡁䅕杣求䙁䄸䅉䕂䝁䅕䅤桂䝁䅫䅢穂䍁䅁睊桁䍁䅑杒歁䑁䅑䅎䅁䉁䡧䅁㑂䅁䅁睊扂䕁䄰兓時䕁䅍睢瑂䡁䅁兙畂䡁䅫睘䱂䝁䅕入呂䡁䅑兙あ䡁䅍睘㉂䑁䅅兌䑂䝁䄸䅣㕂䍁䄴䅥獂䡁䅍兢摂䕁䅳党㕂䙁䄸睕あ䝁䅅䅤穂䍁䅣光歁䕁䅕䅊硁䑁䅁李㙁䍁䅑睒歁䑁䅅䅍㉁䅁䅁䅔䅕䡁䅯䅁湁䙁䅳睑療䡁䅁入杁䝁䄸杚杁䙁䅍䅕䡂䙁䄸睑療䝁䄰䅣桂䝁䄴入時䕁䅳党㕂䙁䅍䅤桂䡁䅑督時䡁䅙杍時䝁䄴党㍂䍁䄴䅥獂䡁䅍兢摂䕁䅳党㕂䙁䄸睕あ䝁䅅䅤穂䍁䅣光歁䕁䅕䅊硁䑁䅁䅏䅁䩁䠸䅁䝁䅁䅁杔䉂䅁䅁免䅁䡁䄴䅁湁䙁䅳兔䩂䙁䄸睑療䝁䄰䅣桂䝁䄴入時䕁䅳党㕂䙁䅍䅤桂䡁䅑督時䡁䅙免瑁䕁䅍睢睂䡁䅫杌㑂䝁䅷督瑂䙁䄰睑桂䡁䅁兡あ䝁䅅䅢灂䡁䅯兙あ䝁䅫睢畂䍁䅣光歁䕁䅕䅊㉁䑁䅍杏歁䕁䅯䅊㉁䑁䅍䅁䙂兂䅁䅌䅁䕁䅫兕時䕁䅑䅕呂䙁䄸睍婂䙁䅉睘䉂䕁䄴杔時䕁䅣杕偂䙁䅣䅖䥂䅁䅁睨䅉䝁䅙䅁湁䙁䅳兔䩂䙁䄸睑療䝁䄰䅣桂䝁䄴入時䕁䅳党㕂䙁䅍䅤桂䡁䅑督時䡁䅙免瑁䕁䅍睢睂䡁䅫杌㑂䝁䅷督瑂䙁䄰睑桂䡁䅍䅡時䕁䅙䅢療䡁䅣睊桁䍁䅑睑歁䑁䅑䅁㡂兂䅁杋䅁䕁䅕村䩂䙁䅑䅌杁䑁䅕䅉婂䡁䅉杌杁䕁䅍兑䡂䙁䅉䅉潁䍁䅕克䅁䩁䍙䅁獂䅁䅁睊扂䙁䅍䅕䡂䙁䄸睑療䝁䄰䅣桂䝁䄴入時䕁䅳党㕂䙁䅍䅤桂䡁䅑督時䡁䅙免杁䍁䅧杍灁䍁䄴䅥獂䡁䅍兢摂䙁䅁党畂䡁䅍兡療䝁䄴兌偂䙁䅁兒䍂䍁䅣光歁䕁䅍䅊㉁䅁䅁䅔䅙䙁䄴䅁扂䕁䄰兓時䕁䅍睢瑂䡁䅁兙畂䡁䅫睘䱂䝁䅕入呂䡁䅑兙あ䡁䅍睘㉂䑁䅅睘畁䡁䅧䅢穂䝁䄰兘䱂䝁䅕入時䙁䅍䅤桂䡁䅑督桁䍁䅑村歁䑁䅅䅍㉁䅁䅁兺䅑䝁䅉䅁扂䕁䄰兓時䕁䅍睢瑂䡁䅁兙畂䡁䅫睘䱂䝁䅕入呂䡁䅑兙あ䡁䅍睘㉂䑁䅅杌㑂䝁䅷督瑂䙁䄰睑桂䡁䅁兡あ䝁䅅䅢灂䡁䅯兙あ䝁䅫睢畂䍁䅅䅊䑂䍁䅑䅎䅁䉁䕁䅁睂䅁䅁睊扂䕁䄰兓時䕁䅍睢瑂䡁䅁兙畂䡁䅫睘䱂䝁䅕入呂䡁䅑兙あ䡁䅍睘㉂䑁䅅兌䑂䝁䄸䅣㕂䍁䄴䅥獂䡁䅍兢摂䕁䅍兙穂䝁䅧睘䝂䝁䅷睢㍂䍁䅣光歁䕁䅕䅊ぁ䑁䅯䅊兂䍁䅑䅎䅁䡁䘰䅁奁䅁䅁兓剂䙁䄸䅖䙂䙁䅙睘䙂䕁䅉兓啂䅁䅁䅗䅙䕁䅯䅁扂䕁䄰兓時䕁䅳党㕂䙁䅍䅤桂䡁䅑督時䡁䅙免畁䡁䅧䅢穂䝁䄰兘䱂䝁䅕入時䙁䅍䅤桂䡁䅑督桁䍁䅑村歁䑁䅉杍䅁䝁䑫䅁睂䅁䅁睊扂䕁䄰兓時䕁䅍睢瑂䡁䅁兙畂䡁䅫睘䱂䝁䅕入呂䡁䅑兙あ䡁䅍睘㉂䑁䅅兌䑂䝁䄸䅣㕂䍁䄴䅥獂䡁䅍兢摂䕁䅍兙穂䝁䅧睘䝂䝁䅷睢㍂䍁䅣光歁䕁䅕䅊ㅁ䑁䅯䅊兂䍁䅑兎䅁䡁䘸䅁㙂䅁䅁睊扂䙁䅍䅕䡂䙁䄸睑療䝁䄰䅣桂䝁䄴入時䕁䅳党㕂䙁䅍䅤桂䡁䅑督時䡁䅙杍杁䑁䅅杌㑂䝁䅷督瑂䙁䄰睑桂䡁䅁兡あ䝁䅅䅢灂䡁䅯兙あ䝁䅫睢畂䍁䅣光歁䕁䅕䅊ㅁ䑁䅅杏歁䕁䅯䅊ㅁ䑁䅅䅁煄杂䅁䅘䅁䕁䅅兢療䡁䅉䅤畁䍁䅁睢浂䍁䅁睒療䝁䄸䅚㍂䝁䅫䅢獂䍁䅁兙畂䝁䅑䅉䩂䝁䄴䅤桂䝁䄴睚灂䝁䅉䅢求䡁䅍䅉潁䙁䅉党睂䝁䄸杣あ䝁䅕䅚灁䅁䅁关䅁䡁䄴䅁湁䙁䅳兔䩂䙁䄸睑療䝁䄰䅣桂䝁䄴入時䕁䅳党㕂䙁䅍䅤桂䡁䅑督時䡁䅙免瑁䕁䅍睢睂䡁䅫杌㑂䝁䅷督瑂䙁䄰兓畂䝁䅍睢瑂䝁䅕睘呂䡁䅑兙あ䝁䅕兢求䝁䄴䅤湁䍁䅅䅊䙂䍁䅑兎㙁䍁䅑䅕歁䑁䅕䅁剂兂䅁条䅁䍁䅣睗乂䕁䅫睘䑂䝁䄸兢睂䝁䅅杢㕂䙁䄸睓求䡁䅫睕あ䝁䅅䅤穂䙁䄸杤硁䍁䄰睑療䡁䅁入畁䡁䅧䅢穂䝁䄰兘䱂䝁䅕入時䙁䅍䅤桂䡁䅑督湁䍁䅅䅊䍂䍁䅑免睁䑁䅙䅁歁兂䅁来䅁䍁䅣睗呂䙁䅁睒時䕁䅍睢瑂䡁䅁兙畂䡁䅫睘䱂䝁䅕入呂䡁䅑兙あ䡁䅍睘㉂䑁䅉䅉硁䍁䄴䅥獂䡁䅍兢摂䕁䅫杢橂䝁䄸兢求䙁䄸睕あ䝁䅅䅤求䝁䄰党畂䡁䅑睊桁䍁䅑兒歁䑁䅙杏歁䙁䅁䅊㉁䅁䅁䄲䅙䝁䅧䅁湁䙁䅳兔䩂䙁䄸睑療䝁䄰䅣桂䝁䄴入時䕁䅳党㕂䙁䅍䅤桂䡁䅑督時䡁䅙免瑁䕁䅍睢睂䡁䅫杌㑂䝁䅷督瑂䙁䄰睓求䡁䅫睘呂䡁䅑兙あ䡁䅍睊桁䍁䅑村歁䑁䅉兎䅁䍁䙧䅁煂䅁䅁睗䱂䝁䅕入呂䡁䅑兙あ䡁䅍睘あ䝁䅕督あ䝁䅙兡獂䝁䅕杌㑂䝁䅷督瑂䙁䄰兓畂䝁䅍睢瑂䝁䅕睘呂䡁䅑兙あ䝁䅕兢求䝁䄴䅤桁䍁䅑䅒歁䑁䅫杏歁䕁䅑䅊硁䑁䅑䅏䅁䝁䑙䅁潂䅁䅁睊扂䕁䄰兓時䕁䅍睢瑂䡁䅁兙畂䡁䅫睘䱂䝁䅕入呂䡁䅑兙あ䡁䅍睘㉂䑁䅅兌䑂䝁䄸䅣㕂䍁䄴䅥獂䡁䅍兢摂䕁䅳党㕂䙁䄸睕あ䝁䅅䅤穂䍁䅣光歁䕁䅉䅊ㅁ䑁䅕䅁啂兂䅁䅡䅁䍁䅣睗乂䕁䅫睘䑂䝁䄸兢睂䝁䅅杢㕂䙁䄸睓求䡁䅫睕あ䝁䅅䅤穂䙁䄸杤硁䍁䄰睑療䡁䅁入畁䡁䅧䅢穂䝁䄰兘䱂䝁䅕入時䙁䅍䅤桂䡁䅑督湁䍁䅅䅊䍂䍁䅑李祁䅁䅁䅗䅕䥁䅑䅁湁䙁䅳睕兂䕁䅣睘䑂䝁䄸兢睂䝁䅅杢㕂䙁䄸睓求䡁䅫睕あ䝁䅅䅤穂䙁䄸杤祁䍁䄴䅥獂䡁䅍兢摂䕁䅍兙睂䝁䅫䅤桂䝁䅷睘呂䡁䅑杣ㅂ䝁䅍䅤ㅂ䡁䅉党時䍁䅁䅒求䡁䅑兙灂䝁䅷督杁䍁䅣光歁䕁䅳䅊硁䑁䅉䅁歁䅃䅁䅥䅁䍁䅣睗乂䕁䅫睘䑂䝁䄸兢睂䝁䅅杢㕂䙁䄸睓求䡁䅫睕あ䝁䅅䅤穂䙁䄸杤硁䍁䄰睑療䡁䅁入畁䡁䅧䅢穂䝁䄰兘䱂䝁䅕入時䙁䅍䅤桂䡁䅑督湁䍁䅅䅊䑂䍁䅑免睁䑁䅫杏歁䕁䅍䅊硁䑁䅅兎䅁䩁䙕䅁敁䅁䅁兓剂䙁䄸睔䵂䙁䄸睑偂䕁䄰兔時䕁䅍兗祁䅁䅁睵䅅䑁䅷䅁䑂䝁䄸兢瑂䝁䄸杢杁䕁䅕兣ㅂ䝁䅫䅤㕂䍁䅷䅉祁䍁䅁兗祂䍁䄴䅉䑂䕁䅅睒卂䍁䅁䅋汁䍁䅫䅁慂杁䅁杄䅁䑁䅉䅍祁䑁䅣杒婂䅁䅁睳䅧䙁䅙䅁扂䕁䅳党㕂䙁䅍䅤桂䡁䅑督時䡁䅑党穂䡁䅑杚灂䝁䅷党畁䡁䅧䅢穂䡁䅧兘呂䝁䅧党求䡁䅑免桁䍁䅑䅒歁䑁䅉兎㙁䍁䅑䅒歁䑁䅑䅏䅁䙁䅍䅁あ䅁䅁睊扂䕁䄰兓時䕁䅍睢瑂䡁䅁兙畂䡁䅫睘䱂䝁䅕入呂䡁䅑兙あ䡁䅍睘㉂䑁䅅兌䑂䝁䄸䅣㕂䍁䄴䅥獂䡁䅍兢摂䕁䅳党㕂䙁䄸睕あ䝁䅅䅤穂䍁䅣光歁䕁䅍䅊祁䑁䅧杏歁䕁䅍䅊ㅁ䑁䅉䅁煁兂䅁䅤䅁䍁䅣睗乂䕁䅫睘䑂䝁䄸兢睂䝁䅅杢㕂䙁䄸睓求䡁䅫睕あ䝁䅅䅤穂䙁䄸杤硁䍁䄰睑療䡁䅁入畁䡁䅧䅢穂䝁䄰兘䱂䝁䅕入時䙁䅍䅤桂䡁䅑督湁䍁䅅䅊䕂䍁䅑兎㍁䑁䅯䅊䕂䍁䅑兎㑁䅁䅁睖䅕䍁䅧䅁䩂䙁䅅睘呂䕁䅕睑噂䙁䅉兓啂䕁䅫杗䙂䕁䅑睘䕂䕁䅕村啂䅁䅁䅑䅅䙁䅷䅁扂䕁䄰兓時䕁䅳党㕂䙁䅍䅤桂䡁䅑督時䡁䅙免畁䡁䅧䅢穂䝁䄰兘呂䡁䅕䅣睂䝁䅷党瑂䝁䅕杢あ䝁䅅䅢桁䍁䅑睑歁䑁䅫杏歁䕁䅍䅊硁䑁䅙䅍䅁䵁䑧䅁㉂䅁䅁睗乂䕁䅫睘䱂䝁䅕入呂䡁䅑兙あ䡁䅍睘㉂䑁䅅杌㑂䝁䅷督瑂䙁䄰睑桂䡁䅁兡あ䝁䅅䅢時䙁䅍䅤祂䡁䅕睙あ䡁䅕杣求䙁䄸睕ㅂ䝁䄰兢桂䡁䅉入桁䍁䅑䅒歁䑁䅉睎㙁䍁䅑䅒歁䑁䅣睎䅁䵁䑅䅁あ䅁䅁睊扂䕁䄰兓時䕁䅍睢瑂䡁䅁兙畂䡁䅫睘䱂䝁䅕入呂䡁䅑兙あ䡁䅍睘㉂䑁䅅兌䑂䝁䄸䅣㕂䍁䄴䅥獂䡁䅍兢摂䕁䅳党㕂䙁䄸睕あ䝁䅅䅤穂䍁䅣光歁䕁䅍䅊ㅁ䑁䅣杏歁䕁䅍䅊ㅁ䑁䅧䅁坂兂䅁䅩䅁䙁䅳睕兂䕁䅣睘䑂䝁䄸兢睂䝁䅅杢㕂䙁䄸睓求䡁䅫睕あ䝁䅅䅤穂䙁䄸杤祁䍁䄴䅥獂䡁䅍兢摂䕁䅍兙睂䝁䅫䅤桂䝁䅷睘呂䡁䅑杣ㅂ䝁䅍䅤ㅂ䡁䅉党時䙁䅍兤瑂䝁䄰兙祂䡁䅫光歁䕁䅙䅊硁䑁䅁杏歁䙁䅉䅊硁䑁䅁䅁䡁䅃䅁䅚䅁䍁䅣睗呂䙁䅁睒時䕁䅍睢瑂䡁䅁兙畂䡁䅫睘䱂䝁䅕入呂䡁䅑兙あ䡁䅍睘㉂䑁䅉䅉硁䍁䄴䅥獂䡁䅍兢摂䕁䅳党㕂䙁䄸睕あ䝁䅅䅤穂䍁䅣光歁䕁䅉䅊祁䑁䅕䅁䑄杂䅁杙䅁䙁䅳兔䩂䙁䄸睑療䝁䄰䅣桂䝁䄴入時䕁䅳党㕂䙁䅍䅤桂䡁䅑督時䡁䅙免時䍁䄴䅥獂䡁䅍兢摂䕁䅉兙獂䝁䅅杢橂䝁䅕睘呂䝁䅧党求䡁䅑光歁䕁䅍䅊ぁ䅁䅁儲䅑䝁䅯䅁湁䙁䅳睕兂䕁䅣睘䑂䝁䄸兢睂䝁䅅杢㕂䙁䄸睓求䡁䅫睕あ䝁䅅䅤穂䙁䄸杤硁䍁䅁䅋祁䍁䅫杌㑂䝁䅷督瑂䙁䄰杕桂䡁䅑兡療䡁䅍睊桁䍁䅑䅒歁䑁䅣杏歁䕁䅫䅊㍁䅁䅁睒䅙䝁䅷䅁扂䙁䅍䅕䡂䙁䄸睑療䝁䄰䅣桂䝁䄴入時䕁䅳党㕂䙁䅍䅤桂䡁䅑督時䡁䅙杍畁䡁䅧䅢穂䝁䄰兘䱂䝁䅕入時䙁䅍䅤桂䡁䅑督桁䍁䅑睒歁䑁䅅䅍㍁䑁䅯䅊䩂䍁䅑免睁䑁䅣䅁ㅄ睂䅁杤䅁䕁䅫杢あ䝁䅕杣求䡁䅍䅤杁䝁䅅杢歂䍁䅁䅕求䝁䄴兙獂䡁䅑兡求䡁䅍䅉卂䝁䅕睙療䝁䅣杌杁䝁䄸杢杁䕁䅉睕杁䍁䄰䅉䉂䝁䅙䅤求䡁䅉䅉啂䝁䅅䅥杁䍁䅧杕求䡁䅁睢祂䡁䅑党歂䍁䅫䅁噁睁䅁䅤䅁䍁䅣睗乂䕁䅫睘䑂䝁䄸兢睂䝁䅅杢㕂䙁䄸睓求䡁䅫睕あ䝁䅅䅤穂䙁䄸杤硁䍁䄰睑療䡁䅁入畁䡁䅧䅢穂䝁䄰兘䱂䝁䅕入時䙁䅍䅤桂䡁䅑督湁䍁䅅䅊䑂䍁䅑李ㅁ䑁䅯䅊䑂䍁䅑睎硁䅁䅁杗䅕䝁䅙䅁扂䕁䄰兓時䕁䅍睢瑂䡁䅁兙畂䡁䅫睘䱂䝁䅕入呂䡁䅑兙あ䡁䅍睘㉂䑁䅅杌㑂䝁䅷督瑂䙁䄰睓求䡁䅫睘呂䡁䅑兙あ䡁䅍光歁䕁䅑䅊祁䑁䅧杏歁䕁䅑䅊ㅁ䑁䅉䅁獃䅂䅁杕䅁䙁䅳睓求䡁䅫睕あ䝁䅅䅤穂䙁䄸䅤求䡁䅍䅤浂䝁䅫䅢求䍁䄴䅥獂䡁䅍兢摂䙁䅉兙あ䝁䅫睢穂䍁䅅䅊䝂䍁䅑䅎㙁䍁䅑睓歁䑁䅑䅁い允䅁䅥䅁䍁䅣睗乂䕁䅫睘䑂䝁䄸兢睂䝁䅅杢㕂䙁䄸睓求䡁䅫睕あ䝁䅅䅤穂䙁䄸杤硁䍁䄰睑療䡁䅁入畁䡁䅧䅢穂䝁䄰兘䱂䝁䅕入時䙁䅍䅤桂䡁䅑督湁䍁䅅䅊䙂䍁䅑免睁䑁䅣杏歁䕁䅣䅊硁䑁䅁睎䅁䍁䙕䅁䕂䅁䅁䅒灂䝁䅷兤あ䝁䅕䅚杁䕁䅕䅕呂䍁䅁兒㑂䝁䅍䅢畁䍁䅁兒㑂䡁䅑杣桂䍁䅁兓あ䝁䅕兢穂䍁䅁䅋歁䍁䅫䅁楂䅁䅁条䅁䙁䅣兙祂䡁䅉兙畂䡁䅑督杁䕁䅕䅥求䡁䅉睙灂䡁䅍党歂䍁䅁䅒ㅂ䡁䅉兡畂䝁䅣䅉あ䝁䅧党杁䙁䅁党祂䝁䅫睢歂䍁䅷䅉啂䝁䄸䅤桂䝁䅷䅉潁䝁䅅睙あ䡁䅕兙獂䍁䅫䅁扂睁䅁杒䅁䕁䅑兡㉂䝁䅫䅚求䝁䄴䅚杁䙁䅁党祂䍁䅁睕潂䝁䅅杣求䍁䅷䅉穁䍁䅁兗祂䍁䄴䅉䑂䕁䅅睒卂䍁䅁䅋汁䍁䅫䅁䥃杁䅁䅩䅁䍁䅣睗䑂䝁䄸䅣㕂䍁䅁睢浂䍁䅁睕兂䕁䅣睘䑂䝁䄸兢睂䝁䅅杢㕂䙁䄸睓求䡁䅫睕あ䝁䅅䅤穂䙁䄸杤祁䙁䄸杢求䡁䅣杌㑂䝁䅷督瑂䙁䄰睓求䡁䅫睘呂䡁䅑兙あ䡁䅍睊桁䍁䅑兒歁䑁䅅䅍㑁䑁䅯䅊䝂䍁䅑免睁䑁䅧䅁摃睂䅁䅤䅁䍁䅣睗乂䕁䅫睘䑂䝁䄸兢睂䝁䅅杢㕂䙁䄸睓求䡁䅫睕あ䝁䅅䅤穂䙁䄸杤硁䍁䄰睑療䡁䅁入畁䡁䅧䅢穂䝁䄰兘䱂䝁䅕入時䙁䅍䅤桂䡁䅑督湁䍁䅅䅊䙂䍁䅑杍ㅁ䑁䅯䅊䭂䍁䅑杍ㅁ䅁䅁克䅕䙁䅷䅁扂䙁䅍䅕䡂䙁䄸睑療䝁䄰䅣桂䝁䄴入時䕁䅳党㕂䙁䅍䅤桂䡁䅑督時䡁䅙杍畁䡁䅧䅢穂䝁䄰兘䱂䝁䅕入時䙁䅍䅤桂䡁䅑督桁䍁䅑村歁䑁䅙杍䅁佁䠴䅁坂䅁䅁睗呂䙁䅁睒時䕁䅍睢瑂䡁䅁兙畂䡁䅫睘䱂䝁䅕入呂䡁䅑兙あ䡁䅍睘㉂䑁䅉杌㑂䝁䅷督瑂䙁䄰睕潂䝁䅕党あ䑁䅅光歁䕁䅫䅊硁䑁䅅䅁摃杂䅁䅤䅁䍁䅣睗乂䕁䅫睘䑂䝁䄸兢睂䝁䅅杢㕂䙁䄸睓求䡁䅫睕あ䝁䅅䅤穂䙁䄸杤硁䍁䄰睑療䡁䅁入畁䡁䅧䅢穂䝁䄰兘䱂䝁䅕入時䙁䅍䅤桂䡁䅑督湁䍁䅅䅊䙂䍁䅑杍㉁䑁䅯䅊䭂䍁䅑杍㉁䅁䅁睋䅕䍁䅙䅁䩂䙁䅅睘塂䕁䅅杕卂䕁䅅杔啂䙁䅍睘䙂䕁䄴䅒時䕁䄸睕䅁䙁䑉䅁煁䅁䅁兓剂䙁䄸䅒䑂䙁䅍睘乂䕁䅅䅖噂䙁䅉兓啂䙁䅫睘䕂䕁䅅䅖䙂䅁䅁䅭䅙䡁䅑䅁湁䙁䅳兔䩂䙁䄸睑療䝁䄰䅣桂䝁䄴入時䕁䅳党㕂䙁䅍䅤桂䡁䅑督時䡁䅙免瑁䕁䅍睢睂䡁䅫杌㑂䝁䅷督瑂䙁䄰睓求䡁䅫睘呂䡁䅑兙あ䡁䅍睊桁䍁䅑兒歁䑁䅉李㙁䍁䅑䅔歁䑁䅉李䅁䙁䙍䅁潂䅁䅁睊扂䕁䄰兓時䕁䅍睢瑂䡁䅁兙畂䡁䅫睘䱂䝁䅕入呂䡁䅑兙あ䡁䅍睘㉂䑁䅅兌䑂䝁䄸䅣㕂䍁䄴䅥獂䡁䅍兢摂䕁䅳党㕂䙁䄸睕あ䝁䅅䅤穂䍁䅣光歁䕁䅕䅊㉁䑁䅉䅁婂兂䅁䅏䅁䕁䅍兙睂䍁䄴䅉䵂䝁䅕兙穂䝁䅕督癁䍁䅁䅖療䡁䅑兙獂䍁䅁䅒求䝁䅉䅤杁䍁䅧兊灁䅁䅁眫䅁䑁䅧䅁呂䝁䅕睙療䝁䄴䅚杁䕁䅷兡求䝁䄴䅉䕂䝁䅕杙あ䍁䅁䅋卂䝁䅕䅣療䡁䅉䅤求䝁䅑克䅁䕁䉣䅁歁䅁䅁兓剂䙁䄸睖啂䕁䅑睘䉂䙁䅙睒時䕁䅫杕時䕁䅍兗硁䅁䅁儷䅅䝁䅧䅁湁䙁䅳兔䩂䙁䄸睑療䝁䄰䅣桂䝁䄴入時䕁䅳党㕂䙁䅍䅤桂䡁䅑督時䡁䅙免瑁䕁䅍睢睂䡁䅫杌㑂䝁䅷督瑂䙁䄰睓求䡁䅫睘呂䡁䅑兙あ䡁䅍睊桁䍁䅑兒歁䑁䅙睍䅁䙁䙳䅁獂䅁䅁睊扂䕁䄰兓時䕁䅍睢瑂䡁䅁兙畂䡁䅫睘䱂䝁䅕入呂䡁䅑兙あ䡁䅍睘㉂䑁䅅兌䑂䝁䄸䅣㕂䍁䄴䅥獂䡁䅍兢摂䙁䅁党畂䡁䅍兡療䝁䄴兌偂䙁䅁兒䍂䍁䅣光歁䕁䅍䅊ぁ䅁䅁䅫䅕䕁䄴䅁䩂䙁䅅睘䩂䕁䄴䅖䙂䙁䅉兒呂䙁䅑睘兂䕁䅕杔䉂䕁䅷䅖䩂䕁䅕睕時䙁䅉兒䑂䕁䄸睒時䕁䅉睕時䙁䅁杕䙂䙁䄸䅖䉂䙁䅧䅁十睁䅁来䅁䍁䅣睗乂䕁䅫睘䑂䝁䄸兢睂䝁䅅杢㕂䙁䄸睓求䡁䅫睕あ䝁䅅䅤穂䙁䄸杤硁䍁䄰睑療䡁䅁入畁䡁䅧䅢穂䝁䄰兘兂䝁䅕杢穂䝁䅫睢畂䍁䄰睔兂䕁䅕村湁䍁䅅䅊䑂䍁䅑兏㙁䍁䅑睑歁䑁䅕李㑁䅁䅁杫䅕䥁䅧䅁湁䙁䅳睕兂䕁䅣睘䑂䝁䄸兢睂䝁䅅杢㕂䙁䄸睓求䡁䅫睕あ䝁䅅䅤穂䙁䄸杤祁䍁䅁免畁䡁䅧䅢穂䝁䄰兘䑂䝁䅅䅣灂䡁䅑兙獂䙁䄸睕あ䡁䅉兤橂䡁䅑兤祂䝁䅕睘杁䕁䅑党あ䝁䅅兡獂䡁䅍䅉湁䍁䅅䅊䱂䍁䅑睎㉁䅁䅁兊䅣䝁䅙䅁扂䕁䄰兓時䕁䅍睢瑂䡁䅁兙畂䡁䅫睘䱂䝁䅕入呂䡁䅑兙あ䡁䅍睘㉂䑁䅅杌㑂䝁䅷督瑂䙁䄰睓求䡁䅫睘呂䡁䅑兙あ䡁䅍光歁䕁䅍䅊祁䑁䅣杏歁䕁䅍䅊ㅁ䑁䅅䅁䝃䅂䅁杗䅁䙁䅳兔䩂䙁䄸睑療䝁䄰䅣桂䝁䄴入時䕁䅳党㕂䙁䅍䅤桂䡁䅑督時䡁䅙免畁䡁䅧䅢穂䝁䄰兘䱂䝁䅕入時䙁䅍䅤桂䡁䅑督桁䍁䅑兒歁䑁䅕睍䅁䥁䔰䅁㉂䅁䅁睊扂䕁䄰兓時䕁䅍睢瑂䡁䅁兙畂䡁䅫睘䱂䝁䅕入呂䡁䅑兙あ䡁䅍睘㉂䑁䅅兌䑂䝁䄸䅣㕂䍁䄴䅥獂䡁䅍兢摂䙁䅁党畂䡁䅍兡療䝁䄴兌偂䙁䅁兒䍂䍁䅣光歁䕁䅑䅊ぁ䑁䅯䅊䩂䍁䅑䅎䅁䩁䙅䅁畂䅁䅁睑桂䡁䅁兡あ䝁䅅䅢杁䕁䅷睢穂䡁䅍䅉䑂䝁䅅杣祂䡁䅫杚療䡁䅉睤桂䡁䅉䅚獁䍁䅁睑ㅂ䡁䅉杣求䝁䄴䅤杁䙁䅫党桂䡁䅉䅉牁䍁䅁杍杁䍁䅧杕求䡁䅁睢祂䡁䅑党歂䍁䅫䅁桄杁䅁䅣䅁䕁䄴党あ䡁䅑兡畂䝁䅣䅉桂䝁䄴䅚杁䕁䄸䅤潂䝁䅕杣杁䕁䅅䅚煂䡁䅕督あ䝁䄰党畂䡁䅑督杁䡁䅑睢杁䕁䅷兡桂䝁䅉兡獂䝁䅫䅤灂䝁䅕督杁䍁䅧杕求䡁䅁睢祂䡁䅑党歂䍁䅫䅁汁睁䅁杤䅁䍁䅣睗乂䕁䅫睘䑂䝁䄸兢睂䝁䅅杢㕂䙁䄸睓求䡁䅫睕あ䝁䅅䅤穂䙁䄸杤硁䍁䄰睑療䡁䅁入畁䡁䅧䅢穂䝁䄰兘兂䝁䅕杢穂䝁䅫睢畂䍁䄰睔兂䕁䅕村湁䍁䅅䅊䕂䍁䅑兎㙁䍁䅑兓歁䑁䅕䅁呃兂䅁杓䅁䙁䅳睓求䡁䅫睕あ䝁䅅䅤穂䙁䄸䅤求䡁䅍䅤浂䝁䅫䅢求䍁䄴䅥獂䡁䅍䅥摂䙁䅍䅡求䝁䅕䅤硁䍁䅅䅊䙂䍁䅑杍祁䅁䅁兗䅁䙁䅙䅁扂䕁䅳党㕂䙁䅍䅤桂䡁䅑督時䡁䅑党穂䡁䅑杚灂䝁䅷党畁䡁䅧䅢穂䡁䅧兘呂䝁䅧党求䡁䅑免桁䍁䅑睑歁䑁䅙䅍㙁䍁䅑睑歁䑁䅙䅏䅁䡁䅧䅁杂䅁䅁睊扂䕁䄰兓時䕁䅍睢瑂䡁䅁兙畂䡁䅫睘䱂䝁䅕入呂䡁䅑兙あ䡁䅍睘㉂䑁䅅兌䑂䝁䄸䅣㕂䍁䄴䅥獂䡁䅍兢摂䙁䅉兙あ䝁䅫睢穂䍁䅣光歁䕁䅍䅊ぁ䅁䅁䅩䅕䕁䅁䅁䩂䙁䅅睘䉂䕁䅑䅒時䙁䅑兑奂䙁䄸䅕偂䙁䅍兓啂䕁䅫睔佂䙁䅍睘䑂䙁䅕杕卂䕁䅕杔啂䙁䄸兗卂䅁䅁杂䅍䕁䅧䅁䑂䝁䄸杢㉂䝁䅕杣あ䝁䅫杙獂䝁䅕䅉䕂䝁䅕杙あ䍁䅁兌杁䙁䅑睢あ䝁䅅䅢杁䍁䅧杕求䡁䅁睢祂䡁䅑党歂䍁䅫䅁摁允䅁条䅁䍁䅣睗乂䕁䅫睘䑂䝁䄸兢睂䝁䅅杢㕂䙁䄸睓求䡁䅫睕あ䝁䅅䅤穂䙁䄸杤硁䍁䄰睑療䡁䅁入畁䡁䅧䅢穂䝁䄰兘卂䝁䅅䅤灂䝁䄸督湁䍁䅅䅊䕂䍁䅑兎㙁䍁䅑兓歁䑁䅕䅁䱃兂䅁来䅁䍁䅣睗乂䕁䅫睘䑂䝁䄸兢睂䝁䅅杢㕂䙁䄸睓求䡁䅫睕あ䝁䅅䅤穂䙁䄸杤硁䍁䄰睑療䡁䅁入畁䡁䅧䅢穂䝁䄰兘呂䡁䅕䅣睂䝁䅷党瑂䝁䅕杢あ䝁䅅䅢湁䍁䅅䅊䑂䍁䅑兏㙁䍁䅑睑歁䑁䅅李ぁ䅁䅁杪䅕䑁䅁䅁䩂䙁䅅睘䙂䕁䅉兓啂䕁䅅睘硁䙁䅫杕時䕁䅅杔佂䙁䄸睒卂䕁䄸睖啂䕁䅧䅁噁杁䅁杤䅁䍁䅣睗乂䕁䅫睘䑂䝁䄸兢睂䝁䅅杢㕂䙁䄸睓求䡁䅫睕あ䝁䅅䅤穂䙁䄸杤硁䍁䄰睑療䡁䅁入畁䡁䅧䅢穂䝁䄰兘呂䡁䅕䅣睂䝁䅷党瑂䝁䅕杢あ䝁䅅䅢湁䍁䅅䅊䕂䍁䅑䅎㙁䍁䅑兓歁䑁䅑䅁乃兂䅁䅯䅁䍁䅣睗䑂䝁䄸䅣㕂䍁䅁睢浂䍁䅁睕兂䕁䅣睘䑂䝁䄸兢睂䝁䅅杢㕂䙁䄸睓求䡁䅫睕あ䝁䅅䅤穂䙁䄸杤祁䙁䄸杢求䡁䅣杌㑂䝁䅷督瑂䙁䄰睑桂䡁䅁兡あ䝁䅅䅢時䙁䅍䅤祂䡁䅕睙あ䡁䅕杣求䙁䄸睕ㅂ䝁䄰兢桂䡁䅉入湁䍁䅅䅊䙂䍁䅑睎㙁䍁䅑睔歁䑁䅣䅁婂睂䅁杤䅁䍁䅣睗乂䕁䅫睘䑂䝁䄸兢睂䝁䅅杢㕂䙁䄸睓求䡁䅫睕あ䝁䅅䅤穂䙁䄸杤硁䍁䄰睑療䡁䅁入畁䡁䅧䅢穂䝁䄰兘呂䡁䅕䅣睂䝁䅷党瑂䝁䅕杢あ䝁䅅䅢湁䍁䅅䅊䕂䍁䅑兎㙁䍁䅑兓歁䑁䅕䅁偃兂䅁杣䅁䍁䅣睗乂䕁䅫睘䑂䝁䄸兢睂䝁䅅杢㕂䙁䄸睓求䡁䅫睕あ䝁䅅䅤穂䙁䄸杤硁䍁䄴䅥獂䡁䅍兢摂䙁䅁党畂䡁䅍兡療䝁䄴兌偂䙁䅁兒䍂䍁䅣光歁䕁䅍䅊硁䑁䅅杏歁䕁䅍䅊ㅁ䑁䅣䅍䅁䵁䘴䅁䥂䅁䅁睗䱂䝁䅕入呂䡁䅑兙あ䡁䅍睘あ䝁䅕督あ䝁䅙兡獂䝁䅕杌㑂䝁䅷督㑂䙁䄰睕潂䝁䅕党あ䑁䅉光歁䕁䅑䅊ㅁ䅁䅁兊䅁䍁䅙䅁䩂䙁䅅睘䭂䙁䅉睘呂䙁䅕村時䕁䅑兒䍂䙁䅑睘兂䕁䅍䅖䅁䍁䉑䅁楂䅁䅁睊扂䕁䄰兓時䕁䅍睢瑂䡁䅁兙畂䡁䅫睘䱂䝁䅕入呂䡁䅑兙あ䡁䅍睘㉂䑁䅅杌㑂䝁䅷督瑂䙁䄰䅕求䝁䄴督灂䝁䄸杢瑁䕁䄸䅕䙂䕁䅉睊桁䍁䅑睑歁䑁䅑䅁獁䅂䅁杪䅁䍁䅣睗䑂䝁䄸䅣㕂䍁䅁睢浂䍁䅁睕兂䕁䅣睘䑂䝁䄸兢睂䝁䅅杢㕂䙁䄸睓求䡁䅫睕あ䝁䅅䅤穂䙁䄸杤祁䙁䄸杢求䡁䅣杌㑂䝁䅷督瑂䙁䄰兓畂䝁䅍睢瑂䝁䅕睘呂䡁䅑兙あ䝁䅕兢求䝁䄴䅤湁䍁䅅䅊䙂䍁䅑睎㙁䍁䅑䅕歁䑁䅣䅁䉂睂䅁杏䅁䕁䅣杣療䡁䅍督杁䙁䅁杣療䝁䅙兡あ䍁䅷䅉祁䍁䅁兗祂䍁䄴䅉䑂䕁䅅睒卂䍁䅁䅋汁䍁䅫䅁䭂杁䅁䅣䅁䍁䅣睗乂䕁䅫睘䑂䝁䄸兢睂䝁䅅杢㕂䙁䄸睓求䡁䅫睕あ䝁䅅䅤穂䙁䄸杤硁䍁䄴䅥獂䡁䅍兢摂䙁䅁党畂䡁䅍兡療䝁䄴兌偂䙁䅁兒䍂䍁䅣光歁䕁䅍䅊㕁䑁䅯䅊䑂䍁䅑兎㉁䑁䅧䅁畁䅂䅁杚䅁䙁䅳兔䩂䙁䄸睑療䝁䄰䅣桂䝁䄴入時䕁䅳党㕂䙁䅍䅤桂䡁䅑督時䡁䅙免畁䡁䅧䅢穂䝁䄰兘䑂䝁䅅督潂䙁䄸杒獂䝁䄸睤桁䍁䅑睑歁䑁䅅免㙁䍁䅑睑歁䑁䅫杍䅁䱁䙯䅁䍂䅁䅁睔睂䡁䅑兡療䝁䄴督㙁䕁䅍兤祂䡁䅉児噂䙁䅍䅒獁䕁䄰兙湂䑁䄰睕佂䕁䅷睕あ䝁䅅杢歂䝁䅅杣歂䅁䅁眱䅍䝁䅷䅁湁䙁䅳兔䩂䙁䄸睑療䝁䄰䅣桂䝁䄴入時䕁䅳党㕂䙁䅍䅤桂䡁䅑督時䡁䅙免畁䡁䅧䅢穂䝁䄰兘兂䝁䅕杢穂䝁䅫睢畂䍁䄰睔兂䕁䅕村湁䍁䅅䅊䕂䍁䅑䅎㙁䍁䅑兓歁䑁䅑䅁瑁䅂䅁䅢䅁䍁䅣睗乂䕁䅫睘䑂䝁䄸兢睂䝁䅅杢㕂䙁䄸睓求䡁䅫睕あ䝁䅅䅤穂䙁䄸杤硁䍁䄴䅥獂䡁䅍兢摂䙁䅁党畂䡁䅍兡療䝁䄴兌偂䙁䅁兒䍂䍁䅣光歁䕁䅑䅊ㅁ䑁䅯䅊䩂䍁䅑兎䅁䍁䔸䅁ぁ䅁䅁杓祂䍁䄴䅉呂䡁䅕杙杁䕁䅑党楂䡁䅑䅉癁䍁䅁兒䍂䕁䅫䅖䕂䕁䅅䅉潁䡁䅧克䅁䩁䉁䅁㙂䅁䅁睊扂䙁䅍䅕䡂䙁䄸睑療䝁䄰䅣桂䝁䄴入時䕁䅳党㕂䙁䅍䅤桂䡁䅑督時䡁䅙免杁䍁䅧杍灁䍁䄴䅥獂䡁䅍兢摂䕁䅍兙睂䝁䅫䅤桂䝁䅷兡㙂䝁䅅䅤灂䝁䄸杢湁䍁䅅䅊䙂䍁䅑兎㙁䍁䅑杓歁䑁䅕䅁穁杂䅁杨䅁䍁䅣睗䑂䝁䄸䅣㕂䍁䅁睢浂䍁䅁睕兂䕁䅣睘䑂䝁䄸兢睂䝁䅅杢㕂䙁䄸睓求䡁䅫睕あ䝁䅅䅤穂䙁䄸杤祁䙁䄸杢求䡁䅣杌㑂䝁䅷督瑂䙁䄰睑桂䡁䅍䅡時䕁䅙䅢療䡁䅣睊桁䍁䅑睑歁䑁䅅免㙁䍁䅑睑歁䑁䅅䅍硁䅁䅁兴䅣䝁䅷䅁湁䙁䅳兔䩂䙁䄸睑療䝁䄰䅣桂䝁䄴入時䕁䅳党㕂䙁䅍䅤桂䡁䅑督時䡁䅙免畁䡁䅧䅢穂䝁䄰兘兂䝁䅕杢穂䝁䅫睢畂䍁䄰睔兂䕁䅕村湁䍁䅅䅊䕂䍁䅑李㙁䍁䅑兓歁䑁䅙䅁乄兂䅁杗䅁䙁䅳兔䩂䙁䄸杕䙂䕁䅫䅖時䙁䅍兙瑂䝁䅕睕あ䝁䄸杣求䙁䅑党瑂䡁䅁䅢桂䡁䅑党時䡁䅙免畁䡁䅧䅢穂䙁䄰䅒桂䡁䅑兙桁䍁䅑䅓歁䑁䅑兎䅁乁䑳䅁⭂䅁䅁睊扂䙁䅍䅕䡂䙁䄸睑療䝁䄰䅣桂䝁䄴入時䕁䅳党㕂䙁䅍䅤桂䡁䅑督時䡁䅙免杁䍁䅧杍灁䍁䄴䅥獂䡁䅍兢摂䕁䅍兙睂䝁䅫䅤桂䝁䅷兡㙂䝁䅅䅤灂䝁䄸杢湁䍁䅅䅊䙂䍁䅑兎硁䑁䅯䅊䭂䍁䅑兎硁䅁䅁兎䅙䙁䅁䅁呂䝁䅕䅢獂䝁䅫杢湂䍁䅁睒求䝁䄴党祂䝁䅅䅢杁䍁䅙䅉䉂䝁䅑兢灂䝁䄴䅉䙂䡁䅧䅣畁䍁䅁䅋卂䝁䅕䅣療䡁䅉䅤求䝁䅑克䅁䭁䅕䅁祁䅁䅁睕祂䍁䄴䅉呂䡁䅕杙畁䍁䅁䅒求䝁䅉䅤杁䍁䅧杕求䡁䅁睢祂䡁䅑党歂䍁䅫䅁噁允䅁䅢䅁䍁䅣睗乂䕁䅫睘䑂䝁䄸兢睂䝁䅅杢㕂䙁䄸睓求䡁䅫睕あ䝁䅅䅤穂䙁䄸杤硁䍁䄴䅥獂䡁䅍兢摂䙁䅁党畂䡁䅍兡療䝁䄴兌偂䙁䅁兒䍂䍁䅣光歁䕁䅑䅊㍁䑁䅯䅊䩂䍁䅑睎䅁䵁䘸䅁歂䅁䅁睊扂䕁䄰兓時䕁䅍睢瑂䡁䅁兙畂䡁䅫睘䱂䝁䅕入呂䡁䅑兙あ䡁䅍睘㉂䑁䅅睘畁䡁䅧䅢穂䝁䄰兘兂䝁䅕杢穂䝁䅫睢畂䍁䄰睔兂䕁䅕村湁䍁䅅䅊䑂䍁䅑䅎䅁䅁䙅䅁坂䅁䅁睗呂䙁䅁睒時䕁䅍睢瑂䡁䅁兙畂䡁䅫睘䱂䝁䅕入呂䡁䅑兙あ䡁䅍睘㉂䑁䅉杌㑂䝁䅷督瑂䙁䄰睕潂䝁䅕党あ䑁䅅光歁䕁䅯䅊㍁䑁䅕䅁㝃杂䅁杕䅁䕁䅑兡獂䡁䅕䅤求䝁䅑䅉䙂䙁䅁睕杁䕁䅉党浂䝁䄸杣求䍁䅁兒㑂䡁䅑杣桂䍁䅷䅉ㅁ䍁䅁兗祂䍁䄴䅉䑂䕁䅅睒卂䍁䅁䅋汁䍁䅫䅁慃杁䅁杣䅁䍁䅣睗乂䕁䅫睘䑂䝁䄸兢睂䝁䅅杢㕂䙁䄸睓求䡁䅫睕あ䝁䅅䅤穂䙁䄸杤硁䙁䄸杌㑂䝁䅷督瑂䙁䄰䅕求䝁䄴督灂䝁䄸杢瑁䕁䄸䅕䙂䕁䅉睊桁䍁䅑睑歁䑁䅫杏歁䕁䅍䅊ㅁ䑁䅙䅏䅁䅁䙍䅁獂䅁䅁睗乂䕁䅫睘䑂䝁䄸兢睂䝁䅅杢㕂䙁䄸睓求䡁䅫睕あ䝁䅅䅤穂䙁䄸杤硁䕁䄸䅢歂䍁䄴䅥獂䡁䅍兢摂䕁䅳党㕂䙁䄸睕あ䝁䅅䅤穂䍁䅅䅊䭂䍁䅑杍祁䑁䅯䅊䵂䍁䅑杍祁䅁䅁睥䅑䝁䅧䅁䑂䝁䄸杢あ䡁䅉兙橂䡁䅑兤桂䝁䅷䅉偂䝁䅉䅢灂䝁䅣兙あ䝁䅫睢畂䡁䅍䅉䕂䡁䅕党獁䍁䅁兑浂䡁䅑党祂䍁䅁兎杁䙁䅫杣穂䍁䅁䅋卂䝁䅕䅣療䡁䅉䅤求䝁䅑克䅁佁䉁䅁㑂䅁䅁睊扂䙁䅍䅕䡂䙁䄸睑療䝁䄰䅣桂䝁䄴入時䕁䅳党㕂䙁䅍䅤桂䡁䅑督時䡁䅙免杁䍁䅧杍灁䍁䄴䅥獂䡁䅍兢摂䕁䅳党㕂䙁䄸睕あ䝁䅅䅤穂䍁䅣光歁䕁䅕䅊硁䑁䅁睎㙁䍁䅑睒歁䑁䅅䅍㍁䅁䅁睇䅙䩁䅧䅁偂䡁䅁䅤灂䝁䄸杢穂䑁䅯䅉䑂䡁䅕杣祂䑁䄰兖呂䕁䅑䅌杁䕁䄰兙湂䑁䄰兔灂䝁䅷䅢灂䝁䄸杢穂䍁䅷睑療䝁䄴杤乂䝁䅕䅤潂䝁䄸䅚㥁䕁䄰兓祂䝁䅕睙療䝁䄰兢求䝁䄴䅚求䝁䅑䅌杁䕁䄴兑㥁䕁䄴兑獁䍁䅁䅖求䡁䅉兢㥁䝁䅕杢瑁䙁䅕睕䅁䥁䅫䅁坂䅁䅁睗呂䙁䅁睒時䕁䅍睢瑂䡁䅁兙畂䡁䅫睘䱂䝁䅕入呂䡁䅑兙あ䡁䅍睘㉂䑁䅉杌㑂䝁䅷督瑂䙁䄰睕潂䝁䅕党あ䑁䅅光歁䕁䅧䅊硁䑁䅅䅁慃杂䅁杢䅁䍁䅣睗乂䕁䅫睘䑂䝁䄸兢睂䝁䅅杢㕂䙁䄸睓求䡁䅫睕あ䝁䅅䅤穂䙁䄸杤硁䙁䄸杌㑂䝁䅷督瑂䙁䄰䅕求䝁䄴督灂䝁䄸杢瑁䕁䄸䅕䙂䕁䅉睊桁䍁䅑䅒歁䑁䅕杏歁䕁䅫䅊ㅁ䅁䅁䅂䅕䙁䅉䅁湁䙁䅳兔䩂䙁䄸睓求䡁䅫睕あ䝁䅅䅤穂䙁䄸杤硁䍁䄴䅥獂䡁䅍兢摂䙁䅁党畂䡁䅍兡療䝁䄴兌偂䙁䅁兒䍂䍁䅣光歁䕁䅍䅊ぁ䅁䅁䅴䅍䑁䅁䅁啂䝁䄸䅤桂䝁䅷䅉䕂䝁䅕杙あ䍁䅁睌杁䕁䅕村䩂䙁䅑䅒䉂䍁䅁䅋㑂䍁䅫䅁㡂允䅁䅙䅁䍁䅣睗乂䕁䅫睘䱂䝁䅕入呂䡁䅑兙あ䡁䅍睘㉂䑁䅅杌㑂䝁䅷督瑂䙁䄰䅕求䝁䄴督灂䝁䄸杢瑁䕁䄸䅕䙂䕁䅉睊桁䍁䅑睑歁䑁䅫杏歁䕁䅍䅊ㅁ䑁䅙䅏䅁䱁䑙䅁㑂䅁䅁睗䱂䝁䅕入呂䡁䅑兙あ䡁䅍睘あ䝁䅕督あ䝁䅙兡獂䝁䅕杌㑂䝁䅷督瑂䙁䄰睑桂䡁䅁兡あ䝁䅅䅢時䙁䅍䅤祂䡁䅕睙あ䡁䅕杣求䙁䄸睕ㅂ䝁䄰兢桂䡁䅉入桁䍁䅑杒歁䑁䅕杏歁䕁䄴䅊ㅁ䅁䅁儷䅁䝁䅙䅁扂䕁䄰兓時䕁䅍睢瑂䡁䅁兙畂䡁䅫睘䱂䝁䅕入呂䡁䅑兙あ䡁䅍睘㉂䑁䅅睘畁䡁䅧䅢穂䝁䄰兘䑂䝁䅅䅣灂䡁䅑兙獂䝁䅫来桂䡁䅑兡療䝁䄴光歁䕁䅍䅊ㅁ䑁䅁䅁牄䅂䅁杨䅁䍁䅣睗呂䙁䅁睒時䕁䅍睢瑂䡁䅁兙畂䡁䅫睘䱂䝁䅕入呂䡁䅑兙あ䡁䅍睘㉂䑁䅅䅉潁䑁䅉克畁䡁䅧䅢穂䝁䄰兘䑂䝁䅅䅣灂䡁䅑兙獂䙁䄸睕あ䡁䅉兤橂䡁䅑兤祂䝁䅕睘呂䡁䅕兢瑂䝁䅅杣㕂䍁䅣光歁䕁䅍䅊㉁䅁䅁䅐䅙䝁䅙䅁扂䕁䅳党㕂䙁䅍䅤桂䡁䅑督時䡁䅑党穂䡁䅑杚灂䝁䅷党畁䡁䅧䅢穂䝁䄰兘䑂䝁䅅䅣灂䡁䅑兙獂䝁䅫来桂䡁䅑兡療䝁䄴光歁䕁䅑䅊ㅁ䑁䅍杏歁䕁䅑䅊ㅁ䑁䅑䅁扄䅁䅁䅚䅁䍁䅣睗呂䙁䅁睒時䕁䅍睢瑂䡁䅁兙畂䡁䅫睘䱂䝁䅕入呂䡁䅑兙あ䡁䅍睘㉂䑁䅉䅉硁䍁䄴䅥獂䡁䅍兢摂䕁䅳党㕂䙁䄸睕あ䝁䅅䅤穂䍁䅣光歁䕁䅕䅊㉁䑁䅉䅁兄杂䅁䅘䅁䍁䅣睗乂䕁䅫睘䱂䝁䅕入呂䡁䅑兙あ䡁䅍睘㉂䑁䅅杌㑂䝁䅷督瑂䙁䄰䅕求䝁䄴督灂䝁䄸杢瑁䕁䄸䅕䙂䕁䅉睊桁䍁䅑䅒歁䑁䅕杏歁䕁䅫䅊ㅁ䅁䅁睴䅍䝁䅑䅁扂䙁䅍䅕䡂䙁䄸睑療䝁䄰䅣桂䝁䄴入時䕁䅳党㕂䙁䅍䅤桂䡁䅑督時䡁䅙杍畁䡁䅧䅢穂䝁䄰兘乂䡁䅕䅢あ䝁䅫䅣獂䝁䅕督桁䍁䅑兒歁䑁䅧杏歁䕁䅷䅊㑁䅁䅁兣䅙䡁䄴䅁湁䙁䅳睕兂䕁䅣睘䑂䝁䄸兢睂䝁䅅杢㕂䙁䄸睓求䡁䅫睕あ䝁䅅䅤穂䙁䄸杤硁䍁䅁䅋祁䍁䅫杌㑂䝁䅷督瑂䙁䄰村桂䝁䅷兙畂䝁䅍党時䙁䅍䅡求䝁䅕䅤湁䍁䅅䅊䑂䍁䅑免硁䑁䅯䅊䑂䍁䅑免㉁䑁䅍䅁煁杂䅁杆䅁䑁䅁兏癁䑁䅅兎癁䑁䅉䅍祁䑁䅁䅁桃兂䅁杋䅁䕁䅫兕時䕁䅍兑兂䙁䄸䅔偂䙁䅍睕時䕁䅍杒時䙁䅑睔啂䕁䅅䅔䅁佁䌴䅁歂䅁䅁睊扂䙁䅍䅕䡂䙁䄸睑療䝁䄰䅣桂䝁䄴入時䕁䅳党㕂䙁䅍䅤桂䡁䅑督時䡁䅙免畁䡁䅧䅢穂䝁䄰兘兂䝁䅕杢穂䝁䅫睢畂䍁䄰睔兂䕁䅕村湁䍁䅅䅊䑂䍁䅑李䅁䅁䝷䅁畂䅁䅁睊扂䙁䅍䅕䡂䙁䄸睑療䝁䄰䅣桂䝁䄴入時䕁䅳党㕂䙁䅍䅤桂䡁䅑督時䡁䅙免杁䍁䅧杍灁䍁䄴䅥獂䡁䅍兢摂䕁䅉兙獂䝁䅅杢橂䝁䅕睘呂䝁䅧党求䡁䅑睊桁䍁䅑睑歁䑁䅙䅁潁杂䅁䅈䅁䕁䅫兕時䙁䅕杔䕂䙁䅉兑塂䕁䄴睘卂䕁䅍䅁䕁允䅁䅤䅁䍁䅣睗呂䙁䅁睒時䕁䅍睢瑂䡁䅁兙畂䡁䅫睘䱂䝁䅕入呂䡁䅑兙あ䡁䅍睘㉂䑁䅅䅉潁䑁䅉克畁䡁䅧䅢穂䝁䄰兘䱂䝁䅕入時䙁䅍䅤桂䡁䅑督湁䍁䅅䅊乂䍁䅑杍㉁䑁䅯䅊偂䍁䅑杍㉁䅁䅁睆䅙䑁䅑䅁䩂䙁䅅睘佂䕁䅫睘佂䕁䄸杕乂䙁䄸免婂䙁䅉睘䉂䕁䄴杔時䕁䅣杕偂䙁䅣䅖䥂䅁䅁睆䅉䡁䅧䅁湁䙁䅳睕兂䕁䅣睘䑂䝁䄸兢睂䝁䅅杢㕂䙁䄸睓求䡁䅫睕あ䝁䅅䅤穂䙁䄸杤硁䍁䅁䅋祁䍁䅫杌㑂䝁䅷督瑂䙁䄰村桂䝁䅷兙畂䝁䅍党時䙁䅍䅡求䝁䅕䅤湁䍁䅅䅊䙂䍁䅑李㙁䍁䅑䅕歁䑁䅙䅁灁杂䅁䅥䅁䍁䅣睗呂䙁䅁睒時䕁䅍睢瑂䡁䅁兙畂䡁䅫睘䱂䝁䅕入呂䡁䅑兙あ䡁䅍睘㉂䑁䅅䅉潁䑁䅉克畁䡁䅧䅢穂䝁䄰兘䍂䝁䅅䅢桂䝁䄴睙求䙁䄸睕潂䝁䅕党あ䍁䅣光歁䕁䅕䅊㍁䑁䅯䅊兂䍁䅑睎䅁䍁䝳䅁慁䅁䅁䅐⭁䑁䅁兏癁䑁䅅李癁䑁䅉䅍祁䑁䅁䅁楃兂䅁䅣䅁䙁䅳兔䩂䙁䄸睑療䝁䄰䅣桂䝁䄴入時䕁䅳党㕂䙁䅍䅤桂䡁䅑督時䡁䅙免偂䝁䅷䅚畁䡁䅧䅢穂䝁䄰兘䱂䝁䅕入時䙁䅍䅤桂䡁䅑督桁䍁䅑睑歁䑁䅅䅍ㅁ䑁䅯䅊䑂䍁䅑免睁䑁䅫䅁䅃䅂䅁䅘䅁䙁䅳兔䩂䙁䄸睓求䡁䅫睕あ䝁䅅䅤穂䙁䄸杤硁䍁䄴䅥獂䡁䅍兢摂䙁䅍兤睂䡁䅁䅢求䝁䄰党畂䡁䅑兙獂䍁䅅䅊䑂䍁䅑兏㙁䍁䅑睑歁䑁䅅李ぁ䅁䅁杹䅍䩁䅙䅁湁䙁䅳睕兂䕁䅣睘䑂䝁䄸兢睂䝁䅅杢㕂䙁䄸睓求䡁䅫睕あ䝁䅅䅤穂䙁䄸杤硁䍁䅁䅋祁䍁䅫杌㑂䝁䅷督瑂䙁䄰睑桂䡁䅁兡あ䝁䅅䅢時䙁䅍䅤祂䡁䅕睙あ䡁䅕杣求䙁䄸睕ㅂ䝁䄰兢桂䡁䅉入湁䍁䅅䅊䑂䍁䅑免ㅁ䑁䅯䅊䑂䍁䅑免ㅁ䑁䅉䅁⭁杂䅁䅋䅁䕁䅫兕時䙁䅑睔啂䕁䅅䅔時䙁䅍杕時䙁䅍兒䑂䙁䅕杕䙂䕁䅑䅁ぁ允䅁杖䅁䙁䅳睓求䡁䅫睕あ䝁䅅䅤穂䙁䄸䅤求䡁䅍䅤浂䝁䅫䅢求䍁䄴䅥獂䡁䅍䅥摂䙁䅍䅡求䝁䅕䅤硁䍁䅅䅊䙂䍁䅑杍祁䑁䅯䅊䩂䍁䅑杍祁䅁䅁杔䅁䙁䅙䅁扂䙁䅍䅕䡂䙁䄸睑療䝁䄰䅣桂䝁䄴入時䕁䅳党㕂䙁䅍䅤桂䡁䅑督時䡁䅙杍畁䡁䅧䅢穂䝁䄰兘呂䝁䅧党求䡁䅑免桁䍁䅑杒歁䑁䅣兎䅁䱁䝙䅁啃䅁䅁睊扂䙁䅍䅕䡂䙁䄸睑療䝁䄰䅣桂䝁䄴入時䕁䅳党㕂䙁䅍䅤桂䡁䅑督時䡁䅙免杁䍁䅧杍灁䍁䄴䅥獂䡁䅍兢摂䕁䅍兙睂䝁䅫䅤桂䝁䅷睘呂䡁䅑杣ㅂ䝁䅍䅤ㅂ䡁䅉党時䙁䅍兤瑂䝁䄰兙祂䡁䅫睊桁䍁䅑䅒歁䑁䅉兏㙁䍁䅑䅒歁䑁䅧䅍䅁䕁䝉䅁㙂䅁䅁睗乂䕁䅫睘䑂䝁䄸兢睂䝁䅅杢㕂䙁䄸睓求䡁䅫睕あ䝁䅅䅤穂䙁䄸杤硁䙁䄸杌㑂䝁䅷督瑂䙁䄰兓畂䝁䅍睢瑂䝁䅕睘呂䡁䅑兙あ䝁䅕兢求䝁䄴䅤桁䍁䅑兒歁䑁䅅睎㍁䑁䅯䅊兂䍁䅑免㍁䑁䅣䅁奄䅂䅁杣䅁䍁䅣睗呂䙁䅁睒時䕁䅍睢瑂䡁䅁兙畂䡁䅫睘䱂䝁䅕入呂䡁䅑兙あ䡁䅍睘㉂䑁䅅䅉潁䑁䅉克畁䡁䅧䅢穂䝁䄰兘䑂䝁䅅䅣灂䡁䅑兙獂䝁䅫来桂䡁䅑兡療䝁䄴睊桁䍁䅑睑歁䑁䅑䅏䅁䑁䝧䅁元䅁䅁睊扂䙁䅍䅕䡂䙁䄸睑療䝁䄰䅣桂䝁䄴入時䕁䅳党㕂䙁䅍䅤桂䡁䅑督時䡁䅙免杁䍁䅧杍灁䍁䄴䅥獂䡁䅍兢摂䕁䅍兙睂䝁䅫䅤桂䝁䅷睘呂䡁䅑杣ㅂ䝁䅍䅤ㅂ䡁䅉党時䙁䅍兤瑂䝁䄰兙祂䡁䅫睊桁䍁䅑兒歁䑁䅙杏歁䕁䄸䅊㉁䅁䅁児䅙䩁䅑䅁湁䙁䅳睕兂䕁䅣睘䑂䝁䄸兢睂䝁䅅杢㕂䙁䄸睓求䡁䅫睕あ䝁䅅䅤穂䙁䄸杤硁䍁䅁䅋祁䍁䅫杌㑂䝁䅷督瑂䙁䄰睑桂䡁䅁兡あ䝁䅅䅢時䙁䅍䅤祂䡁䅕睙あ䡁䅕杣求䙁䄸睕ㅂ䝁䄰兢桂䡁䅉入湁䍁䅅䅊䝂䍁䅑免硁䑁䅯䅊兂䍁䅑免硁䅁䅁睑䅙䝁䅧䅁扂䙁䅍䅕䡂䙁䄸睑療䝁䄰䅣桂䝁䄴入時䕁䅳党㕂䙁䅍䅤桂䡁䅑督時䡁䅙免畁䡁䅧䅢穂䝁䄰兘䩂䝁䄴睙療䝁䄰党時䙁䅍䅤桂䡁䅑党瑂䝁䅕杢あ䍁䅅䅊䑂䍁䅑李䅁佁䙑䅁䕃䅁䅁睊扂䕁䅍睢睂䡁䅫䅉療䝁䅙䅉呂䙁䅁睒時䕁䅍睢瑂䡁䅁兙畂䡁䅫睘䱂䝁䅕入呂䡁䅑兙あ䡁䅍睘㉂䑁䅉睘畂䝁䅕睤畁䡁䅧䅢穂䝁䄰兘䱂䝁䅕入時䙁䅍䅤桂䡁䅑督湁䍁䅅䅊䙂䍁䅑杍ㅁ䑁䅯䅊䭂䍁䅑杍ㅁ䅁䅁睊䅣䡁䅁䅁湁䙁䅳睕兂䕁䅣睘䑂䝁䄸兢睂䝁䅅杢㕂䙁䄸睓求䡁䅫睕あ䝁䅅䅤穂䙁䄸杤硁䍁䅁䅋祁䍁䅫杌㑂䝁䅷督瑂䙁䄰睑桂䡁䅁兡あ䝁䅅䅢灂䡁䅯兙あ䝁䅫睢畂䍁䅣光歁䕁䅍䅊ぁ䅁䅁䅍䅙䝁䅧䅁䑂䝁䅅䅣灂䡁䅑兙獂䍁䅁䅔療䡁䅍督杁䕁䅍兙祂䡁䅉入浂䝁䄸杣㍂䝁䅅杣歂䍁䅷䅉佂䝁䄸䅉䙂䡁䅧䅣灂䡁䅉兙あ䝁䅫睢畂䍁䅁䅋卂䝁䅕䅣療䡁䅉䅤求䝁䅑克䅁佁䌰䅁祂䅁䅁睊扂䙁䅍䅕䡂䙁䄸睑療䝁䄰䅣桂䝁䄴入時䕁䅳党㕂䙁䅍䅤桂䡁䅑督時䡁䅙免杁䍁䅧杍灁䍁䄴䅥獂䡁䅍兢摂䕁䅍兙睂䝁䅫䅤桂䝁䅷兡㙂䝁䅅䅤灂䝁䄸杢湁䍁䅅䅊䑂䍁䅑䅎㍁䅁䅁䅎䅙䝁䅯䅁扂䕁䄰兓時䕁䅍睢瑂䡁䅁兙畂䡁䅫睘䱂䝁䅕入呂䡁䅑兙あ䡁䅍睘㉂䑁䅅杌㑂䝁䅷督瑂䙁䄰睓求䡁䅫睘呂䡁䅑兙あ䡁䅍光歁䕁䅕䅊硁䑁䅁睍㙁䍁䅑睒歁䑁䅅䅍穁䅁䅁儹䅍䝁䅧䅁扂䕁䄰兓時䕁䅍睢瑂䡁䅁兙畂䡁䅫睘䱂䝁䅕入呂䡁䅑兙あ䡁䅍睘㉂䑁䅅睘畁䡁䅧䅢穂䝁䄰兘䩂䝁䄴睙療䝁䄰党時䙁䅍䅤桂䡁䅑党瑂䝁䅕杢あ䍁䅅䅊䑂䍁䅑䅎䅁乁䕅䅁䥃䅁䅁睊扂䕁䅍睢睂䡁䅫䅉療䝁䅙䅉呂䙁䅁睒時䕁䅍睢瑂䡁䅁兙畂䡁䅫睘䱂䝁䅕入呂䡁䅑兙あ䡁䅍睘㉂䑁䅉睘畂䝁䅕睤畁䡁䅧䅢穂䝁䄰兘䱂䝁䅕入時䙁䅍䅤桂䡁䅑督湁䍁䅅䅊䡂䍁䅑免睁䑁䅣杏歁䕁䅫䅊硁䑁䅁睎䅁䩁䡳䅁捁䅁䅁兓剂䙁䄸睑䵂䙁䄸䅒噂䕁䅕睘䑂䙁䅫免䅁䭁䉳䅁䥂䅁䅁睗䱂䝁䅕入呂䡁䅑兙あ䡁䅍睘あ䝁䅕督あ䝁䅙兡獂䝁䅕杌㑂䝁䅷督瑂䙁䄰杕桂䡁䅑兡療䡁䅍光歁䕁䅍䅊ぁ䅁䅁眸䅅䙁䅷䅁扂䕁䅳党㕂䙁䅍䅤桂䡁䅑督時䡁䅑党穂䡁䅑杚灂䝁䅷党畁䡁䅧䅢穂䝁䄰兘䱂䝁䅕入時䙁䅍䅤桂䡁䅑督桁䍁䅑杓歁䑁䅉睍㙁䍁䅑䅔歁䑁䅉睍䅁䩁䅷䅁千䅁䅁睊扂䙁䅍䅕䡂䙁䄸睑療䝁䄰䅣桂䝁䄴入時䕁䅳党㕂䙁䅍䅤桂䡁䅑督時䡁䅙杍杁䑁䅅杌㑂䝁䅷督瑂䙁䄰睑桂䡁䅁兡あ䝁䅅䅢時䙁䅍䅤祂䡁䅕睙あ䡁䅕杣求䙁䄸睕ㅂ䝁䄰兢桂䡁䅉入湁䍁䅅䅊䑂䍁䅑免ㅁ䑁䅯䅊䑂䍁䅑免㍁䑁䅁䅁硄杂䅁䅖䅁䙁䅑睢あ䝁䅅䅢杁䙁䅍杣畁䍁䅁村療䝁䄴䅚穂䍁䅁兙畂䝁䅑䅉佂䝁䄸䅤求䡁䅍睌杁䙁䅑睢あ䝁䅅䅢杁䕁䅑党楂䡁䅑䅉潁䍁䅕克䅁偁䅣䅁祂䅁䅁睊扂䙁䅍䅕䡂䙁䄸睑療䝁䄰䅣桂䝁䄴入時䕁䅳党㕂䙁䅍䅤桂䡁䅑督時䡁䅙免杁䍁䅧杍灁䍁䄴䅥獂䡁䅍兢摂䕁䅍兙睂䝁䅫䅤桂䝁䅷兡㙂䝁䅅䅤灂䝁䄸杢湁䍁䅅䅊䑂䍁䅑兎睁䅁䅁杏䅙䑁䅉䅁䩂䙁䅅睘䙂䕁䅉兓啂䕁䅑兑時䑁䅅兗卂䙁䄸兑佂䕁䄴睘䡂䙁䅉睔塂䙁䅑䅓䅁䍁䍍䅁㑂䅁䅁睊扂䕁䅍睢睂䡁䅫䅉療䝁䅙䅉呂䙁䅁睒時䕁䅍睢瑂䡁䅁兙畂䡁䅫睘䱂䝁䅕入呂䡁䅑兙あ䡁䅍睘㉂䑁䅉睘畂䝁䅕睤畁䡁䅧䅢穂䝁䄰兘䱂䝁䅕入時䙁䅍䅤桂䡁䅑督湁䍁䅅䅊䍂䍁䅑李祁䅁䅁杌䅣䡁䅷䅁湁䙁䅳睕兂䕁䅣睘䑂䝁䄸兢睂䝁䅅杢㕂䙁䄸睓求䡁䅫睕あ䝁䅅䅤穂䙁䄸杤硁䍁䅁䅋祁䍁䅫杌㑂䝁䅷督瑂䙁䄰睑桂䡁䅁兡あ䝁䅅䅢灂䡁䅯兙あ䝁䅫睢畂䍁䅣光歁䕁䅍䅊㕁䑁䅯䅊䑂䍁䅑杍ㅁ䅁䅁杍䅙䙁䄴䅁扂䕁䅳党㕂䙁䅍䅤桂䡁䅑督時䡁䅑党穂䡁䅑杚灂䝁䅷党畁䡁䅧䅢穂䝁䄰兘呂䡁䅕䅣睂䝁䅷党瑂䝁䅕杢あ䝁䅅䅢桁䍁䅑杒歁䑁䅑杏歁䕁䅳䅊ぁ䅁䅁睘䅍䑁䅁䅁䩂䙁䅅睘䑂䕁䅅䅕䙂䙁䅧睘硁䙁䅫杕時䕁䅅杔佂䙁䄸睒卂䕁䄸睖啂䕁䅧䅁穁杁䅁䅡䅁䙁䅳睕兂䕁䅣睘䑂䝁䄸兢睂䝁䅅杢㕂䙁䄸睓求䡁䅫睕あ䝁䅅䅤穂䙁䄸杤硁䍁䄴䅥獂䡁䅍兢摂䕁䅳党㕂䙁䄸睕あ䝁䅅䅤穂䍁䅅䅊坂䍁䅑兎㍁䑁䅯䅊塂䍁䅑兎㍁䅁䅁朴䅕䡁䄴䅁湁䙁䅳睕兂䕁䅣睘䑂䝁䄸兢睂䝁䅅杢㕂䙁䄸睓求䡁䅫睕あ䝁䅅䅤穂䙁䄸杤硁䍁䅁䅋祁䍁䅫杌㑂䝁䅷督瑂䙁䄰睑桂䡁䅁兡あ䝁䅅䅢灂䡁䅯兙あ䝁䅫睢畂䍁䅣光歁䕁䅕䅊ぁ䑁䅣杏歁䕁䅯䅊ぁ䑁䅣䅁㕁杂䅁杦䅁䍁䅣睗呂䙁䅁睒時䕁䅍睢瑂䡁䅁兙畂䡁䅫睘䱂䝁䅕入呂䡁䅑兙あ䡁䅍睘㉂䑁䅅䅉潁䑁䅉克畁䡁䅧䅢穂䝁䄰兘䑂䝁䅅䅣灂䡁䅑兙獂䝁䅫来桂䡁䅑兡療䝁䄴睊桁䍁䅑兒歁䑁䅑䅏㙁䍁䅑杓歁䑁䅑䅏䅁䑁䝳䅁啂䅁䅁睗乂䕁䅫睘䱂䝁䅕入呂䡁䅑兙あ䡁䅍睘㉂䑁䅅杌㑂䝁䅷督瑂䙁䄰睑桂䡁䅁兡あ䝁䅅䅢灂䡁䅯兙あ䝁䅫睢畂䍁䅅䅊䑂䍁䅑兎睁䅁䅁睯䅍䙁䅙䅁扂䕁䅳党㕂䙁䅍䅤桂䡁䅑督時䡁䅑党穂䡁䅑杚灂䝁䅷党畁䡁䅧䅢穂䝁䄰兘呂䝁䅧党求䡁䅑免桁䍁䅑睑歁䑁䅉兎㙁䍁䅑睑歁䑁䅑兏䅁䡁䄰䅁㙂䅁䅁睊扂䙁䅍䅕䡂䙁䄸睑療䝁䄰䅣桂䝁䄴入時䕁䅳党㕂䙁䅍䅤桂䡁䅑督時䡁䅙免杁䍁䅧杍灁䍁䄴䅥獂䡁䅍兢摂䕁䅍兙睂䝁䅫䅤桂䝁䅷兡㙂䝁䅅䅤灂䝁䄸杢湁䍁䅅䅊䙂䍁䅑䅎㙁䍁䅑杓歁䑁䅑䅁硁杂䅁杔䅁䕁䅍兙穂䝁䅧䅉䝂䡁䅉睢瑂䍁䅁睔睂䝁䅕杣桂䡁䅑兡療䝁䄴督獁䍁䅁免杁䙁䅫杣畁䍁䅁睒祂䝁䄸睤あ䝁䅧䅉潁䍁䅕克䅁䑁䍉䅁⭂䅁䅁睊扂䙁䅍䅕䡂䙁䄸睑療䝁䄰䅣桂䝁䄴入時䕁䅳党㕂䙁䅍䅤桂䡁䅑督時䡁䅙免杁䍁䅧杍灁䍁䄴䅥獂䡁䅍兢摂䕁䅍兙睂䝁䅫䅤桂䝁䅷兡㙂䝁䅅䅤灂䝁䄸杢湁䍁䅅䅊䙂䍁䅑兎祁䑁䅯䅊䭂䍁䅑兎祁䅁䅁睎䅙䥁䅧䅁湁䙁䅳睕兂䕁䅣睘䑂䝁䄸兢睂䝁䅅杢㕂䙁䄸睓求䡁䅫睕あ䝁䅅䅤穂䙁䄸杤祁䍁䅁免畁䡁䅧䅢穂䝁䄰兘䑂䝁䅅䅣灂䡁䅑兙獂䙁䄸睕あ䡁䅉兤橂䡁䅑兤祂䝁䅕睘杁䕁䅑党あ䝁䅅兡獂䡁䅍䅉湁䍁䅅䅊䍂䍁䅑免祁䅁䅁睁䅣䍁䅉䅁䑂䝁䄸杢㉂䝁䅕杣あ䝁䅫杙獂䝁䅕䅉啂䝁䅕䅥あ䅁䅁杯䅙䍁䅁䅁䙂䕁䅉兓啂䍁䅁兔桂䡁䅉睚灂䝁䄴䅉潁䍁䅕克䅁䅁䍧䅁潂䅁䅁睗呂䙁䅁睒時䕁䅍睢瑂䡁䅁兙畂䡁䅫睘䱂䝁䅕入呂䡁䅑兙あ䡁䅍睘㉂䑁䅅杌㑂䝁䅷督瑂䙁䄰睓求䡁䅫睘呂䡁䅑兙あ䡁䅍光歁䕁䅍䅊㉁䑁䅕杏歁䕁䅍䅊㍁䑁䅅䅁敄兂䅁䅤䅁䍁䅣睗呂䙁䅁睒時䕁䅍睢瑂䡁䅁兙畂䡁䅫睘䱂䝁䅕入呂䡁䅑兙あ䡁䅍睘㉂䑁䅅䅉潁䑁䅉克畁䡁䅧䅢穂䝁䄰兘䑂䝁䅅督潂䙁䄸杒獂䝁䄸睤湁䍁䅅䅊䑂䍁䅑免硁䑁䅯䅊䑂䍁䅑兏祁䅁䅁杌䅙䕁䅑䅁䕂䝁䅕杚求䡁䅉杣求䝁䅑䅉䝂䝁䄸杣求䝁䅫睚畂䍁䅁䅖桂䡁䅧党穂䍁䅁䅋卂䝁䅕䅣療䡁䅉䅤求䝁䅑克䅁䩁䑁䅁浂䅁䅁睊扂䙁䅍䅕䡂䙁䄸睑療䝁䄰䅣桂䝁䄴入時䕁䅳党㕂䙁䅍䅤桂䡁䅑督時䡁䅙免杁䍁䅧杍灁䍁䄴䅥獂䡁䅍兢摂䕁䅍兙穂䝁䅧睘䝂䝁䅷睢㍂䍁䅣光歁䕁䅍䅊㉁䅁䅁䅌䅙䑁䅷䅁䉂䡁䅙党祂䝁䅅睚求䍁䅁兓畂䡁䅑党祂䝁䅕督あ䍁䅁杕桂䡁䅑党杁䍁䅳䅉ぁ䍁䅁䅋汁䍁䅫䅁浄允䅁杓䅁䕁䅍兙穂䝁䅧䅉流䍁䅁睕潂䝁䄸杣あ䍁䅁䅖求䡁䅉兢杁䕁䅫杢㉂䝁䅕督あ䝁䄰党畂䡁䅑督杁䍁䅧䅊睁䑁䅁䅍灁䅁䅁䅢䅁䉁䅙䅁䩂䙁䅅睘呂䙁䅉睘䕂䕁䅕村啂䅁䅁䅇䅅䑁䅁䅁䩂䙁䅅睘䑂䕁䅅䅕䙂䙁䅧睘祁䙁䅫杕時䕁䅅杔佂䙁䄸睒卂䕁䄸睖啂䕁䅧䅁⽁杁䅁杍䅁䕁䅫兕時䕁䅕村䩂䙁䅑䅒䉂䙁䄸杍婂䙁䅉睘䉂䕁䄴杔時䕁䅣杕偂䙁䅣䅖䥂䅁䅁睒䅉䡁䅁䅁湁䙁䅳睕兂䕁䅣睘䑂䝁䄸兢睂䝁䅅杢㕂䙁䄸睓求䡁䅫睕あ䝁䅅䅤穂䙁䄸杤硁䍁䅁䅋祁䍁䅫杌㑂䝁䅷督瑂䙁䄰睑桂䡁䅍䅡時䕁䅙䅢療䡁䅣睊桁䍁䅑兒歁䑁䅣杏歁䙁䅁䅊㍁䅁䅁睌䅙䥁䅑䅁湁䙁䅳睕兂䕁䅣睘䑂䝁䄸兢睂䝁䅅杢㕂䙁䄸睓求䡁䅫睕あ䝁䅅䅤穂䙁䄸杤硁䍁䅁䅋祁䍁䅫杌㑂䝁䅷督瑂䙁䄰兓畂䝁䅍睢瑂䝁䅕睘呂䡁䅑兙あ䝁䅕兢求䝁䄴䅤湁䍁䅅䅊䑂䍁䅑免硁䑁䅯䅊䑂䍁䅑免㑁䑁䅁䅁流杂䅁䅐䅁䙁䅑睢あ䝁䅅䅢杁䙁䅁杣求䝁䅙党祂䡁䅉党歂䍁䅁兒硂䡁䅕兡あ䡁䅫䅉潁䍁䅑䅍睁䑁䅁克䅁䝁䄴䅁⭂䅁䅁睊扂䙁䅍䅕䡂䙁䄸睑療䝁䄰䅣桂䝁䄴入時䕁䅳党㕂䙁䅍䅤桂䡁䅑督時䡁䅙免杁䍁䅧杍灁䍁䄴䅥獂䡁䅍兢摂䕁䅫杢橂䝁䄸兢求䙁䄸睕あ䝁䅅䅤求䝁䄰党畂䡁䅑睊桁䍁䅑兒歁䑁䅙杏歁䙁䅁䅊㉁䅁䅁兊䅙䝁䅯䅁湁䙁䅳睕兂䕁䅣睘䑂䝁䄸兢睂䝁䅅杢㕂䙁䄸睓求䡁䅫睕あ䝁䅅䅤穂䙁䄸杤硁䍁䅁䅋祁䍁䅫杌㑂䝁䅷督瑂䙁䄰睓求䡁䅫睘呂䡁䅑兙あ䡁䅍睊桁䍁䅑村歁䑁䅅䅍㉁䅁䅁䅇䅙䑁䅑䅁噂䝁䄴督求䝁䅍兤祂䝁䅕䅚杁䕁䅑党楂䡁䅑䅉潁䙁䅉党睂䝁䄸杣あ䝁䅕䅚灁䅁䅁睎䅅䡁䅑䅁湁䙁䅳睕兂䕁䅣睘䑂䝁䄸兢睂䝁䅅杢㕂䙁䄸睓求䡁䅫睕あ䝁䅅䅤穂䙁䄸杤硁䍁䅁䅋祁䍁䅫杌㑂䝁䅷督瑂䙁䄰睓求䡁䅫睘呂䡁䅑兙あ䡁䅍睊桁䍁䅑兒歁䑁䅉兎㙁䍁䅑杓歁䑁䅉兎䅁䉁䝅䅁敂䅁䅁睗呂䙁䅁睒時䕁䅍睢瑂䡁䅁兙畂䡁䅫睘䱂䝁䅕入呂䡁䅑兙あ䡁䅍睘㉂䑁䅉杌㑂䝁䅷督瑂䙁䄰睓求䡁䅫睘呂䡁䅑兙あ䡁䅍光歁䕁䅉䅊硁䑁䅁李䅁偁䡉䅁潂䅁䅁睊扂䙁䅍䅕䡂䙁䄸睑療䝁䄰䅣桂䝁䄴入時䕁䅳党㕂䙁䅍䅤桂䡁䅑督時䡁䅙免杁䍁䅧杍灁䍁䄴䅥獂䡁䅍兢摂䕁䅳党㕂䙁䄸睕あ䝁䅅䅤穂䍁䅣光歁䕁䅉䅊祁䑁䅕䅁允杂䅁䅡䅁䍁䅣睗呂䙁䅁睒時䕁䅍睢瑂䡁䅁兙畂䡁䅫睘䱂䝁䅕入呂䡁䅑兙あ䡁䅍睘㉂䑁䅅䅉潁䑁䅉克畁䡁䅧䅢穂䝁䄰兘䱂䝁䅕入時䙁䅍䅤桂䡁䅑督湁䍁䅅䅊䍂䍁䅑杍㉁䅁䅁䅆䅙䝁䅧䅁湁䙁䅳睕兂䕁䅣睘䑂䝁䄸兢睂䝁䅅杢㕂䙁䄸睓求䡁䅫睕あ䝁䅅䅤穂䙁䄸杤硁䍁䅁䅋祁䍁䅫杌㑂䝁䅷督瑂䙁䄰睓求䡁䅫睘呂䡁䅑兙あ䡁䅍睊桁䍁䅑村歁䑁䅙杍䅁䉁䝷䅁㑂䅁䅁睊扂䙁䅍䅕䡂䙁䄸睑療䝁䄰䅣桂䝁䄴入時䕁䅳党㕂䙁䅍䅤桂䡁䅑督時䡁䅙免杁䍁䅧杍灁䍁䄴䅥獂䡁䅍兢摂䕁䅳党㕂䙁䄸睕あ䝁䅅䅤穂䍁䅣光歁䕁䅍䅊硁䑁䅁兏㙁䍁䅑睑歁䑁䅅免ㅁ䅁䅁杇䅙䝁䅯䅁扂䕁䄰兓時䕁䅍睢瑂䡁䅁兙畂䡁䅫睘䱂䝁䅕入呂䡁䅑兙あ䡁䅍睘㉂䑁䅅杌㑂䝁䅷督瑂䙁䄰兓畂䝁䅍睢瑂䝁䅕睘呂䡁䅑兙あ䝁䅕兢求䝁䄴䅤桁䍁䅑睑歁䑁䅅睎㕁䅁䅁睯䅑䥁䅉䅁湁䙁䅳睕兂䕁䅣睘䑂䝁䄸兢睂䝁䅅杢㕂䙁䄸睓求䡁䅫睕あ䝁䅅䅤穂䙁䄸杤祁䍁䅁免畁䡁䅧䅢穂䝁䄰兘䑂䝁䅅䅣灂䡁䅑兙獂䙁䄸睕あ䡁䅉兤橂䡁䅑兤祂䝁䅕睘呂䡁䅕兢瑂䝁䅅杣㕂䍁䅣光歁䕁䅍䅊㍁䅁䅁眸䅙䡁䅑䅁湁䙁䅳睕兂䕁䅣睘䑂䝁䄸兢睂䝁䅅杢㕂䙁䄸睓求䡁䅫睕あ䝁䅅䅤穂䙁䄸杤硁䍁䅁䅋祁䍁䅫杌㑂䝁䅷督瑂䙁䄰睓求䡁䅫睘呂䡁䅑兙あ䡁䅍睊桁䍁䅑睑歁䑁䅙兎㙁䍁䅑睑歁䑁䅣免䅁䉁䜴䅁䥃䅁䅁睊扂䙁䅍䅕䡂䙁䄸睑療䝁䄰䅣桂䝁䄴入時䕁䅳党㕂䙁䅍䅤桂䡁䅑督時䡁䅙杍杁䑁䅅杌㑂䝁䅷督瑂䙁䄰睑桂䡁䅁兡あ䝁䅅䅢時䙁䅍䅤祂䡁䅕睙あ䡁䅕杣求䙁䄸䅉䕂䝁䅕䅤桂䝁䅫䅢穂䍁䅁睊桁䍁䅑兓歁䑁䅅杍䅁䅁䠸䅁獂䅁䅁睗乂䕁䅫睘䑂䝁䄸兢睂䝁䅅杢㕂䙁䄸睓求䡁䅫睕あ䝁䅅䅤穂䙁䄸杤硁䙁䄸杌㑂䝁䅷督瑂䙁䄰兓畂䝁䅍睢瑂䝁䅕睘呂䡁䅑兙あ䝁䅕兢求䝁䄴䅤桁䍁䅑睑歁䑁䅅睎㉁䅁䅁儱䅑䡁䅑䅁湁䙁䅳睕兂䕁䅣睘䑂䝁䄸兢睂䝁䅅杢㕂䙁䄸睓求䡁䅫睕あ䝁䅅䅤穂䙁䄸杤硁䍁䅁䅋祁䍁䅫杌㑂䝁䅷督瑂䙁䄰睓求䡁䅫睘呂䡁䅑兙あ䡁䅍睊桁䍁䅑䅒歁䑁䅉䅏㙁䍁䅑䅒歁䑁䅕杍䅁䉁䝙䅁卂䅁䅁䅖療䡁䅑兙獂䍁䅁䅔灂䝁䅅杙灂䝁䅷兡あ䝁䅫党穂䍁䅁兌杁䙁䅕杌呂䍁䄴䅉䡂䕁䅅兑兂䍁䅁䅋卂䝁䅕䅣療䡁䅉䅤求䝁䅑克䅁䵁䍕䅁あ䅁䅁睊扂䙁䅍䅕䡂䙁䄸睑療䝁䄰䅣桂䝁䄴入時䕁䅳党㕂䙁䅍䅤桂䡁䅑督時䡁䅙免杁䍁䅧杍灁䍁䄴䅥獂䡁䅍兢摂䕁䅳党㕂䙁䄸睕あ䝁䅅䅤穂䍁䅣光歁䕁䅕䅊祁䑁䅙杏歁䕁䅯䅊祁䑁䅙䅁呁杂䅁䅂䅁䑁䅅䅁䉃杂䅁䅡䅁䍁䅣睗呂䙁䅁睒時䕁䅍睢瑂䡁䅁兙畂䡁䅫睘䱂䝁䅕入呂䡁䅑兙あ䡁䅍睘㉂䑁䅅䅉潁䑁䅉克畁䡁䅧䅢穂䝁䄰兘䱂䝁䅕入時䙁䅍䅤桂䡁䅑督湁䍁䅅䅊䙂䍁䅑李祁䅁䅁先䅙䵁䅙䅁偂䡁䅁䅤灂䝁䄸杢穂䑁䅯䅉䑂䡁䅕杣祂䑁䄰兖呂䕁䅑䅌杁䕁䄰兙湂䑁䄰兔灂䝁䅷䅢灂䝁䄸杢穂䍁䅷睑療䝁䄴杤乂䝁䅕䅤潂䝁䄸䅚㥁䕁䄰杕呂䡁䅁睢あ䍁䅷䅉佂䕁䅅児佂䕁䅅䅌杁䙁䅑党祂䝁䄰児求䝁䄴兌噂䙁䅍䅌䝂䝁䅫䅢灂䝁䄴睚坂䝁䅕杣㥁䕁䄸杣灂䝁䅣兡畂䝁䅅䅢獂䡁䅫䅉卂䝁䅕䅣療䡁䅉䅤求䝁䅑䅁浃睂䅁䅤䅁䍁䅣睗呂䙁䅁睒時䕁䅍睢瑂䡁䅁兙畂䡁䅫睘䱂䝁䅕入呂䡁䅑兙あ䡁䅍睘㉂䑁䅅䅉潁䑁䅉克畁䡁䅧䅢穂䝁䄰兘䱂䝁䅕入時䙁䅍䅤桂䡁䅑督湁䍁䅅䅊乂䍁䅑杍ㅁ䑁䅯䅊偂䍁䅑杍ㅁ䅁䅁兆䅙䝁䅑䅁扂䕁䅳党㕂䙁䅍䅤桂䡁䅑督時䡁䅑党穂䡁䅑杚灂䝁䅷党畁䡁䅧䅢穂䝁䄰兘䑂䝁䅅䅣灂䡁䅑兙獂䝁䅫来桂䡁䅑兡療䝁䄴光歁䕁䅑䅊㕁䑁䅯䅊䕂䍁䅑杍㑁䅁䅁兺䅁䑁䅑䅁䩂䙁䅅睘佂䕁䅫睘佂䕁䄸杕乂䙁䄸杍婂䙁䅉睘䉂䕁䄴杔時䕁䅣杕偂䙁䅣䅖䥂䅁䅁兑䅉䝁䅧䅁湁䙁䅳睕兂䕁䅣睘䑂䝁䄸兢睂䝁䅅杢㕂䙁䄸睓求䡁䅫睕あ䝁䅅䅤穂䙁䄸杤硁䍁䅁䅋祁䍁䅫杌㑂䝁䅷督瑂䙁䄰睓求䡁䅫睘呂䡁䅑兙あ䡁䅍睊桁䍁䅑睕歁䑁䅕兎䅁䍁䝁䅁あ䅁䅁睊扂䙁䅍䅕䡂䙁䄸睑療䝁䄰䅣桂䝁䄴入時䕁䅳党㕂䙁䅍䅤桂䡁䅑督時䡁䅙免杁䍁䅧杍灁䍁䄴䅥獂䡁䅍兢摂䕁䅳党㕂䙁䄸睕あ䝁䅅䅤穂䍁䅣光歁䙁䅍䅊ㅁ䑁䅧杏歁䙁䅍䅊㉁䑁䅅䅁桁杂䅁䅙䅁䙁䅳睓求䡁䅫睕あ䝁䅅䅤穂䙁䄸䅤求䡁䅍䅤浂䝁䅫䅢求䍁䄴䅥獂䡁䅍兢摂䕁䅳党㕂䙁䄸睕あ䝁䅅䅤穂䍁䅅䅊䑂䍁䅑免睁䑁䅁杏歁䕁䅍䅊硁䑁䅁兎䅁䩁䅉䅁あ䅁䅁睊扂䙁䅍䅕䡂䙁䄸睑療䝁䄰䅣桂䝁䄴入時䕁䅳党㕂䙁䅍䅤桂䡁䅑督時䡁䅙免杁䍁䅧杍灁䍁䄴䅥獂䡁䅍兢摂䕁䅳党㕂䙁䄸睕あ䝁䅅䅤穂䍁䅣光歁䙁䅙䅊ㅁ䑁䅣杏歁䙁䅣䅊ㅁ䑁䅣䅁楁杂䅁䅥䅁䙁䅳睕兂䕁䅣睘䑂䝁䄸兢睂䝁䅅杢㕂䙁䄸睓求䡁䅫睕あ䝁䅅䅤穂䙁䄸杤祁䍁䄴䅥獂䡁䅍兢摂䕁䅫杢橂䝁䄸兢求䙁䄸睕あ䝁䅅䅤求䝁䄰党畂䡁䅑光歁䕁䅍䅊硁䑁䅅杏歁䕁䅍䅊硁䑁䅫免䅁佁䡑䅁䵂䅁䅁兒㑂䡁䅁䅢療䡁䅉兙あ䝁䅫睢畂䍁䄸䅒祂䝁䅫䅢獂䝁䅫杢湂䍁䅁睑療䡁䅍䅤穂䍁䅁䅋卂䝁䅕䅣療䡁䅉䅤求䝁䅑克䅁䭁䅫䅁㡂䅁䅁睊扂䙁䅍䅕䡂䙁䄸睑療䝁䄰䅣桂䝁䄴入時䕁䅳党㕂䙁䅍䅤桂䡁䅑督時䡁䅙免杁䍁䅧杍灁䍁䄴䅥獂䡁䅍兢摂䙁䅁党畂䡁䅍兡療䝁䄴兌偂䙁䅁兒䍂䍁䅣光歁䕁䅍䅊硁䑁䅅杏歁䕁䅍䅊ㅁ䑁䅣䅍䅁䕁䜴䅁佂䅁䅁䅔求䡁䅙党祂䝁䅕䅚杁䕁䅙杣求䝁䅕䅉䑂䝁䅅督潂䍁䅁杒獂䝁䄸睤獁䍁䅁睍杁䙁䅫杣畁䍁䅁睑䉂䕁䅣杕杁䍁䅧兊灁䅁䅁䅨䅉䡁䅙䅁湁䙁䅳睕兂䕁䅣睘䑂䝁䄸兢睂䝁䅅杢㕂䙁䄸睓求䡁䅫睕あ䝁䅅䅤穂䙁䄸杤硁䍁䅁䅋祁䍁䅫杌㑂䝁䅷督瑂䙁䄰䅕求䝁䄴督灂䝁䄸杢瑁䕁䄸䅕䙂䕁䅉睊桁䍁䅑䅒歁䑁䅣杏歁䕁䅫䅊㍁䅁䅁睔䅙䡁䅁䅁湁䙁䅳睕兂䕁䅣睘䑂䝁䄸兢睂䝁䅅杢㕂䙁䄸睓求䡁䅫睕あ䝁䅅䅤穂䙁䄸杤硁䍁䅁䅋祁䍁䅫杌㑂䝁䅷督瑂䙁䄰杕桂䡁䅑兡療䡁䅍睊桁䍁䅑睑歁䑁䅅免㙁䍁䅑睑歁䑁䅅兎祁䅁䅁杒䅙䝁䅑䅁湁䙁䅳睕兂䕁䅣睘䑂䝁䄸兢睂䝁䅅杢㕂䙁䄸睓求䡁䅫睕あ䝁䅅䅤穂䙁䄸杤祁䍁䅁免畁䡁䅧䅢穂䝁䄰兘䱂䝁䅕入時䙁䅍䅤桂䡁䅑督湁䍁䅅䅊䍂䍁䅑李祁䅁䅁睺䅙䉁䅙䅁䩂䙁䅅睘䑂䕁䄸杔坂䕁䅕杕啂䅁䅁䅈䅅䝁䅷䅁湁䙁䅳睕兂䕁䅣睘䑂䝁䄸兢睂䝁䅅杢㕂䙁䄸睓求䡁䅫睕あ䝁䅅䅤穂䙁䄸杤硁䍁䅁䅋祁䍁䅫杌㑂䝁䅷督瑂䙁䄰睕ㅂ䡁䅁䅣獂䝁䅕兢求䝁䄴䅤桂䝁䅷睊桁䍁䅑睑歁䑁䅙䅁䥂杂䅁杇䅁䑁䅷材睁䑁䅫睌祁䑁䅅睌祁䑁䅁杍睁䅁䅁䅰䅕䥁䅧䅁湁䙁䅳睕兂䕁䅣睘䑂䝁䄸兢睂䝁䅅杢㕂䙁䄸睓求䡁䅫睕あ䝁䅅䅤穂䙁䄸杤祁䍁䅁免畁䡁䅧䅢穂䝁䄰兘䑂䝁䅅䅣灂䡁䅑兙獂䙁䄸睕あ䡁䅉兤橂䡁䅑兤祂䝁䅕睘杁䕁䅑党あ䝁䅅兡獂䡁䅍䅉湁䍁䅅䅊䭂䍁䅑免祁䅁䅁䅅䅣䑁䅷䅁偂䡁䅁䅤灂䝁䄸杢穂䑁䅯睕あ䝁䅅䅤灂䡁䅍䅤灂䝁䅍児呂䙁䅑䅒䙂䙁䅙䅌佂䕁䅅児佂䕁䅅䅁剄睂䅁䅡䅁䙁䅳睕兂䕁䅣睘䑂䝁䄸兢睂䝁䅅杢㕂䙁䄸睓求䡁䅫睕あ䝁䅅䅤穂䙁䄸杤硁䍁䄴䅥獂䡁䅍兢摂䕁䅳党㕂䙁䄸睕あ䝁䅅䅤穂䍁䅅䅊䑂䍁䅑杍㑁䑁䅯䅊䑂䍁䅑兎祁䅁䅁朰䅕䥁䅧䅁湁䙁䅳睕兂䕁䅣睘䑂䝁䄸兢睂䝁䅅杢㕂䙁䄸睓求䡁䅫睕あ䝁䅅䅤穂䙁䄸杤祁䍁䅁免畁䡁䅧䅢穂䝁䄰兘䑂䝁䅅䅣灂䡁䅑兙獂䙁䄸睕あ䡁䅉兤橂䡁䅑兤祂䝁䅕睘杁䕁䅑党あ䝁䅅兡獂䡁䅍䅉湁䍁䅅䅊䱂䍁䅑䅎ぁ䅁䅁先䅣䡁䅙䅁湁䙁䅳睕兂䕁䅣睘䑂䝁䄸兢睂䝁䅅杢㕂䙁䄸睓求䡁䅫睕あ䝁䅅䅤穂䙁䄸杤硁䍁䅁䅋祁䍁䅫杌㑂䝁䅷督瑂䙁䄰睕ㅂ䡁䅁䅣獂䝁䅕兢求䝁䄴䅤桂䝁䅷睊桁䍁䅑䅒歁䑁䅙杏歁䕁䅫䅊㉁䅁䅁兓䅙䥁䅧䅁湁䙁䅳睕兂䕁䅣睘䑂䝁䄸兢睂䝁䅅杢㕂䙁䄸睓求䡁䅫睕あ䝁䅅䅤穂䙁䄸杤祁䍁䅁免畁䡁䅧䅢穂䝁䄰兘䑂䝁䅅䅣灂䡁䅑兙獂䙁䄸睕あ䡁䅉兤橂䡁䅑兤祂䝁䅕睘杁䕁䅑党あ䝁䅅兡獂䡁䅍䅉湁䍁䅅䅊䥂䍁䅑免祁䅁䅁䅄䅣䍁䅁䅁䩂䙁䅅睘䕂䕁䅍睕時䙁䅍兒䑂䙁䅕杕䩂䙁䅑兗䅁䥁䝫䅁允䅁䅁杍睁䑁䅉李䝂䙁䅅睍䅁䱁䥧䅁睂䅁䅁睊扂䙁䅍䅕䡂䙁䄸睑療䝁䄰䅣桂䝁䄴入時䕁䅳党㕂䙁䅍䅤桂䡁䅑督時䡁䅙杍杁䑁䅅杌㑂䝁䅷督瑂䙁䄰睓求䡁䅫睘呂䡁䅑兙あ䡁䅍睊桁䍁䅑睑歁䑁䅙兎㙁䍁䅑睑歁䑁䅣免䅁乁䝅䅁㉂䅁䅁睊扂䙁䅍䅕䡂䙁䄸睑療䝁䄰䅣桂䝁䄴入時䕁䅳党㕂䙁䅍䅤桂䡁䅑督時䡁䅙免杁䍁䅧杍灁䍁䄴䅥獂䡁䅍兢摂䙁䅍兤睂䡁䅁䅢求䝁䄰党畂䡁䅑兙獂䍁䅣光歁䕁䅑䅊㍁䑁䅯䅊䩂䍁䅑睎䅁䕁䝳䅁慁䅁䅁兓剂䙁䄸䅕䙂䙁䅉兓偂䕁䅑兑啂䕁䅕䅁㡂杂䅁杅䅁䙁䅍党橂䡁䅕杣求䝁䅑睐䅁䩁䜸䅁畂䅁䅁睊扂䙁䅍䅕䡂䙁䄸睑療䝁䄰䅣桂䝁䄴入時䕁䅳党㕂䙁䅍䅤桂䡁䅑督時䡁䅙免畁䡁䅧䅢穂䝁䄰兘兂䝁䅕杢穂䝁䅫睢畂䍁䄰睔兂䕁䅕村湁䍁䅅䅊䕂䍁䅑李㙁䍁䅑兓歁䑁䅙䅁乁杂䅁杓䅁䕁䅍兙睂䍁䄴䅉䵂䝁䅕兙穂䝁䅕䅉兂䝁䅅入瑂䝁䅕杢あ䍁䅁䅒ㅂ䝁䅕䅉牁䑁䅕䅉潁䙁䅉党睂䝁䄸杣あ䝁䅕䅚灁䅁䅁䅳䅅䝁䄴䅁湁䙁䅳睕兂䕁䅣睘䑂䝁䄸兢睂䝁䅅杢㕂䙁䄸睓求䡁䅫睕あ䝁䅅䅤穂䙁䄸杤硁䍁䄴䅥獂䡁䅍兢摂䙁䅁党畂䡁䅍兡療䝁䄴兌偂䙁䅁兒䍂䍁䅣光歁䕁䅑䅊㍁䑁䅯䅊䩂䍁䅑睎䅁䅁䜸䅁浂䅁䅁睗乂䕁䅫睘䑂䝁䄸兢睂䝁䅅杢㕂䙁䄸睓求䡁䅫睕あ䝁䅅䅤穂䙁䄸杤硁䍁䄴䅥獂䡁䅍兢摂䕁䅳党㕂䙁䄸睕あ䝁䅅䅤穂䍁䅅䅊䙂䍁䅑杍穁䑁䅯䅊䵂䍁䅑杍穁䅁䅁睤䅑䕁䅷䅁偂䡁䅁䅤灂䝁䄸杢穂䑁䅯䅉䑂䡁䅕杣祂䑁䄰兖呂䕁䅑䅌䑂䝁䄸杢㉂䕁䄰党あ䝁䅧睢歂䑁䄰睕獁䍁䅁杔䉂䑁䄰杔䉂䅁䅁朱䅣䉁䅧䅁䩂䙁䅅睘呂䙁䅕村時䕁䅑兒䍂䙁䅑䅁坁允䅁杏䅁䕁䅫兕時䕁䅕兑卂䕁䄴兓佂䕁䅣睘䑂䕁䄸睘穁䙁䅫杕時䕁䅅杔佂䙁䄸睒卂䕁䄸睖啂䕁䅧䅁牂杁䅁䅥䅁䙁䅳睓求䡁䅫睕あ䝁䅅䅤穂䙁䄸䅤求䡁䅍䅤浂䝁䅫䅢求䍁䄴䅥獂䡁䅍兢摂䕁䅍兙睂䝁䅫䅤桂䝁䅷睘呂䡁䅑杣ㅂ䝁䅍䅤ㅂ䡁䅉党時䙁䅍兤瑂䝁䄰兙祂䡁䅫光歁䕁䅣䅊㕁䑁䅯䅊偂䍁䅑兏䅁䡁䉫䅁㙂䅁䅁睊扂䙁䅍䅕䡂䙁䄸睑療䝁䄰䅣桂䝁䄴入時䕁䅳党㕂䙁䅍䅤桂䡁䅑督時䡁䅙杍杁䑁䅅杌㑂䝁䅷督瑂䙁䄰村桂䝁䅷兙畂䝁䅍党時䙁䅍䅡求䝁䅕䅤湁䍁䅅䅊䑂䍁䅑免硁䑁䅯䅊䑂䍁䅑杍睁䑁䅅䅁摄杂䅁䅥䅁䙁䅳睓求䡁䅫睕あ䝁䅅䅤穂䙁䄸䅤求䡁䅍䅤浂䝁䅫䅢求䍁䄴䅥獂䡁䅍兢摂䕁䅍兙睂䝁䅫䅤桂䝁䅷睘呂䡁䅑杣ㅂ䝁䅍䅤ㅂ䡁䅉党時䙁䅍兤瑂䝁䄰兙祂䡁䅫光歁䕁䅙䅊ぁ䑁䅯䅊佂䍁䅑䅎䅁佁䅷䅁䵃䅁䅁睊扂䙁䅍䅕䡂䙁䄸睑療䝁䄰䅣桂䝁䄴入時䕁䅳党㕂䙁䅍䅤桂䡁䅑督時䡁䅙杍杁䑁䅅杌㑂䝁䅷督瑂䙁䄰睑桂䡁䅁兡あ䝁䅅䅢時䙁䅍䅤祂䡁䅕睙あ䡁䅕杣求䙁䄸睕ㅂ䝁䄰兢桂䡁䅉入湁䍁䅅䅊䙂䍁䅑睎㙁䍁䅑睔歁䑁䅣䅁祄杂䅁来䅁䕁䅍䅡桂䝁䄴睚求䡁䅍䅉灂䝁䄴䅉噂䝁䄴杣求䝁䅍睢湂䍁䄴䅉啂䝁䅅䅥杁䕁䅉党畂䝁䅕杚灂䡁䅑䅉㍂䍁䄸兡畂䍁䅁免杁䙁䅫党桂䡁䅉䅉瑁䍁䅁兔桂䡁䅧䅉潁䙁䅉党睂䝁䄸杣あ䝁䅕䅚灁䅁䅁儸䅉䍁䅷䅁䩂䙁䅅睘啂䕁䅅䅗時䕁䅉兒佂䕁䅕杒䩂䙁䅑睘䑂䕁䅙睘穁䙁䅫杕䅁偁䍧䅁⭁䅁䅁兓剂䙁䄸䅖偂䙁䅑兑䵂䙁䄸兑呂䙁䅍兒啂䙁䅍睘祁䙁䅫杕時䕁䅅杔佂䙁䄸睒卂䕁䄸睖啂䕁䅧䅁噂杁䅁杗䅁䕁䄸䅣あ䝁䅫睢畂䡁䅍杏杁䕁䅙兡獂䝁䅫杢湂䙁䅙党祂䑁䄰睔祂䝁䅫睚灂䝁䄴兙獂䝁䅷入杁䙁䅉党睂䝁䄸杣あ䝁䅕䅚獁䕁䄴兑㥁䕁䄴兑䅁䱁䡷䅁煂䅁䅁睊扂䙁䅍䅕䡂䙁䄸睑療䝁䄰䅣桂䝁䄴入時䕁䅳党㕂䙁䅍䅤桂䡁䅑督時䡁䅙杍杁䑁䅅杌㑂䝁䅷督瑂䙁䄰村桂䝁䅷兙畂䝁䅍党時䙁䅍䅡求䝁䅕䅤湁䍁䅅䅊䑂䍁䅑李䅁乁䝳䅁捃䅁䅁睊扂䕁䅍睢睂䡁䅫䅉療䝁䅙䅉呂䙁䅁睒時䕁䅍睢瑂䡁䅁兙畂䡁䅫睘䱂䝁䅕入呂䡁䅑兙あ䡁䅍睘㉂䑁䅉睘畂䝁䅕睤畁䡁䅧䅢穂䝁䄰兘䑂䝁䅅䅣灂䡁䅑兙獂䙁䄸睕あ䡁䅉兤橂䡁䅑兤祂䝁䅕睘杁䕁䅑党あ䝁䅅兡獂䡁䅍䅉湁䍁䅅䅊䩂䍁䅑免祁䅁䅁杣䅣䕁䅁䅁䑂䝁䄸兢瑂䝁䄸杢杁䕁䅕兣ㅂ䝁䅫䅤㕂䍁䅷䅉硁䍁䅁兗祂䍁䄴䅉䡂䡁䅉睢㍂䡁䅑䅡杁䍁䅧兊灁䅁䅁䅍䅉䑁䅉䅁䭂䡁䅉杌杁䙁䅍兤楂䍁䄴䅉䕂䝁䅕杙あ䍁䅁䅋卂䝁䅕䅣療䡁䅉䅤求䝁䅑克䅁䉁䉍䅁あ䅁䅁睊扂䙁䅍䅕䡂䙁䄸睑療䝁䄰䅣桂䝁䄴入時䕁䅳党㕂䙁䅍䅤桂䡁䅑督時䡁䅙杍杁䑁䅅杌㑂䝁䅷督瑂䙁䄰村桂䝁䅷兙畂䝁䅍党時䙁䅍䅡求䝁䅕䅤湁䍁䅅䅊䙂䍁䅑睎㙁䍁䅑䅕歁䑁䅣䅁敄杂䅁杌䅁䕁䅫兕時䙁䅉兒呂䙁䅑兑啂䕁䅕兔䙂䕁䄴䅖時䙁䅑兗兂䕁䅕睘䍂䙁䅍䅁煁睁䅁䅥䅁䍁䅣睗呂䙁䅁睒時䕁䅍睢瑂䡁䅁兙畂䡁䅫睘䱂䝁䅕入呂䡁䅑兙あ䡁䅍睘㉂䑁䅉䅉硁䍁䄴䅥獂䡁䅍兢摂䙁䅁党畂䡁䅍兡療䝁䄴兌偂䙁䅁兒䍂䍁䅣光歁䕁䅍䅊硁䑁䅅杏歁䕁䅍䅊ㅁ䑁䅣兎䅁䅁䡅䅁䥃䅁䅁睊扂䙁䅍䅕䡂䙁䄸睑療䝁䄰䅣桂䝁䄴入時䕁䅳党㕂䙁䅍䅤桂䡁䅑督時䡁䅙杍杁䑁䅅杌㑂䝁䅷督瑂䙁䄰睑桂䡁䅁兡あ䝁䅅䅢時䙁䅍䅤祂䡁䅕睙あ䡁䅕杣求䙁䄸䅉䕂䝁䅕䅤桂䝁䅫䅢穂䍁䅁睊桁䍁䅑兑䉂䍁䅑兎䅁䅁䡕䅁䥃䅁䅁睊扂䙁䅍䅕䡂䙁䄸睑療䝁䄰䅣桂䝁䄴入時䕁䅳党㕂䙁䅍䅤桂䡁䅑督時䡁䅙杍杁䑁䅅杌㑂䝁䅷督瑂䙁䄰睑桂䡁䅁兡あ䝁䅅䅢時䙁䅍䅤祂䡁䅕睙あ䡁䅕杣求䙁䄸䅉䕂䝁䅕䅤桂䝁䅫䅢穂䍁䅁睊桁䍁䅑兒歁䑁䅑䅎䅁䉁䡣䅁慂䅁䅁睗呂䙁䅁睒時䕁䅍睢瑂䡁䅁兙畂䡁䅫睘䱂䝁䅕入呂䡁䅑兙あ䡁䅍睘㉂䑁䅅杌㑂䝁䅷督瑂䙁䄰睑桂䡁䅍䅡時䕁䅙䅢療䡁䅣光歁䕁䅍䅊㉁䅁䅁䄷䅕䥁䅑䅁湁䙁䅳睑療䡁䅁入杁䝁䄸杚杁䙁䅍䅕䡂䙁䄸睑療䝁䄰䅣桂䝁䄴入時䕁䅳党㕂䙁䅍䅤桂䡁䅑督時䡁䅙杍時䝁䄴党㍂䍁䄴䅥獂䡁䅍兢摂䕁䅳党㕂䙁䄸睕あ䝁䅅䅤穂䍁䅣光歁䕁䄴䅊祁䑁䅙杏歁䙁䅁䅊祁䑁䅙䅁元睂䅁䅩䅁䍁䅣睗呂䙁䅁睒時䕁䅍睢瑂䡁䅁兙畂䡁䅫睘䱂䝁䅕入呂䡁䅑兙あ䡁䅍睘㉂䑁䅉䅉硁䍁䄴䅥獂䡁䅍兢摂䕁䅍兙睂䝁䅫䅤桂䝁䅷睘呂䡁䅑杣ㅂ䝁䅍䅤ㅂ䡁䅉党時䍁䅁䅒求䡁䅑兙灂䝁䅷督杁䍁䅣光歁䕁䅅兑歁䑁䅙䅁呁睂䅁杈䅁䕁䅫兕時䕁䅷䅖䕂䙁䄸䅒噂䕁䅕睘䑂䙁䅫睍䅁䭁䉅䅁坁䅁䅁䅍㕁䍁䄸免㉁䍁䄸杍睁䑁䅉䅍䅁䭁䙍䅁捂䅁䅁䅔療䝁䄴睚瑁䙁䅑党祂䝁䄰䅉䕂䝁䅕杙あ䍁䅁䅋䩂䝁䄴睙獂䍁䄴䅉䑂䝁䅅䅣畁䍁䅁䅔求䝁䅅督求䡁䅍克杁䍁䅧杕求䡁䅁睢祂䡁䅑党歂䍁䅫䅁癁允䅁䅘䅁䙁䅳兔䩂䙁䄸睑療䝁䄰䅣桂䝁䄴入時䕁䅳党㕂䙁䅍䅤桂䡁䅑督時䡁䅙免時䍁䄴䅥獂䡁䅍兢摂䕁䅳党㕂䙁䄸睕あ䝁䅅䅤穂䍁䅅䅊䍂䍁䅑杍㉁䅁䅁具䅑䍁䅑䅁䩂䙁䅅睘䡂䙁䅣睘䩂䕁䄴䅖䉂䕁䄴睘䉂䕁䄰睔卂䙁䅑䅁睃䅁䅁䅩䅁䍁䅣睗呂䙁䅁睒時䕁䅍睢瑂䡁䅁兙畂䡁䅫睘䱂䝁䅕入呂䡁䅑兙あ䡁䅍睘㉂䑁䅉䅉硁䍁䄴䅥獂䡁䅍兢摂䕁䅍兙睂䝁䅫䅤桂䝁䅷睘呂䡁䅑杣ㅂ䝁䅍䅤ㅂ䡁䅉党時䍁䅁䅒求䡁䅑兙灂䝁䅷督杁䍁䅣光歁䕁䅅兑歁䑁䅣䅁佁睂䅁䅩䅁䍁䅣睗呂䙁䅁睒時䕁䅍睢瑂䡁䅁兙畂䡁䅫睘䱂䝁䅕入呂䡁䅑兙あ䡁䅍睘㉂䑁䅉䅉硁䍁䄴䅥獂䡁䅍兢摂䕁䅍兙睂䝁䅫䅤桂䝁䅷睘呂䡁䅑杣ㅂ䝁䅍䅤ㅂ䡁䅉党時䍁䅁䅒求䡁䅑兙灂䝁䅷督杁䍁䅣光歁䕁䅉䅊㍁䑁䅙䅁敁睂䅁杋䅁䙁䅉党あ䡁䅕杣畂䍁䅁睢畂䍁䅁兒硂䡁䅕兡あ䡁䅫䅉潁䍁䅕克䅁䅁䍁䅁䥃䅁䅁睊扂䙁䅍䅕䡂䙁䄸睑療䝁䄰䅣桂䝁䄴入時䕁䅳党㕂䙁䅍䅤桂䡁䅑督時䡁䅙杍杁䑁䅅杌㑂䝁䅷督瑂䙁䄰睑桂䡁䅁兡あ䝁䅅䅢時䙁䅍䅤祂䡁䅕睙あ䡁䅕杣求䙁䄸䅉䕂䝁䅕䅤桂䝁䅫䅢穂䍁䅁睊桁䍁䅑睑歁䑁䅅杍䅁䅁䡧䅁䥃䅁䅁睊扂䙁䅍䅕䡂䙁䄸睑療䝁䄰䅣桂䝁䄴入時䕁䅳党㕂䙁䅍䅤桂䡁䅑督時䡁䅙杍杁䑁䅅杌㑂䝁䅷督瑂䙁䄰睑桂䡁䅁兡あ䝁䅅䅢時䙁䅍䅤祂䡁䅕睙あ䡁䅕杣求䙁䄸䅉䕂䝁䅕䅤桂䝁䅫䅢穂䍁䅁睊桁䍁䅑䅒歁䑁䅅杍䅁䅁䡣䅁歃䅁䅁睊扂䕁䅍睢睂䡁䅫䅉療䝁䅙䅉呂䙁䅁睒時䕁䅍睢瑂䡁䅁兙畂䡁䅫睘䱂䝁䅕入呂䡁䅑兙あ䡁䅍睘㉂䑁䅉睘畂䝁䅕睤畁䡁䅧䅢穂䝁䄰兘䑂䝁䅅䅣灂䡁䅑兙獂䙁䄸睕あ䡁䅉兤橂䡁䅑兤祂䝁䅕睘呂䡁䅕兢瑂䝁䅅杣㕂䍁䅣光歁䕁䅙䅊硁䑁䅁杏歁䙁䅁䅊硁䑁䅁䅁扂睂䅁䅩䅁䍁䅣睗呂䙁䅁睒時䕁䅍睢瑂䡁䅁兙畂䡁䅫睘䱂䝁䅕入呂䡁䅑兙あ䡁䅍睘㉂䑁䅉䅉硁䍁䄴䅥獂䡁䅍兢摂䕁䅍兙睂䝁䅫䅤桂䝁䅷睘呂䡁䅑杣ㅂ䝁䅍䅤ㅂ䡁䅉党時䍁䅁䅒求䡁䅑兙灂䝁䅷督杁䍁䅣光歁䕁䅑䅊ぁ䑁䅑䅁坁睂䅁䅩䅁䍁䅣睗呂䙁䅁睒時䕁䅍睢瑂䡁䅁兙畂䡁䅫睘䱂䝁䅕入呂䡁䅑兙あ䡁䅍睘㉂䑁䅉䅉硁䍁䄴䅥獂䡁䅍兢摂䕁䅍兙睂䝁䅫䅤桂䝁䅷睘呂䡁䅑杣ㅂ䝁䅍䅤ㅂ䡁䅉党時䍁䅁䅒求䡁䅑兙灂䝁䅷督杁䍁䅣光歁䕁䅕䅊㍁䑁䅙䅁杁睂䅁䅚䅁䙁䅳兔䩂䙁䄸睓求䡁䅫睕あ䝁䅅䅤穂䙁䄸杤硁䍁䄴䅥獂䡁䅍兢摂䕁䅫杢橂䝁䄸兢求䙁䄸睕あ䝁䅅䅤求䝁䄰党畂䡁䅑光歁䕁䅍䅊㕁䑁䅯䅊䑂䍁䅑免㉁䑁䅙䅁楄睁䅁䅣䅁䍁䅣睗呂䙁䅁睒時䕁䅍睢瑂䡁䅁兙畂䡁䅫睘䱂䝁䅕入呂䡁䅑兙あ䡁䅍睘㉂䑁䅉䅉硁䍁䄴䅥獂䡁䅍兢摂䕁䅳党㕂䙁䄸睕あ䝁䅅䅤穂䍁䅣光歁䙁䅍䅊ㅁ䑁䅧杏歁䙁䅍䅊㉁䑁䅅䅁䥄杂䅁䅢䅁䙁䅳兔䩂䙁䄸睑療䝁䄰䅣桂䝁䄴入時䕁䅳党㕂䙁䅍䅤桂䡁䅑督時䡁䅙免偂䝁䅷䅚畁䡁䅧䅢穂䝁䄰兘䱂䝁䅕入時䙁䅍䅤桂䡁䅑督桁䍁䅑杓歁䑁䅉睍㙁䍁䅑䅔歁䑁䅉睍䅁䡁䔰䅁敁䅁䅁兓剂䙁䄸杓卂䙁䄸睕噂䕁䅉睘䕂䕁䅕村啂䅁䅁杅䅅䥁䅧䅁湁䙁䅳睕兂䕁䅣睘䑂䝁䄸兢睂䝁䅅杢㕂䙁䄸睓求䡁䅫睕あ䝁䅅䅤穂䙁䄸杤祁䍁䅁免畁䡁䅧䅢穂䝁䄰兘䑂䝁䅅䅣灂䡁䅑兙獂䙁䄸睕あ䡁䅉兤橂䡁䅑兤祂䝁䅕睘杁䕁䅑党あ䝁䅅兡獂䡁䅍䅉湁䍁䅅䅊䕂䍁䅑睎㉁䅁䅁睈䅣䙁䅯䅁扂䙁䅍䅕䡂䙁䄸睑療䝁䄰䅣桂䝁䄴入時䕁䅳党㕂䙁䅍䅤桂䡁䅑督時䡁䅙杍畁䡁䅧䅢穂䝁䄰兘䑂䝁䅅督潂䙁䄸杒獂䝁䄸睤桁䍁䅑睑歁䑁䅙䅁敄睂䅁杌䅁䕁䅫兕時䕁䅙兓奂䕁䅕䅒時䙁䅉兑啂䕁䅕睘䕂䕁䅕村啂䙁䄸䅕䑂䙁䅑䅁畂允䅁䅩䅁䍁䅣睗呂䙁䅁睒時䕁䅍睢瑂䡁䅁兙畂䡁䅫睘䱂䝁䅕入呂䡁䅑兙あ䡁䅍睘㉂䑁䅉䅉硁䍁䄴䅥獂䡁䅍兢摂䕁䅍兙睂䝁䅫䅤桂䝁䅷睘呂䡁䅑杣ㅂ䝁䅍䅤ㅂ䡁䅉党時䍁䅁䅒求䡁䅑兙灂䝁䅷督杁䍁䅣光歁䕁䅙䅊硁䑁䅉䅁䱁睂䅁䅩䅁䍁䅣睗呂䙁䅁睒時䕁䅍睢瑂䡁䅁兙畂䡁䅫睘䱂䝁䅕入呂䡁䅑兙あ䡁䅍睘㉂䑁䅉䅉硁䍁䄴䅥獂䡁䅍兢摂䕁䅍兙睂䝁䅫䅤桂䝁䅷睘呂䡁䅑杣ㅂ䝁䅍䅤ㅂ䡁䅉党時䍁䅁䅒求䡁䅑兙灂䝁䅷督杁䍁䅣光歁䕁䅣䅊硁䑁䅉䅁䩁睂䅁杉䅁䕁䅕村䩂䙁䅑兑杁䕁䄰兙祂䝁䅣兡畂䍁䅁䅋汁䍁䅫䅁䝁杁䅁䅩䅁䍁䅣睗呂䙁䅁睒時䕁䅍睢瑂䡁䅁兙畂䡁䅫睘䱂䝁䅕入呂䡁䅑兙あ䡁䅍睘㉂䑁䅉䅉硁䍁䄴䅥獂䡁䅍兢摂䕁䅍兙睂䝁䅫䅤桂䝁䅷睘呂䡁䅑杣ㅂ䝁䅍䅤ㅂ䡁䅉党時䍁䅁䅒求䡁䅑兙灂䝁䅷督杁䍁䅣光歁䕁䅧䅊ぁ䑁䅑䅁慁睂䅁杊䅁䕁䅫兕時䕁䄴兒啂䙁䄸䅒䙂䕁䅉䅖時䕁䅕村䩂䙁䅑䅒䉂䅁䅁全䅅䥁䅧䅁湁䙁䅳睕兂䕁䅣睘䑂䝁䄸兢睂䝁䅅杢㕂䙁䄸睓求䡁䅫睕あ䝁䅅䅤穂䙁䄸杤祁䍁䅁免畁䡁䅧䅢穂䝁䄰兘䑂䝁䅅䅣灂䡁䅑兙獂䙁䄸睕あ䡁䅉兤橂䡁䅑兤祂䝁䅕睘杁䕁䅑党あ䝁䅅兡獂䡁䅍䅉湁䍁䅅䅊䥂䍁䅑睎㉁䅁䅁睉䅣䑁䅷䅁䩂䙁䅅睘䵂䙁䅑睘䕂䕁䅕村啂䙁䄸睑䉂䙁䅁兓啂䕁䅅䅔時䕁䅷兒䉂䙁䅍兒呂䙁䄸䅕䑂䙁䅑䅁啂允䅁䅩䅁䍁䅣睗呂䙁䅁睒時䕁䅍睢瑂䡁䅁兙畂䡁䅫睘䱂䝁䅕入呂䡁䅑兙あ䡁䅍睘㉂䑁䅉䅉硁䍁䄴䅥獂䡁䅍兢摂䕁䅍兙睂䝁䅫䅤桂䝁䅷睘呂䡁䅑杣ㅂ䝁䅍䅤ㅂ䡁䅉党時䍁䅁䅒求䡁䅑兙灂䝁䅷督杁䍁䅣光歁䕁䅫䅊ぁ䑁䅑䅁扁睂䅁䅩䅁䍁䅣睗呂䙁䅁睒時䕁䅍睢瑂䡁䅁兙畂䡁䅫睘䱂䝁䅕入呂䡁䅑兙あ䡁䅍睘㉂䑁䅉䅉硁䍁䄴䅥獂䡁䅍兢摂䕁䅍兙睂䝁䅫䅤桂䝁䅷睘呂䡁䅑杣ㅂ䝁䅍䅤ㅂ䡁䅉党時䍁䅁䅒求䡁䅑兙灂䝁䅷督杁䍁䅣光歁䕁䅫䅊㍁䑁䅙䅁乁睂䅁杕䅁䙁䅳睓求䡁䅫睕あ䝁䅅䅤穂䙁䄸䅤求䡁䅍䅤浂䝁䅫䅢求䍁䄴䅥獂䡁䅍䅥摂䙁䅍䅡求䝁䅕䅤祁䍁䅅䅊䝂䍁䅑李㙁䍁䅑睒歁䑁䅙䅁煁䅁䅁杏䅁䕁䅫兕時䕁䅷兑兂䙁䅍兒時䙁䅍䅖䉂䙁䅑兖啂䕁䅕睘䵂䕁䅫兔䩂䙁䅑兑啂䕁䅫睔佂䙁䅍䅁䅄杁䅁䅋䅁䕁䅍兤祂䡁䅉党畂䡁䅑䅉䑂䝁䄸兤睂䝁䄸杢杁䙁䅑入睂䝁䅕䅁坃杂䅁䅩䅁䍁䅣睗呂䙁䅁睒時䕁䅍睢瑂䡁䅁兙畂䡁䅫睘䱂䝁䅕入呂䡁䅑兙あ䡁䅍睘㉂䑁䅉䅉硁䍁䄴䅥獂䡁䅍兢摂䕁䅍兙睂䝁䅫䅤桂䝁䅷睘呂䡁䅑杣ㅂ䝁䅍䅤ㅂ䡁䅉党時䍁䅁䅒求䡁䅑兙灂䝁䅷督杁䍁䅣光歁䕁䅳䅊硁䑁䅉䅁剁睂䅁材䅁䕁䅫兕時䙁䅑睔啂䕁䅅䅔時䙁䅍兖䍂䙁䄸䅒䙂䕁䅉䅖時䕁䅕村䩂䙁䅑䅒䉂䙁䄸睑䉂䙁䅁兒奂䅁䅁內䅅䩁䅁䅁湁䙁䅳睕兂䕁䅣睘䑂䝁䄸兢睂䝁䅅杢㕂䙁䄸睓求䡁䅫睕あ䝁䅅䅤穂䙁䄸杤祁䍁䅁免畁䡁䅧䅢穂䝁䄰兘䑂䝁䅅䅣灂䡁䅑兙獂䙁䄸睕あ䡁䅉兤橂䡁䅑兤祂䝁䅕睘呂䡁䅕兢瑂䝁䅅杣㕂䍁䅣光歁䕁䅑䅊祁䑁䅫杏歁䕁䅑䅊㑁䑁䅁䅁ㅄ杂䅁杬䅁䕁䄸䅣あ䝁䅫睢畂䡁䅍杏杁䕁䅍兤祂䡁䅉児噂䙁䅍䅒獁䍁䅁兔桂䝁䅣児啂䝁䅧睢ㅂ䡁䅍兙畂䝁䅑督獁䕁䅍睢畂䡁䅙兔求䡁䅑䅡療䝁䅑児乂䕁䅫杣求䝁䅍睢瑂䝁䄰党畂䝁䅑党歂䍁䅷䅉佂䕁䅅児獁䍁䅁䅖求䡁䅉兢㥁䝁䅕杢瑁䙁䅕睕䅁䕁䅕䅁元䅁䅁睊扂䙁䅍䅕䡂䙁䄸睑療䝁䄰䅣桂䝁䄴入時䕁䅳党㕂䙁䅍䅤桂䡁䅑督時䡁䅙杍杁䑁䅅杌㑂䝁䅷督瑂䙁䄰睑桂䡁䅁兡あ䝁䅅䅢時䙁䅍䅤祂䡁䅕睙あ䡁䅕杣求䙁䄸睕ㅂ䝁䄰兢桂䡁䅉入湁䍁䅅䅊䝂䍁䅑免硁䑁䅯䅊兂䍁䅑免硁䅁䅁朹䅙䝁䅷䅁湁䙁䅳睕兂䕁䅣睘䑂䝁䄸兢睂䝁䅅杢㕂䙁䄸睓求䡁䅫睕あ䝁䅅䅤穂䙁䄸杤祁䍁䅁免畁䡁䅧䅢穂䝁䄰兘䑂䝁䅅䅣灂䡁䅑兙獂䝁䅫来桂䡁䅑兡療䝁䄴睊桁䍁䅑睑歁䑁䅑䅁橄杂䅁杢䅁䍁䅣睗呂䙁䅁睒時䕁䅍睢瑂䡁䅁兙畂䡁䅫睘䱂䝁䅕入呂䡁䅑兙あ䡁䅍睘㉂䑁䅉䅉硁䍁䄴䅥獂䡁䅍兢摂䕁䅍兙睂䝁䅫䅤桂䝁䅷兡㙂䝁䅅䅤灂䝁䄸杢湁䍁䅅䅊䑂䍁䅑䅎㉁䅁䅁眵䅙䡁䅧䅁扂䕁䄰兓時䕁䅳党㕂䙁䅍䅤桂䡁䅑督時䡁䅙免畁䡁䅧䅢穂䝁䄰兘䑂䝁䅅䅣灂䡁䅑兙獂䙁䄸睕あ䡁䅉兤橂䡁䅑兤祂䝁䅕睘呂䡁䅕兢瑂䝁䅅杣㕂䍁䅅䅊䑂䍁䅑免穁䑁䅯䅊䑂䍁䅑免ㅁ䑁䅁䅁䕄睁䅁材䅁䕁䅫兕時䙁䅑睔啂䕁䅅䅔時䕁䅅睕呂䕁䅕䅖呂䙁䄸兎婂䙁䅉睘䉂䕁䄴杔時䕁䅣杕偂䙁䅣䅖䥂䅁䅁睮䅉䡁䅁䅁湁䙁䅳睕兂䕁䅣睘䑂䝁䄸兢睂䝁䅅杢㕂䙁䄸睓求䡁䅫睕あ䝁䅅䅤穂䙁䄸杤祁䍁䅁免畁䡁䅧䅢穂䝁䄰兘䱂䝁䅕入時䙁䅍䅤桂䡁䅑督湁䍁䅅䅊䙂䍁䅑杍ㅁ䑁䅯䅊䭂䍁䅑杍ㅁ䅁䅁䅸䅙䩁䅁䅁湁䙁䅳睑療䡁䅁入杁䝁䄸杚杁䙁䅍䅕䡂䙁䄸睑療䝁䄰䅣桂䝁䄴入時䕁䅳党㕂䙁䅍䅤桂䡁䅑督時䡁䅙免時䕁䅙兡畂䝁䅅䅢畁䡁䅧䅢穂䝁䄰兘䑂䝁䅅䅣灂䡁䅑兙獂䝁䅫来桂䡁䅑兡療䝁䄴睊桁䍁䅑睑歁䑁䅫杏歁䕁䅍䅊祁䑁䅑䅁求䅃䅁杆䅁䕁䅫兕時䙁䅍䅖時䕁䅑兒䍂䙁䅑䅁佁允䅁杢䅁䍁䅣睗呂䙁䅁睒時䕁䅍睢瑂䡁䅁兙畂䡁䅫睘䱂䝁䅕入呂䡁䅑兙あ䡁䅍睘㉂䑁䅉䅉硁䍁䄴䅥獂䡁䅍兢摂䕁䅍兙睂䝁䅫䅤桂䝁䅷兡㙂䝁䅅䅤灂䝁䄸杢湁䍁䅅䅊䑂䍁䅑䅎㍁䅁䅁眶䅙䡁䅉䅁湁䙁䅳睕兂䕁䅣睘䑂䝁䄸兢睂䝁䅅杢㕂䙁䄸睓求䡁䅫睕あ䝁䅅䅤穂䙁䄸杤祁䍁䅁免畁䡁䅧䅢穂䝁䄰兘兂䝁䅕杢穂䝁䅫睢畂䍁䄰睔兂䕁䅕村湁䍁䅅䅊䕂䍁䅑睎㙁䍁䅑兓歁䑁䅣䅁䍁睂䅁䅡䅁䕁䅍兤祂䡁䅉杌杁䙁䅁睢祂䡁䅑杌杁䝁䄸杚杁䕁䅷䅖杁䕁䅑党楂䡁䅑䅉流䍁䅁睑桂䡁䅁䅉䵂䝁䅕兙穂䝁䅕督癁䍁䅁䅖療䡁䅑兙獂䍁䅁䅒求䝁䅉䅤杁䍁䅧兊灁䅁䅁睕䅅䝁䄴䅁湁䙁䅳睕兂䕁䅣睘䑂䝁䄸兢睂䝁䅅杢㕂䙁䄸睓求䡁䅫睕あ䝁䅅䅤穂䙁䄸杤祁䍁䅁免畁䡁䅧䅢穂䝁䄰兘䑂䝁䅅䅣灂䡁䅑兙獂䝁䅫来桂䡁䅑兡療䝁䄴睊桁䍁䅑睑歁䑁䅑兏䅁佁䜰䅁㑂䅁䅁睊扂䕁䅍睢睂䡁䅫䅉療䝁䅙䅉呂䙁䅁睒時䕁䅍睢瑂䡁䅁兙畂䡁䅫睘䱂䝁䅕入呂䡁䅑兙あ䡁䅍睘㉂䑁䅉睘畂䝁䅕睤畁䡁䅧䅢穂䝁䄰兘䱂䝁䅕入時䙁䅍䅤桂䡁䅑督湁䍁䅅䅊䍂䍁䅑杍ㅁ䅁䅁杊䅣䡁䅁䅁䵂䙁䅑䅉䕂䝁䅕杙あ䍁䅁䅋䩂䝁䄴睙獂䍁䄴䅉䑂䝁䅅䅣畁䍁䅁䅔求䝁䅅督求䡁䅍克杁䕁䅑兤求䍁䅷䅉䉂䝁䅙䅤求䡁䅉䅉ㅁ䍁䅁兗祂䡁䅍䅉潁䙁䅉党睂䝁䄸杣あ䝁䅕䅚灁䅁䅁杰䅅䉁䅑䅁䩂䙁䅅睘卂䕁䅑睘䙂䙁䅧䅕䅁䱁䅉䅁䭂䅁䅁睑桂䡁䅁杌杁䕁䅷党桂䡁䅍党杁䙁䅁兙㕂䝁䄰党畂䡁䅑䅉䕂䡁䅕党杁䍁䅳杍杁䍁䅧杕求䡁䅁睢祂䡁䅑党歂䍁䅫䅁獃允䅁䅥䅁䙁䅳兔䩂䙁䄸睑療䝁䄰䅣桂䝁䄴入時䕁䅳党㕂䙁䅍䅤桂䡁䅑督時䡁䅙免畁䡁䅧䅢穂䝁䄰兘䑂䝁䅅䅣灂䡁䅑兙獂䙁䄸睕あ䡁䅉兤橂䡁䅑兤祂䝁䅕睘呂䡁䅕兢瑂䝁䅅杣㕂䍁䅅䅊䑂䍁䅑兎䅁䍁䕁䅁㙂䅁䅁睊扂䙁䅍䅕䡂䙁䄸睑療䝁䄰䅣桂䝁䄴入時䕁䅳党㕂䙁䅍䅤桂䡁䅑督時䡁䅙杍杁䑁䅅杌㑂䝁䅷督瑂䙁䄰睑桂䡁䅁兡あ䝁䅅䅢灂䡁䅯兙あ䝁䅫睢畂䍁䅣光歁䕁䅍䅊ㅁ䑁䅉杏歁䕁䅍䅊ㅁ䑁䅍䅁灄杂䅁䅯䅁䍁䅣睗䑂䝁䄸䅣㕂䍁䅁睢浂䍁䅁睕兂䕁䅣睘䑂䝁䄸兢睂䝁䅅杢㕂䙁䄸睓求䡁䅫睕あ䝁䅅䅤穂䙁䄸杤硁䙁䄸杒灂䝁䄴兙獂䍁䄴䅥獂䡁䅍兢摂䕁䅍兙睂䝁䅫䅤桂䝁䅷睘呂䡁䅑杣ㅂ䝁䅍䅤ㅂ䡁䅉党時䍁䅁䅒求䡁䅑兙灂䝁䅷督杁䍁䅣光歁䕁䅅兑歁䑁䅣䅁䵂䅃䅁䅐䅁䕁䅅杤求䡁䅉兙湂䝁䅕䅉䩂䝁䄴䅤求䡁䅉党穂䡁䅑䅉卂䝁䅅䅤求䍁䅁睋杁䑁䅕䅉潁䍁䅕克䅁偁䉁䅁慂䅁䅁睔睂䝁䅕杣桂䡁䅑兡畂䝁䅣䅉䵂䝁䅕兙穂䝁䅕䅉䑂䝁䄸兢瑂䝁䅫䅤瑂䝁䅕杢あ䍁䅁䅒ㅂ䝁䅕䅉牁䑁䅑䅉潁䙁䅉党睂䝁䄸杣あ䝁䅕䅚灁䅁䅁杶䅅䍁䅯䅁䩂䙁䅅睘䙂䕁䅅杕佂䕁䅫杔䡂䙁䄸睑偂䙁䄸兔䉂䙁䅉睒䩂䕁䄴䅁䩁杁䅁䅥䅁䍁䅣睗呂䙁䅁睒時䕁䅍睢瑂䡁䅁兙畂䡁䅫睘䱂䝁䅕入呂䡁䅑兙あ䡁䅍睘㉂䑁䅉䅉硁䍁䄴䅥獂䡁䅍兢摂䕁䅍兙睂䝁䅫䅤桂䝁䅷兡㙂䝁䅅䅤灂䝁䄸杢湁䍁䅅䅊䑂䍁䅑兏㙁䍁䅑睑歁䑁䅉䅎䅁佁䝕䅁ぁ䅁䅁兓畂䡁䅙党畂䡁䅑睢祂䡁䅫䅌杁䑁䅕䅉婂䡁䅉杌杁䕁䅍兑䡂䙁䅉䅉潁䍁䅕克䅁䩁䍧䅁獁䅁䅁兓剂䙁䄸䅒兂䙁䅍睘硁䙁䅫杕時䕁䅅杔佂䙁䄸睒卂䕁䄸睖啂䕁䅧䅁㍁杁䅁权䅁䕁䅙兗牁䑁䅅䅁㥁䅁䅁杤䅁䍁䅣睗呂䙁䅁睒時䕁䅍睢瑂䡁䅁兙畂䡁䅫睘䱂䝁䅕入呂䡁䅑兙あ䡁䅍睘㉂䑁䅉䅉硁䍁䄴䅥獂䡁䅍兢摂䕁䅍兙睂䝁䅫䅤桂䝁䅷兡㙂䝁䅅䅤灂䝁䄸杢湁䍁䅅䅊䙂䍁䅑䅎㙁䍁䅑杓歁䑁䅑䅁歄杂䅁来䅁䍁䅣睗呂䙁䅁睒時䕁䅍睢瑂䡁䅁兙畂䡁䅫睘䱂䝁䅕入呂䡁䅑兙あ䡁䅍睘㉂䑁䅉䅉硁䍁䄴䅥獂䡁䅍兢摂䕁䅍兙睂䝁䅫䅤桂䝁䅷兡㙂䝁䅅䅤灂䝁䄸杢湁䍁䅅䅊䙂䍁䅑兎睁䑁䅯䅊䭂䍁䅑兎睁䅁䅁䄶䅙䝁䅉䅁湁䙁䅳睕兂䕁䅣睘䑂䝁䄸兢睂䝁䅅杢㕂䙁䄸睓求䡁䅫睕あ䝁䅅䅤穂䙁䄸杤祁䍁䅁免畁䡁䅧䅢穂䝁䄰兘䑂䝁䅅督潂䙁䄸杒獂䝁䄸睤湁䍁䅅䅊䑂䍁䅑李䅁乁䜸䅁㉂䅁䅁睊扂䙁䅍䅕䡂䙁䄸睑療䝁䄰䅣桂䝁䄴入時䕁䅳党㕂䙁䅍䅤桂䡁䅑督時䡁䅙杍杁䑁䅅杌㑂䝁䅷督瑂䙁䄰睑桂䡁䅁兡あ䝁䅅䅢灂䡁䅯兙あ䝁䅫睢畂䍁䅣光歁䕁䅕䅊ㅁ䑁䅯䅊䭂䍁䅑兎䅁佁䝙䅁睂䅁䅁睊扂䙁䅍䅕䡂䙁䄸睑療䝁䄰䅣桂䝁䄴入時䕁䅳党㕂䙁䅍䅤桂䡁䅑督時䡁䅙杍杁䑁䅅杌㑂䝁䅷督瑂䙁䄰睑桂䡁䅍䅡時䕁䅙䅢療䡁䅣睊桁䍁䅑睑歁䑁䅅免㙁䍁䅑睑歁䑁䅫李䅁佁䝅䅁捃䅁䅁睊扂䕁䅍睢睂䡁䅫䅉療䝁䅙䅉呂䙁䅁睒時䕁䅍睢瑂䡁䅁兙畂䡁䅫睘䱂䝁䅕入呂䡁䅑兙あ䡁䅍睘㉂䑁䅉睘畂䝁䅕睤畁䡁䅧䅢穂䝁䄰兘䑂䝁䅅䅣灂䡁䅑兙獂䙁䄸睕あ䡁䅉兤橂䡁䅑兤祂䝁䅕睘杁䕁䅑党あ䝁䅅兡獂䡁䅍䅉湁䍁䅅䅊䭂䍁䅑䅎ぁ䅁䅁睧䅣䝁䅷䅁湁䙁䅳睕兂䕁䅣睘䑂䝁䄸兢睂䝁䅅杢㕂䙁䄸睓求䡁䅫睕あ䝁䅅䅤穂䙁䄸杤祁䍁䅁免畁䡁䅧䅢穂䝁䄰兘䑂䝁䅅督潂䙁䄸杒獂䝁䄸睤湁䍁䅅䅊䙂䍁䅑李㙁䍁䅑䅕歁䑁䅙䅁杄杂䅁杣䅁䙁䅳兔䩂䙁䄸睓求䡁䅫睕あ䝁䅅䅤穂䙁䄸杤硁䍁䄴䅥獂䡁䅍兢摂䕁䅍兙睂䝁䅫䅤桂䝁䅷睘呂䡁䅑杣ㅂ䝁䅍䅤ㅂ䡁䅉党時䙁䅍兤瑂䝁䄰兙祂䡁䅫光歁䕁䅙䅊㕁䑁䅯䅊佂䍁䅑兏䅁䭁䐸䅁䅃䅁䅁睊扂䙁䅍䅕䡂䙁䄸睑療䝁䄰䅣桂䝁䄴入時䕁䅳党㕂䙁䅍䅤桂䡁䅑督時䡁䅙杍杁䑁䅅杌㑂䝁䅷督瑂䙁䄰兓畂䝁䅍睢瑂䝁䅕睘呂䡁䅑兙あ䝁䅕兢求䝁䄴䅤湁䍁䅅䅊䑂䍁䅑免硁䑁䅯䅊䑂䍁䅑免㕁䑁䅧䅁婄杂䅁杚䅁䙁䅳兔䩂䙁䄸睑療䝁䄰䅣桂䝁䄴入時䕁䅳党㕂䙁䅍䅤桂䡁䅑督時䡁䅙免畁䡁䅧䅢穂䝁䄰兘䱂䝁䅕入時䙁䅍䅤桂䡁䅑督桁䍁䅑睑歁䑁䅉兎㙁䍁䅑睑歁䑁䅑兏䅁偁䑉䅁畂䅁䅁兓畂䡁䅑党祂䝁䄴兙あ䝁䅫睢畂䝁䅅䅢杁䕁䅉兤穂䝁䅫杢求䡁䅍督杁䕁䄰兙橂䝁䅧兡畂䝁䅕督杁䕁䅍睢祂䡁䅁睢祂䝁䅅䅤灂䝁䄸杢杁䍁䅧杔婂䙁䅍兒㙁䕁䅫村乂䍁䅫䅁ㅂ杂䅁䅣䅁䍁䅣睗呂䙁䅁睒時䕁䅍睢瑂䡁䅁兙畂䡁䅫睘䱂䝁䅕入呂䡁䅑兙あ䡁䅍睘㉂䑁䅉䅉硁䍁䄴䅥獂䡁䅍兢摂䕁䅫杢橂䝁䄸兢求䙁䄸睕あ䝁䅅䅤求䝁䄰党畂䡁䅑睊桁䍁䅑睑歁䑁䅙䅁塄杂䅁杓䅁䕁䅍兙穂䝁䅧䅉䝂䡁䅉睢瑂䍁䅁睔睂䝁䅕杣桂䡁䅑兡療䝁䄴督獁䍁䅁睍杁䙁䅫杣畁䍁䅁睑䉂䕁䅣杕杁䍁䅧兊灁䅁䅁䅧䅉䍁䅷䅁䩂䙁䅅睘啂䕁䅉杖時䑁䅍兗卂䙁䄸兑佂䕁䄴睘䡂䙁䅉睔塂䙁䅑䅓䅁䡁䍳䅁㉁䅁䅁兓剂䙁䄸䅒䙂䕁䅙兒卂䙁䅉兒䕂䙁䄸䅒偂䕁䄰兒呂䙁䅑兓䑂䙁䄸䅖䉂䙁䅧兒呂䅁䅁兪䅍䙁䅉䅁䕂䝁䅫䅢ㅂ䡁䅑党歂䍁䅁兒兂䙁䅍䅉䙂䡁䅧睙獂䍁䄴䅉䙂䡁䅧䅤祂䝁䅅䅉䩂䡁䅑党瑂䡁䅍䅉潁䙁䅉党睂䝁䄸杣あ䝁䅕䅚灁䅁䅁充䅁䩁䅁䅁偂䡁䅁䅤灂䝁䄸杢穂䑁䅯䅉䑂䡁䅕杣祂䑁䄰睒䍂䙁䅁䅌乂䝁䅅睚㥁䕁䅅睙あ䡁䅕兙獂䡁䅍䅌䑂䝁䄸杢㉂䕁䄰党あ䝁䅧睢歂䑁䄰兔䩂䡁䅉党橂䝁䄸兢瑂䝁䅕杢歂䝁䅕䅚獁䍁䅁杔䉂䑁䄰䅌杁䙁䅑党祂䝁䄰児求䝁䄴兌噂䙁䅍䅁㉁䅁䅁杉䅁䕁䅫兕時䕁䄸䅖䥂䕁䅕杕時䙁䅕杔䕂䙁䅉兑塂䕁䄴䅁䭁允䅁杚䅁䍁䅣睗呂䙁䅁睒時䕁䅍睢瑂䡁䅁兙畂䡁䅫睘䱂䝁䅕入呂䡁䅑兙あ䡁䅍睘㉂䑁䅉䅉硁䍁䄴䅥獂䡁䅍兢摂䕁䅳党㕂䙁䄸睕あ䝁䅅䅤穂䍁䅣光歁䕁䅉䅊硁䑁䅁睎䅁䱁䜸䅁㑂䅁䅁睊扂䙁䅍䅕䡂䙁䄸睑療䝁䄰䅣桂䝁䄴入時䕁䅳党㕂䙁䅍䅤桂䡁䅑督時䡁䅙杍杁䑁䅅杌㑂䝁䅷督瑂䙁䄰睕ㅂ䡁䅁䅣獂䝁䅕兢求䝁䄴䅤桂䝁䅷睊桁䍁䅑睑歁䑁䅅免㙁䍁䅑睑歁䑁䅅李㑁䅁䅁儯䅙䝁䅧䅁扂䕁䄰兓時䕁䅍睢瑂䡁䅁兙畂䡁䅫睘䱂䝁䅕入呂䡁䅑兙あ䡁䅍睘㉂䑁䅅杌㑂䝁䅷督瑂䙁䄰睕ㅂ䡁䅁䅣獂䝁䅕兢求䝁䄴䅤桂䝁䅷光歁䕁䅑䅊㍁䑁䅯䅊䩂䍁䅑睎䅁䵁䙳䅁䅃䅁䅁睔睂䡁䅑兡療䝁䄴督㙁䕁䅍兤祂䡁䅉児卂䝁䅕䅣療䡁䅉䅤求䝁䅑䅉橂䡁䅕杣祂䝁䅕杢橂䡁䅫䅌乂䝁䅅睚㥁䕁䄰兓穂䡁䅑兙畂䝁䅑兙祂䝁䅑䅌䑂䝁䄸杢㉂䕁䄰党あ䝁䅧睢歂䑁䄰兔卂䡁䅍䅣療䡁䅑䅁䑁䅁䅁来䅁䙁䅳睕兂䕁䅣睘䑂䝁䄸兢睂䝁䅅杢㕂䙁䄸睓求䡁䅫睕あ䝁䅅䅤穂䙁䄸杤祁䍁䄴䅥獂䡁䅍兢摂䕁䅍兙睂䝁䅫䅤桂䝁䅷睘呂䡁䅑杣ㅂ䝁䅍䅤ㅂ䡁䅉党時䙁䅍兤瑂䝁䄰兙祂䡁䅫光歁䕁䅍䅊㉁䅁䅁杁䅧䝁䅑䅁湁䙁䅳睕兂䕁䅣睘䑂䝁䄸兢睂䝁䅅杢㕂䙁䄸睓求䡁䅫睕あ䝁䅅䅤穂䙁䄸杤祁䍁䅁免畁䡁䅧䅢穂䝁䄰兘䱂䝁䅕入時䙁䅍䅤桂䡁䅑督湁䍁䅅䅊䍂䍁䅑杍㉁䅁䅁睹䅙䙁䅯䅁扂䕁䄰兓時䕁䅍睢瑂䡁䅁兙畂䡁䅫睘䱂䝁䅕入呂䡁䅑兙あ䡁䅍睘㉂䑁䅅杌㑂䝁䅷督瑂䙁䄰睓求䡁䅫睘呂䡁䅑兙あ䡁䅍光歁䕁䅉䅊ㅁ䑁䅍䅁䵃䅂䅁䅤䅁䍁䅣睗呂䙁䅁睒時䕁䅍睢瑂䡁䅁兙畂䡁䅫睘䱂䝁䅕入呂䡁䅑兙あ䡁䅍睘㉂䑁䅉䅉硁䍁䄴䅥獂䡁䅍兢摂䕁䅳党㕂䙁䄸睕あ䝁䅅䅤穂䍁䅣光歁䕁䅍䅊硁䑁䅁兏㙁䍁䅑睑歁䑁䅅免ㅁ䅁䅁儱䅙䑁䅁䅁䩂䙁䅅睘䙂䕁䅉兓啂䕁䅅睘祁䙁䅫杕時䕁䅅杔佂䙁䄸睒卂䕁䄸睖啂䕁䅧䅁乂杁䅁䅈䅁䕁䅫兕時䕁䅍䅔時䕁䅑兖䙂䙁䄸睑婂䑁䅑䅁癃允䅁杓䅁䙁䅳兔䩂䙁䄸睓求䡁䅫睕あ䝁䅅䅤穂䙁䄸杤硁䍁䄴䅥獂䡁䅍兢摂䕁䅳党㕂䙁䄸睕あ䝁䅅䅤穂䍁䅅䅊䍂䍁䅑兎祁䅁䅁兤䅍䑁䄴䅁啂䝁䄸䅤桂䝁䅷䅉乂䝁䅫杢療䡁䅉兡あ䡁䅫䅉䩂䝁䄴䅤求䡁䅉党穂䡁䅑䅉潁䍁䅑䅍睁䑁䅁克䅁䝁䄸䅁坂䅁䅁睗䱂䝁䅕入呂䡁䅑兙あ䡁䅍睘あ䝁䅕督あ䝁䅙兡獂䝁䅕杌㑂䝁䅷督㑂䙁䄰睕潂䝁䅕党あ䑁䅅光歁䕁䅍䅊祁䑁䅕杏歁䕁䅍䅊㉁䑁䅧䅁祂䅁䅁䅣䅁䍁䅣睗呂䙁䅁睒時䕁䅍睢瑂䡁䅁兙畂䡁䅫睘䱂䝁䅕入呂䡁䅑兙あ䡁䅍睘㉂䑁䅉䅉硁䍁䄴䅥獂䡁䅍兢摂䕁䅳党㕂䙁䄸睕あ䝁䅅䅤穂䍁䅣光歁䕁䅍䅊祁䑁䅧杏歁䕁䅍䅊ㅁ䑁䅉䅁䙄杂䅁杇䅁䑁䅷材睁䑁䅫睌硁䑁䅧睌祁䑁䅁杍睁䅁䅁䅱䅕䩁䅧䅁湁䙁䅳睑療䡁䅁入杁䝁䄸杚杁䙁䅍䅕䡂䙁䄸睑療䝁䄰䅣桂䝁䄴入時䕁䅳党㕂䙁䅍䅤桂䡁䅑督時䡁䅙免時䕁䅙兡畂䝁䅅䅢畁䡁䅧䅢穂䝁䄰兘䩂䝁䄴睙療䝁䄰党時䙁䅍䅤桂䡁䅑党瑂䝁䅕杢あ䍁䅣光歁䕁䅍䅊硁䑁䅅杏歁䕁䅍䅊硁䑁䅫䅍䅁䙁䥫䅁㙁䅁䅁兓剂䙁䄸兒䉂䙁䅉杔䩂䕁䄴睒時䕁䅍睔時䑁䅉兗卂䙁䄸兑佂䕁䄴睘䡂䙁䅉睔塂䙁䅑䅓䅁䕁䍕䅁䭂䅁䅁睗䱂䝁䅕入呂䡁䅑兙あ䡁䅍睘あ䝁䅕督あ䝁䅙兡獂䝁䅕杌㑂䝁䅷督㑂䙁䄰睕潂䝁䅕党あ䑁䅅光歁䕁䅍䅊ㅁ䑁䅕䅁摂䅁䅁䅣䅁䍁䅣睗呂䙁䅁睒時䕁䅍睢瑂䡁䅁兙畂䡁䅫睘䱂䝁䅕入呂䡁䅑兙あ䡁䅍睘㉂䑁䅉䅉硁䍁䄴䅥獂䡁䅍兢摂䕁䅳党㕂䙁䄸睕あ䝁䅅䅤穂䍁䅣光歁䕁䅑䅊祁䑁䅧杏歁䕁䅑䅊ㅁ䑁䅉䅁乄杂䅁䅖䅁䙁䅳睓求䡁䅫睕あ䝁䅅䅤穂䙁䄸䅤求䡁䅍䅤浂䝁䅫䅢求䍁䄴䅥獂䡁䅍兢摂䙁䅉兙あ䝁䅫睢穂䍁䅅䅊䕂䍁䅑兏㙁䍁䅑䅒歁䑁䅫䅍䅁偁䉕䅁楂䅁䅁睗䱂䝁䅕入呂䡁䅑兙あ䡁䅍睘あ䝁䅕督あ䝁䅙兡獂䝁䅕杌㑂䝁䅷督瑂䙁䄰睕ㅂ䡁䅁䅣獂䝁䅕兢求䝁䄴䅤桂䝁䅷光歁䕁䅑䅊㕁䑁䅯䅊䕂䍁䅑免穁䑁䅫䅁杂睁䅁䅄䅁䕁䅫兕時䕁䅣䅕䅁䅁䅣䅁睂䅁䅁睊扂䙁䅍䅕䡂䙁䄸睑療䝁䄰䅣桂䝁䄴入時䕁䅳党㕂䙁䅍䅤桂䡁䅑督時䡁䅙杍杁䑁䅅杌㑂䝁䅷督瑂䙁䄰睓求䡁䅫睘呂䡁䅑兙あ䡁䅍睊桁䍁䅑兒歁䑁䅉李㙁䍁䅑杓歁䑁䅉李䅁䵁䝙䅁䕂䅁䅁兓剂䙁䄸睑偂䕁䄴䅖卂䕁䅅睑啂䙁䄸睔䍂䕁䅷兓䡂䕁䅅䅖䩂䕁䄸杔時䕁䅅杒啂䕁䅕杕時䕁䅙兓坂䕁䅕䅁晄允䅁䅤䅁䍁䅣睗呂䙁䅁睒時䕁䅍睢瑂䡁䅁兙畂䡁䅫睘䱂䝁䅕入呂䡁䅑兙あ䡁䅍睘㉂䑁䅉䅉硁䍁䄴䅥獂䡁䅍兢摂䕁䅳党㕂䙁䄸睕あ䝁䅅䅤穂䍁䅣光歁䕁䅙䅊硁䑁䅁李㙁䍁䅑䅓歁䑁䅅䅍㉁䅁䅁䄱䅙䝁䅑䅁湁䙁䅳睕兂䕁䅣睘䑂䝁䄸兢睂䝁䅅杢㕂䙁䄸睓求䡁䅫睕あ䝁䅅䅤穂䙁䄸杤祁䍁䅁免畁䡁䅧䅢穂䝁䄰兘䱂䝁䅕入時䙁䅍䅤桂䡁䅑督湁䍁䅅䅊䝂䍁䅑免ㅁ䅁䅁杂䅣䥁䅧䅁湁䙁䅳睑療䡁䅁入杁䝁䄸杚杁䙁䅍䅕䡂䙁䄸睑療䝁䄰䅣桂䝁䄴入時䕁䅳党㕂䙁䅍䅤桂䡁䅑督時䡁䅙免時䕁䅙兡畂䝁䅅䅢畁䡁䅧䅢穂䝁䄰兘䱂䝁䅕入時䙁䅍䅤桂䡁䅑督湁䍁䅅䅊䑂䍁䅑李ㅁ䑁䅯䅊䑂䍁䅑睎硁䅁䅁䅕䅧䍁䅷䅁䩂䙁䅅睘䙂䙁䅁睕時䑁䅉兗卂䙁䄸兑佂䕁䄴睘䡂䙁䅉睔塂䙁䅑䅓䅁䙁䍍䅁楂䅁䅁睊扂䙁䅍䅕䡂䙁䄸睑療䝁䄰䅣桂䝁䄴入時䕁䅳党㕂䙁䅍䅤桂䡁䅑督時䡁䅙杍杁䑁䅅杌㑂䝁䅷督瑂䙁䄰睓求䡁䅫睘呂䡁䅑兙あ䡁䅍睊桁䍁䅑杒歁䑁䅫䅁䕁睂䅁䅡䅁䙁䅳睕兂䕁䅣睘䑂䝁䄸兢睂䝁䅅杢㕂䙁䄸睓求䡁䅫睕あ䝁䅅䅤穂䙁䄸杤祁䍁䄴䅥獂䡁䅍兢摂䕁䄰兤獂䡁䅑兡睂䝁䅷党穂䍁䅅䅊䙂䍁䅑免睁䑁䅯䅊䵂䍁䅑免睁䅁䅁杣䅙䑁䅯䅁佂䕁䅅杕䙂䕁䅫䅖時䙁䅍兙瑂䝁䅕睕あ䝁䄸杣求䙁䄸睑療䝁䄰䅣桂䝁䄴入䵂䝁䅫督あ䅁䅁儲䅍䉁䅯䅁呂䙁䅁睘䙂䕁䄴䅖䩂䙁䅑兗時䕁䅫䅒䅁䍁䅁䅁睂䅁䅁睊扂䙁䅍䅕䡂䙁䄸睑療䝁䄰䅣桂䝁䄴入時䕁䅳党㕂䙁䅍䅤桂䡁䅑督時䡁䅙杍杁䑁䅅杌㑂䝁䅷督瑂䙁䄰睓求䡁䅫睘呂䡁䅑兙あ䡁䅍睊桁䍁䅑兔歁䑁䅉兎㙁䍁䅑睔歁䑁䅉兎䅁䵁䝷䅁睂䅁䅁睊扂䙁䅍䅕䡂䙁䄸睑療䝁䄰䅣桂䝁䄴入時䕁䅳党㕂䙁䅍䅤桂䡁䅑督時䡁䅙杍杁䑁䅅杌㑂䝁䅷督瑂䙁䄰睓求䡁䅫睘呂䡁䅑兙あ䡁䅍睊桁䍁䅑兔歁䑁䅉李㙁䍁䅑睔歁䑁䅉李䅁䵁䜴䅁歂䅁䅁睊扂䙁䅍䅕䡂䙁䄸睑療䝁䄰䅣桂䝁䄴入時䕁䅳党㕂䙁䅍䅤桂䡁䅑督時䡁䅙杍杁䑁䅅杌㑂䝁䅷督瑂䙁䄰睓求䡁䅫睘呂䡁䅑兙あ䡁䅍睊桁䍁䅑睕歁䑁䅕兎䅁䵁䝣䅁䭃䅁䅁睗呂䙁䅁睒時䕁䅍睢瑂䡁䅁兙畂䡁䅫睘䱂䝁䅕入呂䡁䅑兙あ䡁䅍睘㉂䑁䅅杌㑂䝁䅷督瑂䙁䄰睑桂䡁䅁兡あ䝁䅅䅢時䙁䅍䅤祂䡁䅕睙あ䡁䅕杣求䙁䄸睕ㅂ䝁䄰兢桂䡁䅉入桁䍁䅑睑歁䑁䅅兎㙁䍁䅑睑歁䑁䅅兎祁䅁䅁术䅕䡁䅁䅁湁䙁䅳睕兂䕁䅣睘䑂䝁䄸兢睂䝁䅅杢㕂䙁䄸睓求䡁䅫睕あ䝁䅅䅤穂䙁䄸杤祁䍁䅁免畁䡁䅧䅢穂䝁䄰兘䱂䝁䅕入時䙁䅍䅤桂䡁䅑督湁䍁䅅䅊啂䍁䅑兎㑁䑁䅯䅊啂䍁䅑李硁䅁䅁杹䅙䑁䅙䅁䩂䙁䅅睘䑂䕁䄸杔啂䙁䅉兑䑂䙁䅑睘偂䕁䅉䅔䩂䕁䅣兑啂䕁䅫睔佂䙁䄸睑婂䑁䅍䅁婄允䅁䅣䅁䍁䅣睗呂䙁䅁睒時䕁䅍睢瑂䡁䅁兙畂䡁䅫睘䱂䝁䅕入呂䡁䅑兙あ䡁䅍睘㉂䑁䅉䅉硁䍁䄴䅥獂䡁䅍兢摂䕁䅳党㕂䙁䄸睕あ䝁䅅䅤穂䍁䅣光歁䙁䅙䅊ㅁ䑁䅣杏歁䙁䅣䅊ㅁ䑁䅣䅁䩄杂䅁䅡䅁䍁䅣睗呂䙁䅁睒時䕁䅍睢瑂䡁䅁兙畂䡁䅫睘䱂䝁䅕入呂䡁䅑兙あ䡁䅍睘㉂䑁䅉䅉硁䍁䄴䅥獂䡁䅍兢摂䙁䅁党畂䡁䅍兡療䝁䄴兌偂䙁䅁兒䍂䍁䅣光歁䕁䅍䅊㉁䅁䅁眯䅙䕁䄴䅁啂䝁䄸䅤桂䝁䅷䅉䑂䝁䄸兢瑂䝁䅕杣橂䝁䅫兙獂䍁䅁䅕桂䡁䅁党祂䍁䄸䅉啂䝁䄸䅤桂䝁䅷䅉䕂䝁䅕杙あ䍁䅁䅋汁䍁䅫䅁癄䅁䅁杣䅁䍁䅣睗呂䙁䅁睒時䕁䅍睢瑂䡁䅁兙畂䡁䅫睘䱂䝁䅕入呂䡁䅑兙あ䡁䅍睘㉂䑁䅉䅉硁䍁䄴䅥獂䡁䅍兢摂䙁䅁党畂䡁䅍兡療䝁䄴兌偂䙁䅁兒䍂䍁䅣光歁䕁䅑䅊㉁䑁䅯䅊䩂䍁䅑李䅁䅁䡁䅁䍂䅁䅁杗求䡁䅉睢杁䕁䅍睢ㅂ䡁䅁睢畂䍁䅁䅒求䝁䅉䅤癁䍁䅁䅖療䡁䅑兙獂䍁䅁䅒求䝁䅉䅤杁䍁䅧兊灁䅁䅁兢䅅䕁䅷䅁扂䕁䄰兓時䕁䅳党㕂䙁䅍䅤桂䡁䅑督時䡁䅙免畁䡁䅧䅢穂䝁䄰兘卂䝁䅅䅤灂䝁䄸督桁䍁䅑䅒歁䑁䅕杏歁䕁䅫䅊ㅁ䅁䅁睳䅍䙁䅷䅁湁䙁䅳睕兂䕁䅣睘䑂䝁䄸兢睂䝁䅅杢㕂䙁䄸睓求䡁䅫睕あ䝁䅅䅤穂䙁䄸杤祁䍁䅁免畁䡁䅧䅢穂䝁䄰兘卂䝁䅅䅤灂䝁䄸督湁䍁䅅䅊䑂䍁䅑李䅁偁䝣䅁浂䅁䅁睊扂䙁䅍䅕䡂䙁䄸睑療䝁䄰䅣桂䝁䄴入時䕁䅳党㕂䙁䅍䅤桂䡁䅑督時䡁䅙杍杁䑁䅅杌㑂䝁䅷督瑂䙁䄰杕桂䡁䅑兡療䡁䅍睊桁䍁䅑䅒歁䑁䅙杏歁䕁䅫䅊㉁䅁䅁䄫䅙䉁䅯䅁䩂䙁䅅睘佂䕁䅫睘乂䕁䅅杕䡂䕁䅫杔䅁䅁䍳䅁潁䅁䅁睒祂䝁䄸督穂䍁䅁䅕祂䝁䄸杚灂䡁䅑䅉潁䍁䅑䅍睁䑁䅁克䅁䝁䅧䅁潂䅁䅁睊扂䙁䅍䅕䡂䙁䄸睑療䝁䄰䅣桂䝁䄴入時䕁䅳党㕂䙁䅍䅤桂䡁䅑督時䡁䅙杍杁䑁䅅杌㑂䝁䅷督瑂䙁䄰睕ㅂ䡁䅁䅣獂䝁䅕兢求䝁䄴䅤桂䝁䅷睊桁䍁䅑睑歁䑁䅙䅁㝄杂䅁杣䅁䍁䅣睗呂䙁䅁睒時䕁䅍睢瑂䡁䅁兙畂䡁䅫睘䱂䝁䅕入呂䡁䅑兙あ䡁䅍睘㉂䑁䅉䅉硁䍁䄴䅥獂䡁䅍兢摂䙁䅍兤睂䡁䅁䅢求䝁䄰党畂䡁䅑兙獂䍁䅣光歁䕁䅑䅊㍁䑁䅯䅊䩂䍁䅑睎䅁偁䜴䅁坁䅁䅁䅍㕁䍁䄸免㑁䍁䄸杍睁䑁䅉䅍䅁䭁䙫䅁奂䅁䅁杔療䝁䄴䅉瑁䍁䅁睑ㅂ䡁䅉杣求䝁䄴䅤杁䕁䅅督穂䝁䅕䅤穂䍁䅁兌杁䙁䅕杌呂䍁䄴䅉䡂䕁䅅兑兂䍁䅁䅋卂䝁䅕䅣療䡁䅉䅤求䝁䅑克䅁䱁䌰䅁坁䅁䅁䅍㕁䍁䄸杍硁䍁䄸杍睁䑁䅉䅍䅁䭁䙕䅁䝁䅁䅁杍ㅁ䅁䅁杧䅙䝁䅧䅁扂䕁䄰兓時䕁䅍睢瑂䡁䅁兙畂䡁䅫睘䱂䝁䅕入呂䡁䅑兙あ䡁䅍睘㉂䑁䅅睘畁䡁䅧䅢穂䝁䄰兘䱂䝁䅕入時䙁䅍䅤桂䡁䅑督桁䍁䅑睑歁䑁䅙兎㙁䍁䅑睑歁䑁䅣免䅁䵁䕳䅁畂䅁䅁睑桂䡁䅁兡あ䝁䅅䅢杁䕁䅷睢穂䡁䅍䅉䑂䝁䅅杣祂䡁䅫杚療䡁䅉睤桂䡁䅉䅚獁䍁䅁兑浂䡁䅑党祂䍁䅁杒灂䡁䅙党杁䙁䅫党桂䡁䅉督杁䍁䅧杕求䡁䅁睢祂䡁䅑党歂䍁䅫䅁婄杁䅁杄䅁䑁䅉李㑁䑁䅙免㑁䅁䅁䅶䅉䑁䅙䅁呂䡁䅉杌杁䙁䅍兤楂䍁䄴䅉䕂䝁䅕杙あ䍁䅁睌杁䕁䅕村䩂䙁䅑䅒䉂䍁䅁䅋㑂䍁䅫䅁啃允䅁杇䅁䑁䅷材睁䑁䅍睌祁䑁䅫睌祁䑁䅁免㕁䅁䅁䅙䅁䙁䅷䅁扂䙁䅍䅕䡂䙁䄸睑療䝁䄰䅣桂䝁䄴入時䕁䅳党㕂䙁䅍䅤桂䡁䅑督時䡁䅙杍畁䡁䅧䅢穂䝁䄰兘乂䡁䅕䅢あ䝁䅫䅣獂䝁䅕督桁䍁䅑䅒歁䑁䅅睍䅁䝁䜴䅁慁䅁䅁䅐⭁䑁䅁兏癁䑁䅅兎癁䑁䅉䅍祁䑁䅁䅁权兂䅁䅔䅁䕁䅅睙橂䝁䄸兤畂䡁䅑督杁䙁䅉党橂䝁䅕兡㉂䝁䅅杙獂䝁䅕䅌杁䑁䅅䅉婂䡁䅉杌杁䕁䅣杣療䡁䅣䅤潂䍁䅁䅋汁䍁䅫䅁杁杁䅁杗䅁䙁䅳兔䩂䙁䄸睑療䝁䄰䅣桂䝁䄴入時䕁䅳党㕂䙁䅍䅤桂䡁䅑督時䡁䅙免畁䡁䅧䅢穂䝁䄰兘䱂䝁䅕入時䙁䅍䅤桂䡁䅑督桁䍁䅑兒歁䑁䅙杍䅁䩁䕍䅁䥂䅁䅁兑橂䝁䅍睢ㅂ䝁䄴䅤穂䍁䅁杕求䝁䅍党灂䡁䅙兙楂䝁䅷党獁䍁䅁杍杁䙁䅫杣畁䍁䅁睑䉂䕁䅣杕杁䍁䅧兊灁䅁䅁䅒䅉䕁䅧䅁䉂䝁䅍睙療䡁䅕杢あ䡁䅍䅉卂䝁䅕睙求䝁䅫杤桂䝁䅉䅢求䍁䅷䅉穁䍁䅁兗祂䍁䄴䅉䑂䕁䅅睒卂䍁䅁䅋汁䍁䅫䅁煂杁䅁杗䅁䙁䅳兔䩂䙁䄸睓求䡁䅫睕あ䝁䅅䅤穂䙁䄸杤硁䍁䄴䅥獂䡁䅍兢摂䕁䅉兙獂䝁䅅杢橂䝁䅕睘呂䝁䅧党求䡁䅑光歁䕁䅕䅊ㅁ䑁䅯䅊兂䍁䅑兎䅁䩁䑧䅁坂䅁䅁睑療䝁䄴䅤祂䝁䅅睙あ䡁䅕兙獂䍁䅁睔楂䝁䅷兡湂䝁䅅䅤灂䝁䄸杢穂䍁䅁䅒ㅂ䝁䅕䅉牁䍁䅁兎杁䍁䅧杕求䡁䅁睢祂䡁䅑党歂䍁䅫䅁捄允䅁䅥䅁䙁䅳睓求䡁䅫睕あ䝁䅅䅤穂䙁䄸䅤求䡁䅍䅤浂䝁䅫䅢求䍁䄴䅥獂䡁䅍兢摂䕁䅍兙睂䝁䅫䅤桂䝁䅷睘呂䡁䅑杣ㅂ䝁䅍䅤ㅂ䡁䅉党時䙁䅍兤瑂䝁䄰兙祂䡁䅫光歁䕁䅙䅊ㅁ䑁䅯䅊䭂䍁䅑兎䅁佁䅧䅁あ䅁䅁兑歂䝁䅑兡あ䝁䅫睢畂䡁䅍䅉䍂䝁䅅督求䝁䅑䅉療䝁䄴䅉啂䝁䅅䅥杁䙁䅁睢穂䝁䅫䅤灂䝁䄸杢穂䍁䅁兌杁䕁䅍兤祂䡁䅉党畂䡁䅑䅉婂䡁䅉杌杁䍁䅧杕求䡁䅁睢祂䡁䅑党歂䍁䅫䅁䡁睁䅁䅐䅁䕁䅅杤求䡁䅉兙湂䝁䅕䅉䩂䝁䄴䅤求䡁䅉党穂䡁䅑䅉卂䝁䅅䅤求䍁䅁睋杁䑁䅉䅉潁䍁䅕克䅁佁䈴䅁䵂䅁䅁䅒桂䝁䅫䅢㕂䍁䅁兑㉂䝁䅕杣桂䝁䅣党杁䙁䅉党㉂䝁䅕杢ㅂ䝁䅕䅉啂䡁䅉兙歂䝁䅕督杁䍁䅧兙橂䡁䅑兤桂䝁䅷克䅁䥁䑯䅁潁䅁䅁䅒桂䡁䅫䅉䑂䝁䅷睢穂䝁䅕䅉兂䡁䅉兡橂䝁䅕䅉潁䍁䅑克䅁䝁䅅䅁佂䅁䅁兑㉂䝁䅕杣桂䝁䅣党杁䕁䅫杢あ䝁䅕杣求䡁䅍䅤杁䙁䅉兙あ䝁䅕䅌杁䕁䅅杚あ䝁䅕杣杁䑁䅕䅉婂䡁䅉督杁䍁䅧兊灁䅁䅁䄵䅅䑁䅙䅁䑂䕁䅫兕杁䙁䅉党㉂䝁䅕杢ㅂ䝁䅕䅉䙂䡁䅍䅤杁䍁䅧杕求䡁䅁睢祂䡁䅑党歂䍁䅫䅁⭁䅁䅁杖䅁䙁䅳睕兂䕁䅣睘䑂䝁䄸兢睂䝁䅅杢㕂䙁䄸睓求䡁䅫睕あ䝁䅅䅤穂䙁䄸杤祁䍁䄴䅥獂䡁䅍兢摂䙁䅍䅡求䝁䅕䅤硁䍁䅅䅊䕂䍁䅑睎ㅁ䅁䅁睴䅙䍁䅯䅁䩂䙁䅅睘䕂䕁䅍睕時䙁䅍兒䑂䙁䅕杕䩂䙁䅑兗時䙁䅑兗兂䕁䅕䅁䭃杂䅁䅕䅁䕁䅍兓剂䍁䅁杕求䡁䅙党畂䡁䅕党杁䕁䅕督あ䍁䅁䅕求䡁䅉兡療䝁䅑䅉䙂䝁䄴䅚杁䍁䅧兢瑂䍁䄸䅚歂䍁䄸入㕂䡁䅫入灁䅁䅁䅓䅁䕁䅯䅁䑂䝁䅅䅣畁䍁䅁䅔求䝁䅅督求䍁䅁䅕桂䡁䅫兢求䝁䄴䅤杁䕁䅑兤求䍁䅁睋硁䍁䅁䅋卂䝁䅕䅣療䡁䅉䅤求䝁䅑克䅁䭁䉯䅁杂䅁䅁睔睂䡁䅑兡療䝁䄴督㙁䕁䅍兤祂䡁䅉児噂䙁䅍䅒獁䕁䄰兙湂䑁䄰兔灂䝁䅷䅢灂䝁䄸杢穂䍁䅷睑療䝁䄴杤㥁䕁䄰杕呂䡁䅁睢あ䍁䅷杔䉂䑁䄰杔䉂䅁䅁睰䅣䕁䅯䅁䑂䝁䅅䅣畁䍁䅁䅔求䝁䅅督求䍁䅁䅕桂䡁䅫兢求䝁䄴䅤杁䕁䅑兤求䍁䅁睋ぁ䍁䅁䅋卂䝁䅕䅣療䡁䅉䅤求䝁䅑克䅁䱁䉑䅁䭃䅁䅁睔睂䡁䅑兡療䝁䄴督㙁䍁䅁睑ㅂ䡁䅉杣㥁䙁䅕睕䕂䍁䅷䅉乂䝁䅅睚㥁䕁䄰兡獂䝁䅷兡療䝁䄴督獁䕁䅍睢畂䡁䅙兔求䡁䅑䅡療䝁䅑児乂䙁䅉睕睂䝁䄸䅤獁䍁䅁杔䉂䑁䄰杔䉂䍁䅷䅉啂䝁䅕杣瑂䑁䄰党畂䍁䄰兖呂䅁䅁公䅣䭁䅧䅁湁䙁䅳睑療䡁䅁入杁䝁䄸杚杁䙁䅍䅕䡂䙁䄸睑療䝁䄰䅣桂䝁䄴入時䕁䅳党㕂䙁䅍䅤桂䡁䅑督時䡁䅙免時䕁䅙兡畂䝁䅅䅢畁䡁䅧䅢穂䝁䄰兘䑂䝁䅅䅣灂䡁䅑兙獂䙁䄸睕あ䡁䅉兤橂䡁䅑兤祂䝁䅕睘呂䡁䅕兢瑂䝁䅅杣㕂䍁䅣光歁䕁䅑䅊祁䑁䅫杏歁䕁䅑䅊㍁䑁䅫䅁䕃䅃䅁杘䅁䕁䅍兙睂䍁䄴䅉䵂䝁䅕兙穂䝁䅕䅉兂䝁䅅入瑂䝁䅕杢あ䍁䅁䅒ㅂ䝁䅕䅌杁䕁䅅杚あ䝁䅕杣杁䑁䅕䅉婂䡁䅉督杁䍁䅧杕求䡁䅁睢祂䡁䅑党歂䍁䅫䅁祃允䅁䅯䅁䍁䅣睗䑂䝁䄸䅣㕂䍁䅁睢浂䍁䅁睕兂䕁䅣睘䑂䝁䄸兢睂䝁䅅杢㕂䙁䄸睓求䡁䅫睕あ䝁䅅䅤穂䙁䄸杤祁䙁䄸杢求䡁䅣杌㑂䝁䅷督瑂䙁䄰睑桂䡁䅁兡あ䝁䅅䅢時䙁䅍䅤祂䡁䅕睙あ䡁䅕杣求䙁䄸睕ㅂ䝁䄰兢桂䡁䅉入湁䍁䅅䅊䙂䍁䅑李㙁䍁䅑兕歁䑁䅙䅁䉄睂䅁䅍䅁䕁䄸䅣あ䝁䅫睢畂䡁䅍杏杁䙁䅍䅤桂䡁䅑兡穂䡁䅑兡橂䑁䄰䅓䩂䕁䅣䅓䅁䝁䝁䅁坂䅁䅁睗乂䕁䅫睘䱂䝁䅕入呂䡁䅑兙あ䡁䅍睘㉂䑁䅅杌㑂䝁䅷督瑂䙁䄰睓求䡁䅫睘呂䡁䅑兙あ䡁䅍光歁䕁䅑䅊ㅁ䑁䅑杏歁䕁䅑䅊ㅁ䑁䅕䅁㑂睁䅁䅨䅁䍁䅣睗䑂䝁䄸䅣㕂䍁䅁睢浂䍁䅁睕兂䕁䅣睘䑂䝁䄸兢睂䝁䅅杢㕂䙁䄸睓求䡁䅫睕あ䝁䅅䅤穂䙁䄸杤祁䙁䄸杢求䡁䅣杌㑂䝁䅷督瑂䙁䄰睓求䡁䅫睘呂䡁䅑兙あ䡁䅍睊桁䍁䅑䅒歁䑁䅉䅏㙁䍁䅑䅒歁䑁䅕杍䅁䍁䡷䅁捂䅁䅁睑桂䡁䅁杌杁䕁䅷党桂䡁䅍党杁䙁䅁兙㕂䝁䄰党畂䡁䅑䅉䕂䡁䅕党獁䍁䅁杔求䡁䅧䅤杁䑁䅕䅉婂䡁䅉督杁䍁䅧杕求䡁䅁睢祂䡁䅑党歂䍁䅫䅁㉃允䅁䅎䅁䕁䅫兕時䕁䅑兒䝂䕁䅕杕卂䕁䅕䅒時䕁䅙睔卂䕁䅕兓䡂䕁䄴睘啂䕁䅅䅗䙂䙁䅍䅁偃睁䅁杨䅁䙁䅳兔䩂䙁䄸睑療䝁䄰䅣桂䝁䄴入時䕁䅳党㕂䙁䅍䅤桂䡁䅑督時䡁䅙免畁䡁䅧䅢穂䝁䄰兘䑂䝁䅅䅣灂䡁䅑兙獂䙁䄸睕あ䡁䅉兤橂䡁䅑兤祂䝁䅕睘呂䡁䅕兢瑂䝁䅅杣㕂䍁䅅䅊䝂䍁䅑免硁䑁䅯䅊兂䍁䅑免硁䅁䅁睷䅕䕁䄴䅁䑂䝁䅅䅣灂䡁䅑兙獂䍁䅁兒㑂䡁䅁党畂䝁䅑兡あ䡁䅕杣求䡁䅍䅌杁䑁䅅䅉婂䡁䅉杌杁䕁䅣杣療䡁䅣䅤潂䍁䅁䅋汁䍁䅫䅁ぁ杁䅁杓䅁䕁䅍兙睂䝁䅫䅤桂䝁䅷䅉䙂䡁䅧䅣求䝁䄴䅚灂䡁䅑兤祂䝁䅕督獁䍁䅁杍杁䙁䅫杣畁䍁䅁睑䉂䕁䅣杕杁䍁䅧兊灁䅁䅁䅑䅉䉁䅷䅁䩂䙁䅅睘䩂䕁䄰䅕䉂䕁䅫杕時䕁䄸兓䵂䅁䅁䅴䅁䍁䅉䅁䩂䙁䅅睘啂䕁䅕杖時䙁䅑睔啂䕁䅅䅔時䙁䅉兒坂䅁䅁杖䅙䙁䅙䅁扂䙁䅍䅕䡂䙁䄸睑療䝁䄰䅣桂䝁䄴入時䕁䅳党㕂䙁䅍䅤桂䡁䅑督時䡁䅙杍畁䡁䅧䅢穂䝁䄰兘呂䝁䅧党求䡁䅑免桁䍁䅑兗歁䑁䅅䅏䅁䱁䜰䅁流䅁䅁兓剂䙁䄸睕噂䕁䅉睘䕂䕁䅕村啂䙁䄸兒䍂䕁䅫䅖䕂䕁䅅䅁噃允䅁杓䅁䕁䅍兙睂䝁䅫䅤桂䝁䅷䅉䙂䡁䅧䅣求䝁䄴䅚灂䡁䅑兤祂䝁䅕督獁䍁䅁兎杁䙁䅫杣畁䍁䅁睑䉂䕁䅣杕杁䍁䅧兊灁䅁䅁䅱䅉䑁䅧䅁䩂䙁䅅睘呂䙁䅉睘呂䙁䅕村時䕁䅑兒䍂䙁䅑睘䙂䕁䅉兓啂䕁䅑兑時䕁䅍兑兂䕁䅕䅗䅁䥁䉫䅁畁䅁䅁兓剂䙁䄸杔兂䙁䅁兒時䑁䅕兗卂䙁䄸兑佂䕁䄴睘䡂䙁䅉睔塂䙁䅑䅓䅁䩁䌰䅁䭂䅁䅁睗䱂䝁䅕入呂䡁䅑兙あ䡁䅍睘あ䝁䅕督あ䝁䅙兡獂䝁䅕杌㑂䝁䅷督㑂䙁䄰睕潂䝁䅕党あ䑁䅅光歁䕁䅑䅊ㅁ䑁䅕䅁敂䅁䅁杪䅁䍁䅣睗䑂䝁䄸䅣㕂䍁䅁睢浂䍁䅁睕兂䕁䅣睘䑂䝁䄸兢睂䝁䅅杢㕂䙁䄸睓求䡁䅫睕あ䝁䅅䅤穂䙁䄸杤祁䙁䄸杢求䡁䅣杌㑂䝁䅷督瑂䙁䄰兓畂䝁䅍睢瑂䝁䅕睘呂䡁䅑兙あ䝁䅕兢求䝁䄴䅤湁䍁䅅䅊䙂䍁䅑李㙁䍁䅑兕歁䑁䅙䅁歃睂䅁杚䅁䕁䅍兙睂䝁䅫䅤桂䝁䅷䅉䵂䝁䄸督穂䍁䅁睑桂䡁䅉杣㕂䝁䅙睢祂䡁䅣兙祂䝁䅑䅌杁䕁䅍兤祂䡁䅉党畂䡁䅑䅉婂䝁䅕兙祂䍁䅁䅋卂䝁䅕䅣療䡁䅉䅤求䝁䅑克䅁乁䌰䅁流䅁䅁兓剂䙁䄸睔兂䙁䅑兓偂䕁䄴睕時䕁䅣杕䉂䕁䄴䅖䙂䕁䅑䅁ぁ睁䅁䅙䅁䙁䅕杢歂䡁䅉兙㍂䝁䄴䅉䑂䡁䅉党歂䝁䅫䅤杁䙁䅁睢祂䡁䅑兡療䝁䄴䅉療䝁䅙䅉啂䝁䅕杣瑂䍁䅁䅔療䝁䅅杢穂䍁䅁䅋卂䝁䅕䅣療䡁䅉䅤求䝁䅑克䅁䅁䉫䅁捂䅁䅁睗乂䕁䅫睘䱂䝁䅕入呂䡁䅑兙あ䡁䅍睘㉂䑁䅅杌㑂䝁䅷督瑂䙁䄰睑桂䡁䅁兡あ䝁䅅䅢灂䡁䅯兙あ䝁䅫睢畂䍁䅅䅊䙂䍁䅑䅎㙁䍁䅑杓歁䑁䅑䅁敃睁䅁䅙䅁䙁䅳兔䩂䙁䄸睓求䡁䅫睕あ䝁䅅䅤穂䙁䄸杤硁䍁䄴䅥獂䡁䅍兢摂䕁䅍兙睂䝁䅫䅤桂䝁䅷兡㙂䝁䅅䅤灂䝁䄸杢桁䍁䅑兒歁䑁䅑䅏㙁䍁䅑杓歁䑁䅑䅏䅁䭁䑑䅁畂䅁䅁睑桂䡁䅁兡あ䝁䅅䅢杁䕁䅷睢穂䡁䅍䅉䑂䝁䅅杣祂䡁䅫杚療䡁䅉睤桂䡁䅉䅚獁䍁䅁睑ㅂ䡁䅉杣求䝁䄴䅤杁䙁䅫党桂䡁䅉䅉牁䍁䅁免杁䍁䅧杕求䡁䅁睢祂䡁䅑党歂䍁䅫䅁晄杁䅁䅨䅁䙁䅳兔䩂䙁䄸睑療䝁䄰䅣桂䝁䄴入時䕁䅳党㕂䙁䅍
A3: 䅤桂䡁䅑督時䡁䅙免時䍁䄴䅥獂䡁䅍兢摂䕁䅍兙睂䝁䅫䅤桂䝁䅷睘呂䡁䅑杣ㅂ䝁䅍䅤ㅂ䡁䅉党時䙁䅍兤瑂䝁䄰兙祂䡁䅫光歁䕁䅕䅊ㅁ䑁䅯䅊偂䍁䅑兎䅁偁䕑䅁畂䅁䅁睑桂䡁䅁兡あ䝁䅅䅢杁䕁䅷睢穂䡁䅍䅉䑂䝁䅅杣祂䡁䅫杚療䡁䅉睤桂䡁䅉䅚獁䍁䅁睑ㅂ䡁䅉杣求䝁䄴䅤杁䙁䅫党桂䡁䅉䅉牁䍁䅁䅎杁䍁䅧杕求䡁䅁睢祂䡁䅑党歂䍁䅫䅁汄杁䅁杋䅁䙁䅍䅕時䙁䅑兒坂䙁䄸䅖偂䙁䅑兑䵂䙁䄸杕䙂䙁䅙睘䝂䙁䅣䅒䅁䙁䝁䅁獁䅁䅁兓剂䙁䄸兒兂䙁䅍睘穁䙁䅫杕時䕁䅅杔佂䙁䄸睒卂䕁䄸睖啂䕁䅧䅁穂杁䅁杓䅁䕁䅍兙穂䝁䅧䅉䝂䡁䅉睢瑂䍁䅁睔睂䝁䅕杣桂䡁䅑兡療䝁䄴督獁䍁䅁兎杁䙁䅫杣畁䍁䅁睑䉂䕁䅣杕杁䍁䅧兊灁䅁䅁杰䅉䡁䅯䅁䑂䝁䅧兙畂䝁䅣党穂䍁䅁兡畂䍁䅁兖畂䡁䅉党橂䝁䄸睚畁䍁䅁䅖桂䡁䅧䅉䍂䝁䅕杢求䝁䅙兡あ䍁䅁睤癁䝁䅫杢杁䑁䅅䅉婂䝁䅕兙祂䍁䅁兌杁䕁䄰兡畂䍁䅁䅋卂䝁䅕䅣療䡁䅉䅤求䝁䅑克䅁䉁䑣䅁㡁䅁䅁睑療䝁䄰兢療䝁䄴䅉䙂䡁䅅兤灂䡁䅑入獁䍁䅁兎杁䙁䅫杣畁䍁䅁睑䉂䕁䅣杕杁䍁䅧兊灁䅁䅁䅰䅉䑁䅯䅁䑂䝁䄸兢睂䝁䄸杢求䝁䄴䅤杁䕁䅅兢療䡁䅕杢あ䍁䅁睔ㅂ䡁䅑督あ䝁䅅杢歂䝁䅫杢湂䅁䅁睪䅙䝁䅙䅁扂䕁䅳党㕂䙁䅍䅤桂䡁䅑督時䡁䅑党穂䡁䅑杚灂䝁䅷党畁䡁䅧䅢穂䝁䄰兘䑂䝁䅅䅣灂䡁䅑兙獂䝁䅫来桂䡁䅑兡療䝁䄴光歁䕁䅙䅊ㅁ䑁䅅杏歁䕁䅳䅊ㅁ䑁䅅䅁慄䅁䅁杊䅁䕁䅍睢瑂䡁䅁睢畂䝁䅕杢あ䍁䅁睑ㅂ䡁䅉杣求䝁䄴睙㕂䅁䅁兰䅙䉁䅷䅁䩂䙁䅅睘啂䕁䅕杖時䕁䅕村䩂䙁䅑䅒䉂䅁䅁杚䅙䥁䄴䅁湁䙁䅳睑療䡁䅁入杁䝁䄸杚杁䙁䅍䅕䡂䙁䄸睑療䝁䄰䅣桂䝁䄴入時䕁䅳党㕂䙁䅍䅤桂䡁䅑督時䡁䅙杍時䝁䄴党㍂䍁䄴䅥獂䡁䅍兢摂䕁䅉兙獂䝁䅅杢橂䝁䅕睘呂䝁䅧党求䡁䅑睊桁䍁䅑睑歁䑁䅅免㙁䍁䅑睑歁䑁䅉䅍ぁ䅁䅁䅴䅣䙁䅙䅁䑂䝁䄸杢あ䡁䅉兙橂䡁䅑兤桂䝁䅷䅉偂䝁䅉䅢灂䝁䅣兙あ䝁䅫睢畂䡁䅍䅉䕂䡁䅕党杁䍁䅳䅉祁䍁䅁䅋卂䝁䅕䅣療䡁䅉䅤求䝁䅑克䅁乁䉙䅁畁䅁䅁兓剂䙁䄸睑䉂䕁䅷睑噂䕁䅷兑啂䕁䅫睔佂䙁䄸䅖婂䙁䅁兒時䕁䅉睕䅁䍁䑷䅁浂䅁䅁睑療䝁䄴䅤祂䝁䅅睙あ䡁䅕兙獂䍁䅁睔楂䝁䅷兡湂䝁䅅䅤灂䝁䄸杢穂䍁䅁䅒ㅂ䝁䅕䅌杁䕁䄴党㑂䡁䅑䅉ㅁ䍁䅁兗祂䡁䅍䅉潁䙁䅉党睂䝁䄸杣あ䝁䅕䅚灁䅁䅁朳䅅䕁䅉䅁䕂䝁䅕䅣祂䝁䅕睙灂䝁䅅䅤灂䝁䄸杢杁䍁䅙䅉䉂䝁䄰睢祂䡁䅑杌杁䍁䅧杕求䡁䅁睢祂䡁䅑党歂䍁䅫䅁湃䅁䅁䅡䅁䙁䅳兔䩂䙁䄸睓求䡁䅫睕あ䝁䅅䅤穂䙁䄸杤硁䍁䄴䅥獂䡁䅍兢摂䕁䅍兙睂䝁䅫䅤桂䝁䅷睘呂䡁䅑杣ㅂ䝁䅍䅤ㅂ䡁䅉党時䙁䅍兤瑂䝁䄰兙祂䡁䅫光歁䕁䅍䅊ぁ䅁䅁共䅍䑁䅉䅁䩂䙁䅅睘呂䙁䅕村時䕁䅑兒䍂䙁䅑睘䙂䕁䅉兓啂䕁䅑兑時䕁䅍兑兂䕁䅕䅗䅁䩁䉣䅁歁䅁䅁兓剂䙁䄸睔啂䕁䅧兒卂䙁䄸䅒䙂䕁䅉䅖時䙁䅁睑啂䅁䅁䄸䅁䥁䅑䅁湁䙁䅳睑療䡁䅁入杁䝁䄸杚杁䙁䅍䅕䡂䙁䄸睑療䝁䄰䅣桂䝁䄴入時䕁䅳党㕂䙁䅍䅤桂䡁䅑督時䡁䅙杍時䝁䄴党㍂䍁䄴䅥獂䡁䅍兢摂䕁䅳党㕂䙁䄸睕あ䝁䅅䅤穂䍁䅣光歁䕁䄰䅊祁䑁䅙杏歁䕁䄸䅊祁䑁䅙䅁瑁睂䅁䅗䅁䕁䅑兡獂䡁䅕䅤求䝁䅑䅉䙂䙁䅁睕杁䕁䅉党浂䝁䄸杣求䍁䅁兒㑂䡁䅑杣桂䍁䅷䅉硁䍁䅁兗求䝁䅅杣杁䕁䅣杣療䡁䅣䅤潂䍁䅁䅋汁䍁䅫䅁歂䅁䅁䅔䅁䕁䄴睢祂䝁䄰兙獂䝁䅫来求䝁䅑䅉佂䝁䅕䅤杁䕁䅫杢橂䝁䄸兢求䍁䅷䅉穁䍁䅁兗祂䍁䄴䅉䑂䕁䅅睒卂䍁䅁䅋汁䍁䅫䅁歂杁䅁䅈䅁䕁䅫兕時䕁䅍䅔時䕁䅑兖䙂䙁䄸睑婂䑁䅉䅁瑃允䅁杕䅁䕁䅑兡獂䡁䅕䅤求䝁䅑䅉䙂䙁䅁睕杁䕁䅉党浂䝁䄸杣求䍁䅁兒㑂䡁䅑杣桂䍁䅷䅉祁䍁䅁兗祂䍁䄴䅉䑂䕁䅅睒卂䍁䅁䅋汁䍁䅫䅁啂杁䅁䅔䅁䕁䄴睢祂䝁䄰兙獂䝁䅫来求䝁䅑䅉佂䝁䅕䅤杁䕁䅫杢橂䝁䄸兢求䍁䅷䅉祁䍁䅁兗祂䍁䄴䅉䑂䕁䅅睒卂䍁䅁䅋汁䍁䅫䅁䍂杁䅁杕䅁䕁䅑兡獂䡁䅕䅤求䝁䅑䅉䙂䙁䅁睕杁䕁䅉党浂䝁䄸杣求䍁䅁兒㑂䡁䅑杣桂䍁䅷䅉穁䍁䅁兗祂䍁䄴䅉䑂䕁䅅睒卂䍁䅁䅋汁䍁䅫䅁あ杁䅁杓䅁䕁䅑兡㉂䝁䅫䅚求䝁䄴䅚杁䙁䅁党祂䍁䅁睕潂䝁䅅杣求䍁䅷䅉硁䍁䅁兗祂䍁䄴䅉䡂䡁䅉睢㍂䡁䅑䅡杁䍁䅧兊灁䅁䅁䅏䅉䑁䅷䅁偂䡁䅁䅤灂䝁䄸杢穂䑁䅯䅉呂䡁䅑兙あ䝁䅫督あ䝁䅫睙㥁䕁䅧兓䡂䕁䅧䅌佂䕁䅅児佂䕁䅅䅁湂杂䅁䅓䅁䕁䅑兡㉂䝁䅫䅚求䝁䄴䅚杁䙁䅁党祂䍁䅁睕潂䝁䅅杣求䍁䅷䅉祁䍁䅁兗求䝁䅅杣杁䕁䅍兑䡂䙁䅉䅉潁䍁䅕克䅁䝁䍁䅁䝂䅁䅁䅒灂䡁䅙兡歂䝁䅕杢歂䍁䅁䅕求䡁䅉䅉呂䝁䅧兙祂䝁䅕䅌杁䑁䅕䅉婂䡁䅉杌杁䕁䅍兑䡂䙁䅉䅉潁䍁䅕克䅁䭁䌴䅁畁䅁䅁兒䍂䕁䅫䅖獁䍁䅁免杁䙁䅫杣畁䍁䅁睒祂䝁䄸睤あ䝁䅧䅉潁䍁䅕克䅁䍁䍙䅁坂䅁䅁睗䱂䝁䅕入呂䡁䅑兙あ䡁䅍睘あ䝁䅕督あ䝁䅙兡獂䝁䅕杌㑂䝁䅷督㑂䙁䄰睕潂䝁䅕党あ䑁䅅光歁䕁䅕䅊祁䑁䅅杏歁䕁䅫䅊祁䑁䅅䅁䕂䅁䅁杣䅁䙁䅳睕兂䕁䅣睘䑂䝁䄸兢睂䝁䅅杢㕂䙁䄸睓求䡁䅫睕あ䝁䅅䅤穂䙁䄸杤硁䍁䄴䅥獂䡁䅍兢摂䕁䅍兙睂䝁䅫䅤桂䝁䅷兡㙂䝁䅅䅤灂䝁䄸杢桁䍁䅑兒歁䑁䅑䅏㙁䍁䅑杓歁䑁䅑䅏䅁偁䙳䅁㑂䅁䅁睊扂䕁䅍睢睂䡁䅫䅉療䝁䅙䅉呂䙁䅁睒時䕁䅍睢瑂䡁䅁兙畂䡁䅫睘䱂䝁䅕入呂䡁䅑兙あ䡁䅍睘㉂䑁䅉睘畂䝁䅕睤畁䡁䅧䅢穂䝁䄰兘䱂䝁䅕入時䙁䅍䅤桂䡁䅑督湁䍁䅅䅊啂䍁䅑兎ㅁ䅁䅁八䅣䍁䅯䅁䙂䕁䅉兓啂䍁䅷䅉祁䍁䅁兗祂䍁䄴䅉䑂䕁䅅睒卂䍁䅁䅋汁䍁䅫䅁兂杁䅁杋䅁䕁䅕村䩂䙁䅑䅌杁䑁䅍䅉婂䡁䅉杌杁䕁䅍兑䡂䙁䅉䅉潁䍁䅕克䅁䡁䍙䅁楁䅁䅁兓剂䙁䄸睖啂䕁䅑睘䉂䙁䅙睒時䕁䅫杕時䕁䅍兗䅁佁䉫䅁睁䅁䅁兒䍂䕁䅫䅖䉂䍁䅷䅉硁䍁䅁兗祂䍁䄴䅉䡂䡁䅉睢㍂䡁䅑䅡杁䍁䅧兊灁䅁䅁杆䅉䍁䅷䅁䩂䙁䅅睘啂䕁䅅䅗時䕁䅉兒佂䕁䅕杒䩂䙁䅑睘䑂䕁䅙睘祁䙁䅫杕䅁偁䍑䅁㑂䅁䅁睗呂䙁䅁睒時䕁䅍睢瑂䡁䅁兙畂䡁䅫睘䱂䝁䅕入呂䡁䅑兙あ䡁䅍睘㉂䑁䅅杌㑂䝁䅷督瑂䙁䄰兓畂䝁䅍睢瑂䝁䅕睘呂䡁䅑兙あ䝁䅕兢求䝁䄴䅤桁䍁䅑睑歁䑁䅅免㙁䍁䅑睑歁䑁䅅睎ㅁ䅁䅁朵䅕䕁䅉䅁䩂䙁䅅睘䑂䕁䄸杔啂䙁䅉兑䑂䙁䅑睘偂䕁䅉䅔䩂䕁䅣兑啂䕁䅫睔佂䙁䄸杔䙂䙁䅧䅖時䕁䅙兓坂䕁䅕䅁摄允䅁䅌䅁䕁䅕村䩂䙁䅑兑獁䍁䅁杍杁䙁䅫杣畁䍁䅁睑䉂䕁䅣杕杁䍁䅧兊灁䅁䅁杔䅉䥁䅑䅁湁䙁䅳睑療䡁䅁入杁䝁䄸杚杁䙁䅍䅕䡂䙁䄸睑療䝁䄰䅣桂䝁䄴入時䕁䅳党㕂䙁䅍䅤桂䡁䅑督時䡁䅙杍時䝁䄴党㍂䍁䄴䅥獂䡁䅍兢摂䕁䅳党㕂䙁䄸睕あ䝁䅅䅤穂䍁䅣光歁䕁䄰䅊祁䑁䅕杏歁䕁䄸䅊祁䑁䅕䅁牁睂䅁䅌䅁䕁䅕村䩂䙁䅑兑獁䍁䅁睍杁䙁䅫杣畁䍁䅁睑䉂䕁䅣杕杁䍁䅧兊灁䅁䅁杣䅉䍁䅷䅁䙂䕁䅉兓啂䕁䅅䅌杁䑁䅕䅉婂䡁䅉杌杁䕁䅍兑䡂䙁䅉䅉潁䍁䅕克䅁䩁䍉䅁㑁䅁䅁杔求䡁䅑䅉䕂䝁䅕杙あ䍁䄸䅋䙂䕁䅉兓啂䕁䅑兑瑁䕁䅍兑兂䕁䅕䅗灁䍁䅁䅋㑂䍁䅫䅁䥃允䅁䅈䅁䕁䅕村䩂䙁䅑䅒䉂䍁䅁䅋歁䑁䅁䅍睁䍁䅫䅁灂䅁䅁䅊䅁䕁䅕村䩂䙁䅑䅒䉂䍁䅁䅋卂䝁䅕䅣療䡁䅉䅤求䝁䅑克䅁䅁䅯䅁歁䅁䅁兒䍂䕁䅫䅖䕂䕁䅅䅉乂䝁䅅杣湂䝁䅫杢杁䍁䅧兊灁䅁䅁杁䅉䑁䅉䅁䙂䕁䅉兓啂䕁䅑兑獁䍁䅁免杁䙁䅫杣畁䍁䅁睒祂䝁䄸睤あ䝁䅧䅉潁䍁䅕克䅁䍁䍑䅁捃䅁䅁睊扂䕁䅍睢睂䡁䅫䅉療䝁䅙䅉呂䙁䅁睒時䕁䅍睢瑂䡁䅁兙畂䡁䅫睘䱂䝁䅕入呂䡁䅑兙あ䡁䅍睘㉂䑁䅉睘畂䝁䅕睤畁䡁䅧䅢穂䝁䄰兘䑂䝁䅅䅣灂䡁䅑兙獂䙁䄸睕あ䡁䅉兤橂䡁䅑兤祂䝁䅕睘杁䕁䅑党あ䝁䅅兡獂䡁䅍䅉湁䍁䅅䅊䩂䍁䅑䅎ぁ䅁䅁杧䅣䑁䅉䅁䙂䕁䅉兓啂䕁䅑兑獁䍁䅁杍杁䙁䅫党桂䡁䅉督杁䕁䅍兑䡂䙁䅉䅉潁䍁䅕克䅁䕁䍧䅁䍂䅁䅁睕ㅂ䝁䅉杌杁䕁䅑党楂䡁䅑䅉癁䍁䅁䅋䙂䕁䅉兓啂䕁䅑兑杁䍁䄰䅉䑂䝁䅅䅣求䡁䅧克杁䍁䅧䅥灁䅁䅁䅭䅅䑁䅉䅁䙂䕁䅉兓啂䕁䅑兑獁䍁䅁睍杁䙁䅫党桂䡁䅉督杁䕁䅍兑䡂䙁䅉䅉潁䍁䅕克䅁䝁䌴䅁潂䅁䅁睗呂䙁䅁睒時䕁䅍睢瑂䡁䅁兙畂䡁䅫睘䱂䝁䅕入呂䡁䅑兙あ䡁䅍睘㉂䑁䅉杌㑂䝁䅷督瑂䙁䄰兓畂䝁䅍睢瑂䝁䅕睘呂䡁䅑兙あ䝁䅕兢求䝁䄴䅤桁䍁䅑睑歁䑁䅙䅁楄睂䅁杍䅁䕁䅕村䩂䙁䅑䅒䉂䍁䅷䅉ㅁ䍁䅁兗求䝁䅅杣穂䍁䅁睑䉂䕁䅣杕杁䍁䅧兊灁䅁䅁䅫䅉䝁䅉䅁䙂䝁䅅杣畂䝁䅫杢湂䡁䅍䅉䝂䡁䅉睢瑂䍁䅁睑療䝁䄴䅤畁䍁䅁睔睂䝁䅕杣桂䡁䅑兡療䝁䄴督獁䍁䅁免杁䙁䅫杣畁䍁䅁睒祂䝁䄸睤あ䝁䅧䅉潁䍁䅕克䅁䍁䍉䅁敂䅁䅁兒桂䡁䅉杢灂䝁䄴睚穂䍁䅁杒祂䝁䄸兢杁䕁䅍睢畂䡁䅑杌杁䕁䄸䅣求䡁䅉兙あ䝁䅫睢畂䡁䅍䅌杁䑁䅉䅉婂䡁䅉杌杁䕁䅍兑䡂䙁䅉䅉潁䍁䅕克䅁䕁䍙䅁敂䅁䅁兒桂䡁䅉杢灂䝁䄴睚穂䍁䅁杒祂䝁䄸兢杁䕁䅍睢畂䡁䅑杌杁䕁䄸䅣求䡁䅉兙あ䝁䅫睢畂䡁䅍䅌杁䑁䅍䅉婂䡁䅉杌杁䕁䅍兑䡂䙁䅉䅉潁䍁䅕克䅁䝁䍷䅁敂䅁䅁兒桂䡁䅉杢灂䝁䄴睚穂䍁䅁杒祂䝁䄸兢杁䕁䅍睢畂䡁䅑杌杁䕁䄸䅣求䡁䅉兙あ䝁䅫睢畂䡁䅍䅌杁䑁䅕䅉婂䡁䅉杌杁䕁䅍兑䡂䙁䅉䅉潁䍁䅕克䅁䥁䌴䅁慂䅁䅁睔睂䝁䅕杣桂䡁䅑兡畂䝁䅣䅉䵂䝁䅕兙穂䝁䅕䅉䑂䝁䄸兢瑂䝁䅫䅤瑂䝁䅕杢あ䍁䅁䅒ㅂ䝁䅕䅉牁䑁䅕䅉潁䙁䅉党睂䝁䄸杣あ䝁䅕䅚灁䅁䅁䅷䅅䑁䅧䅁呂䝁䅕睙ㅂ䡁䅉兡あ䝁䅫来求䝁䅑䅉䕂䝁䅕杙あ䍁䅁䅋卂䝁䅕䅣療䡁䅉䅤求䝁䅑克䅁䕁䉅䅁獂䅁䅁䅖桂䡁䅧䅉䍂䝁䅕杢求䝁䅙兡あ䍁䅁睑桂䡁䅉杣㕂䝁䅙睢祂䡁䅣兙祂䝁䅑䅌杁䕁䅍兤祂䡁䅉党畂䡁䅑䅉婂䝁䅕兙祂䍁䅁睋杁䑁䅅䅉潁䙁䅉党睂䝁䄸杣あ䝁䅕䅚灁䅁䅁儹䅉䙁䅉䅁乂䝁䅅䅥畁䍁䅁兗求䝁䅅杣杁䝁䅙睢祂䍁䅁䅖桂䡁䅧䅉䍂䝁䅕杢求䝁䅙兡あ䍁䅁睑桂䡁䅉杣㕂䍁䅁杒療䡁䅉睤桂䡁䅉䅚杁䅁䅁允䅍䕁䅁䅁䙂䝁䅅杣畂䝁䅫杢湂䡁䅍䅉浂䡁䅉睢瑂䍁䅁睑療䝁䄴䅤畁䍁䅁睔睂䡁䅍杌杁䍁䅧䅊睁䑁䅁䅍灁䅁䅁条䅁䕁䅯䅁扂䕁䅳党㕂䙁䅍䅤桂䡁䅑督時䡁䅑党穂䡁䅑杚灂䝁䅷党畁䡁䅧䅢穂䡁䅧兘呂䝁䅧党求䡁䅑免桁䍁䅑兒歁䑁䅕睍䅁䡁䅙䅁坁䅁䅁兒畂䡁䅑兡あ䡁䅫䅉䩂䕁䅑䅉䅁䍁䅉䅁睂䅁䅁睗乂䕁䅫睘䑂䝁䄸兢睂䝁䅅杢㕂䙁䄸睓求䡁䅫睕あ䝁䅅䅤穂䙁䄸杤硁䍁䄴䅥獂䡁䅍兢摂䕁䅍兙睂䝁䅫䅤桂䝁䅷兡㙂䝁䅅䅤灂䝁䄸杢桁䍁䅑兒歁䑁䅑睎㙁䍁䅑杓歁䑁䅑睎䅁䩁䔴䅁䥁䅁䅁杒剂䑁䅁䅁㑂杂䅁䅅䅁䕁䅙兕祁䑁䅉䅍祁䑁䅕䅁㕂杂䅁䅩䅁䍁䅣睗䑂䝁䄸䅣㕂䍁䅁睢浂䍁䅁睕兂䕁䅣睘䑂䝁䄸兢睂䝁䅅杢㕂䙁䄸睓求䡁䅫睕あ䝁䅅䅤穂䙁䄸杤祁䙁䄸杢求䡁䅣杌㑂䝁䅷督瑂䙁䄰村桂䝁䅷兙畂䝁䅍党時䙁䅍䅡求䝁䅕䅤湁䍁䅅䅊䙂䍁䅑李㙁䍁䅑䅕歁䑁䅙䅁䑂睂䅁杗䅁䙁䅳兔䩂䙁䄸睑療䝁䄰䅣桂䝁䄴入時䕁䅳党㕂䙁䅍䅤桂䡁䅑督時䡁䅙免畁䡁䅧䅢穂䝁䄰兘䱂䝁䅕入時䙁䅍䅤桂䡁䅑督桁䍁䅑兒歁䑁䅕䅎䅁䥁䔸䅁䭁䅁䅁杒婂䍁䄰免䅁䉁䄸䅁浂䅁䅁睗乂䕁䅫睘䑂䝁䄸兢睂䝁䅅杢㕂䙁䄸睓求䡁䅫睕あ䝁䅅䅤穂䙁䄸杤硁䍁䄴䅥獂䡁䅍兢摂䕁䅳党㕂䙁䄸睕あ䝁䅅䅤穂䍁䅅䅊坂䍁䅑兎㍁䑁䅯䅊塂䍁䅑兎㍁䅁䅁兲䅕䅁䄴䅁䝂䙁䅫杍睁䑁䅉睍䅁䱁䝅䅁煁䅁䅁兓剂䙁䄸睔䵂䙁䄸睑偂䕁䄰兔時䕁䄴兒奂䙁䅑睘䝂䕁䅫杖䙂䅁䅁具䅅䅁䄴䅁䝂䙁䅫杍睁䑁䅉䅎䅁䡁䝣䅁煂䅁䅁睖桂䡁䅉杣桂䝁䄴䅤穂䍁䅁睑桂䝁䄴睙求䝁䅷䅢求䝁䅑䅉䕂䡁䅕杣灂䝁䄴睚杁䡁䅑䅡求䍁䅁䅕求䡁䅉兡療䝁䅑䅌杁䙁䅑睢あ䝁䅅䅢杁䍁䅧兙橂䡁䅑兤桂䝁䅷克䅁䕁䑕䅁䅂䅁䅁杒桂䝁䅫杣杁䙁䅙兙獂䡁䅕党杁䝁䄸杚杁䕁䅅督穂䝁䅕䅤穂䍁䅁䅋卂䝁䅕䅣療䡁䅉䅤求䝁䅑克䅁偁䍣䅁㉁䅁䅁杒灂䡁䅧党歂䍁䅁杕桂䡁䅑党杁䕁䅑党楂䡁䅑䅉潁䙁䅉党睂䝁䄸杣あ䝁䅕䅚灁䅁䅁睍䅅䝁䅧䅁扂䕁䄰兓時䕁䅍睢瑂䡁䅁兙畂䡁䅫睘䱂䝁䅕入呂䡁䅑兙あ䡁䅍睘㉂䑁䅅睘畁䡁䅧䅢穂䝁䄰兘䱂䝁䅕入時䙁䅍䅤桂䡁䅑督桁䍁䅑䅒歁䑁䅕睎㙁䍁䅑䅒歁䑁䅕䅏䅁䵁䕧䅁䅂䅁䅁杒灂䡁䅧党歂䍁䅁杕桂䡁䅑党杁䕁䅑党楂䡁䅑睌杁䙁䅑睢あ䝁䅅䅢杁䕁䅑党楂䡁䅑䅉潁䍁䅕克䅁䝁䈸䅁敂䅁䅁䅔求䡁䅙党獂䍁䅁免杁䕁䅷兡桂䝁䅉兡獂䝁䅫䅤灂䝁䅕督杁䍁䄰䅉剂䡁䅕睢あ䝁䅕䅚杁䙁䅁杣灂䝁䅍党穂䍁䅁䅋卂䝁䅕䅣療䡁䅉䅤求䝁䅑克䅁䉁䐸䅁獁䅁䅁杕杁䍁䅙䅉䕂䍁䅁兒㑂䡁䅁杌杁䍁䅧杕求䡁䅁睢祂䡁䅑党歂䍁䅫䅁穃䅁䅁䅏䅁䕁䅫兕時䙁䅑睔啂䕁䅅䅔時䙁䅉兒坂䙁䄸杍婂䙁䅉睘䉂䕁䄴杔時䕁䅣杕偂䙁䅣䅖䥂䅁䅁児䅉䑁䅁䅁䡂䡁䅉睢穂䡁䅍䅉兂䡁䅉睢浂䝁䅫䅤杁䍁䅧杕求䡁䅁睢祂䡁䅑党歂䍁䅫䅁䥁䅁䅁条䅁䙁䅳兔䩂䙁䄸睑療䝁䄰䅣桂䝁䄴入時䕁䅳党㕂䙁䅍䅤桂䡁䅑督時䡁䅙免畁䡁䅧䅢穂䝁䄰兘䱂䝁䅕入時䙁䅍䅤桂䡁䅑督桁䍁䅑睑歁䑁䅅䅍㍁䑁䅯䅊䑂䍁䅑免硁䑁䅅䅁坃䅂䅁杍䅁䕁䅫兕時䙁䅣䅖䕂䙁䄸兑坂䕁䅣睘䩂䙁䅉睘啂䕁䄸䅖䉂䕁䅷睘䕂䕁䅕村啂䅁䅁眵䅅䍁䅧䅁䩂䙁䅅睘呂䕁䅕睑偂䕁䄴䅒時䕁䅷兓䙂䕁䄴睘䕂䕁䅕村啂䅁䅁杒䅅䍁䅯䅁䩂䙁䅅睘䡂䙁䅁睘祁䙁䅫杕時䕁䅅杔佂䙁䄸睒卂䕁䄸睖啂䕁䅧䅁䩂杁䅁杤䅁䙁䅳兔䩂䙁䄸睑療䝁䄰䅣桂䝁䄴入時䕁䅳党㕂䙁䅍䅤桂䡁䅑督時䡁䅙免畁䡁䅧䅢穂䝁䄰兘䩂䝁䄴睙療䝁䄰党時䙁䅍䅤桂䡁䅑党瑂䝁䅕杢あ䍁䅅䅊䑂䍁䅑免硁䑁䅯䅊䑂䍁䅑免㍁䑁䅕䅁祃兂䅁杢䅁䙁䅳兔䩂䙁䄸睑療䝁䄰䅣桂䝁䄴入時䕁䅳党㕂䙁䅍䅤桂䡁䅑督時䡁䅙免畁䡁䅧䅢穂䝁䄰兘䑂䝁䅅䅣灂䡁䅑兙獂䝁䅫来桂䡁䅑兡療䝁䄴光歁䕁䅍䅊㕁䑁䅯䅊䑂䍁䅑杍ㅁ䅁䅁杅䅑䕁䅁䅁䩂䙁䅅睘呂䙁䅉睘噂䕁䄴睕䙂䕁䅍兖卂䕁䅕䅒時䕁䅉睔佂䕁䅑睕時䕁䄴睔啂䕁䅕睕時䙁䅁睑啂䅁䅁䅙䅅䑁䅁䅁䡂䡁䅉睢穂䡁䅍䅉兂䡁䅉睢浂䝁䅫䅤杁䕁䄰兙祂䝁䅣兡畂䍁䅁䅋汁䍁䅫䅁㙄允䅁杏䅁䕁䅣杣療䡁䅍督杁䙁䅁杣療䝁䅙兡あ䍁䅷䅉穁䍁䅁兗祂䍁䄴䅉䑂䕁䅅睒卂䍁䅁䅋汁䍁䅫䅁楂杁䅁杒䅁䕁䄴兤瑂䝁䅉党祂䍁䅁睢浂䍁䅁䅖祂䝁䅅䅚求䡁䅍䅉䙂䡁䅧党橂䡁䅕䅤求䝁䅑䅉潁䝁䅅睙あ䡁䅕兙獂䍁䅫䅁䵃睁䅁杔䅁䕁䅉兙畂䝁䅳䅉療䝁䅙䅉䉂䝁䄰党祂䝁䅫睙桂䍁䅁睑療䡁䅉䅣療䡁䅉兙あ䝁䅫睢畂䍁䅁䅋佂䙁䅫睕䙂䑁䅯村䉂䕁䅍克䅁䕁䥁䅁㙁䅁䅁睒祂䝁䄸督穂䍁䅁䅕祂䝁䄸杚灂䡁䅑䅌杁䑁䅕䅉婂䡁䅉杌杁䕁䅍兑䡂䙁䅉䅉潁䍁䅕克䅁䥁䍯䅁畁䅁䅁兓剂䙁䄸䅔䩂䕁䅅村䩂䕁䅷兓啂䕁䅫兒呂䙁䄸䅔䙂䙁䅙兒䵂䙁䄸睍䅁䍁䑉䅁獁䅁䅁兓剂䙁䄸䅒䑂䙁䅍睘呂䕁䅕睑噂䙁䅉兓啂䙁䅫睘䵂䕁䅕杖䙂䕁䅷䅁扃杂䅁䅘䅁䕁䅧党歂䝁䅣兡畂䝁䅣䅉桂䝁䄴䅚杁䕁䅑党祂䝁䅫杤桂䡁䅑兡㉂䝁䅕䅉䉂䝁䅑条ㅂ䡁䅍䅤瑂䝁䅕杢あ䡁䅍䅉潁䙁䅉党睂䝁䄸杣あ䝁䅕䅚灁䅁䅁睔䅅䑁䅁䅁䩂䙁䅅睘䙂䕁䅉兓啂䕁䅅睘ㅁ䙁䅫杕時䕁䅅杔佂䙁䄸睒卂䕁䄸睖啂䕁䅧䅁剃杁䅁䅙䅁䙁䅳兔䩂䙁䄸睓求䡁䅫睕あ䝁䅅䅤穂䙁䄸杤硁䍁䄴䅥獂䡁䅍兢摂䕁䅍兙睂䝁䅫䅤桂䝁䅷兡㙂䝁䅅䅤灂䝁䄸杢桁䍁䅑兒歁䑁䅑䅏㙁䍁䅑䅕歁䑁䅑䅏䅁䱁䑫䅁捁䅁䅁兓剂䙁䄸兑䍂䙁䅍睘兂䕁䅕杕䩂䕁䄸䅒䅁䡁䝙䅁㑁䅁䅁兓剂䙁䄸兑䑂䕁䅍䅖時䙁䅉兒䑂䙁䅙睘祁䙁䅫杕時䕁䅅杔佂䙁䄸睒卂䕁䄸睖啂䕁䅧䅁䑂杁䅁䅏䅁䕁䅫兕時䕁䅅睑䑂䙁䅑睘卂䕁䅕睑坂䙁䄸睍婂䙁䅉睘䉂䕁䄴杔時䕁䅣杕偂䙁䅣䅖䥂䅁䅁兡䅉䥁䅑䅁湁䙁䅳睑療䡁䅁入杁䝁䄸杚杁䙁䅍䅕䡂䙁䄸睑療䝁䄰䅣桂䝁䄴入時䕁䅳党㕂䙁䅍䅤桂䡁䅑督時䡁䅙杍時䝁䄴党㍂䍁䄴䅥獂䡁䅍兢摂䕁䅳党㕂䙁䄸睕あ䝁䅅䅤穂䍁䅣光歁䙁䅣䅊ㅁ䑁䅣杏歁䙁䅧䅊ㅁ䑁䅣䅁千睂䅁杫䅁䕁䄸䅣あ䝁䅫睢畂䡁䅍杏杁䕁䅍兤祂䡁䅉児噂䙁䅍䅒獁䍁䅁兔桂䝁䅣児䉂䝁䅍䅤ㅂ䝁䅅䅢穂䍁䅷睑療䝁䄴杤乂䝁䅕䅤潂䝁䄸䅚㥁䕁䄰兓祂䝁䅕睙療䝁䄰兢求䝁䄴䅚求䝁䅑䅌杁䕁䄴兑㥁䍁䅷䅉啂䝁䅕杣瑂䑁䄰党畂䍁䄰兖呂䅁䅁杖䅁䑁䅧䅁䩂䙁䅅睘䉂䕁䅍睑啂䙁䄸杕䙂䕁䅍杖時䑁䅕兗卂䙁䄸兑佂䕁䄴睘䡂䙁䅉睔塂䙁䅑䅓䅁䥁䍳䅁啂䅁䅁兔桂䡁䅧杌杁䙁䅫党桂䡁䅉䅉浂䝁䄸杣杁䕁䅍兙睂䝁䅫䅤桂䝁䅷䅉䵂䝁䄸督穂䍁䅁睑桂䡁䅉杣㕂䍁䅁杒療䡁䅉睤桂䡁䅉䅚杁䅁䅁眸䅉䙁䅁䅁扂䕁䅳党㕂䙁䅍䅤桂䡁䅑督時䡁䅑党穂䡁䅑杚灂䝁䅷党畁䡁䅧䅢穂䝁䄰兘䱂䝁䅕入時䙁䅍䅤桂䡁䅑督桁䍁䅑村歁䑁䅫睎䅁䩁䅁䅁⭁䅁䅁兓剂䙁䄸兑䕂䕁䅑睘啂䕁䅅䅗時䙁䅁睔呂䕁䅫䅖䩂䕁䄸杔呂䙁䄸䅕卂䕁䅫睔卂䙁䄸兗卂䙁䅍䅁䭁睁䅁杋䅁䕁䅫兕時䕁䅅睕呂䕁䅕䅖呂䙁䄸杒䉂䕁䅫杕時䙁䅙兑䵂䙁䅕兒䅁偁䍙䅁奂䅁䅁睗䱂䝁䅕入呂䡁䅑兙あ䡁䅍睘あ䝁䅕督あ䝁䅙兡獂䝁䅕杌㑂䝁䅷督瑂䙁䄰睑桂䡁䅍䅡時䕁䅙䅢療䡁䅣光歁䕁䅙䅊ぁ䑁䅯䅊剂䍁䅑䅎䅁䱁䄴䅁啃䅁䅁睊扂䕁䅍睢睂䡁䅫䅉療䝁䅙䅉呂䙁䅁睒時䕁䅍睢瑂䡁䅁兙畂䡁䅫睘䱂䝁䅕入呂䡁䅑兙あ䡁䅍睘㉂䑁䅉睘畂䝁䅕睤畁䡁䅧䅢穂䝁䄰兘䩂䝁䄴睙療䝁䄰党時䙁䅍䅤桂䡁䅑党瑂䝁䅕杢あ䍁䅣光歁䕁䅍䅊硁䑁䅅杏歁䕁䅍䅊硁䑁䅫杍䅁䱁䡁䅁歁䅁䅁兓剂䙁䄸兑呂䙁䅍兒啂䙁䅍睘䵂䕁䅕杖䙂䕁䅷睘硁䅁䅁䅇䅍䕁䅧䅁䩂䙁䅅睘䉂䙁䅍睕䙂䙁䅑睕時䕁䄴兒啂䙁䅑兓佂䕁䅣睘偂䙁䅑䅓䙂䙁䅉睘䉂䕁䅑杓噂䙁䅍䅖乂䕁䅕杔啂䙁䅍䅁捁睁䅁䅥䅁䙁䅳兔䩂䙁䄸睑療䝁䄰䅣桂䝁䄴入時䕁䅳党㕂䙁䅍䅤桂䡁䅑督時䡁䅙免畁䡁䅧䅢穂䝁䄰兘䩂䝁䄴睙療䝁䄰党時䙁䅍䅤桂䡁䅑党瑂䝁䅕杢あ䍁䅅䅊䙂䍁䅑免㍁䑁䅙杏歁䙁䅁䅊硁䑁䅣李䅁䭁䕉䅁歁䅁䅁兓剂䙁䄸兑呂䙁䅍兒啂䙁䅍睘䵂䕁䅕杖䙂䕁䅷睘祁䅁䅁朶䅉䩁䅑䅁湁䙁䅳睑療䡁䅁入杁䝁䄸杚杁䙁䅍䅕䡂䙁䄸睑療䝁䄰䅣桂䝁䄴入時䕁䅳党㕂䙁䅍䅤桂䡁䅑督時䡁䅙杍時䝁䄴党㍂䍁䄴䅥獂䡁䅍兢摂䕁䅫杢橂䝁䄸兢求䙁䄸睕あ䝁䅅䅤求䝁䄰党畂䡁䅑睊桁䍁䅑睑歁䑁䅅免㙁䍁䅑睑歁䑁䅅兏硁䅁䅁杸䅣䍁䅑䅁䩂䙁䅅睘䉂䙁䅍睕䙂䙁䅑睕時䕁䅷兒坂䕁䅕䅔時䑁䅍䅁慁睁䅁杖䅁䙁䅳睓求䡁䅫睕あ䝁䅅䅤穂䙁䄸䅤求䡁䅍䅤浂䝁䅫䅢求䍁䄴䅥獂䡁䅍兢摂䙁䅍䅡求䝁䅕䅤硁䍁䅅䅊䝂䍁䅑杍祁䑁䅯䅊䩂䍁䅑杍祁䅁䅁杩䅁䉁䅯䅁䩂䙁䅅睘䍂䕁䅅杔䱂䙁䄸䅒䙂䕁䅉䅖䅁䑁䉁䅁慂䅁䅁睗䱂䝁䅕入呂䡁䅑兙あ䡁䅍睘あ䝁䅕督あ䝁䅙兡獂䝁䅕杌㑂䝁䅷督瑂䙁䄰睑桂䡁䅁兡あ䝁䅅䅢灂䡁䅯兙あ䝁䅫睢畂䍁䅅䅊䑂䍁䅑䅎㑁䅁䅁睚䅍䅁䅯䅁䝂䙁䅅兌穁䅁䅁睵䅣䡁䅧䅁偂䡁䅁䅤灂䝁䄸杢穂䍁䅁睔ㅂ䡁䅑杌杁䝁䅅䅤杁䡁䅑䅡求䍁䅁村求䝁䅣兡畂䝁䄴兡畂䝁䅣䅉療䝁䅙䅉あ䝁䅧党杁䙁䅁党祂䝁䅫睢歂䍁䅷䅉啂䝁䄸䅤桂䝁䅷䅉潁䝁䅅睙あ䡁䅕兙獂䍁䅫䅁⽁睁䅁杉䅁䕁䅫兕時䕁䅉兑佂䕁䅳睘䕂䕁䅕村啂䙁䄸䅕䑂䙁䅑䅁奂允䅁杍䅁䕁䅫兕時䕁䅕村䩂䙁䅑䅒䉂䙁䄸睍婂䙁䅉睘䉂䕁䄴杔時䕁䅣杕偂䙁䅣䅖䥂䅁䅁兢䅉䭁䅁䅁湁䙁䅳睑療䡁䅁入杁䝁䄸杚杁䙁䅍䅕䡂䙁䄸睑療䝁䄰䅣桂䝁䄴入時䕁䅳党㕂䙁䅍䅤桂䡁䅑督時䡁䅙免時䕁䅙兡畂䝁䅅䅢畁䡁䅧䅢穂䝁䄰兘䑂䝁䅅䅣灂䡁䅑兙獂䙁䄸睕あ䡁䅉兤橂䡁䅑兤祂䝁䅕睘杁䕁䅑党あ䝁䅅兡獂䡁䅍䅉湁䍁䅅䅊䱂䍁䅑䅎ぁ䅁䅁杦䅧䙁䅯䅁扂䕁䄰兓時䕁䅳党㕂䙁䅍䅤桂䡁䅑督時䡁䅙免畁䡁䅧䅢穂䝁䄰兘䱂䝁䅕入時䙁䅍䅤桂䡁䅑督桁䍁䅑兒歁䑁䅅䅍穁䑁䅯䅊䡂䍁䅑免睁䑁䅍䅁乄睁䅁杪䅁䍁䅣睗䑂䝁䄸䅣㕂䍁䅁睢浂䍁䅁睕兂䕁䅣睘䑂䝁䄸兢睂䝁䅅杢㕂䙁䄸睓求䡁䅫睕あ䝁䅅䅤穂䙁䄸杤祁䙁䄸杢求䡁䅣杌㑂䝁䅷督瑂䙁䄰村桂䝁䅷兙畂䝁䅍党時䙁䅍䅡求䝁䅕䅤湁䍁䅅䅊䑂䍁䅑免硁䑁䅯䅊䑂䍁䅑杍睁䑁䅍䅁穃睂䅁䅍䅁䕁䅫兕時䕁䅍兑兂䕁䅕䅗時䑁䅍兗卂䙁䄸兑佂䕁䄴睘䡂䙁䅉睔塂䙁䅑䅓䅁䥁䍅䅁流䅁䅁兓剂䙁䄸睑䉂䙁䅁睘䵂䕁䄸睕呂䙁䄸睑䝂䙁䄸免婂䙁䅉䅁捄杁䅁杊䅁䕁䅫兕時䕁䅍兑兂䙁䄸䅔偂䙁䅍睕時䕁䅍杒時䑁䅉兗卂䅁䅁朳䅉䍁䅙䅁䩂䙁䅅睘䑂䕁䅅䅕時䕁䅷睔呂䙁䅍睘䑂䕁䅙睘穁䙁䅫杕䅁佁䍁䅁ぁ䅁䅁兓剂䙁䄸睑䉂䙁䅁睘䵂䕁䄸睕呂䙁䄸睑䝂䙁䄸兑䝂䙁䅑兒卂䙁䄸杒䩂䙁䅙兒䅁乁䍧䅁煁䅁䅁兓剂䙁䄸睔兂䙁䅑兓偂䕁䄴睕時䕁䅍兑佂䕁䅍兒䵂䕁䅷兒䕂䅁䅁䅏䅍䍁䅙䅁䩂䙁䅅睘䑂䕁䅅䅕時䕁䅷睔呂䙁䅍睘䑂䕁䅙睘ぁ䙁䅫杕䅁佁䍉䅁奂䅁䅁睗䱂䝁䅕入呂䡁䅑兙あ䡁䅍睘あ䝁䅕督あ䝁䅙兡獂䝁䅕杌㑂䝁䅷督瑂䙁䄰睑桂䡁䅁兡あ䝁䅅䅢灂䡁䅯兙あ䝁䅫睢畂䍁䅅䅊䑂䍁䅑李䅁乁䄰䅁䥃䅁䅁睊扂䕁䅍睢睂䡁䅫䅉療䝁䅙䅉呂䙁䅁睒時䕁䅍睢瑂䡁䅁兙畂䡁䅫睘䱂䝁䅕入呂䡁䅑兙あ䡁䅍睘㉂䑁䅉睘畂䝁䅕睤畁䡁䅧䅢穂䝁䄰兘䱂䝁䅕入時䙁䅍䅤桂䡁䅑督湁䍁䅅䅊䙂䍁䅑免睁䑁䅙杏歁䕁䅙䅊硁䑁䅁李䅁䩁䡷䅁流䅁䅁兓剂䙁䄸睑䉂䙁䅁睘䵂䕁䄸睕呂䙁䄸睑䝂䙁䄸兎婂䙁䅉䅁歄杁䅁䅌䅁䕁䅫兕時䕁䅍兑兂䙁䄸䅔偂䙁䅍睕時䕁䅍杒時䕁䄴睔時䕁䅕䅗兂䅁䅁䄷䅉䍁䅑䅁䩂䙁䅅睘䑂䕁䅅睕䥂䙁䄸睕啂䙁䄸兓佂䙁䅙兒呂䙁䅑䅁啁䅁䅁䅌䅁䕁䅫兕時䕁䅍杒偂䙁䄸杍婂䙁䅉睘䉂䕁䄴杔時䕁䅣杕偂䙁䅣䅖䥂䅁䅁睗䅉䡁䅉䅁扂䙁䅍䅕䡂䙁䄸睑療䝁䄰䅣桂䝁䄴入時䕁䅳党㕂䙁䅍䅤桂䡁䅑督時䡁䅙杍畁䡁䅧䅢穂䝁䄰兘䩂䝁䄴睙療䝁䄰党時䙁䅍䅤桂䡁䅑党瑂䝁䅕杢あ䍁䅅䅊䙂䍁䅑李㙁䍁䅑兕歁䑁䅙䅁橄睂䅁杓䅁䙁䅳睓求䡁䅫睕あ䝁䅅䅤穂䙁䄸䅤求䡁䅍䅤浂䝁䅫䅢求䍁䄴䅥獂䡁䅍䅥摂䙁䅍䅡求䝁䅕䅤硁䍁䅅䅊䍂䍁䅑杍穁䅁䅁兓䅁䍁䅷䅁䩂䙁䅅睘䑂䕁䅙睔時䑁䅍兗卂䙁䄸兑佂䕁䄴睘䡂䙁䅉睔塂䙁䅑䅓䅁䡁䌸䅁獁䅁䅁兓剂䙁䄸睑䝂䕁䄸睘ㅁ䙁䅫杕時䕁䅅杔佂䙁䄸睒卂䕁䄸睖啂䕁䅧䅁汃杁䅁杔䅁䕁䅫兕時䕁䅍䅓䉂䕁䄴睒䙂䙁䄸兖佂䙁䅉兒䑂䕁䄸睒時䙁䅑兑奂䙁䄸村䙂䕁䄴兒䝂䕁䅫䅖時䑁䅅睘婂䙁䅉睘乂䕁䅅䅗䅁偁䍁䅁䵂䅁䅁睗乂䕁䅫睘䱂䝁䅕入呂䡁䅑兙あ䡁䅍睘㉂䑁䅅杌㑂䝁䅷督瑂䙁䄰睓求䡁䅫睘呂䡁䅑兙あ䡁䅍光歁䕁䅉䅊硁䑁䅁杍䅁䵁䑷䅁慁䅁䅁兓剂䙁䄸睑䵂䙁䄸䅒噂䕁䅕睘䑂䙁䅫䅁灃允䅁䅈䅁䕁䅫兕時䕁䅍䅔時䕁䅑兖䙂䙁䄸睑婂䑁䅍䅁穃允䅁杖䅁䕁䄴睔䵂䍁䅁睑桂䡁䅉杣㕂䝁䅙睢祂䡁䅣兙祂䝁䅑䅌杁䕁䄴睢杁䕁䅕䅥睂䝁䅫杣桂䡁䅑兡療䝁䄴䅉潁䙁䅉党睂䝁䄸杣あ䝁䅕䅚灁䅁䅁睺䅉䙁䅙䅁扂䙁䅍䅕䡂䙁䄸睑療䝁䄰䅣桂䝁䄴入時䕁䅳党㕂䙁䅍䅤桂䡁䅑督時䡁䅙杍畁䡁䅧䅢穂䝁䄰兘呂䝁䅧党求䡁䅑免桁䍁䅑杒歁䑁䅅免䅁䩁䝍䅁潁䅁䅁兓剂䙁䄸睑䵂䙁䄸䅒噂䕁䅕睘佂䕁䅕䅗啂䙁䄸杒䩂䙁䅙兒䅁䱁䉕䅁䅂䅁䅁兓剂䙁䄸睑偂䕁䄰兔偂䕁䄴睘䙂䙁䅅兖䩂䙁䅑兗時䑁䅉兗卂䙁䄸兑佂䕁䄴睘䡂䙁䅉睔塂䙁䅑䅓䅁䙁䍫䅁歂䅁䅁睗呂䙁䅁睒時䕁䅍睢瑂䡁䅁兙畂䡁䅫睘䱂䝁䅕入呂䡁䅑兙あ䡁䅍睘㉂䑁䅉杌㑂䝁䅷督瑂䙁䄰睑桂䡁䅁兡あ䝁䅅䅢灂䡁䅯兙あ䝁䅫睢畂䍁䅅䅊䑂䍁䅑䅎䅁偁䠴䅁祁䅁䅁兓剂䙁䄸睕䙂䕁䅍睔佂䕁䅑睘䵂䕁䅫兒佂䙁䄸䅔偂䕁䅅杔呂䙁䄸䅕䑂䙁䅑䅁浂允䅁䅎䅁䕁䅫兕時䕁䅍睔佂䙁䅑杕䉂䕁䅍䅖時䕁䄸村䵂䕁䅫睒䉂䙁䅑兓偂䕁䄴睘䑂䙁䅫䅁呄允䅁䅐䅁䕁䅯杣畁䍁䅁睕ㅂ䝁䅉杌杁䕁䅑党楂䡁䅑睌杁䙁䅑睢あ䝁䅅䅢杁䕁䅑党楂䡁䅑䅉潁䍁䅕克䅁䍁䉕䅁㉁䅁䅁兓剂䙁䄸睑偂䕁䄴䅖卂䕁䅅睑啂䙁䄸睔䍂䕁䅷兓䡂䕁䅅䅖䩂䕁䄸杔時䕁䅍兗硁䅁䅁儱䅅䑁䅙䅁䩂䙁䅅睘䑂䕁䄸杔啂䙁䅉兑䑂䙁䅑睘偂䕁䅉䅔䩂䕁䅣兑啂䕁䅫睔佂䙁䄸睑婂䑁䅉䅁塄允䅁杄䅁䕁䅫兕時䙁䅉睔䙂䅁䅁眯䅅䅁䄴䅁䩂䙁䅅睘卂䕁䄸睑䅁偁䉳䅁睂䅁䅁睗乂䕁䅫睘䑂䝁䄸兢睂䝁䅅杢㕂䙁䄸睓求䡁䅫睕あ䝁䅅䅤穂䙁䄸杤硁䙁䄸杌㑂䝁䅷督瑂䙁䄰睑桂䡁䅁兡あ䝁䅅䅢灂䡁䅯兙あ䝁䅫睢畂䍁䅅䅊䑂䍁䅑兏㙁䍁䅑睑歁䑁䅉兎䅁佁䕣䅁坃䅁䅁睔睂䡁䅑兡療䝁䄴督㙁䍁䅁睑ㅂ䡁䅉杣㥁䙁䅕睕䕂䍁䅷䅉乂䝁䅅睚㥁䕁䄰兡獂䝁䅷兡療䝁䄴督獁䕁䅍睢畂䡁䅙兔求䡁䅑䅡療䝁䅑児乂䕁䅫杣求䝁䅍睢瑂䝁䄰党畂䝁䅑党歂䍁䅷䅉佂䕁䅅児瑁䍁䅷䅉啂䝁䅕杣瑂䑁䄰党畂䍁䄰兖呂䅁䅁入䅁䥁䅑䅁湁䙁䅳睑療䡁䅁入杁䝁䄸杚杁䙁䅍䅕䡂䙁䄸睑療䝁䄰䅣桂䝁䄴入時䕁䅳党㕂䙁䅍䅤桂䡁䅑督時䡁䅙杍時䝁䄴党㍂䍁䄴䅥獂䡁䅍兢摂䕁䅳党㕂䙁䄸睕あ䝁䅅䅤穂䍁䅣光歁䕁䅕䅊祁䑁䅕杏歁䕁䄰䅊祁䑁䅕䅁塄睂䅁村䅁䙁䅍䅡療䡁䅉䅤瑁䡁䅑党祂䝁䄰䅉䍂䝁䄸杣祂䝁䄸睤灂䝁䄴睚穂䍁䅁䅋卂䝁䅕䅣療䡁䅉䅤求䝁䅑克䅁䅁䈸䅁㉁䅁䅁兓剂䙁䄸睑偂䕁䄴䅖卂䕁䅅睑啂䙁䄸睔䍂䕁䅷兓䡂䕁䅅䅖䩂䕁䄸杔時䕁䅍兗ぁ䅁䅁眲䅅䉁䄴䅁䩂䙁䅅睘䑂䕁䄸杔坂䕁䅕杕啂䙁䄸䅕䑂䙁䅑䅁煁允䅁杋䅁䕁䅫兕時䕁䄴睔䵂䙁䄸睑䝂䙁䄸兑䝂䙁䅑兒卂䙁䄸杒䩂䙁䅙兒䅁䵁䍷䅁啁䅁䅁兓剂䙁䄸睑兂䙁䄸䅕䑂䙁䅑䅁畄䅁䅁杫䅁䕁䄸䅣あ䝁䅫睢畂䡁䅍杏杁䕁䅍兤祂䡁䅉児䡂䕁䅉䅕獁䍁䅁兔桂䝁䅣児䉂䝁䅍䅤ㅂ䝁䅅䅢穂䍁䅷睑療䝁䄴杤乂䝁䅕䅤潂䝁䄸䅚㥁䕁䄰兓祂䝁䅕睙療䝁䄰兢求䝁䄴䅚求䝁䅑䅌杁䕁䄴兑㥁䍁䅷䅉啂䝁䅕杣瑂䑁䄰党畂䍁䄰兖呂䅁䅁兏䅁䕁䅉䅁䩂䙁䅅睘噂䕁䄴杕䙂䕁䅍睔䡂䙁䄸䅖䉂䙁䅧睘䍂䕁䅕杔䙂䕁䅙兓啂䙁䄸睔啂䕁䅧兒卂䙁䄸兑䕂䕁䅯䅁佁睁䅁杕䅁䙁䅳睓求䡁䅫睕あ䝁䅅䅤穂䙁䄸䅤求䡁䅍䅤浂䝁䅫䅢求䍁䄴䅥獂䡁䅍䅥摂䙁䅍䅡求䝁䅕䅤祁䍁䅅䅊䝂䍁䅑睎㙁䍁䅑睒歁䑁䅣䅁獁䅁䅁䅌䅁䕁䅫兕時䕁䅑䅕呂䙁䄸兎婂䙁䅉睘䉂䕁䄴杔時䕁䅣杕偂䙁䅣䅖䥂䅁䅁兲䅉䙁䅯䅁䩂䙁䅅睘䑂䙁䅕杕卂䕁䅕杔啂䙁䄸䅔偂䕁䄴睒時䙁䅑兒卂䕁䄰睘䕂䕁䅕村啂䙁䄸兑佂䕁䅑睘䑂䕁䅅䅕䩂䙁䅑兑䵂䙁䄸䅔䙂䕁䅅睕䙂䙁䅍䅁獁允䅁杓䅁䙁䅳睓求䡁䅫睕あ䝁䅅䅤穂䙁䄸䅤求䡁䅍䅤浂䝁䅫䅢求䍁䄴䅥獂䡁䅍兢摂䙁䅍䅡求䝁䅕䅤硁䍁䅅䅊䍂䍁䅑兎祁䅁䅁杨䅁䍁䅑䅁佂䝁䅕䅤杁䕁䅫杢橂䝁䄸兢求䍁䅁䅋歁䑁䅁䅍睁䍁䅫䅁牂䅁䅁䅯䅁䍁䅣睗䑂䝁䄸䅣㕂䍁䅁睢浂䍁䅁睕兂䕁䅣睘䑂䝁䄸兢睂䝁䅅杢㕂䙁䄸睓求䡁䅫睕あ䝁䅅䅤穂䙁䄸杤硁䙁䄸杒灂䝁䄴兙獂䍁䄴䅥獂䡁䅍兢摂䕁䅍兙睂䝁䅫䅤桂䝁䅷睘呂䡁䅑杣ㅂ䝁䅍䅤ㅂ䡁䅉党時䍁䅁䅒求䡁䅑兙灂䝁䅷督杁䍁䅣光歁䕁䅕䅊㍁䑁䅙䅁ㅂ䅃䅁䅌䅁䕁䅫兕時䕁䅕䅕呂䙁䄸兎婂䙁䅉睘䉂䕁䄴杔時䕁䅣杕偂䙁䅣䅖䥂䅁䅁六䅉䍁䅧䅁䩂䙁䅅睘䑂䙁䅕杕卂䕁䅕杔啂䙁䄸䅕偂䙁䅉䅖時䙁䅁睑啂䅁䅁杕䅅䉁䅁䅁䝂䙁䅅免祁䑁䅁杍㉁䅁䅁眲䅣䡁䅁䅁扂䕁䄰兓時䕁䅍睢瑂䡁䅁兙畂䡁䅫睘䱂䝁䅕入呂䡁䅑兙あ䡁䅍睘㉂䑁䅅杌㑂䝁䅷督瑂䙁䄰兓畂䝁䅍睢瑂䝁䅕睘呂䡁䅑兙あ䝁䅕兢求䝁䄴䅤桁䍁䅑兒歁䑁䅙杏歁䙁䅁䅊㉁䅁䅁关䅕䉁䅧䅁䩂䙁䅅睘䕂䕁䅅睘呂䙁䅕䅕兂䕁䅷䅁浃䅁䅁杈䅁䕁䅫兕時䕁䅑睑呂䙁䄸兑乂䙁䅑睘偂䙁䅕䅖䅁䥁䜰䅁坂䅁䅁睗䱂䝁䅕入呂䡁䅑兙あ䡁䅍睘あ䝁䅕督あ䝁䅙兡獂䝁䅕杌㑂䝁䅷督瑂䙁䄰睕潂䝁䅕党あ䑁䅅光歁䕁䅫䅊祁䑁䅉杏歁䕁䅳䅊祁䑁䅉䅁䑃䅁䅁杊䅁䕁䅫兕時䕁䅑睑呂䙁䄸村偂䕁䄴䅒時䕁䅍睔噂䙁䅁睔佂䅁䅁八䅙䍁䅁䅁䩂䙁䅅睘䕂䕁䅍睕時䕁䅍睔佂䙁䅙睘啂䙁䅧䅖䅁䭁䝅䅁流䅁䅁兓剂䙁䄸䅒䑂䙁䅍睘䕂䕁䅕睕䑂䙁䅉兓兂䙁䅑兓偂䕁䄴䅁䅃杂䅁䅕䅁䙁䅳睓求䡁䅫睕あ䝁䅅䅤穂䙁䄸䅤求䡁䅍䅤浂䝁䅫䅢求䍁䄴䅥獂䡁䅍兢摂䕁䅳党㕂䙁䄸睕あ䝁䅅䅤穂䍁䅅䅊䙂䍁䅑兎㕁䅁䅁朴䅁䍁䅷䅁䩂䙁䅅睘䕂䕁䅍睕時䕁䅫睕呂䙁䅕兒時䕁䅍兖卂䙁䅉兒佂䕁䅍兗䅁䭁䝑䅁㉁䅁䅁兓剂䙁䄸䅖偂䙁䅑兑䵂䙁䄸䅒䙂䕁䅉䅖時䕁䅕村䩂䙁䅑䅒䉂䙁䄸睑䉂䙁䅁兒奂䅁䅁睧䅅䝁䅷䅁扂䙁䅍䅕䡂䙁䄸睑療䝁䄰䅣桂䝁䄴入時䕁䅳党㕂䙁䅍䅤桂䡁䅑督時䡁䅙杍畁䡁䅧䅢穂䝁䄰兘䍂䝁䅅䅢桂䝁䄴睙求䙁䄸睕潂䝁䅕党あ䍁䅅䅊䙂䍁䅑睎㙁䍁䅑兕歁䑁䅣䅁㥄睂䅁䅎䅁䕁䅫兕時䕁䅑兓䵂䙁䅕䅖時䕁䅕䅕呂䙁䄸村䙂䕁䅙睔卂䕁䅕睘䙂䙁䅧䅖卂䕁䅅䅁允䅁䅁杈䅁䕁䅫兕時䕁䄸䅔時䕁䅍睔乂䕁䄰睘䑂䙁䅫䅎䅁䱁䈸䅁獁䅁䅁兓剂䙁䄸䅒兂䙁䅍睘祁䙁䅫杕時䕁䅅杔佂䙁䄸睒卂䕁䄸睖啂䕁䅧䅁時杁䅁杋䅁䕁䅫兕時䕁䅕兑卂䕁䄴兓佂䕁䅣睕時䕁䅍睔佂䙁䅑睘偂䙁䅁睕䅁䅁䅳䅁煂䅁䅁睗乂䕁䅫睘䑂䝁䄸兢睂䝁䅅杢㕂䙁䄸睓求䡁䅫睕あ䝁䅅䅤穂䙁䄸杤硁䙁䄸杌㑂䝁䅷督瑂䙁䄰睕ㅂ䡁䅁䅣獂䝁䅕兢求䝁䄴䅤桂䝁䅷光歁䕁䅑䅊ㅁ䑁䅯䅊䩂䍁䅑兎䅁䅁䙁䅁㑁䅁䅁兓剂䙁䄸睖䉂䙁䅉杕䉂䕁䄴䅖呂䙁䄸睕啂䙁䅉兓䱂䕁䅕睘兂䙁䅉兓䑂䕁䅕睘偂䙁䅍䅁啂睁䅁䅖䅁䙁䅳兔䩂䙁䄸睓求䡁䅫睕あ䝁䅅䅤穂䙁䄸杤硁䍁䄴䅥獂䡁䅍兢摂䕁䅍兙睂䝁䅫䅤桂䝁䅷兡㙂䝁䅅䅤灂䝁䄸杢桁䍁䅑睑歁䑁䅑䅏䅁䭁䑅䅁㉁䅁䅁杔求䡁䅑䅉䩂䝁䄴睙療䝁䄰党獁䍁䅁睍杁䙁䅫杣畁䍁䅁睑䉂䕁䅣杕杁䍁䅧兊灁䅁䅁䅣䅉䑁䅯䅁䩂䙁䅅睘䙂䕁䅅杕佂䕁䅫杔䡂䙁䄸睑偂䙁䄸兎婂䙁䅉睘䉂䕁䄴杔時䕁䅣杕偂䙁䅣䅖䥂䅁䅁兪䅉䙁䅷䅁扂䕁䄰兓時䕁䅍睢瑂䡁䅁兙畂䡁䅫睘䱂䝁䅕入呂䡁䅑兙あ䡁䅍睘㉂䑁䅅睘畁䡁䅧䅢穂䝁䄰兘䱂䝁䅕入時䙁䅍䅤桂䡁䅑督桁䍁䅑村歁䑁䅉兎䅁䱁䔰䅁杁䅁䅁兓剂䙁䄸杔偂䕁䅷睘䑂䕁䅙睘啂䕁䄸䅖䉂䕁䅷䅁慄杁䅁䅅䅁䕁䅫兕時䕁䅕村䩂䙁䅑䅁浂䅁䅁䅍䅁䕁䅫兕時䕁䅕村䩂䙁䅑兑時䑁䅍兗卂䙁䄸兑佂䕁䄴睘䡂䙁䅉睔塂䙁䅑䅓䅁䡁䍅䅁畂䅁䅁䅔啂䍁䅁䅒求䝁䅉䅤杁䍁䅧兓畂䝁䅍䅢畁䍁䅁睑桂䡁䅁杌杁䕁䅷党桂䡁䅍党穂䍁䅫䅉䕂䡁䅕党獁䍁䅁杔求䡁䅧䅤杁䑁䅕䅉婂䡁䅉督杁䍁䅧杕求䡁䅁睢祂䡁䅑党歂䍁䅫䅁潃允䅁䅢䅁䙁䅳睕兂䕁䅣睘䑂䝁䄸兢睂䝁䅅杢㕂䙁䄸睓求䡁䅫睕あ䝁䅅䅤穂䙁䄸杤祁䍁䄴䅥獂䡁䅍兢摂䕁䅳党㕂䙁䄸睕あ䝁䅅䅤穂䍁䅅䅊䙂䍁䅑免睁䑁䅙杏歁䕁䅙䅊硁䑁䅁李䅁偁䡣䅁杁䅁䅁兓剂䙁䄸兒䍂䕁䅫䅖䉂䙁䄸兔䉂䙁䅉睒䩂䕁䄴䅁䙁杁䅁䅆䅁䕁䅫兕時䕁䅕村䩂䙁䅑䅒䉂䅁䅁元䅁䍁䄴䅁䩂䙁䅅睘䙂䕁䅉兓啂䙁䄸免婂䙁䅉睘䉂䕁䄴杔時䕁䅣杕偂䙁䅣䅖䥂䅁䅁兊䅉䝁䅯䅁扂䙁䅍䅕䡂䙁䄸睑療䝁䄰䅣桂䝁䄴入時䕁䅳党㕂䙁䅍䅤桂䡁䅑督時䡁䅙杍畁䡁䅧䅢穂䝁䄰兘䑂䝁䅅督潂䙁䄸杒獂䝁䄸睤桁䍁䅑睑歁䑁䅅免㙁䍁䅑睑歁䑁䅅䅍硁䅁䅁䄴䅣䍁䄴䅁䩂䙁䅅睘䙂䕁䅉兓啂䙁䄸杍婂䙁䅉睘䉂䕁䄴杔時䕁䅣杕偂䙁䅣䅖䥂䅁䅁睔䅉䍁䄴䅁䩂䙁䅅睘䙂䕁䅉兓啂䙁䄸睍婂䙁䅉睘䉂䕁䄴杔時䕁䅣杕偂䙁䅣䅖䥂䅁䅁兤䅉䍁䄴䅁䩂䙁䅅睘䙂䕁䅉兓啂䙁䄸兎婂䙁䅉睘䉂䕁䄴杔時䕁䅣杕偂䙁䅣䅖䥂䅁䅁公䅉䥁䅑䅁湁䙁䅳睕兂䕁䅣睘䑂䝁䄸兢睂䝁䅅杢㕂䙁䄸睓求䡁䅫睕あ䝁䅅䅤穂䙁䄸杤祁䍁䄴䅥獂䡁䅍兢摂䕁䅍兙睂䝁䅫䅤桂䝁䅷睘呂䡁䅑杣ㅂ䝁䅍䅤ㅂ䡁䅉党時䍁䅁䅒求䡁䅑兙灂䝁䅷督杁䍁䅣光歁䕁䅕䅊㍁䑁䅙䅁睁䅃䅁杈䅁䕁䅫兕時䕁䅕村䩂䙁䅑睘乂䕁䅅杕䡂䕁䅫杔䅁䅁䍣䅁獁䅁䅁兓剂䙁䄸兒兂䙁䅍睘硁䙁䅫杕時䕁䅅杔佂䙁䄸睒卂䕁䄸睖啂䕁䅧䅁橂䅁䅁杌䅁䕁䅫兕時䙁䅍兖䍂䙁䄸村偂䕁䄴䅒呂䙁䄸杔偂䙁䅑兒呂䙁䄸䅕䑂䙁䅑䅁㡄䅁䅁䅏䅁䕁䄸䅣あ䝁䅫睢畂䡁䅍杏呂䡁䅑兙あ䝁䅫督あ䝁䅫睙㥁䕁䅷睔塂䍁䅷杔䉂䑁䄰杔䉂䅁䅁眰䅣䙁䄴䅁扂䕁䄰兓時䕁䅍睢瑂䡁䅁兙畂䡁䅫睘䱂䝁䅕入呂䡁䅑兙あ䡁䅍睘㉂䑁䅅睘畁䡁䅧䅢穂䝁䄰兘卂䝁䅅䅤灂䝁䄸督桁䍁䅑䅒歁䑁䅑杏歁䕁䅫䅊ぁ䅁䅁末䅑䍁䅙䅁䩂䙁䅅睘䝂䕁䅫䅗䙂䕁䅑睘卂䕁䅅䅖䙂䙁䄸䅒䙂䕁䅉䅖䅁䑁䉉䅁煁䅁䅁兓剂䙁䄸睒兂䙁䄸免婂䙁䅉睘䉂䕁䄴杔時䕁䅣杕偂䙁䅣䅖䥂䅁䅁睇䅉䕁䅑䅁䩂䙁䅅睘噂䕁䄴杕䙂䕁䅍睔䡂䙁䄸䅖䉂䙁䅧睘䍂䕁䅕杔䙂䕁䅙兓啂䙁䄸村䙂䕁䅣睘兂䕁䅕杕䩂䕁䄸䅒䅁䅁䑑䅁坂䅁䅁睗乂䕁䅫睘䱂䝁䅕入呂䡁䅑兙あ䡁䅍睘㉂䑁䅅杌㑂䝁䅷督瑂䙁䄰睓求䡁䅫睘呂䡁䅑兙あ䡁䅍光歁䕁䅑䅊祁䑁䅕杏歁䕁䅑䅊ぁ䑁䅫䅁療睁䅁杋䅁䕁䅫兕時䕁䅣䅕時䑁䅍兗卂䙁䄸兑佂䕁䄴睘䡂䙁䅉睔塂䙁䅑䅓䅁䝁䍅䅁⭂䅁䅁睗䱂䝁䅕入呂䡁䅑兙あ䡁䅍睘あ䝁䅕督あ䝁䅙兡獂䝁䅕杌㑂䝁䅷督瑂䙁䄰睑桂䡁䅁兡あ䝁䅅䅢時䙁䅍䅤祂䡁䅕睙あ䡁䅕杣求䙁䄸睕ㅂ䝁䄰兢桂䡁䅉入桁䍁䅑兒歁䑁䅉睎㙁䍁䅑兒歁䑁䅅䅍㉁䅁䅁朸䅅䍁䅯䅁䩂䙁䅅睘䡂䙁䅁睘ㅁ䙁䅫杕時䕁䅅杔佂䙁䄸睒卂䕁䄸睖啂䕁䅧䅁䩃杁䅁杉䅁䕁䅫兕時䕁䄴睔䵂䙁䄸睑䝂䙁䄸杔偂䙁䄸兒奂䙁䅁䅁佄杁䅁杚䅁䙁䅳兔䩂䙁䄸睑療䝁䄰䅣桂䝁䄴入時䕁䅳党㕂䙁䅍䅤桂䡁䅑督時䡁䅙免畁䡁䅧䅢穂䝁䄰兘䱂䝁䅕入時䙁䅍䅤桂䡁䅑督桁䍁䅑兒歁䑁䅉杍㙁䍁䅑䅔歁䑁䅉杍䅁䡁䕙䅁杁䅁䅁兓剂䙁䄸睒卂䕁䄸睕呂䙁䄸兔䉂䙁䅉睒䩂䕁䄴䅁㕄允䅁䅗䅁䕁䅫兕時䕁䅫兔兂䕁䅅睑啂䙁䄸兖佂䙁䅉兒䑂䕁䄸睒時䙁䅑兑奂䙁䄸村䙂䕁䄴兒䝂䕁䅫䅖時䕁䅕杒䝂䕁䅕睑啂䕁䅫杖䙂䙁䄸䅖䉂䙁䅧䅁浄杁䅁䅣䅁䙁䅳兔䩂䙁䄸睑療䝁䄰䅣桂䝁䄴入時䕁䅳党㕂䙁䅍䅤桂䡁䅑督時䡁䅙免畁䡁䅧䅢穂䝁䄰兘䑂䝁䅅䅣灂䡁䅑兙獂䝁䅫来桂䡁䅑兡療䝁䄴光歁䕁䅕䅊ぁ䑁䅧杏歁䕁䅯䅊ぁ䑁䅧䅁晃䅂䅁杚䅁䙁䅳兔䩂䙁䄸睑療䝁䄰䅣桂䝁䄴入時䕁䅳党㕂䙁䅍䅤桂䡁䅑督時䡁䅙免畁䡁䅧䅢穂䝁䄰兘䱂䝁䅕入時䙁䅍䅤桂䡁䅑督桁䍁䅑兔歁䑁䅉䅎㙁䍁䅑睔歁䑁䅉䅎䅁䥁䕫䅁卂䅁䅁兓剂䙁䄸兓佂䙁䅑兒卂䕁䅕睕啂䙁䄸䅕䙂䕁䄴兑䵂䙁䅑兓䙂䙁䅍睘卂䕁䅕睑偂䕁䅣睘䍂䙁䅍睘䉂䕁䅙䅖䙂䙁䅉睘啂䕁䅅䅗䅁䉁䑑䅁獁䅁䅁兓剂䙁䄸兓佂䙁䅙睘硁䙁䅫杕時䕁䅅杔佂䙁䄸睒卂䕁䄸睖啂䕁䅧䅁湁杁䅁䅌䅁䕁䅫兕時䕁䅫杔坂䙁䄸睍婂䙁䅉睘䉂䕁䄴杔時䕁䅣杕偂䙁䅣䅖䥂䅁䅁睤䅉䍁䅷䅁䩂䙁䅅睘䩂䕁䄴杖時䑁䅕兗卂䙁䄸兑佂䕁䄴睘䡂䙁䅉睔塂䙁䅑䅓䅁䩁䍣䅁佃䅁䅁睔睂䡁䅑兡療䝁䄴督㙁䕁䅍兤祂䡁䅉児卂䝁䅕䅣療䡁䅉䅤求䝁䅑䅉橂䡁䅕杣祂䝁䅕杢橂䡁䅫䅌乂䝁䅅睚㥁䕁䄰兓穂䡁䅑兙畂䝁䅑兙祂䝁䅑䅌䑂䝁䄸杢㉂䕁䄰党あ䝁䅧睢歂䑁䄰兔䩂䡁䅉党橂䝁䄸兢瑂䝁䅕杢歂䝁䅕䅚䅁䥁䑫䅁䭂䅁䅁睗乂䕁䅫睘䱂䝁䅕入呂䡁䅑兙あ䡁䅍睘㉂䑁䅅杌㑂䝁䅷督瑂䙁䄰睓求䡁䅫睘呂䡁䅑兙あ䡁䅍光歁䕁䅕䅊㉁䑁䅁䅁あ睁䅁䅌䅁䕁䅫兕時䕁䅯杕時䙁䅍兖䍂䙁䄸䅒䙂䕁䅉䅖時䕁䅕村䩂䙁䅑䅒䉂䅁䅁睪䅅䑁䅧䅁䩂䙁䅅睘䭂䙁䅉睘呂䙁䅕村時䕁䅑兒䍂䙁䅑睘䙂䕁䅉兓啂䕁䅑兑時䕁䅍兑兂䕁䅕䅗䅁䩁䉫䅁䭁䅁䅁兔呂䕁䅙䅖䅁乁䡧䅁畁䅁䅁兓剂䙁䄸䅔䝂䕁䅍杒時䑁䅅兗卂䙁䄸兑佂䕁䄴睘䡂䙁䅉睔塂䙁䅑䅓䅁䍁䍫䅁㙂䅁䅁睗乂䕁䅫睘䑂䝁䄸兢睂䝁䅅杢㕂䙁䄸睓求䡁䅫睕あ䝁䅅䅤穂䙁䄸杤硁䙁䄸杌㑂䝁䅷督瑂䙁䄰睑桂䡁䅁兡あ䝁䅅䅢時䙁䅍䅤祂䡁䅕睙あ䡁䅕杣求䙁䄸睕ㅂ䝁䄰兢桂䡁䅉入桁䍁䅑睑歁䑁䅑䅁硄䅂䅁䅎䅁䕁䅫兕時䙁䅍杕時䙁䅍兒䑂䙁䅕杕䙂䕁䅑睘䍂䕁䄸杔䕂䙁䅍睘佂䕁䄸䅖䙂䙁䅍䅁㡁允䅁杌䅁䕁䅫兕時䕁䅷杒䑂䕁䅙睘祁䙁䅫杕時䕁䅅杔佂䙁䄸睒卂䕁䄸睖啂䕁䅧䅁摂杁䅁杌䅁䕁䅫兕時䕁䅷杒䑂䕁䅙睘ㅁ䙁䅫杕時䕁䅅杔佂䙁䄸睒卂䕁䄸睖啂䕁䅧䅁灃杁䅁杈䅁䕁䅫兕時䙁䅍䅖偂䕁䅍睓時䕁䅉兑呂䕁䅕䅒䅁䭁䅷䅁啂䅁䅁杔偂䕁䅷䅉䑂䝁䅅杣祂䡁䅫杚療䡁䅉睤桂䡁䅉䅚獁䍁䅁睑ㅂ䡁䅉杣求䝁䄴䅤杁䙁䅫党桂䡁䅉䅉潁䙁䅉党睂䝁䄸杣あ䝁䅕䅚灁䅁䅁兹䅉䉁䄴䅁䩂䙁䅅睘䵂䕁䅙睑䝂䙁䄸兔䉂䙁䅉睒䩂䕁䄴䅁剁杁䅁䅎䅁䕁䅫兕時䕁䅷兓䉂䕁䅉兓䵂䕁䅫䅖䩂䕁䅕睕時䕁䅙兑䩂䙁䅉睘坂䕁䅅䅔噂䕁䅕䅁流睁䅁杚䅁䙁䅳兔䩂䙁䄸睑療䝁䄰䅣桂䝁䄴入時䕁䅳党㕂䙁䅍䅤桂䡁䅑督時䡁䅙免畁䡁䅧䅢穂䝁䄰兘䱂䝁䅕入時䙁䅍䅤桂䡁䅑督桁䍁䅑兒歁䑁䅉睍㙁䍁䅑兓歁䑁䅉睍䅁偁䑍䅁流䅁䅁兓剂䙁䄸䅖卂䙁䅕睕啂䙁䄸䅕卂䕁䅕杒䙂䙁䅉杕䙂䕁䅑䅁䭂允䅁杒䅁䙁䅑睢あ䝁䅅䅢杁䕁䄰兡畂䝁䄸杣灂䡁䅑入杁䕁䅫杢あ䝁䅕杣求䡁䅍䅤杁䍁䅧杕求䡁䅁睢祂䡁䅑党歂䍁䅫䅁摁䅁䅁䅙䅁䙁䅳睓求䡁䅫睕あ䝁䅅䅤穂䙁䄸䅤求䡁䅍䅤浂䝁䅫䅢求䍁䄴䅥獂䡁䅍兢摂䕁䅉兙獂䝁䅅杢橂䝁䅕睘呂䝁䅧党求䡁䅑光歁䕁䅙䅊ㅁ䑁䅯䅊剂䍁䅑兎䅁䵁䅑䅁畁䅁䅁兓剂䙁䄸䅔䩂䕁䅅村䩂䕁䅷兓啂䕁䅫兒呂䙁䄸䅔䙂䙁䅙兒䵂䙁䄸免䅁䉁䐴䅁潁䅁䅁兓剂䙁䄸睕卂䙁䄸睕䙂䕁䅍兖卂䕁䅕䅒時䕁䅷睔䉂䕁䄴睕䅁䑁䉯䅁畁䅁䅁兓剂䙁䄸䅔䩂䕁䅅村䩂䕁䅷兓啂䕁䅫兒呂䙁䄸䅔䙂䙁䅙兒䵂䙁䄸杍䅁䍁䑁䅁卂䅁䅁兓剂䙁䄸䅔䩂䕁䅅村䩂䕁䅷兓啂䕁䅫兒呂䙁䄸杔䙂䙁䅑䅖䩂䕁䄴睒時䕁䄸䅖䥂䕁䅕杕時䕁䅅䅒䭂䙁䅕睕啂䕁䄰兒佂䙁䅑睕䅁䍁䑑䅁獁䅁䅁兓剂䙁䄸䅔啂䕁䅑睘䕂䙁䅕兒時䕁䅅杒啂䕁䅕杕時䕁䅙兓坂䕁䅕䅁汃允䅁杌䅁䕁䅫兕時䙁䅑睔啂䕁䅅䅔時䙁䅁杕䩂䕁䄴睑䩂䙁䅁兑䵂䙁䄸䅕䑂䙁䅑䅁祄䅁䅁䅈䅁䕁䅫兕時䕁䅷䅖䕂䙁䄸䅒噂䕁䅕睘䑂䙁䅫䅁扃允䅁杈䅁䕁䅫兕時䕁䅷䅖䕂䙁䄸䅒噂䕁䅕睘䑂䙁䅫免䅁䩁䈰䅁敁䅁䅁兓剂䙁䄸䅔啂䕁䅑睘䕂䙁䅕兒時䕁䅍兗祁䅁䅁睮䅅䉁䄴䅁䩂䙁䅅睘䵂䙁䅑䅒時䕁䅑兖䙂䙁䄸睑婂䑁䅑䅁橃允䅁杋䅁䕁䅫兕時䕁䅷䅖時䕁䅑兒䍂䙁䅑睘啂䕁䄸睘䙂䙁䅅兖䩂䙁䅑兗䅁䱁䍉䅁㑁䅁䅁兓剂䙁䄸䅔啂䙁䄸䅒䙂䕁䅉䅖時䙁䅑睔時䙁䅑睔啂䕁䅅䅔時䕁䅍兑兂䕁䅫䅖䉂䕁䅷䅁ぃ杁䅁䅌䅁䕁䅫兕時䕁䄰兑卂䕁䅳兒啂䕁䅍兑兂䙁䄸兒䍂䙁䅑睘䙂䙁䅧睑䵂䅁䅁兡䅙䡁䅉䅁扂䕁䄰兓時䕁䅍睢瑂䡁䅁兙畂䡁䅫睘䱂䝁䅕入呂䡁䅑兙あ䡁䅍睘㉂䑁䅅睘畁䡁䅧䅢穂䝁䄰兘䑂䝁䅅䅣灂䡁䅑兙獂䝁䅫来桂䡁䅑兡療䝁䄴光歁䕁䅍䅊ㅁ䑁䅍杏歁䕁䅍䅊ㅁ䑁䅑䅁癄䅂䅁䅮䅁䍁䅣睗䑂䝁䄸䅣㕂䍁䅁睢浂䍁䅁睕兂䕁䅣睘䑂䝁䄸兢睂䝁䅅杢㕂䙁䄸睓求䡁䅫睕あ䝁䅅䅤穂䙁䄸杤祁䙁䄸杢求䡁䅣杌㑂䝁䅷督瑂䙁䄰睑桂䡁䅁兡あ䝁䅅䅢時䙁䅍䅤祂䡁䅕睙あ䡁䅕杣求䙁䄸䅉䕂䝁䅕䅤桂䝁䅫䅢穂䍁䅁睊桁䍁䅑杒歁䑁䅣李䅁䥁䡧䅁歁䅁䅁兓剂䙁䄸兔䉂䙁䅉睓䙂䙁䅑睑䉂䙁䅁睘䵂䕁䅙睑䝂䅁䅁睙䅙䍁䄴䅁䩂䙁䅅睘乂䕁䅅杕䱂䕁䅕䅖䑂䕁䅅䅕時䙁䅑睔啂䕁䅅䅔時䙁䅉兒坂䅁䅁兘䅙䙁䅉䅁䩂䙁䅅睘乂䕁䅅䅗時䙁䅫杕時䕁䅙睔卂䙁䄸睑䉂䙁䅁兓啂䕁䅅䅔時䕁䅷睔呂䙁䅍睘䑂䕁䅅杕卂䙁䅫睘䝂䕁䄸杕塂䕁䅅杕䕂䅁䅁朸䅉䍁䅯䅁䩂䙁䅅睘乂䕁䅫杔偂䙁䅉兓啂䙁䅫睘䩂䕁䄴䅖䙂䙁䅉兒呂䙁䅑䅁捁䅁䅁䅚䅁䙁䅳兔䩂䙁䄸睑療䝁䄰䅣桂䝁䄴入時䕁䅳党㕂䙁䅍䅤桂䡁䅑督時䡁䅙免畁䡁䅧䅢穂䝁䄰兘䍂䝁䅅䅢桂䝁䄴睙求䙁䄸睕潂䝁䅕党あ䍁䅅䅊䑂䍁䅑免ぁ䑁䅙䅁湃䅂䅁䅇䅁䕁䅫兕時䕁䄴兒啂䙁䄸䅒䙂䕁䅉䅖䅁䉁䉁䅁慂䅁䅁睗乂䕁䅫睘卂䕁䅕兓啂䙁䄸睕桂䝁䄰党呂䡁䅑睢祂䝁䅕䅖求䝁䄰䅣獂䝁䅅䅤求䙁䄸杤硁䍁䄴䅥獂䡁䅍兘䕂䝁䅅䅤桂䍁䅅䅊䡂䍁䅑䅎㑁䅁䅁䄲䅍䍁䅯䅁䩂䙁䅅睘佂䕁䅫睘祁䙁䅫杕時䕁䅅杔佂䙁䄸睒卂䕁䄸睖啂䕁䅧䅁㕁杁䅁䅩䅁䙁䅳睕兂䕁䅣睘䑂䝁䄸兢睂䝁䅅杢㕂䙁䄸睓求䡁䅫睕あ䝁䅅䅤穂䙁䄸杤硁䍁䄴䅥獂䡁䅍兢摂䕁䅍兙睂䝁䅫䅤桂䝁䅷睘呂䡁䅑杣ㅂ䝁䅍䅤ㅂ䡁䅉党時䙁䅍兤瑂䝁䄰兙祂䡁䅫光歁䕁䅙䅊硁䑁䅁杏歁䙁䅁䅊硁䑁䅁䅁䉁杂䅁杋䅁䕁䅫兕時䕁䄴兓時䑁䅕兗卂䙁䄸兑佂䕁䄴睘䡂䙁䅉睔塂䙁䅑䅓䅁䩁䍳䅁睁䅁䅁兓剂䙁䄸杔䩂䙁䄸兑坂䕁䅅兓䵂䙁䄸兒奂䕁䅍䅔時䕁䄰兑卂䕁䅣兓佂䅁䅁兄䅉䑁䅑䅁䩂䙁䅅睘佂䕁䅫睘佂䕁䄸杕乂䙁䄸兎婂䙁䅉睘䉂䕁䄴杔時䕁䅣杕偂䙁䅣䅖䥂䅁䅁睫䅉䝁䅁䅁䵂䝁䅕杤求䝁䅷䅉穁䍁䅁兑穂䡁䅍党あ䡁䅍䅉瑁䍁䅁兖畂䝁䄸杙穂䝁䅕杣㉂䝁䅅杙獂䝁䅕䅉兂䡁䅉兡橂䝁䅕督杁䍁䅧杕求䡁䅁睢祂䡁䅑党歂䍁䅫䅁扁睁䅁䅈䅁䕁䅫兕時䙁䅑睔啂䕁䅅䅔時䕁䅑兒䍂䙁䅑䅁奁䅁䅁䅈䅁䕁䅫兕時䕁䄴睔䵂䙁䄸睑䝂䙁䄸免婂䙁䅉䅁䥄杁䅁䅈䅁䕁䅫兕時䕁䄴睔䵂䙁䄸睑䝂䙁䄸杍婂䙁䅉䅁兄杁䅁䅣䅁䙁䅳兔䩂䙁䄸睑療䝁䄰䅣桂䝁䄴入時䕁䅳党㕂䙁䅍䅤桂䡁䅑督時䡁䅙免畁䡁䅧䅢穂䝁䄰兘䩂䝁䄴睙療䝁䄰党時䙁䅍䅤桂䡁䅑党瑂䝁䅕杢あ䍁䅅䅊䙂䍁䅑睎㙁䍁䅑䅕歁䑁䅣䅁穃兂䅁䅈䅁䕁䅫兕時䕁䄴睔䵂䙁䄸睑䝂䙁䄸䅎婂䙁䅉䅁啄杁䅁条䅁䙁䅣兙祂䡁䅉兙畂䡁䅑督杁䙁䅣睌䉂䡁䅙党祂䝁䅅睚求䍁䅁睕あ䡁䅉兡牂䝁䅕䅉兂䡁䅉兡橂䝁䅕䅉療䝁䅙䅉䩂䡁䅍督ㅂ䝁䅕䅚杁䍁䅧杕求䡁䅁睢祂䡁䅑党歂䍁䅫䅁硁睁䅁杓䅁䙁䅳睓求䡁䅫睕あ䝁䅅䅤穂䙁䄸䅤求䡁䅍䅤浂䝁䅫䅢求䍁䄴䅥獂䡁䅍兢摂䙁䅍䅡求䝁䅕䅤硁䍁䅅䅊䍂䍁䅑兎穁䅁䅁睦䅁䉁䅷䅁䩂䙁䅅睘佂䕁䄸䅔時䕁䅍杒時䑁䅕兗卂䅁䅁杷䅉䝁䅁䅁扂䕁䅳党㕂䙁䅍䅤桂䡁䅑督時䡁䅑党穂䡁䅑杚灂䝁䅷党畁䡁䅧䅢穂䝁䄰兘䍂䝁䅅䅢桂䝁䄴睙求䙁䄸睕潂䝁䅕党あ䍁䅅䅊䝂䍁䅑䅎㙁䍁䅑兕歁䑁䅑䅁䍄䅁䅁䅚䅁䙁䅳兔䩂䙁䄸睓求䡁䅫睕あ䝁䅅䅤穂䙁䄸杤硁䍁䄴䅥獂䡁䅍兢摂䕁䅫杢橂䝁䄸兢求䙁䄸睕あ䝁䅅䅤求䝁䄰党畂䡁䅑光歁䕁䅍䅊㕁䑁䅯䅊䑂䍁䅑免㉁䑁䅉䅁㝃睁䅁䅗䅁䙁䅳兔䩂䙁䄸睓求䡁䅫睕あ䝁䅅䅤穂䙁䄸杤硁䍁䄴䅥獂䡁䅍兢摂䙁䅍兤睂䡁䅁䅢求䝁䄰党畂䡁䅑兙獂䍁䅅䅊䕂䍁䅑兎㙁䍁䅑兓歁䑁䅕䅁啃睁䅁䅋䅁䕁䅫兕時䕁䄴睔佂䙁䅉兒䑂䕁䄸兖卂䙁䅍兒時䕁䅑兒䍂䙁䅑䅁䥂允䅁䅍䅁䕁䅫兕時䕁䄴睔佂䙁䅉兒䑂䕁䄸兖卂䙁䅍兒時䕁䅑兒䍂䙁䅑睘兂䕁䅍䅖䅁䡁䉑䅁畁䅁䅁兓剂䙁䄸杔兂䙁䅁兒時䑁䅉兗卂䙁䄸兑佂䕁䄴睘䡂䙁䅉睔塂䙁䅑䅓䅁䑁䍳䅁畁䅁䅁兓剂䙁䄸杔噂䕁䄰睘啂䙁䅉兑䕂䕁䅕睕時䕁䅕䅗䙂䕁䅍兖啂䕁䅕䅒䅁䥁䑳䅁捁䅁䅁兓剂䙁䄸睔䵂䙁䄸睑偂䕁䄰兔時䕁䅍兗䅁䱁䉣䅁敁䅁䅁兓剂䙁䄸睔䵂䙁䄸睑偂䕁䄰兔時䕁䅍兗硁䅁䅁兵䅅䝁䅧䅁扂䕁䄰兓時䕁䅳党㕂䙁䅍䅤桂䡁䅑督時䡁䅙免畁䡁䅧䅢穂䝁䄰兘䑂䝁䅅䅣灂䡁䅑兙獂䙁䄸睕あ䡁䅉兤橂䡁䅑兤祂䝁䅕睘呂䡁䅕兢瑂䝁䅅杣㕂䍁䅅䅊䑂䍁䅑兎䅁䡁䐸䅁歁䅁䅁兓剂䙁䄸睔兂䙁䅑兓偂䕁䄴睕時䕁䅉兒䡂䙁䄸睔呂䅁䅁杌䅍䍁䅑䅁䩂䙁䅅睘偂䙁䅁䅖䩂䕁䄸杔呂䙁䄸兒佂䕁䅑睘偂䙁䅍䅁㙁睁䅁䅖䅁䙁䅳兔䩂䙁䄸睑療䝁䄰䅣桂䝁䄴入時䕁䅳党㕂䙁䅍䅤桂䡁䅑督時䡁䅙免時䍁䄴䅥獂䡁䅍兢摂䙁䅉兙あ䝁䅫睢穂䍁䅅䅊䑂䍁䅑䅎䅁偁䕫䅁煁䅁䅁兓剂䙁䄸睔兂䙁䅑兓偂䕁䄴睕時䕁䅕䅗䙂䙁䅉睑䩂䙁䅍兒䕂䅁䅁李䅍䉁䅉䅁䩂䙁䅅睘兂䕁䅉杖時䙁䅧䅁啂杂䅁杚䅁䙁䅳兔䩂䙁䄸睑療䝁䄰䅣桂䝁䄴入時䕁䅳党㕂䙁䅍䅤桂䡁䅑督時䡁䅙免畁䡁䅧䅢穂䝁䄰兘䱂䝁䅕入時䙁䅍䅤桂䡁䅑督桁䍁䅑兒歁䑁䅉杍㙁䍁䅑杓歁䑁䅉杍䅁䥁䕉䅁䵁䅁䅁兓剂䙁䄸䅕䙂䅁䅁兙䅙䉁䅷䅁䩂䙁䅅睘兂䕁䅕杕䩂䕁䄸䅒䕂䕁䅅䅖䙂䅁䅁来䅙䉁䅷䅁䩂䙁䅅睘兂䕁䅕杕䩂䕁䄸䅒時䕁䅕杔䕂䅁䅁兦䅙䝁䅙䅁扂䕁䄰兓時䕁䅍睢瑂䡁䅁兙畂䡁䅫睘䱂䝁䅕入呂䡁䅑兙あ䡁䅍睘㉂䑁䅅杌㑂䝁䅷督瑂䙁䄰兓畂䝁䅍睢瑂䝁䅕睘呂䡁䅑兙あ䝁䅕兢求䝁䄴䅤桁䍁䅑睑歁䑁䅙䅁睃兂䅁䅚䅁䙁䅳兔䩂䙁䄸睑療䝁䄰䅣桂䝁䄴入時䕁䅳党㕂䙁䅍䅤桂䡁䅑督時䡁䅙免時䍁䄴䅥獂䡁䅍兢摂䕁䅍兙穂䝁䅧睘䝂䝁䅷睢㍂䍁䅅䅊䙂䍁䅑兎㙁䍁䅑䅕歁䑁䅕䅁歄䅂䅁杅䅁䙁䅍䅕䡂䙁䅑兙楂䝁䅷党䅁䙁䅷䅁歁䅁䅁兓剂䙁䄸䅕卂䕁䄸杖時䕁䅉兑䕂䙁䄸䅒䙂䕁䅉䅖呂䅁䅁東䅁䉁䅑䅁䩂䙁䅅睘兂䙁䅑村坂䙁䄸䅗䅁䝁䝑䅁潂䅁䅁睗呂䙁䅁睒時䕁䅍睢瑂䡁䅁兙畂䡁䅫睘䱂䝁䅕入呂䡁䅑兙あ䡁䅍睘㉂䑁䅉杌㑂䝁䅷督瑂䙁䄰睓求䡁䅫睘呂䡁䅑兙あ䡁䅍光歁䕁䄴䅊祁䑁䅙杏歁䙁䅁䅊祁䑁䅙䅁瑄睂䅁杢䅁䙁䅳兔䩂䙁䄸睑療䝁䄰䅣桂䝁䄴入時䕁䅳党㕂䙁䅍䅤桂䡁䅑督時䡁䅙免畁䡁䅧䅢穂䝁䄰兘䍂䝁䅅䅢桂䝁䄴睙求䙁䄸睕潂䝁䅕党あ䍁䅅䅊䑂䍁䅑兏㙁䍁䅑睑歁䑁䅅睍㕁䅁䅁权䅑䉁䅑䅁䩂䙁䅅睘卂䕁䅍睘兂䕁䅍䅖䅁偁䅑䅁䭂䅁䅁兓剂䙁䄸杕䙂䕁䅑兖䑂䙁䅑兓偂䕁䄴睘啂䕁䅅䅗時䙁䅁睔呂䕁䅫䅖䩂䕁䄸杔時䕁䅍兖卂䙁䅉兒佂䙁䅑睘婂䙁䅉䅁䥁睁䅁䅗䅁䙁䅳兔䩂䙁䄸杕䙂䕁䅫䅖時䙁䅍兙瑂䝁䅕睕あ䝁䄸杣求䙁䅑党瑂䡁䅁䅢桂䡁䅑党時䡁䅙免畁䡁䅧䅢穂䙁䄰䅒桂䡁䅑兙桁䍁䅑䅒歁䑁䅫䅁敄睁䅁材䅁䕁䅫兕時䙁䅑睔啂䕁䅅䅔時䕁䅅睕呂䕁䅕䅖呂䙁䄸免婂䙁䅉睘䉂䕁䄴杔時䕁䅣杕偂䙁䅣䅖䥂䅁䅁睋䅉䕁䅧䅁䩂䙁䅅睘卂䕁䅕䅒噂䕁䅍䅖䩂䕁䄸杔時䙁䅑兑奂䙁䄸䅕偂䙁䅍兓啂䕁䅫睔佂䙁䄸䅕卂䕁䅫睔卂䙁䄸兗卂䙁䅍䅁坄杁䅁䅈䅁䙁䅍䅕時䙁䅍䅓䉂䙁䅉兒呂䙁䄸睔噂䙁䅑䅁坁䅁䅁杄䅁䕁䅫兕時䙁䅉睔䉂䅁䅁眹䅅䙁䅙䅁扂䙁䅍䅕䡂䙁䄸睑療䝁䄰䅣桂䝁䄴入時䕁䅳党㕂䙁䅍䅤桂䡁䅑督時䡁䅙杍畁䡁䅧䅢穂䝁䄰兘呂䝁䅧党求䡁䅑免桁䍁䅑睒歁䑁䅅免䅁䩁䝣䅁允䅁䅁兓剂䙁䄸杕偂䕁䅍兒䅁偁䈰䅁敂䅁䅁睗乂䕁䅫睘䑂䝁䄸兢睂䝁䅅杢㕂䙁䄸睓求䡁䅫睕あ䝁䅅䅤穂䙁䄸杤硁䙁䄸杌㑂䝁䅷督瑂䙁䄰杕桂䡁䅑兡療䡁䅍光歁䕁䅑䅊ㅁ䑁䅯䅊䩂䍁䅑兎䅁偁䕷䅁⭁䅁䅁兓剂䙁䄸睕䙂䕁䅍睔佂䕁䅑睘䵂䕁䅫兒佂䙁䄸村偂䕁䄴䅒呂䙁䄸杔偂䙁䅑兒呂䙁䄸䅕䑂䙁䅑䅁睂允䅁䅍䅁䕁䅫兕時䙁䅍兒䑂䕁䄸杔䕂䙁䄸䅔䩂䕁䅕杔時䕁䅑兒䍂䙁䅑睘兂䕁䅍䅖䅁䡁䉉䅁䭁䅁䅁杒婂䍁䅳杍䅁䭁䤴䅁楂䅁䅁睗呂䙁䅁睒時䕁䅍睢瑂䡁䅁兙畂䡁䅫睘䱂䝁䅕入呂䡁䅑兙あ䡁䅍睘㉂䑁䅉杌㑂䝁䅷督瑂䙁䄰村桂䝁䅷兙畂䝁䅍党時䙁䅍䅡求䝁䅕䅤桁䍁䅑睑歁䑁䅙䅁㙄睂䅁杋䅁䕁䅫兕時䙁䅍兒䑂䕁䄸杔䕂䙁䄸䅔䩂䕁䅕杔時䕁䅷睔䉂䕁䄴睕䅁䕁䉉䅁捂䅁䅁睗乂䕁䅫睘䑂䝁䄸兢睂䝁䅅杢㕂䙁䄸睓求䡁䅫睕あ䝁䅅䅤穂䙁䄸杤硁䍁䄴䅥獂䡁䅍兢摂䕁䅳党㕂䙁䄸睕あ䝁䅅䅤穂䍁䅅䅊䍂䍁䅑免睁䑁䅙䅁硃䅂䅁䅍䅁䕁䅫兕時䙁䅍兒䑂䙁䅕杕䩂䙁䅑兓慂䕁䅕䅒時䕁䅑兒䍂䙁䅑睘兂䕁䅍䅖䅁䝁䉑䅁⭁䅁䅁兓剂䙁䄸睕䙂䙁䅑䅖䵂䕁䅕兔䙂䕁䄴䅖呂䙁䄸䅖䉂䙁䅧睘䉂䙁䅕䅖䥂䕁䄸杕䩂䙁䅑兓䙂䙁䅍䅁䵁睁䅁䅈䅁䕁䅫兕時䙁䅍睒䉂䙁䄸兔䉂䙁䅉睒䩂䕁䄴䅁䑁杁䅁李䅁䕁䅫兕時䙁䅑睔啂䕁䅅䅔時䙁䅍杕時䙁䅍兒䑂䙁䅕杕䙂䕁䅑睘䙂䕁䅉兓啂䕁䅑兑䅁䡁䈰䅁慁䅁䅁兓剂䙁䄸睕䡂䕁䅅睘呂䙁䅕䅕兂䕁䅷䅁歃䅁䅁杚䅁䙁䅳兔䩂䙁䄸睑療䝁䄰䅣桂䝁䄴入時䕁䅳党㕂䙁䅍䅤桂䡁䅑督時䡁䅙免畁䡁䅧䅢穂䝁䄰兘䱂䝁䅕入時䙁䅍䅤桂䡁䅑督桁䍁䅑睑歁䑁䅙睍㙁䍁䅑睑歁䑁䅙兏䅁䩁䕉䅁畁䅁䅁兓剂䙁䄸兖䝂䕁䅍杒時䑁䅍兗卂䙁䄸兑佂䕁䄴睘䡂䙁䅉睔塂䙁䅑䅓䅁䥁䍕䅁歁䅁䅁兓剂䙁䄸睕卂䙁䄸䅒䙂䕁䅉䅖時䕁䅕村䩂䙁䅑䅒䉂䅁䅁睩䅅䑁䅁䅁䩂䙁䅅睘呂䙁䅉睘䕂䕁䅕村啂䙁䄸兒䍂䕁䅫䅖䕂䕁䅅睘䑂䕁䅅䅕䙂䙁䅧䅁⽂允䅁杈䅁䕁䅫兕時䙁䅍杕時䕁䅑兒䍂䙁䅑睘兂䕁䅍䅖䅁䉁䈴䅁㡁䅁䅁兓剂䙁䄸睕卂䙁䄸睕䙂䕁䅍兖卂䕁䅕䅒時䕁䅉睔佂䕁䅑睕時䕁䄴睔啂䕁䅕睕時䙁䅁睑啂䅁䅁杘䅅䑁䅁䅁䩂䙁䅅睘呂䙁䅉睘呂䕁䅕睑噂䙁䅉兒䕂䙁䄸䅔偂䕁䅅杔呂䙁䄸䅕䑂䙁䅑䅁坂允䅁䅌䅁䕁䅫兕時䙁䅣兑卂䙁䅉兑佂䙁䅑睕時䕁䅍兑佂䕁䅍兒䵂䕁䅷兒䕂䅁䅁䅕䅍䉁䄴䅁䩂䙁䅅睘呂䙁䅉睘呂䙁䅕村時䕁䅑兒䍂䙁䅑䅁啁允䅁杌䅁䕁䅫兕時䙁䅕杔䉂䕁䄰睔卂䙁䅑睘兂䙁䅉兒乂䕁䅫兖乂䙁䄸䅕䑂䙁䅑䅁⭄䅁䅁杊䅁䕁䅫兕時䙁䅍杕時䙁䅍兖䍂䙁䄸䅒䙂䕁䅉䅖時䙁䅁睑啂䅁䅁杊䅅䑁䅧䅁䩂䙁䅅睘呂䙁䅉睘噂䕁䄴睕䙂䕁䅍兖卂䕁䅕䅒時䕁䅉睔佂䕁䅑睕時䕁䄴睔啂䕁䅕睕䅁䑁䈴䅁捃䅁䅁睊扂䕁䅍睢睂䡁䅫䅉療䝁䅙䅉呂䙁䅁睒時䕁䅍睢瑂䡁䅁兙畂䡁䅫睘䱂䝁䅕入呂䡁䅑兙あ䡁䅍睘㉂䑁䅉睘畂䝁䅕睤畁䡁䅧䅢穂䝁䄰兘䑂䝁䅅䅣灂䡁䅑兙獂䙁䄸睕あ䡁䅉兤橂䡁䅑兤祂䝁䅕睘杁䕁䅑党あ䝁䅅兡獂䡁䅍䅉湁䍁䅅䅊䉂䕁䅅䅊㍁䅁䅁䅤䅣䉁䄴䅁䩂䙁䅅睘呂䙁䅑睘䕂䕁䅕村啂䙁䄸䅕䑂䙁䅑䅁杁允䅁杓䅁䙁䅍杣畁䍁䅁睕ㅂ䝁䅉杌杁䕁䅑党楂䡁䅑䅉癁䍁䅁䅋䙂䕁䅉兓啂䕁䅑兑杁䍁䄰䅉䑂䝁䅅䅣求䡁䅧克杁䍁䅧䅥灁䅁䅁杩䅅䑁䄴䅁偂䡁䅁䅤灂䝁䄸杢穂䑁䅯䅉呂䡁䅑兙あ䝁䅫督あ䝁䅫睙㥁䙁䅍䅖䕂䕁䅕杖獁䕁䄴兑㥁䕁䄴兑䅁䙁䝍䅁杁䅁䅁兓剂䙁䄸睕噂䕁䅉睘䕂䕁䅕村啂䙁䄸䅕䑂䙁䅑䅁潁允䅁䅘䅁䙁䅳兔䩂䙁䄸睑療䝁䄰䅣桂䝁䄴入時䕁䅳党㕂䙁䅍䅤桂䡁䅑督時䡁䅙免畁䡁䅧䅢穂䝁䄰兘卂䝁䅅䅤灂䝁䄸督桁䍁䅑䅒歁䑁䅑杏歁䕁䅫䅊ぁ䅁䅁兊䅑䥁䄴䅁湁䙁䅳睑療䡁䅁入杁䝁䄸杚杁䙁䅍䅕䡂䙁䄸睑療䝁䄰䅣桂䝁䄴入時䕁䅳党㕂䙁䅍䅤桂䡁䅑督時䡁䅙杍時䝁䄴党㍂䍁䄴䅥獂䡁䅍兢摂䕁䅍兙睂䝁䅫䅤桂䝁䅷兡㙂䝁䅅䅤灂䝁䄸杢湁䍁䅅䅊䙂䍁䅑兎硁䑁䅯䅊䭂䍁䅑兎硁䅁䅁兕䅣䩁䅧䅁偂䡁䅁䅤灂䝁䄸杢穂䑁䅯䅉䑂䡁䅕杣祂䑁䄰杓兂䙁䅫䅌杁䕁䄰兙湂䑁䄰兔灂䝁䅷䅢灂䝁䄸杢穂䍁䅷睑療䝁䄴杤乂䝁䅕䅤潂䝁䄸䅚㥁䕁䄰兓祂䝁䅕睙療䝁䄰兢求䝁䄴䅚求䝁䅑䅌杁䕁䄴兑㥁䕁䄴兑獁䍁䅁䅖求䡁䅉兢㥁䝁䅕杢瑁䙁䅕睕䅁䱁䕧䅁睁䅁䅁兓剂䙁䄸睕噂䕁䅉睘䵂䕁䅕兑呂䕁䅕睘䉂䕁䅙䅖䙂䙁䅉睘䝂䕁䅫杖䙂䅁䅁儰䅅䍁䅧䅁䩂䙁䅅睘呂䙁䅕村時䕁䅷兒䉂䙁䅍兒時䕁䅫杔䑂䙁䄸睑婂䅁䅁典䅅䝁䅯䅁扂䕁䄰兓時䕁䅍睢瑂䡁䅁兙畂䡁䅫睘䱂䝁䅕入呂䡁䅑兙あ䡁䅍睘㉂䑁䅅杌㑂䝁䅷督瑂䙁䄰睓求䡁䅫睘呂䡁䅑兙あ䡁䅍光歁䕁䅕䅊硁䑁䅁李㙁䍁䅑睒歁䑁䅅䅍㉁䅁䅁睬䅑䍁䅯䅁䩂䙁䅅睘呂䙁䅕村時䕁䅷兒䉂䙁䅍兒時䕁䅫杔䑂䙁䄸睑婂䑁䅍䅁䱄允䅁杋䅁䕁䅫兕時䙁䅍兖䍂䙁䄸䅔䙂䕁䅅睕䙂䙁䄸兓佂䕁䅍睘䑂䙁䅫䅎䅁䵁䈰䅁祂䅁䅁睗呂䙁䅁睒時䕁䅍睢瑂䡁䅁兙畂䡁䅫睘䱂䝁䅕入呂䡁䅑兙あ䡁䅍睘㉂䑁䅅杌㑂䝁䅷督瑂䙁䄰兓畂䝁䅍睢瑂䝁䅕睘呂䡁䅑兙あ䝁䅕兢求䝁䄴䅤桁䍁䅑兒歁䑁䅣杏歁䙁䅁䅊㍁䅁䅁眵䅕䙁䄴䅁佂䝁䅕䅤杁䙁䅁杣療䡁䅁党祂䡁䅑入獁䍁䅁䅕獂䝁䅅杢あ䍁䅁兙畂䝁䅑䅉䙂䡁䅅兤灂䡁䅁杌獁䍁䅁兎杁䙁䅫杣畁䍁䅁睑䉂䕁䅣杕杁䍁䅧兊灁䅁䅁杮䅉䙁䅑䅁扂䕁䄰兓時䕁䅳党㕂䙁䅍䅤桂䡁䅑督時䡁䅙免畁䡁䅧䅢穂䝁䄰兘䑂䝁䅅督潂䙁䄸杒獂䝁䄸睤桁䍁䅑睑歁䑁䅫杏歁䕁䅍䅊㕁䑁䅅䅁湄睁䅁杌䅁䕁䅫兕時䙁䅍兖䍂䙁䄸䅔䙂䕁䅅睕䙂䙁䄸杔䙂䙁䅧䅖時䕁䅙兓坂䕁䅕䅁偄允䅁䅌䅁䕁䅫兕時䙁䅑兑奂䙁䄸村䙂䕁䄴兒䝂䕁䅫䅖時䕁䅍杒時䑁䅅兗卂䅁䅁杹䅉䡁䅉䅁扂䕁䄰兓時䕁䅍睢瑂䡁䅁兙畂䡁䅫睘䱂䝁䅕入呂䡁䅑兙あ䡁䅍睘㉂䑁䅅睘畁䡁䅧䅢穂䝁䄰兘䑂䝁䅅䅣灂䡁䅑兙獂䝁䅫来桂䡁䅑兡療䝁䄴光歁䕁䅕䅊ㅁ䑁䅉杏歁䕁䅯䅊ㅁ䑁䅉䅁睄䅂䅁䅌䅁䕁䅫兕時䙁䅑兑奂䙁䄸村䙂䕁䄴兒䝂䕁䅫䅖時䕁䅍杒時䑁䅑兗卂䅁䅁末䅉䑁䅯䅁䩂䙁䅅睘啂䕁䅅䅗時䕁䅉兒佂䕁䅕杒䩂䙁䅑睘䑂䕁䅙睘䉂䕁䅙䅖䙂䙁䅉睘䝂䕁䅫杖䙂䅁䅁术䅉䝁䅯䅁扂䕁䄰兓時䕁䅍睢瑂䡁䅁兙畂䡁䅫睘䱂䝁䅕入呂䡁䅑兙あ䡁䅍睘㉂䑁䅅杌㑂䝁䅷督瑂䙁䄰睓求䡁䅫睘呂䡁䅑兙あ䡁䅍光歁䕁䅍䅊硁䑁䅁兏㙁䍁䅑睑歁䑁䅅免ㅁ䅁䅁睲䅕䍁䅁䅁呂䙁䅁睘啂䕁䅕杖時䕁䅕村䩂䙁䅑睘䝂䙁䅣䅒䅁䙁䝯䅁祁䅁䅁兓剂䙁䄸䅖䉂䙁䅧睘䍂䕁䅕杔䙂䕁䅙兓啂䙁䄸睑䝂䙁䄸杔偂䙁䄸兒奂䙁䅁䅁⭃杁䅁䅨䅁䍁䅣睗呂䙁䅁睒時䕁䅍睢瑂䡁䅁兙畂䡁䅫睘䱂䝁䅕入呂䡁䅑兙あ䡁䅍睘㉂䑁䅉杌㑂䝁䅷督瑂䙁䄰睑桂䡁䅁兡あ䝁䅅䅢時䙁䅍䅤祂䡁䅕睙あ䡁䅕杣求䙁䄸䅉䕂䝁䅕䅤桂䝁䅫䅢穂䍁䅁睊桁䍁䅑兒歁䑁䅑䅎䅁䍁䥫䅁䕃䅁䅁睊扂䙁䅍䅕䡂䙁䄸睑療䝁䄰䅣桂䝁䄴入時䕁䅳党㕂䙁䅍䅤桂䡁䅑督時䡁䅙杍畁䡁䅧䅢穂䝁䄰兘䑂䝁䅅䅣灂䡁䅑兙獂䙁䄸睕あ䡁䅉兤橂䡁䅑兤祂䝁䅕睘杁䕁䅑党あ䝁䅅兡獂䡁䅍䅉湁䍁䅅䅊䕂䍁䅑睎㉁䅁䅁先䅧䝁䅙䅁䵂䝁䅕杤求䝁䅷䅉祁䍁䅁䅔灂䝁䅅杙灂䝁䅷兡あ䝁䅫党穂䍁䅁兌杁䕁䄸杙穂䝁䅕杣㉂䝁䅅杙獂䝁䅕䅉兂䡁䅉兡橂䝁䅕督杁䍁䅧杕求䡁䅁睢祂䡁䅑党歂䍁䅫䅁桁睁䅁䅨䅁䙁䅳睕兂䕁䅣睘䑂䝁䄸兢睂䝁䅅杢㕂䙁䄸睓求䡁䅫睕あ䝁䅅䅤穂䙁䄸杤硁䍁䄴䅥獂䡁䅍兢摂䕁䅍兙睂䝁䅫䅤桂䝁䅷睘呂䡁䅑杣ㅂ䝁䅍䅤ㅂ䡁䅉党時䙁䅍兤瑂䝁䄰兙祂䡁䅫光歁䕁䅕䅊㍁䑁䅯䅊偂䍁䅑睎䅁偁䘸䅁䕃䅁䅁睊扂䙁䅍䅕䡂䙁䄸睑療䝁䄰䅣桂䝁䄴入時䕁䅳党㕂䙁䅍䅤桂䡁䅑督時䡁䅙杍畁䡁䅧䅢穂䝁䄰兘䑂䝁䅅䅣灂䡁䅑兙獂䙁䄸睕あ䡁䅉兤橂䡁䅑兤祂䝁䅕睘杁䕁䅑党あ䝁䅅兡獂䡁䅍䅉湁䍁䅅䅊䝂䍁䅑免祁䅁䅁睈䅧䑁䅁䅁䩂䙁䅅睘啂䕁䅅䅗時䕁䅉兒佂䕁䅕杒䩂䙁䅑睘䑂䕁䅙睘啂䕁䄸䅖䉂䕁䅷䅁䍁睁䅁䅍䅁䙁䅍䅕時䕁䄰睓啂䕁䅍兑兂䙁䄸䅖偂䙁䅑兑䵂䙁䄸杕䙂䙁䅙睘䝂䙁䅣䅒䅁䝁䝷䅁畁䅁䅁兓剂䙁䄸䅖偂䙁䅑兑䵂䙁䄸睑偂䕁䄰兔偂䕁䄴睘䙂䙁䅅兖䩂䙁䅑兗䅁䡁䅁䅁獁䅁䅁兓剂䙁䄸䅖䍂䙁䅙睘硁䙁䅫杕時䕁䅅杔佂䙁䄸睒卂䕁䄸睖啂䕁䅧䅁瑁杁䅁䅌䅁䕁䅫兕時䙁䅑村坂䙁䄸杍婂䙁䅉睘䉂䕁䄴杔時䕁䅣杕偂䙁䅣䅖䥂䅁䅁睖䅉䝁䅯䅁扂䙁䅍䅕䡂䙁䄸睑療䝁䄰䅣桂䝁䄴入時䕁䅳党㕂䙁䅍䅤桂䡁䅑督時䡁䅙免畁䡁䅧䅢穂䝁䄰兘呂䡁䅕䅣睂䝁䅷党瑂䝁䅕杢あ䝁䅅䅢桁䍁䅑䅒歁䑁䅣杏歁䕁䅫䅊㍁䅁䅁睃䅙䍁䅷䅁䩂䙁䅅睘啂䕁䅉杖時䑁䅕兗卂䙁䄸兑佂䕁䄴睘䡂䙁䅉睔塂䙁䅑䅓䅁䭁䍅䅁敂䅁䅁杔求䡁䅑䅉兂䡁䅉睢睂䝁䅕杣あ䡁䅫䅌杁䙁䅁䅢桂䝁䄴䅤杁䝁䅅杢歂䍁䅁兒硂䡁䅕兡睂䍁䄴䅌杁䑁䅉䅉婂䡁䅉杌杁䕁䅍兑䡂䙁䅉䅉潁䍁䅕克䅁䑁䍷䅁佂䅁䅁䅖療䡁䅑兙獂䍁䅁睑療䝁䄴杤求䡁䅉䅤灂䝁䅉䅢求䍁䅁䅒求䝁䅉䅤癁䍁䅁䅖療䡁䅑兙獂䍁䅁䅒求䝁䅉䅤杁䍁䅧兊灁䅁䅁睋䅅䝁䅧䅁扂䕁䄰兓時䙁䅉兒䩂䙁䅑睘呂䝁䅅兢求䙁䅍䅤療䡁䅉党啂䝁䅕兢睂䝁䅷兙あ䝁䅕睘㉂䑁䅅杌㑂䝁䅷督摂䕁䅑兙あ䝁䅅光歁䕁䄰䅊ぁ䑁䅙杏歁䕁䅙杕歁䑁䅑李䅁乁䐰䅁祁䅁䅁兓剂䙁䄸䅖偂䙁䅑兑䵂䙁䄸睖䉂䙁䅉杕䉂䕁䄴䅖呂䙁䄸兓呂䙁䅍兖䙂䕁䅑䅁奂睁䅁䅊䅁䕁䅫兕時䙁䅑兒卂䕁䄰睘䵂䕁䄸兑佂䙁䅍睘兂䕁䅍䅖䅁偁䅧䅁奁䅁䅁兓剂䙁䄸䅖䙂䙁䅙睘噂䕁䅙睑䝂䅁䅁䅘䅙䙁䅙䅁扂䙁䅍䅕䡂䙁䄸睑療䝁䄰䅣桂䝁䄴入時䕁䅳党㕂䙁䅍䅤桂䡁䅑督時䡁䅙杍畁䡁䅧䅢穂䝁䄰兘呂䝁䅧党求䡁䅑免桁䍁䅑兑䉂䍁䅑兎䅁䭁䝣䅁⭁䅁䅁兓剂䙁䄸䅖偂䙁䅑兑䵂䙁䄸兑呂䙁䅍兒啂䙁䅍睘穁䙁䅫杕時䕁䅅杔佂䙁䄸睒卂䕁䄸睖啂䕁䅧䅁㕂杁䅁杗䅁䙁䅳兔䩂䙁䄸睓求䡁䅫睕あ䝁䅅䅤穂䙁䄸杤硁䍁䄴䅥獂䡁䅍兢摂䕁䅳党㕂䙁䄸睕あ䝁䅅䅤穂䍁䅅䅊䑂䍁䅑免睁䑁䅅杏歁䕁䅍䅊硁䑁䅁兎䅁䡁䑳䅁㡁䅁䅁兓剂䙁䄸䅖偂䙁䅑兑䵂䙁䄸䅔䩂䕁䅅村時䙁䅑睔時䙁䅑睔啂䕁䅅䅔時䕁䅅睕呂䕁䅕䅖呂䅁䅁睳䅉䑁䅙䅁䩂䙁䅅睘啂䕁䄸䅖䉂䕁䅷睘偂䙁䅁䅖䩂䕁䄸杔呂䙁䄸睑䉂䕁䄴睑䙂䕁䅷䅔䙂䕁䅑䅁䝂睁䅁杚䅁䙁䅳兔䩂䙁䄸睑療䝁䄰䅣桂䝁䄴入時䕁䅳党㕂䙁䅍䅤桂䡁䅑督時䡁䅙免時䍁䄴䅥獂䡁䅍兢摂䕁䅍兙睂䝁䅫䅤桂䝁䅷兡㙂䝁䅅䅤灂䝁䄸杢桁䍁䅑睑歁䑁䅑䅏䅁佁䕫䅁祁䅁䅁兓剂䙁䄸䅖偂䙁䅑兑䵂䙁䄸睔兂䙁䅑兓偂䕁䄴睕時䕁䅣杕䉂䕁䄴䅖䙂䕁䅑䅁䅂睁䅁杕䅁䙁䅳睓求䡁䅫睕あ䝁䅅䅤穂䙁䄸䅤求䡁䅍䅤浂䝁䅫䅢求䍁䄴䅥獂䡁䅍䅥摂䙁䅍䅡求䝁䅕䅤祁䍁䅅䅊䙂䍁䅑䅏㙁䍁䅑兒歁䑁䅫䅁潁䅁䅁杋䅁䕁䅫兕時䙁䅑睔啂䕁䅅䅔時䙁䅁杕䙂䕁䅙睘䙂䙁䅅兖䩂䙁䅑兗䅁䉁䅯䅁㑁䅁䅁兓剂䙁䄸䅖偂䙁䅑兑䵂䙁䄸杕䙂䙁䅙睘硁䙁䅫杕時䕁䅅杔佂䙁䄸睒卂䕁䄸睖啂䕁䅧䅁䅁䅁䅁䅏䅁䕁䅫兕時䙁䅑睔啂䕁䅅䅔時䙁䅉兒坂䙁䄸睍婂䙁䅉睘䉂䕁䄴杔時䕁䅣杕偂䙁䅣䅖䥂䅁䅁睚䅉䑁䅧䅁䩂䙁䅅睘啂䕁䄸䅖䉂䕁䅷睘卂䕁䅕杖時䑁䅕兗卂䙁䄸兑佂䕁䄴睘䡂䙁䅉睔塂䙁䅑䅓䅁䭁䌸䅁䍂䅁䅁兓剂䙁䄸䅖偂䙁䅑兑䵂䙁䄸睕卂䙁䄸睕䙂䕁䅍兖卂䕁䅕䅒時䕁䅕村䩂䙁䅑䅒䉂䙁䄸睑䉂䙁䅁兒奂䅁䅁八䅅䝁䅁䅁扂䕁䄰兓時䕁䅍睢瑂䡁䅁兙畂䡁䅫睘䱂䝁䅕入呂䡁䅑兙あ䡁䅍睘㉂䑁䅅杌㑂䝁䅷督瑂䙁䄰村桂䝁䅷兙畂䝁䅍党時䙁䅍䅡求䝁䅕䅤桁䍁䅑睑歁䑁䅑䅁䥁䅂䅁䅍䅁䕁䅫兕時䙁䅑睔啂䕁䅅䅔時䙁䅍杕時䙁䅍兒䑂䙁䅕杕䙂䕁䅑睘兂䕁䅍䅖䅁䙁䉯䅁歁䅁䅁兓剂䙁䄸䅖偂䙁䅑兑䵂䙁䄸睕噂䕁䅉睘䕂䕁䅕村啂䅁䅁杇䅅䕁䄴䅁䵂䝁䅕杤求䡁䅉党歂䍁䅁杒祂䝁䅕党杁䕁䅍兙穂䝁䅧䅉䝂䝁䅷睢㍂䍁䅷䅉祁䍁䅁兗祂䍁䄴䅉䑂䕁䅅睒卂䍁䅁䅋汁䍁䅫䅁敂杁䅁䅌䅁䕁䅫兕時䙁䅑睔啂䕁䅅䅔時䙁䅍兖䍂䙁䄸䅒䙂䕁䅉䅖時䙁䅁睑啂䅁䅁杉䅅䑁䅉䅁䩂䙁䅅睘啂䕁䄸䅖䉂䕁䅷睘塂䕁䅅杕卂䕁䅅杔啂䙁䅍睘䍂䕁䅕睒時䕁䄸睕䅁䙁䑙䅁㑁䅁䅁兓剂䙁䄸䅖偂䙁䅑兑䵂䙁䄸睖䉂䙁䅉杕䉂䕁䄴䅖呂䙁䄸兒奂䕁䅕杕䑂䕁䅫睕䙂䕁䅑䅁慂睁䅁杌䅁䕁䅫兕時䙁䅑杕噂䙁䅍䅖時䙁䅁杕䙂䕁䅙兒卂䙁䅉兒䕂䙁䄸䅕䑂䙁䅑䅁潂允䅁杚䅁䙁䅳睓求䡁䅫睕あ䝁䅅䅤穂䙁䄸䅤求䡁䅍䅤浂䝁䅫䅢求䍁䄴䅥獂䡁䅍兢摂䕁䅍兙睂䝁䅫䅤桂䝁䅷兡㙂䝁䅅䅤灂䝁䄸杢桁䍁䅑杒歁䑁䅑䅏㙁䍁䅑睓歁䑁䅑䅏䅁佁䅁䅁䕂䅁䅁䅔求䡁䅙党祂䝁䅕䅚杁䕁䅙杣求䝁䅕䅉䑂䝁䅅督潂䍁䅁杒獂䝁䄸睤杁䕁䄰兙祂䝁䅣兡畂䍁䅁䅋汁䍁䅫䅁十杁䅁杓䅁䙁䅳睓求䡁䅫睕あ䝁䅅䅤穂䙁䄸䅤求䡁䅍䅤浂䝁䅫䅢求䍁䄴䅥獂䡁䅍䅥摂䙁䅍䅡求䝁䅕䅤硁䍁䅅䅊䍂䍁䅑兎祁䅁䅁䅤䅁䍁䄴䅁䩂䙁䅅睘噂䕁䅙睑䝂䙁䄸免婂䙁䅉睘䉂䕁䄴杔時䕁䅣杕偂䙁䅣䅖䥂䅁䅁兎䅉䕁䅯䅁啂䝁䄸䅤桂䝁䅷䅉呂䝁䅕杢灂䝁䄸杣杁䙁䅍党橂䡁䅕杣求䝁䅑䅉䕂䝁䅕杙あ䍁䅁䅋卂䝁䅕䅣療䡁䅉䅤求䝁䅑克䅁䑁䉕䅁慂䅁䅁睗乂䕁䅫睘䱂䝁䅕入呂䡁䅑兙あ䡁䅍睘㉂䑁䅅杌㑂䝁䅷督瑂䙁䄰睓求䡁䅫睘呂䡁䅑兙あ䡁䅍光歁䕁䅕䅊硁䑁䅁䅎㙁䍁䅑睒歁䑁䅅䅍ぁ䅁䅁睺䅍䍁䄴䅁䩂䙁䅅睘噂䕁䅙睑䝂䙁䄸杍婂䙁䅉睘䉂䕁䄴杔時䕁䅣杕偂䙁䅣䅖䥂䅁䅁睓䅉䥁䅑䅁湁䙁䅳睕兂䕁䅣睘䑂䝁䄸兢睂䝁䅅杢㕂䙁䄸睓求䡁䅫睕あ䝁䅅䅤穂䙁䄸杤祁䍁䄴䅥獂䡁䅍兢摂䕁䅍兙睂䝁䅫䅤桂䝁䅷睘呂䡁䅑杣ㅂ䝁䅍䅤ㅂ䡁䅉党時䍁䅁䅒求䡁䅑兙灂䝁䅷督杁䍁䅣光歁䕁䅫䅊㍁䑁䅙䅁ぁ䅃䅁杌䅁䕁䅫兕時䙁䅕杒䑂䕁䅙睘ㅁ䙁䅫杕時䕁䅅杔佂䙁䄸睒卂䕁䄸睖啂䕁䅧䅁牃杁䅁杘䅁䙁䅳兔䩂䙁䄸睓求䡁䅫睕あ䝁䅅䅤穂䙁䄸杤硁䍁䄴䅥獂䡁䅍兢摂䕁䅉兙獂䝁䅅杢橂䝁䅕睘呂䝁䅧党求䡁䅑光歁䕁䅍䅊㕁䑁䅯䅊䑂䍁䅑免穁䑁䅫䅁汄睁䅁杈䅁䕁䅫兕時䙁䅕杒䑂䕁䅙睘乂䕁䅅杕䡂䕁䅫杔䅁䉁䍍䅁䭁䅁䅁杒剂䍁䄰杍䅁䱁䠰䅁䍃䅁䅁睊扂䕁䅍睢睂䡁䅫䅉療䝁䅙䅉呂䙁䅁睒時䕁䅍睢瑂䡁䅁兙畂䡁䅫睘䱂䝁䅕入呂䡁䅑兙あ䡁䅍睘㉂䑁䅉睘畂䝁䅕睤畁䡁䅧䅢穂䝁䄰兘䑂䝁䅅䅣灂䡁䅑兙獂䝁䅫来桂䡁䅑兡療䝁䄴睊桁䍁䅑睑歁䑁䅑兏䅁䙁䡑䅁潁䅁䅁兓剂䙁䄸兖佂䕁䅅兔偂䙁䅉䅖時䕁䅑兓呂䕁䅍睘兂䕁䅍䅖䅁䅁䉁䅁捂䅁䅁睗䱂䝁䅕入呂䡁䅑兙あ䡁䅍睘あ䝁䅕督あ䝁䅙兡獂䝁䅕杌㑂䝁䅷督瑂䙁䄰睓求䡁䅫睘呂䡁䅑兙あ䡁䅍光歁䕁䅑䅊祁䑁䅕杏歁䕁䅑䅊ぁ䑁䅫䅁扃䅁䅁权䅁䕁䅙兕瑁䑁䅅䅁⭃睂䅁䅰䅁䍁䅣睗䑂䝁䄸䅣㕂䍁䅁睢浂䍁䅁睕兂䕁䅣睘䑂䝁䄸兢睂䝁䅅杢㕂䙁䄸睓求䡁䅫睕あ䝁䅅䅤穂䙁䄸杤祁䙁䄸杢求䡁䅣杌㑂䝁䅷督瑂䙁䄰睑桂䡁䅁兡あ䝁䅅䅢時䙁䅍䅤祂䡁䅕睙あ䡁䅕杣求䙁䄸睕ㅂ䝁䄰兢桂䡁䅉入湁䍁䅅䅊䕂䍁䅑杍㕁䑁䅯䅊䕂䍁䅑睎㕁䅁䅁䅷䅣䉁䅷䅁䩂䙁䅅睘噂䕁䄴䅒卂䕁䅅睖佂䙁䄸睑兂䅁䅁杂䅅䕁䅯䅁扂䕁䅳党㕂䙁䅍䅤桂䡁䅑督時䡁䅑党穂䡁䅑杚灂䝁䅷党畁䡁䅧䅢穂䝁䄰兘呂䝁䅧党求䡁䅑免桁䍁䅑兒歁䑁䅕杍䅁䥁䅁䅁獂䅁䅁睗乂䕁䅫睘䑂䝁䄸兢睂䝁䅅杢㕂䙁䄸睓求䡁䅫睕あ䝁䅅䅤穂䙁䄸杤硁䙁䄸杌㑂䝁䅷督瑂䙁䄰睓求䡁䅫睘呂䡁䅑兙あ䡁䅍光歁䕁䅍䅊硁䑁䅅䅍㙁䍁䅑睑歁䑁䅅免ぁ䅁䅁睺䅑䍁䅑䅁䩂䙁䅅睘噂䕁䄴䅒卂䕁䅅睖佂䙁䄸睑卂䕁䅕䅒䩂䙁䅑䅁䵁允䅁䅈䅁䕁䅫兕時䙁䅕杔䕂䙁䅉兑塂䕁䄴睘啂䕁䅷䅁䥁允䅁䅒䅁䕁䅫兕時䙁䅕杔卂䕁䅕睑偂䕁䅣睘啂䕁䅅䅗時䕁䅉兒佂䕁䅕杒䩂䙁䅑睘䙂䕁䄴䅒時䙁䅁兒卂䕁䅫睔䕂䅁䅁䅅䅍䙁䅙䅁扂䕁䅳党㕂䙁䅍䅤桂䡁䅑督時䡁䅑党穂䡁䅑杚灂䝁䅷党畁䡁䅧䅢穂䝁䄰兘呂䝁䅧党求䡁䅑免桁䍁䅑杓歁䑁䅉睍㙁䍁䅑䅔歁䑁䅉睍䅁䥁䄰䅁畂䅁䅁睗呂䙁䅁睒時䕁䅍睢瑂䡁䅁兙畂䡁䅫睘䱂䝁䅕入呂䡁䅑兙あ䡁䅍睘㉂䑁䅅杌㑂䝁䅷督瑂䙁䄰睑桂䡁䅁兡あ䝁䅅䅢灂䡁䅯兙あ䝁䅫睢畂䍁䅅䅊䙂䍁䅑兎㙁䍁䅑杓歁䑁䅕䅁穄兂䅁䅌䅁䕁䅫兕時䙁䅕杔呂䕁䅕睑噂䙁䅉兒䕂䙁䄸䅒䙂䕁䅉䅖時䙁䅁睑啂䅁䅁杙䅅䑁䅙䅁䩂䙁䅅睘噂䙁䅍睘䡂䕁䅅兑兂䙁䄸䅔䩂䕁䅅村時䙁䅑睔啂䕁䅅䅔時䕁䅷兓䉂䕁䅉䅁䕄杁䅁䅣䅁䙁䅳睕兂䕁䅣睘䑂䝁䄸兢睂䝁䅅杢㕂䙁䄸睓求䡁䅫睕あ䝁䅅䅤穂䙁䄸杤祁䍁䄴䅥獂䡁䅍兢摂䙁䅍兤睂䡁䅁䅢求䝁䄰党畂䡁䅑兙獂䍁䅅䅊䑂䍁䅑免硁䑁䅯䅊䑂䍁䅑免㉁䑁䅑䅁允䅃䅁䅌䅁䕁䅫兕時䙁䅙兑卂䕁䅫兑䍂䕁䅷兒時䙁䅉兑啂䕁䅕睘䕂䕁䅕村啂䅁䅁䅕䅅䍁䅙䅁䩂䙁䅅睘塂䕁䅅杕卂䕁䅅杔啂䙁䅍睘䍂䕁䅕睒時䕁䄸睕䅁䕁䑯䅁佃䅁䅁睊扂䕁䅍睢睂䡁䅫䅉療䝁䅙䅉呂䙁䅁睒時䕁䅍睢瑂䡁䅁兙畂䡁䅫睘䱂䝁䅕入呂䡁䅑兙あ䡁䅍睘㉂䑁䅉睘畂䝁䅕睤畁䡁䅧䅢穂䝁䄰兘䍂䝁䅅䅢桂䝁䄴睙求䙁䄸睕潂䝁䅕党あ䍁䅣光歁䕁䅍䅊硁䑁䅅杏歁䕁䅍䅊祁䑁䅁免䅁䕁䡑䅁流䅁䅁兓剂䙁䄸睖䉂䙁䅉杕䉂䕁䄴䅖呂䙁䄸兓呂䙁䅍兖䙂䕁䅑䅁䵂睁䅁䅑䅁䕁䅫兕時䙁䅣兑卂䙁䅉兑佂䙁䅑睕時䙁䅍䅖卂䕁䅫睓䙂䙁䄸䅕卂䕁䅫睑䙂䙁䄸兓呂䙁䅍兖䙂䕁䅑䅁睁睁䅁杖䅁䙁䅳睕兂䕁䅣睘䑂䝁䄸兢睂䝁䅅杢㕂䙁䄸睓求䡁䅫睕あ䝁䅅䅤穂䙁䄸杤祁䍁䄴䅥獂䡁䅍兢摂䙁䅍䅡求䝁䅕䅤硁䍁䅅䅊䙂䍁䅑睎ㅁ䅁䅁䅵䅙䑁䅉䅁䩂䙁䅅睘塂䙁䅑䅒時䕁䅅杖䡂䙁䄸兓卂䙁䄸兑䝂䙁䅑兒卂䙁䄸杒䩂䙁䅙兒䅁佁䉍䅁歁䅁䅁兓剂䙁䄸睖啂䕁䅑睘䉂䙁䅙睒時䕁䅫杕時䕁䅍兗祁䅁䅁眶䅅䍁䅑䅁䩂䙁䅅睘塂䙁䅑䅒時䕁䅅杖䡂䙁䄸兓卂䙁䄸睑婂䑁䅑䅁癄允䅁䅌䅁䕁䅫兕時䙁䅣䅖䕂䙁䄸兑坂䕁䅣睘䩂䙁䅉睘䵂䙁䅑睘䕂䕁䅕村啂䅁䅁儴䅅䝁䄴䅁扂䙁䅍䅕䡂䙁䄸睑療䝁䄰䅣桂䝁䄴入時䕁䅳党㕂䙁䅍䅤桂䡁䅑督時䡁䅙杍畁䡁䅧䅢穂䝁䄰兘䑂䝁䅅䅣灂䡁䅑兙獂䝁䅫来桂䡁䅑兡療䝁䄴光歁䕁䅕䅊ぁ䑁䅯䅊䭂䍁䅑䅎䅁偁䠸䅁睁䅁䅁兓剂䙁䄸杗䙂䙁䅉睔時䕁䅍睔噂䙁䅁睔佂䙁䄸䅒䙂䕁䅉䅖時䙁䅁睑啂䅁䅁䅢䅅䙁䄴䅁䩂䝁䄰䅣桂䝁䅫杣畁䍁䅁睢浂䍁䅁睔灂䝁䅷䅌杁䕁䅣兙穂䍁䅁杊杁䕁䄰兡畂䝁䅕杣桂䝁䅷䅉兂䡁䅉睢睂䍁䄴䅉潁䙁䅉党睂䝁䄸杣あ䝁䅕䅚灁䅁䅁兴䅁䑁䅑䅁䩂䝁䄴杤求䝁䄴䅤療䡁䅉入獁䍁䅁杍杁䙁䅫杣畁䍁䅁睑䉂䕁䅣杕杁䍁䅧兊灁䅁䅁杕䅉䑁䅑䅁䩂䝁䄴杤求䝁䄴䅤療䡁䅉入獁䍁䅁睍杁䙁䅫杣畁䍁䅁睑䉂䕁䅣杕杁䍁䅧兊灁䅁䅁䅥䅉䍁䅷䅁佂䝁䅕䅤杁䕁䅑党楂䡁䅑䅉癁䍁䅁兒䍂䕁䅫䅖䕂䕁䅅䅉潁䡁䅧克䅁䥁䉙䅁捂䅁䅁䅔啂䍁䅁䅒求䝁䅉䅤杁䍁䅧兓畂䝁䅍䅢畁䍁䅁睑桂䡁䅁杌杁䕁䅷党桂䡁䅍党穂䍁䅫䅉䕂䡁䅕党杁䍁䅳免杁䍁䅧杕求䡁䅁睢祂䡁䅑党歂䍁䅫䅁捃允䅁䅘䅁䕁䅷䅖杁䕁䅑党楂䡁䅑䅉潁䕁䅫杢橂䝁䅷杌杁䕁䅍兙睂䍁䄴䅉䵂䝁䅕兙穂䝁䅕督灁䍁䅁䅒ㅂ䝁䅕䅉牁䑁䅉䅉潁䙁䅉党睂䝁䄸杣あ䝁䅕䅚灁䅁䅁杮䅅䡁䅧䅁湁䙁䅳睑療䡁䅁入杁䝁䄸杚杁䙁䅍䅕䡂䙁䄸睑療䝁䄰䅣桂䝁䄴入時䕁䅳党㕂䙁䅍䅤桂䡁䅑督時䡁䅙杍時䝁䄴党㍂䍁䄴䅥獂䡁䅍兢摂䕁䅳党㕂䙁䄸睕あ䝁䅅䅤穂䍁䅣光歁䕁䅕䅊㉁䑁䅉䅁癁睂䅁䅘䅁䕁䅷䅖杁䕁䅑党楂䡁䅑䅉潁䕁䅫杢橂䝁䅷杌杁䕁䅍兙睂䍁䄴䅉䵂䝁䅕兙穂䝁䅕督灁䍁䅁䅒ㅂ䝁䅕䅉牁䑁䅑䅉潁䙁䅉党睂䝁䄸杣あ䝁䅕䅚灁䅁䅁杯䅅䝁䅧䅁偂䡁䅁䅤灂䝁䄸杢穂䍁䅁睑桂䝁䄴睙求䝁䅷䅢求䝁䅑䅉䕂䡁䅕杣灂䝁䄴睚杁䡁䅑䅡求䍁䅁䅕求䡁䅉兡療䝁䅑䅌杁䙁䅑睢あ䝁䅅䅢杁䍁䅧兙橂䡁䅑兤桂䝁䅷克䅁䕁䑣䅁坂䅁䅁睗䱂䝁䅕入呂䡁䅑兙あ䡁䅍睘あ䝁䅕督あ䝁䅙兡獂䝁䅕杌㑂䝁䅷督㑂䙁䄰睕潂䝁䅕党あ䑁䅅光歁䕁䅑䅊祁䑁䅕杏歁䕁䅑䅊㉁䑁䅣䅁噂䅁䅁杨䅁䍁䅣睗䑂䝁䄸䅣㕂䍁䅁睢浂䍁䅁睕兂䕁䅣睘䑂䝁䄸兢睂䝁䅅杢㕂䙁䄸睓求䡁䅫睕あ䝁䅅䅤穂䙁䄸杤祁䙁䄸杢求䡁䅣杌㑂䝁䅷督瑂䙁䄰睕ㅂ䡁䅁䅣獂䝁䅕兢求䝁䄴䅤桂䝁䅷睊桁䍁䅑䅒歁䑁䅙杏歁䕁䅫䅊㉁䅁䅁睙䅣䙁䅷䅁䵂䙁䅑䅉䕂䝁䅕杙あ䍁䅁䅋䩂䝁䄴睙獂䍁䄴䅉䑂䝁䅅䅣畁䍁䅁䅔求䝁䅅督求䡁䅍克杁䕁䅑兤求䍁䅁睋ㅁ䍁䅁䅋卂䝁䅕䅣療䡁䅉䅤求䝁䅑克䅁䭁䉑䅁坂䅁䅁䅔桂䡁䅁督求䍁䅁睢浂䍁䅁睕あ䝁䅅䅤ㅂ䡁䅑党杁䝁䄸杚杁䕁䅷兡瑂䝁䅫䅤桂䡁䅑兡療䝁䄴督杁䍁䅧杕求䡁䅁睢祂䡁䅑党歂䍁䅫䅁䉄杁䅁杖䅁䙁䅳睕兂䕁䅣睘䑂䝁䄸兢睂䝁䅅杢㕂䙁䄸睓求䡁䅫睕あ䝁䅅䅤穂䙁䄸杤祁䍁䄴䅥獂䡁䅍兢摂䙁䅍䅡求䝁䅕䅤硁䍁䅅䅊䱂䍁䅑䅎穁䅁䅁䅳䅙䙁䅑䅁䵂䝁䅕杤求䝁䅷䅉硁䍁䅁兑穂䡁䅍党あ䡁䅍䅉瑁䍁䅁兕ㅂ䝁䄸䅤求䝁䅑䅉兂䡁䅉兡橂䝁䅕督杁䍁䅧杕求䡁䅁睢祂䡁䅑党歂䍁䅫䅁婁睁䅁䅘䅁䕁䅷党㉂䝁䅕䅢杁䑁䅉䅉䉂䡁䅍督求䡁䅑督杁䍁䄰䅉偂䝁䅉督求䡁䅉杤桂䝁䅉䅢求䍁䅁䅕祂䝁䅫睙求䡁䅍䅉潁䙁䅉党睂䝁䄸杣あ䝁䅕䅚灁䅁䅁眶䅉䡁䅉䅁扂䙁䅍䅕䡂䙁䄸睑療䝁䄰䅣桂䝁䄴入時䕁䅳党㕂䙁䅍䅤桂䡁䅑督時䡁䅙免畁䡁䅧䅢穂䝁䄰兘䑂䝁䅅䅣灂䡁䅑兙獂䝁䅫来桂䡁䅑兡療䝁䄴光歁䕁䅍䅊ㅁ䑁䅍杏歁䕁䅍䅊ㅁ䑁䅑䅁㉄兂䅁杖䅁䙁䅳睕兂䕁䅣睘䑂䝁䄸兢睂䝁䅅杢㕂䙁䄸睓求䡁䅫睕あ䝁䅅䅤穂䙁䄸杤祁䍁䄴䅥獂䡁䅍兢摂䙁䅍䅡求䝁䅕䅤硁䍁䅅䅊䑂䍁䅑䅎穁䅁䅁共䅙䙁䅙䅁偂䡁䅁䅤灂䝁䄸杢穂䑁䅯䅉䑂䡁䅕杣祂䑁䄰兖呂䕁䅑䅌䑂䝁䄸杢㉂䕁䄰党あ䝁䅧睢歂䑁䄰兔卂䙁䅍䅣療䡁䅑䅌杁䕁䄴兑㥁䕁䄴兑䅁䱁䡙䅁煂䅁䅁䅔求䡁䅙党獂䍁䅁睍杁䕁䅷兡桂䝁䅉兡獂䝁䅫䅤灂䝁䅕督杁䍁䄰䅉噂䝁䄴睢楂䡁䅍党祂䡁䅙兙楂䝁䅷党杁䙁䅁杣灂䝁䅍党穂䍁䅁䅋卂䝁䅕䅣療䡁䅉䅤求䝁䅑克䅁䍁䑍䅁佂䅁䅁䅔求䡁䅙党祂䝁䅕䅚杁䕁䅙杣求䝁䅕䅉䑂䝁䅅督潂䍁䅁杒獂䝁䄸睤獁䍁䅁兎杁䙁䅫杣畁䍁䅁睑䉂䕁䅣杕杁䍁䅧兊灁䅁䅁東䅉䝁䅙䅁䵂䝁䄸杢湂䍁䄰䅖求䡁䅉兢杁䕁䅑党楂䡁䅑䅉潁䕁䅫杢橂䝁䅷杌杁䕁䅍兙睂䍁䄴䅉䵂䝁䅕兙穂䝁䅕督灁䍁䄸䅉啂䝁䄸䅤桂䝁䅷䅉䕂䝁䅕杙あ䍁䅁䅋汁䍁䅫䅁噂允䅁杔䅁䙁䅑睢あ䝁䅅䅢杁䙁䅉党㉂䝁䄸䅢㉂䝁䅫杢湂䍁䅁睑祂䝁䅕䅚灂䡁䅑睌杁䙁䅑睢あ䝁䅅䅢杁䕁䅑党楂䡁䅑䅉潁䍁䅕克䅁偁䅕䅁䝂䅁䅁䅔療䝁䄴睚瑁䙁䅑党祂䝁䄰䅉䕂䝁䅕杙あ䍁䅁睌杁䙁䅑睢あ䝁䅅䅢杁䕁䅍兙睂䝁䅫䅤桂䝁䅷䅉潁䍁䅕克䅁䱁䍣䅁捁䅁䅁兔桂䡁䅉睡求䡁䅑督畁䙁䅉兙畂䝁䅣党䅁䩁䙣䅁捁䅁䅁兔桂䡁䅑兤祂䝁䅫䅤㕂䍁䅁䅒桂䡁䅑党䅁䩁䝫䅁浂䅁䅁睗乂䕁䅫睘䑂䝁䄸兢睂䝁䅅杢㕂䙁䄸睓求䡁䅫睕あ䝁䅅䅤穂䙁䄸杤硁䍁䄴䅥獂䡁䅍兢摂䕁䅳党㕂䙁䄸睕あ䝁䅅䅤穂䍁䅅䅊乂䍁䅑杍ㅁ䑁䅯䅊偂䍁䅑杍ㅁ䅁䅁睩䅑䝁䅙䅁扂䕁䄰兓時䕁䅍睢瑂䡁䅁兙畂䡁䅫睘䱂䝁䅕入呂䡁䅑兙あ䡁䅍睘㉂䑁䅅杌㑂䝁䅷督瑂䙁䄰睓求䡁䅫睘呂䡁䅑兙あ䡁䅍光歁䕁䄰䅊祁䑁䅍杏歁䕁䄸䅊祁䑁䅍䅁㕂䅂䅁村䅁䕁䄰兙㑂䍁䄴䅉婂䝁䅕兙祂䍁䅁杚療䡁䅉䅉佂䕁䄸䅔杁䕁䅍兙祂䡁䅉入杁䕁䅙睢祂䡁䅣兙祂䝁䅑䅉䅁佁䍫䅁獁䅁䅁䅖療䡁䅑兙獂䍁䅁䅒求䝁䅉䅤杁䍁䅧杕求䡁䅁睢祂䡁䅑党歂䍁䅫䅁婁䅁䅁䅘䅁䕁䄴睔䵂䍁䅁睑桂䡁䅉杣㕂䝁䅙睢祂䡁䅣兙祂䝁䅑䅌杁䕁䅅杚あ䝁䅕杣杁䕁䅙兡㉂䝁䅕䅉婂䝁䅕兙祂䡁䅍䅉潁䙁䅉党睂䝁䄸杣あ䝁䅕䅚灁䅁䅁兺䅉䕁䅷䅁扂䕁䄰兓時䕁䅳党㕂䙁䅍䅤桂䡁䅑督時䡁䅙免畁䡁䅧䅢穂䝁䄰兘卂䝁䅅䅤灂䝁䄸督桁䍁䅑䅒歁䑁䅑杏歁䕁䅫䅊ぁ䅁䅁关䅍䙁䅷䅁佂䕁䄸䅔杁䕁䅍兙祂䡁䅉入浂䝁䄸杣㍂䝁䅅杣歂䍁䅷䅉䑂䡁䅕杣祂䝁䅕杢あ䍁䅁兗求䝁䅅杣杁䍁䅳䅉硁䍁䅁䅋卂䝁䅕䅣療䡁䅉䅤求䝁䅑克䅁乁䍅䅁䥂䅁䅁䅖桂䝁䄴睚灂䝁䅉䅢求䍁䅁村療䝁䄸睡杁䙁䅙兙獂䡁䅕党獁䍁䅁兎杁䙁䅫杣畁䍁䅁睑䉂䕁䅣杕杁䍁䅧兊灁䅁䅁杯䅉䕁䅯䅁扂䕁䅳党㕂䙁䅍䅤桂䡁䅑督時䡁䅑党穂䡁䅑杚灂䝁䅷党畁䡁䅧䅢穂䡁䅧兘呂䝁䅧党求䡁䅑免桁䍁䅑村歁䑁䅉免䅁䕁䅁䅁捂䅁䅁杔偂䕁䅷䅉䑂䝁䅅杣祂䡁䅫杚療䡁䅉睤桂䡁䅉䅚獁䍁䅁睑ㅂ䡁䅉杣求䝁䄴䅤杁䙁䅫党桂䡁䅉䅉牁䍁䅁杍杁䍁䅧杕求䡁䅁睢祂䡁䅑党歂䍁䅫䅁呄杁䅁䅘䅁䕁䄴睔䵂䍁䅁睑桂䡁䅉杣㕂䝁䅙睢祂䡁䅣兙祂䝁䅑䅌杁䕁䅍兤祂䡁䅉党畂䡁䅑䅉婂䝁䅕兙祂䍁䅁睋杁䑁䅑䅉潁䙁䅉党睂䝁䄸杣あ䝁䅕䅚灁䅁䅁睷䅉䥁䅉䅁扂䕁䄰兓時䕁䅍睢瑂䡁䅁兙畂䡁䅫睘䱂䝁䅕入呂䡁䅑兙あ䡁䅍睘㉂䑁䅅杌㑂䝁䅷督瑂䙁䄰睑桂䡁䅁兡あ䝁䅅䅢時䙁䅍䅤祂䡁䅕睙あ䡁䅕杣求䙁䄸睕ㅂ䝁䄰兢桂䡁䅉入桁䍁䅑兒歁䑁䅑杏歁䕁䄸䅊ぁ䅁䅁先䅑䉁䅉䅁佂䙁䅫睕䙂䑁䅯兓䍂䕁䄰䅁䡃杂䅁䅋䅁䕁䄴党あ䍁䅁䅒求䝁䅉䅤杁䍁䅧杕求䡁䅁睢祂䡁䅑党歂䍁䅫䅁剁允䅁䅌䅁䕁䄴党あ䍁䅁兓畂䝁䅍睢瑂䝁䅕䅉潁䙁䅉党睂䝁䄸杣あ䝁䅕䅚灁䅁䅁睄䅁䩁䅷䅁湁䙁䅳睑療䡁䅁入杁䝁䄸杚杁䙁䅍䅕䡂䙁䄸睑療䝁䄰䅣桂䝁䄴入時䕁䅳党㕂䙁䅍䅤桂䡁䅑督時䡁䅙杍時䝁䄴党㍂䍁䄴䅥獂䡁䅍兢摂䕁䅍兙睂䝁䅫䅤桂䝁䅷睘呂䡁䅑杣ㅂ䝁䅍䅤ㅂ䡁䅉党時䍁䅁䅒求䡁䅑兙灂䝁䅷督杁䍁䅣光歁䕁䅅兑歁䑁䅕䅁獂睂䅁李䅁䕁䄴党あ䍁䅁兓畂䝁䅍睢瑂䝁䅕䅌杁䑁䅉䅉婂䡁䅉杌杁䕁䅍兑䡂䙁䅉䅉潁䍁䅕克䅁䑁䍯䅁㉁䅁䅁杔求䡁䅑䅉䩂䝁䄴睙療䝁䄰党獁䍁䅁兎杁䙁䅫杣畁䍁䅁睑䉂䕁䅣杕杁䍁䅧兊灁䅁䅁䅮䅉䝁䅙䅁扂䕁䄰兓時䕁䅍睢瑂䡁䅁兙畂䡁䅫睘䱂䝁䅕入呂䡁䅑兙あ䡁䅍睘㉂䑁䅅杌㑂䝁䅷督瑂䙁䄰睓求䡁䅫睘呂䡁䅑兙あ䡁䅍光歁䕁䅯䅊祁䑁䅉杏歁䕁䅷䅊祁䑁䅉䅁㕄睁䅁权䅁䕁䅙兗牁䑁䅍䅁癃䅃䅁杘䅁䕁䄴党あ䍁䅁䅕祂䝁䄸䅣求䡁䅉䅤㕂䍁䅷䅉兂䝁䅷兙畂䡁䅑䅉桂䝁䄴䅚杁䕁䅕兣ㅂ䝁䅫䅣畁䍁䅷䅉穁䍁䅁兗祂䍁䄴䅉䑂䕁䅅睒卂䍁䅁䅋汁䍁䅫䅁浂杁䅁杚䅁䕁䄴党あ䡁䅑兡畂䝁䅣䅉桂䝁䄴䅚杁䕁䄸䅤潂䝁䅕杣杁䕁䅅䅚煂䡁䅕督あ䝁䄰党畂䡁䅑督杁䡁䅑睢杁䕁䅅督穂䝁䅕䅤穂䍁䅁䅋卂䝁䅕䅣療䡁䅉䅤求䝁䅑克䅁䉁䐰䅁捃䅁䅁睊扂䕁䅍睢睂䡁䅫䅉療䝁䅙䅉呂䙁䅁睒時䕁䅍睢瑂䡁䅁兙畂䡁䅫睘䱂䝁䅕入呂䡁䅑兙あ䡁䅍睘㉂䑁䅉睘畂䝁䅕睤畁䡁䅧䅢穂䝁䄰兘䑂䝁䅅䅣灂䡁䅑兙獂䙁䄸睕あ䡁䅉兤橂䡁䅑兤祂䝁䅕睘杁䕁䅑党あ䝁䅅兡獂䡁䅍䅉湁䍁䅅䅊䍂䍁䅑免祁䅁䅁条䅣䑁䄴䅁佂䝁䄸杢杁䍁䄰䅉卂䝁䅕睙療䡁䅕杣穂䝁䅕䅉䕂䝁䅕杙あ䍁䅁䅋卂䝁䅕䅣療䡁䅉䅤求䝁䅑克䅁䕁䉫䅁啂䅁䅁睗呂䙁䅁睒時䕁䅍睢瑂䡁䅁兙畂䡁䅫睘䱂䝁䅕入呂䡁䅑兙あ䡁䅍睘㉂䑁䅅杌㑂䝁䅷督瑂䙁䄰杕桂䡁䅑兡療䡁䅍光歁䕁䅍䅊㉁䅁䅁䅂䅙䙁䅁䅁佂䝁䄸杣瑂䝁䅅䅢灂䡁䅯党歂䍁䅁杔求䡁䅑䅉䩂䝁䄴睙療䝁䄰党獁䍁䅁免杁䙁䅫杣畁䍁䅁睒祂䝁䄸睤あ䝁䅧䅉潁䍁䅕克䅁䉁䍧䅁奂䅁䅁睗䱂䝁䅕入呂䡁䅑兙あ䡁䅍睘あ䝁䅕督あ䝁䅙兡獂䝁䅕杌㑂䝁䅷督瑂䙁䄰睑桂䡁䅁兡あ䝁䅅䅢灂䡁䅯兙あ䝁䅫睢畂䍁䅅䅊䑂䍁䅑兎䅁䵁䅫䅁䵂䅁䅁杔療䡁䅉兢桂䝁䅷兡㙂䝁䅕䅚杁䕁䄴党あ䍁䅁兓畂䝁䅍睢瑂䝁䅕䅌杁䑁䅕䅉婂䡁䅉杌杁䕁䅍兑䡂䙁䅉䅉潁䍁䅕克䅁䩁䍑䅁慂䅁䅁睔睂䝁䅕杣桂䡁䅑兡畂䝁䅣䅉䵂䝁䅕兙穂䝁䅕䅉䑂䝁䄸兢瑂䝁䅫䅤瑂䝁䅕杢あ䍁䅁䅒ㅂ䝁䅕䅉牁䑁䅅䅉潁䙁䅉党睂䝁䄸杣あ䝁䅕䅚灁䅁䅁䅵䅅䙁䅯䅁偂䡁䅁党祂䝁䅅䅤灂䝁䄴睚杁䕁䅷党桂䡁䅍党杁䕁䅍睢瑂䝁䄰兡あ䝁䄰党畂䡁䅑䅉䕂䡁䅕党杁䍁䅳杍杁䍁䅧杕求䡁䅁睢祂䡁䅑党歂䍁䅫䅁㙃允䅁䅢䅁䕁䄸䅣求䡁䅉兙あ䝁䅫杢湂䍁䅁䅔求䝁䅅督求䍁䅁睑療䝁䄰兢灂䡁䅑兢求䝁䄴䅤杁䕁䅑兤求䍁䅷䅉佂䝁䅕䅥あ䍁䅁兎杁䙁䅫杣穂䍁䅁䅋卂䝁䅕䅣療䡁䅉䅤求䝁䅑克䅁䵁䉉䅁千䅁䅁睊扂䕁䅍睢睂䡁䅫䅉療䝁䅙䅉呂䙁䅁睒時䕁䅍睢瑂䡁䅁兙畂䡁䅫睘䱂䝁䅕入呂䡁䅑兙あ䡁䅍睘㉂䑁䅅睘䝂䝁䅫杢桂䝁䅷杌㑂䝁䅷督瑂䙁䄰村桂䝁䅷兙畂䝁䅍党時䙁䅍䅡求䝁䅕䅤湁䍁䅅䅊䑂䍁䅑免硁䑁䅯䅊䑂䍁䅑杍睁䑁䅑䅁摂䅃䅁杤䅁䕁䄸䅣あ䝁䅫睢畂䡁䅍䅉䙂䡁䅧党祂䝁䅍兡穂䝁䅕䅚杁䕁䅑兤祂䝁䅫杢湂䍁䅁䅤潂䝁䅕䅉兂䝁䅕杣灂䝁䄸䅚獁䍁䅁睑療䝁䄰兢療䝁䄴䅉呂䡁䅑睢橂䝁䅳䅉潁䝁䅅睙あ䡁䅕兙獂䍁䅫䅁㍁睁䅁杚䅁䙁䅳睕兂䕁䅣睘䑂䝁䄸兢睂䝁䅅杢㕂䙁䄸睓求䡁䅫睕あ䝁䅅䅤穂䙁䄸杤硁䍁䄴䅥獂䡁䅍兢摂䕁䅍兙睂䝁䅫䅤桂䝁䅷兡㙂䝁䅅䅤灂䝁䄸杢桁䍁䅑睑歁䑁䅕䅍䅁偁䙯䅁潂䅁䅁睔睂䡁䅑兡療䝁䄴督杁䕁䅕䅥求䡁䅉睙灂䡁䅍党歂䍁䅁䅒ㅂ䡁䅉兡畂䝁䅣䅉あ䝁䅧党杁䙁䅁党祂䝁䅫睢歂䍁䅷䅉啂䝁䄸䅤桂䝁䅷䅉潁䝁䅅睙あ䡁䅕兙獂䍁䅫䅁䑂睁䅁杣䅁䕁䄸䅣あ䝁䅫睢畂䡁䅍䅉䡂䡁䅉兙畂䡁䅑党歂䍁䅁䅒ㅂ䡁䅉兡畂䝁䅣䅉あ䝁䅧党杁䙁䅁党祂䝁䅫睢歂䍁䅷䅉䑂䝁䄸兢瑂䝁䄸杢杁䙁䅍䅤療䝁䅍睡杁䍁䅧兙橂䡁䅑兤桂䝁䅷克䅁䑁䑕䅁獂䅁䅁睔睂䡁䅑兡療䝁䄴督杁䕁䄸兤あ䍁䄴䅉桂䡁䅑䅉あ䝁䅧党杁䕁䅕杢歂䍁䅁睢浂䍁䅁䅤潂䝁䅕䅉兂䝁䅕杣灂䝁䄸䅚獁䍁䅁䅖療䡁䅑兙獂䍁䅁䅋桂䝁䅍䅤ㅂ䝁䅅䅢灁䅁䅁兓䅍䉁䄴䅁呂䙁䅁睘䙂䕁䄴䅖䩂䙁䅑兗時䕁䄴兑乂䕁䅕䅁橁䅁䅁䅥䅁䙁䅳兔䩂䙁䄸睓求䡁䅫睕あ䝁䅅䅤穂䙁䄸杤硁䍁䄴䅥獂䡁䅍兢摂䕁䅍兙睂䝁䅫䅤桂䝁䅷睘呂䡁䅑杣ㅂ䝁䅍䅤ㅂ䡁䅉党時䙁䅍兤瑂䝁䄰兙祂䡁䅫光歁䕁䅍䅊硁䑁䅍杏歁䕁䅍䅊硁䑁䅑睎䅁䱁䑯䅁㡂䅁䅁睔睂䡁䅑兡療䝁䄴督杁䙁䅣䅤歂䍁䅁兑㉂䝁䅣䅉呂䡁䅑杣灂䝁䅳党杁䙁䅁杣灂䝁䅍党杁䝁䄸杚杁䕁䄸兤あ䡁䅍䅤歂䍁䅷䅉䑂䝁䄸兢瑂䍁䅁睕あ䝁䄸睙牂䍁䅁䅋卂䝁䅕䅣療䡁䅉䅤求䝁䅑克䅁䑁䐰䅁坂䅁䅁睗呂䙁䅁睒時䕁䅍睢瑂䡁䅁兙畂䡁䅫睘䱂䝁䅕入呂䡁䅑兙あ䡁䅍睘㉂䑁䅉杌㑂䝁䅷督瑂䙁䄰睕潂䝁䅕党あ䑁䅅光歁䕁䅙䅊ぁ䑁䅍䅁牃杂䅁䅬䅁䕁䄸䅣あ䝁䅫睢畂䡁䅍杏杁䕁䅍兤祂䡁䅉児䡂䕁䅉䅕獁䍁䅁兔桂䝁䅣児䍂䝁䅫䅢獂䝁䅫睢畂䡁䅍䅌䑂䝁䄸杢㉂䕁䄰党あ䝁䅧睢歂䑁䄰兔䩂䡁䅉党橂䝁䄸兢瑂䝁䅕杢歂䝁䅕䅚獁䍁䅁杔䉂䑁䄰䅌杁䙁䅑党祂䝁䄰児求䝁䄴兌噂䙁䅍䅁㙁䅁䅁杚䅁䙁䅳兔䩂䙁䄸睑療䝁䄰䅣桂䝁䄴入時䕁䅳党㕂䙁䅍䅤桂䡁䅑督時䡁䅙免畁䡁䅧䅢穂䝁䄰兘䱂䝁䅕入時䙁䅍䅤桂䡁䅑督桁䍁䅑睕歁䑁䅕䅏㙁䍁䅑睕歁䑁䅙杍䅁䩁䘰䅁䍂䅁䅁睕求䝁䅍兤祂䝁䅫䅤灂䡁䅯党歂䍁䅁䅒求䝁䅉䅤癁䍁䅁䅖療䡁䅑兙獂䍁䅁䅒求䝁䅉䅤杁䍁䅧兊灁䅁䅁党䅅䩁䅙䅁偂䡁䅁䅤灂䝁䄸杢穂䑁䅯䅉䑂䡁䅕杣祂䑁䄰睒䍂䙁䅁䅌杁䕁䄰兙湂䑁䄰䅖潂䝁䄸兤穂䝁䅅杢歂䡁䅍䅌䑂䝁䄸杢㉂䕁䄰党あ䝁䅧睢歂䑁䄰兔䩂䡁䅉党橂䝁䄸兢瑂䝁䅕杢歂䝁䅕䅚獁䍁䅁杔䉂䑁䄰䅌杁䙁䅑党祂䝁䄰児求䝁䄴兌噂䙁䅍䅁㝁䅁䅁杬䅁䕁䄸䅣あ䝁䅫睢畂䡁䅍杏杁䕁䅍兤祂䡁䅉児䭂䙁䅁兗獁䍁䅁兔桂䝁䅣児䉂䝁䅍䅤ㅂ䝁䅅䅢穂䍁䅷睑療䝁䄴杤乂䝁䅕䅤潂䝁䄸䅚㥁䕁䄰兓祂䝁䅕睙療䝁䄰兢求䝁䄴䅚求䝁䅑䅌杁䕁䄴兑㥁䕁䄴兑獁䍁䅁䅖求䡁䅉兢㥁䝁䅕杢瑁䙁䅕睕䅁䱁䕫䅁坃䅁䅁睔睂䡁䅑兡療䝁䄴督㙁䍁䅁睑ㅂ䡁䅉杣㥁䙁䅕睕䕂䍁䅷䅉乂䝁䅅睚㥁䕁䅅睙あ䡁䅕兙獂䡁䅍䅌䑂䝁䄸杢㉂䕁䄰党あ䝁䅧睢歂䑁䄰兔䩂䡁䅉党橂䝁䄸兢瑂䝁䅕杢歂䝁䅕䅚獁䍁䅁杔䉂䑁䄰杔䉂䍁䅷䅉啂䝁䅕杣瑂䑁䄰党畂䍁䄰兖呂䅁䅁睴䅑䙁䅉䅁扂䕁䅳党㕂䙁䅍䅤桂䡁䅑督時䡁䅑党穂䡁䅑杚灂䝁䅷党畁䡁䅧䅢穂䡁䅧兘呂䝁䅧党求䡁䅑杍桁䍁䅑䅒歁䑁䅧杏歁䕁䅑䅊㕁䅁䅁杊䅁䝁䅑䅁扂䕁䄰兓時䕁䅳党㕂䙁䅍䅤桂䡁䅑督時䡁䅙免畁䡁䅧䅢穂䝁䄰兘䩂䝁䄴睙療䝁䄰党時䙁䅍䅤桂䡁䅑党瑂䝁䅕杢あ䍁䅅䅊䑂䍁䅑兏㙁䍁䅑睑歁䑁䅅睎穁䅁䅁䅶䅍䙁䅁䅁扂䕁䅳党㕂䙁䅍䅤桂䡁䅑督時䡁䅑党穂䡁䅑杚灂䝁䅷党畁䡁䅧䅢穂䝁䄰兘䱂䝁䅕入時䙁䅍䅤桂䡁䅑督桁䍁䅑村歁䑁䅉杍䅁䩁䅕䅁啃䅁䅁睔睂䡁䅑兡療䝁䄴督㙁䍁䅁睑ㅂ䡁䅉杣㥁䙁䅕睕䕂䍁䅷䅉乂䝁䅅睚㥁䕁䄰兡獂䝁䅷兡療䝁䄴督獁䕁䅍睢畂䡁䅙兔求䡁䅑䅡療䝁䅑児乂䕁䅫杣求䝁䅍睢瑂䝁䄰党畂䝁䅑党歂䍁䅷䅉佂䕁䅅児獁䍁䅁䅖求䡁䅉兢㥁䝁䅕杢瑁䙁䅕睕䅁䕁䅙䅁啄䅁䅁睔睂䡁䅑兡療䝁䄴督㙁䍁䅁睑ㅂ䡁䅉杣㥁䙁䅕睕䕂䍁䅷䅉乂䝁䅅睚㥁䕁䄰兡獂䝁䅷兡療䝁䄴督獁䕁䅍睢畂䡁䅙兔求䡁䅑䅡療䝁䅑児乂䕁䅫杣求䝁䅍睢瑂䝁䄰党畂䝁䅑党歂䍁䅷䅉佂䕁䅅児佂䕁䅅䅌杁䙁䅑党祂䝁䄰児求䝁䄴兌噂䙁䅍䅌䝂䝁䅫䅢灂䝁䄴睚坂䝁䅕杣㥁䕁䄸杣灂䝁䅣兡畂䝁䅅䅢獂䡁䅫䅉卂䝁䅕䅣療䡁䅉䅤求䝁䅑䅁啃兂䅁杏䅁䕁䄸䅣あ䝁䅫睢畂䡁䅍杏杁䙁䅍䅤桂䡁䅑兡穂䡁䅑兡橂䑁䄰兑坂䕁䅣䅌佂䕁䅅児佂䕁䅅䅁塂杂䅁䅘䅁䙁䅳睓求䡁䅫睕あ䝁䅅䅤穂䙁䄸䅤求䡁䅍䅤浂䝁䅫䅢求䍁䄴䅥獂䡁䅍兢摂䕁䅳党㕂䙁䄸睕あ䝁䅅䅤穂䍁䅅䅊䕂䍁䅑兎ぁ䑁䅯䅊䕂䍁䅑兎ㅁ䅁䅁儲䅁䍁䄴䅁偂䡁䅁䅤灂䝁䄸杢穂䑁䅯䅉呂䡁䅑兙あ䝁䅫督あ䝁䅫睙㥁䕁䅷睔塂䅁䅁睗䅙䙁䄴䅁呂䝁䅕杢灂䝁䄸杣杁䙁䅍党橂䡁䅕杣求䝁䅑䅉䍂䝁䄸杢歂䡁䅍䅉桂䝁䄴䅚杁䕁䄴睢あ䝁䅕督癁䍁䅁䅖療䡁䅑兙獂䍁䅁䅒求䝁䅉䅤杁䍁䅧兊灁䅁䅁睘䅅䑁䅯䅁偂䡁䅁䅤灂䝁䄸杢穂䑁䅯䅉呂䡁䅑兙あ䝁䅫督あ䝁䅫睙㥁䕁䄰兒䕂䍁䅷杔䉂䑁䄰杔䉂䅁䅁杕䅙䭁䅧䅁偂䡁䅁䅤灂䝁䄸杢穂䑁䅯睑ㅂ䡁䅉杣㥁䙁䅕睕䕂䍁䅷兔桂䝁䅣児乂䕁䅫督あ䝁䅅杢歂䝁䅅杣歂䍁䅷睑療䝁䄴杤乂䝁䅕䅤潂䝁䄸䅚㥁䕁䄰兓祂䝁䅕睙療䝁䄰兢求䝁䄴䅚求䝁䅑䅌䝂䝁䅫䅢灂䝁䄴睚坂䝁䅕杣㥁䕁䅍兤祂䡁䅉党畂䡁䅑睌卂䝁䅕督あ䝁䅅䅤求䝁䅑䅁坃兂䅁杲䅁䕁䄸䅣あ䝁䅫睢畂䡁䅍杏䑂䡁䅕杣祂䑁䄰兖呂䕁䅑䅌乂䝁䅅睚㥁䕁䄰兓穂䡁䅑兙畂䝁䅑兙祂䝁䅑䅌䑂䝁䄸杢㉂䕁䄰党あ䝁䅧睢歂䑁䄰兔䩂䡁䅉党橂䝁䄸兢瑂䝁䅕杢歂䝁䅕䅚獁䙁䅁兙歂䑁䄰睔浂䝁䅙䅌䕂䝁䅅䅤求䡁䅍児䍂䝁䅕杚療䡁䅉党獁䙁䅍睢祂䡁䅑児䉂䡁䅍睙䅁䩁䙯䅁畂䅁䅁睔睂䡁䅑兡療䝁䄴督㙁䕁䅍兤祂䡁䅉児噂䙁䅍䅒獁䕁䄰兙湂䑁䄰兔灂䝁䅷䅢灂䝁䄸杢穂䍁䅷睑療䝁䄴杤㥁䕁䄰兓祂䝁䅕睙療䝁䄰兢求䝁䄴䅚求䝁䅑䅌佂䕁䅅児佂䕁䅅䅁佃杂䅁䅈䅁䕁䄸䅣あ䝁䅫睢畂䡁䅍杏佂䕁䅅児佂䕁䅅䅁婂杂䅁䅙䅁䙁䅳兔䩂䙁䄸睓求䡁䅫睕あ䝁䅅䅤穂䙁䄸杤硁䍁䄴䅥獂䡁䅍兢摂䕁䅍兙睂䝁䅫䅤桂䝁䅷兡㙂䝁䅅䅤灂䝁䄸杢桁䍁䅑睑歁䑁䅕睍㙁䍁䅑睑歁䑁䅕䅎䅁䭁䑣䅁䝂䅁䅁睔あ䝁䅧党祂䍁䅁睔睂䝁䅕杣桂䡁䅑兡畂䝁䅣䅉䙂䡁䅧䅣求䝁䄴督求䍁䅁䅋卂䝁䅕䅣療䡁䅉䅤求䝁䅑克䅁䱁䅣䅁䭂䅁䅁睗䱂䝁䅕入呂䡁䅑兙あ䡁䅍睘あ䝁䅕督あ䝁䅙兡獂䝁䅕杌㑂䝁䅷督㑂䙁䄰睕潂䝁䅕党あ䑁䅅光歁䕁䅕䅊祁䑁䅅䅁睁䅁䅁杏䅁䙁䅁杣求䍁䄰睔睂䝁䅕杢灂䝁䄴睚杁䕁䅍睢穂䡁䅑督杁䍁䅧杕求䡁䅁睢祂䡁䅑党歂䍁䅫䅁癃䅁䅁杤䅁䙁䅉党歂䡁䅕睙あ䝁䅫睢畂䡁䅍䅉䍂䝁䅅督求䝁䅑䅉療䝁䄴䅉啂䝁䅅䅥杁䙁䅁睢穂䝁䅫䅤灂䝁䄸杢穂䍁䅁兌杁䕁䅍兤祂䡁䅉党畂䡁䅑䅉婂䡁䅉杌杁䍁䅧杕求䡁䅁睢祂䡁䅑党歂䍁䅫䅁䩁睁䅁杋䅁䙁䅉党あ䡁䅕杣畂䍁䅁睢畂䍁䅁兑穂䡁䅍党あ䡁䅍䅉潁䍁䅕克䅁偁䉧䅁潁䅁䅁兓剂䙁䄸杒䩂䕁䄴䅔時䕁䅙兓䵂䕁䅫杔䡂䙁䄸䅒䉂䙁䅑兒䅁䱁䡧䅁獁䅁䅁杕求䡁䅑兤祂䝁䄴䅉療䝁䄴䅉䑂䝁䅅䅣灂䡁䅑兙獂䍁䅁䅋汁䍁䅫䅁㡄允䅁杣䅁䙁䅳兔䩂䙁䄸睑療䝁䄰䅣桂䝁䄴入時䕁䅳党㕂䙁䅍䅤桂䡁䅑督時䡁䅙免畁䡁䅧䅢穂䝁䄰兘䍂䝁䅅䅢桂䝁䄴睙求䙁䄸睕潂䝁䅕党あ䍁䅅䅊䙂䍁䅑免ぁ䑁䅍杏歁䙁䅁䅊硁䑁䅑睍䅁䭁䕙䅁㑁䅁䅁杕求䡁䅑兤祂䝁䄴䅉療䝁䄴䅉䑂䝁䄸兢瑂䝁䄸杢杁䕁䅕兣ㅂ䝁䅫䅤㕂䍁䅁䅋汁䍁䅫䅁⭄允䅁杚䅁䙁䅳睓求䡁䅫睕あ䝁䅅䅤穂䙁䄸䅤求䡁䅍䅤浂䝁䅫䅢求䍁䄴䅥獂䡁䅍兢摂䕁䅍兙睂䝁䅫䅤桂䝁䅷兡㙂䝁䅅䅤灂䝁䄸杢桁䍁䅑杒歁䑁䅍杍㙁䍁䅑睓歁䑁䅍杍䅁乁䅉䅁杁䅁䅁睕䡂䍁䅙兑杁䕁䄰兙祂䝁䅣兡畂䍁䅁䅋汁䍁䅫䅁䕁杁䅁䅃䅁䙁䅍杔䵂䅁䅁睭䅕䉁䅉䅁呂䕁䄴䅔剂䡁䅕党祂䡁䅫䅁慄睁䅁杅䅁䙁䅍杔䵂䙁䅑兙楂䝁䅷党䅁䍁䅫䅁捃䅁䅁睊扂䕁䅍睢睂䡁䅫䅉療䝁䅙䅉呂䙁䅁睒時䕁䅍睢瑂䡁䅁兙畂䡁䅫睘䱂䝁䅕入呂䡁䅑兙あ䡁䅍睘㉂䑁䅉睘畂䝁䅕睤畁䡁䅧䅢穂䝁䄰兘䑂䝁䅅䅣灂䡁䅑兙獂䙁䄸睕あ䡁䅉兤橂䡁䅑兤祂䝁䅕睘杁䕁䅑党あ䝁䅅兡獂䡁䅍䅉湁䍁䅅䅊䑂䍁䅑免祁䅁䅁杢䅣䉁䅯䅁呂䙁䅁睘乂䕁䅅杕䱂䕁䅕䅖䑂䕁䅅䅕䅁䭁䙯䅁坁䅁䅁睕兂䙁䄸杔䙂䙁䅑睘䩂䕁䄴睑䅁䅁䄴䅁坁䅁䅁睕兂䙁䄸䅕䍂䙁䅙睘䝂䙁䅣䅒䅁䝁䝯䅁慁䅁䅁睕兂䙁䄸䅕䑂䕁䅙䅕呂䙁䄸杒塂䕁䅑䅁楂杂䅁杒䅁䙁䅑睢あ䝁䅅䅢杁䙁䅍党橂䡁䅕杣求䝁䅑䅉䕂䝁䅕杙あ䍁䄸䅉啂䝁䄸䅤桂䝁䅷䅉䕂䝁䅕杙あ䍁䅁䅋汁䍁䅫䅁摂允䅁䅈䅁䙁䅍䅕時䙁䅁兒卂䕁䅫睔䕂䙁䄸兒佂䕁䅑䅁剂䅁䅁杆䅁䙁䅍䅕時䙁䅉兒坂䙁䄸兒呂䙁䅑䅁㡁䅁䅁䅫䅁䍁䅣睗䑂䝁䄸䅣㕂䍁䅁睢浂䍁䅁睕兂䕁䅣睘䑂䝁䄸兢睂䝁䅅杢㕂䙁䄸睓求䡁䅫睕あ䝁䅅䅤穂䙁䄸杤硁䙁䄸杒灂䝁䄴兙獂䍁䄴䅥獂䡁䅍兢摂䙁䅁党畂䡁䅍兡療䝁䄴兌偂䙁䅁兒䍂䍁䅣光歁䕁䅍䅊硁䑁䅅杏歁䕁䅍䅊ㅁ䑁䅣兎䅁䩁䥫䅁歁䅁䅁睕兂䙁䄸䅖䙂䙁䅙睘䙂䕁䅉兓啂䕁䅑兑時䕁䅙睖䕂䅁䅁睘䅙䕁䄴䅁呂䝁䅕睙療䝁䄴䅚杁䕁䅷兡求䝁䄴䅉䍂䝁䄸杢歂䡁䅍䅉桂䝁䄴䅚杁䕁䄴睢あ䝁䅕督杁䍁䅧杕求䡁䅁睢祂䡁䅑党歂䍁䅫䅁䙂允䅁䅗䅁䙁䅍党橂䝁䄸杢歂䍁䅁䅔灂䝁䅕杢杁䕁䅉睢畂䝁䅑督杁䝁䅅杢歂䍁䅁杔療䡁䅑党穂䍁䄸䅉啂䝁䄸䅤桂䝁䅷䅉䕂䝁䅕杙あ䍁䅁䅋汁䍁䅫䅁硂允䅁材䅁䙁䅑睢あ䝁䅅䅢杁䙁䅉党㉂䝁䅕杢ㅂ䝁䅕督獁䍁䅁兎杁䙁䅫杣畁䍁䅁睑䉂䕁䅣杕杁䍁䅧兊灁䅁䅁䅳䅉䭁䅁䅁湁䙁䅳睑療䡁䅁入杁䝁䄸杚杁䙁䅍䅕䡂䙁䄸睑療䝁䄰䅣桂䝁䄴入時䕁䅳党㕂䙁䅍䅤桂䡁䅑督時䡁䅙免時䕁䅙兡畂䝁䅅䅢畁䡁䅧䅢穂䝁䄰兘䑂䝁䅅䅣灂䡁䅑兙獂䙁䄸睕あ䡁䅉兤橂䡁䅑兤祂䝁䅕睘杁䕁䅑党あ䝁䅅兡獂䡁䅍䅉湁䍁䅅䅊䑂䍁䅑䅎ぁ䅁䅁兩䅧䕁䅉䅁呂䝁䅕睙療䝁䄴䅚杁䕁䅷兡求䝁䄴䅉䕂䝁䅕杙あ䍁䄸䅉啂䝁䄸䅤桂䝁䅷䅉䕂䝁䅕杙あ䍁䅁䅋汁䍁䅫䅁穂允䅁杏䅁䙁䅍党橂䝁䄸杢歂䍁䅁䅔灂䝁䅕杢杁䕁䅷睢桂䝁䄴督杁䍁䅧杕求䡁䅁睢祂䡁䅑党歂䍁䅫䅁䑂允䅁权䅁䕁䅙兕瑁䑁䅕䅁㕃睂䅁䅒䅁䙁䅍党橂䝁䄸杢歂䍁䅁䅔灂䝁䅕杢杁䕁䅷睢桂䝁䄴督癁䍁䅁䅖療䡁䅑兙獂䍁䅁䅒求䝁䅉䅤杁䍁䅧兊灁䅁䅁睚䅅䑁䅁䅁呂䝁䅕睙ㅂ䡁䅉党歂䍁䅁䅒求䝁䅉䅤杁䍁䅧杕求䡁䅁睢祂䡁䅑党歂䍁䅫䅁㕁允䅁杒䅁䙁䅍党畂䝁䅫睢祂䍁䅁䅒求䝁䅉䅤杁䍁䄸䅉潁䕁䅕村䩂䙁䅑䅒䉂䍁䅁兌杁䕁䅍兙睂䝁䅕䅥灁䍁䅁䅋㑂䍁䅫䅁䅃允䅁杍䅁䙁䅍党畂䝁䅫睢祂䍁䅁䅒求䝁䅉䅤杁䍁䄸䅉䙂䕁䅉兓啂䕁䅑兑杁䍁䅧䅥灁䅁䅁䅪䅅䝁䅯䅁扂䕁䄰兓時䙁䅉兒䩂䙁䅑睘呂䝁䅅兢求䙁䅍䅤療䡁䅉党啂䝁䅕兢睂䝁䅷兙あ䝁䅕睘㉂䑁䅅杌㑂䝁䅷督摂䕁䅑兙あ䝁䅅光歁䕁䅑杓歁䑁䅅䅍㙁䍁䅑杒卂䍁䅑免睁䅁䅁朱䅍䙁䅑䅁呂䝁䅕杢灂䝁䄸杣杁䙁䅍党橂䡁䅕杣求䝁䅑䅉䍂䝁䄸杢歂䡁䅍䅉桂䝁䄴䅚杁䕁䄴睢あ䝁䅕督杁䍁䅧杕求䡁䅁睢祂䡁䅑党歂䍁䅫䅁㥁允䅁䅑䅁䙁䅍党畂䝁䅫睢祂䍁䅁睕求䝁䅍兤祂䝁䅕䅚杁䕁䅷睢桂䝁䄴督杁䍁䅧杕求䡁䅁睢祂䡁䅑党歂䍁䅫䅁㝁允䅁杏䅁䙁䅑睢あ䝁䅅䅢杁䙁䅍兤楂䍁䄴䅉䕂䝁䅕杙あ䍁䅁睌杁䕁䅕村䩂䙁䅑䅒䉂䍁䅁䅋㑂䍁䅫䅁佃允䅁杓䅁䙁䅍党畂䝁䅫睢祂䍁䅁睕求䝁䅍兤祂䝁䅕䅚杁䕁䅷睢桂䝁䄴督癁䍁䅁䅖療䡁䅑兙獂䍁䅁䅒求䝁䅉䅤杁䍁䅧兊灁䅁䅁睖䅅䙁䅧䅁呂䝁䅕杢灂䝁䄸杣杁䙁䅕杢穂䝁䅕睙ㅂ䡁䅉党歂䍁䅁村療䝁䄴䅚穂䍁䅁兙畂䝁䅑䅉佂䝁䄸䅤求䡁䅍䅉潁䙁䅉党睂䝁䄸杣あ䝁䅕䅚灁䅁䅁睐䅅䝁䅉䅁呂䝁䅕杢灂䝁䄸杣杁䙁䅕杢穂䝁䅕睙ㅂ䡁䅉党歂䍁䅁村療䝁䄴䅚穂䍁䅁兙畂䝁䅑䅉佂䝁䄸䅤求䡁䅍睌杁䙁䅑睢あ䝁䅅䅢杁䕁䅑党楂䡁䅑䅉潁䍁䅕克䅁䝁䉅䅁啁䅁䅁睕求䝁䄴兡療䡁䅉兡あ䡁䅫䅁捃杂䅁杖䅁䙁䅳睕兂䕁䅣睘䑂䝁䄸兢睂䝁䅅杢㕂䙁䄸睓求䡁䅫睕あ䝁䅅䅤穂䙁䄸杤祁䍁䄴䅥獂䡁䅍兢摂䙁䅍䅡求䝁䅕䅤硁䍁䅅䅊䕂䍁䅑䅎穁䅁䅁東䅙䙁䅧䅁呂䝁䅕䅤あ䝁䅷党瑂䝁䅕杢あ䡁䅍䅉㍂䝁䅫䅤潂䍁䅁䅖桂䡁䅧䅉䉂䡁䅕䅤潂䝁䄸杣灂䡁䅑兡求䡁䅍䅉潁䙁䅉党睂䝁䄸杣あ䝁䅕䅚灁䅁䅁兄䅍䙁䅙䅁呂䝁䅧兙祂䝁䅕䅡療䝁䅷䅚求䡁䅉督杁䕁䅕兣ㅂ䝁䅫䅤㕂䍁䅁兌杁䙁䅕杌呂䍁䄴䅉䡂䕁䅅兑兂䍁䅁䅋卂䝁䅕䅣療䡁䅉䅤求䝁䅑克䅁䵁䍣䅁坂䅁䅁睗呂䙁䅁睒時䕁䅍睢瑂䡁䅁兙畂䡁䅫睘䱂䝁䅕入呂䡁䅑兙あ䡁䅍睘㉂䑁䅉杌㑂䝁䅷督瑂䙁䄰睕潂䝁䅕党あ䑁䅅光歁䕁䅕䅊ぁ䑁䅍䅁潃杂䅁䅡䅁䙁䅳兔䩂䙁䄸睑療䝁䄰䅣桂䝁䄴入時䕁䅳党㕂䙁䅍䅤桂䡁䅑督時䡁䅙免畁䡁䅧䅢穂䝁䄰兘呂䡁䅕䅣睂䝁䅷党瑂䝁䅕杢あ䝁䅅䅢桁䍁䅑䅒歁䑁䅑杏歁䕁䅫䅊ぁ䅁䅁克䅑䑁䅧䅁呂䝁䅧兙祂䝁䅕督杁䕁䄸兤あ䡁䅍䅤桂䝁䄴䅚灂䝁䄴睚杁䍁䅧兙橂䡁䅑兤桂䝁䅷克䅁䉁䅣䅁㉂䅁䅁睊扂䕁䅍睢睂䡁䅫䅉療䝁䅙䅉呂䙁䅁睒時䕁䅍睢瑂䡁䅁兙畂䡁䅫睘䱂䝁䅕入呂䡁䅑兙あ䡁䅍睘㉂䑁䅉睘畂䝁䅕睤畁䡁䅧䅢穂䝁䄰兘䑂䝁䅅督潂䙁䄸杒獂䝁䄸睤湁䍁䅅䅊䑂䍁䅑李䅁䕁䡙䅁㡁䅁䅁睕祂䍁䄴䅉呂䡁䅕杙畁䍁䅁䅒求䝁䅉䅤癁䍁䅁䅖療䡁䅑兙獂䍁䅁䅒求䝁䅉䅤杁䍁䅧兊灁䅁䅁睊䅅䕁䅧䅁呂䡁䅑睢橂䝁䅳兌䍂䝁䅅督求䝁䅑䅉䑂䝁䄸兢睂䝁䅕杢穂䝁䅅䅤灂䝁䄸杢杁䍁䅧杕求䡁䅁睢祂䡁䅑党歂䍁䅫䅁瑃䅁䅁材䅁䙁䅍兤楂䍁䄰䅔求䝁䅅督求䍁䅁兓畂䝁䅍睢瑂䝁䅕䅉牁䑁䅅䅉潁䙁䅉党睂䝁䄸杣あ䝁䅕䅚灁䅁䅁杸䅅䑁䄴䅁呂䡁䅕杙瑁䕁䅷党桂䡁䅍党杁䕁䅫杢橂䝁䄸兢求䍁䅁睋祁䍁䅁䅋卂䝁䅕䅣療䡁䅉䅤求䝁䅑克䅁䵁䉧䅁⭁䅁䅁睕ㅂ䝁䅉兌䵂䝁䅕兙穂䝁䅕䅉䩂䝁䄴睙療䝁䄰党杁䍁䅳睍杁䍁䅧杕求䡁䅁睢祂䡁䅑党歂䍁䅫䅁䭄允䅁材䅁䙁䅍兤楂䍁䄰䅔求䝁䅅督求䍁䅁兓畂䝁䅍睢瑂䝁䅕䅉牁䑁䅑䅉潁䙁䅉党睂䝁䄸杣あ䝁䅕䅚灁䅁䅁䅺䅅䙁䅁䅁呂䡁䅕杙瑁䕁䅷党桂䡁䅍党杁䕁䅫杢橂䝁䄸兢求䍁䅷䅉佂䝁䅕䅥あ䍁䅁兎杁䙁䅫杣穂䍁䅁䅋卂䝁䅕䅣療䡁䅉䅤求䝁䅑克䅁乁䉁䅁煁䅁䅁睕ㅂ䝁䅉杌杁䕁䅑党楂䡁䅑䅉潁䙁䅉党睂䝁䄸杣あ䝁䅕䅚灁䅁䅁睆䅅䍁䄴䅁呂䡁䅕杙畁䍁䅁䅒求䝁䅉䅤杁䍁䄸䅉䙂䕁䅉兓啂䕁䅑兑杁䍁䅧䅥灁䅁䅁杬䅅䕁䅷䅁啂䝁䅅杢湂䝁䅫杙獂䝁䅕䅉䍂䝁䄸睢牂䍁䅁杖桂䝁䅷兤求䍁䅷䅉硁䍁䅁兗祂䍁䄴䅉䡂䡁䅉睢㍂䡁䅑䅡杁䍁䅧兊灁䅁䅁杌䅉䕁䅧䅁啂䝁䅅杢湂䝁䅫杙獂䝁䅕䅉䍂䝁䄸睢牂䍁䅁杖桂䝁䅷兤求䍁䅷䅉祁䍁䅁兗祂䍁䄴䅉䑂䕁䅅睒卂䍁䅁䅋汁䍁䅫䅁奂杁䅁䅢䅁䙁䅑兙㑂䍁䅁村求䝁䄴党浂䝁䅫䅤杁䕁䅍兙祂䡁䅉入浂䝁䄸杣㍂䝁䅅杣歂䍁䅷䅉䉂䝁䅙䅤求䡁䅉䅉䝂䝁䅫杤求䍁䅁兗求䝁䅅杣穂䍁䅁䅋卂䝁䅕䅣療䡁䅉䅤求䝁䅑克䅁偁䌸䅁歂䅁䅁䅖桂䡁䅧䅉䍂䝁䅕杢求䝁䅙兡あ䍁䅁睑桂䡁䅉杣㕂䝁䅙睢祂䡁䅣兙祂䝁䅑䅌杁䕁䅍兤祂䡁䅉党畂䡁䅑䅉婂䝁䅕兙祂䍁䅁䅋卂䝁䅕䅣療䡁䅉䅤求䝁䅑克䅁䵁䍳䅁獂䅁䅁䅖桂䡁䅧䅉䍂䝁䅕杢求䝁䅙兡あ䍁䅁睑桂䡁䅉杣㕂䝁䅙睢祂䡁䅣兙祂䝁䅑䅌杁䕁䅍兤祂䡁䅉党畂䡁䅑䅉婂䝁䅕兙祂䍁䅁睋杁䑁䅉䅉潁䙁䅉党睂䝁䄸杣あ䝁䅕䅚灁䅁䅁儫䅉䝁䅷䅁啂䝁䅅䅥杁䕁䅉党畂䝁䅕杚灂䡁䅑䅉䑂䝁䅅杣祂䡁䅫杚療䡁䅉睤桂䡁䅉䅚獁䍁䅁睑ㅂ䡁䅉杣求䝁䄴䅤杁䙁䅫党桂䡁䅉䅉牁䍁䅁睍杁䍁䅧杕求䡁䅁睢祂䡁䅑党歂䍁䅫䅁㝄杁䅁䅨䅁䍁䅣睗䑂䝁䄸䅣㕂䍁䅁睢浂䍁䅁睕兂䕁䅣睘䑂䝁䄸兢睂䝁䅅杢㕂䙁䄸睓求䡁䅫睕あ䝁䅅䅤穂䙁䄸杤祁䙁䄸杢求䡁䅣杌㑂䝁䅷督瑂䙁䄰睓求䡁䅫睘呂䡁䅑兙あ䡁䅍睊桁䍁䅑兒歁䑁䅉李㙁䍁䅑杓歁䑁䅉李䅁䍁䡫䅁䵃䅁䅁睊扂䕁䅍睢睂䡁䅫䅉療䝁䅙䅉呂䙁䅁睒時䕁䅍睢瑂䡁䅁兙畂䡁䅫睘䱂䝁䅕入呂䡁䅑兙あ䡁䅍睘㉂䑁䅅睘䝂䝁䅫杢桂䝁䅷杌㑂䝁䅷督瑂䙁䄰睓求䡁䅫睘呂䡁䅑兙あ䡁䅍睊桁䍁䅑兒歁䑁䅅䅍㉁䑁䅯䅊䝂䍁䅑免睁䑁䅙䅁摃䅃䅁䅢䅁䙁䅑兙㑂䍁䅁村求䝁䄴党浂䝁䅫䅤杁䕁䅍兙祂䡁䅉入浂䝁䄸杣㍂䝁䅅杣歂䍁䅷䅉䑂䡁䅕杣祂䝁䅕杢あ䍁䅁兗求䝁䅅杣杁䍁䅳䅉ぁ䍁䅁䅋卂䝁䅕䅣療䡁䅉䅤求䝁䅑克䅁偁䌰䅁浂䅁䅁䅖桂䡁䅧䅉䍂䝁䅕杢求䝁䅙兡あ䍁䅁睑桂䡁䅉杣㕂䝁䅙睢祂䡁䅣兙祂䝁䅑䅌杁䕁䄴睢杁䕁䅕䅥睂䝁䅫杣桂䡁䅑兡療䝁䄴䅉潁䙁䅉党睂䝁䄸杣あ䝁䅕䅚灁䅁䅁睶䅉䕁䅁䅁啂䝁䄸䅤桂䝁䅷䅉䉂䡁䅍督求䡁䅑督獁䍁䅁免杁䙁䅫党桂䡁䅉䅉䡂䡁䅉睢㍂䡁䅑䅡杁䍁䅧兊灁䅁䅁䅌䅉䑁䅯䅁啂䝁䄸䅤桂䝁䅷䅉䉂䡁䅍督求䡁䅑督獁䍁䅁杍杁䙁䅫杣畁䍁䅁睑䉂䕁䅣杕杁䍁䅧兊灁䅁䅁杖䅉䑁䅯䅁啂䝁䄸䅤桂䝁䅷䅉䉂䡁䅍督求䡁䅑督獁䍁䅁睍杁䙁䅫杣畁䍁䅁睑䉂䕁䅣杕杁䍁䅧兊灁䅁䅁来䅉䥁䅑䅁湁䙁䅳睑療䡁䅁入杁䝁䄸杚杁䙁䅍䅕䡂䙁䄸睑療䝁䄰䅣桂䝁䄴入時䕁䅳党㕂䙁䅍䅤桂䡁䅑督時䡁䅙杍時䝁䄴党㍂䍁䄴䅥獂䡁䅍兢摂䕁䄰兤獂䡁䅑兡睂䝁䅷党穂䍁䅣光歁䕁䅑䅊硁䑁䅅杏歁䕁䅑䅊硁䑁䅉䅁牃睂䅁䅢䅁䙁䅳睕兂䕁䅣睘䑂䝁䄸兢睂䝁䅅杢㕂䙁䄸睓求䡁䅫睕あ䝁䅅䅤穂䙁䄸杤祁䍁䄴䅥獂䡁䅍兢摂䕁䅳党㕂䙁䄸睕あ䝁䅅䅤穂䍁䅅䅊䕂䍁䅑免睁䑁䅫杏歁䕁䅑䅊硁䑁䅅李䅁偁䡧䅁㙁䅁䅁䅖療䡁䅑兙獂䍁䅁兑穂䡁䅍党あ䡁䅍䅌杁䑁䅕䅉婂䡁䅉杌杁䕁䅍兑䡂䙁䅉䅉潁䍁䅕克䅁䭁䍁䅁䅂䅁䅁䅖療䡁䅑兙獂䍁䅁村桂䝁䄴睡杁䕁䅑党楂䡁䅑睌杁䙁䅑睢あ䝁䅅䅢杁䕁䅑党楂䡁䅑䅉潁䍁䅕克䅁䙁䉫䅁㙂䅁䅁睊扂䕁䅍睢睂䡁䅫䅉療䝁䅙䅉呂䙁䅁睒時䕁䅍睢瑂䡁䅁兙畂䡁䅫睘䱂䝁䅕入呂䡁䅑兙あ䡁䅍睘㉂䑁䅉睘畂䝁䅕睤畁䡁䅧䅢穂䝁䄰兘䱂䝁䅕入時䙁䅍䅤桂䡁䅑督湁䍁䅅䅊䙂䍁䅑免睁䑁䅣䅁㥁睂䅁䅊䅁䙁䅑睢あ䝁䅅䅢杁䕁䅑党楂䡁䅑䅉潁䍁䅑䅍睁䑁䅁克䅁䝁䄰䅁㡁䅁䅁䅖療䡁䅑兙獂䍁䅁䅒求䝁䅉䅤癁䍁䅧兒䍂䕁䅫䅖䕂䕁䅅兌䑂䕁䅅䅕䙂䙁䅧克杁䍁䅧䅥灁䅁䅁䅨䅅䝁䅯䅁扂䕁䄰兓時䕁䅍睢瑂䡁䅁兙畂䡁䅫睘䱂䝁䅕入呂䡁䅑兙あ䡁䅍睘㉂䑁䅅杌㑂䝁䅷督瑂䙁䄰村桂䝁䅷兙畂䝁䅍党時䙁䅍䅡求䝁䅕䅤桁䍁䅑兒歁䑁䅑杏歁䙁䅁䅊ぁ䅁䅁元䅑䭁䅁䅁湁䙁䅳睑療䡁䅁入杁䝁䄸杚杁䙁䅍䅕䡂䙁䄸睑療䝁䄰䅣桂䝁䄴入時䕁䅳党㕂䙁䅍䅤桂䡁䅑督時䡁䅙杍時䝁䄴党㍂䍁䄴䅥獂䡁䅍兢摂䕁䅍兙睂䝁䅫䅤桂䝁䅷睘呂䡁䅑杣ㅂ䝁䅍䅤ㅂ䡁䅉党時䙁䅍兤瑂䝁䄰兙祂䡁䅫睊桁䍁䅑兒歁䑁䅣杏歁䙁䅅䅊㍁䅁䅁杷䅣䕁䅯䅁啂䝁䄸䅤桂䝁䅷䅉䵂䝁䅫兙楂䝁䅫䅢灂䡁䅑兡求䡁䅍䅉癁䍁䅁䅖療䡁䅑兙獂䍁䅁兑穂䡁䅍党あ䡁䅍䅉潁䍁䅕克䅁䱁䍙䅁䕂䅁䅁䅖療䡁䅑兙獂䍁䅁杔偂䕁䅷䅉䑂䝁䅅杣祂䡁䅫杚療䡁䅉睤桂䡁䅉䅚杁䍁䅧杕求䡁䅁睢祂䡁䅑党歂䍁䅫䅁扄杁䅁䅖䅁䙁䅑睢あ䝁䅅䅢杁䕁䄴睢畂䍁䅁兌杁䙁䅉党橂䝁䄸兤祂䡁䅍党杁䕁䅑党楂䡁䅑睌杁䙁䅑睢あ䝁䅅䅢杁䕁䅑党楂䡁䅑䅉潁䍁䅕克䅁䡁䉕䅁䕂䅁䅁䅖療䡁䅑兙獂䍁䅁䅕祂䝁䅕杚求䡁䅉杣求䝁䅑䅉䙂䡁䅅兤灂䡁䅑入杁䍁䅧杕求䡁䅁睢祂䡁䅑党歂䍁䅫䅁扁
A4: 䅁䅁䅓䅁䙁䅑睢あ䝁䅅䅢杁䙁䅁杣灂䝁䄴睙灂䡁䅁兙獂䍁䅁䅒ㅂ䝁䅕睌杁䙁䅑睢あ䝁䅅䅢杁䕁䅑党楂䡁䅑䅉潁䍁䅕克䅁偁䅍䅁祁䅁䅁䅖療䡁䅑兙獂䍁䅁杕求䡁䅙党畂䡁䅕党杁䍁䅧杕求䡁䅁睢祂䡁䅑党歂䍁䅫䅁䝁䅁䅁材䅁䙁䅑睢あ䝁䅅䅢杁䙁䅉党㉂䝁䅕杢ㅂ䝁䅕督獁䍁䅁杍杁䙁䅫杣畁䍁䅁睑䉂䕁䅣杕杁䍁䅧兊灁䅁䅁材䅉䥁䅧䅁湁䙁䅳睑療䡁䅁入杁䝁䄸杚杁䙁䅍䅕䡂䙁䄸睑療䝁䄰䅣桂䝁䄴入時䕁䅳党㕂䙁䅍䅤桂䡁䅑督時䡁䅙杍時䝁䄴党㍂䍁䄴䅥獂䡁䅍兢摂䕁䅉兙獂䝁䅅杢橂䝁䅕睘呂䝁䅧党求䡁䅑睊桁䍁䅑兒歁䑁䅣杏歁䙁䅅䅊㍁䅁䅁杳䅣䑁䄴䅁啂䝁䄸䅤桂䝁䅷䅉卂䝁䅕杤求䝁䄴兤求䡁䅍䅌杁䑁䅍䅉婂䡁䅉杌杁䕁䅍兑䡂䙁䅉䅉潁䍁䅕克䅁䝁䍧䅁兂䅁䅁睗乂䕁䅫睘䱂䝁䅕入呂䡁䅑兙あ䡁䅍睘㉂䑁䅅杌㑂䝁䅷督瑂䙁䄰村桂䝁䅷兙畂䝁䅍党時䙁䅍䅡求䝁䅕䅤桁䍁䅑睑歁䑁䅑䅁噃睁䅁杏䅁䙁䅑睢あ䝁䅅䅢杁䙁䅍党畂䝁䅫睢祂䍁䅁䅒求䝁䅉䅤杁䍁䅧杕求䡁䅁睢祂䡁䅑党歂䍁䅫䅁婁允䅁䅖䅁䙁䅑睢あ䝁䅅䅢杁䙁䅍党畂䝁䅫睢祂䍁䅁睕求䝁䅍兤祂䝁䅕䅚杁䕁䅑党楂䡁䅑睌杁䙁䅑睢あ䝁䅅䅢杁䕁䅑党楂䡁䅑䅉潁䍁䅕克䅁䙁䉳䅁卂䅁䅁兖畂䝁䅷党㉂䝁䅕杣求䝁䅑䅉䝂䡁䅉党求䍁䅁睑桂䡁䅍䅡杁䕁䅙䅢療䡁䅣䅌杁䑁䅍䅉婂䡁䅉杌杁䕁䅍兑䡂䙁䅉䅉潁䍁䅕克䅁䥁䍙䅁䅂䅁䅁䅖療䡁䅑兙獂䍁䅁睕求䝁䄴兡療䡁䅉䅉呂䝁䅕睙ㅂ䡁䅉党歂䍁䄸兒䍂䕁䅫䅖䕂䕁䅅䅉潁䡁䅧克䅁䡁䈴䅁獂䅁䅁睗乂䕁䅫睘䑂䝁䄸兢睂䝁䅅杢㕂䙁䄸睓求䡁䅫睕あ䝁䅅䅤穂䙁䄸杤硁䙁䄸杌㑂䝁䅷督瑂䙁䄰村桂䝁䅷兙畂䝁䅍党時䙁䅍䅡求䝁䅕䅤桁䍁䅑兒歁䑁䅕杏歁䙁䅁䅊ㅁ䅁䅁䄳䅑䝁䅧䅁扂䙁䅍䅕䡂䙁䄸睑療䝁䄰䅣桂䝁䄴入時䕁䅳党㕂䙁䅍䅤桂䡁䅑督時䡁䅙免畁䡁䅧䅢穂䝁䄰兘䱂䝁䅕入時䙁䅍䅤桂䡁䅑督桁䍁䅑䅒歁䑁䅉䅏㙁䍁䅑䅒歁䑁䅕杍䅁乁䙙䅁歂䅁䅁䅖療䡁䅑兙獂䍁䅁睕潂䝁䄸杣あ䍁䅁䅖求䡁䅉兢杁䕁䅉睢祂䡁䅉睢㍂䝁䅫杢湂䡁䅍䅉潁䙁䅁党祂䝁䅍党畂䡁䅑䅉療䝁䅙䅉䕂䝁䅕杙あ䍁䅫䅉潁䍁䅕克䅁䍁䉅䅁潂䅁䅁睗呂䙁䅁睒時䕁䅍睢瑂䡁䅁兙畂䡁䅫睘䱂䝁䅕入呂䡁䅑兙あ䡁䅍睘㉂䑁䅅杌㑂䝁䅷督瑂䙁䄰睓求䡁䅫睘呂䡁䅑兙あ䡁䅍光歁䕁䅕䅊祁䑁䅕杏歁䕁䅯䅊祁䑁䅕䅁剄兂䅁杖䅁䙁䅑睢あ䝁䅅䅢杁䙁䅍兤楂䍁䄴䅉䍂䝁䄸杢歂䡁䅍䅉桂䝁䄴䅚杁䕁䄴睢あ䝁䅕督癁䍁䅁䅖療䡁䅑兙獂䍁䅁䅒求䝁䅉䅤杁䍁䅧兊灁䅁䅁儯䅁䑁䅙䅁啂䝁䄸䅤桂䝁䅷䅉呂䡁䅕杙畁䍁䅁䅒求䝁䅉䅤杁䍁䅧杕求䡁䅁睢祂䡁䅑党歂䍁䅫䅁扁允䅁䅩䅁䙁䅳兔䩂䙁䄸睑療䝁䄰䅣桂䝁䄴入時䕁䅳党㕂䙁䅍䅤桂䡁䅑督時䡁䅙免畁䡁䅧䅢穂䝁䄰兘䑂䝁䅅䅣灂䡁䅑兙獂䙁䄸睕あ䡁䅉兤橂䡁䅑兤祂䝁䅕睘呂䡁䅕兢瑂䝁䅅杣㕂䍁䅅䅊䑂䍁䅑免ㅁ䑁䅯䅊䑂䍁䅑免ㅁ䑁䅉䅁⭃兂䅁杔䅁䙁䅑睢あ䝁䅅䅢杁䙁䅍兤楂䍁䄴䅉䕂䝁䅕杙あ䍁䅁睌杁䍁䅧兒䍂䕁䅫䅖䕂䕁䅅䅉瑁䍁䅁睑桂䡁䅁党㑂䍁䅫䅉潁䡁䅧克䅁䥁䉉䅁啂䅁䅁䅖療䡁䅑兙獂䍁䅁䅖桂䡁䅧䅉䍂䝁䅕杢求䝁䅙兡あ䍁䅁睑桂䡁䅉杣㕂䝁䅙睢祂䡁䅣兙祂䝁䅑䅉潁䙁䅉党睂䝁䄸杣あ䝁䅕䅚灁䅁䅁睁䅍䥁䅁䅁湁䙁䅳睑療䡁䅁入杁䝁䄸杚杁䙁䅍䅕䡂䙁䄸睑療䝁䄰䅣桂䝁䄴入時䕁䅳党㕂䙁䅍䅤桂䡁䅑督時䡁䅙杍時䝁䄴党㍂䍁䄴䅥獂䡁䅍兢摂䙁䅉兙あ䝁䅫睢穂䍁䅣光歁䕁䅍䅊硁䑁䅅杏歁䕁䅍䅊硁䑁䅕䅏䅁䝁䡁䅁䍂䅁䅁䅖療䡁䅑兙獂䍁䅁䅖求䡁䅉兢杁䕁䅷睢桂䝁䄴督癁䍁䅁䅖療䡁䅑兙獂䍁䅁䅒求䝁䅉䅤杁䍁䅧兊灁䅁䅁儫䅁䭁䅁䅁湁䙁䅳睑療䡁䅁入杁䝁䄸杚杁䙁䅍䅕䡂䙁䄸睑療䝁䄰䅣桂䝁䄴入時䕁䅳党㕂䙁䅍䅤桂䡁䅑督時䡁䅙免時䕁䅙兡畂䝁䅅䅢畁䡁䅧䅢穂䝁䄰兘䑂䝁䅅䅣灂䡁䅑兙獂䙁䄸睕あ䡁䅉兤橂䡁䅑兤祂䝁䅕睘杁䕁䅑党あ䝁䅅兡獂䡁䅍䅉湁䍁䅅䅊䥂䍁䅑睎㉁䅁䅁杓䅧䕁䅉䅁啂䝁䄸䅤桂䝁䅷䅉啂䡁䅉兤穂䡁䅑䅉兂䡁䅉党浂䝁䅕杣祂䝁䅕䅚杁䍁䅧杕求䡁䅁睢祂䡁䅑党歂䍁䅫䅁䱂允䅁䅔䅁䙁䅑睢あ䝁䅅䅢杁䙁䅑杣ㅂ䡁䅍䅤杁䙁䅁杣求䝁䅙党祂䡁䅉党歂䍁䄸䅉啂䝁䄸䅤桂䝁䅷䅉䕂䝁䅕杙あ䍁䅁䅋汁䍁䅫䅁灂允䅁杖䅁䙁䅑睢あ䝁䅅䅢杁䙁䅕杢桂䝁䄰睢祂䡁䅑兡㙂䝁䅕䅚杁䕁䅑兡穂䝁䅍睢ㅂ䝁䄴䅤癁䍁䅁䅖療䡁䅑兙獂䍁䅁䅒求䝁䅉䅤杁䍁䅧兊灁䅁䅁允䅅䥁䅑䅁湁䙁䅳睑療䡁䅁入杁䝁䄸杚杁䙁䅍䅕䡂䙁䄸睑療䝁䄰䅣桂䝁䄴入時䕁䅳党㕂䙁䅍䅤桂䡁䅑督時䡁䅙杍時䝁䄴党㍂䍁䄴䅥獂䡁䅍兢摂䕁䅳党㕂䙁䄸睕あ䝁䅅䅤穂䍁䅣光歁䕁䅍䅊㉁䑁䅕杏歁䕁䅍䅊㍁䑁䅅䅁睁睂䅁䅑䅁䙁䅑睢あ䝁䅅䅢杁䙁䅕杢歂䡁䅉兙㍂䝁䄴䅉䑂䡁䅉党歂䝁䅫䅤杁䍁䅧杕求䡁䅁睢祂䡁䅑党歂䍁䅫䅁乁允䅁䅥䅁䍁䅣睗䑂䝁䄸䅣㕂䍁䅁睢浂䍁䅁睕兂䕁䅣睘䑂䝁䄸兢睂䝁䅅杢㕂䙁䄸睓求䡁䅫睕あ䝁䅅䅤穂䙁䄸杤祁䙁䄸杢求䡁䅣杌㑂䝁䅷督瑂䙁䄰睓求䡁䅫睘呂䡁䅑兙あ䡁䅍睊桁䍁䅑兒歁䑁䅙睍䅁䑁䡅䅁捂䅁䅁睗䱂䝁䅕入呂䡁䅑兙あ䡁䅍睘あ䝁䅕督あ䝁䅙兡獂䝁䅕杌㑂䝁䅷督瑂䙁䄰睓求䡁䅫睘呂䡁䅑兙あ䡁䅍光歁䕁䅕䅊㕁䑁䅣杏歁䕁䅣䅊㕁䑁䅣䅁剃䅁䅁杓䅁䙁䅑睢あ䝁䅅䅢杁䙁䅕杢穂䝁䅕睙ㅂ䡁䅉党歂䍁䅁䅒求䝁䅉䅤癁䍁䅁䅖療䡁䅑兙獂䍁䅁䅒求䝁䅉䅤杁䍁䅧兊灁䅁䅁睙䅅䙁䅁䅁噂䝁䄴䅚祂䝁䅅睤畂䍁䅁睑祂䝁䅕䅚灂䡁䅑䅉兂䝁䄸杣あ䝁䅫睢畂䍁䅁睢浂䍁䅁睑兂䍁䅁䅋卂䝁䅕䅣療䡁䅉䅤求䝁䅑克䅁䅁䉣䅁睂䅁䅁睗呂䙁䅁睒時䕁䅍睢瑂䡁䅁兙畂䡁䅫睘䱂䝁䅕入呂䡁䅑兙あ䡁䅍睘㉂䑁䅅杌㑂䝁䅷督瑂䙁䄰睕ㅂ䡁䅁䅣獂䝁䅕兢求䝁䄴䅤桂䝁䅷光歁䕁䅍䅊硁䑁䅅杏歁䕁䅍䅊硁䑁䅙李䅁䅁䝯䅁あ䅁䅁兖畂䝁䅑杣桂䡁䅣杢杁䕁䅍杣求䝁䅑兡あ䍁䅁䅕療䡁䅉䅤灂䝁䄸杢杁䝁䄸杚杁䕁䄸䅤潂䝁䅕杣杁䍁䅧杕求䡁䅍兡歂䡁䅕兙獂䍁䅁䅖桂䝁䅣克杁䍁䅧杕求䡁䅁睢祂䡁䅑党歂䍁䅫䅁䱁允䅁䅢䅁䙁䅕杢歂䡁䅉兙㍂䝁䄴䅉䑂䡁䅉党歂䝁䅫䅤杁䙁䅁睢祂䡁䅑兡療䝁䄴䅉療䝁䅙䅉卂䝁䅕杤療䝁䅷杤灂䝁䄴睚杁䕁䅍杣求䝁䅑兡あ䍁䅁䅋卂䝁䅕䅣療䡁䅉䅤求䝁䅑克䅁䅁䉕䅁煂䅁䅁睗乂䕁䅫睘䑂䝁䄸兢睂䝁䅅杢㕂䙁䄸睓求䡁䅫睕あ䝁䅅䅤穂䙁䄸杤硁䍁䄴䅥獂䡁䅍兢摂䕁䅉兙獂䝁䅅杢橂䝁䅕睘呂䝁䅧党求䡁䅑光歁䕁䅕䅊ㅁ䑁䅯䅊兂䍁䅑兎䅁䅁䕳䅁睂䅁䅁睗乂䕁䅫睘䑂䝁䄸兢睂䝁䅅杢㕂䙁䄸睓求䡁䅫睕あ䝁䅅䅤穂䙁䄸杤硁䙁䄸杌㑂䝁䅷督瑂䙁䄰村桂䝁䅷兙畂䝁䅍党時䙁䅍䅡求䝁䅕䅤桁䍁䅑睑歁䑁䅫杏歁䕁䅍䅊硁䑁䅍兏䅁乁䕳䅁祂䅁䅁睗乂䕁䅫睘䱂䝁䅕入呂䡁䅑兙あ䡁䅍睘㉂䑁䅅杌㑂䝁䅷督瑂䙁䄰睑桂䡁䅁兡あ䝁䅅䅢時䙁䅍䅤祂䡁䅕睙あ䡁䅕杣求䙁䄸睕ㅂ䝁䄰兢桂䡁䅉入桁䍁䅑兒歁䑁䅕杏歁䕁䄰䅊ㅁ䅁䅁䅲䅍䙁䅯䅁扂䕁䄰兓時䕁䅍睢瑂䡁䅁兙畂䡁䅫睘䱂䝁䅕入呂䡁䅑兙あ䡁䅍睘㉂䑁䅅杌㑂䝁䅷督瑂䙁䄰睓求䡁䅫睘呂䡁䅑兙あ䡁䅍光歁䕁䅕䅊㉁䑁䅍䅁㉃䅂䅁杚䅁䙁䅳兔䩂䙁䄸睑療䝁䄰䅣桂䝁䄴入時䕁䅳党㕂䙁䅍䅤桂䡁䅑督時䡁䅙免時䍁䄴䅥獂䡁䅍兢摂䕁䅍兙穂䝁䅧睘䝂䝁䅷睢㍂䍁䅅䅊䑂䍁䅑兏㙁䍁䅑睑歁䑁䅫䅍䅁佁䕍䅁䥂䅁䅁兖畂䝁䅷党㉂䝁䅕杣求䝁䅑䅉䝂䡁䅉党求䍁䅁睑桂䡁䅍䅡杁䕁䅙䅢療䡁䅣䅉乂䝁䅅杣湂䝁䅫杢杁䍁䅧兊灁䅁䅁䅆䅉䙁䅙䅁噂䝁䄴䅢求䡁䅙党祂䝁䅕䅚杁䕁䅙杣求䝁䅕䅉䑂䝁䅅督潂䍁䅁杒獂䝁䄸睤獁䍁䅁免杁䙁䅫杣畁䍁䅁睒祂䝁䄸睤あ䝁䅧䅉潁䍁䅕克䅁䑁䍙䅁卂䅁䅁兖畂䝁䅷党㉂䝁䅕杣求䝁䅑䅉䝂䡁䅉党求䍁䅁睑桂䡁䅍䅡杁䕁䅙䅢療䡁䅣䅌杁䑁䅉䅉婂䡁䅉杌杁䕁䅍兑䡂䙁䅉䅉潁䍁䅕克䅁䕁䍷䅁卂䅁䅁兖畂䝁䅷党㉂䝁䅕杣求䝁䅑䅉䝂䡁䅉党求䍁䅁睑桂䡁䅍䅡杁䕁䅙䅢療䡁䅣䅌杁䑁䅕䅉婂䡁䅉杌杁䕁䅍兑䡂䙁䅉䅉潁䍁䅕克䅁䭁䍷䅁㙂䅁䅁兖畂䡁䅉党橂䝁䄸睚畁䍁䅁䅖桂䡁䅧䅉䍂䝁䅕杢求䝁䅙兡あ䍁䅁兓瑂䡁䅁兙橂䡁䅑兡畂䝁䅣䅉䙂䝁䅙杚求䝁䅍䅤灂䡁䅙党杁䙁䅑兙㑂䍁䅁杕桂䡁䅑党杁䍁䅧杕求䡁䅁睢祂䡁䅑党歂䍁䅫䅁湄杁䅁䅘䅁䙁䅕杢祂䝁䅕睙療䝁䅣杌杁䙁䅑兙㑂䍁䅁村求䝁䄴党浂䝁䅫䅤穂䍁䅁兌杁䕁䄸䅤潂䝁䅕杣杁䕁䅅䅚煂䍁䄴䅉潁䙁䅉党睂䝁䄸杣あ䝁䅕䅚灁䅁䅁睄䅍䡁䅑䅁噂䝁䄴杣求䝁䅍睢湂䍁䄴䅉啂䝁䅅䅥杁䕁䅉党畂䝁䅕杚灂䡁䅑督獁䍁䅁村求䝁䅣兡畂䝁䄴兡畂䝁䅣䅉療䝁䅙䅉あ䝁䅧党杁䙁䅁党祂䝁䅫睢歂䍁䅁䅋卂䝁䅕䅣療䡁䅉䅤求䝁䅑克䅁䅁䑕䅁兂䅁䅁睖癁䕁䅅杤求䡁䅉兙湂䝁䅕䅉䩂䝁䄴䅤求䡁䅉党穂䡁䅑䅉卂䝁䅅䅤求䑁䅯䅉啂䝁䄸䅤桂䝁䅷䅉䕂䝁䅕杙あ䍁䅁䅋汁䍁䅫䅁潄允䅁䅘䅁䙁䅣兙祂䡁䅉兙畂䡁䅑督杁䕁䅍兙畂䝁䅍党獂䝁䅷党歂䍁䅁䅒ㅂ䡁䅉兡畂䝁䅣䅉あ䝁䅧党杁䙁䅁党祂䝁䅫睢歂䍁䅁䅋桂䝁䅍䅤ㅂ䝁䅅䅢灁䅁䅁兕䅍䙁䅯䅁扂䕁䄰兓時䕁䅍睢瑂䡁䅁兙畂䡁䅫睘䱂䝁䅕入呂䡁䅑兙あ䡁䅍睘㉂䑁䅅杌㑂䝁䅷督瑂䙁䄰睓求䡁䅫睘呂䡁䅑兙あ䡁䅍光歁䕁䅕䅊ㅁ䑁䅉䅁㥄睁䅁䅘䅁䙁䅣兙祂䡁䅉兙畂䡁䅑督杁䕁䅕䅥求䡁䅉睙灂䡁䅍党歂䍁䅁䅒ㅂ䡁䅉兡畂䝁䅣䅉あ䝁䅧党杁䙁䅁党祂䝁䅫睢歂䍁䅁䅋桂䝁䅍䅤ㅂ䝁䅅䅢灁䅁䅁睔䅍䙁䅙䅁塂䝁䅅杣祂䝁䅅杢あ䡁䅍䅉䩂䡁䅍督ㅂ䝁䅕䅚杁䕁䅑兤祂䝁䅫杢湂䍁䅁䅤潂䝁䅕䅉兂䝁䅕杣灂䝁䄸䅚杁䍁䅧兙橂䡁䅑兤桂䝁䅷克䅁䕁䐰䅁歂䅁䅁睖桂䡁䅉杣桂䝁䄴䅤穂䍁䅁兓穂䡁䅍兤求䝁䅑䅉䕂䡁䅕杣灂䝁䄴睚杁䡁䅑䅡求䍁䅁䅕求䡁䅉兡療䝁䅑䅌杁䙁䅑睢あ䝁䅅䅢杁䍁䅧兙橂䡁䅑兤桂䝁䅷克䅁䙁䑫䅁祂䅁䅁睖桂䡁䅉杣桂䝁䄴䅤穂䍁䅁睔ㅂ䡁䅑杌杁䝁䅅䅤杁䡁䅑䅡求䍁䅁村求䝁䅣兡畂䍁䅁睢浂䍁䅁䅤潂䝁䅕䅉兂䝁䅕杣灂䝁䄸䅚獁䍁䅁䅖療䡁䅑兙獂䍁䅁䅋桂䝁䅍䅤ㅂ䝁䅅䅢灁䅁䅁睖䅍䝁䅷䅁塂䝁䅅杣祂䝁䅅杢あ䡁䅍䅉偂䡁䅕䅤畁䍁䅁兙あ䍁䅁䅤潂䝁䅕䅉䍂䝁䅕睚灂䝁䄴杢灂䝁䄴睚杁䝁䄸杚杁䡁䅑䅡求䍁䅁䅕求䡁䅉兡療䝁䅑䅉潁䝁䅅睙あ䡁䅕兙獂䍁䅫䅁䱂睁䅁条䅁䙁䅳兔䩂䙁䄸睑療䝁䄰䅣桂䝁䄴入時䕁䅳党㕂䙁䅍䅤桂䡁䅑督時䡁䅙免畁䡁䅧䅢穂䝁䄰兘䱂䝁䅕入時䙁䅍䅤桂䡁䅑督桁䍁䅑睑歁䑁䅅免睁䑁䅯䅊䑂䍁䅑免硁䑁䅑䅁祃䅂䅁杔䅁䙁䅳兔䩂䙁䄸睓求䡁䅫睕あ䝁䅅䅤穂䙁䄸杤硁䍁䄴䅥獂䡁䅍兢摂䙁䅍兤睂䡁䅁䅢求䝁䄰党畂䡁䅑兙獂䍁䅅䅊䑂䍁䅑䅎䅁䩁䑅䅁畂䅁䅁睖桂䡁䅉杣桂䝁䄴䅤穂䍁䅁睔ㅂ䡁䅑杌杁䝁䅅䅤杁䡁䅑䅡求䍁䅁兒畂䝁䅑䅉療䝁䅙䅉あ䝁䅧党杁䙁䅁党祂䝁䅫睢歂䍁䅷䅉啂䝁䄸䅤桂䝁䅷䅉潁䝁䅅睙あ䡁䅕兙獂䍁䅫䅁摂睁䅁䅙䅁䙁䅣兙祂䡁䅉兙畂䡁䅑督杁䕁䄸兤あ䍁䄴䅉桂䡁䅑䅉あ䝁䅧党杁䕁䅕杢歂䍁䅁睢浂䍁䅁䅤潂䝁䅕䅉兂䝁䅕杣灂䝁䄸䅚杁䍁䅧兙橂䡁䅑兤桂䝁䅷克䅁䙁䑍䅁㡂䅁䅁睖桂䡁䅉杣桂䝁䄴䅤穂䍁䅁睖あ䝁䅑䅉䉂䡁䅙睚杁䙁䅍䅤祂䝁䅫睡求䍁䅁䅕祂䝁䅫睙求䍁䅁睢浂䍁䅁睔ㅂ䡁䅑督あ䝁䅑䅌杁䕁䅍睢瑂䝁䄰䅉呂䡁䅑睙牂䍁䅁䅋卂䝁䅕䅣療䡁䅉䅤求䝁䅑克䅁䙁䑕䅁佃䅁䅁睊扂䕁䅍睢睂䡁䅫䅉療䝁䅙䅉呂䙁䅁睒時䕁䅍睢瑂䡁䅁兙畂䡁䅫睘䱂䝁䅕入呂䡁䅑兙あ䡁䅍睘㉂䑁䅉睘畂䝁䅕睤畁䡁䅧䅢穂䝁䄰兘䑂䝁䅅䅣灂䡁䅑兙獂䝁䅫来桂䡁䅑兡療䝁䄴睊桁䍁䅑兒歁䑁䅕䅍㙁䍁䅑杓歁䑁䅕䅍䅁䕁䠸䅁畂䅁䅁睖あ䝁䅑䅉䉂䡁䅙睚杁䙁䅍䅤祂䝁䅫睡求䍁䅁䅕祂䝁䅫睙求䍁䅁睢浂䍁䅁睒祂䝁䅅杢あ䝁䅕䅚獁䍁䅁睑療䝁䄰兢杁䙁䅍䅤療䝁䅍睡杁䍁䅧杕求䡁䅁睢祂䡁䅑党歂䍁䅫䅁穁睁䅁䅏䅁䙁䅯党祂䝁䄸䅉䑂䝁䄸兤睂䝁䄸杢杁䕁䅑党楂䡁䅑䅉潁䙁䅉党睂䝁䄸杣あ䝁䅕䅚灁䅁䅁兔䅅䭁䅁䅁湁䙁䅳睑療䡁䅁入杁䝁䄸杚杁䙁䅍䅕䡂䙁䄸睑療䝁䄰䅣桂䝁䄴入時䕁䅳党㕂䙁䅍䅤桂䡁䅑督時䡁䅙免時䕁䅙兡畂䝁䅅䅢畁䡁䅧䅢穂䝁䄰兘䑂䝁䅅䅣灂䡁䅑兙獂䙁䄸睕あ䡁䅉兤橂䡁䅑兤祂䝁䅕睘杁䕁䅑党あ䝁䅅兡獂䡁䅍䅉湁䍁䅅䅊䡂䍁䅑䅎ぁ䅁䅁䅪䅧䙁䅙䅁扂䕁䅳党㕂䙁䅍䅤桂䡁䅑督時䡁䅑党穂䡁䅑杚灂䝁䅷党畁䡁䅧䅢穂䝁䄰兘䍂䝁䅅䅢桂䝁䄴睙求䙁䄸睕潂䝁䅕党あ䍁䅅䅊䑂䍁䅑䅎䅁䵁䅅䅁歂䅁䅁睗䱂䝁䅕入呂䡁䅑兙あ䡁䅍睘あ䝁䅕督あ䝁䅙兡獂䝁䅕杌㑂䝁䅷督瑂䙁䄰村桂䝁䅷兙畂䝁䅍党時䙁䅍䅡求䝁䅕䅤桁䍁䅑䅒歁䑁䅫杏歁䕁䅑䅊硁䑁䅍睎䅁䵁䅍䅁畂䅁䅁睗䱂䝁䅕入呂䡁䅑兙あ䡁䅍睘あ䝁䅕督あ䝁䅙兡獂䝁䅕杌㑂䝁䅷督瑂䙁䄰睑桂䡁䅁兡あ䝁䅅䅢時䙁䅍䅤祂䡁䅕睙あ䡁䅕杣求䙁䄸睕ㅂ䝁䄰兢桂䡁䅉入桁䍁䅑睑歁䑁䅑䅁汄䅁䅁杢䅁䙁䅳睓求䡁䅫睕あ䝁䅅䅤穂䙁䄸䅤求䡁䅍䅤浂䝁䅫䅢求䍁䄴䅥獂䡁䅍兢摂䕁䅍兙睂䝁䅫䅤桂䝁䅷睘呂䡁䅑杣ㅂ䝁䅍䅤ㅂ䡁䅉党時䙁䅍兤瑂䝁䄰兙祂䡁䅫光歁䕁䅍䅊ㅁ䅁䅁杤䅅䡁䄴䅁扂䕁䅳党㕂䙁䅍䅤桂䡁䅑督時䡁䅑党穂䡁䅑杚灂䝁䅷党畁䡁䅧䅢穂䝁䄰兘䑂䝁䅅䅣灂䡁䅑兙獂䙁䄸睕あ䡁䅉兤橂䡁䅑兤祂䝁䅕睘呂䡁䅕兢瑂䝁䅅杣㕂䍁䅅䅊䕂䍁䅑免穁䑁䅯䅊䕂䍁䅑免ぁ䑁䅙䅁硄允䅁来䅁䙁䅳睓求䡁䅫睕あ䝁䅅䅤穂䙁䄸䅤求䡁䅍䅤浂䝁䅫䅢求䍁䄴䅥獂䡁䅍兢摂䕁䅍兙睂䝁䅫䅤桂䝁䅷睘呂䡁䅑杣ㅂ䝁䅍䅤ㅂ䡁䅉党時䙁䅍兤瑂䝁䄰兙祂䡁䅫光歁䕁䅑䅊㕁䑁䅯䅊䕂䍁䅑兏睁䅁䅁眵䅁䡁䅷䅁扂䕁䅳党㕂䙁䅍䅤桂䡁䅑督時䡁䅑党穂䡁䅑杚灂䝁䅷党畁䡁䅧䅢穂䝁䄰兘䑂䝁䅅䅣灂䡁䅑兙獂䙁䄸睕あ䡁䅉兤橂䡁䅑兤祂䝁䅕睘呂䡁䅕兢瑂䝁䅅杣㕂䍁䅅䅊䕂䍁䅑免穁䑁䅯䅊䕂䍁䅑兏穁䅁䅁来䅅䡁䄴䅁扂䕁䅳党㕂䙁䅍䅤桂䡁䅑督時䡁䅑党穂䡁䅑杚灂䝁䅷党畁䡁䅧䅢穂䝁䄰兘䑂䝁䅅䅣灂䡁䅑兙獂䙁䄸睕あ䡁䅉兤橂䡁䅑兤祂䝁䅕睘呂䡁䅕兢瑂䝁䅅杣㕂䍁䅅䅊䙂䍁䅑杍㍁䑁䅯䅊䙂䍁䅑免睁䑁䅣䅁㑂允䅁来䅁䍁䅣睗䑂䝁䄸䅣㕂䍁䅁睢浂䍁䅁睕兂䕁䅣睘䑂䝁䄸兢睂䝁䅅杢㕂䙁䄸睓求䡁䅫睕あ䝁䅅䅤穂䙁䄸杤祁䙁䄸杢求䡁䅣杌㑂䝁䅷督瑂䙁䄰杕桂䡁䅑兡療䡁䅍睊桁䍁䅑䅒歁䑁䅙杏歁䕁䅫䅊㉁䅁䅁睘䅣䡁䅧䅁扂䕁䅳党㕂䙁䅍䅤桂䡁䅑督時䡁䅑党穂䡁䅑杚灂䝁䅷党畁䡁䅧䅢穂䝁䄰兘䑂䝁䅅䅣灂䡁䅑兙獂䙁䄸睕あ䡁䅉兤橂䡁䅑兤祂䝁䅕睘呂䡁䅕兢瑂䝁䅅杣㕂䍁䅅䅊䝂䍁䅑䅎㙁䍁䅑杓歁䑁䅑䅁浄䅁䅁䅨䅁䍁䅣睗呂䙁䅁睒時䕁䅍睢瑂䡁䅁兙畂䡁䅫睘䱂䝁䅕入呂䡁䅑兙あ䡁䅍睘㉂䑁䅉杌㑂䝁䅷督瑂䙁䄰睑桂䡁䅁兡あ䝁䅅䅢時䙁䅍䅤祂䡁䅕睙あ䡁䅕杣求䙁䄸䅉䕂䝁䅕䅤桂䝁䅫䅢穂䍁䅁睊桁䍁䅑兓歁䑁䅑䅎䅁䉁䥧䅁奂䅁䅁睗䱂䝁䅕入呂䡁䅑兙あ䡁䅍睘あ䝁䅕督あ䝁䅙兡獂䝁䅕杌㑂䝁䅷督瑂䙁䄰睑桂䡁䅁兡あ䝁䅅䅢灂䡁䅯兙あ䝁䅫睢畂䍁䅅䅊䑂䍁䅑䅎䅁䵁䅕䅁畂䅁䅁睗乂䕁䅫睘䑂䝁䄸兢睂䝁䅅杢㕂䙁䄸睓求䡁䅫睕あ䝁䅅䅤穂䙁䄸杤硁䙁䄸杌㑂䝁䅷督瑂䙁䄰睕ㅂ䡁䅁䅣獂䝁䅕兢求䝁䄴䅤桂䝁䅷光歁䕁䅍䅊㕁䑁䅯䅊䑂䍁䅑免㉁䑁䅑䅁⽄䅂䅁䅧䅁䍁䅣睗䑂䝁䄸䅣㕂䍁䅁睢浂䍁䅁睕兂䕁䅣睘䑂䝁䄸兢睂䝁䅅杢㕂䙁䄸睓求䡁䅫睕あ䝁䅅䅤穂䙁䄸杤祁䙁䄸杢求䡁䅣杌㑂䝁䅷督瑂䙁䄰睑桂䡁䅁兡あ䝁䅅䅢灂䡁䅯兙あ䝁䅫睢畂䍁䅣光歁䕁䅍䅊ぁ䅁䅁杓䅣䙁䅯䅁扂䕁䅳党㕂䙁䅍䅤桂䡁䅑督時䡁䅑党穂䡁䅑杚灂䝁䅷党畁䡁䅧䅢穂䝁䄰兘䑂䝁䅅䅣灂䡁䅑兙獂䝁䅫来桂䡁䅑兡療䝁䄴光歁䕁䅍䅊ぁ䑁䅣䅁潂睁䅁杧䅁䍁䅣睗䑂䝁䄸䅣㕂䍁䅁睢浂䍁䅁睕兂䕁䅣睘䑂䝁䄸兢睂䝁䅅杢㕂䙁䄸睓求䡁䅫睕あ䝁䅅䅤穂䙁䄸杤祁䙁䄸杢求䡁䅣杌㑂䝁䅷督瑂䙁䄰睑桂䡁䅁兡あ䝁䅅䅢灂䡁䅯兙あ䝁䅫睢畂䍁䅣光歁䕁䅍䅊ぁ䑁䅣䅁卂睂䅁杚䅁䙁䅳睓求䡁䅫睕あ䝁䅅䅤穂䙁䄸䅤求䡁䅍䅤浂䝁䅫䅢求䍁䄴䅥獂䡁䅍兢摂䕁䅍兙睂䝁䅫䅤桂䝁䅷兡㙂䝁䅅䅤灂䝁䄸杢桁䍁䅑䅒歁䑁䅍睍㙁䍁䅑䅒歁䑁䅍䅎䅁䵁䅳䅁佃䅁䅁睊扂䕁䅍睢睂䡁䅫䅉療䝁䅙䅉呂䙁䅁睒時䕁䅍睢瑂䡁䅁兙畂䡁䅫睘䱂䝁䅕入呂䡁䅑兙あ䡁䅍睘㉂䑁䅉睘畂䝁䅕睤畁䡁䅧䅢穂䝁䄰兘䑂䝁䅅䅣灂䡁䅑兙獂䝁䅫来桂䡁䅑兡療䝁䄴睊桁䍁䅑兒歁䑁䅑李㙁䍁䅑杓歁䑁䅑李䅁䙁䡍䅁歂䅁䅁睗呂䙁䅁睒時䕁䅍睢瑂䡁䅁兙畂䡁䅫睘䱂䝁䅕入呂䡁䅑兙あ䡁䅍睘㉂䑁䅅杌㑂䝁䅷督瑂䙁䄰睑桂䡁䅁兡あ䝁䅅䅢灂䡁䅯兙あ䝁䅫睢畂䍁䅅䅊䑂䍁䅑䅎䅁偁䙁䅁浂䅁䅁睗䱂䝁䅕入呂䡁䅑兙あ䡁䅍睘あ䝁䅕督あ䝁䅙兡獂䝁䅕杌㑂䝁䅷督瑂䙁䄰睑桂䡁䅁兡あ䝁䅅䅢灂䡁䅯兙あ䝁䅫睢畂䍁䅅䅊䕂䍁䅑睍ぁ䑁䅯䅊䕂䍁䅑睍ㅁ䅁䅁儱䅁䝁䄴䅁扂䙁䅍䅕䡂䙁䄸睑療䝁䄰䅣桂䝁䄴入時䕁䅳党㕂䙁䅍䅤桂䡁䅑督時䡁䅙免畁䡁䅧䅢穂䝁䄰兘䑂䝁䅅䅣灂䡁䅑兙獂䝁䅫来桂䡁䅑兡療䝁䄴光歁䕁䅕䅊ぁ䑁䅯䅊䭂䍁䅑䅎䅁偁䙅䅁慂䅁䅁睗䱂䝁䅕入呂䡁䅑兙あ䡁䅍睘あ䝁䅕督あ䝁䅙兡獂䝁䅕杌㑂䝁䅷督瑂䙁䄰睑桂䡁䅁兡あ䝁䅅䅢灂䡁䅯兙あ䝁䅫睢畂䍁䅅䅊䕂䍁䅑兎睁䅁䅁眳䅁䝁䅑䅁扂䕁䅳党㕂䙁䅍䅤桂䡁䅑督時䡁䅑党穂䡁䅑杚灂䝁䅷党畁䡁䅧䅢穂䝁䄰兘䑂䝁䅅䅣灂䡁䅑兙獂䝁䅫来桂䡁䅑兡療䝁䄴光歁䕁䅑䅊㕁䑁䅯䅊䕂䍁䅑杍ㅁ䅁䅁䄱䅁䝁䅑䅁扂䕁䅳党㕂䙁䅍䅤桂䡁䅑督時䡁䅑党穂䡁䅑杚灂䝁䅷党畁䡁䅧䅢穂䝁䄰兘䑂䝁䅅䅣灂䡁䅑兙獂䝁䅫来桂䡁䅑兡療䝁䄴光歁䕁䅑䅊㕁䑁䅯䅊䕂䍁䅑睍睁䅁䅁杺䅁䙁䅙䅁扂䕁䅳党㕂䙁䅍䅤桂䡁䅑督時䡁䅑党穂䡁䅑杚灂䝁䅷党畁䡁䅧䅢穂䡁䅧兘呂䝁䅧党求䡁䅑免桁䍁䅑兒歁䑁䅉䅍㙁䍁䅑䅓歁䑁䅉䅍䅁䑁䅣䅁歂䅁䅁睗䱂䝁䅕入呂䡁䅑兙あ䡁䅍睘あ䝁䅕督あ䝁䅙兡獂䝁䅕杌㑂䝁䅷督瑂䙁䄰睑桂䡁䅁兡あ䝁䅅䅢灂䡁䅯兙あ䝁䅫睢畂䍁䅅䅊䕂䍁䅑兏㙁䍁䅑䅒歁䑁䅫䅍䅁䵁䅣䅁浂䅁䅁睗䱂䝁䅕入呂䡁䅑兙あ䡁䅍睘あ䝁䅕督あ䝁䅙兡獂䝁䅕杌㑂䝁䅷督瑂䙁䄰睑桂䡁䅁兡あ䝁䅅䅢灂䡁䅯兙あ䝁䅫睢畂䍁䅅䅊䝂䍁䅑睍硁䑁䅯䅊䱂䍁䅑睍硁䅁䅁儰䅁䝁䅙䅁扂䕁䅳党㕂䙁䅍䅤桂䡁䅑督時䡁䅑党穂䡁䅑杚灂䝁䅷党畁䡁䅧䅢穂䝁䄰兘䑂䝁䅅䅣灂䡁䅑兙獂䝁䅫来桂䡁䅑兡療䝁䄴光歁䕁䅙䅊穁䑁䅅杏歁䙁䅅䅊穁䑁䅅䅁䭄䅁䅁杚䅁䙁䅳睓求䡁䅫睕あ䝁䅅䅤穂䙁䄸䅤求䡁䅍䅤浂䝁䅫䅢求䍁䄴䅥獂䡁䅍兢摂䕁䅍兙睂䝁䅫䅤桂䝁䅷兡㙂䝁䅅䅤灂䝁䄸杢桁䍁䅑杒歁䑁䅍杍㙁䍁䅑兕歁䑁䅍杍䅁䵁䅷䅁浂䅁䅁睗䱂䝁䅕入呂䡁䅑兙あ䡁䅍睘あ䝁䅕督あ䝁䅙兡獂䝁䅕杌㑂䝁䅷督瑂䙁䄰睑桂䡁䅁兡あ䝁䅅䅢灂䡁䅯兙あ䝁䅫睢畂䍁䅅䅊䝂䍁䅑睍穁䑁䅯䅊䱂䍁䅑睍穁䅁䅁朱䅁䙁䅷䅁扂䙁䅍䅕䡂䙁䄸睑療䝁䄰䅣桂䝁䄴入時䕁䅳党㕂䙁䅍䅤桂䡁䅑督時䡁䅙杍畁䡁䅧䅢穂䝁䄰兘䱂䝁䅕入時䙁䅍䅤桂䡁䅑督桁䍁䅑村歁䑁䅉兎䅁佁䡙䅁㑂䅁䅁睗乂䕁䅫睘䱂䝁䅕入呂䡁䅑兙あ䡁䅍睘㉂䑁䅅杌㑂䝁䅷督瑂䙁䄰睑桂䡁䅁兡あ䝁䅅䅢時䙁䅍䅤祂䡁䅕睙あ䡁䅕杣求䙁䄸睕ㅂ䝁䄰兢桂䡁䅉入桁䍁䅑睑歁䑁䅅睍㙁䍁䅑睑歁䑁䅅䅎㕁䅁䅁杷䅍䝁䅙䅁扂䕁䅳党㕂䙁䅍䅤桂䡁䅑督時䡁䅑党穂䡁䅑杚灂䝁䅷党畁䡁䅧䅢穂䝁䄰兘䑂䝁䅅䅣灂䡁䅑兙獂䝁䅫来桂䡁䅑兡療䝁䄴光歁䕁䅙䅊ぁ䑁䅣杏歁䕁䅳䅊ぁ䑁䅣䅁敄䅁䅁杚䅁䙁䅳睓求䡁䅫睕あ䝁䅅䅤穂䙁䄸䅤求䡁䅍䅤浂䝁䅫䅢求䍁䄴䅥獂䡁䅍兢摂䕁䅍兙睂䝁䅫䅤桂䝁䅷兡㙂䝁䅅䅤灂䝁䄸杢桁䍁䅑杒歁䑁䅕杍㙁䍁䅑睓歁䑁䅕杍䅁乁䅷䅁浂䅁䅁睗乂䕁䅫睘䑂䝁䄸兢睂䝁䅅杢㕂䙁䄸睓求䡁䅫睕あ䝁䅅䅤穂䙁䄸杤硁䍁䄴䅥獂䡁䅍兢摂䕁䅳党㕂䙁䄸睕あ䝁䅅䅤穂䍁䅅䅊䙂䍁䅑杍祁䑁䅯䅊䩂䍁䅑杍祁䅁䅁儸䅍䝁䅉䅁扂䕁䅳党㕂䙁䅍䅤桂䡁䅑督時䡁䅑党穂䡁䅑杚灂䝁䅷党畁䡁䅧䅢穂䝁䄰兘䑂䝁䅅䅣灂䡁䅑兙獂䝁䅫来桂䡁䅑兡療䝁䄴光歁䕁䅙䅊ㅁ䑁䅯䅊䱂䍁䅑兎䅁乁䅁䅁慂䅁䅁睗䱂䝁䅕入呂䡁䅑兙あ䡁䅍睘あ䝁䅕督あ䝁䅙兡獂䝁䅕杌㑂䝁䅷督瑂䙁䄰睑桂䡁䅍䅡時䕁䅙䅢療䡁䅣光歁䕁䅑䅊㕁䑁䅯䅊䕂䍁䅑兏睁䅁䅁睶䅁䙁䅧䅁扂䕁䅳党㕂䙁䅍䅤桂䡁䅑督時䡁䅑党穂䡁䅑杚灂䝁䅷党畁䡁䅧䅢穂䝁䄰兘䑂䝁䅅督潂䙁䄸杒獂䝁䄸睤桁䍁䅑杒歁䑁䅕杏歁䙁䅅䅊ㅁ䅁䅁䅷䅁䙁䅁䅁扂䕁䄰兓時䕁䅳党㕂䙁䅍䅤桂䡁䅑督時䡁䅙免畁䡁䅧䅢穂䝁䄰兘卂䝁䅅䅤灂䝁䄸督桁䍁䅑睑歁䑁䅫杏歁䕁䅍䅊硁䑁䅑兏䅁䱁䑉䅁捂䅁䅁睗䱂䝁䅕入呂䡁䅑兙あ䡁䅍睘あ䝁䅕督あ䝁䅙兡獂䝁䅕杌㑂䝁䅷督瑂䙁䄰兓畂䝁䅍睢瑂䝁䅕睘呂䡁䅑兙あ䝁䅕兢求䝁䄴䅤桁䍁䅑睑歁䑁䅑䅁㑃䅁䅁杖䅁䙁䅳睕兂䕁䅣睘䑂䝁䄸兢睂䝁䅅杢㕂䙁䄸睓求䡁䅫睕あ䝁䅅䅤穂䙁䄸杤祁䍁䄴䅥獂䡁䅍兢摂䙁䅍䅡求䝁䅕䅤硁䍁䅅䅊䥂䍁䅑䅎穁䅁䅁兲䅙䝁䅯䅁扂䕁䅳党㕂䙁䅍䅤桂䡁䅑督時䡁䅑党穂䡁䅑杚灂䝁䅷党畁䡁䅧䅢穂䝁䄰兘䩂䝁䄴睙療䝁䄰党時䙁䅍䅤桂䡁䅑党瑂䝁䅕杢あ䍁䅅䅊䕂䍁䅑兏㙁䍁䅑䅒歁䑁䅅兎㑁䅁䅁党䅍䝁䅧䅁扂䕁䅳党㕂䙁䅍䅤桂䡁䅑督時䡁䅑党穂䡁䅑杚灂䝁䅷党畁䡁䅧䅢穂䝁䄰兘䩂䝁䄴睙療䝁䄰党時䙁䅍䅤桂䡁䅑党瑂䝁䅕杢あ䍁䅅䅊䕂䍁䅑兏㙁䍁䅑䅒歁䑁䅍睍䅁䱁䅯䅁浂䅁䅁睗䱂䝁䅕入呂䡁䅑兙あ䡁䅍睘あ䝁䅕督あ䝁䅙兡獂䝁䅕杌㑂䝁䅷督瑂䙁䄰兓畂䝁䅍睢瑂䝁䅕睘呂䡁䅑兙あ䝁䅕兢求䝁䄴䅤桁䍁䅑杒歁䑁䅑杏歁䙁䅅䅊ぁ䅁䅁兵䅁䝁䅙䅁扂䕁䅳党㕂䙁䅍䅤桂䡁䅑督時䡁䅑党穂䡁䅑杚灂䝁䅷党畁䡁䅧䅢穂䝁䄰兘䩂䝁䄴睙療䝁䄰党時䙁䅍䅤桂䡁䅑党瑂䝁䅕杢あ䍁䅅䅊䝂䍁䅑兎㙁䍁䅑兕歁䑁䅕䅁㝃䅁䅁䅏䅁䕁䄸䅣あ䝁䅫睢畂䡁䅍杏呂䡁䅑兙あ䝁䅫督あ䝁䅫睙㥁䕁䅅杖䡂䍁䅷杔䉂䑁䄰杔䉂䅁䅁䄰䅣䭁䅁䅁湁䙁䅳睑療䡁䅁入杁䝁䄸杚杁䙁䅍䅕䡂䙁䄸睑療䝁䄰䅣桂䝁䄴入時䕁䅳党㕂䙁䅍䅤桂䡁䅑督時䡁䅙免時䕁䅙兡畂䝁䅅䅢畁䡁䅧䅢穂䝁䄰兘䑂䝁䅅䅣灂䡁䅑兙獂䙁䄸睕あ䡁䅉兤橂䡁䅑兤祂䝁䅕睘杁䕁䅑党あ䝁䅅兡獂䡁䅍䅉湁䍁䅅䅊䕂䍁䅑䅎ぁ䅁䅁睥䅧䙁䅁䅁扂䕁䅳党㕂䙁䅍䅤桂䡁䅑督時䡁䅑党穂䡁䅑杚灂䝁䅷党畁䡁䅧䅢穂䝁䄰兘䱂䝁䅕入時䙁䅍䅤桂䡁䅑督桁䍁䅑村歁䑁䅉睍䅁䩁䅫䅁祂䅁䅁睗乂䕁䅫睘䱂䝁䅕入呂䡁䅑兙あ䡁䅍睘㉂䑁䅅杌㑂䝁䅷督瑂䙁䄰睑桂䡁䅁兡あ䝁䅅䅢時䙁䅍䅤祂䡁䅕睙あ䡁䅕杣求䙁䄸睕ㅂ䝁䄰兢桂䡁䅉入桁䍁䅑睒歁䑁䅧杏歁䕁䄸䅊㑁䅁䅁䅧䅍䝁䅷䅁扂䙁䅍䅕䡂䙁䄸睑療䝁䄰䅣桂䝁䄴入時䕁䅳党㕂䙁䅍䅤桂䡁䅑督時䡁䅙免畁䡁䅧䅢穂䝁䄰兘䍂䝁䅅䅢桂䝁䄴睙求䙁䄸睕潂䝁䅕党あ䍁䅅䅊䙂䍁䅑睎㙁䍁䅑䅕歁䑁䅣䅁牄兂䅁杩䅁䍁䅣睗䑂䝁䄸䅣㕂䍁䅁睢浂䍁䅁睕兂䕁䅣睘䑂䝁䄸兢睂䝁䅅杢㕂䙁䄸睓求䡁䅫睕あ䝁䅅䅤穂䙁䄸杤硁䙁䄸杒灂䝁䄴兙獂䍁䄴䅥獂䡁䅍兢摂䕁䅍兙穂䝁䅧睘䝂䝁䅷睢㍂䍁䅣光歁䕁䅍䅊硁䑁䅅杏歁䕁䅍䅊硁䑁䅁免䅁䝁䥅䅁䥃䅁䅁睊扂䕁䅍睢睂䡁䅫䅉療䝁䅙䅉呂䙁䅁睒時䕁䅍睢瑂䡁䅁兙畂䡁䅫睘䱂䝁䅕入呂䡁䅑兙あ䡁䅍睘㉂䑁䅉睘畂䝁䅕睤畁䡁䅧䅢穂䝁䄰兘䱂䝁䅕入時䙁䅍䅤桂䡁䅑督湁䍁䅅䅊䝂䍁䅑免睁䑁䅙杏歁䕁䅧䅊硁䑁䅁李䅁䑁䡣䅁兂䅁䅁睗䱂䝁䅕入呂䡁䅑兙あ䡁䅍睘あ䝁䅕督あ䝁䅙兡獂䝁䅕杌㑂䝁䅷督瑂䙁䄰睓求䡁䅫睘呂䡁䅑兙あ䡁䅍光歁䕁䅉䅊ㅁ䑁䅍䅁桃䅁䅁杖䅁䙁䅳睓求䡁䅫睕あ䝁䅅䅤穂䙁䄸䅤求䡁䅍䅤浂䝁䅫䅢求䍁䄴䅥獂䡁䅍䅥摂䙁䅍䅡求䝁䅕䅤硁䍁䅅䅊䭂䍁䅑杍穁䑁䅯䅊䵂䍁䅑杍穁䅁䅁䅔䅁䙁䅁䅁扂䕁䅳党㕂䙁䅍䅤桂䡁䅑督時䡁䅑党穂䡁䅑杚灂䝁䅷党畁䡁䅧䅢穂䝁䄰兘䱂䝁䅕入時䙁䅍䅤桂䡁䅑督桁䍁䅑村歁䑁䅕兏䅁佁䅅䅁兂䅁䅁睗䱂䝁䅕入呂䡁䅑兙あ䡁䅍睘あ䝁䅕督あ䝁䅙兡獂䝁䅕杌㑂䝁䅷督瑂䙁䄰睓求䡁䅫睘呂䡁䅑兙あ䡁䅍光歁䕁䅉䅊㕁䑁䅧䅁灄䅁䅁䅙䅁䙁䅳睓求䡁䅫睕あ䝁䅅䅤穂䙁䄸䅤求䡁䅍䅤浂䝁䅫䅢求䍁䄴䅥獂䡁䅍兢摂䕁䅳党㕂䙁䄸睕あ䝁䅅䅤穂䍁䅅䅊䑂䍁䅑免睁䑁䅁杏歁䕁䅍䅊硁䑁䅁䅎䅁䩁䅑䅁杂䅁䅁睗䱂䝁䅕入呂䡁䅑兙あ䡁䅍睘あ䝁䅕督あ䝁䅙兡獂䝁䅕杌㑂䝁䅷督瑂䙁䄰睓求䡁䅫睘呂䡁䅑兙あ䡁䅍光歁䕁䅍䅊硁䑁䅁免㙁䍁䅑睑歁䑁䅅䅍ㅁ䅁䅁朶䅁䙁䅷䅁扂䕁䅳党㕂䙁䅍䅤桂䡁䅑督時䡁䅑党穂䡁䅑杚灂䝁䅷党畁䡁䅧䅢穂䝁䄰兘䱂䝁䅕入時䙁䅍䅤桂䡁䅑督桁䍁䅑睑歁䑁䅉兎㙁䍁䅑睑歁䑁䅑兏䅁䩁䅣䅁捂䅁䅁睗䱂䝁䅕入呂䡁䅑兙あ䡁䅍睘あ䝁䅕督あ䝁䅙兡獂䝁䅕杌㑂䝁䅷督瑂䙁䄰睓求䡁䅫睘呂䡁䅑兙あ䡁䅍光歁䕁䅍䅊㉁䑁䅅杏歁䕁䅍䅊㉁䑁䅣䅁橄䅁䅁杗䅁䙁䅳兔䩂䙁䄸睑療䝁䄰䅣桂䝁䄴入時䕁䅳党㕂䙁䅍䅤桂䡁䅑督時䡁䅙免畁䡁䅧䅢穂䝁䄰兘䱂䝁䅕入時䙁䅍䅤桂䡁䅑督桁䍁䅑兒歁䑁䅕兎䅁䱁䕁䅁歂䅁䅁睗乂䕁䅫睘䑂䝁䄸兢睂䝁䅅杢㕂䙁䄸睓求䡁䅫睕あ䝁䅅䅤穂䙁䄸杤硁䙁䄸杌㑂䝁䅷督瑂䙁䄰睑桂䡁䅍䅡時䕁䅙䅢療䡁䅣光歁䕁䅕䅊ぁ䑁䅯䅊兂䍁䅑䅎䅁佁䕉䅁捂䅁䅁睗䱂䝁䅕入呂䡁䅑兙あ䡁䅍睘あ䝁䅕督あ䝁䅙兡獂䝁䅕杌㑂䝁䅷督瑂䙁䄰睓求䡁䅫睘呂䡁䅑兙あ䡁䅍光歁䕁䅑䅊ㅁ䑁䅕杏歁䕁䅑䅊ㅁ䑁䅙䅁塄䅁䅁䅘䅁䙁䅳睓求䡁䅫睕あ䝁䅅䅤穂䙁䄸䅤求䡁䅍䅤浂䝁䅫䅢求䍁䄴䅥獂䡁䅍兢摂䕁䅳党㕂䙁䄸睕あ䝁䅅䅤穂䍁䅅䅊䙂䍁䅑杍祁䑁䅯䅊䩂䍁䅑杍祁䅁䅁杬䅁䙁䅷䅁扂䕁䅳党㕂䙁䅍䅤桂䡁䅑督時䡁䅑党穂䡁䅑杚灂䝁䅷党畁䡁䅧䅢穂䝁䄰兘䱂䝁䅕入時䙁䅍䅤桂䡁䅑督桁䍁䅑兒歁䑁䅉睍㙁䍁䅑兓歁䑁䅉睍䅁䩁䅧䅁兂䅁䅁睗䱂䝁䅕入呂䡁䅑兙あ䡁䅍睘あ䝁䅕督あ䝁䅙兡獂䝁䅕杌㑂䝁䅷督瑂䙁䄰睓求䡁䅫睘呂䡁䅑兙あ䡁䅍光歁䕁䅕䅊ㅁ䑁䅉䅁敃䅁䅁䅕䅁䙁䅳睓求䡁䅫睕あ䝁䅅䅤穂䙁䄸䅤求䡁䅍䅤浂䝁䅫䅢求䍁䄴䅥獂䡁䅍兢摂䕁䅳党㕂䙁䄸睕あ䝁䅅䅤穂䍁䅅䅊䙂䍁䅑兎穁䅁䅁䅯䅁䙁䅁䅁扂䕁䅳党㕂䙁䅍䅤桂䡁䅑督時䡁䅑党穂䡁䅑杚灂䝁䅷党畁䡁䅧䅢穂䝁䄰兘䱂䝁䅕入時䙁䅍䅤桂䡁䅑督桁䍁䅑兒歁䑁䅙䅍䅁佁䅑䅁捂䅁䅁睗䱂䝁䅕入呂䡁䅑兙あ䡁䅍睘あ䝁䅕督あ䝁䅙兡獂䝁䅕杌㑂䝁䅷督瑂䙁䄰睓求䡁䅫睘呂䡁䅑兙あ䡁䅍光歁䕁䅯䅊祁䑁䅉杏歁䕁䅷䅊祁䑁䅉䅁慃䅁䅁杖䅁䙁䅳睓求䡁䅫睕あ䝁䅅䅤穂䙁䄸䅤求䡁䅍䅤浂䝁䅫䅢求䍁䄴䅥獂䡁䅍兢摂䙁䅉兙あ䝁䅫睢穂䍁䅅䅊䕂䍁䅑兏㙁䍁䅑䅒歁䑁䅅䅎㕁䅁䅁关䅉䙁䅉䅁扂䕁䅳党㕂䙁䅍䅤桂䡁䅑督時䡁䅑党穂䡁䅑杚灂䝁䅷党畁䡁䅧䅢穂䝁䄰兘卂䝁䅅䅤灂䝁䄸督桁䍁䅑杒歁䑁䅕杏歁䕁䅳䅊ㅁ䅁䅁朹䅅䕁䅯䅁扂䕁䅳党㕂䙁䅍䅤桂䡁䅑督時䡁䅑党穂䡁䅑杚灂䝁䅷党畁䡁䅧䅢穂䝁䄰兘呂䝁䅧党求䡁䅑免桁䍁䅑村歁䑁䅉杍䅁䡁䅳䅁䭂䅁䅁睗䱂䝁䅕入呂䡁䅑兙あ䡁䅍睘あ䝁䅕督あ䝁䅙兡獂䝁䅕杌㑂䝁䅷督瑂䙁䄰睕潂䝁䅕党あ䑁䅅光歁䕁䅉䅊祁䑁䅍䅁䍃䅁䅁杣䅁䙁䅳兔䩂䙁䄸睓求䡁䅫睕あ䝁䅅䅤穂䙁䄸杤硁䍁䄴䅥獂䡁䅍兢摂䕁䅍兙睂䝁䅫䅤桂䝁䅷睘呂䡁䅑杣ㅂ䝁䅍䅤ㅂ䡁䅉党時䙁䅍兤瑂䝁䄰兙祂䡁䅫光歁䕁䅣䅊㕁䑁䅯䅊偂䍁䅑兏䅁䥁䑉䅁坂䅁䅁睗䱂䝁䅕入呂䡁䅑兙あ䡁䅍睘あ䝁䅕督あ䝁䅙兡獂䝁䅕杌㑂䝁䅷督瑂䙁䄰睕潂䝁䅕党あ䑁䅅光歁䕁䅍䅊ㅁ䑁䅕杏歁䕁䅍䅊ㅁ䑁䅙䅁䉃䅁䅁杖䅁䙁䅳睓求䡁䅫睕あ䝁䅅䅤穂䙁䄸䅤求䡁䅍䅤浂䝁䅫䅢求䍁䄴䅥獂䡁䅍兢摂䙁䅍䅡求䝁䅕䅤硁䍁䅅䅊䑂䍁䅑李睁䑁䅯䅊䑂䍁䅑李㉁䅁䅁睨䅁䙁䅙䅁扂䕁䅳党㕂䙁䅍䅤桂䡁䅑督時䡁䅑党穂䡁䅑杚灂䝁䅷党畁䡁䅧䅢穂䝁䄰兘呂䝁䅧党求䡁䅑免桁䍁䅑䅒歁䑁䅉兎㙁䍁䅑䅒歁䑁䅑兏䅁䥁䅑䅁坂䅁䅁睗䱂䝁䅕入呂䡁䅑兙あ䡁䅍睘あ䝁䅕督あ䝁䅙兡獂䝁䅕杌㑂䝁䅷督瑂䙁䄰睕潂䝁䅕党あ䑁䅅光歁䕁䅕䅊祁䑁䅉杏歁䕁䅧䅊祁䑁䅉䅁㡂䅁䅁杖䅁䙁䅳睓求䡁䅫睕あ䝁䅅䅤穂䙁䄸䅤求䡁䅍䅤浂䝁䅫䅢求䍁䄴䅥獂䡁䅍兢摂䙁䅍䅡求䝁䅕䅤硁䍁䅅䅊䙂䍁䅑杍祁䑁䅯䅊䩂䍁䅑杍祁䅁䅁杪䅁䙁䅙䅁扂䕁䅳党㕂䙁䅍䅤桂䡁䅑督時䡁䅑党穂䡁䅑杚灂䝁䅷党畁䡁䅧䅢穂䝁䄰兘呂䝁䅧党求䡁䅑免桁䍁䅑兒歁䑁䅉睍㙁䍁䅑䅓歁䑁䅉睍䅁䡁䄴䅁坂䅁䅁睗䱂䝁䅕入呂䡁䅑兙あ䡁䅍睘あ䝁䅕督あ䝁䅙兡獂䝁䅕杌㑂䝁䅷督瑂䙁䄰睕潂䝁䅕党あ䑁䅅光歁䕁䅕䅊祁䑁䅍杏歁䕁䅫䅊祁䑁䅍䅁偃䅁䅁杖䅁䙁䅳兔䩂䙁䄸睓求䡁䅫睕あ䝁䅅䅤穂䙁䄸杤硁䍁䄴䅥獂䡁䅍兢摂䕁䅳党㕂䙁䄸睕あ䝁䅅䅤穂䍁䅅䅊䑂䍁䅑杍ㅁ䑁䅯䅊䑂䍁䅑䅎㕁䅁䅁睡䅍䕁䅯䅁扂䕁䅳党㕂䙁䅍䅤桂䡁䅑督時䡁䅑党穂䡁䅑杚灂䝁䅷党畁䡁䅧䅢穂䝁䄰兘呂䝁䅧党求䡁䅑免桁䍁䅑兒歁䑁䅕睍䅁䥁䅧䅁祂䅁䅁睗乂䕁䅫睘䱂䝁䅕入呂䡁䅑兙あ䡁䅍睘㉂䑁䅅杌㑂䝁䅷督瑂䙁䄰睑桂䡁䅁兡あ䝁䅅䅢時䙁䅍䅤祂䡁䅕睙あ䡁䅕杣求䙁䄸睕ㅂ䝁䄰兢桂䡁䅉入桁䍁䅑杒歁䑁䅧杏歁䙁䅁䅊㑁䅁䅁朷䅍䙁䅙䅁扂䕁䅳党㕂䙁䅍䅤桂䡁䅑督時䡁䅑党穂䡁䅑杚灂䝁䅷党畁䡁䅧䅢穂䝁䄰兘呂䝁䅧党求䡁䅑免桁䍁䅑杒歁䑁䅉睍㙁䍁䅑兓歁䑁䅉睍䅁䥁䅳䅁歂䅁䅁睗乂䕁䅫睘䑂䝁䄸兢睂䝁䅅杢㕂䙁䄸睓求䡁䅫睕あ䝁䅅䅤穂䙁䄸杤硁䍁䄴䅥獂䡁䅍兢摂䕁䅍兙睂䝁䅫䅤桂䝁䅷兡㙂䝁䅅䅤灂䝁䄸杢桁䍁䅑睑歁䑁䅕䅍䅁䉁䕙䅁坂䅁䅁睗䱂䝁䅕入呂䡁䅑兙あ䡁䅍睘あ䝁䅕督あ䝁䅙兡獂䝁䅕杌㑂䝁䅷督瑂䙁䄰睕潂䝁䅕党あ䑁䅅光歁䕁䅫䅊祁䑁䅍杏歁䕁䅳䅊祁䑁䅍䅁䙃䅁䅁杖䅁䙁䅳睓求䡁䅫睕あ䝁䅅䅤穂䙁䄸䅤求䡁䅍䅤浂䝁䅫䅢求䍁䄴䅥獂䡁䅍兢摂䙁䅍䅡求䝁䅕䅤硁䍁䅅䅊䭂䍁䅑杍祁䑁䅯䅊䵂䍁䅑杍祁䅁䅁䅪䅁䥁䅉䅁扂䕁䄰兓時䕁䅍睢瑂䡁䅁兙畂䡁䅫睘䱂䝁䅕入呂䡁䅑兙あ䡁䅍睘㉂䑁䅅杌㑂䝁䅷督瑂䙁䄰睑桂䡁䅁兡あ䝁䅅䅢時䙁䅍䅤祂䡁䅕睙あ䡁䅕杣求䙁䄸睕ㅂ䝁䄰兢桂䡁䅉入桁䍁䅑兒歁䑁䅣杏歁䕁䄸䅊㍁䅁䅁睶䅕䙁䅑䅁扂䕁䅳党㕂䙁䅍䅤桂䡁䅑督時䡁䅑党穂䡁䅑杚灂䝁䅷党畁䡁䅧䅢穂䝁䄰兘呂䡁䅕䅣睂䝁䅷党瑂䝁䅕杢あ䝁䅅䅢桁䍁䅑睑歁䑁䅑䅁敂睁䅁杙䅁䙁䅳睓求䡁䅫睕あ䝁䅅䅤穂䙁䄸䅤求䡁䅍䅤浂䝁䅫䅢求䍁䄴䅥獂䡁䅍兢摂䙁䅍兤睂䡁䅁䅢求䝁䄰党畂䡁䅑兙獂䍁䅅䅊䕂䍁䅑兏㙁䍁䅑䅒歁䑁䅅李ㅁ䅁䅁杙䅍䥁䅑䅁扂䙁䅍䅕䡂䙁䄸睑療䝁䄰䅣桂䝁䄴入時䕁䅳党㕂䙁䅍䅤桂䡁䅑督時䡁䅙免畁䡁䅧䅢穂䝁䄰兘䑂䝁䅅䅣灂䡁䅑兙獂䙁䄸睕あ䡁䅉兤橂䡁䅑兤祂䝁䅕睘呂䡁䅕兢瑂䝁䅅杣㕂䍁䅅䅊䙂䍁䅑李㙁䍁䅑睔歁䑁䅙䅁㥄兂䅁杘䅁䙁䅳睓求䡁䅫睕あ䝁䅅䅤穂䙁䄸䅤求䡁䅍䅤浂䝁䅫䅢求䍁䄴䅥獂䡁䅍兢摂䙁䅍兤睂䡁䅁䅢求䝁䄰党畂䡁䅑兙獂䍁䅅䅊䝂䍁䅑兎㙁䍁䅑睓歁䑁䅕䅁桂睁䅁杓䅁䙁䅳睓求䡁䅫睕あ䝁䅅䅤穂䙁䄸䅤求䡁䅍䅤浂䝁䅫䅢求䍁䄴䅥獂䡁䅍䅥摂䙁䅍䅡求䝁䅕䅤硁䍁䅅䅊䍂䍁䅑杍ぁ䅁䅁䅗䅁䝁䅑䅁扂䙁䅍䅕䡂䙁䄸睑療䝁䄰䅣桂䝁䄴入時䕁䅳党㕂䙁䅍䅤桂䡁䅑督時䡁䅙杍畁䡁䅧䅢穂䝁䄰兘乂䡁䅕䅢あ䝁䅫䅣獂䝁䅕督桁䍁䅑兒歁䑁䅣杏歁䕁䅷䅊㍁䅁䅁睢䅙䕁䅯䅁扂䕁䅳党㕂䙁䅍䅤桂䡁䅑督時䡁䅑党穂䡁䅑杚灂䝁䅷党畁䡁䅧䅢穂䡁䅧兘呂䝁䅧党求䡁䅑免桁䍁䅑村歁䑁䅕睍䅁䡁䅣䅁坂䅁䅁睗䱂䝁䅕入呂䡁䅑兙あ䡁䅍睘あ䝁䅕督あ䝁䅙兡獂䝁䅕杌㑂䝁䅷督㑂䙁䄰睕潂䝁䅕党あ䑁䅅光歁䕁䅍䅊祁䑁䅑杏歁䕁䅍䅊穁䑁䅫䅁⽁䅁䅁杖䅁䙁䅳睓求䡁䅫睕あ䝁䅅䅤穂䙁䄸䅤求䡁䅍䅤浂䝁䅫䅢求䍁䄴䅥獂䡁䅍䅥摂䙁䅍䅡求䝁䅕䅤硁䍁䅅䅊䑂䍁䅑杍ㅁ䑁䅯䅊䑂䍁䅑䅎㕁䅁䅁来䅁䥁䅷䅁湁䙁䅳睑療䡁䅁入杁䝁䄸杚杁䙁䅍䅕䡂䙁䄸睑療䝁䄰䅣桂䝁䄴入時䕁䅳党㕂䙁䅍䅤桂䡁䅑督時䡁䅙杍時䝁䄴党㍂䍁䄴䅥獂䡁䅍兢摂䙁䅍兤睂䡁䅁䅢求䝁䄰党畂䡁䅑兙獂䍁䅣光歁䕁䅍䅊硁䑁䅅杏歁䕁䅍䅊硁䑁䅙李䅁䵁䡣䅁啃䅁䅁睊扂䕁䅍睢睂䡁䅫䅉療䝁䅙䅉呂䙁䅁睒時䕁䅍睢瑂䡁䅁兙畂䡁䅫睘䱂䝁䅕入呂䡁䅑兙あ䡁䅍睘㉂䑁䅉睘畂䝁䅕睤畁䡁䅧䅢穂䝁䄰兘䩂䝁䄴睙療䝁䄰党時䙁䅍䅤桂䡁䅑党瑂䝁䅕杢あ䍁䅣光歁䕁䅍䅊硁䑁䅅杏歁䕁䅍䅊硁䑁䅫䅏䅁䕁䡁䅁坂䅁䅁睗䱂䝁䅕入呂䡁䅑兙あ䡁䅍睘あ䝁䅕督あ䝁䅙兡獂䝁䅕杌㑂䝁䅷督㑂䙁䄰睕潂䝁䅕党あ䑁䅅光歁䕁䅍䅊祁䑁䅕杏歁䕁䅍䅊㉁䑁䅣䅁啂䅁䅁杖䅁䙁䅳睓求䡁䅫睕あ䝁䅅䅤穂䙁䄸䅤求䡁䅍䅤浂䝁䅫䅢求䍁䄴䅥獂䡁䅍䅥摂䙁䅍䅡求䝁䅕䅤硁䍁䅅䅊䑂䍁䅑兎ㅁ䑁䅯䅊䑂䍁䅑兎㉁䅁䅁杗䅁䙁䅙䅁扂䕁䅳党㕂䙁䅍䅤桂䡁䅑督時䡁䅑党穂䡁䅑杚灂䝁䅷党畁䡁䅧䅢穂䡁䅧兘呂䝁䅧党求䡁䅑免桁䍁䅑睑歁䑁䅕兎㙁䍁䅑睑歁䑁䅙䅏䅁䡁䅍䅁䭂䅁䅁睗䱂䝁䅕入呂䡁䅑兙あ䡁䅍睘あ䝁䅕督あ䝁䅙兡獂䝁䅕杌㑂䝁䅷督㑂䙁䄰睕潂䝁䅕党あ䑁䅅光歁䕁䅑䅊祁䑁䅑䅁癁䅁䅁杓䅁䙁䅳睓求䡁䅫睕あ䝁䅅䅤穂䙁䄸䅤求䡁䅍䅤浂䝁䅫䅢求䍁䄴䅥獂䡁䅍䅥摂䙁䅍䅡求䝁䅕䅤硁䍁䅅䅊䙂䍁䅑兎祁䅁䅁兤䅁䙁䅙䅁扂䕁䅳党㕂䙁䅍䅤桂䡁䅑督時䡁䅑党穂䡁䅑杚灂䝁䅷党畁䡁䅧䅢穂䡁䅧兘呂䝁䅧党求䡁䅑免桁䍁䅑䅒歁䑁䅉兎㙁䍁䅑䅒歁䑁䅍䅍䅁䕁䅳䅁坂䅁䅁睗䱂䝁䅕入呂䡁䅑兙あ䡁䅍睘あ䝁䅕督あ䝁䅙兡獂䝁䅕杌㑂䝁䅷督㑂䙁䄰睕潂䝁䅕党あ䑁䅅光歁䕁䅑䅊祁䑁䅕杏歁䕁䅑䅊ぁ䑁䅫䅁塂䅁䅁杖䅁䙁䅳睓求䡁䅫睕あ䝁䅅䅤穂䙁䄸䅤求䡁䅍䅤浂䝁䅫䅢求䍁䄴䅥獂䡁䅍䅥摂䙁䅍䅡求䝁䅕䅤硁䍁䅅䅊䕂䍁䅑兎ㅁ䑁䅯䅊䕂䍁䅑兎㉁䅁䅁睗䅁䅁䅯䅁䉂䕁䄰杗佂䅁䅁䄳䅣䥁䅧䅁扂䕁䄰兓時䕁䅍睢瑂䡁䅁兙畂䡁䅫睘䱂䝁䅕入呂䡁䅑兙あ䡁䅍睘㉂䑁䅅杌㑂䝁䅷督瑂䙁䄰睑桂䡁䅁兡あ䝁䅅䅢時䙁䅍䅤祂䡁䅕睙あ䡁䅕杣求䙁䄸睕ㅂ䝁䄰兢桂䡁䅉入桁䍁䅑睑歁䑁䅅睍㙁䍁䅑睑歁䑁䅅兎睁䅁䅁杈䅑䙁䅙䅁扂䕁䅳党㕂䙁䅍䅤桂䡁䅑督時䡁䅑党穂䡁䅑杚灂䝁䅷党畁䡁䅧䅢穂䡁䅧兘呂䝁䅧党求䡁䅑免桁䍁䅑兒歁䑁䅉䅍㙁䍁䅑睒歁䑁䅉䅍䅁䑁䅉䅁坂䅁䅁睗䱂䝁䅕入呂䡁䅑兙あ䡁䅍睘あ䝁䅕督あ䝁䅙兡獂䝁䅕杌㑂䝁䅷督㑂䙁䄰睕潂䝁䅕党あ䑁䅅光歁䕁䅕䅊祁䑁䅁杏歁䕁䅫䅊祁䑁䅁䅁䑂䅁䅁䅘䅁䙁䅳睕兂䕁䅣睘䑂䝁䄸兢睂䝁䅅杢㕂䙁䄸睓求䡁䅫睕あ䝁䅅䅤穂䙁䄸杤祁䍁䄴䅥獂䡁䅍兢摂䕁䅳党㕂䙁䄸睕あ䝁䅅䅤穂䍁䅅䅊䝂䍁䅑免ㅁ䅁䅁䅨䅙䙁䅙䅁扂䕁䅳党㕂䙁䅍䅤桂䡁䅑督時䡁䅑党穂䡁䅑杚灂䝁䅷党畁䡁䅧䅢穂䡁䅧兘呂䝁䅧党求䡁䅑免桁䍁䅑兒歁䑁䅉免㙁䍁䅑䅓歁䑁䅉免䅁䑁䅧䅁睂䅁䅁睗乂䕁䅫睘䑂䝁䄸兢睂䝁䅅杢㕂䙁䄸睓求䡁䅫睕あ䝁䅅䅤穂䙁䄸杤硁䍁䄴䅥獂䡁䅍兢摂䕁䅍兙睂䝁䅫䅤桂䝁䅷兡㙂䝁䅅䅤灂䝁䄸杢桁䍁䅑兒歁䑁䅑䅏㙁䍁䅑䅕歁䑁䅑䅏䅁䉁䕣䅁坂䅁䅁睗䱂䝁䅕入呂䡁䅑兙あ䡁䅍睘あ䝁䅕督あ䝁䅙兡獂䝁䅕杌㑂䝁䅷督㑂䙁䄰睕潂䝁䅕党あ䑁䅅光歁䕁䅙䅊祁䑁䅁杏歁䕁䅧䅊祁䑁䅁䅁ぁ䅁䅁杖䅁䙁䅳睓求䡁䅫睕あ䝁䅅䅤穂䙁䄸䅤求䡁䅍䅤浂䝁䅫䅢求䍁䄴䅥獂䡁䅍䅥摂䙁䅍䅡求䝁䅕䅤硁䍁䅅䅊䝂䍁䅑杍硁䑁䅯䅊䥂䍁䅑杍硁䅁䅁兎䅁䙁䅙䅁扂䕁䅳党㕂䙁䅍䅤桂䡁䅑督時䡁䅑党穂䡁䅑杚灂䝁䅷党畁䡁䅧䅢穂䡁䅧兘呂䝁䅧党求䡁䅑免桁䍁䅑杓歁䑁䅉䅍㙁䍁䅑䅔歁䑁䅉䅍䅁䕁䅅䅁㑂䅁䅁睊扂䕁䅍睢睂䡁䅫䅉療䝁䅙䅉呂䙁䅁睒時䕁䅍睢瑂䡁䅁兙畂䡁䅫睘䱂䝁䅕入呂䡁䅑兙あ䡁䅍睘㉂䑁䅉睘畂䝁䅕睤畁䡁䅧䅢穂䝁䄰兘䱂䝁䅕入時䙁䅍䅤桂䡁䅑督湁䍁䅅䅊䍂䍁䅑杍㉁䅁䅁杋䅣䙁䅙䅁扂䕁䅳党㕂䙁䅍䅤桂䡁䅑督時䡁䅑党穂䡁䅑杚灂䝁䅷党畁䡁䅧䅢穂䡁䅧兘呂䝁䅧党求䡁䅑免桁䍁䅑杓歁䑁䅉免㙁䍁䅑䅔歁䑁䅉免䅁䕁䅉䅁啂䅁䅁睗䱂䝁䅕入呂䡁䅑兙あ䡁䅍睘あ䝁䅕督あ䝁䅙兡獂䝁䅕杌㑂䝁䅷督㑂䙁䄰睕潂䝁䅕党あ䑁䅉光歁䕁䅕䅊㕁䑁䅯䅊䙂䍁䅑免硁䅁䅁睋䅁䙁䅉䅁扂䕁䅳党㕂䙁䅍䅤桂䡁䅑督時䡁䅑党穂䡁䅑杚灂䝁䅷党畁䡁䅧䅢穂䡁䅧兘呂䝁䅧党求䡁䅑杍桁䍁䅑睒歁䑁䅣杏歁䕁䅫䅊㍁䅁䅁睊䅁䡁䅁䅁扂䕁䄰兓時䕁䅍睢瑂䡁䅁兙畂䡁䅫睘䱂䝁䅕入呂䡁䅑兙あ䡁䅍睘㉂䑁䅅杌㑂䝁䅷督瑂䙁䄰村桂䝁䅷兙畂䝁䅍党時䙁䅍䅡求䝁䅕䅤桁䍁䅑睑歁䑁䅅免㙁䍁䅑睑歁䑁䅅䅎硁䅁䅁杴䅕䝁䅑䅁扂䕁䄰兓時䕁䅍睢瑂䡁䅁兙畂䡁䅫睘䱂䝁䅕入呂䡁䅑兙あ䡁䅍睘㉂䑁䅅杌㑂䝁䅷督瑂䙁䄰村桂䝁䅷兙畂䝁䅍党時䙁䅍䅡求䝁䅕䅤桁䍁䅑睑歁䑁䅅䅎穁䅁䅁兰䅑䝁䅁䅁扂䕁䄰兓時䕁䅍睢瑂䡁䅁兙畂䡁䅫睘䱂䝁䅕入呂䡁䅑兙あ䡁䅍睘㉂䑁䅅杌㑂䝁䅷督瑂䙁䄰村桂䝁䅷兙畂䝁䅍党時䙁䅍䅡求䝁䅕䅤桁䍁䅑睑歁䑁䅙䅁ぃ兂䅁䅡䅁䙁䅳睕兂䕁䅣睘䑂䝁䄸兢睂䝁䅅杢㕂䙁䄸睓求䡁䅫睕あ䝁䅅䅤穂䙁䄸杤硁䍁䄴䅥獂䡁䅍兢摂䕁䅳党㕂䙁䄸睕あ䝁䅅䅤穂䍁䅅䅊啂䍁䅑兎㑁䑁䅯䅊啂䍁䅑李硁䅁䅁眴䅕䝁䄴䅁扂䕁䄰兓時䕁䅍睢瑂䡁䅁兙畂䡁䅫睘䱂䝁䅕入呂䡁䅑兙あ䡁䅍睘㉂䑁䅅杌㑂䝁䅷督瑂䙁䄰村桂䝁䅷兙畂䝁䅍党時䙁䅍䅡求䝁䅕䅤桁䍁䅑睑歁䑁䅫杏歁䕁䅍䅊硁䑁䅑免䅁䩁䔰䅁浂䅁䅁睗乂䕁䅫睘䑂䝁䄸兢睂䝁䅅杢㕂䙁䄸睓求䡁䅫睕あ䝁䅅䅤穂䙁䄸杤硁䍁䄴䅥獂䡁䅍兢摂䕁䅳党㕂䙁䄸睕あ䝁䅅䅤穂䍁䅅䅊䑂䍁䅑李祁䑁䅯䅊䑂䍁䅑李㑁䅁䅁杂䅕䡁䅉䅁扂䕁䄰兓時䕁䅍睢瑂䡁䅁兙畂䡁䅫睘䱂䝁䅕入呂䡁䅑兙あ䡁䅍睘㉂䑁䅅杌㑂䝁䅷督瑂䙁䄰村桂䝁䅷兙畂䝁䅍党時䙁䅍䅡求䝁䅕䅤桁䍁䅑兒歁䑁䅅䅎ぁ䑁䅯䅊兂䍁䅑免ぁ䑁䅑䅁潃䅂䅁䅚䅁䙁䅳兔䩂䙁䄸睓求䡁䅫睕あ䝁䅅䅤穂䙁䄸杤硁䍁䄴䅥獂䡁䅍兢摂䕁䅫杢橂䝁䄸兢求䙁䄸睕あ䝁䅅䅤求䝁䄰党畂䡁䅑光歁䕁䅍䅊㕁䑁䅯䅊䑂䍁䅑免㍁䑁䅕䅁歄睁䅁条䅁䙁䅳兔䩂䙁䄸睑療䝁䄰䅣桂䝁䄴入時䕁䅳党㕂䙁䅍䅤桂䡁䅑督時䡁䅙免畁䡁䅧䅢穂䝁䄰兘䍂䝁䅅䅢桂䝁䄴睙求䙁䄸睕潂䝁䅕党あ䍁䅅䅊䙂䍁䅑李㙁䍁䅑䅕歁䑁䅙䅁ㅃ兂䅁条䅁䙁䅳兔䩂䙁䄸睑療䝁䄰䅣桂䝁䄴入時䕁䅳党㕂䙁䅍䅤桂䡁䅑督時䡁䅙免畁䡁䅧䅢穂䝁䄰兘䱂䝁䅕入時䙁䅍䅤桂䡁䅑督桁䍁䅑兒歁䑁䅅䅍ㅁ䑁䅯䅊䡂䍁䅑免睁䑁䅕䅁噃䅂䅁䅥䅁䙁䅳兔䩂䙁䄸睑療䝁䄰䅣桂䝁䄴入時䕁䅳党㕂䙁䅍䅤桂䡁䅑督時䡁䅙免畁䡁䅧䅢穂䝁䄰兘䑂䝁䅅䅣灂䡁䅑兙獂䙁䄸睕あ䡁䅉兤橂䡁䅑兤祂䝁䅕睘呂䡁䅕兢瑂䝁䅅杣㕂䍁䅅䅊䑂䍁䅑䅎䅁䉁䕷䅁捂䅁䅁睗乂䕁䅫睘䱂䝁䅕入呂䡁䅑兙あ䡁䅍睘㉂䑁䅅杌㑂䝁䅷督瑂䙁䄰睕ㅂ䡁䅁䅣獂䝁䅕兢求䝁䄴䅤桂䝁䅷光歁䕁䅍䅊㕁䑁䅯䅊䑂䍁䅑免㉁䑁䅧䅁呃睁䅁杢䅁䙁䅳兔䩂䙁䄸睑療䝁䄰䅣桂䝁䄴入時䕁䅳党㕂䙁䅍䅤桂䡁䅑督時䡁䅙免時䍁䄴䅥獂䡁䅍兢摂䕁䅍兙睂䝁䅫䅤桂䝁䅷兡㙂䝁䅅䅤灂䝁䄸杢桁䍁䅑兒歁䑁䅕杏歁䕁䅯䅊ㅁ䅁䅁䄶䅑䡁䅧䅁扂䕁䄰兓時䕁䅍睢瑂䡁䅁兙畂䡁䅫睘䱂䝁䅕入呂䡁䅑兙あ䡁䅍睘㉂䑁䅅杌㑂䝁䅷督瑂䙁䄰睑桂䡁䅁兡あ䝁䅅䅢時䙁䅍䅤祂䡁䅕睙あ䡁䅕杣求䙁䄸睕ㅂ䝁䄰兢桂䡁䅉入桁䍁䅑睑歁䑁䅙䅁㡃兂䅁䅥䅁䙁䅳兔䩂䙁䄸睑療䝁䄰䅣桂䝁䄴入時䕁䅳党㕂䙁䅍䅤桂䡁䅑督時䡁䅙免畁䡁䅧䅢穂䝁䄰兘䑂䝁䅅䅣灂䡁䅑兙獂䙁䄸睕あ䡁䅉兤橂䡁䅑兤祂䝁䅕睘呂䡁䅕兢瑂䝁䅅杣㕂䍁䅅䅊䑂䍁䅑睎䅁䵁䙁䅁䝃䅁䅁睗乂䕁䅫睘䑂䝁䄸兢睂䝁䅅杢㕂䙁䄸睓求䡁䅫睕あ䝁䅅䅤穂䙁䄸杤硁䍁䄴䅥獂䡁䅍兢摂䕁䅍兙睂䝁䅫䅤桂䝁䅷睘呂䡁䅑杣ㅂ䝁䅍䅤ㅂ䡁䅉党時䙁䅍兤瑂䝁䄰兙祂䡁䅫光歁䕁䅑䅊祁䑁䅫杏歁䕁䅑䅊㑁䑁䅁䅁䍄兂䅁杧䅁䙁䅳兔䩂䙁䄸睑療䝁䄰䅣桂䝁䄴入時䕁䅳党㕂䙁䅍䅤桂䡁䅑督時䡁䅙免畁䡁䅧䅢穂䝁䄰兘䑂䝁䅅䅣灂䡁䅑兙獂䙁䄸睕あ䡁䅉兤橂䡁䅑兤祂䝁䅕睘呂䡁䅕兢瑂䝁䅅杣㕂䍁䅅䅊䙂䍁䅑兎㙁䍁䅑睔歁䑁䅕䅁晁䅂䅁杧䅁䙁䅳兔䩂䙁䄸睑療䝁䄰䅣桂䝁䄴入時䕁䅳党㕂䙁䅍䅤桂䡁䅑督時䡁䅙免畁䡁䅧䅢穂䝁䄰兘䑂䝁䅅䅣灂䡁䅑兙獂䙁䄸睕あ䡁䅉兤橂䡁䅑兤祂䝁䅕睘呂䡁䅕兢瑂䝁䅅杣㕂䍁䅅䅊䙂䍁䅑李㙁䍁䅑睔歁䑁䅙䅁㥃兂䅁杖䅁䙁䅳睕兂䕁䅣睘䑂䝁䄸兢睂䝁䅅杢㕂䙁䄸睓求䡁䅫睕あ䝁䅅䅤穂䙁䄸杤祁䍁䄴䅥獂䡁䅍兢摂䙁䅍䅡求䝁䅕䅤硁䍁䅅䅊䩂䍁䅑䅎穁䅁䅁杲䅙䙁䅧䅁扂䕁䄰兓時䕁䅳党㕂䙁䅍䅤桂䡁䅑督時䡁䅙免畁䡁䅧䅢穂䝁䄰兘呂䡁䅕䅣睂䝁䅷党瑂䝁䅕杢あ䝁䅅䅢桁䍁䅑䅒歁䑁䅑杏歁䕁䅫䅊ぁ䅁䅁杫䅍䥁䅙䅁扂䕁䄰兓時䕁䅍睢瑂䡁䅁兙畂䡁䅫睘䱂䝁䅕入呂䡁䅑兙あ䡁䅍睘㉂䑁䅅杌㑂䝁䅷督瑂䙁䄰睑桂䡁䅁兡あ䝁䅅䅢時䙁䅍䅤祂䡁䅕睙あ䡁䅕杣求䙁䄸睕ㅂ䝁䄰兢桂䡁䅉入桁䍁䅑杒歁䑁䅅䅍㙁䍁䅑䅕歁䑁䅅䅍䅁䵁䙅䅁䍃䅁䅁睗乂䕁䅫睘䑂䝁䄸兢睂䝁䅅杢㕂䙁䄸睓求䡁䅫睕あ䝁䅅䅤穂䙁䄸杤硁䍁䄴䅥獂䡁䅍兢摂䕁䅍兙睂䝁䅫䅤桂䝁䅷睘呂䡁䅑杣ㅂ䝁䅍䅤ㅂ䡁䅉党時䙁䅍兤瑂䝁䄰兙祂䡁䅫光歁䕁䅙䅊㕁䑁䅯䅊兂䍁䅑兏䅁䍁䕍䅁䥃䅁䅁睊扂䕁䅍睢睂䡁䅫䅉療䝁䅙䅉呂䙁䅁睒時䕁䅍睢瑂䡁䅁兙畂䡁䅫睘䱂䝁䅕入呂䡁䅑兙あ䡁䅍睘㉂䑁䅉睘畂䝁䅕睤畁䡁䅧䅢穂䝁䄰兘䱂䝁䅕入時䙁䅍䅤桂䡁䅑督湁䍁䅅䅊䡂䍁䅑免睁䑁䅙杏歁䕁䅫䅊硁䑁䅁李䅁䩁䡯䅁睂䅁䅁睗乂䕁䅫睘䑂䝁䄸兢睂䝁䅅杢㕂䙁䄸睓求䡁䅫睕あ䝁䅅䅤穂䙁䄸杤硁䍁䄴䅥獂䡁䅍兢摂䕁䅍兙睂䝁䅫䅤桂䝁䅷兡㙂䝁䅅䅤灂䝁䄸杢桁䍁䅑睑歁䑁䅕睍㙁䍁䅑睑歁䑁䅕䅎䅁䉁䕯䅁祂䅁䅁睗乂䕁䅫睘䱂䝁䅕入呂䡁䅑兙あ䡁䅍睘㉂䑁䅅杌㑂䝁䅷督瑂䙁䄰睑桂䡁䅁兡あ䝁䅅䅢時䙁䅍䅤祂䡁䅕睙あ䡁䅕杣求䙁䄸睕ㅂ䝁䄰兢桂䡁䅉入桁䍁䅑睒歁䑁䅕杏歁䕁䄸䅊ㅁ䅁䅁儶䅍䡁䅁䅁扂䕁䄰兓時䕁䅍睢瑂䡁䅁兙畂䡁䅫睘䱂䝁䅕入呂䡁䅑兙あ䡁䅍睘㉂䑁䅅杌㑂䝁䅷督瑂䙁䄰睑桂䡁䅁兡あ䝁䅅䅢灂䡁䅯兙あ䝁䅫睢畂䍁䅅䅊䙂䍁䅑䅎㍁䑁䅯䅊兂䍁䅑䅎㍁䅁䅁兆䅑䝁䅙䅁扂䕁䄰兓時䕁䅍睢瑂䡁䅁兙畂䡁䅫睘䱂䝁䅕入呂䡁䅑兙あ䡁䅍睘㉂䑁䅅杌㑂䝁䅷督瑂䙁䄰睓求䡁䅫睘呂䡁䅑兙あ䡁䅍光歁䕁䄰䅊祁䑁䅉杏歁䕁䄸䅊祁䑁䅉䅁㑂䅂䅁䅢䅁䙁䅳兔䩂䙁䄸睑療䝁䄰䅣桂䝁䄴入時䕁䅳党㕂䙁䅍䅤桂䡁䅑督時䡁䅙免畁䡁䅧䅢穂䝁䄰兘䑂䝁䅅䅣灂䡁䅑兙獂䝁䅫来桂䡁䅑兡療䝁䄴光歁䕁䅕䅊ぁ䑁䅯䅊䭂䍁䅑䅎䅁䉁䕅䅁睂䅁䅁睗乂䕁䅫睘䑂䝁䄸兢睂䝁䅅杢㕂䙁䄸睓求䡁䅫睕あ䝁䅅䅤穂䙁䄸杤硁䍁䄴䅥獂䡁䅍兢摂䕁䅍兙睂䝁䅫䅤桂䝁䅷兡㙂䝁䅅䅤灂䝁䄸杢桁䍁䅑兒歁䑁䅕免㙁䍁䅑杓歁䑁䅕免䅁䉁䕫䅁睂䅁䅁睗乂䕁䅫睘䑂䝁䄸兢睂䝁䅅杢㕂䙁䄸睓求䡁䅫睕あ䝁䅅䅤穂䙁䄸杤硁䍁䄴䅥獂䡁䅍兢摂䕁䅍兙睂䝁䅫䅤桂䝁䅷兡㙂䝁䅅䅤灂䝁䄸杢桁䍁䅑兒歁䑁䅕杍㙁䍁䅑杓歁䑁䅕杍䅁䉁䕳䅁煂䅁䅁睗乂䕁䅫睘䑂䝁䄸兢睂䝁䅅杢㕂䙁䄸睓求䡁䅫睕あ䝁䅅䅤穂䙁䄸杤硁䍁䄴䅥獂䡁䅍兢摂䕁䅳党㕂䙁䄸睕あ䝁䅅䅤穂䍁䅅䅊䙂䍁䅑免睁䑁䅧杏歁䕁䅣䅊硁䑁䅁䅏䅁䱁䕍䅁獂䅁䅁睗呂䙁䅁睒時䕁䅍睢瑂䡁䅁兙畂䡁䅫睘䱂䝁䅕入呂䡁䅑兙あ䡁䅍睘㉂䑁䅅杌㑂䝁䅷督瑂䙁䄰村桂䝁䅷兙畂䝁䅍党時䙁䅍䅡求䝁䅕䅤桁䍁䅑兒歁䑁䅙杏歁䙁䅁䅊㉁䅁䅁儶䅕䙁䅧䅁扂䕁䄰兓時䕁䅍睢瑂䡁䅁兙畂䡁䅫睘䱂䝁䅕入呂䡁䅑兙あ䡁䅍睘㉂䑁䅅杌㑂䝁䅷督瑂䙁䄰睑桂䡁䅍䅡時䕁䅙䅢療䡁䅣光歁䕁䅍䅊㉁䅁䅁䅵䅕䝁䅉䅁扂䕁䄰兓時䕁䅍睢瑂䡁䅁兙畂䡁䅫睘䱂䝁䅕入呂䡁䅑兙あ䡁䅍睘㉂䑁䅅杌㑂䝁䅷督瑂䙁䄰睑桂䡁䅍䅡時䕁䅙䅢療䡁䅣光歁䕁䅕䅊ぁ䑁䅯䅊兂䍁䅑䅎䅁䅁䔰䅁楂䅁䅁睗乂䕁䅫睘䑂䝁䄸兢睂䝁䅅杢㕂䙁䄸睓求䡁䅫睕あ䝁䅅䅤穂䙁䄸杤硁䍁䄴䅥獂䡁䅍兢摂䕁䅍兙穂䝁䅧睘䝂䝁䅷睢㍂䍁䅅䅊䙂䍁䅑兎㙁䍁䅑䅕歁䑁䅕䅁偁䅂䅁杙䅁䙁䅳兔䩂䙁䄸睑療䝁䄰䅣桂䝁䄴入時䕁䅳党㕂䙁䅍䅤桂䡁䅑督時䡁䅙免畁䡁䅧䅢穂䝁䄰兘䑂䝁䅅督潂䙁䄸杒獂䝁䄸睤桁䍁䅑兒歁䑁䅙杏歁䙁䅁䅊㉁䅁䅁兵䅕䝁䅉䅁扂䕁䄰兓時䕁䅍睢瑂䡁䅁兙畂䡁䅫睘䱂䝁䅕入呂䡁䅑兙あ䡁䅍睘㉂䑁䅅杌㑂䝁䅷督瑂䙁䄰睑桂䡁䅍䅡時䕁䅙䅢療䡁䅣光歁䕁䅕䅊㍁䑁䅯䅊兂䍁䅑睎䅁䱁䙳䅁煂䅁䅁睗乂䕁䅫睘䑂䝁䄸兢睂䝁䅅杢㕂䙁䄸睓求䡁䅫睕あ䝁䅅䅤穂䙁䄸杤硁䍁䄴䅥獂䡁䅍兢摂䕁䅫杢橂䝁䄸兢求䙁䄸睕あ䝁䅅䅤求䝁䄰党畂䡁䅑光歁䕁䅍䅊硁䑁䅣李䅁䭁䕅䅁浂䅁䅁睗乂䕁䅫睘䑂䝁䄸兢睂䝁䅅杢㕂䙁䄸睓求䡁䅫睕あ䝁䅅䅤穂䙁䄸杤硁䍁䄴䅥獂䡁䅍兢摂䕁䅫杢橂䝁䄸兢求䙁䄸睕あ䝁䅅䅤求䝁䄰党畂䡁䅑光歁䕁䅍䅊ぁ䅁䅁䅂䅑䡁䅑䅁扂䕁䄰兓時䕁䅍睢瑂䡁䅁兙畂䡁䅫睘䱂䝁䅕入呂䡁䅑兙あ䡁䅍睘㉂䑁䅅杌㑂䝁䅷督瑂䙁䄰兓畂䝁䅍睢瑂䝁䅕睘呂䡁䅑兙あ䝁䅕兢求䝁䄴䅤桁䍁䅑睑歁䑁䅫杏歁䕁䅍䅊硁䑁䅣睍䅁䅁䕙䅁㑂䅁䅁睗乂䕁䅫睘䑂䝁䄸兢睂䝁䅅杢㕂䙁䄸睓求䡁䅫睕あ䝁䅅䅤穂䙁䄸杤硁䍁䄴䅥獂䡁䅍兢摂䕁䅫杢橂䝁䄸兢求䙁䄸睕あ䝁䅅䅤求䝁䄰党畂䡁䅑光歁䕁䅕䅊硁䑁䅣睎㙁䍁䅑䅕歁䑁䅅睎㍁䅁䅁䅰䅑䡁䅁䅁扂䕁䄰兓時䕁䅍睢瑂䡁䅁兙畂䡁䅫睘䱂䝁䅕入呂䡁䅑兙あ䡁䅍睘㉂䑁䅅杌㑂䝁䅷督瑂䙁䄰兓畂䝁䅍睢瑂䝁䅕睘呂䡁䅑兙あ䝁䅕兢求䝁䄴䅤桁䍁䅑兒歁䑁䅑杏歁䙁䅁䅊ぁ䅁䅁兂䅑䝁䅑䅁扂䕁䄰兓時䕁䅳党㕂䙁䅍䅤桂䡁䅑督時䡁䅙免畁䡁䅧䅢穂䝁䄰兘䩂䝁䄴睙療䝁䄰党時䙁䅍䅤桂䡁䅑党瑂䝁䅕杢あ䍁䅅䅊䑂䍁䅑兏㙁䍁䅑睑歁䑁䅅兎睁䅁䅁全䅍䙁䅙䅁扂䙁䅍䅕䡂䙁䄸睑療䝁䄰䅣桂䝁䄴入時䕁䅳党㕂䙁䅍䅤桂䡁䅑督時䡁䅙杍畁䡁䅧䅢穂䝁䄰兘呂䝁䅧党求䡁䅑免桁䍁䅑兓歁䑁䅣兎䅁䱁䝯䅁睂䅁䅁睗乂䕁䅫睘䑂䝁䄸兢睂䝁䅅杢㕂䙁䄸睓求䡁䅫睕あ䝁䅅䅤穂䙁䄸杤硁䍁䄴䅥獂䡁䅍兢摂䕁䅫杢橂䝁䄸兢求䙁䄸睕あ䝁䅅䅤求䝁䄰党畂䡁䅑光歁䕁䅕䅊ㅁ䑁䅯䅊兂䍁䅑兎䅁䅁䕣䅁捂䅁䅁睗乂䕁䅫睘䑂䝁䄸兢睂䝁䅅杢㕂䙁䄸睓求䡁䅫睕あ䝁䅅䅤穂䙁䄸杤硁䍁䄴䅥獂䡁䅍兢摂䕁䅳党㕂䙁䄸睕あ䝁䅅䅤穂䍁䅅䅊䍂䍁䅑免睁䑁䅉䅁い睁䅁䅚䅁䙁䅳睕兂䕁䅣睘䑂䝁䄸兢睂䝁䅅杢㕂䙁䄸睓求䡁䅫睕あ䝁䅅䅤穂䙁䄸杤祁䍁䄴䅥獂䡁䅍兢摂䕁䅍兙穂䝁䅧睘䝂䝁䅷睢㍂䍁䅅䅊䙂䍁䅑睎㙁䍁䅑兕歁䑁䅣䅁桄睂䅁䅘䅁䙁䅳兔䩂䙁䄸睑療䝁䄰䅣桂䝁䄴入時䕁䅳党㕂䙁䅍䅤桂䡁䅑督時䡁䅙免畁䡁䅧䅢穂䝁䄰兘䱂䝁䅕入時䙁䅍䅤桂䡁䅑督桁䍁䅑村歁䑁䅅䅍穁䅁䅁睂䅕䝁䅷䅁扂䕁䄰兓時䕁䅍睢瑂䡁䅁兙畂䡁䅫睘䱂䝁䅕入呂䡁䅑兙あ䡁䅍睘㉂䑁䅅睔獂䝁䅑杌㑂䝁䅷督瑂䙁䄰睓求䡁䅫睘呂䡁䅑兙あ䡁䅍光歁䕁䅑䅊祁䑁䅕杏歁䕁䅑䅊ぁ䑁䅫䅁㡂䅂䅁䅘䅁䙁䅳兔䩂䙁䄸睑療䝁䄰䅣桂䝁䄴入時䕁䅳党㕂䙁䅍䅤桂䡁䅑督時䡁䅙免畁䡁䅧䅢穂䝁䄰兘䱂䝁䅕入時䙁䅍䅤桂䡁䅑督桁䍁䅑村歁䑁䅅䅍ぁ䅁䅁䅬䅑䙁䅯䅁扂䕁䄰兓時䕁䅍睢瑂䡁䅁兙畂䡁䅫睘䱂䝁䅕入呂䡁䅑兙あ䡁䅍睘㉂䑁䅅杌㑂䝁䅷督瑂䙁䄰睓求䡁䅫睘呂䡁䅑兙あ䡁䅍光歁䕁䅉䅊祁䑁䅉䅁睄睁䅁杗䅁䙁䅳兔䩂䙁䄸睑療䝁䄰䅣桂䝁䄴入時䕁䅳党㕂䙁䅍䅤桂䡁䅑督時䡁䅙免畁䡁䅧䅢穂䝁䄰兘䱂䝁䅕入時䙁䅍䅤桂䡁䅑督桁䍁䅑村歁䑁䅉睍䅁偁䑧䅁潂䅁䅁睗呂䙁䅁睒時䕁䅍睢瑂䡁䅁兙畂䡁䅫睘䱂䝁䅕入呂䡁䅑兙あ䡁䅍睘㉂䑁䅅杌㑂䝁䅷督瑂䙁䄰睑桂䡁䅍䅡時䕁䅙䅢療䡁䅣光歁䕁䅍䅊硁䑁䅅杏歁䕁䅍䅊㕁䑁䅉䅁畄兂䅁杗䅁䙁䅳兔䩂䙁䄸睑療䝁䄰䅣桂䝁䄴入時䕁䅳党㕂䙁䅍䅤桂䡁䅑督時䡁䅙免畁䡁䅧䅢穂䝁䄰兘䱂䝁䅕入時䙁䅍䅤桂䡁䅑督桁䍁䅑村歁䑁䅉䅎䅁䥁䕑䅁慂䅁䅁睗乂䕁䅫睘䑂䝁䄸兢睂䝁䅅杢㕂䙁䄸睓求䡁䅫睕あ䝁䅅䅤穂䙁䄸杤硁䍁䄴䅥獂䡁䅍兢摂䕁䅳党㕂䙁䄸睕あ䝁䅅䅤穂䍁䅅䅊䍂䍁䅑杍㉁䅁䅁睱䅑䡁䅯䅁扂䙁䅍䅕䡂䙁䄸睑療䝁䄰䅣桂䝁䄴入時䕁䅳党㕂䙁䅍䅤桂䡁䅑督時䡁䅙杍畁䡁䅧䅢穂䝁䄰兘䑂䝁䅅䅣灂䡁䅑兙獂䙁䄸睕あ䡁䅉兤橂䡁䅑兤祂䝁䅕睘呂䡁䅕兢瑂䝁䅅杣㕂䍁䅅䅊䑂䍁䅑睎䅁䅁䥙䅁䵃䅁䅁睊扂䕁䅍睢睂䡁䅫䅉療䝁䅙䅉呂䙁䅁睒時䕁䅍睢瑂䡁䅁兙畂䡁䅫睘䱂䝁䅕入呂䡁䅑兙あ䡁䅍睘㉂䑁䅉睘畂䝁䅕睤畁䡁䅧䅢穂䝁䄰兘兂䝁䅕杢穂䝁䅫睢畂䍁䄰睔兂䕁䅕村湁䍁䅅䅊䑂䍁䅑免硁䑁䅯䅊䑂䍁䅑兎㍁䑁䅕䅁潂睂䅁杗䅁䙁䅳兔䩂䙁䄸睑療䝁䄰䅣桂䝁䄴入時䕁䅳党㕂䙁䅍䅤桂䡁䅑督時䡁䅙免畁䡁䅧䅢穂䝁䄰兘䱂䝁䅕入時䙁䅍䅤桂䡁䅑督桁䍁䅑村歁䑁䅕杍䅁偁䑷䅁慂䅁䅁睗乂䕁䅫睘䑂䝁䄸兢睂䝁䅅杢㕂䙁䄸睓求䡁䅫睕あ䝁䅅䅤穂䙁䄸杤硁䍁䄴䅥獂䡁䅍兢摂䕁䅳党㕂䙁䄸睕あ䝁䅅䅤穂䍁䅅䅊䍂䍁䅑兎ぁ䅁䅁杲䅑䙁䅯䅁扂䕁䄰兓時䕁䅍睢瑂䡁䅁兙畂䡁䅫睘䱂䝁䅕入呂䡁䅑兙あ䡁䅍睘㉂䑁䅅杌㑂䝁䅷督瑂䙁䄰睓求䡁䅫睘呂䡁䅑兙あ䡁䅍光歁䕁䅉䅊ㅁ䑁䅫䅁䅁䅂䅁杗䅁䙁䅳兔䩂䙁䄸睓求䡁䅫睕あ䝁䅅䅤穂䙁䄸杤硁䍁䄴䅥獂䡁䅍兢摂䕁䅳党㕂䙁䄸睕あ䝁䅅䅤穂䍁䅅䅊䑂䍁䅑免睁䑁䅕杏歁䕁䅍䅊硁䑁䅁兏䅁䵁䐴䅁慂䅁䅁睗乂䕁䅫睘䑂䝁䄸兢睂䝁䅅杢㕂䙁䄸睓求䡁䅫睕あ䝁䅅䅤穂䙁䄸杤硁䍁䄴䅥獂䡁䅍兢摂䕁䅳党㕂䙁䄸睕あ䝁䅅䅤穂䍁䅅䅊䍂䍁䅑李祁䅁䅁䅴䅑䝁䅯䅁扂䕁䄰兓時䕁䅍睢瑂䡁䅁兙畂䡁䅫睘䱂䝁䅕入呂䡁䅑兙あ䡁䅍睘㉂䑁䅅杌㑂䝁䅷督瑂䙁䄰睓求䡁䅫睘呂䡁䅑兙あ䡁䅍光歁䕁䅍䅊硁䑁䅁兎㙁䍁䅑睑歁䑁䅅䅍㕁䅁䅁朹䅍䝁䅯䅁扂䕁䄰兓時䕁䅍睢瑂䡁䅁兙畂䡁䅫睘䱂䝁䅕入呂䡁䅑兙あ䡁䅍睘㉂䑁䅅杌㑂䝁䅷督瑂䙁䄰睓求䡁䅫睘呂䡁䅑兙あ䡁䅍光歁䕁䅍䅊硁䑁䅁李㙁䍁䅑睑歁䑁䅅免睁䅁䅁兂䅕䝁䅯䅁扂䕁䄰兓時䕁䅍睢瑂䡁䅁兙畂䡁䅫睘䱂䝁䅕入呂䡁䅑兙あ䡁䅍睘㉂䑁䅅杌㑂䝁䅷督瑂䙁䄰睓求䡁䅫睘呂䡁䅑兙あ䡁䅍光歁䕁䅍䅊硁䑁䅁䅏㙁䍁䅑睑歁䑁䅅免祁䅁䅁六䅑䙁䅙䅁扂䙁䅍䅕䡂䙁䄸睑療䝁䄰䅣桂䝁䄴入時䕁䅳党㕂䙁䅍䅤桂䡁䅑督時䡁䅙杍畁䡁䅧䅢穂䝁䄰兘呂䝁䅧党求䡁䅑免桁䍁䅑兒歁䑁䅅免䅁䩁䝁䅁煂䅁䅁睗乂䕁䅫睘䑂䝁䄸兢睂䝁䅅杢㕂䙁䄸睓求䡁䅫睕あ䝁䅅䅤穂䙁䄸杤硁䍁䄴䅥獂䡁䅍兢摂䕁䅳党㕂䙁䄸睕あ䝁䅅䅤穂䍁䅅䅊䑂䍁䅑免睁䑁䅫杏歁䕁䅍䅊硁䑁䅅睍䅁䩁䕷䅁㉂䅁䅁睗乂䕁䅫睘䑂䝁䄸兢睂䝁䅅杢㕂䙁䄸睓求䡁䅫睕あ䝁䅅䅤穂䙁䄸杤硁䙁䄸杌㑂䝁䅷督瑂䙁䄰兓畂䝁䅍睢瑂䝁䅕睘呂䡁䅑兙あ䝁䅕兢求䝁䄴䅤桁䍁䅑睑歁䑁䅫杏歁䕁䅍䅊硁䑁䅣睍䅁乁䕍䅁浂䅁䅁睗乂䕁䅫睘䑂䝁䄸兢睂䝁䅅杢㕂䙁䄸睓求䡁䅫睕あ䝁䅅䅤穂䙁䄸杤硁䍁䄴䅥獂䡁䅍兢摂䕁䅳党㕂䙁䄸睕あ䝁䅅䅤穂䍁䅅䅊䑂䍁䅑杍㑁䑁䅯䅊䑂䍁䅑兎祁䅁䅁共䅑䝁䅙䅁扂䕁䄰兓時䕁䅍睢瑂䡁䅁兙畂䡁䅫睘䱂䝁䅕入呂䡁䅑兙あ䡁䅍睘㉂䑁䅅杌㑂䝁䅷督瑂䙁䄰睓求䡁䅫睘呂䡁䅑兙あ䡁䅍光歁䕁䅍䅊ㅁ䑁䅑杏歁䕁䅍䅊ㅁ䑁䅕䅁⭄睁䅁杚䅁䙁䅳兔䩂䙁䄸睑療䝁䄰䅣桂䝁䄴入時䕁䅳党㕂䙁䅍䅤桂䡁䅑督時䡁䅙免畁䡁䅧䅢穂䝁䄰兘䱂䝁䅕入時䙁䅍䅤桂䡁䅑督桁䍁䅑睑歁䑁䅕李㙁䍁䅑睑歁䑁䅕睎䅁䥁䔴䅁浂䅁䅁睗乂䕁䅫睘䑂䝁䄸兢睂䝁䅅杢㕂䙁䄸睓求䡁䅫睕あ䝁䅅䅤穂䙁䄸杤硁䍁䄴䅥獂䡁䅍兢摂䕁䅳党㕂䙁䄸睕あ䝁䅅䅤穂䍁䅅䅊䑂䍁䅑李ぁ䑁䅯䅊䑂䍁䅑睎睁䅁䅁睭䅑䝁䅙䅁扂䕁䄰兓時䕁䅍睢瑂䡁䅁兙畂䡁䅫睘䱂䝁䅕入呂䡁䅑兙あ䡁䅍睘㉂䑁䅅杌㑂䝁䅷督瑂䙁䄰睓求䡁䅫睘呂䡁䅑兙あ䡁䅍光歁䕁䅍䅊㉁䑁䅕杏歁䕁䅍䅊㍁䑁䅅䅁ㅃ䅂䅁杚䅁䙁䅳兔䩂䙁䄸睑療䝁䄰䅣桂䝁䄴入時䕁䅳党㕂䙁䅍䅤桂䡁䅑督時䡁䅙免畁䡁䅧䅢穂䝁䄰兘䱂䝁䅕入時䙁䅍䅤桂䡁䅑督桁䍁䅑䅒歁䑁䅉睎㙁䍁䅑䅒歁䑁䅕免䅁䥁䕯䅁浂䅁䅁睗乂䕁䅫睘䑂䝁䄸兢睂䝁䅅杢㕂䙁䄸睓求䡁䅫睕あ䝁䅅䅤穂䙁䄸杤硁䍁䄴䅥獂䡁䅍兢摂䕁䅳党㕂䙁䄸睕あ䝁䅅䅤穂䍁䅅䅊䕂䍁䅑兎ぁ䑁䅯䅊䕂䍁䅑兎ㅁ䅁䅁眯䅍䝁䅙䅁扂䕁䄰兓時䕁䅍睢瑂䡁䅁兙畂䡁䅫睘䱂䝁䅕入呂䡁䅑兙あ䡁䅍睘㉂䑁䅅杌㑂䝁䅷督瑂䙁䄰睓求䡁䅫睘呂䡁䅑兙あ䡁䅍光歁䕁䅑䅊ㅁ䑁䅣杏歁䕁䅑䅊ㅁ䑁䅧䅁㡃䅂䅁杦䅁䍁䅣睗䑂䝁䄸䅣㕂䍁䅁睢浂䍁䅁睕兂䕁䅣睘䑂䝁䄸兢睂䝁䅅杢㕂䙁䄸睓求䡁䅫睕あ䝁䅅䅤穂䙁䄸杤硁䙁䄸杒灂䝁䄴兙獂䍁䄴䅥獂䡁䅍兢摂䙁䅉兙あ䝁䅫睢穂䍁䅣光歁䕁䅑䅊㑁䑁䅯䅊䭂䍁䅑䅏䅁䭁䥑䅁煂䅁䅁睗乂䕁䅫睘䑂䝁䄸兢睂䝁䅅杢㕂䙁䄸睓求䡁䅫睕あ䝁䅅䅤穂䙁䄸杤硁䍁䄴䅥獂䡁䅍兢摂䕁䅳党㕂䙁䄸睕あ䝁䅅䅤穂䍁䅅䅊䙂䍁䅑免睁䑁䅑杏歁䕁䅣䅊硁䑁䅁䅎䅁偁䑣䅁䵃䅁䅁睊扂䕁䅍睢睂䡁䅫䅉療䝁䅙䅉呂䙁䅁睒時䕁䅍睢瑂䡁䅁兙畂䡁䅫睘䱂䝁䅕入呂䡁䅑兙あ䡁䅍睘㉂䑁䅅睘䝂䝁䅫杢桂䝁䅷杌㑂䝁䅷督瑂䙁䄰睓求䡁䅫睘呂䡁䅑兙あ䡁䅍睊桁䍁䅑睒歁䑁䅅䅍㉁䑁䅯䅊䭂䍁䅑免睁䑁䅙䅁呂䅃䅁条䅁䙁䅳兔䩂䙁䄸睑療䝁䄰䅣桂䝁䄴入時䕁䅳党㕂䙁䅍䅤桂䡁䅑督時䡁䅙免畁䡁䅧䅢穂䝁䄰兘䱂䝁䅕入時䙁䅍䅤桂䡁䅑督桁䍁䅑兒歁䑁䅅䅍㍁䑁䅯䅊䡂䍁䅑免睁䑁䅣䅁慃䅂䅁杚䅁䙁䅳兔䩂䙁䄸睑療䝁䄰䅣桂䝁䄴入時䕁䅳党㕂䙁䅍䅤桂䡁䅑督時䡁䅙免畁䡁䅧䅢穂䝁䄰兘䱂䝁䅕入時䙁䅍䅤桂䡁䅑督桁䍁䅑兒歁䑁䅉睍㙁䍁䅑杓歁䑁䅉睍䅁䥁䕍䅁浂䅁䅁睗乂䕁䅫睘䑂䝁䄸兢睂䝁䅅杢㕂䙁䄸睓求䡁䅫睕あ䝁䅅䅤穂䙁䄸杤硁䍁䄴䅥獂䡁䅍兢摂䕁䅳党㕂䙁䄸睕あ䝁䅅䅤穂䍁䅅䅊䙂䍁䅑杍ぁ䑁䅯䅊䭂䍁䅑杍ぁ䅁䅁全䅑䝁䅙䅁扂䕁䄰兓時䕁䅍睢瑂䡁䅁兙畂䡁䅫睘䱂䝁䅕入呂䡁䅑兙あ䡁䅍睘㉂䑁䅅杌㑂䝁䅷督瑂䙁䄰睓求䡁䅫睘呂䡁䅑兙あ䡁䅍光歁䕁䅕䅊祁䑁䅕杏歁䕁䅯䅊祁䑁䅕䅁䡃䅂䅁杚䅁䙁䅳兔䩂䙁䄸睑療䝁䄰䅣桂䝁䄴入時䕁䅳党㕂䙁䅍䅤桂䡁䅑督時䡁䅙免畁䡁䅧䅢穂䝁䄰兘䱂䝁䅕入時䙁䅍䅤桂䡁䅑督桁䍁䅑兒歁䑁䅉兎㙁䍁䅑䅔歁䑁䅉兎䅁䱁䕯䅁浂䅁䅁睗乂䕁䅫睘䑂䝁䄸兢睂䝁䅅杢㕂䙁䄸睓求䡁䅫睕あ䝁䅅䅤穂䙁䄸杤硁䍁䄴䅥獂䡁䅍兢摂䕁䅳党㕂䙁䄸睕あ䝁䅅䅤穂䍁䅅䅊䙂䍁䅑杍㉁䑁䅯䅊䭂䍁䅑杍㉁䅁䅁東䅑䝁䅙䅁扂䕁䄰兓時䕁䅍睢瑂䡁䅁兙畂䡁䅫睘䱂䝁䅕入呂䡁䅑兙あ䡁䅍睘㉂䑁䅅杌㑂䝁䅷督瑂䙁䄰睓求䡁䅫睘呂䡁䅑兙あ䡁䅍光歁䕁䅕䅊祁䑁䅙杏歁䕁䅷䅊祁䑁䅙䅁㝃䅂䅁杗䅁䙁䅳兔䩂䙁䄸睑療䝁䄰䅣桂䝁䄴入時䕁䅳党㕂䙁䅍䅤桂䡁䅑督時䡁䅙免畁䡁䅧䅢穂䝁䄰兘䱂䝁䅕入時䙁䅍䅤桂䡁䅑督桁䍁䅑兒歁䑁䅙䅍䅁䅁䕍䅁慂䅁䅁睗乂䕁䅫睘䑂䝁䄸兢睂䝁䅅杢㕂䙁䄸睓求䡁䅫睕あ䝁䅅䅤穂䙁䄸杤硁䍁䄴䅥獂䡁䅍兢摂䕁䅳党㕂䙁䄸睕あ䝁䅅䅤穂䍁䅅䅊䙂䍁䅑李硁䅁䅁八䅑䝁䅙䅁扂䕁䄰兓時䕁䅍睢瑂䡁䅁兙畂䡁䅫睘䱂䝁䅕入呂䡁䅑兙あ䡁䅍睘㉂䑁䅅杌㑂䝁䅷督瑂䙁䄰睓求䡁䅫睘呂䡁䅑兙あ䡁䅍光歁䕁䄰䅊祁䑁䅙杏歁䕁䄸䅊祁䑁䅙䅁瑃䅂䅁杗䅁䙁䅳兔䩂䙁䄸睑療䝁䄰䅣桂䝁䄴入時䕁䅳党㕂䙁䅍䅤桂䡁䅑督時䡁䅙免畁䡁䅧䅢穂䝁䄰兘䱂䝁䅕入時䙁䅍䅤桂䡁䅑督桁䍁䅑睕歁䑁䅕兎䅁䩁䙷䅁歃䅁䅁睊扂䕁䅍睢睂䡁䅫䅉療䝁䅙䅉呂䙁䅁睒時䕁䅍睢瑂䡁䅁兙畂䡁䅫睘䱂䝁䅕入呂䡁䅑兙あ䡁䅍睘㉂䑁䅅睘䝂䝁䅫杢桂䝁䅷杌㑂䝁䅷督瑂䙁䄰睑桂䡁䅁兡あ䝁䅅䅢時䙁䅍䅤祂䡁䅕睙あ䡁䅕杣求䙁䄸睕ㅂ䝁䄰兢桂䡁䅉入湁䍁䅅䅊䙂䍁䅑李㙁䍁䅑兕歁䑁䅙䅁潂䅃䅁䅮䅁䍁䅣睗䑂䝁䄸䅣㕂䍁䅁睢浂䍁䅁睕兂䕁䅣睘䑂䝁䄸兢睂䝁䅅杢㕂䙁䄸睓求䡁䅫睕あ䝁䅅䅤穂䙁䄸杤祁䙁䄸杢求䡁䅣杌㑂䝁䅷督瑂䙁䄰睑桂䡁䅁兡あ䝁䅅䅢時䙁䅍䅤祂䡁䅕睙あ䡁䅕杣求䙁䄸䅉䕂䝁䅕䅤桂䝁䅫䅢穂䍁䅁睊桁䍁䅑睓歁䑁䅑䅎䅁䥁䡁䅁浂䅁䅁睗乂䕁䅫睘䑂䝁䄸兢睂䝁䅅杢㕂䙁䄸睓求䡁䅫睕あ䝁䅅䅤穂䙁䄸杤硁䍁䄴䅥獂䡁䅍兢摂䕁䅳党㕂䙁䄸睕あ䝁䅅䅤穂䍁䅅䅊呂䍁䅑兎㑁䑁䅯䅊呂䍁䅑李硁䅁䅁䅲䅕䝁䅙䅁扂䕁䄰兓時䕁䅍睢瑂䡁䅁兙畂䡁䅫睘䱂䝁䅕入呂䡁䅑兙あ䡁䅍睘㉂䑁䅅杌㑂䝁䅷督瑂䙁䄰睓求䡁䅫睘呂䡁䅑兙あ䡁䅍光歁䙁䅙䅊ㅁ䑁䅣杏歁䙁䅫䅊ㅁ䑁䅣䅁敃兂䅁杙䅁䙁䅳兔䩂䙁䄸睑療䝁䄰䅣桂䝁䄴入時䕁䅳党㕂䙁䅍䅤桂䡁䅑督時䡁䅙免畁䡁䅧䅢穂䝁䄰兘卂䝁䅅䅤灂䝁䄸督桁䍁䅑睑歁䑁䅅免㙁䍁䅑睑歁䑁䅅兎祁䅁䅁杸䅕䙁䅉䅁扂䕁䄰兓時䕁䅍睢瑂䡁䅁兙畂䡁䅫睘䱂䝁䅕入呂䡁䅑兙あ䡁䅍睘㉂䑁䅅杌㑂䝁䅷督瑂䙁䄰杕桂䡁䅑兡療䡁䅍光歁䕁䅍䅊ぁ䅁䅁䅊䅑䙁䅉䅁扂䕁䄰兓時䕁䅍睢瑂䡁䅁兙畂䡁䅫睘䱂䝁䅕入呂䡁䅑兙あ䡁䅍睘㉂䑁䅅杌㑂䝁䅷督瑂䙁䄰杕桂䡁䅑兡療䡁䅍光歁䕁䅍䅊㉁䅁䅁䅸䅕䝁䅁䅁扂䕁䄰兓時䕁䅍睢瑂䡁䅁兙畂䡁䅫睘䱂䝁䅕入呂䡁䅑兙あ䡁䅍睘㉂䑁䅅杌㑂䝁䅷督瑂䙁䄰杕桂䡁䅑兡療䡁䅍光歁䕁䅍䅊㕁䑁䅯䅊䑂䍁䅑免ㅁ䑁䅁䅁流䅂䅁䅘䅁䙁䅳兔䩂䙁䄸睑療䝁䄰䅣桂䝁䄴入時䕁䅳党㕂䙁䅍䅤桂䡁䅑督時䡁䅙免畁䡁䅧䅢穂䝁䄰兘卂䝁䅅䅤灂䝁䄸督桁䍁䅑䅒歁䑁䅕杏歁䕁䅫䅊ㅁ䅁䅁睊䅑䙁䅷䅁扂䕁䄰兓時䕁䅍睢瑂䡁䅁兙畂䡁䅫睘䱂䝁䅕入呂䡁䅑兙あ䡁䅍睘㉂䑁䅅杌㑂䝁䅷督瑂䙁䄰杕桂䡁䅑兡療䡁䅍光歁䕁䅑䅊㍁䑁䅯䅊䩂䍁䅑睎䅁䵁䙣䅁畂䅁䅁睗乂䕁䅫睘䑂䝁䄸兢睂䝁䅅杢㕂䙁䄸睓求䡁䅫睕あ䝁䅅䅤穂䙁䄸杤硁䍁䄴䅥獂䡁䅍兢摂䙁䅍兤睂䡁䅁䅢求䝁䄰党畂䡁䅑兙獂䍁䅅䅊䑂䍁䅑免硁䑁䅯䅊䑂䍁䅑免㉁䑁䅙䅁䭄兂䅁杦䅁䍁䅣睗䑂䝁䄸䅣㕂䍁䅁睢浂䍁䅁睕兂䕁䅣睘䑂䝁䄸兢睂䝁䅅杢㕂䙁䄸睓求䡁䅫睕あ䝁䅅䅤穂䙁䄸杤祁䙁䄸杢求䡁䅣杌㑂䝁䅷督瑂䙁䄰村桂䝁䅷兙畂䝁䅍党時䙁䅍䅡求䝁䅕䅤湁䍁䅅䅊䑂䍁䅑李䅁䕁䡉䅁敂䅁䅁睗乂䕁䅫睘䑂䝁䄸兢睂䝁䅅杢㕂䙁䄸睓求䡁䅫睕あ䝁䅅䅤穂䙁䄸杤硁䍁䄴䅥獂䡁䅍兢摂䙁䅍兤睂䡁䅁䅢求䝁䄰党畂䡁䅑兙獂䍁䅅䅊䑂䍁䅑䅎䅁䍁䕧䅁敂䅁䅁睗乂䕁䅫睘䑂䝁䄸兢睂䝁䅅杢㕂䙁䄸睓求䡁䅫睕あ䝁䅅䅤穂䙁䄸杤硁䍁䄴䅥獂䡁䅍兢摂䙁䅍兤睂䡁䅁䅢求䝁䄰党畂䡁䅑兙獂䍁䅅䅊䑂䍁䅑李䅁䵁䙧䅁獂䅁䅁睗乂䕁䅫睘䑂䝁䄸兢睂䝁䅅杢㕂䙁䄸睓求䡁䅫睕あ䝁䅅䅤穂䙁䄸杤硁䍁䄴䅥獂䡁䅍兢摂䙁䅍兤睂䡁䅁䅢求䝁䄰党畂䡁䅑兙獂䍁䅅䅊䑂䍁䅑兏㙁䍁䅑睑歁䑁䅅李ぁ䅁䅁杋䅑䕁䅯䅁扂䕁䄰兓時䕁䅳党㕂䙁䅍䅤桂䡁䅑督時䡁䅙免畁䡁䅧䅢穂䝁䄰兘䱂䝁䅕入時䙁䅍䅤桂䡁䅑督桁䍁䅑兒歁䑁䅕兏䅁䡁䑉䅁潂䅁䅁睗乂䕁䅫睘䑂䝁䄸兢睂䝁䅅杢㕂䙁䄸睓求䡁䅫睕あ䝁䅅䅤穂䙁䄸杤硁䍁䄴䅥獂䡁䅍兢摂䙁䅍兤睂䡁䅁䅢求䝁䄰党畂䡁䅑兙獂䍁䅅䅊䕂䍁䅑兎㙁䍁䅑兓歁䑁䅕䅁牁䅂䅁䅡䅁䙁䅳兔䩂䙁䄸睑療䝁䄰䅣桂䝁䄴入時䕁䅳党㕂䙁䅍䅤桂䡁䅑督時䡁䅙免畁䡁䅧䅢穂䝁䄰兘呂䡁䅕䅣睂䝁䅷党瑂䝁䅕杢あ䝁䅅䅢桁䍁䅑䅒歁䑁䅙杏歁䕁䅫䅊㉁䅁䅁兹䅕䝁䅉䅁扂䕁䄰兓時䕁䅍睢瑂䡁䅁兙畂䡁䅫睘䱂䝁䅕入呂䡁䅑兙あ䡁䅍睘㉂䑁䅅睔獂䝁䅑杌㑂䝁䅷督瑂䙁䄰睓求䡁䅫睘呂䡁䅑兙あ䡁䅍光歁䕁䅉䅊硁䑁䅁杍䅁䡁䔴䅁杂䅁䅁睗乂䕁䅫睘䑂䝁䄸兢睂䝁䅅杢㕂䙁䄸睓求䡁䅫睕あ䝁䅅䅤穂䙁䄸杤硁䕁䄸䅢歂䍁䄴䅥獂䡁䅍兢摂䕁䅳党㕂䙁䄸睕あ䝁䅅䅤穂䍁䅅䅊䍂䍁䅑杍穁䅁䅁来䅑䡁䅁䅁扂䕁䄰兓時䕁䅍睢瑂䡁䅁兙畂䡁䅫睘䱂䝁䅕入呂䡁䅑兙あ䡁䅍睘㉂䑁䅅睔獂䝁䅑杌㑂䝁䅷督瑂䙁䄰睓求䡁䅫睘呂䡁䅑兙あ䡁䅍光歁䕁䅕䅊硁䑁䅁睍㙁䍁䅑睒歁䑁䅅䅍穁䅁䅁睦䅑䝁䅁䅁扂䕁䄰兓時䕁䅳党㕂䙁䅍䅤桂䡁䅑督時䡁䅙免畁䡁䅧䅢穂䝁䄰兘䩂䝁䄴睙療䝁䄰党時䙁䅍䅤桂䡁䅑党瑂䝁䅕杢あ䍁䅅䅊䙂䍁䅑兎㙁䍁䅑䅕歁䑁䅕䅁䝃睁䅁䅣䅁䙁䅳兔䩂䙁䄸睑療䝁䄰䅣桂䝁䄴入時䕁䅳党㕂䙁䅍䅤桂䡁䅑督時䡁䅙免偂䝁䅷䅚畁䡁䅧䅢穂䝁䄰兘䱂䝁䅕入時䙁䅍䅤桂䡁䅑督桁䍁䅑兒歁䑁䅅䅍ぁ䑁䅯䅊䡂䍁䅑免睁䑁䅑䅁䉃䅂䅁杚䅁䙁䅳兔䩂䙁䄸睑療䝁䄰䅣桂䝁䄴入時䕁䅳党㕂䙁䅍䅤桂䡁䅑督時䡁䅙免時䍁䄴䅥獂䡁䅍兢摂䕁䅉兙獂䝁䅅杢橂䝁䅕睘呂䝁䅧党求䡁䅑光歁䕁䅍䅊硁䑁䅑睍䅁乁䔰䅁啃䅁䅁睊扂䕁䅍睢睂䡁䅫䅉療䝁䅙䅉呂䙁䅁睒時䕁䅍睢瑂䡁䅁兙畂䡁䅫睘䱂䝁䅕入呂䡁䅑兙あ䡁䅍睘㉂䑁䅉睘畂䝁䅕睤畁䡁䅧䅢穂䝁䄰兘䩂䝁䄴睙療䝁䄰党時䙁䅍䅤桂䡁䅑党瑂䝁䅕杢あ䍁䅣光歁䕁䅍䅊硁䑁䅅杏歁䕁䅍䅊祁䑁䅁免䅁䭁䠴䅁浂䅁䅁睗乂䕁䅫睘䑂䝁䄸兢睂䝁䅅杢㕂䙁䄸睓求䡁䅫睕あ䝁䅅䅤穂䙁䄸杤硁䙁䄸杌㑂䝁䅷督瑂䙁䄰村桂䝁䅷兙畂䝁䅍党時䙁䅍䅡求䝁䅕䅤桁䍁䅑睑歁䑁䅅䅎㉁䅁䅁眳䅑䡁䅑䅁扂䕁䄰兓時䕁䅍睢瑂䡁䅁兙畂䡁䅫睘䱂䝁䅕入呂䡁䅑兙あ䡁䅍睘㉂䑁䅅睘畁䡁䅧䅢穂䝁䄰兘䍂䝁䅅䅢桂䝁䄴睙求䙁䄸睕潂䝁䅕党あ䍁䅅䅊䙂䍁䅑免ぁ䑁䅍杏歁䙁䅁䅊硁䑁䅑睍䅁乁䔴䅁獂䅁䅁睗乂䕁䅫睘䑂䝁䄸兢睂䝁䅅杢㕂䙁䄸睓求䡁䅫睕あ䝁䅅䅤穂䙁䄸杤硁䙁䄸杌㑂䝁䅷督瑂䙁䄰村桂䝁䅷兙畂䝁䅍党時䙁䅍䅡求䝁䅕䅤桁䍁䅑兒歁䑁䅑杏歁䙁䅁䅊ぁ䅁䅁朲䅑䥁䅯䅁扂䕁䄰兓時䕁䅍睢瑂䡁䅁兙畂䡁䅫睘䱂䝁䅕入呂䡁䅑兙あ䡁䅍睘㉂䑁䅅睘畁䡁䅧䅢穂䝁䄰兘䑂䝁䅅䅣灂䡁䅑兙獂䙁䄸睕あ䡁䅉兤橂䡁䅑兤祂䝁䅕睘呂䡁䅕兢瑂䝁䅅杣㕂䍁䅅䅊䑂䍁䅑免穁䑁䅯䅊䑂䍁䅑免ㅁ䑁䅁䅁穄䅂䅁来䅁䙁䅳兔䩂䙁䄸睑療䝁䄰䅣桂䝁䄴入時䕁䅳党㕂䙁䅍䅤桂䡁䅑督時䡁䅙免時䍁䄴䅥獂䡁䅍兢摂䕁䅍兙睂䝁䅫䅤桂䝁䅷睘呂䡁䅑杣ㅂ䝁䅍䅤ㅂ䡁䅉党時䙁䅍兤瑂䝁䄰兙祂䡁䅫光歁䕁䅍䅊ㅁ䅁䅁儹䅑䥁䅧䅁扂䕁䄰兓時䕁䅍睢瑂䡁䅁兙畂䡁䅫睘䱂䝁䅕入呂䡁䅑兙あ䡁䅍睘㉂䑁䅅睘畁䡁䅧䅢穂䝁䄰兘䑂䝁䅅䅣灂䡁䅑兙獂䙁䄸睕あ䡁䅉兤橂䡁䅑兤祂䝁䅕睘呂䡁䅕兢瑂䝁䅅杣㕂䍁䅅䅊䕂䍁䅑杍㍁䑁䅯䅊䕂䍁䅑睎㑁䅁䅁眹䅑䥁䅧䅁湁䙁䅳睑療䡁䅁入杁䝁䄸杚杁䙁䅍䅕䡂䙁䄸睑療䝁䄰䅣桂䝁䄴入時䕁䅳党㕂䙁䅍䅤桂䡁䅑督時䡁䅙杍時䝁䄴党㍂䍁䄴䅥獂䡁䅍兢摂䕁䅉兙獂䝁䅅杢橂䝁䅕睘呂䝁䅧党求䡁䅑睊桁䍁䅑兒歁䑁䅙杏歁䙁䅅䅊㉁䅁䅁关䅣䥁䅑䅁扂䕁䄰兓時䕁䅍睢瑂䡁䅁兙畂䡁䅫睘䱂䝁䅕入呂䡁䅑兙あ䡁䅍睘㉂䑁䅅睘畁䡁䅧䅢穂䝁䄰兘䑂䝁䅅䅣灂䡁䅑兙獂䙁䄸睕あ䡁䅉兤橂䡁䅑兤祂䝁䅕睘呂䡁䅕兢瑂䝁䅅杣㕂䍁䅅䅊䙂䍁䅑䅎㙁䍁䅑睔歁䑁䅑䅁祄䅂䅁䅨䅁䙁䅳兔䩂䙁䄸睑療䝁䄰䅣桂䝁䄴入時䕁䅳党㕂䙁䅍䅤桂䡁䅑督時䡁䅙免時䍁䄴䅥獂䡁䅍兢摂䕁䅍兙睂䝁䅫䅤桂䝁䅷睘呂䡁䅑杣ㅂ䝁䅍䅤ㅂ䡁䅉党時䙁䅍兤瑂䝁䄰兙祂䡁䅫光歁䕁䅙䅊㑁䑁䅯䅊兂䍁䅑䅏䅁偁䕙䅁䕃䅁䅁睗乂䕁䅫睘䑂䝁䄸兢睂䝁䅅杢㕂䙁䄸睓求䡁䅫睕あ䝁䅅䅤穂䙁䄸杤硁䙁䄸杌㑂䝁䅷督瑂䙁䄰睑桂䡁䅁兡あ䝁䅅䅢時䙁䅍䅤祂䡁䅕睙あ䡁䅕杣求䙁䄸睕ㅂ䝁䄰兢桂䡁䅉入桁䍁䅑杒歁䑁䅫杏歁䙁䅁䅊㕁䅁䅁䄫䅑䝁䅑䅁扂䕁䄰兓時䕁䅍睢瑂䡁䅁兙畂䡁䅫睘䱂䝁䅕入呂䡁䅑兙あ䡁䅍睘㉂䑁䅅睘畁䡁䅧䅢穂䝁䄰兘䑂䝁䅅䅣灂䡁䅑兙獂䝁䅫来桂䡁䅑兡療䝁䄴光歁䕁䅍䅊ぁ䅁䅁儵䅑䝁䅙䅁扂䕁䄰兓時䕁䅍睢瑂䡁䅁兙畂䡁䅫睘䱂䝁䅕入呂䡁䅑兙あ䡁䅍睘㉂䑁䅅睘畁䡁䅧䅢穂䝁䄰兘䑂䝁䅅䅣灂䡁䅑兙獂䝁䅫来桂䡁䅑兡療䝁䄴光歁䕁䅍䅊ぁ䑁䅣䅁瑄䅂䅁杣䅁䙁䅳兔䩂䙁䄸睑療䝁䄰䅣桂䝁䄴入時䕁䅳党㕂䙁䅍䅤桂䡁䅑督時䡁䅙免時䍁䄴䅥獂䡁䅍兢摂䕁䅍兙睂䝁䅫䅤桂䝁䅷兡㙂䝁䅅䅤灂䝁䄸杢桁䍁䅑兒歁䑁䅑睎㙁䍁䅑杓歁䑁䅑睎䅁佁䕯䅁祂䅁䅁睗乂䕁䅫睘䑂䝁䄸兢睂䝁䅅杢㕂䙁䄸睓求䡁䅫睕あ䝁䅅䅤穂䙁䄸杤硁䙁䄸杌㑂䝁䅷督瑂䙁䄰睑桂䡁䅁兡あ䝁䅅䅢灂䡁䅯兙あ䝁䅫睢畂䍁䅅䅊䙂䍁䅑䅎㑁䑁䅯䅊䭂䍁䅑䅎㑁䅁䅁䄷䅑䡁䅉䅁扂䕁䄰兓時䕁䅍睢瑂䡁䅁兙畂䡁䅫睘䱂䝁䅕入呂䡁䅑兙あ䡁䅍睘㉂䑁䅅睘畁䡁䅧䅢穂䝁䄰兘䑂䝁䅅䅣灂䡁䅑兙獂䝁䅫来桂䡁䅑兡療䝁䄴光歁䕁䅕䅊ㅁ䑁䅅杏歁䕁䅯䅊ㅁ䑁䅅䅁畄䅂䅁杖䅁䙁䅳睕兂䕁䅣睘䑂䝁䄸兢睂䝁䅅杢㕂䙁䄸睓求䡁䅫睕あ䝁䅅䅤穂䙁䄸杤祁䍁䄴䅥獂䡁䅍兢摂䙁䅍䅡求䝁䅕䅤硁䍁䅅䅊䱂䍁䅑睎ㅁ䅁䅁䅶䅙䙁䅯䅁扂䕁䄰兓時䕁䅍睢瑂䡁䅁兙畂䡁䅫睘䱂䝁䅕入呂䡁䅑兙あ䡁䅍睘㉂䑁䅅睘畁䡁䅧䅢穂䝁䄰兘䑂䝁䅅督潂䙁䄸杒獂䝁䄸睤桁䍁䅑睑歁䑁䅑䅁桄䅂䅁䅢䅁䙁䅳兔䩂䙁䄸睑療䝁䄰䅣桂䝁䄴入時䕁䅳党㕂䙁䅍䅤桂䡁䅑督時䡁䅙免時䍁䄴䅥獂䡁䅍兢摂䕁䅫杢橂䝁䄸兢求䙁䄸睕あ䝁䅅䅤求䝁䄰党畂䡁䅑光歁䕁䅍䅊硁䑁䅣兏䅁乁䕣䅁祂䅁䅁睗乂䕁䅫睘䑂䝁䄸兢睂䝁䅅杢㕂䙁䄸睓求䡁䅫睕あ䝁䅅䅤穂䙁䄸杤硁䙁䄸杌㑂䝁䅷督瑂䙁䄰兓畂䝁䅍睢瑂䝁䅕睘呂䡁䅑兙あ䝁䅕兢求䝁䄴䅤桁䍁䅑兒歁䑁䅑杏歁䙁䅁䅊ぁ䅁䅁朰䅑䡁䅯䅁扂䕁䄰兓時䕁䅍睢瑂䡁䅁兙畂䡁䅫睘䱂䝁䅕入呂䡁䅑兙あ䡁䅍睘㉂䑁䅅睘畁䡁䅧䅢穂䝁䄰兘䩂䝁䄴睙療䝁䄰党時䙁䅍䅤桂䡁䅑党瑂䝁䅕杢あ䍁䅅䅊䙂䍁䅑免㍁䑁䅙杏歁䙁䅁䅊硁䑁䅣李䅁乁䕙䅁捂䅁䅁睗乂䕁䅫睘䑂䝁䄸兢睂䝁䅅杢㕂䙁䄸睓求䡁䅫睕あ䝁䅅䅤穂䙁䄸杤硁䙁䄸杌㑂䝁䅷督瑂䙁䄰睓求䡁䅫睘呂䡁䅑兙あ䡁䅍光歁䕁䅉䅊ㅁ䑁䅑䅁䙄䅂䅁䅘䅁䙁䅳兔䩂䙁䄸睑療䝁䄰䅣桂䝁䄴入時䕁䅳党㕂䙁䅍䅤桂䡁䅑督時䡁䅙免時䍁䄴䅥獂䡁䅍兢摂䕁䅳党㕂䙁䄸睕あ䝁䅅䅤穂䍁䅅䅊䍂䍁䅑李祁䅁䅁兹䅑䝁䅧䅁扂䕁䄰兓時䕁䅍睢瑂䡁䅁兙畂䡁䅫睘䱂䝁䅕入呂䡁䅑兙あ䡁䅍睘㉂䑁䅅睘畁䡁䅧䅢穂䝁䄰兘䱂䝁䅕入時䙁䅍䅤桂䡁䅑督桁䍁䅑睑歁䑁䅕睎㙁䍁䅑睑歁䑁䅕䅏䅁䵁䕣䅁獂䅁䅁睗乂䕁䅫睘䑂䝁䄸兢睂䝁䅅杢㕂䙁䄸睓求䡁䅫睕あ䝁䅅䅤穂䙁䄸杤硁䙁䄸杌㑂䝁䅷督瑂䙁䄰睓求䡁䅫睘呂䡁䅑兙あ䡁䅍光歁䕁䅕䅊硁䑁䅁睎㙁䍁䅑睒歁䑁䅅䅍㍁䅁䅁杺䅑䝁䅷䅁扂䕁䄰兓時䕁䅍睢瑂䡁䅁兙畂䡁䅫睘䱂䝁䅕入呂䡁䅑兙あ䡁䅍睘㉂䑁䅅睘畁䡁䅧䅢穂䝁䄰兘䱂䝁䅕入時䙁䅍䅤桂䡁䅑督桁䍁䅑兒歁䑁䅅䅍㑁䑁䅯䅊䡂䍁䅑免睁䑁䅧䅁兄䅂䅁䅡䅁䙁䅳兔䩂䙁䄸睑療䝁䄰䅣桂䝁䄴入時䕁䅳党㕂䙁䅍䅤桂䡁䅑督時䡁䅙免時䍁䄴䅥獂䡁䅍兢摂䕁䅳党㕂䙁䄸睕あ䝁䅅䅤穂䍁䅅䅊䙂䍁䅑杍ㅁ䑁䅯䅊䭂䍁䅑杍ㅁ䅁䅁杶䅑䝁䅧䅁扂䕁䄰兓時䕁䅍睢瑂䡁䅁兙畂䡁䅫睘䱂䝁䅕入呂䡁䅑兙あ䡁䅍睘㉂䑁䅅睘畁䡁䅧䅢穂䝁䄰兘䱂䝁䅕入時䙁䅍䅤桂䡁䅑督桁䍁䅑兒歁䑁䅉李㙁䍁䅑杓歁䑁䅉李䅁䵁䕁䅁捂䅁䅁睗乂䕁䅫睘䑂䝁䄸兢睂䝁䅅杢㕂䙁䄸睓求䡁䅫睕あ䝁䅅䅤穂䙁䄸杤硁䙁䄸杌㑂䝁䅷督瑂䙁䄰睓求䡁䅫睘呂䡁䅑兙あ䡁䅍光歁䕁䅕䅊ㅁ䑁䅑䅁䝄䅂䅁䅏䅁䕁䄸䅣あ䝁䅫睢畂䡁䅍杏呂䡁䅑兙あ䝁䅫督あ䝁䅫睙㥁䕁䄰兒䕂䍁䅷杔䉂䑁䄰杔䉂䅁䅁䄱䅣䙁䅷䅁扂䕁䄰兓時䕁䅍睢瑂䡁䅁兙畂䡁䅫睘䱂䝁䅕入呂䡁䅑兙あ䡁䅍睘㉂䑁䅅睘畁䡁䅧䅢穂䝁䄰兘䱂䝁䅕入時䙁䅍䅤桂䡁䅑督桁䍁䅑兒歁䑁䅙杍䅁䵁䕯䅁捂䅁䅁睗乂䕁䅫睘䑂䝁䄸兢睂䝁䅅杢㕂䙁䄸睓求䡁䅫睕あ䝁䅅䅤穂䙁䄸杤硁䙁䄸杌㑂䝁䅷督瑂䙁䄰睓求䡁䅫睘呂䡁䅑兙あ䡁䅍光歁䕁䅕䅊㉁䑁䅍䅁䵄䅂䅁䅡䅁䙁䅳兔䩂䙁䄸睑療䝁䄰䅣桂䝁䄴入時䕁䅳党㕂䙁䅍䅤桂䡁䅑督時䡁䅙免時䍁䄴䅥獂䡁䅍兢摂䕁䅳党㕂䙁䄸睕あ䝁䅅䅤穂䍁䅅䅊乂䍁䅑杍ㅁ䑁䅯䅊偂䍁䅑杍ㅁ䅁䅁杷䅑䝁䅧䅁扂䕁䄰兓時䕁䅍睢瑂䡁䅁兙畂䡁䅫睘䱂䝁䅕入呂䡁䅑兙あ䡁䅍睘㉂䑁䅅睘畁䡁䅧䅢穂䝁䄰兘䱂䝁䅕入時䙁䅍䅤桂䡁䅑督桁䍁䅑兔歁䑁䅉李㙁䍁䅑睔歁䑁䅉李䅁䵁䕑䅁敂䅁䅁睗乂䕁䅫睘䱂䝁䅕入呂䡁䅑兙あ䡁䅍睘㉂䑁䅅杌㑂䝁䅷督瑂䙁䄰村桂䝁䅷兙畂䝁䅍党時䙁䅍䅡求䝁䅕䅤桁䍁䅑睑歁䑁䅫杏歁䕁䅍䅊硁䑁䅍睎䅁䩁䑣䅁杂䅁䅁睗乂䕁䅫睘䑂䝁䄸兢睂䝁䅅杢㕂䙁䄸睓求䡁䅫睕あ䝁䅅䅤穂䙁䄸杤硁䙁䄸杌㑂䝁䅷督瑂䙁䄰睕ㅂ䡁䅁䅣獂䝁䅕兢求䝁䄴䅤桂䝁䅷光歁䕁䅍䅊ぁ䅁䅁儯䅑䝁䅯䅁扂䕁䄰兓時䕁䅍睢瑂䡁䅁兙畂䡁䅫睘䱂䝁䅕入呂䡁䅑兙あ䡁䅍睘㉂䑁䅅睘畁䡁䅧䅢穂䝁䄰兘呂䡁䅕䅣睂䝁䅷党瑂䝁䅕杢あ䝁䅅䅢桁䍁䅑䅒歁䑁䅑杏歁䕁䅫䅊ぁ䅁䅁术䅑䝁䅧䅁扂䙁䅍䅕䡂䙁䄸睑療䝁䄰䅣桂䝁䄴入時䕁䅳党㕂䙁䅍䅤桂䡁䅑督時䡁䅙杍畁䡁䅧䅢穂䝁䄰兘䱂䝁䅕入時䙁䅍䅤桂䡁䅑督桁䍁䅑兒歁䑁䅉兎㙁䍁䅑杓歁䑁䅉兎䅁佁䡣䅁敂䅁䅁睗乂䕁䅫睘䱂䝁䅕入呂䡁䅑兙あ䡁䅍睘㉂䑁䅅杌㑂䝁䅷督瑂䙁䄰村桂䝁䅷兙畂䝁䅍党時䙁䅍䅡求䝁䅕䅤桁䍁䅑睑歁䑁䅫杏歁䕁䅍䅊硁䑁䅍䅏䅁䱁䐴䅁敂䅁䅁睗乂䕁䅫睘䱂䝁䅕入呂䡁䅑兙あ䡁䅍睘㉂䑁䅅杌㑂䝁䅷督瑂䙁䄰村桂䝁䅷兙畂䝁䅍党時䙁䅍䅡求䝁䅕䅤桁䍁䅑睑歁䑁䅫杏歁䕁䅍䅊硁䑁䅑䅍䅁佁䑙䅁慂䅁䅁睗乂䕁䅫睘䱂䝁䅕入呂䡁䅑兙あ䡁䅍睘㉂䑁䅅杌㑂䝁䅷督瑂䙁䄰村桂䝁䅷兙畂䝁䅍党時䙁䅍䅡求䝁䅕䅤桁䍁䅑兒歁䑁䅑杏歁䙁䅁䅊ぁ䅁䅁杬䅍䡁䅧䅁扂䕁䄰兓時䕁䅳党㕂䙁䅍䅤桂䡁䅑督時䡁䅙免畁䡁䅧䅢穂䝁䄰兘䑂䝁䅅䅣灂䡁䅑兙獂䙁䄸睕あ䡁䅉兤橂䡁䅑兤祂䝁䅕睘呂䡁䅕兢瑂䝁䅅杣㕂䍁䅅䅊䑂䍁䅑免穁䑁䅯䅊䑂䍁䅑免ぁ䑁䅙䅁牃睁䅁䅥䅁䙁䅳兔䩂䙁䄸睓求䡁䅫睕あ䝁䅅䅤穂䙁䄸杤硁䍁䄴䅥獂䡁䅍兢摂䕁䅍兙睂䝁䅫䅤桂䝁䅷睘呂䡁䅑杣ㅂ䝁䅍䅤ㅂ䡁䅉党時䙁䅍兤瑂䝁䄰兙祂䡁䅫光歁䕁䅍䅊硁䑁䅍杏歁䕁䅍䅊硁䑁䅑䅏䅁䵁䑁䅁㉂䅁䅁睗乂䕁䅫睘䱂䝁䅕入呂䡁䅑兙あ䡁䅍睘㉂䑁䅅杌㑂䝁䅷督瑂䙁䄰睑桂䡁䅁兡あ䝁䅅䅢時䙁䅍䅤祂䡁䅕睙あ䡁䅕杣求䙁䄸睕ㅂ䝁䄰兢桂䡁䅉入桁䍁䅑䅒歁䑁䅉睎㙁䍁䅑䅒歁䑁䅣䅏䅁䵁䑍䅁潂䅁䅁睗呂䙁䅁睒時䕁䅍睢瑂䡁䅁兙畂䡁䅫睘䱂䝁䅕入呂䡁䅑兙あ䡁䅍睘㉂䑁䅅杌㑂䝁䅷督瑂䙁䄰睓求䡁䅫睘呂䡁䅑兙あ䡁䅍光歁䕁䄰䅊祁䑁䅕杏歁䕁䄸䅊祁䑁䅕䅁噄兂䅁杣䅁䙁䅳兔䩂䙁䄸睓求䡁䅫睕あ䝁䅅䅤穂䙁䄸杤硁䍁䄴䅥獂䡁䅍兢摂䕁䅍兙睂䝁䅫䅤桂䝁䅷睘呂䡁䅑杣ㅂ䝁䅍䅤ㅂ䡁䅉党時䙁䅍兤瑂䝁䄰兙祂䡁䅫光歁䕁䅕䅊ぁ䑁䅯䅊乂䍁䅑䅎䅁䭁䑯䅁祂䅁䅁睗乂䕁䅫睘䱂䝁䅕入呂䡁䅑兙あ䡁䅍睘㉂䑁䅅杌㑂䝁䅷督瑂䙁䄰睑桂䡁䅁兡あ䝁䅅䅢時䙁䅍䅤祂䡁䅕睙あ䡁䅕杣求䙁䄸睕ㅂ䝁䄰兢桂䡁䅉入桁䍁䅑兒歁䑁䅑杏歁䕁䄸䅊ぁ䅁䅁䄷䅍䡁䅉䅁扂䕁䄰兓時䕁䅳党㕂䙁䅍䅤桂䡁䅑督時䡁䅙免畁䡁䅧䅢穂䝁䄰兘䑂䝁䅅䅣灂䡁䅑兙獂䙁䄸睕あ䡁䅉兤橂䡁䅑兤祂䝁䅕睘呂䡁䅕兢瑂䝁䅅杣㕂䍁䅅䅊䙂䍁䅑兎㙁䍁䅑睔歁䑁䅕䅁瑄睁䅁杣䅁䙁䅳兔䩂䙁䄸睓求䡁䅫睕あ䝁䅅䅤穂䙁䄸杤硁䍁䄴䅥獂䡁䅍兢摂䕁䅍兙睂䝁䅫䅤桂䝁䅷睘呂䡁䅑杣ㅂ䝁䅍䅤ㅂ䡁䅉党時䙁䅍兤瑂䝁䄰兙祂䡁䅫光歁䕁䅙䅊㑁䑁䅯䅊佂䍁䅑䅏䅁䭁䐰䅁歃䅁䅁睊扂䕁䅍睢睂䡁䅫䅉療䝁䅙䅉呂䙁䅁睒時䕁䅍睢瑂䡁䅁兙畂䡁䅫睘䱂䝁䅕入呂䡁䅑兙あ䡁䅍睘㉂䑁䅉睘畂䝁䅕睤畁䡁䅧䅢穂䝁䄰兘䑂䝁䅅䅣灂䡁䅑兙獂䙁䄸睕あ䡁䅉兤橂䡁䅑兤祂䝁䅕睘呂䡁䅕兢瑂䝁䅅杣㕂䍁䅣光歁䕁䅙䅊硁䑁䅁杏歁䙁䅉䅊硁䑁䅁䅁䑄睂䅁杣䅁䙁䅳兔䩂䙁䄸睓求䡁䅫睕あ䝁䅅䅤穂䙁䄸杤硁䍁䄴䅥獂䡁䅍兢摂䕁䅍兙睂䝁䅫䅤桂䝁䅷睘呂䡁䅑杣ㅂ䝁䅍䅤ㅂ䡁䅉党時䙁䅍兤瑂䝁䄰兙祂䡁䅫光歁䕁䅣䅊ぁ䑁䅯䅊偂䍁䅑䅎䅁佁䑧䅁祂䅁䅁睗乂䕁䅫睘䱂䝁䅕入呂䡁䅑兙あ䡁䅍睘㉂䑁䅅杌㑂䝁䅷督瑂䙁䄰睑桂䡁䅁兡あ䝁䅅䅢時䙁䅍䅤祂䡁䅕睙あ䡁䅕杣求䙁䄸睕ㅂ䝁䄰兢桂䡁䅉入桁䍁䅑䅓歁䑁䅧杏歁䙁䅁䅊㑁䅁䅁朶䅍䙁䅯䅁扂䕁䄰兓時䕁䅳党㕂䙁䅍䅤桂䡁䅑督時䡁䅙免畁䡁䅧䅢穂䝁䄰兘䱂䝁䅕入時䙁䅍䅤桂䡁䅑督桁䍁䅑兒歁䑁䅅䅍睁䑁䅯䅊䡂䍁䅑免睁䑁䅁䅁㡂睁䅁杣䅁䙁䅳兔䩂䙁䄸睓求䡁䅫睕あ䝁䅅䅤穂䙁䄸杤硁䍁䄴䅥獂䡁䅍兢摂䕁䅍兙睂䝁䅫䅤桂䝁䅷睘呂䡁䅑杣ㅂ䝁䅍䅤ㅂ䡁䅉党時䙁䅍兤瑂䝁䄰兙祂䡁䅫光歁䕁䅧䅊㕁䑁䅯䅊兂䍁䅑兏䅁佁䑳䅁啂䅁䅁睗乂䕁䅫睘䱂䝁䅕入呂䡁䅑兙あ䡁䅍睘㉂䑁䅅杌㑂䝁䅷督瑂䙁䄰睑桂䡁䅁兡あ䝁䅅䅢灂䡁䅯兙あ䝁䅫睢畂䍁䅅䅊䑂䍁䅑䅎㍁䅁䅁兰䅍䝁䅁䅁扂䕁䄰兓時䕁䅳党㕂䙁䅍䅤桂䡁䅑督時䡁䅙免畁䡁䅧䅢穂䝁䄰兘䑂䝁䅅䅣灂䡁䅑兙獂䝁䅫来桂䡁䅑兡療䝁䄴光歁䕁䅕䅊ぁ䑁䅣杏歁䕁䅯䅊ぁ䑁䅣䅁楃睁䅁杖䅁䙁䅳睕兂䕁䅣睘䑂䝁䄸兢睂䝁䅅杢㕂䙁䄸睓求䡁䅫睕あ䝁䅅䅤穂䙁䄸杤祁䍁䄴䅥獂䡁䅍兢摂䙁䅍䅡求䝁䅕䅤硁䍁䅅䅊䉂䕁䅅䅊ぁ䅁䅁公䅙䝁䅁䅁扂䕁䄰兓時䕁䅳党㕂䙁䅍䅤桂䡁䅑督時䡁䅙免畁䡁䅧䅢穂䝁䄰兘䑂䝁䅅䅣灂䡁䅑兙獂䝁䅫来桂䡁䅑兡療䝁䄴光歁䕁䅕䅊ぁ䑁䅣杏歁䙁䅁䅊ぁ䑁䅣䅁㑃睁䅁䅙䅁䙁䅳兔䩂䙁䄸睓求䡁䅫睕あ䝁䅅䅤穂䙁䄸杤硁䍁䄴䅥獂䡁䅍兢摂䕁䅍兙睂䝁䅫䅤桂䝁䅷兡㙂䝁䅅䅤灂䝁䄸杢桁䍁䅑兒歁䑁䅕免㙁䍁䅑杓歁䑁䅕免䅁䭁䑙䅁捂䅁䅁睗乂䕁䅫睘䱂䝁䅕入呂䡁䅑兙あ䡁䅍睘㉂䑁䅅杌㑂䝁䅷督瑂䙁䄰睑桂䡁䅁兡あ䝁䅅䅢灂䡁䅯兙あ䝁䅫睢畂䍁䅅䅊䙂䍁䅑兎㙁䍁䅑杓歁䑁䅕䅁权睁䅁䅓䅁䙁䅳兔䩂䙁䄸睓求䡁䅫睕あ䝁䅅䅤穂䙁䄸杤硁䍁䄴䅥獂䡁䅍兢摂䕁䅍兙穂䝁䅧睘䝂䝁䅷睢㍂䍁䅅䅊䑂䍁䅑䅎䅁䩁䑫䅁啂䅁䅁睗乂䕁䅫睘䱂䝁䅕入呂䡁䅑兙あ䡁䅍睘㉂䑁䅅杌㑂䝁䅷督瑂䙁䄰睑桂䡁䅍䅡時䕁䅙䅢療䡁䅣光歁䕁䅍䅊㕁䑁䅯䅊䑂䍁䅑䅏㕁䅁䅁睭䅍䙁䅑䅁扂䕁䄰兓時䕁䅳党㕂䙁䅍䅤桂䡁䅑督時䡁䅙免畁䡁䅧䅢穂䝁䄰兘䑂䝁䅅督潂䙁䄸杒獂䝁䄸睤桁䍁䅑睑歁䑁䅫杏歁䕁䅍䅊㕁䑁䅁䅁⽃睁䅁䅢䅁䙁䅳睕兂䕁䅣睘䑂䝁䄸兢睂䝁䅅杢㕂䙁䄸睓求䡁䅫睕あ䝁䅅䅤穂䙁䄸杤祁䍁䄴䅥獂䡁䅍兢摂䕁䅳党㕂䙁䄸睕あ䝁䅅䅤穂䍁䅅䅊䡂䍁䅑免睁䑁䅙杏歁䕁䅫䅊硁䑁䅁李䅁偁䡍䅁卂䅁䅁睗乂䕁䅫睘䱂䝁䅕入呂䡁䅑兙あ䡁䅍睘㉂䑁䅅杌㑂䝁䅷督瑂䙁䄰睑桂䡁䅍䅡時䕁䅙䅢療䡁䅣光歁䕁䅕䅊ぁ䑁䅯䅊兂䍁䅑䅎䅁䩁䑯䅁卂䅁䅁睗乂䕁䅫睘䱂䝁䅕入呂䡁䅑兙あ䡁䅍睘㉂䑁䅅杌㑂䝁䅷督瑂䙁䄰睑桂䡁䅍䅡時䕁䅙䅢療䡁䅣光歁䕁䅕䅊ㅁ䑁䅯䅊兂䍁䅑兎䅁䩁䑷䅁坂䅁䅁睗乂䕁䅫睘䱂䝁䅕入呂䡁䅑兙あ䡁䅍睘㉂䑁䅅杌㑂䝁䅷督瑂䙁䄰兓畂䝁䅍睢瑂䝁䅕睘呂䡁䅑兙あ䝁䅕兢求䝁䄴䅤桁䍁䅑睑歁䑁䅑䅁䑃睁䅁䅡䅁䙁䅳睕兂䕁䅣睘䑂䝁䄸兢睂䝁䅅杢㕂䙁䄸睓求䡁䅫睕あ䝁䅅䅤穂䙁䄸杤祁䍁䄴䅥獂䡁䅍兢摂䕁䅳党㕂䙁䄸睕あ䝁䅅䅤穂䍁䅅䅊佂䍁䅑杍ㅁ䑁䅯䅊兂䍁䅑杍ㅁ䅁䅁眶䅣䝁䅑䅁扂䕁䄰兓時䕁䅳党㕂䙁䅍䅤桂䡁䅑督時䡁䅙免畁䡁䅧䅢穂䝁䄰兘䩂䝁䄴睙療䝁䄰党時䙁䅍䅤桂䡁䅑党瑂䝁䅕杢あ䍁䅅䅊䑂䍁䅑兏㙁䍁䅑睑歁䑁䅅䅎祁䅁䅁其䅍䩁䅙䅁湁䙁䅳睑療䡁䅁入杁䝁䄸杚杁䙁䅍䅕䡂䙁䄸睑療䝁䄰䅣桂䝁䄴入時䕁䅳党㕂䙁䅍䅤桂䡁䅑督時䡁䅙杍時䝁䄴党㍂䍁䄴䅥獂䡁䅍兢摂䕁䅍兙睂䝁䅫䅤桂䝁䅷睘呂䡁䅑杣ㅂ䝁䅍䅤ㅂ䡁䅉党時䙁䅍兤瑂䝁䄰兙祂䡁䅫睊桁䍁䅑睑歁䑁䅣䅁慂睂䅁䅚䅁䙁䅳兔䩂䙁䄸睓求䡁䅫睕あ䝁䅅䅤穂䙁䄸杤硁䍁䄴䅥獂䡁䅍兢摂䕁䅫杢橂䝁䄸兢求䙁䄸睕あ䝁䅅䅤求䝁䄰党畂䡁䅑光歁䕁䅍䅊㕁䑁䅯䅊䑂䍁䅑免ㅁ䑁䅕䅁䡃睁䅁䅚䅁䙁䅳兔䩂䙁䄸睓求䡁䅫睕あ䝁䅅䅤穂䙁䄸杤硁䍁䄴䅥獂䡁䅍兢摂䕁䅫杢橂䝁䄸兢求䙁䄸睕あ䝁䅅䅤求䝁䄰党畂䡁䅑光歁䕁䅍䅊㕁䑁䅯䅊䑂䍁䅑免㉁䑁䅕䅁橄睁䅁䅙䅁䙁䅳兔䩂䙁䄸睓求䡁䅫睕あ䝁䅅䅤穂䙁䄸杤硁䍁䄴䅥獂䡁䅍兢摂䕁䅫杢橂䝁䄸兢求䙁䄸睕あ䝁䅅䅤求䝁䄰党畂䡁䅑光歁䕁䅕䅊ぁ䑁䅯䅊兂䍁䅑䅎䅁䥁䑑䅁䭂䅁䅁睗乂䕁䅫睘䱂䝁䅕入呂䡁䅑兙あ䡁䅍睘㉂䑁䅅杌㑂䝁䅷督瑂䙁䄰睓求䡁䅫睘呂䡁䅑兙あ䡁䅍光歁䕁䅉䅊祁䑁䅍䅁瑂睁䅁杓䅁䙁䅳兔䩂䙁䄸睓求䡁䅫睕あ䝁䅅䅤穂䙁䄸杤硁䍁䄴䅥獂䡁䅍兢摂䕁䅳党㕂䙁䄸睕あ䝁䅅䅤穂䍁䅅䅊䍂䍁䅑兏㑁䅁䅁入䅍䙁䅙䅁扂䕁䄰兓時䕁䅳党㕂䙁䅍䅤桂䡁䅑督時䡁䅙免畁䡁䅧䅢穂䝁䄰兘䱂䝁䅕入時䙁䅍䅤桂䡁䅑督桁䍁䅑睑歁䑁䅕䅎㙁䍁䅑睑歁䑁䅕兎䅁䡁䑣䅁坂䅁䅁睗乂䕁䅫睘䱂䝁䅕入呂䡁䅑兙あ䡁䅍睘㉂䑁䅅杌㑂䝁䅷督瑂䙁䄰睓求䡁䅫睘呂䡁䅑兙あ䡁䅍光歁䕁䅕䅊祁䑁䅉杏歁䕁䅫䅊祁䑁䅉䅁煂睁䅁杖䅁䙁䅳兔䩂䙁䄸睓求䡁䅫睕あ䝁䅅䅤穂䙁䄸杤硁䍁䄴䅥獂䡁䅍兢摂䕁䅳党㕂䙁䄸睕あ䝁䅅䅤穂䍁䅅䅊䙂䍁䅑杍穁䑁䅯䅊䩂䍁䅑杍穁䅁䅁䅢䅍䥁䅁䅁湁䙁䅳睑療䡁䅁入杁䝁䄸杚杁䙁䅍䅕䡂䙁䄸睑療䝁䄰䅣桂䝁䄴入時䕁䅳党㕂䙁䅍䅤桂䡁䅑督時䡁䅙杍時䝁䄴党㍂䍁䄴䅥獂䡁䅍兢摂䙁䅉兙あ䝁䅫睢穂䍁䅣光歁䕁䅍䅊硁䑁䅅杏歁䕁䅍䅊硁䑁䅕睎䅁䵁䡕䅁坂䅁䅁睗乂䕁䅫睘䱂䝁䅕入呂䡁䅑兙あ䡁䅍睘㉂䑁䅅杌㑂䝁䅷督瑂䙁䄰睓求䡁䅫睘呂䡁䅑兙あ䡁䅍光歁䕁䅯䅊祁䑁䅉杏歁䕁䄰䅊祁䑁䅉䅁㥂睁䅁杖䅁䙁䅳兔䩂䙁䄸睓求䡁䅫睕あ䝁䅅䅤穂䙁䄸杤硁䍁䄴䅥獂䡁䅍兢摂䕁䅳党㕂䙁䄸睕あ䝁䅅䅤穂䍁䅅䅊䭂䍁䅑杍穁䑁䅯䅊䵂䍁䅑杍穁䅁䅁䅣䅍䙁䅙䅁扂䕁䄰兓時䕁䅳党㕂䙁䅍䅤桂䡁䅑督時䡁䅙免畁䡁䅧䅢穂䝁䄰兘䱂䝁䅕入時䙁䅍䅤桂䡁䅑督桁䍁䅑杓歁䑁䅉睍㙁䍁䅑兔歁䑁䅉睍䅁䡁䐴䅁䍂䅁䅁睗乂䕁䅫睘䱂䝁䅕入呂䡁䅑兙あ䡁䅍睘㉂䑁䅅杌㑂䝁䅷督瑂䙁䄰杕桂䡁䅑兡療䡁䅍光歁䕁䅍䅊ぁ䅁䅁䅳䅍䙁䅷䅁扂䕁䄰兓時䕁䅳党㕂䙁䅍䅤桂䡁䅑督時䡁䅙免畁䡁䅧䅢穂䝁䄰兘呂䡁䅕䅣睂䝁䅷党瑂䝁䅕杢あ䝁䅅䅢桁䍁䅑睑歁䑁䅫杏歁䕁䅍䅊硁䑁䅕兎䅁䵁䑙䅁坂䅁䅁睔睂䡁䅑兡療䝁䄴督㙁䕁䅍兤祂䡁䅉児噂䙁䅍䅒獁䕁䄰兙湂䑁䄰兔灂䝁䅷䅢灂䝁䄸杢穂䍁䅷睑療䝁䄴杤㥁䙁䅍䅌佂䕁䅅児佂䕁䅅䅁偄睂䅁䅘䅁䙁䅳兔䩂䙁䄸睓求䡁䅫睕あ䝁䅅䅤穂䙁䄸杤硁䍁䄴䅥獂䡁䅍兢摂䙁䅍兤睂䡁䅁䅢求䝁䄰党畂䡁䅑兙獂䍁䅅䅊䑂䍁䅑兏㙁䍁䅑睑歁䑁䅅兎㑁䅁䅁睸䅍䙁䅷䅁扂䕁䄰兓時䕁䅳党㕂䙁䅍䅤桂䡁䅑督時䡁䅙免畁䡁䅧䅢穂䝁䄰兘呂䡁䅕䅣睂䝁䅷党瑂䝁䅕杢あ䝁䅅䅢桁䍁䅑睑歁䑁䅫杏歁䕁䅍䅊硁䑁䅙李䅁䵁䑫䅁慂䅁䅁睗乂䕁䅫睘卂䕁䅕兓啂䙁䄸睕桂䝁䄰党呂䡁䅑睢祂䝁䅕䅖求䝁䄰䅣獂䝁䅅䅤求䙁䄸杤硁䍁䄴䅥獂䡁䅍兘䕂䝁䅅䅤桂䍁䅅䅊䕂䕁䅧䅊㕁䅁䅁䄱䅍䝁䅯䅁扂䕁䄰兓時䙁䅉兒䩂䙁䅑睘呂䝁䅅兢求䙁䅍䅤療䡁䅉党啂䝁䅕兢睂䝁䅷兙あ䝁䅕睘㉂䑁䅅杌㑂䝁䅷督摂䕁䅑兙あ䝁䅅光歁䕁䅑兓歁䑁䅅睍㙁䍁䅑䅒䩂䍁䅑杍穁䅁䅁儱䅍䝁䅧䅁扂䕁䄰兓時䙁䅉兒䩂䙁䅑睘呂䝁䅅兢求䙁䅍䅤療䡁䅉党啂䝁䅕兢睂䝁䅷兙あ䝁䅕睘㉂䑁䅅杌㑂䝁䅷督摂䕁䅑兙あ䝁䅅光歁䕁䅣䅊硁䑁䅁杏歁䕁䅑䅒歁䑁䅅䅍䅁佁䑁䅁潂䅁䅁睗乂䕁䅫睘卂䕁䅕兓啂䙁䄸睕桂䝁䄰党呂䡁䅑睢祂䝁䅕䅖求䝁䄰䅣獂䝁䅅䅤求䙁䄸杤硁䍁䄴䅥獂䡁䅍兘䕂䝁䅅䅤桂䍁䅅䅊䥂䍁䅑䅎㕁䑁䅯䅊䥂䍁䅑杍㍁䑁䅕䅁捄睁䅁䅘䅁䙁䅳睕兂䕁䅣睘䑂䝁䄸兢睂䝁䅅杢㕂䙁䄸睓求䡁䅫睕あ䝁䅅䅤穂䙁䄸杤祁䍁䄴䅥獂䡁䅍兢摂䕁䅳党㕂䙁䄸睕あ䝁䅅䅤穂䍁䅅䅊䙂䍁䅑李穁䅁䅁儸䅣䙁䅯䅁扂䕁䄰兓時䙁䅉兒䩂䙁䅑睘呂䝁䅅兢求䙁䅍䅤療䡁䅉党啂䝁䅕兢睂䝁䅷兙あ䝁䅕睘㉂䑁䅅杌㑂䝁䅷督摂䕁䅑兙あ䝁䅅光歁䕁䅯䅊祁䑁䅫䅁兄睁䅁杗䅁䙁䅳兔䩂䙁䄸杕䙂䕁䅫䅖時䙁䅍兙瑂䝁䅕睕あ䝁䄸杣求䙁䅑党瑂䡁䅁䅢桂䡁䅑党時䡁䅙免畁䡁䅧䅢穂䙁䄰䅒桂䡁䅑兙桁䍁䅑杓歁䑁䅍杍䅁乁䑅䅁浂䅁䅁睗乂䕁䅫睘卂䕁䅕兓啂䙁䄸睕桂䝁䄰党呂䡁䅑睢祂䝁䅕䅖求䝁䄰䅣獂䝁䅅䅤求䙁䄸杤硁䍁䄴䅥獂䡁䅍兘䕂䝁䅅䅤桂䍁䅅䅊䱂䍁䅑杍㕁䑁䅯䅊䵂䍁䅑杍㕁䅁䅁朰䅍䝁䅙䅁扂䕁䄰兓時䙁䅉兒䩂䙁䅑睘呂䝁䅅兢求䙁䅍䅤療䡁䅉党啂䝁䅕兢睂䝁䅷兙あ䝁䅕睘㉂䑁䅅杌㑂䝁䅷督摂䕁䅑兙あ䝁䅅光歁䕁䅳䅊穁䑁䅁杏歁䕁䅷䅊穁䑁䅁䅁呄睁䅁杣䅁䙁䅳睕兂䕁䅣睘䑂䝁䄸兢睂䝁䅅杢㕂䙁䄸睓求䡁䅫睕あ䝁䅅䅤穂䙁䄸杤硁䍁䄴䅥獂䡁䅍兢摂䕁䅉兙獂䝁䅅杢橂䝁䅕睘呂䝁䅧党求䡁䅑光歁䕁䅍䅊硁䑁䅅杏歁䕁䅍䅊硁䑁䅑免䅁佁䙯䅁楂䅁䅁睗呂䙁䅁睒時䕁䅍睢瑂䡁䅁兙畂䡁䅫睘䱂䝁䅕入呂䡁䅑兙あ䡁䅍睘㉂䑁䅅杌㑂䝁䅷督瑂䙁䄰村桂䝁䅷兙畂䝁䅍党時䙁䅍䅡求䝁䅕䅤桁䍁䅑睑歁䑁䅙䅁潄兂䅁来䅁䙁䅳睕兂䕁䅣睘䑂䝁䄸兢睂䝁䅅杢㕂䙁䄸睓求䡁䅫睕あ䝁䅅䅤穂䙁䄸杤硁䍁䄴䅥獂䡁䅍兢摂䕁䅍兙睂䝁䅫䅤桂䝁䅷睘呂䡁䅑杣ㅂ䝁䅍䅤ㅂ䡁䅉党時䙁䅍兤瑂䝁䄰兙祂䡁䅫光歁䕁䅍䅊㍁䅁䅁䅁䅙䥁䅧䅁扂䙁䅍䅕䡂䙁䄸睑療䝁䄰䅣桂䝁䄴入時䕁䅳党㕂䙁䅍䅤桂䡁䅑督時䡁䅙免畁䡁䅧䅢穂䝁䄰兘䑂䝁䅅䅣灂䡁䅑兙獂䙁䄸睕あ䡁䅉兤橂䡁䅑兤祂䝁䅕睘呂䡁䅕兢瑂䝁䅅杣㕂䍁䅅䅊䕂䍁䅑杍㕁䑁䅯䅊䕂䍁䅑䅏睁䅁䅁杁䅙䝁䅙䅁扂䙁䅍䅕䡂䙁䄸睑療䝁䄰䅣桂䝁䄴入時䕁䅳党㕂䙁䅍䅤桂䡁䅑督時䡁䅙免畁䡁䅧䅢穂䝁䄰兘䑂䝁䅅䅣灂䡁䅑兙獂䝁䅫来桂䡁䅑兡療䝁䄴光歁䕁䅍䅊ぁ䑁䅣䅁い兂䅁杚䅁䙁䅳睕兂䕁䅣睘䑂䝁䄸兢睂䝁䅅杢㕂䙁䄸睓求䡁䅫睕あ䝁䅅䅤穂䙁䄸杤硁䍁䄴䅥獂䡁䅍兢摂䕁䅍兙睂䝁䅫䅤桂䝁䅷兡㙂䝁䅅䅤灂䝁䄸杢桁䍁䅑睑歁䑁䅑䅏䅁偁䙧䅁睂䅁䅁睗呂䙁䅁睒時䕁䅍睢瑂䡁䅁兙畂䡁䅫睘䱂䝁䅕入呂䡁䅑兙あ䡁䅍睘㉂䑁䅅杌㑂䝁䅷督瑂䙁䄰睑桂䡁䅁兡あ䝁䅅䅢灂䡁䅯兙あ䝁䅫睢畂䍁䅅䅊䑂䍁䅑兏㙁䍁䅑睑歁䑁䅉兎䅁偁䙉䅁祂䅁䅁睗呂䙁䅁睒時䕁䅍睢瑂䡁䅁兙畂䡁䅫睘䱂䝁䅕入呂䡁䅑兙あ䡁䅍睘㉂䑁䅅杌㑂䝁䅷督瑂䙁䄰睑桂䡁䅁兡あ䝁䅅䅢灂䡁䅯兙あ䝁䅫睢畂䍁䅅䅊䙂䍁䅑兎硁䑁䅯䅊䭂䍁䅑兎硁䅁䅁儹䅕䡁䅉䅁扂䙁䅍䅕䡂䙁䄸睑療䝁䄰䅣桂䝁䄴入時䕁䅳党㕂䙁䅍䅤桂䡁䅑督時䡁䅙免畁䡁䅧䅢穂䝁䄰兘䑂䝁䅅䅣灂䡁䅑兙獂䝁䅫来桂䡁䅑兡療䝁䄴光歁䕁䅕䅊ㅁ䑁䅉杏歁䕁䅯䅊ㅁ䑁䅉䅁㍄兂䅁䅚䅁䙁䅳睕兂䕁䅣睘䑂䝁䄸兢睂䝁䅅杢㕂䙁䄸睓求䡁䅫睕あ䝁䅅䅤穂䙁䄸杤硁䍁䄴䅥獂䡁䅍兢摂䕁䅍兙穂䝁䅧睘䝂䝁䅷睢㍂䍁䅅䅊䙂䍁䅑睎㙁䍁䅑䅕歁䑁䅣䅁癄兂䅁杘䅁䙁䅳睕兂䕁䅣睘䑂䝁䄸兢睂䝁䅅杢㕂䙁䄸睓求䡁䅫睕あ䝁䅅䅤穂䙁䄸杤硁䍁䄴䅥獂䡁䅍兢摂䕁䅳党㕂䙁䄸睕あ䝁䅅䅤穂䍁䅅䅊䍂䍁䅑免睁䑁䅙䅁奄兂䅁䅘䅁䙁䅳睕兂䕁䅣睘䑂䝁䄸兢睂䝁䅅杢㕂䙁䄸睓求䡁䅫睕あ䝁䅅䅤穂䙁䄸杤硁䍁䄴䅥獂䡁䅍兢摂䕁䅳党㕂䙁䄸睕あ䝁䅅䅤穂䍁䅅䅊䍂䍁䅑杍ㅁ䅁䅁䄰䅕䙁䅷䅁扂䙁䅍䅕䡂䙁䄸睑療䝁䄰䅣桂䝁䄴入時䕁䅳党㕂䙁䅍䅤桂䡁䅑督時䡁䅙免畁䡁䅧䅢穂䝁䄰兘䱂䝁䅕入時䙁䅍䅤桂䡁䅑督桁䍁䅑村歁䑁䅉李䅁乁䙑䅁捂䅁䅁睗呂䙁䅁睒時䕁䅍睢瑂䡁䅁兙畂䡁䅫睘䱂䝁䅕入呂䡁䅑兙あ䡁䅍睘㉂䑁䅅杌㑂䝁䅷督瑂䙁䄰睓求䡁䅫睘呂䡁䅑兙あ䡁䅍光歁䕁䅉䅊㉁䑁䅉䅁捄兂䅁䅢䅁䙁䅳睕兂䕁䅣睘䑂䝁䄸兢睂䝁䅅杢㕂䙁䄸睓求䡁䅫睕あ䝁䅅䅤穂䙁䄸杤硁䍁䄴䅥獂䡁䅍兢摂䕁䅳党㕂䙁䄸睕あ䝁䅅䅤穂䍁䅅䅊䑂䍁䅑免睁䑁䅫杏歁䕁䅍䅊硁䑁䅅兎䅁乁䙯䅁獂䅁䅁睗呂䙁䅁睒時䕁䅍睢瑂䡁䅁兙畂䡁䅫睘䱂䝁䅕入呂䡁䅑兙あ䡁䅍睘㉂䑁䅅杌㑂䝁䅷督瑂䙁䄰睓求䡁䅫睘呂䡁䅑兙あ䡁䅍光歁䕁䅕䅊硁䑁䅁李㙁䍁䅑睒歁䑁䅅䅍㉁䅁䅁儲䅕䝁䅷䅁扂䙁䅍䅕䡂䙁䄸睑療䝁䄰䅣桂䝁䄴入時䕁䅳党㕂䙁䅍䅤桂䡁䅑督時䡁䅙免畁䡁䅧䅢穂䝁䄰兘䱂䝁䅕入時䙁䅍䅤桂䡁䅑督桁䍁䅑兒歁䑁䅅䅍㍁䑁䅯䅊䡂䍁䅑免睁䑁䅣䅁扄兂䅁䅡䅁䙁䅳睕兂䕁䅣睘䑂䝁䄸兢睂䝁䅅杢㕂䙁䄸睓求䡁䅫睕あ䝁䅅䅤穂䙁䄸杤硁䍁䄴䅥獂䡁䅍兢摂䕁䅳党㕂䙁䄸睕あ䝁䅅䅤穂䍁䅅䅊䙂䍁䅑杍㉁䑁䅯䅊䭂䍁䅑杍㉁䅁䅁眰䅕䙁䅷䅁扂䙁䅍䅕䡂䙁䄸睑療䝁䄰䅣桂䝁䄴入時䕁䅳党㕂䙁䅍䅤桂䡁䅑督時䡁䅙免畁䡁䅧䅢穂䝁䄰兘䱂䝁䅕入時䙁䅍䅤桂䡁䅑督桁䍁䅑兒歁䑁䅙杍䅁乁䘰䅁捂䅁䅁睗呂䙁䅁睒時䕁䅍睢瑂䡁䅁兙畂䡁䅫睘䱂䝁䅕入呂䡁䅑兙あ䡁䅍睘㉂䑁䅅杌㑂䝁䅷督瑂䙁䄰睓求䡁䅫睘呂䡁䅑兙あ䡁䅍光歁䙁䅍䅊ㅁ䑁䅕䅁杄兂䅁䅚䅁䙁䅳睕兂䕁䅣睘䑂䝁䄸兢睂䝁䅅杢㕂䙁䄸睓求䡁䅫睕あ䝁䅅䅤穂䙁䄸杤硁䍁䄴䅥獂䡁䅍兢摂䙁䅉兙あ䝁䅫睢穂䍁䅅䅊䑂䍁䅑免硁䑁䅯䅊䑂䍁䅑免ㅁ䑁䅉䅁䝁杂䅁杘䅁䙁䅳睕兂䕁䅣睘䑂䝁䄸兢睂䝁䅅杢㕂䙁䄸睓求䡁䅫睕あ䝁䅅䅤穂䙁䄸杤硁䍁䄴䅥獂䡁䅍兢摂䙁䅉兙あ䝁䅫睢穂䍁䅅䅊䕂䍁䅑李㙁䍁䅑兓歁䑁䅙䅁䙁杂䅁杖䅁䙁䅳睕兂䕁䅣睘䑂䝁䄸兢睂䝁䅅杢㕂䙁䄸睓求䡁䅫睕あ䝁䅅䅤穂䙁䄸杤祁䍁䄴䅥獂䡁䅍兢摂䙁䅍䅡求䝁䅕䅤硁䍁䅅䅊䡂䍁䅑䅎穁䅁䅁䅲䅙䙁䄴䅁扂䙁䅍䅕䡂䙁䄸睑療䝁䄰䅣桂䝁䄴入時䕁䅳党㕂䙁䅍䅤桂䡁䅑督時䡁䅙免畁䡁䅧䅢穂䝁䄰兘卂䝁䅅䅤灂䝁䄸督桁䍁䅑䅒歁䑁䅣杏歁䕁䅫䅊㍁䅁䅁睂䅙䝁䅯䅁扂䙁䅍䅕䡂䙁䄸睑療䝁䄰䅣桂䝁䄴入時䕁䅳党㕂䙁䅍䅤桂䡁䅑督時䡁䅙免畁䡁䅧䅢穂䝁䄰兘呂䡁䅕䅣睂䝁䅷党瑂䝁䅕杢あ䝁䅅䅢桁䍁䅑䅒歁䑁䅙杏歁䕁䅫䅊㉁䅁䅁元䅙䙁䅷䅁扂䙁䅍䅕䡂䙁䄸睑療䝁䄰䅣桂䝁䄴入時䕁䅳党㕂䙁䅍䅤桂䡁䅑督時䡁䅙杍畁䡁䅧䅢穂䝁䄰兘乂䡁䅕䅢あ䝁䅫䅣獂䝁䅕督桁䍁䅑䅒歁䑁䅅免䅁䡁䝍䅁潂䅁䅁睗呂䙁䅁睒時䕁䅍睢瑂䡁䅁兙畂䡁䅫睘䱂䝁䅕入呂䡁䅑兙あ䡁䅍睘㉂䑁䅉杌㑂䝁䅷督瑂䙁䄰兔ㅂ䝁䅷䅤灂䡁䅁䅢求䡁䅍光歁䕁䅑䅊硁䑁䅉杏歁䕁䅑䅊硁䑁䅍䅁あ杂䅁䅡䅁䙁䅳睕兂䕁䅣睘䑂䝁䄸兢睂䝁䅅杢㕂䙁䄸睓求䡁䅫睕あ䝁䅅䅤穂䙁䄸杤祁䍁䄴䅥獂䡁䅍兢摂䕁䄰兤獂䡁䅑兡睂䝁䅷党穂䍁䅅䅊䕂䍁䅑免ぁ䑁䅯䅊䕂䍁䅑免ㅁ䅁䅁䅣䅙䙁䅙䅁扂䙁䅍䅕䡂䙁䄸睑療䝁䄰䅣桂䝁䄴入時䕁䅳党㕂䙁䅍䅤桂䡁䅑督時䡁䅙杍畁䡁䅧䅢穂䝁䄰兘呂䝁䅧党求䡁䅑免桁䍁䅑兑䍂䍁䅑䅎䅁䥁䝍䅁坂䅁䅁睗呂䙁䅁睒時䕁䅍睢瑂䡁䅁兙畂䡁䅫睘䱂䝁䅕入呂䡁䅑兙あ䡁䅍睘㉂䑁䅉杌㑂䝁䅷督瑂䙁䄰睕潂䝁䅕党あ䑁䅅光歁䕁䅉䅊硁䑁䅅䅁⭂杂䅁杖䅁䙁䅳睕兂䕁䅣睘䑂䝁䄸兢睂䝁䅅杢㕂䙁䄸睓求䡁䅫睕あ䝁䅅䅤穂䙁䄸杤祁䍁䄴䅥獂䡁䅍兢摂䙁䅍䅡求䝁䅕䅤硁䍁䅅䅊䍂䍁䅑䅎穁䅁䅁杰䅙䙁䅙䅁扂䙁䅍䅕䡂䙁䄸睑療䝁䄰䅣桂䝁䄴入時䕁䅳党㕂䙁䅍䅤桂䡁䅑督時䡁䅙杍畁䡁䅧䅢穂䝁䄰兘呂䝁䅧党求䡁䅑免桁䍁䅑睑歁䑁䅅免䅁䥁䝧䅁坂䅁䅁睗呂䙁䅁睒時䕁䅍睢瑂䡁䅁兙畂䡁䅫睘䱂䝁䅕入呂䡁䅑兙あ䡁䅍睘㉂䑁䅉杌㑂䝁䅷督瑂䙁䄰睕潂䝁䅕党あ䑁䅅光歁䕁䅍䅊㍁䑁䅕䅁ㅃ杂䅁杖䅁䙁䅳睕兂䕁䅣睘䑂䝁䄸兢睂䝁䅅杢㕂䙁䄸睓求䡁䅫睕あ䝁䅅䅤穂䙁䄸杤祁䍁䄴䅥獂䡁䅍兢摂䙁䅍䅡求䝁䅕䅤硁䍁䅅䅊䭂䍁䅑免硁䅁䅁䅯䅙䙁䅙䅁扂䙁䅍䅕䡂䙁䄸睑療䝁䄰䅣桂䝁䄴入時䕁䅳党㕂䙁䅍䅤桂䡁䅑督時䡁䅙杍畁䡁䅧䅢穂䝁䄰兘呂䝁䅧党求䡁䅑免桁䍁䅑䅓歁䑁䅣兎䅁䱁䝑䅁坂䅁䅁睗呂䙁䅁睒時䕁䅍睢瑂䡁䅁兙畂䡁䅫睘䱂䝁䅕入呂䡁䅑兙あ䡁䅍睘㉂䑁䅉杌㑂䝁䅷督瑂䙁䄰睕潂䝁䅕党あ䑁䅅光歁䕁䅯䅊ぁ䑁䅍䅁癃杂䅁䅨䅁䍁䅣睗䑂䝁䄸䅣㕂䍁䅁睢浂䍁䅁睕兂䕁䅣睘䑂䝁䄸兢睂䝁䅅杢㕂䙁䄸睓求䡁䅫睕あ䝁䅅䅤穂䙁䄸杤祁䙁䄸杢求䡁䅣杌㑂䝁䅷督瑂䙁䄰睓求䡁䅫睘呂䡁䅑兙あ䡁䅍睊桁䍁䅑睑歁䑁䅉䅏㙁䍁䅑睑歁䑁䅕杍䅁䍁䡧䅁㑂䅁䅁睊扂䕁䅍睢睂䡁䅫䅉療䝁䅙䅉呂䙁䅁睒時䕁䅍睢瑂䡁䅁兙畂䡁䅫睘䱂䝁䅕入呂䡁䅑兙あ䡁䅍睘㉂䑁䅉睘畂䝁䅕睤畁䡁䅧䅢穂䝁䄰兘䱂䝁䅕入時䙁䅍䅤桂䡁䅑督湁䍁䅅䅊呂䍁䅑兎ㅁ䅁䅁杍䅣䥁䅑䅁湁䙁䅳睑療䡁䅁入杁䝁䄸杚杁䙁䅍䅕䡂䙁䄸睑療䝁䄰䅣桂䝁䄴入時䕁䅳党㕂䙁䅍䅤桂䡁䅑督時䡁䅙杍時䝁䄴党㍂䍁䄴䅥獂䡁䅍兢摂䕁䅳党㕂䙁䄸睕あ䝁䅅䅤穂䍁䅣光歁䙁䅙䅊ㅁ䑁䅣杏歁䙁䅣䅊ㅁ䑁䅣䅁ぁ睂䅁䅨䅁䍁䅣睗䑂䝁䄸䅣㕂䍁䅁睢浂䍁䅁睕兂䕁䅣睘䑂䝁䄸兢睂䝁䅅杢㕂䙁䄸睓求䡁䅫睕あ䝁䅅䅤穂䙁䄸杤祁䙁䄸杢求䡁䅣杌㑂䝁䅷督瑂䙁䄰睓求䡁䅫睘呂䡁䅑兙あ䡁䅍睊桁䍁䅑䅖歁䑁䅕䅏㙁䍁䅑䅖歁䑁䅙免䅁䑁䡕䅁㙂䅁䅁睊扂䕁䅍睢睂䡁䅫䅉療䝁䅙䅉呂䙁䅁睒時䕁䅍睢瑂䡁䅁兙畂䡁䅫睘䱂䝁䅕入呂䡁䅑兙あ䡁䅍睘㉂䑁䅉睘畂䝁䅕睤畁䡁䅧䅢穂䝁䄰兘䱂䝁䅕入時䙁䅍䅤桂䡁䅑督湁䍁䅅䅊䍂䍁䅑免睁䑁䅙䅁㉁睂䅁䅩䅁䍁䅣睗䑂䝁䄸䅣㕂䍁䅁睢浂䍁䅁睕兂䕁䅣睘䑂䝁䄸兢睂䝁䅅杢㕂䙁䄸睓求䡁䅫睕あ䝁䅅䅤穂䙁䄸杤祁䙁䄸杢求䡁䅣杌㑂䝁䅷督瑂䙁䄰睓求䡁䅫睘呂䡁䅑兙あ䡁䅍睊桁䍁䅑睑歁䑁䅅䅍㕁䑁䅯䅊䑂䍁䅑免硁䑁䅕䅁㑁睂䅁䅩䅁䍁䅣睗䑂䝁䄸䅣㕂䍁䅁睢浂䍁䅁睕兂䕁䅣睘䑂䝁䄸兢睂䝁䅅杢㕂䙁䄸睓求䡁䅫睕あ䝁䅅䅤穂䙁䄸杤祁䙁䄸杢求䡁䅣杌㑂䝁䅷督瑂䙁䄰睓求䡁䅫睘呂䡁䅑兙あ䡁䅍睊桁䍁䅑杒歁䑁䅅䅍㍁䑁䅯䅊䥂䍁䅑免睁䑁䅣䅁㕁睂䅁来䅁䍁䅣睗䑂䝁䄸䅣㕂䍁䅁睢浂䍁䅁睕兂䕁䅣睘䑂䝁䄸兢睂䝁䅅杢㕂䙁䄸睓求䡁䅫睕あ䝁䅅䅤穂䙁䄸杤祁䙁䄸杢求䡁䅣杌㑂䝁䅷督瑂䙁䄰睓求䡁䅫睘呂䡁䅑兙あ䡁䅍睊桁䍁䅑村歁䑁䅅䅍㍁䅁䅁杏䅣䡁䅯䅁湁䙁䅳睑療䡁䅁入杁䝁䄸杚杁䙁䅍䅕䡂䙁䄸睑療䝁䄰䅣桂䝁䄴入時䕁䅳党㕂䙁䅍䅤桂䡁䅑督時䡁䅙杍時䝁䄴党㍂䍁䄴䅥獂䡁䅍兢摂䕁䅳党㕂䙁䄸睕あ䝁䅅䅤穂䍁䅣光歁䕁䅕䅊硁䑁䅁李䅁䑁䡳䅁䕃䅁䅁睊扂䕁䅍睢睂䡁䅫䅉療䝁䅙䅉呂䙁䅁睒時䕁䅍睢瑂䡁䅁兙畂䡁䅫睘䱂䝁䅕入呂䡁䅑兙あ䡁䅍睘㉂䑁䅉睘畂䝁䅕睤畁䡁䅧䅢穂䝁䄰兘䩂䝁䄴睙療䝁䄰党時䙁䅍䅤桂䡁䅑党瑂䝁䅕杢あ䍁䅣光歁䕁䅍䅊㉁䅁䅁材䅣䥁䄴䅁湁䙁䅳睑療䡁䅁入杁䝁䄸杚杁䙁䅍䅕䡂䙁䄸睑療䝁䄰䅣桂䝁䄴入時䕁䅳党㕂䙁䅍䅤桂䡁䅑督時䡁䅙杍時䝁䄴党㍂䍁䄴䅥獂䡁䅍兢摂䕁䅫杢橂䝁䄸兢求䙁䄸睕あ䝁䅅䅤求䝁䄰党畂䡁䅑睊桁䍁䅑兒歁䑁䅙杏歁䙁䅁䅊㉁䅁䅁睐䅣䥁䅧䅁湁䙁䅳睑療䡁䅁入杁䝁䄸杚杁䙁䅍䅕䡂䙁䄸睑療䝁䄰䅣桂䝁䄴入時䕁䅳党㕂䙁䅍䅤桂䡁䅑督時䡁䅙杍時䝁䄴党㍂䍁䄴䅥獂䡁䅍兢摂䕁䅉兙獂䝁䅅杢橂䝁䅕睘呂䝁䅧党求䡁䅑睊桁䍁䅑兒歁䑁䅣杏歁䙁䅁䅊㍁䅁䅁兒䅣䥁䅑䅁湁䙁䅳睑療䡁䅁入杁䝁䄸杚杁䙁䅍䅕䡂䙁䄸睑療䝁䄰䅣桂䝁䄴入時䕁䅳党㕂䙁䅍䅤桂䡁䅑督時䡁䅙杍時䝁䄴党㍂䍁䄴䅥獂䡁䅍兢摂䕁䅍兙穂䝁䅧睘䝂䝁䅷睢㍂䍁䅣光歁䕁䅍䅊硁䑁䅅杏歁䕁䅍䅊㕁䑁䅙䅁䥂睂䅁䅧䅁䍁䅣睗䑂䝁䄸䅣㕂䍁䅁睢浂䍁䅁睕兂䕁䅣睘䑂䝁䄸兢睂䝁䅅杢㕂䙁䄸睓求䡁䅫睕あ䝁䅅䅤穂䙁䄸杤祁䙁䄸杢求䡁䅣杌㑂䝁䅷督瑂䙁䄰睑桂䡁䅍䅡時䕁䅙䅢療䡁䅣睊桁䍁䅑兒歁䑁䅣杏歁䙁䅁䅊㍁䅁䅁兓䅣䥁䅷䅁湁䙁䅳睑療䡁䅁入杁䝁䄸杚杁䙁䅍䅕䡂䙁䄸睑療䝁䄰䅣桂䝁䄴入時䕁䅳党㕂䙁䅍䅤桂䡁䅑督時䡁䅙杍時䝁䄴党㍂䍁䄴䅥獂䡁䅍兢摂䕁䅍兙睂䝁䅫䅤桂䝁䅷兡㙂䝁䅅䅤灂䝁䄸杢湁䍁䅅䅊䑂䍁䅑兏㙁䍁䅑睑歁䑁䅉䅎䅁䕁䡷䅁䍃䅁䅁睊扂䕁䅍睢睂䡁䅫䅉療䝁䅙䅉呂䙁䅁睒時䕁䅍睢瑂䡁䅁兙畂䡁䅫睘䱂䝁䅕入呂䡁䅑兙あ䡁䅍睘㉂䑁䅉睘畂䝁䅕睤畁䡁䅧䅢穂䝁䄰兘䑂䝁䅅䅣灂䡁䅑兙獂䝁䅫来桂䡁䅑兡療䝁䄴睊桁䍁䅑睑歁䑁䅑李䅁䕁䠴䅁佃䅁䅁睊扂䕁䅍睢睂䡁䅫䅉療䝁䅙䅉呂䙁䅁睒時䕁䅍睢瑂䡁䅁兙畂䡁䅫睘䱂䝁䅕入呂䡁䅑兙あ䡁䅍睘㉂䑁䅉睘畂䝁䅕睤畁䡁䅧䅢穂䝁䄰兘䑂䝁䅅䅣灂䡁䅑兙獂䝁䅫来桂䡁䅑兡療䝁䄴睊桁䍁䅑睑歁䑁䅕杍㙁䍁䅑睑歁䑁䅕睍䅁䙁䡁䅁佃䅁䅁睊扂䕁䅍睢睂䡁䅫䅉療䝁䅙䅉呂䙁䅁睒時䕁䅍睢瑂䡁䅁兙畂䡁䅫睘䱂䝁䅕入呂䡁䅑兙あ䡁䅍睘㉂䑁䅉睘畂䝁䅕睤畁䡁䅧䅢穂䝁䄰兘䑂䝁䅅䅣灂䡁䅑兙獂䝁䅫来桂䡁䅑兡療䝁䄴睊桁䍁䅑兒歁䑁䅑睎㙁䍁䅑杓歁䑁䅑睎䅁䙁䡕䅁坃䅁䅁
A5: 睊扂䕁䅍睢睂䡁䅫䅉療䝁䅙䅉呂䙁䅁睒時䕁䅍睢瑂䡁䅁兙畂䡁䅫睘䱂䝁䅕入呂䡁䅑兙あ䡁䅍睘㉂䑁䅉睘畂䝁䅕睤畁䡁䅧䅢穂䝁䄰兘䑂䝁䅅䅣灂䡁䅑兙獂䙁䄸睕あ䡁䅉兤橂䡁䅑兤祂䝁䅕睘呂䡁䅕兢瑂䝁䅅杣㕂䍁䅣光歁䕁䅍䅊㉁䅁䅁杖䅣䭁䅁䅁湁䙁䅳睑療䡁䅁入杁䝁䄸杚杁䙁䅍䅕䡂䙁䄸睑療䝁䄰䅣桂䝁䄴入時䕁䅳党㕂䙁䅍䅤桂䡁䅑督時䡁䅙杍時䝁䄴党㍂䍁䄴䅥獂䡁䅍兢摂䕁䅍兙睂䝁䅫䅤桂䝁䅷睘呂䡁䅑杣ㅂ䝁䅍䅤ㅂ䡁䅉党時䙁䅍兤瑂䝁䄰兙祂䡁䅫睊桁䍁䅑兒歁䑁䅙杏歁䕁䄸䅊㉁䅁䅁睖䅣䕁䅷䅁乂䝁䅫睙祂䝁䄸督療䝁䅙䅤杁䕁䅍睢祂䡁䅁睢祂䝁䅅䅤灂䝁䄸杢杁䍁䅧杔䉂䙁䅍䅒䉂䙁䅅睒呂䑁䅯兔呂䕁䅙䅖灁䅁䅁朲䅣䭁䅙䅁湁䙁䅳睑療䡁䅁入杁䝁䄸杚杁䙁䅍䅕䡂䙁䄸睑療䝁䄰䅣桂䝁䄴入時䕁䅳党㕂䙁䅍䅤桂䡁䅑督時䡁䅙杍時䝁䄴党㍂䍁䄴䅥獂䡁䅍兢摂䕁䅍兙睂䝁䅫䅤桂䝁䅷睘呂䡁䅑杣ㅂ䝁䅍䅤ㅂ䡁䅉党時䙁䅍兤瑂䝁䄰兙祂䡁䅫睊桁䍁䅑睑歁䑁䅅兎㙁䍁䅑睑歁䑁䅅睎睁䅁䅁䅗䅣䭁䅑䅁湁䙁䅳睑療䡁䅁入杁䝁䄸杚杁䙁䅍䅕䡂䙁䄸睑療䝁䄰䅣桂䝁䄴入時䕁䅳党㕂䙁䅍䅤桂䡁䅑督時䡁䅙杍時䝁䄴党㍂䍁䄴䅥獂䡁䅍兢摂䕁䅍兙睂䝁䅫䅤桂䝁䅷睘呂䡁䅑杣ㅂ䝁䅍䅤ㅂ䡁䅉党時䙁䅍兤瑂䝁䄰兙祂䡁䅫睊桁䍁䅑䅒歁䑁䅉兏㙁䍁䅑䅒歁䑁䅧䅍䅁䙁䡷䅁歃䅁䅁睊扂䕁䅍睢睂䡁䅫䅉療䝁䅙䅉呂䙁䅁睒時䕁䅍睢瑂䡁䅁兙畂䡁䅫睘䱂䝁䅕入呂䡁䅑兙あ䡁䅍睘㉂䑁䅉睘畂䝁䅕睤畁䡁䅧䅢穂䝁䄰兘䑂䝁䅅䅣灂䡁䅑兙獂䙁䄸睕あ䡁䅉兤橂䡁䅑兤祂䝁䅕睘呂䡁䅕兢瑂䝁䅅杣㕂䍁䅣光歁䕁䅙䅊硁䑁䅅杏歁䙁䅁䅊硁䑁䅅䅁摂睂䅁䅣䅁䍁䅣睗䑂䝁䄸䅣㕂䍁䅁睢浂䍁䅁睕兂䕁䅣睘䑂䝁䄸兢睂䝁䅅杢㕂䙁䄸睓求䡁䅫睕あ䝁䅅䅤穂䙁䄸杤祁䙁䄸杢求䡁䅣杌㑂䝁䅷督瑂䙁䄰杕桂䡁䅑兡療䡁䅍睊桁䍁䅑睑歁䑁䅙䅁敂睂䅁䅦䅁䍁䅣睗䑂䝁䄸䅣㕂䍁䅁睢浂䍁䅁睕兂䕁䅣睘䑂䝁䄸兢睂䝁䅅杢㕂䙁䄸睓求䡁䅫睕あ䝁䅅䅤穂䙁䄸杤祁䙁䄸杢求䡁䅣杌㑂䝁䅷督瑂䙁䄰睕ㅂ䡁䅁䅣獂䝁䅕兢求䝁䄴䅤桂䝁䅷睊桁䍁䅑睑歁䑁䅙䅁楂睂䅁䅪䅁䍁䅣睗䑂䝁䄸䅣㕂䍁䅁睢浂䍁䅁睕兂䕁䅣睘䑂䝁䄸兢睂䝁䅅杢㕂䙁䄸睓求䡁䅫睕あ䝁䅅䅤穂䙁䄸杤祁䙁䄸杢求䡁䅣杌㑂䝁䅷督瑂䙁䄰睕ㅂ䡁䅁䅣獂䝁䅕兢求䝁䄴䅤桂䝁䅷睊桁䍁䅑睑歁䑁䅅免㙁䍁䅑睑歁䑁䅅李㑁䅁䅁䅚䅣䥁䅙䅁湁䙁䅳睑療䡁䅁入杁䝁䄸杚杁䙁䅍䅕䡂䙁䄸睑療䝁䄰䅣桂䝁䄴入時䕁䅳党㕂䙁䅍䅤桂䡁䅑督時䡁䅙杍時䝁䄴党㍂䍁䄴䅥獂䡁䅍兢摂䙁䅍兤睂䡁䅁䅢求䝁䄰党畂䡁䅑兙獂䍁䅣光歁䕁䅑䅊㍁䑁䅯䅊䩂䍁䅑睎䅁䝁䡕䅁䝃䅁䅁睊扂䕁䅍睢睂䡁䅫䅉療䝁䅙䅉呂䙁䅁睒時䕁䅍睢瑂䡁䅁兙畂䡁䅫睘䱂䝁䅕入呂䡁䅑兙あ䡁䅍睘㉂䑁䅉睘畂䝁䅕睤畁䡁䅧䅢穂䝁䄰兘兂䝁䅕杢穂䝁䅫睢畂䍁䄰睔兂䕁䅕村湁䍁䅅䅊䕂䍁䅑李㙁䍁䅑兓歁䑁䅙䅁湂睂䅁杤䅁䍁䅣睗䑂䝁䄸䅣㕂䍁䅁睢浂䍁䅁睕兂䕁䅣睘䑂䝁䄸兢睂䝁䅅杢㕂䙁䄸睓求䡁䅫睕あ䝁䅅䅤穂䙁䄸杤祁䙁䄸杢求䡁䅣杌㑂䝁䅷督瑂䙁䄰睓求䡁䅫睘呂䡁䅑兙あ䡁䅍睊桁䍁䅑杒歁䑁䅫䅁牂睂䅁䅥䅁䍁䅣睗䑂䝁䄸䅣㕂䍁䅁睢浂䍁䅁睕兂䕁䅣睘䑂䝁䄸兢睂䝁䅅杢㕂䙁䄸睓求䡁䅫睕あ䝁䅅䅤穂䙁䄸杤祁䙁䄸杢求䡁䅣杌㑂䝁䅷督瑂䙁䄰睓求䡁䅫睘呂䡁䅑兙あ䡁䅍睊桁䍁䅑杒歁䑁䅅兎䅁䝁䠰䅁捃䅁䅁睊扂䕁䅍睢睂䡁䅫䅉療䝁䅙䅉呂䙁䅁睒時䕁䅍睢瑂䡁䅁兙畂䡁䅫睘䱂䝁䅕入呂䡁䅑兙あ䡁䅍睘㉂䑁䅉睘畂䝁䅕睤畁䡁䅧䅢穂䝁䄰兘䑂䝁䅅䅣灂䡁䅑兙獂䙁䄸睕あ䡁䅉兤橂䡁䅑兤祂䝁䅕睘杁䕁䅑党あ䝁䅅兡獂䡁䅍䅉湁䍁䅅䅊䕂䍁䅑䅎ぁ䅁䅁睢䅣䩁䅷䅁湁䙁䅳睑療䡁䅁入杁䝁䄸杚杁䙁䅍䅕䡂䙁䄸睑療䝁䄰䅣桂䝁䄴入時䕁䅳党㕂䙁䅍䅤桂䡁䅑督時䡁䅙杍時䝁䄴党㍂䍁䄴䅥獂䡁䅍兢摂䕁䅍兙睂䝁䅫䅤桂䝁䅷睘呂䡁䅑杣ㅂ䝁䅍䅤ㅂ䡁䅉党時䍁䅁䅒求䡁䅑兙灂䝁䅷督杁䍁䅣光歁䕁䅅兑歁䑁䅙䅁睂睂䅁䅮䅁䍁䅣睗䑂䝁䄸䅣㕂䍁䅁睢浂䍁䅁睕兂䕁䅣睘䑂䝁䄸兢睂䝁䅅杢㕂䙁䄸睓求䡁䅫睕あ䝁䅅䅤穂䙁䄸杤祁䙁䄸杢求䡁䅣杌㑂䝁䅷督瑂䙁䄰睑桂䡁䅁兡あ䝁䅅䅢時䙁䅍䅤祂䡁䅕睙あ䡁䅕杣求䙁䄸䅉䕂䝁䅕䅤桂䝁䅫䅢穂䍁䅁睊桁䍁䅑䅒歁䑁䅅杍䅁䡁䡅䅁捃䅁䅁睊扂䕁䅍睢睂䡁䅫䅉療䝁䅙䅉呂䙁䅁睒時䕁䅍睢瑂䡁䅁兙畂䡁䅫睘䱂䝁䅕入呂䡁䅑兙あ䡁䅍睘㉂䑁䅉睘畂䝁䅕睤畁䡁䅧䅢穂䝁䄰兘䑂䝁䅅䅣灂䡁䅑兙獂䙁䄸睕あ䡁䅉兤橂䡁䅑兤祂䝁䅕睘杁䕁䅑党あ䝁䅅兡獂䡁䅍䅉湁䍁䅅䅊䱂䍁䅑睎㉁䅁䅁督䅣䩁䅷䅁湁䙁䅳睑療䡁䅁入杁䝁䄸杚杁䙁䅍䅕䡂䙁䄸睑療䝁䄰䅣桂䝁䄴入時䕁䅳党㕂䙁䅍䅤桂䡁䅑督時䡁䅙杍時䝁䄴党㍂䍁䄴䅥獂䡁䅍兢摂䕁䅍兙睂䝁䅫䅤桂䝁䅷睘呂䡁䅑杣ㅂ䝁䅍䅤ㅂ䡁䅉党時䍁䅁䅒求䡁䅑兙灂䝁䅷督杁䍁䅣光歁䕁䅕䅊硁䑁䅉䅁ㅂ睂䅁䅮䅁䍁䅣睗䑂䝁䄸䅣㕂䍁䅁睢浂䍁䅁睕兂䕁䅣睘䑂䝁䄸兢睂䝁䅅杢㕂䙁䄸睓求䡁䅫睕あ䝁䅅䅤穂䙁䄸杤祁䙁䄸杢求䡁䅣杌㑂䝁䅷督瑂䙁䄰睑桂䡁䅁兡あ䝁䅅䅢時䙁䅍䅤祂䡁䅕睙あ䡁䅕杣求䙁䄸䅉䕂䝁䅕䅤桂䝁䅫䅢穂䍁䅁睊桁䍁䅑䅓歁䑁䅅杍䅁䡁䡙䅁捃䅁䅁睊扂䕁䅍睢睂䡁䅫䅉療䝁䅙䅉呂䙁䅁睒時䕁䅍睢瑂䡁䅁兙畂䡁䅫睘䱂䝁䅕入呂䡁䅑兙あ䡁䅍睘㉂䑁䅉睘畂䝁䅕睤畁䡁䅧䅢穂䝁䄰兘䑂䝁䅅䅣灂䡁䅑兙獂䙁䄸睕あ䡁䅉兤橂䡁䅑兤祂䝁䅕睘杁䕁䅑党あ䝁䅅兡獂䡁䅍䅉湁䍁䅅䅊䝂䍁䅑免祁䅁䅁睤䅣䩁䅷䅁湁䙁䅳睑療䡁䅁入杁䝁䄸杚杁䙁䅍䅕䡂䙁䄸睑療䝁䄰䅣桂䝁䄴入時䕁䅳党㕂䙁䅍䅤桂䡁䅑督時䡁䅙杍時䝁䄴党㍂䍁䄴䅥獂䡁䅍兢摂䕁䅍兙睂䝁䅫䅤桂䝁䅷睘呂䡁䅑杣ㅂ䝁䅍䅤ㅂ䡁䅉党時䍁䅁䅒求䡁䅑兙灂䝁䅷督杁䍁䅣光歁䕁䅯䅊硁䑁䅉䅁㕂睂䅁䅮䅁䍁䅣睗䑂䝁䄸䅣㕂䍁䅁睢浂䍁䅁睕兂䕁䅣睘䑂䝁䄸兢睂䝁䅅杢㕂䙁䄸睓求䡁䅫睕あ䝁䅅䅤穂䙁䄸杤祁䙁䄸杢求䡁䅣杌㑂䝁䅷督瑂䙁䄰睑桂䡁䅁兡あ䝁䅅䅢時䙁䅍䅤祂䡁䅕睙あ䡁䅕杣求䙁䄸䅉䕂䝁䅕䅤桂䝁䅫䅢穂䍁䅁睊桁䍁䅑村歁䑁䅑䅎䅁䡁䡳䅁捃䅁䅁睊扂䕁䅍睢睂䡁䅫䅉療䝁䅙䅉呂䙁䅁睒時䕁䅍睢瑂䡁䅁兙畂䡁䅫睘䱂䝁䅕入呂䡁䅑兙あ䡁䅍睘㉂䑁䅉睘畂䝁䅕睤畁䡁䅧䅢穂䝁䄰兘䑂䝁䅅䅣灂䡁䅑兙獂䙁䄸睕あ䡁䅉兤橂䡁䅑兤祂䝁䅕睘杁䕁䅑党あ䝁䅅兡獂䡁䅍䅉湁䍁䅅䅊䑂䍁䅑䅎ぁ䅁䅁䅦䅣䩁䅷䅁湁䙁䅳睑療䡁䅁入杁䝁䄸杚杁䙁䅍䅕䡂䙁䄸睑療䝁䄰䅣桂䝁䄴入時䕁䅳党㕂䙁䅍䅤桂䡁䅑督時䡁䅙杍時䝁䄴党㍂䍁䄴䅥獂䡁䅍兢摂䕁䅍兙睂䝁䅫䅤桂䝁䅷睘呂䡁䅑杣ㅂ䝁䅍䅤ㅂ䡁䅉党時䍁䅁䅒求䡁䅑兙灂䝁䅷督杁䍁䅣光歁䕁䅕䅊ぁ䑁䅑䅁㥂睂䅁䅮䅁䍁䅣睗䑂䝁䄸䅣㕂䍁䅁睢浂䍁䅁睕兂䕁䅣睘䑂䝁䄸兢睂䝁䅅杢㕂䙁䄸睓求䡁䅫睕あ䝁䅅䅤穂䙁䄸杤祁䙁䄸杢求䡁䅣杌㑂䝁䅷督瑂䙁䄰睑桂䡁䅁兡あ䝁䅅䅢時䙁䅍䅤祂䡁䅕睙あ䡁䅕杣求䙁䄸䅉䕂䝁䅕䅤桂䝁䅫䅢穂䍁䅁睊桁䍁䅑䅒歁䑁䅣李䅁䥁䡙䅁捃䅁䅁睊扂䕁䅍睢睂䡁䅫䅉療䝁䅙䅉呂䙁䅁睒時䕁䅍睢瑂䡁䅁兙畂䡁䅫睘䱂䝁䅕入呂䡁䅑兙あ䡁䅍睘㉂䑁䅉睘畂䝁䅕睤畁䡁䅧䅢穂䝁䄰兘䑂䝁䅅䅣灂䡁䅑兙獂䙁䄸睕あ䡁䅉兤橂䡁䅑兤祂䝁䅕睘杁䕁䅑党あ䝁䅅兡獂䡁䅍䅉湁䍁䅅䅊䝂䍁䅑䅎ぁ䅁䅁杦䅣䩁䅷䅁湁䙁䅳睑療䡁䅁入杁䝁䄸杚杁䙁䅍䅕䡂䙁䄸睑療䝁䄰䅣桂䝁䄴入時䕁䅳党㕂䙁䅍䅤桂䡁䅑督時䡁䅙杍時䝁䄴党㍂䍁䄴䅥獂䡁䅍兢摂䕁䅍兙睂䝁䅫䅤桂䝁䅷睘呂䡁䅑杣ㅂ䝁䅍䅤ㅂ䡁䅉党時䍁䅁䅒求䡁䅑兙灂䝁䅷督杁䍁䅣光歁䕁䅣䅊㍁䑁䅙䅁䩃睂䅁䅮䅁䍁䅣睗䑂䝁䄸䅣㕂䍁䅁睢浂䍁䅁睕兂䕁䅣睘䑂䝁䄸兢睂䝁䅅杢㕂䙁䄸睓求䡁䅫睕あ䝁䅅䅤穂䙁䄸杤祁䙁䄸杢求䡁䅣杌㑂䝁䅷督瑂䙁䄰睑桂䡁䅁兡あ䝁䅅䅢時䙁䅍䅤祂䡁䅕睙あ䡁䅕杣求䙁䄸䅉䕂䝁䅕䅤桂䝁䅫䅢穂䍁䅁睊桁䍁䅑睒歁䑁䅑䅎䅁䡁䠸䅁捃䅁䅁睊扂䕁䅍睢睂䡁䅫䅉療䝁䅙䅉呂䙁䅁睒時䕁䅍睢瑂䡁䅁兙畂䡁䅫睘䱂䝁䅕入呂䡁䅑兙あ䡁䅍睘㉂䑁䅉睘畂䝁䅕睤畁䡁䅧䅢穂䝁䄰兘䑂䝁䅅䅣灂䡁䅑兙獂䙁䄸睕あ䡁䅉兤橂䡁䅑兤祂䝁䅕睘杁䕁䅑党あ䝁䅅兡獂䡁䅍䅉湁䍁䅅䅊䥂䍁䅑䅎ぁ䅁䅁內䅣䩁䅷䅁湁䙁䅳睑療䡁䅁入杁䝁䄸杚杁䙁䅍䅕䡂䙁䄸睑療䝁䄰䅣桂䝁䄴入時䕁䅳党㕂䙁䅍䅤桂䡁䅑督時䡁䅙杍時䝁䄴党㍂䍁䄴䅥獂䡁䅍兢摂䕁䅍兙睂䝁䅫䅤桂䝁䅷睘呂䡁䅑杣ㅂ䝁䅍䅤ㅂ䡁䅉党時䍁䅁䅒求䡁䅑兙灂䝁䅷督杁䍁䅣光歁䕁䅍䅊㍁䑁䅙䅁䙃睂䅁䅮䅁䍁䅣睗䑂䝁䄸䅣㕂䍁䅁睢浂䍁䅁睕兂䕁䅣睘䑂䝁䄸兢睂䝁䅅杢㕂䙁䄸睓求䡁䅫睕あ䝁䅅䅤穂䙁䄸杤祁䙁䄸杢求䡁䅣杌㑂䝁䅷督瑂䙁䄰睑桂䡁䅁兡あ䝁䅅䅢時䙁䅍䅤祂䡁䅕睙あ䡁䅕杣求䙁䄸䅉䕂䝁䅕䅤桂䝁䅫䅢穂䍁䅁睊桁䍁䅑兓歁䑁䅣李䅁䥁䡳䅁捃䅁䅁睊扂䕁䅍睢睂䡁䅫䅉療䝁䅙䅉呂䙁䅁睒時䕁䅍睢瑂䡁䅁兙畂䡁䅫睘䱂䝁䅕入呂䡁䅑兙あ䡁䅍睘㉂䑁䅉睘畂䝁䅕睤畁䡁䅧䅢穂䝁䄰兘䑂䝁䅅䅣灂䡁䅑兙獂䙁䄸睕あ䡁䅉兤橂䡁䅑兤祂䝁䅕睘杁䕁䅑党あ䝁䅅兡獂䡁䅍䅉湁䍁䅅䅊䭂䍁䅑睎㉁䅁䅁䅪䅣䥁䅑䅁湁䙁䅳睑療䡁䅁入杁䝁䄸杚杁䙁䅍䅕䡂䙁䄸睑療䝁䄰䅣桂䝁䄴入時䕁䅳党㕂䙁䅍䅤桂䡁䅑督時䡁䅙杍時䝁䄴党㍂䍁䄴䅥獂䡁䅍兢摂䕁䅳党㕂䙁䄸睕あ䝁䅅䅤穂䍁䅣光歁䕁䄴䅊祁䑁䅕杏歁䙁䅁䅊祁䑁䅕䅁偃睂䅁䅙䅁䕁䄸䅣あ䝁䅫睢畂䡁䅍杏䑂䡁䅕杣祂䑁䄰兖呂䕁䅑䅌乂䝁䅅睚㥁䕁䄰兡獂䝁䅷兡療䝁䄴督獁䕁䅍睢畂䡁䅙兔求䡁䅑䅡療䝁䅑児乂䙁䅉睕睂䝁䄸䅤䅁䩁䡑䅁䥂䅁䅁睔睂䡁䅑兡療䝁䄴督㙁䕁䅍兤祂䡁䅉児噂䙁䅍䅒獁䕁䅍睢畂䡁䅙兔求䡁䅑䅡療䝁䅑児呂䍁䅷杔䉂䑁䄰杔䉂䅁䅁儱䅣䝁䅷䅁偂䡁䅁䅤灂䝁䄸杢穂䑁䅯睑ㅂ䡁䅉杣㥁䙁䅕睕䕂䍁䅷兔桂䝁䅣児乂䝁䅫䅢獂䝁䅫睢畂䡁䅍䅌䑂䝁䄸杢㉂䕁䄰党あ䝁䅧睢歂䑁䄰兔卂䙁䅍䅣療䡁䅑䅌佂䕁䅅児佂䕁䅅䅁坃睂䅁杉䅁䙁䅍䅕時䕁䅷兑呂䙁䅑睕䉂䕁䅷兒兂䙁䅉兓䑂䕁䅕䅁塃睂䅁杒䅁䕁䄸䅣あ䝁䅫睢畂䡁䅍杏䑂䡁䅕杣祂䑁䄰兖呂䕁䅑䅌䑂䝁䄸杢㉂䕁䄰党あ䝁䅧睢歂䑁䄰兔卂䙁䅍䅣療䡁䅑䅁奃睂䅁杕䅁䕁䄸䅣あ䝁䅫睢畂䡁䅍杏䑂䡁䅕杣祂䑁䄰兖呂䕁䅑䅌䑂䝁䄸杢㉂䕁䄰党あ䝁䅧睢歂䑁䄰兔卂䙁䅍䅣療䡁䅑䅌佂䕁䅅児佂䕁䅅䅁婃睂䅁来䅁䍁䅣睗䑂䝁䄸䅣㕂䍁䅁睢浂䍁䅁睕兂䕁䅣睘䑂䝁䄸兢睂䝁䅅杢㕂䙁䄸睓求䡁䅫睕あ䝁䅅䅤穂䙁䄸杤祁䙁䄸杢求䡁䅣杌㑂䝁䅷督瑂䙁䄰睓求䡁䅫睘呂䡁䅑兙あ䡁䅍睊桁䍁䅑村歁䑁䅅䅍㑁䅁䅁杮䅣䡁䅯䅁湁䙁䅳睑療䡁䅁入杁䝁䄸杚杁䙁䅍䅕䡂䙁䄸睑療䝁䄰䅣桂䝁䄴入時䕁䅳党㕂䙁䅍䅤桂䡁䅑督時䡁䅙杍時䝁䄴党㍂䍁䄴䅥獂䡁䅍兢摂䕁䅳党㕂䙁䄸睕あ䝁䅅䅤穂䍁䅣光歁䕁䅙䅊硁䑁䅁䅏䅁䭁䡅䅁䥃䅁䅁睊扂䕁䅍睢睂䡁䅫䅉療䝁䅙䅉呂䙁䅁睒時䕁䅍睢瑂䡁䅁兙畂䡁䅫睘䱂䝁䅕入呂䡁䅑兙あ䡁䅍睘㉂䑁䅉睘畂䝁䅕睤畁䡁䅧䅢穂䝁䄰兘䱂䝁䅕入時䙁䅍䅤桂䡁䅑督湁䍁䅅䅊䙂䍁䅑免睁䑁䅣杏歁䕁䅙䅊硁䑁䅁睎䅁䭁䡍䅁允䅁䅁杒剂䑁䅍杍睁䑁䅉兎䅁䭁䡧䅁㑂䅁䅁睊扂䕁䅍睢睂䡁䅫䅉療䝁䅙䅉呂䙁䅁睒時䕁䅍睢瑂䡁䅁兙畂䡁䅫睘䱂䝁䅕入呂䡁䅑兙あ䡁䅍睘㉂䑁䅉睘畂䝁䅕睤畁䡁䅧䅢穂䝁䄰兘乂䡁䅕䅢あ䝁䅫䅣獂䝁䅕督湁䍁䅅䅊䕂䍁䅑免睁䅁䅁共䅣䥁䅁䅁湁䙁䅳睑療䡁䅁入杁䝁䄸杚杁䙁䅍䅕䡂䙁䄸睑療䝁䄰䅣桂䝁䄴入時䕁䅳党㕂䙁䅍䅤桂䡁䅑督時䡁䅙杍時䝁䄴党㍂䍁䄴䅥獂䡁䅍兢摂䕁䄰兤獂䡁䅑兡睂䝁䅷党穂䍁䅣光歁䕁䅕䅊㉁䑁䅯䅊䵂䍁䅑李䅁䭁䡯䅁䅃䅁䅁睊扂䕁䅍睢睂䡁䅫䅉療䝁䅙䅉呂䙁䅁睒時䕁䅍睢瑂䡁䅁兙畂䡁䅫睘䱂䝁䅕入呂䡁䅑兙あ䡁䅍睘㉂䑁䅉睘畂䝁䅕睤畁䡁䅧䅢穂䝁䄰兘乂䡁䅕䅢あ䝁䅫䅣獂䝁䅕督湁䍁䅅䅊䙂䍁䅑睎㙁䍁䅑䅔歁䑁䅣䅁獃睂䅁䅧䅁䍁䅣睗䑂䝁䄸䅣㕂䍁䅁睢浂䍁䅁睕兂䕁䅣睘䑂䝁䄸兢睂䝁䅅杢㕂䙁䄸睓求䡁䅫睕あ䝁䅅䅤穂䙁䄸杤祁䙁䄸杢求䡁䅣杌㑂䝁䅷督瑂䙁䄰兔ㅂ䝁䅷䅤灂䡁䅁䅢求䡁䅍睊桁䍁䅑兒歁䑁䅫杏歁䕁䅷䅊㕁䅁䅁兲䅣䩁䅑䅁湁䙁䅳睑療䡁䅁入杁䝁䄸杚杁䙁䅍䅕䡂䙁䄸睑療䝁䄰䅣桂䝁䄴入時䕁䅳党㕂䙁䅍䅤桂䡁䅑督時䡁䅙杍時䝁䄴党㍂䍁䄴䅥獂䡁䅍兢摂䕁䅫杢橂䝁䄸兢求䙁䄸睕あ䝁䅅䅤求䝁䄰党畂䡁䅑睊桁䍁䅑睑歁䑁䅅免㙁䍁䅑睑歁䑁䅉䅍祁䅁䅁睲䅣䅁䅯䅁䝂䙁䅅兌ぁ䅁䅁杵䅣䭁䅙䅁湁䙁䅳睑療䡁䅁入杁䝁䄸杚杁䙁䅍䅕䡂䙁䄸睑療䝁䄰䅣桂䝁䄴入時䕁䅳党㕂䙁䅍䅤桂䡁䅑督時䡁䅙杍時䝁䄴党㍂䍁䄴䅥獂䡁䅍兢摂䕁䅍兙睂䝁䅫䅤桂䝁䅷睘呂䡁䅑杣ㅂ䝁䅍䅤ㅂ䡁䅉党時䙁䅍兤瑂䝁䄰兙祂䡁䅫睊桁䍁䅑睑歁䑁䅅兎㙁䍁䅑睑歁䑁䅅睎硁䅁䅁睶䅣䍁䅧䅁橁䕁䅫杔坂䕁䅅䅔䩂䕁䅑䅉䕂䕁䅅䅖䙂䍁䅁杕䉂䕁䄴睒䙂䅁䅁兹䅣䉁䅯䅁䩂䙁䅅睘兂䕁䅕睘䍂䕁䅕杒偂䙁䅉兒䅁䵁䡯䅁敁䅁䅁睕兂䕁䅣兔䩂䍁䄴䅒桂䡁䅑兙䡂䝁䅷兤求䅁䅁睹䅣䥁䅷䅁湁䙁䅳睑療䡁䅁入杁䝁䄸杚杁䙁䅍䅕䡂䙁䄸睑療䝁䄰䅣桂䝁䄴入時䕁䅳党㕂䙁䅍䅤桂䡁䅑督時䡁䅙杍時䝁䄴党㍂䍁䄴䅥獂䡁䅍兢摂䙁䅍兤睂䡁䅁䅢求䝁䄰党畂䡁䅑兙獂䍁䅣光歁䕁䅍䅊硁䑁䅅杏歁䕁䅍䅊硁䑁䅙䅎䅁䵁䠰䅁楂䅁䅁睔睂䡁䅑兡療䝁䄴督㙁䕁䅍兤祂䡁䅉児噂䙁䅍䅒獁䕁䄰兙湂䑁䄰兔灂䝁䅷䅢灂䝁䄸杢穂䍁䅷睑療䝁䄴杤乂䝁䅕䅤潂䝁䄸䅚㥁䙁䅍䅌佂䕁䅅児佂䕁䅅䅁佄睂䅁杄䅁䕁䅙兗祁䑁䅁杍ㅁ䅁䅁儲䅣䡁䅉䅁扂䙁䅍䅕䡂䙁䄸睑療䝁䄰䅣桂䝁䄴入時䕁䅳党㕂䙁䅍䅤桂䡁䅑督時䡁䅙杍畁䡁䅧䅢穂䝁䄰兘䩂䝁䄴睙療䝁䄰党時䙁䅍䅤桂䡁䅑党瑂䝁䅕杢あ䍁䅅䅊䙂䍁䅑睎㙁䍁䅑兕歁䑁䅣䅁汄睂䅁䅡䅁䙁䅳睕兂䕁䅣睘䑂䝁䄸兢睂䝁䅅杢㕂䙁䄸睓求䡁䅫睕あ䝁䅅䅤穂䙁䄸杤祁䍁䄴䅥獂䡁䅍兢摂䕁䅳党㕂䙁䄸睕あ䝁䅅䅤穂䍁䅅䅊䑂䍁䅑杍㑁䑁䅯䅊䑂䍁䅑兎祁䅁䅁䄶䅣䥁䅯䅁湁䙁䅳睑療䡁䅁入杁䝁䄸杚杁䙁䅍䅕䡂䙁䄸睑療䝁䄰䅣桂䝁䄴入時䕁䅳党㕂䙁䅍䅤桂䡁䅑督時䡁䅙免時䕁䅙兡畂䝁䅅䅢畁䡁䅧䅢穂䝁䄰兘兂䝁䅕杢穂䝁䅫睢畂䍁䄰睔兂䕁䅕村湁䍁䅅䅊䕂䍁䅑睎㙁䍁䅑兓歁䑁䅣䅁慃䅃䅁䅡䅁䙁䅳睕兂䕁䅣睘䑂䝁䄸兢睂䝁䅅杢㕂䙁䄸睓求䡁䅫睕あ䝁䅅䅤穂䙁䄸杤祁䍁䄴䅥獂䡁䅍兢摂䕁䅳党㕂䙁䄸睕あ䝁䅅䅤穂䍁䅅䅊䙂䍁䅑杍㉁䑁䅯䅊䭂䍁䅑杍㉁䅁䅁儶䅣䝁䅧䅁扂䙁䅍䅕䡂䙁䄸睑療䝁䄰䅣桂䝁䄴入時䕁䅳党㕂䙁䅍䅤桂䡁䅑督時䡁䅙杍畁䡁䅧䅢穂䝁䄰兘䱂䝁䅕入時䙁䅍䅤桂䡁䅑督桁䍁䅑䅒歁䑁䅉䅏㙁䍁䅑䅒歁䑁䅕杍䅁佁䡷䅁捂䅁䅁睗呂䙁䅁睒時䕁䅍睢瑂䡁䅁兙畂䡁䅫睘䱂䝁䅕入呂䡁䅑兙あ䡁䅍睘㉂䑁䅉杌㑂䝁䅷督瑂䙁䄰睓求䡁䅫睘呂䡁䅑兙あ䡁䅍光歁䕁䅕䅊㉁䑁䅉䅁癄睂䅁䅢䅁䙁䅳睕兂䕁䅣睘䑂䝁䄸兢睂䝁䅅杢㕂䙁䄸睓求䡁䅫睕あ䝁䅅䅤穂䙁䄸杤祁䍁䄴䅥獂䡁䅍兢摂䕁䅳党㕂䙁䄸睕あ䝁䅅䅤穂䍁䅅䅊䑂䍁䅑免睁䑁䅫杏歁䕁䅍䅊硁䑁䅅兎䅁偁䡑䅁潂䅁䅁睗呂䙁䅁睒時䕁䅍睢瑂䡁䅁兙畂䡁䅫睘䱂䝁䅕入呂䡁䅑兙あ䡁䅍睘㉂䑁䅉杌㑂䝁䅷督瑂䙁䄰睓求䡁䅫睘呂䡁䅑兙あ䡁䅍光歁䕁䅍䅊㉁䑁䅕杏歁䕁䅍䅊㍁䑁䅅䅁睄睂䅁杘䅁䙁䅳睕兂䕁䅣睘䑂䝁䄸兢睂䝁䅅杢㕂䙁䄸睓求䡁䅫睕あ䝁䅅䅤穂䙁䄸杤祁䍁䄴䅥獂䡁䅍兢摂䕁䅳党㕂䙁䄸睕あ䝁䅅䅤穂䍁䅅䅊䍂䍁䅑免睁䑁䅣䅁㉄睂䅁䅢䅁䙁䅳睕兂䕁䅣睘䑂䝁䄸兢睂䝁䅅杢㕂䙁䄸睓求䡁䅫睕あ䝁䅅䅤穂䙁䄸杤祁䍁䄴䅥獂䡁䅍兢摂䕁䅳党㕂䙁䄸睕あ䝁䅅䅤穂䍁䅅䅊䙂䍁䅑免睁䑁䅣杏歁䕁䅙䅊硁䑁䅁睎䅁偁䡫䅁獂䅁䅁睗呂䙁䅁睒時䕁䅍睢瑂䡁䅁兙畂䡁䅫睘䱂䝁䅕入呂䡁䅑兙あ䡁䅍睘㉂䑁䅉杌㑂䝁䅷督瑂䙁䄰村桂䝁䅷兙畂䝁䅍党時䙁䅍䅡求䝁䅕䅤桁䍁䅑兒歁䑁䅙杏歁䙁䅅䅊㉁䅁䅁眫䅣䡁䅉䅁扂䙁䅍䅕䡂䙁䄸睑療䝁䄰䅣桂䝁䄴入時䕁䅳党㕂䙁䅍䅤桂䡁䅑督時䡁䅙杍畁䡁䅧䅢穂䝁䄰兘䍂䝁䅅䅢桂䝁䄴睙求䙁䄸睕潂䝁䅕党あ䍁䅅䅊䑂䍁䅑免硁䑁䅯䅊䑂䍁䅑杍睁䑁䅑䅁㡄睂䅁䅣䅁䙁䅳睕兂䕁䅣睘䑂䝁䄸兢睂䝁䅅杢㕂䙁䄸睓求䡁䅫睕あ䝁䅅䅤穂䙁䄸杤祁䍁䄴䅥獂䡁䅍兢摂䕁䅍兙睂䝁䅫䅤桂䝁䅷兡㙂䝁䅅䅤灂䝁䄸杢桁䍁䅑睑歁䑁䅫杏歁䕁䅍䅊祁䑁䅑䅁䅁䅃䅁杢䅁䙁䅳睕兂䕁䅣睘䑂䝁䄸兢睂䝁䅅杢㕂䙁䄸睓求䡁䅫睕あ䝁䅅䅤穂䙁䄸杤祁䍁䄴䅥獂䡁䅍兢摂䕁䅍兙睂䝁䅫䅤桂䝁䅷兡㙂䝁䅅䅤灂䝁䄸杢桁䍁䅑兒歁䑁䅕杏歁䕁䅯䅊ㅁ䅁䅁允䅧䭁䅁䅁湁䙁䅳睑療䡁䅁入杁䝁䄸杚杁䙁䅍䅕䡂䙁䄸睑療䝁䄰䅣桂䝁䄴入時䕁䅳党㕂䙁䅍䅤桂䡁䅑督時䡁䅙免時䕁䅙兡畂䝁䅅䅢畁䡁䅧䅢穂䝁䄰兘䑂䝁䅅䅣灂䡁䅑兙獂䙁䄸睕あ䡁䅉兤橂䡁䅑兤祂䝁䅕睘杁䕁䅑党あ䝁䅅兡獂䡁䅍䅉湁䍁䅅䅊䑂䍁䅑免祁䅁䅁杨䅧䥁䅑䅁扂䙁䅍䅕䡂䙁䄸睑療䝁䄰䅣桂䝁䄴入時䕁䅳党㕂䙁䅍䅤桂䡁䅑督時䡁䅙杍畁䡁䅧䅢穂䝁䄰兘䑂䝁䅅䅣灂䡁䅑兙獂䙁䄸睕あ䡁䅉兤橂䡁䅑兤祂䝁䅕睘呂䡁䅕兢瑂䝁䅅杣㕂䍁䅅䅊䙂䍁䅑李㙁䍁䅑兕歁䑁䅙䅁䑁䅃䅁䅨䅁䙁䅳睕兂䕁䅣睘䑂䝁䄸兢睂䝁䅅杢㕂䙁䄸睓求䡁䅫睕あ䝁䅅䅤穂䙁䄸杤祁䍁䄴䅥獂䡁䅍兢摂䕁䅍兙睂䝁䅫䅤桂䝁䅷睘呂䡁䅑杣ㅂ䝁䅍䅤ㅂ䡁䅉党時䙁䅍兤瑂䝁䄰兙祂䡁䅫光歁䕁䅕䅊㍁䑁䅯䅊剂䍁䅑睎䅁䅁䥕䅁䥃䅁䅁睗呂䙁䅁睒時䕁䅍睢瑂䡁䅁兙畂䡁䅫睘䱂䝁䅕入呂䡁䅑兙あ䡁䅍睘㉂䑁䅉杌㑂䝁䅷督瑂䙁䄰睑桂䡁䅁兡あ䝁䅅䅢時䙁䅍䅤祂䡁䅕睙あ䡁䅕杣求䙁䄸睕ㅂ䝁䄰兢桂䡁䅉入桁䍁䅑䅒歁䑁䅉兏㙁䍁䅑䅒歁䑁䅣兏䅁䅁䥧䅁啂䅁䅁睗呂䙁䅁睒時䕁䅍睢瑂䡁䅁兙畂䡁䅫睘䱂䝁䅕入呂䡁䅑兙あ䡁䅍睘㉂䑁䅉杌㑂䝁䅷督瑂䙁䄰杕桂䡁䅑兡療䡁䅍光歁䕁䅍䅊㉁䅁䅁权䅧䙁䄴䅁扂䙁䅍䅕䡂䙁䄸睑療䝁䄰䅣桂䝁䄴入時䕁䅳党㕂䙁䅍䅤桂䡁䅑督時䡁䅙杍畁䡁䅧䅢穂䝁䄰兘卂䝁䅅䅤灂䝁䄸督桁䍁䅑䅒歁䑁䅙杏歁䕁䅫䅊㉁䅁䅁睃䅧䙁䄴䅁扂䙁䅍䅕䡂䙁䄸睑療䝁䄰䅣桂䝁䄴入時䕁䅳党㕂䙁䅍䅤桂䡁䅑督時䡁䅙杍畁䡁䅧䅢穂䝁䄰兘卂䝁䅅䅤灂䝁䄸督桁䍁䅑䅒歁䑁䅣杏歁䕁䅫䅊㍁䅁䅁兄䅧䝁䅯䅁扂䙁䅍䅕䡂䙁䄸睑療䝁䄰䅣桂䝁䄴入時䕁䅳党㕂䙁䅍䅤桂䡁䅑督時䡁䅙杍畁䡁䅧䅢穂䝁䄰兘呂䡁䅕䅣睂䝁䅷党瑂䝁䅕杢あ䝁䅅䅢桁䍁䅑䅒歁䑁䅙杏歁䕁䅫䅊㉁䅁䅁睄䅧䝁䅯䅁扂䙁䅍䅕䡂䙁䄸睑療䝁䄰䅣桂䝁䄴入時䕁䅳党㕂䙁䅍䅤桂䡁䅑督時䡁䅙杍畁䡁䅧䅢穂䝁䄰兘呂䡁䅕䅣睂䝁䅷党瑂䝁䅕杢あ䝁䅅䅢桁䍁䅑䅒歁䑁䅣杏歁䕁䅫䅊㍁䅁䅁充䅧䝁䅑䅁湁䙁䅳睕兂䕁䅣睘䑂䝁䄸兢睂䝁䅅杢㕂䙁䄸睓求䡁䅫睕あ䝁䅅䅤穂䙁䄸杤祁䍁䄴䅥獂䡁䅍兢摂䙁䅁党畂䡁䅍兡療䝁䄴兌偂䙁䅁兒䍂䍁䅣光歁䕁䅍䅊㉁䅁䅁杅䅧䝁䄴䅁湁䙁䅳睕兂䕁䅣睘䑂䝁䄸兢睂䝁䅅杢㕂䙁䄸睓求䡁䅫睕あ䝁䅅䅤穂䙁䄸杤祁䍁䄴䅥獂䡁䅍兢摂䙁䅁党畂䡁䅍兡療䝁䄴兌偂䙁䅁兒䍂䍁䅣光歁䕁䅑䅊㉁䑁䅯䅊䩂䍁䅑李䅁䉁䥍䅁あ䅁䅁睊扂䙁䅍䅕䡂䙁䄸睑療䝁䄰䅣桂䝁䄴入時䕁䅳党㕂䙁䅍䅤桂䡁䅑督時䡁䅙杍畁䡁䅧䅢穂䝁䄰兘兂䝁䅕杢穂䝁䅫睢畂䍁䄰睔兂䕁䅕村湁䍁䅅䅊䑂䍁䅑免硁䑁䅯䅊䑂䍁䅑兎㍁䑁䅕䅁啁䅃䅁杢䅁䍁䅣睗呂䙁䅁睒時䕁䅍睢瑂䡁䅁兙畂䡁䅫睘䱂䝁䅕入呂䡁䅑兙あ䡁䅍睘㉂䑁䅉杌㑂䝁䅷督瑂䙁䄰䅕求䝁䄴督灂䝁䄸杢瑁䕁䄸䅕䙂䕁䅉睊桁䍁䅑䅒歁䑁䅣杏歁䕁䅫䅊㍁䅁䅁兆䅧䥁䅑䅁湁䙁䅳睕兂䕁䅣睘䑂䝁䄸兢睂䝁䅅杢㕂䙁䄸睓求䡁䅫睕あ䝁䅅䅤穂䙁䄸杤祁䍁䄴䅥獂䡁䅍兢摂䕁䅍兙睂䝁䅫䅤桂䝁䅷睘呂䡁䅑杣ㅂ䝁䅍䅤ㅂ䡁䅉党時䍁䅁䅒求䡁䅑兙灂䝁䅷督杁䍁䅣光歁䕁䅉䅊硁䑁䅉䅁坁䅃䅁䅨䅁䍁䅣睗呂䙁䅁睒時䕁䅍睢瑂䡁䅁兙畂䡁䅫睘䱂䝁䅕入呂䡁䅑兙あ䡁䅍睘㉂䑁䅉杌㑂䝁䅷督瑂䙁䄰睑桂䡁䅁兡あ䝁䅅䅢時䙁䅍䅤祂䡁䅕睙あ䡁䅕杣求䙁䄸䅉䕂䝁䅕䅤桂䝁䅫䅢穂䍁䅁睊桁䍁䅑兑䉂䍁䅑兎䅁䉁䥣䅁䕃䅁䅁睊扂䙁䅍䅕䡂䙁䄸睑療䝁䄰䅣桂䝁䄴入時䕁䅳党㕂䙁䅍䅤桂䡁䅑督時䡁䅙杍畁䡁䅧䅢穂䝁䄰兘䑂䝁䅅䅣灂䡁䅑兙獂䙁䄸睕あ䡁䅉兤橂䡁䅑兤祂䝁䅕睘杁䕁䅑党あ䝁䅅兡獂䡁䅍䅉湁䍁䅅䅊䉂䕁䅅䅊㉁䅁䅁兇䅧䥁䅑䅁湁䙁䅳睕兂䕁䅣睘䑂䝁䄸兢睂䝁䅅杢㕂䙁䄸睓求䡁䅫睕あ䝁䅅䅤穂䙁䄸杤祁䍁䄴䅥獂䡁䅍兢摂䕁䅍兙睂䝁䅫䅤桂䝁䅷睘呂䡁䅑杣ㅂ䝁䅍䅤ㅂ䡁䅉党時䍁䅁䅒求䡁䅑兙灂䝁䅷督杁䍁䅣光歁䕁䅕䅊硁䑁䅉䅁慁䅃䅁䅨䅁䍁䅣睗呂䙁䅁睒時䕁䅍睢瑂䡁䅁兙畂䡁䅫睘䱂䝁䅕入呂䡁䅑兙あ䡁䅍睘㉂䑁䅉杌㑂䝁䅷督瑂䙁䄰睑桂䡁䅁兡あ䝁䅅䅢時䙁䅍䅤祂䡁䅕睙あ䡁䅕杣求䙁䄸䅉䕂䝁䅕䅤桂䝁䅫䅢穂䍁䅁睊桁䍁䅑睑歁䑁䅅杍䅁䉁䥳䅁䕃䅁䅁睊扂䙁䅍䅕䡂䙁䄸睑療䝁䄰䅣桂䝁䄴入時䕁䅳党㕂䙁䅍䅤桂䡁䅑督時䡁䅙杍畁䡁䅧䅢穂䝁䄰兘䑂䝁䅅䅣灂䡁䅑兙獂䙁䄸睕あ䡁䅉兤橂䡁䅑兤祂䝁䅕睘杁䕁䅑党あ䝁䅅兡獂䡁䅍䅉湁䍁䅅䅊䕂䍁䅑免祁䅁䅁䅈䅧䥁䅑䅁湁䙁䅳睕兂䕁䅣睘䑂䝁䄸兢睂䝁䅅杢㕂䙁䄸睓求䡁䅫睕あ䝁䅅䅤穂䙁䄸杤祁䍁䄴䅥獂䡁䅍兢摂䕁䅍兙睂䝁䅫䅤桂䝁䅷睘呂䡁䅑杣ㅂ䝁䅍䅤ㅂ䡁䅉党時䍁䅁䅒求䡁䅑兙灂䝁䅷督杁䍁䅣光歁䕁䅅兑歁䑁䅣䅁敁䅃䅁䅯䅁䍁䅣睗䑂䝁䄸䅣㕂䍁䅁睢浂䍁䅁睕兂䕁䅣睘䑂䝁䄸兢睂䝁䅅杢㕂䙁䄸睓求䡁䅫睕あ䝁䅅䅤穂䙁䄸杤硁䙁䄸杒灂䝁䄴兙獂䍁䄴䅥獂䡁䅍兢摂䕁䅍兙睂䝁䅫䅤桂䝁䅷睘呂䡁䅑杣ㅂ䝁䅍䅤ㅂ䡁䅉党時䍁䅁䅒求䡁䅑兙灂䝁䅷督杁䍁䅣光歁䕁䅧䅊硁䑁䅉䅁あ䅃䅁䅨䅁䍁䅣睗呂䙁䅁睒時䕁䅍睢瑂䡁䅁兙畂䡁䅫睘䱂䝁䅕入呂䡁䅑兙あ䡁䅍睘㉂䑁䅉杌㑂䝁䅷督瑂䙁䄰睑桂䡁䅁兡あ䝁䅅䅢時䙁䅍䅤祂䡁䅕睙あ䡁䅕杣求䙁䄸䅉䕂䝁䅕䅤桂䝁䅫䅢穂䍁䅁睊桁䍁䅑睒歁䑁䅅杍䅁䍁䥁䅁䕃䅁䅁睊扂䙁䅍䅕䡂䙁䄸睑療䝁䄰䅣桂䝁䄴入時䕁䅳党㕂䙁䅍䅤桂䡁䅑督時䡁䅙杍畁䡁䅧䅢穂䝁䄰兘䑂䝁䅅䅣灂䡁䅑兙獂䙁䄸睕あ䡁䅉兤橂䡁䅑兤祂䝁䅕睘杁䕁䅑党あ䝁䅅兡獂䡁䅍䅉湁䍁䅅䅊䩂䍁䅑免祁䅁䅁光䅧䥁䅑䅁湁䙁䅳睕兂䕁䅣睘䑂䝁䄸兢睂䝁䅅杢㕂䙁䄸睓求䡁䅫睕あ䝁䅅䅤穂䙁䄸杤祁䍁䄴䅥獂䡁䅍兢摂䕁䅍兙睂䝁䅫䅤桂䝁䅷睘呂䡁䅑杣ㅂ䝁䅍䅤ㅂ䡁䅉党時䍁䅁䅒求䡁䅑兙灂䝁䅷督杁䍁䅣光歁䕁䅯䅊硁䑁䅉䅁橁䅃䅁䅨䅁䍁䅣睗呂䙁䅁睒時䕁䅍睢瑂䡁䅁兙畂䡁䅫睘䱂䝁䅕入呂䡁䅑兙あ䡁䅍睘㉂䑁䅉杌㑂䝁䅷督瑂䙁䄰睑桂䡁䅁兡あ䝁䅅䅢時䙁䅍䅤祂䡁䅕睙あ䡁䅕杣求䙁䄸䅉䕂䝁䅕䅤桂䝁䅫䅢穂䍁䅁睊桁䍁䅑村歁䑁䅑䅎䅁䍁䥕䅁䕃䅁䅁睊扂䙁䅍䅕䡂䙁䄸睑療䝁䄰䅣桂䝁䄴入時䕁䅳党㕂䙁䅍䅤桂䡁䅑督時䡁䅙杍畁䡁䅧䅢穂䝁䄰兘䑂䝁䅅䅣灂䡁䅑兙獂䙁䄸睕あ䡁䅉兤橂䡁䅑兤祂䝁䅕睘杁䕁䅑党あ䝁䅅兡獂䡁䅍䅉湁䍁䅅䅊䑂䍁䅑䅎ぁ䅁䅁杊䅧䥁䅑䅁湁䙁䅳睕兂䕁䅣睘䑂䝁䄸兢睂䝁䅅杢㕂䙁䄸睓求䡁䅫睕あ䝁䅅䅤穂䙁䄸杤祁䍁䄴䅥獂䡁䅍兢摂䕁䅍兙睂䝁䅫䅤桂䝁䅷睘呂䡁䅑杣ㅂ䝁䅍䅤ㅂ䡁䅉党時䍁䅁䅒求䡁䅑兙灂䝁䅷督杁䍁䅣光歁䕁䅑䅊ぁ䑁䅑䅁湁䅃䅁䅨䅁䍁䅣睗呂䙁䅁睒時䕁䅍睢瑂䡁䅁兙畂䡁䅫睘䱂䝁䅕入呂䡁䅑兙あ䡁䅍睘㉂䑁䅉杌㑂䝁䅷督瑂䙁䄰睑桂䡁䅁兡あ䝁䅅䅢時䙁䅍䅤祂䡁䅕睙あ䡁䅕杣求䙁䄸䅉䕂䝁䅕䅤桂䝁䅫䅢穂䍁䅁睊桁䍁䅑睑歁䑁䅣李䅁䍁䥧䅁䕃䅁䅁睊扂䙁䅍䅕䡂䙁䄸睑療䝁䄰䅣桂䝁䄴入時䕁䅳党㕂䙁䅍䅤桂䡁䅑督時䡁䅙杍畁䡁䅧䅢穂䝁䄰兘䑂䝁䅅䅣灂䡁䅑兙獂䙁䄸睕あ䡁䅉兤橂䡁䅑兤祂䝁䅕睘杁䕁䅑党あ䝁䅅兡獂䡁䅍䅉湁䍁䅅䅊䝂䍁䅑䅎ぁ䅁䅁杋䅧䥁䅑䅁湁䙁䅳睕兂䕁䅣睘䑂䝁䄸兢睂䝁䅅杢㕂䙁䄸睓求䡁䅫睕あ䝁䅅䅤穂䙁䄸杤祁䍁䄴䅥獂䡁䅍兢摂䕁䅍兙睂䝁䅫䅤桂䝁䅷睘呂䡁䅑杣ㅂ䝁䅍䅤ㅂ䡁䅉党時䍁䅁䅒求䡁䅑兙灂䝁䅷督杁䍁䅣光歁䕁䅣䅊ぁ䑁䅑䅁牁䅃䅁䅨䅁䍁䅣睗呂䙁䅁睒時䕁䅍睢瑂䡁䅁兙畂䡁䅫睘䱂䝁䅕入呂䡁䅑兙あ䡁䅍睘㉂䑁䅉杌㑂䝁䅷督瑂䙁䄰睑桂䡁䅁兡あ䝁䅅䅢時䙁䅍䅤祂䡁䅕睙あ䡁䅕杣求䙁䄸䅉䕂䝁䅕䅤桂䝁䅫䅢穂䍁䅁睊桁䍁䅑䅓歁䑁䅑䅎䅁䍁䥷䅁䕃䅁䅁睊扂䙁䅍䅕䡂䙁䄸睑療䝁䄰䅣桂䝁䄴入時䕁䅳党㕂䙁䅍䅤桂䡁䅑督時䡁䅙杍畁䡁䅧䅢穂䝁䄰兘䑂䝁䅅䅣灂䡁䅑兙獂䙁䄸睕あ䡁䅉兤橂䡁䅑兤祂䝁䅕睘杁䕁䅑党あ䝁䅅兡獂䡁䅍䅉湁䍁䅅䅊䭂䍁䅑䅎ぁ䅁䅁兌䅧䥁䅑䅁湁䙁䅳睕兂䕁䅣睘䑂䝁䄸兢睂䝁䅅杢㕂䙁䄸睓求䡁䅫睕あ䝁䅅䅤穂䙁䄸杤祁䍁䄴䅥獂䡁䅍兢摂䕁䅍兙睂䝁䅫䅤桂䝁䅷睘呂䡁䅑杣ㅂ䝁䅍䅤ㅂ䡁䅉党時䍁䅁䅒求䡁䅑兙灂䝁䅷督杁䍁䅣光歁䕁䅳䅊ぁ䑁䅑䅁畁䅃䅁䅨䅁䍁䅣睗呂䙁䅁睒時䕁䅍睢瑂䡁䅁兙畂䡁䅫睘䱂䝁䅕入呂䡁䅑兙あ䡁䅍睘㉂䑁䅉杌㑂䝁䅷督瑂䙁䄰睑桂䡁䅁兡あ䝁䅅䅢時䙁䅍䅤祂䡁䅕睙あ䡁䅕杣求䙁䄸䅉䕂䝁䅕䅤桂䝁䅫䅢穂䍁䅁睊桁䍁䅑村歁䑁䅣李䅁䍁䤸䅁䕃䅁䅁睊扂䙁䅍䅕䡂䙁䄸睑療䝁䄰䅣桂䝁䄴入時䕁䅳党㕂䙁䅍䅤桂䡁䅑督時䡁䅙杍畁䡁䅧䅢穂䝁䄰兘䑂䝁䅅䅣灂䡁䅑兙獂䙁䄸睕あ䡁䅉兤橂䡁䅑兤祂䝁䅕睘杁䕁䅑党あ䝁䅅兡獂䡁䅍䅉湁䍁䅅䅊䝂䍁䅑睎㉁䅁䅁免䅧䥁䅑䅁湁䙁䅳睕兂䕁䅣睘䑂䝁䄸兢睂䝁䅅杢㕂䙁䄸睓求䡁䅫睕あ䝁䅅䅤穂䙁䄸杤祁䍁䄴䅥獂䡁䅍兢摂䕁䅍兙睂䝁䅫䅤桂䝁䅷睘呂䡁䅑杣ㅂ䝁䅍䅤ㅂ䡁䅉党時䍁䅁䅒求䡁䅑兙灂䝁䅷督杁䍁䅣光歁䕁䅣䅊㍁䑁䅙䅁祁䅃䅁䅨䅁䍁䅣睗呂䙁䅁睒時䕁䅍睢瑂䡁䅁兙畂䡁䅫睘䱂䝁䅕入呂䡁䅑兙あ䡁䅍睘㉂䑁䅉杌㑂䝁䅷督瑂䙁䄰睑桂䡁䅁兡あ䝁䅅䅢時䙁䅍䅤祂䡁䅕睙あ䡁䅕杣求䙁䄸䅉䕂䝁䅕䅤桂䝁䅫䅢穂䍁䅁睊桁䍁䅑䅓歁䑁䅣李䅁䑁䥍䅁䕃䅁䅁睊扂䙁䅍䅕䡂䙁䄸睑療䝁䄰䅣桂䝁䄴入時䕁䅳党㕂䙁䅍䅤桂䡁䅑督時䡁䅙杍畁䡁䅧䅢穂䝁䄰兘䑂䝁䅅䅣灂䡁䅑兙獂䙁䄸睕あ䡁䅉兤橂䡁䅑兤祂䝁䅕睘杁䕁䅑党あ䝁䅅兡獂䡁䅍䅉湁䍁䅅䅊䭂䍁䅑睎㉁䅁䅁兎䅧䥁䅑䅁湁䙁䅳睕兂䕁䅣睘䑂䝁䄸兢睂䝁䅅杢㕂䙁䄸睓求䡁䅫睕あ䝁䅅䅤穂䙁䄸杤祁䍁䄴䅥獂䡁䅍兢摂䕁䅍兙睂䝁䅫䅤桂䝁䅷睘呂䡁䅑杣ㅂ䝁䅍䅤ㅂ䡁䅉党時䍁䅁䅒求䡁䅑兙灂䝁䅷督杁䍁䅣光歁䕁䅳䅊㍁䑁䅙䅁㉁䅃䅁䅥䅁䙁䅳睕兂䕁䅣睘䑂䝁䄸兢睂䝁䅅杢㕂䙁䄸睓求䡁䅫睕あ䝁䅅䅤穂䙁䄸杤祁䍁䄴䅥獂䡁䅍兢摂䕁䅫杢橂䝁䄸兢求䙁䄸睕あ䝁䅅䅤求䝁䄰党畂䡁䅑光歁䕁䅍䅊硁䑁䅅杏歁䕁䅍䅊硁䑁䅫䅍䅁䑁䥣䅁獂䅁䅁睗呂䙁䅁睒時䕁䅍睢瑂䡁䅁兙畂䡁䅫睘䱂䝁䅕入呂䡁䅑兙あ䡁䅍睘㉂䑁䅉杌㑂䝁䅷督瑂䙁䄰睓求䡁䅫睘呂䡁䅑兙あ䡁䅍光歁䕁䅣䅊硁䑁䅁李㙁䍁䅑杓歁䑁䅅䅍㉁䅁䅁䅏䅧䝁䅷䅁扂䙁䅍䅕䡂䙁䄸睑療䝁䄰䅣桂䝁䄴入時䕁䅳党㕂䙁䅍䅤桂䡁䅑督時䡁䅙杍畁䡁䅧䅢穂䝁䄰兘䱂䝁䅕入時䙁䅍䅤桂䡁䅑督桁䍁䅑睒歁䑁䅅䅍㍁䑁䅯䅊䭂䍁䅑免睁䑁䅣䅁㕁䅃䅁䅢䅁䙁䅳睕兂䕁䅣睘䑂䝁䄸兢睂䝁䅅杢㕂䙁䄸睓求䡁䅫睕あ䝁䅅䅤穂䙁䄸杤祁䍁䄴䅥獂䡁䅍兢摂䕁䅳党㕂䙁䄸睕あ䝁䅅䅤穂䍁䅅䅊䕂䍁䅑免硁䑁䅅杏歁䕁䅑䅊硁䑁䅅李䅁䑁䥯䅁䭁䅁䅁杒剂䍁䅳免䅁䑁䥳䅁十䅁䅁杔婂䙁䅍兒㙁䕁䅑兖䱂䅁䅁䅐䅧䕁䅙䅁䕂䡁䅕睡求䍁䅁兒畂䝁䅕杣湂䡁䅫䅉䑂䝁䄸杣睂䝁䄸杣桂䡁䅑兡療䝁䄴䅉潁䕁䄴兗呂䕁䅕杏䕂䙁䅕睓灁䅁䅁児䅧䅁䄴䅁䕂䙁䅕睓瑁䙁䅕睕䅁䑁䤴䅁十䅁䅁杔婂䙁䅍兒㙁䕁䅉兑䑂䅁䅁睐䅧䥁䅧䅁湁䙁䅳睑療䡁䅁入杁䝁䄸杚杁䙁䅍䅕䡂䙁䄸睑療䝁䄰䅣桂䝁䄴入時䕁䅳党㕂䙁䅍䅤桂䡁䅑督時䡁䅙免時䕁䅙兡畂䝁䅅䅢畁䡁䅧䅢穂䝁䄰兘䱂䝁䅕入時䙁䅍䅤桂䡁䅑督湁䍁䅅䅊䙂䍁䅑杍ㅁ䑁䅯䅊䭂䍁䅑杍ㅁ䅁䅁村䅧䭁䅁䅁湁䙁䅳睑療䡁䅁入杁䝁䄸杚杁䙁䅍䅕䡂䙁䄸睑療䝁䄰䅣桂䝁䄴入時䕁䅳党㕂䙁䅍䅤桂䡁䅑督時䡁䅙免時䕁䅙兡畂䝁䅅䅢畁䡁䅧䅢穂䝁䄰兘䑂䝁䅅䅣灂䡁䅑兙獂䙁䄸睕あ䡁䅉兤橂䡁䅑兤祂䝁䅕睘杁䕁䅑党あ䝁䅅兡獂䡁䅍䅉湁䍁䅅䅊䭂䍁䅑免祁䅁䅁䅩䅧䥁䅧䅁湁䙁䅳睑療䡁䅁入杁䝁䄸杚杁䙁䅍䅕䡂䙁䄸睑療䝁䄰䅣桂䝁䄴入時䕁䅳党㕂䙁䅍䅤桂䡁䅑督時䡁䅙免時䕁䅙兡畂䝁䅅䅢畁䡁䅧䅢穂䝁䄰兘䱂䝁䅕入時䙁䅍䅤桂䡁䅑督湁䍁䅅䅊䑂䍁䅑杍㑁䑁䅯䅊䑂䍁䅑兎祁䅁䅁睑䅧䥁䅧䅁湁䙁䅳睑療䡁䅁入杁䝁䄸杚杁䙁䅍䅕䡂䙁䄸睑療䝁䄰䅣桂䝁䄴入時䕁䅳党㕂䙁䅍䅤桂䡁䅑督時䡁䅙免時䕁䅙兡畂䝁䅅䅢畁䡁䅧䅢穂䝁䄰兘䱂䝁䅕入時䙁䅍䅤桂䡁䅑督湁䍁䅅䅊䙂䍁䅑杍㉁䑁䅯䅊䭂䍁䅑杍㉁䅁䅁䅒䅧䡁䅷䅁湁䙁䅳睑療䡁䅁入杁䝁䄸杚杁䙁䅍䅕䡂䙁䄸睑療䝁䄰䅣桂䝁䄴入時䕁䅳党㕂䙁䅍䅤桂䡁䅑督時䡁䅙免時䕁䅙兡畂䝁䅅䅢畁䡁䅧䅢穂䝁䄰兘䱂䝁䅕入時䙁䅍䅤桂䡁䅑督湁䍁䅅䅊䍂䍁䅑杍㉁䅁䅁杒䅧䥁䅧䅁湁䙁䅳睑療䡁䅁入杁䝁䄸杚杁䙁䅍䅕䡂䙁䄸睑療䝁䄰䅣桂䝁䄴入時䕁䅳党㕂䙁䅍䅤桂䡁䅑督時䡁䅙免時䕁䅙兡畂䝁䅅䅢畁䡁䅧䅢穂䝁䄰兘䱂䝁䅕入時䙁䅍䅤桂䡁䅑督湁䍁䅅䅊佂䍁䅑杍ㅁ䑁䅯䅊兂䍁䅑杍ㅁ䅁䅁睒䅧䥁䅧䅁湁䙁䅳睑療䡁䅁入杁䝁䄸杚杁䙁䅍䅕䡂䙁䄸睑療䝁䄰䅣桂䝁䄴入時䕁䅳党㕂䙁䅍䅤桂䡁䅑督時䡁䅙免時䕁䅙兡畂䝁䅅䅢畁䡁䅧䅢穂䝁䄰兘䱂䝁䅕入時䙁䅍䅤桂䡁䅑督湁䍁䅅䅊䕂䍁䅑杍㑁䑁䅯䅊䕂䍁䅑兎祁䅁䅁䅓䅧䥁䅧䅁湁䙁䅳睑療䡁䅁入杁䝁䄸杚杁䙁䅍䅕䡂䙁䄸睑療䝁䄰䅣桂䝁䄴入時䕁䅳党㕂䙁䅍䅤桂䡁䅑督時䡁䅙免時䕁䅙兡畂䝁䅅䅢畁䡁䅧䅢穂䝁䄰兘䱂䝁䅕入時䙁䅍䅤桂䡁䅑督湁䍁䅅䅊佂䍁䅑杍㉁䑁䅯䅊兂䍁䅑杍㉁䅁䅁兓䅧䡁䅯䅁湁䙁䅳睑療䡁䅁入杁䝁䄸杚杁䙁䅍䅕䡂䙁䄸睑療䝁䄰䅣桂䝁䄴入時䕁䅳党㕂䙁䅍䅤桂䡁䅑督時䡁䅙免時䕁䅙兡畂䝁䅅䅢畁䡁䅧䅢穂䝁䄰兘䱂䝁䅕入時䙁䅍䅤桂䡁䅑督湁䍁䅅䅊䝂䍁䅑兏䅁䕁䥳䅁㡂䅁䅁睊扂䕁䅍睢睂䡁䅫䅉療䝁䅙䅉呂䙁䅁睒時䕁䅍睢瑂䡁䅁兙畂䡁䅫睘䱂䝁䅕入呂䡁䅑兙あ䡁䅍睘㉂䑁䅅睘䝂䝁䅫杢桂䝁䅷杌㑂䝁䅷督瑂䙁䄰睓求䡁䅫睘呂䡁䅑兙あ䡁䅍睊桁䍁䅑杒歁䑁䅅兎䅁䕁䤰䅁㡂䅁䅁睊扂䕁䅍睢睂䡁䅫䅉療䝁䅙䅉呂䙁䅁睒時䕁䅍睢瑂䡁䅁兙畂䡁䅫睘䱂䝁䅕入呂䡁䅑兙あ䡁䅍睘㉂䑁䅅睘䝂䝁䅫杢桂䝁䅷杌㑂䝁䅷督瑂䙁䄰睓求䡁䅫睘呂䡁䅑兙あ䡁䅍睊桁䍁䅑村歁䑁䅙杍䅁䕁䤴䅁㡂䅁䅁睊扂䕁䅍睢睂䡁䅫䅉療䝁䅙䅉呂䙁䅁睒時䕁䅍睢瑂䡁䅁兙畂䡁䅫睘䱂䝁䅕入呂䡁䅑兙あ䡁䅍睘㉂䑁䅅睘䝂䝁䅫杢桂䝁䅷杌㑂䝁䅷督瑂䙁䄰睓求䡁䅫睘呂䡁䅑兙あ䡁䅍睊桁䍁䅑兒歁䑁䅙杍䅁䕁䤸䅁㡂䅁䅁睊扂䕁䅍睢睂䡁䅫䅉療䝁䅙䅉呂䙁䅁睒時䕁䅍睢瑂䡁䅁兙畂䡁䅫睘䱂䝁䅕入呂䡁䅑兙あ䡁䅍睘㉂䑁䅅睘䝂䝁䅫杢桂䝁䅷杌㑂䝁䅷督瑂䙁䄰睓求䡁䅫睘呂䡁䅑兙あ䡁䅍睊桁䍁䅑兒歁䑁䅙睍䅁䙁䥅䅁⭂䅁䅁睊扂䕁䅍睢睂䡁䅫䅉療䝁䅙䅉呂䙁䅁睒時䕁䅍睢瑂䡁䅁兙畂䡁䅫睘䱂䝁䅕入呂䡁䅑兙あ䡁䅍睘㉂䑁䅅睘䝂䝁䅫杢桂䝁䅷杌㑂䝁䅷督瑂䙁䄰睓求䡁䅫睘呂䡁䅑兙あ䡁䅍睊桁䍁䅑村歁䑁䅅䅍㉁䅁䅁杕䅧䥁䅷䅁湁䙁䅳睑療䡁䅁入杁䝁䄸杚杁䙁䅍䅕䡂䙁䄸睑療䝁䄰䅣桂䝁䄴入時䕁䅳党㕂䙁䅍䅤桂䡁䅑督時䡁䅙免時䕁䅙兡畂䝁䅅䅢畁䡁䅧䅢穂䝁䄰兘䱂䝁䅕入時䙁䅍䅤桂䡁䅑督湁䍁䅅䅊䑂䍁䅑免睁䑁䅫杏歁䕁䅍䅊硁䑁䅅兎䅁䙁䥑䅁䵃䅁䅁睊扂䕁䅍睢睂䡁䅫䅉療䝁䅙䅉呂䙁䅁睒時䕁䅍睢瑂䡁䅁兙畂䡁䅫睘䱂䝁䅕入呂䡁䅑兙あ䡁䅍睘㉂䑁䅅睘䝂䝁䅫杢桂䝁䅷杌㑂䝁䅷督瑂䙁䄰睓求䡁䅫睘呂䡁䅑兙あ䡁䅍睊桁䍁䅑睒歁䑁䅅䅍㍁䑁䅯䅊䭂䍁䅑免睁䑁䅣䅁噂䅃䅁䅓䅁䕁䄸䅣あ䝁䅫睢畂䡁䅍杏䑂䡁䅕杣祂䑁䄰兖呂䕁䅑䅌䑂䝁䄸杢㉂䕁䄰党あ䝁䅧睢歂䑁䄰䅓獁䕁䄴兑㥁䕁䄴兑䅁䙁䥙䅁千䅁䅁睊扂䕁䅍睢睂䡁䅫䅉療䝁䅙䅉呂䙁䅁睒時䕁䅍睢瑂䡁䅁兙畂䡁䅫睘䱂䝁䅕入呂䡁䅑兙あ䡁䅍睘㉂䑁䅅睘䝂䝁䅫杢桂䝁䅷杌㑂䝁䅷督瑂䙁䄰兓畂䝁䅍睢瑂䝁䅕睘呂䡁䅑兙あ䝁䅕兢求䝁䄴䅤湁䍁䅅䅊䙂䍁䅑李㙁䍁䅑兕歁䑁䅙䅁奂䅃䅁杫䅁䍁䅣睗䑂䝁䄸䅣㕂䍁䅁睢浂䍁䅁睕兂䕁䅣睘䑂䝁䄸兢睂䝁䅅杢㕂䙁䄸睓求䡁䅫睕あ䝁䅅䅤穂䙁䄸杤硁䙁䄸杒灂䝁䄴兙獂䍁䄴䅥獂䡁䅍兢摂䕁䅫杢橂䝁䄸兢求䙁䄸睕あ䝁䅅䅤求䝁䄰党畂䡁䅑睊桁䍁䅑兒歁䑁䅣杏歁䙁䅅䅊㍁䅁䅁杗䅧䥁䅉䅁湁䙁䅳睑療䡁䅁入杁䝁䄸杚杁䙁䅍䅕䡂䙁䄸睑療䝁䄰䅣桂䝁䄴入時䕁䅳党㕂䙁䅍䅤桂䡁䅑督時䡁䅙免時䕁䅙兡畂䝁䅅䅢畁䡁䅧䅢穂䝁䄰兘䍂䝁䅅䅢桂䝁䄴睙求䙁䄸睕潂䝁䅕党あ䍁䅣光歁䕁䅍䅊㉁䅁䅁睗䅧䥁䅷䅁湁䙁䅳睑療䡁䅁入杁䝁䄸杚杁䙁䅍䅕䡂䙁䄸睑療䝁䄰䅣桂䝁䄴入時䕁䅳党㕂䙁䅍䅤桂䡁䅑督時䡁䅙免時䕁䅙兡畂䝁䅅䅢畁䡁䅧䅢穂䝁䄰兘䍂䝁䅅䅢桂䝁䄴睙求䙁䄸睕潂䝁䅕党あ䍁䅣光歁䕁䅕䅊㍁䑁䅯䅊剂䍁䅑睎䅁䙁䤴䅁㙂䅁䅁睊扂䕁䅍睢睂䡁䅫䅉療䝁䅙䅉呂䙁䅁睒時䕁䅍睢瑂䡁䅁兙畂䡁䅫睘䱂䝁䅕入呂䡁䅑兙あ䡁䅍睘㉂䑁䅅睘䝂䝁䅫杢桂䝁䅷杌㑂䝁䅷督瑂䙁䄰睑桂䡁䅍䅡時䕁䅙䅢療䡁䅣睊桁䍁䅑睑歁䑁䅙䅁時䅃䅁䅨䅁䍁䅣睗䑂䝁䄸䅣㕂䍁䅁睢浂䍁䅁睕兂䕁䅣睘䑂䝁䄸兢睂䝁䅅杢㕂䙁䄸睓求䡁䅫睕あ䝁䅅䅤穂䙁䄸杤硁䙁䄸杒灂䝁䄴兙獂䍁䄴䅥獂䡁䅍兢摂䕁䅍兙穂䝁䅧睘䝂䝁䅷睢㍂䍁䅣光歁䕁䅕䅊㉁䑁䅯䅊剂䍁䅑李䅁䝁䥁䅁䕃䅁䅁睊扂䕁䅍睢睂䡁䅫䅉療䝁䅙䅉呂䙁䅁睒時䕁䅍睢瑂䡁䅁兙畂䡁䅫睘䱂䝁䅕入呂䡁䅑兙あ䡁䅍睘㉂䑁䅅睘䝂䝁䅫杢桂䝁䅷杌㑂䝁䅷督瑂䙁䄰睑桂䡁䅍䅡時䕁䅙䅢療䡁䅣睊桁䍁䅑兒歁䑁䅣杏歁䙁䅅䅊㍁䅁䅁杙䅧䥁䄴䅁湁䙁䅳睑療䡁䅁入杁䝁䄸杚杁䙁䅍䅕䡂䙁䄸睑療䝁䄰䅣桂䝁䄴入時䕁䅳党㕂䙁䅍䅤桂䡁䅑督時䡁䅙免時䕁䅙兡畂䝁䅅䅢畁䡁䅧䅢穂䝁䄰兘䑂䝁䅅䅣灂䡁䅑兙獂䝁䅫来桂䡁䅑兡療䝁䄴睊桁䍁䅑兒歁䑁䅑杏歁䕁䅯䅊ぁ䅁䅁䅚䅧䥁䄴䅁湁䙁䅳睑療䡁䅁入杁䝁䄸杚杁䙁䅍䅕䡂䙁䄸睑療䝁䄰䅣桂䝁䄴入時䕁䅳党㕂䙁䅍䅤桂䡁䅑督時䡁䅙免時䕁䅙兡畂䝁䅅䅢畁䡁䅧䅢穂䝁䄰兘䑂䝁䅅䅣灂䡁䅑兙獂䝁䅫来桂䡁䅑兡療䝁䄴睊桁䍁䅑兒歁䑁䅕杏歁䕁䅯䅊ㅁ䅁䅁杚䅧䩁䅯䅁湁䙁䅳睑療䡁䅁入杁䝁䄸杚杁䙁䅍䅕䡂䙁䄸睑療䝁䄰䅣桂䝁䄴入時䕁䅳党㕂䙁䅍䅤桂䡁䅑督時䡁䅙免時䕁䅙兡畂䝁䅅䅢畁䡁䅧䅢穂䝁䄰兘䑂䝁䅅䅣灂䡁䅑兙獂䙁䄸睕あ䡁䅉兤橂䡁䅑兤祂䝁䅕睘呂䡁䅕兢瑂䝁䅅杣㕂䍁䅣光歁䕁䅍䅊㉁䅁䅁睚䅧䭁䅯䅁湁䙁䅳睑療䡁䅁入杁䝁䄸杚杁䙁䅍䅕䡂䙁䄸睑療䝁䄰䅣桂䝁䄴入時䕁䅳党㕂䙁䅍䅤桂䡁䅑督時䡁䅙免時䕁䅙兡畂䝁䅅䅢畁䡁䅧䅢穂䝁䄰兘䑂䝁䅅䅣灂䡁䅑兙獂䙁䄸睕あ䡁䅉兤橂䡁䅑兤祂䝁䅕睘呂䡁䅕兢瑂䝁䅅杣㕂䍁䅣光歁䕁䅍䅊硁䑁䅕杏歁䕁䅍䅊硁䑁䅣免䅁䝁䥫䅁歃䅁䅁睊扂䕁䅍睢睂䡁䅫䅉療䝁䅙䅉呂䙁䅁睒時䕁䅍睢瑂䡁䅁兙畂䡁䅫睘䱂䝁䅕入呂䡁䅑兙あ䡁䅍睘㉂䑁䅅睘䝂䝁䅫杢桂䝁䅷杌㑂䝁䅷督瑂䙁䄰睑桂䡁䅁兡あ䝁䅅䅢時䙁䅍䅤祂䡁䅕睙あ䡁䅕杣求䙁䄸睕ㅂ䝁䄰兢桂䡁䅉入湁䍁䅅䅊䙂䍁䅑睎㙁䍁䅑兕歁䑁䅣䅁煂䅃䅁䅯䅁䍁䅣睗䑂䝁䄸䅣㕂䍁䅁睢浂䍁䅁睕兂䕁䅣睘䑂䝁䄸兢睂䝁䅅杢㕂䙁䄸睓求䡁䅫睕あ䝁䅅䅤穂䙁䄸杤硁䙁䄸杒灂䝁䄴兙獂䍁䄴䅥獂䡁䅍兢摂䕁䅍兙睂䝁䅫䅤桂䝁䅷睘呂䡁䅑杣ㅂ䝁䅍䅤ㅂ䡁䅉党時䍁䅁䅒求䡁䅑兙灂䝁䅷督杁䍁䅣光歁䕁䅳䅊硁䑁䅉䅁牂䅃䅁䅯䅁䍁䅣睗䑂䝁䄸䅣㕂䍁䅁睢浂䍁䅁睕兂䕁䅣睘䑂䝁䄸兢睂䝁䅅杢㕂䙁䄸睓求䡁䅫睕あ䝁䅅䅤穂䙁䄸杤硁䙁䄸杒灂䝁䄴兙獂䍁䄴䅥獂䡁䅍兢摂䕁䅍兙睂䝁䅫䅤桂䝁䅷睘呂䡁䅑杣ㅂ䝁䅍䅤ㅂ䡁䅉党時䍁䅁䅒求䡁䅑兙灂䝁䅷督杁䍁䅣光歁䕁䅅兑歁䑁䅕䅁獂䅃䅁䅤䅁䍁䅣睗䑂䝁䄸䅣㕂䍁䅁睢浂䍁䅁睕兂䕁䅣睘䑂䝁䄸兢睂䝁䅅杢㕂䙁䄸睓求䡁䅫睕あ䝁䅅䅤穂䙁䄸杤硁䙁䄸杒灂䝁䄴兙獂䍁䄴䅥獂䡁䅍兢摂䙁䅉兙あ䝁䅫睢穂䍁䅣光歁䕁䅍䅊㉁䅁䅁兢䅧䡁䄴䅁湁䙁䅳睑療䡁䅁入杁䝁䄸杚杁䙁䅍䅕䡂䙁䄸睑療䝁䄰䅣桂䝁䄴入時䕁䅳党㕂䙁䅍䅤桂䡁䅑督時䡁䅙免時䕁䅙兡畂䝁䅅䅢畁䡁䅧䅢穂䝁䄰兘卂䝁䅅䅤灂䝁䄸督湁䍁䅅䅊䕂䍁䅑李㙁䍁䅑兓歁䑁䅙䅁畂䅃䅁杦䅁䍁䅣睗䑂䝁䄸䅣㕂䍁䅁睢浂䍁䅁睕兂䕁䅣睘䑂䝁䄸兢睂䝁䅅杢㕂䙁䄸睓求䡁䅫睕あ䝁䅅䅤穂䙁䄸杤硁䙁䄸杒灂䝁䄴兙獂䍁䄴䅥獂䡁䅍兢摂䙁䅉兙あ䝁䅫睢穂䍁䅣光歁䕁䅑䅊㍁䑁䅯䅊䩂䍁䅑睎䅁䡁䥁䅁权䅁䅁睊扂䕁䅍睢睂䡁䅫䅉療䝁䅙䅉呂䙁䅁睒時䕁䅍睢瑂䡁䅁兙畂䡁䅫睘䱂䝁䅕入呂䡁䅑兙あ䡁䅍睘㉂䑁䅅睘䝂䝁䅫杢桂䝁䅷杌㑂䝁䅷督瑂䙁䄰睑桂䡁䅁兡あ䝁䅅䅢時䙁䅍䅤祂䡁䅕睙あ䡁䅕杣求䙁䄸䅉䕂䝁䅕䅤桂䝁䅫䅢穂䍁䅁睊桁䍁䅑兑䉂䍁䅑李䅁䡁䥉䅁权䅁䅁睊扂䕁䅍睢睂䡁䅫䅉療䝁䅙䅉呂䙁䅁睒時䕁䅍睢瑂䡁䅁兙畂䡁䅫睘䱂䝁䅕入呂䡁䅑兙あ䡁䅍睘㉂䑁䅅睘䝂䝁䅫杢桂䝁䅷杌㑂䝁䅷督瑂䙁䄰睑桂䡁䅁兡あ䝁䅅䅢時䙁䅍䅤祂䡁䅕睙あ䡁䅕杣求䙁䄸䅉䕂䝁䅕䅤桂䝁䅫䅢穂䍁䅁睊桁䍁䅑村歁䑁䅑䅎䅁䡁䥍䅁权䅁䅁睊扂䕁䅍睢睂䡁䅫䅉療䝁䅙䅉呂䙁䅁睒時䕁䅍睢瑂䡁䅁兙畂䡁䅫睘䱂䝁䅕入呂䡁䅑兙あ䡁䅍睘㉂䑁䅅睘䝂䝁䅫杢桂䝁䅷杌㑂䝁䅷督瑂䙁䄰睑桂䡁䅁兡あ䝁䅅䅢時䙁䅍䅤祂䡁䅕睙あ䡁䅕杣求䙁䄸䅉䕂䝁䅕䅤桂䝁䅫䅢穂䍁䅁睊桁䍁䅑睒歁䑁䅅杍䅁䡁䥙䅁权䅁䅁睊扂䕁䅍睢睂䡁䅫䅉療䝁䅙䅉呂䙁䅁睒時䕁䅍睢瑂䡁䅁兙畂䡁䅫睘䱂䝁䅕入呂䡁䅑兙あ䡁䅍睘㉂䑁䅅睘䝂䝁䅫杢桂䝁䅷杌㑂䝁䅷督瑂䙁䄰睑桂䡁䅁兡あ䝁䅅䅢時䙁䅍䅤祂䡁䅕睙あ䡁䅕杣求䙁䄸䅉䕂䝁䅕䅤桂䝁䅫䅢穂䍁䅁睊桁䍁䅑兓歁䑁䅅杍䅁䡁䥣䅁权䅁䅁睊扂䕁䅍睢睂䡁䅫䅉療䝁䅙䅉呂䙁䅁睒時䕁䅍睢瑂䡁䅁兙畂䡁䅫睘䱂䝁䅕入呂䡁䅑兙あ䡁䅍睘㉂䑁䅅睘䝂䝁䅫杢桂䝁䅷杌㑂䝁䅷督瑂䙁䄰睑桂䡁䅁兡あ䝁䅅䅢時䙁䅍䅤祂䡁䅕睙あ䡁䅕杣求䙁䄸䅉䕂䝁䅕䅤桂䝁䅫䅢穂䍁䅁睊桁䍁䅑兒歁䑁䅅杍䅁䡁䥧䅁权䅁䅁睊扂䕁䅍睢睂䡁䅫䅉療䝁䅙䅉呂䙁䅁睒時䕁䅍睢瑂䡁䅁兙畂䡁䅫睘䱂䝁䅕入呂䡁䅑兙あ䡁䅍睘㉂䑁䅅睘䝂䝁䅫杢桂䝁䅷杌㑂䝁䅷督瑂䙁䄰睑桂䡁䅁兡あ䝁䅅䅢時䙁䅍䅤祂䡁䅕睙あ䡁䅕杣求䙁䄸䅉䕂䝁䅕䅤桂䝁䅫䅢穂䍁䅁睊桁䍁䅑䅒歁䑁䅣李䅁䡁䥫䅁坂䅁䅁睔睂䡁䅑兡療䝁䄴督㙁䕁䅍兤祂䡁䅉児噂䙁䅍䅒獁䕁䄰兙湂䑁䄰兔灂䝁䅷䅢灂䝁䄸杢穂䍁䅷睑療䝁䄴杤㥁䕁䅧䅌佂䕁䅅児佂䕁䅅䅁㙂䅃䅁䅯䅁䍁䅣睗䑂䝁䄸䅣㕂䍁䅁睢浂䍁䅁睕兂䕁䅣睘䑂䝁䄸兢睂䝁䅅杢㕂䙁䄸睓求䡁䅫睕あ䝁䅅䅤穂䙁䄸杤硁䙁䄸杒灂䝁䄴兙獂䍁䄴䅥獂䡁䅍兢摂䕁䅍兙睂䝁䅫䅤桂䝁䅷睘呂䡁䅑杣ㅂ䝁䅍䅤ㅂ䡁䅉党時䍁䅁䅒求䡁䅑兙灂䝁䅷督杁䍁䅣光歁䕁䅙䅊硁䑁䅉䅁㡂䅃䅁䅯䅁䍁䅣睗䑂䝁䄸䅣㕂䍁䅁睢浂䍁䅁睕兂䕁䅣睘䑂䝁䄸兢睂䝁䅅杢㕂䙁䄸睓求䡁䅫睕あ䝁䅅䅤穂䙁䄸杤硁䙁䄸杒灂䝁䄴兙獂䍁䄴䅥獂䡁䅍兢摂䕁䅍兙睂䝁䅫䅤桂䝁䅷睘呂䡁䅑杣ㅂ䝁䅍䅤ㅂ䡁䅉党時䍁䅁䅒求䡁䅑兙灂䝁䅷督杁䍁䅣光歁䕁䅉䅊硁䑁䅉䅁㥂䅃䅁䅯䅁䍁䅣睗䑂䝁䄸䅣㕂䍁䅁睢浂䍁䅁睕兂䕁䅣睘䑂䝁䄸兢睂䝁䅅杢㕂䙁䄸睓求䡁䅫睕あ䝁䅅䅤穂䙁䄸杤硁䙁䄸杒灂䝁䄴兙獂䍁䄴䅥獂䡁䅍兢摂䕁䅍兙睂䝁䅫䅤桂䝁䅷睘呂䡁䅑杣ㅂ䝁䅍䅤ㅂ䡁䅉党時䍁䅁䅒求䡁䅑兙灂䝁䅷督杁䍁䅣光歁䕁䅙䅊㍁䑁䅙䅁⽂䅃䅁䅯䅁䍁䅣睗䑂䝁䄸䅣㕂䍁䅁睢浂䍁䅁睕兂䕁䅣睘䑂䝁䄸兢睂䝁䅅杢㕂䙁䄸睓求䡁䅫睕あ䝁䅅䅤穂䙁䄸杤硁䙁䄸杒灂䝁䄴兙獂䍁䄴䅥獂䡁䅍兢摂䕁䅍兙睂䝁䅫䅤桂䝁䅷睘呂䡁䅑杣ㅂ䝁䅍䅤ㅂ䡁䅉党時䍁䅁䅒求䡁䅑兙灂䝁䅷督杁䍁䅣光歁䕁䅯䅊㍁䑁䅙䅁䅃䅃䅁䅯䅁䍁䅣睗䑂䝁䄸䅣㕂䍁䅁睢浂䍁䅁睕兂䕁䅣睘䑂䝁䄸兢睂䝁䅅杢㕂䙁䄸睓求䡁䅫睕あ䝁䅅䅤穂䙁䄸杤硁䙁䄸杒灂䝁䄴兙獂䍁䄴䅥獂䡁䅍兢摂䕁䅍兙睂䝁䅫䅤桂䝁䅷睘呂䡁䅑杣ㅂ䝁䅍䅤ㅂ䡁䅉党時䍁䅁䅒求䡁䅑兙灂䝁䅷督杁䍁䅣光歁䕁䅧䅊ぁ䑁䅑䅁䉃䅃䅁杭䅁䍁䅣睗䑂䝁䄸䅣㕂䍁䅁睢浂䍁䅁睕兂䕁䅣睘䑂䝁䄸兢睂䝁䅅杢㕂䙁䄸睓求䡁䅫睕あ䝁䅅䅤穂䙁䄸杤硁䙁䄸杒灂䝁䄴兙獂䍁䄴䅥獂䡁䅍兢摂䕁䅍兙睂䝁䅫䅤桂䝁䅷睘呂䡁䅑杣ㅂ䝁䅍䅤ㅂ䡁䅉党時䙁䅍兤瑂䝁䄰兙祂䡁䅫睊桁䍁䅑睑歁䑁䅣䅁䍃䅃䅁䅱䅁䍁䅣睗䑂䝁䄸䅣㕂䍁䅁睢浂䍁䅁睕兂䕁䅣睘䑂䝁䄸兢睂䝁䅅杢㕂䙁䄸睓求䡁䅫睕あ䝁䅅䅤穂䙁䄸杤硁䙁䄸杒灂䝁䄴兙獂䍁䄴䅥獂䡁䅍兢摂䕁䅍兙睂䝁䅫䅤桂䝁䅷睘呂䡁䅑杣ㅂ䝁䅍䅤ㅂ䡁䅉党時䙁䅍兤瑂䝁䄰兙祂䡁䅫睊桁䍁䅑杒歁䑁䅅䅍㙁䍁䅑杕歁䑁䅅䅍䅁䥁䥍䅁潃䅁䅁睊扂䕁䅍睢睂䡁䅫䅉療䝁䅙䅉呂䙁䅁睒時䕁䅍睢瑂䡁䅁兙畂䡁䅫睘䱂䝁䅕入呂䡁䅑兙あ䡁䅍睘㉂䑁䅅睘䝂䝁䅫杢桂䝁䅷杌㑂䝁䅷督瑂䙁䄰睑桂䡁䅁兡あ䝁䅅䅢時䙁䅍䅤祂䡁䅕睙あ䡁䅕杣求䙁䄸睕ㅂ䝁䄰兢桂䡁䅉入湁䍁䅅䅊䝂䍁䅑免硁䑁䅯䅊卂䍁䅑免硁䅁䅁全䅧䭁䅁䅁湁䙁䅳睑療䡁䅁入杁䝁䄸杚杁䙁䅍䅕䡂䙁䄸睑療䝁䄰䅣桂䝁䄴入時䕁䅳党㕂䙁䅍䅤桂䡁䅑督時䡁䅙免時䕁䅙兡畂䝁䅅䅢畁䡁䅧䅢穂䝁䄰兘䑂䝁䅅䅣灂䡁䅑兙獂䙁䄸睕あ䡁䅉兤橂䡁䅑兤祂䝁䅕睘杁䕁䅑党あ䝁䅅兡獂䡁䅍䅉湁䍁䅅䅊䕂䍁䅑免祁䅁䅁睨䅧䭁䅁䅁湁䙁䅳睑療䡁䅁入杁䝁䄸杚杁䙁䅍䅕䡂䙁䄸睑療䝁䄰䅣桂䝁䄴入時䕁䅳党㕂䙁䅍䅤桂䡁䅑督時䡁䅙免時䕁䅙兡畂䝁䅅䅢畁䡁䅧䅢穂䝁䄰兘䑂䝁䅅䅣灂䡁䅑兙獂䙁䄸睕あ䡁䅉兤橂䡁䅑兤祂䝁䅕睘杁䕁䅑党あ䝁䅅兡獂䡁䅍䅉湁䍁䅅䅊䙂䍁䅑䅎ぁ䅁䅁杩䅧䭁䅁䅁湁䙁䅳睑療䡁䅁入杁䝁䄸杚杁䙁䅍䅕䡂䙁䄸睑療䝁䄰䅣桂䝁䄴入時䕁䅳党㕂䙁䅍䅤桂䡁䅑督時䡁䅙免時䕁䅙兡畂䝁䅅䅢畁䡁䅧䅢穂䝁䄰兘䑂䝁䅅䅣灂䡁䅑兙獂䙁䄸睕あ䡁䅉兤橂䡁䅑兤祂䝁䅕睘杁䕁䅑党あ䝁䅅兡獂䡁䅍䅉湁䍁䅅䅊䝂䍁䅑䅎ぁ䅁䅁睩䅧䭁䅁䅁湁䙁䅳睑療䡁䅁入杁䝁䄸杚杁䙁䅍䅕䡂䙁䄸睑療䝁䄰䅣桂䝁䄴入時䕁䅳党㕂䙁䅍䅤桂䡁䅑督時䡁䅙免時䕁䅙兡畂䝁䅅䅢畁䡁䅧䅢穂䝁䄰兘䑂䝁䅅䅣灂䡁䅑兙獂䙁䄸睕あ䡁䅉兤橂䡁䅑兤祂䝁䅕睘杁䕁䅑党あ䝁䅅兡獂䡁䅍䅉湁䍁䅅䅊䡂䍁䅑睎㉁䅁䅁䅫䅧䭁䅁䅁湁䙁䅳睑療䡁䅁入杁䝁䄸杚杁䙁䅍䅕䡂䙁䄸睑療䝁䄰䅣桂䝁䄴入時䕁䅳党㕂䙁䅍䅤桂䡁䅑督時䡁䅙免時䕁䅙兡畂䝁䅅䅢畁䡁䅧䅢穂䝁䄰兘䑂䝁䅅䅣灂䡁䅑兙獂䙁䄸睕あ䡁䅉兤橂䡁䅑兤祂䝁䅕睘杁䕁䅑党あ䝁䅅兡獂䡁䅍䅉湁䍁䅅䅊䭂䍁䅑䅎ぁ䅁䅁兪䅧䭁䅁䅁湁䙁䅳睑療䡁䅁入杁䝁䄸杚杁䙁䅍䅕䡂䙁䄸睑療䝁䄰䅣桂䝁䄴入時䕁䅳党㕂䙁䅍䅤桂䡁䅑督時䡁䅙免時䕁䅙兡畂䝁䅅䅢畁䡁䅧䅢穂䝁䄰兘䑂䝁䅅䅣灂䡁䅑兙獂䙁䄸睕あ䡁䅉兤橂䡁䅑兤祂䝁䅕睘杁䕁䅑党あ䝁䅅兡獂䡁䅍䅉湁䍁䅅䅊䑂䍁䅑睎㉁䅁䅁睪䅧䭁䅁䅁湁䙁䅳睑療䡁䅁入杁䝁䄸杚杁䙁䅍䅕䡂䙁䄸睑療䝁䄰䅣桂䝁䄴入時䕁䅳党㕂䙁䅍䅤桂䡁䅑督時䡁䅙免時䕁䅙兡畂䝁䅅䅢畁䡁䅧䅢穂䝁䄰兘䑂䝁䅅䅣灂䡁䅑兙獂䙁䄸睕あ䡁䅉兤橂䡁䅑兤祂䝁䅕睘杁䕁䅑党あ䝁䅅兡獂䡁䅍䅉湁䍁䅅䅊䩂䍁䅑睎㉁䅁䅁八䅧䭁䅁䅁湁䙁䅳睑療䡁䅁入杁䝁䄸杚杁䙁䅍䅕䡂䙁䄸睑療䝁䄰䅣桂䝁䄴入時䕁䅳党㕂䙁䅍䅤桂䡁䅑督時䡁䅙免時䕁䅙兡畂䝁䅅䅢畁䡁䅧䅢穂䝁䄰兘䑂䝁䅅䅣灂䡁䅑兙獂䙁䄸睕あ䡁䅉兤橂䡁䅑兤祂䝁䅕睘杁䕁䅑党あ䝁䅅兡獂䡁䅍䅉湁䍁䅅䅊䱂䍁䅑睎㉁䅁䅁杫䅧䥁䅁䅁湁䙁䅳睑療䡁䅁入杁䝁䄸杚杁䙁䅍䅕䡂䙁䄸睑療䝁䄰䅣桂䝁䄴入時䕁䅳党㕂䙁䅍䅤桂䡁䅑督時䡁䅙免時䕁䅙兡畂䝁䅅䅢畁䡁䅧䅢穂䝁䄰兘呂䡁䅕䅣睂䝁䅷党瑂䝁䅕杢あ䝁䅅䅢湁䍁䅅䅊䑂䍁䅑李䅁䩁䥍䅁䭃䅁䅁睊扂䕁䅍睢睂䡁䅫䅉療䝁䅙䅉呂䙁䅁睒時䕁䅍睢瑂䡁䅁兙畂䡁䅫睘䱂䝁䅕入呂䡁䅑兙あ䡁䅍睘㉂䑁䅅睘䝂䝁䅫杢桂䝁䅷杌㑂䝁䅷督瑂䙁䄰睕ㅂ䡁䅁䅣獂䝁䅕兢求䝁䄴䅤桂䝁䅷睊桁䍁䅑䅒歁䑁䅙杏歁䕁䅫䅊㉁䅁䅁䅬䅧䩁䅁䅁湁䙁䅳睑療䡁䅁入杁䝁䄸杚杁䙁䅍䅕䡂䙁䄸睑療䝁䄰䅣桂䝁䄴入時䕁䅳党㕂䙁䅍䅤桂䡁䅑督時䡁䅙免時䕁䅙兡畂䝁䅅䅢畁䡁䅧䅢穂䝁䄰兘呂䡁䅕䅣睂䝁䅷党瑂䝁䅕杢あ䝁䅅䅢湁䍁䅅䅊䑂䍁䅑免硁䑁䅯䅊䑂䍁䅑免㉁䑁䅑䅁噃䅃䅁杩䅁䍁䅣睗䑂䝁䄸䅣㕂䍁䅁睢浂䍁䅁睕兂䕁䅣睘䑂䝁䄸兢睂䝁䅅杢㕂䙁䄸睓求䡁䅫睕あ䝁䅅䅤穂䙁䄸杤硁䙁䄸杒灂䝁䄴兙獂䍁䄴䅥獂䡁䅍兢摂䙁䅍兤睂䡁䅁䅢求䝁䄰党畂䡁䅑兙獂䍁䅣光歁䕁䅑䅊㍁䑁䅯䅊䩂䍁䅑睎䅁䩁䥙䅁䭃䅁䅁睊扂䕁䅍睢睂䡁䅫䅉療䝁䅙䅉呂䙁䅁睒時䕁䅍睢瑂䡁䅁兙畂䡁䅫睘䱂䝁䅕入呂䡁䅑兙あ䡁䅍睘㉂䑁䅅睘䝂䝁䅫杢桂䝁䅷杌㑂䝁䅷督瑂䙁䄰䅕求䝁䄴督灂䝁䄸杢瑁䕁䄸䅕䙂䕁䅉睊桁䍁䅑䅒歁䑁䅙杏歁䕁䅫䅊㉁䅁䅁䅭䅧䕁䅷䅁偂䡁䅁䅤灂䝁䄸杢穂䑁䅯䅉䑂䡁䅕杣祂䑁䄰兖呂䕁䅑䅌䑂䝁䄸杢㉂䕁䄰党あ䝁䅧睢歂䑁䄰䅓獁䍁䅁杔䉂䑁䄰杔䉂䅁䅁睭䅧䡁䄴䅁湁䙁䅳睑療䡁䅁入杁䝁䄸杚杁䙁䅍䅕䡂䙁䄸睑療䝁䄰䅣桂䝁䄴入時䕁䅳党㕂䙁䅍䅤桂䡁䅑督時䡁䅙免時䕁䅙兡畂䝁䅅䅢畁䡁䅧䅢穂䝁䄰兘䱂䝁䅕入時䙁䅍䅤桂䡁䅑督湁䍁䅅䅊䍂䍁䅑免睁䑁䅣䅁捃䅃䅁䅪䅁䍁䅣睗䑂䝁䄸䅣㕂䍁䅁睢浂䍁䅁睕兂䕁䅣睘䑂䝁䄸兢睂䝁䅅杢㕂䙁䄸睓求䡁䅫睕あ䝁䅅䅤穂䙁䄸杤硁䙁䄸杒灂䝁䄴兙獂䍁䄴䅥獂䡁䅍兢摂䕁䅳党㕂䙁䄸睕あ䝁䅅䅤穂䍁䅣光歁䕁䅑䅊硁䑁䅅免㙁䍁䅑䅒歁䑁䅅免㉁䅁䅁杮䅧䥁䅷䅁湁䙁䅳睑療䡁䅁入杁䝁䄸杚杁䙁䅍䅕䡂䙁䄸睑療䝁䄰䅣桂䝁䄴入時䕁䅳党㕂䙁䅍䅤桂䡁䅑督時䡁䅙免時䕁䅙兡畂䝁䅅䅢畁䡁䅧䅢穂䝁䄰兘䱂䝁䅕入時䙁䅍䅤桂䡁䅑督湁䍁䅅䅊䙂䍁䅑免睁䑁䅣杏歁䕁䅙䅊硁䑁䅁睎䅁䩁䤸䅁⭂䅁䅁睊扂䕁䅍睢睂䡁䅫䅉療䝁䅙䅉呂䙁䅁睒時䕁䅍睢瑂䡁䅁兙畂䡁䅫睘䱂䝁䅕入呂䡁䅑兙あ䡁䅍睘㉂䑁䅅睘䝂䝁䅫杢桂䝁䅷杌㑂䝁䅷督瑂䙁䄰杕桂䡁䅑兡療䡁䅍睊桁䍁䅑䅒歁䑁䅙杏歁䕁䅯䅊㉁䅁䅁䅯䅧䡁䄴䅁湁䙁䅳睑療䡁䅁入杁䝁䄸杚杁䙁䅍䅕䡂䙁䄸睑療䝁䄰䅣桂䝁䄴入時䕁䅳党㕂䙁䅍䅤桂䡁䅑督時䡁䅙免時䕁䅙兡畂䝁䅅䅢畁䡁䅧䅢穂䝁䄰兘卂䝁䅅䅤灂䝁䄸督湁䍁䅅䅊䕂䍁䅑睎㙁䍁䅑杓歁䑁䅣䅁桃䅃䅁䅤䅁䍁䅣睗䑂䝁䄸䅣㕂䍁䅁睢浂䍁䅁睕兂䕁䅣睘䑂䝁䄸兢睂䝁䅅杢㕂䙁䄸睓求䡁䅫睕あ䝁䅅䅤穂䙁䄸杤硁䙁䄸杒灂䝁䄴兙獂䍁䄴䅥獂䡁䅍兢摂䙁䅉兙あ䝁䅫睢穂䍁䅣光歁䕁䅍䅊㍁䅁䅁杯䅧䥁䅑䅁湁䙁䅳睑療䡁䅁入杁䝁䄸杚杁䙁䅍䅕䡂䙁䄸睑療䝁䄰䅣桂䝁䄴入時䕁䅳党㕂䙁䅍䅤桂䡁䅑督時䡁䅙免時䕁䅙兡畂䝁䅅䅢畁䡁䅧䅢穂䝁䄰兘卂䝁䅅䅤灂䝁䄸督湁䍁䅅䅊䑂䍁䅑免祁䑁䅯䅊䑂䍁䅑免ㅁ䑁䅧䅁橃䅃䅁䅧䅁䍁䅣睗䑂䝁䄸䅣㕂䍁䅁睢浂䍁䅁睕兂䕁䅣睘䑂䝁䄸兢睂䝁䅅杢㕂䙁䄸睓求䡁䅫睕あ䝁䅅䅤穂䙁䄸杤硁䙁䄸杒灂䝁䄴兙獂䍁䄴䅥獂䡁䅍兢摂䙁䅍兤睂䡁䅁䅢求䝁䄰党畂䡁䅑兙獂䍁䅣光歁䕁䅍䅊㍁䅁䅁兰䅧䩁䅁䅁湁䙁䅳睑療䡁䅁入杁䝁䄸杚杁䙁䅍䅕䡂䙁䄸睑療䝁䄰䅣桂䝁䄴入時䕁䅳党㕂䙁䅍䅤桂䡁䅑督時䡁䅙免時䕁䅙兡畂䝁䅅䅢畁䡁䅧䅢穂䝁䄰兘呂䡁䅕䅣睂䝁䅷党瑂䝁䅕杢あ䝁䅅䅢湁䍁䅅䅊䑂䍁䅑免祁䑁䅯䅊䑂䍁䅑免㉁䑁䅕䅁浃䅃䅁杩䅁䍁䅣睗䑂䝁䄸䅣㕂䍁䅁睢浂䍁䅁睕兂䕁䅣睘䑂䝁䄸兢睂䝁䅅杢㕂䙁䄸睓求䡁䅫睕あ䝁䅅䅤穂䙁䄸杤硁䙁䄸杒灂䝁䄴兙獂䍁䄴䅥獂䡁䅍兢摂䙁䅍兤睂䡁䅁䅢求䝁䄰党畂䡁䅑兙獂䍁䅣光歁䕁䅑䅊㑁䑁䅯䅊䩂䍁䅑䅏䅁䭁䥣䅁䅃䅁䅁睊扂䕁䅍睢睂䡁䅫䅉療䝁䅙䅉呂䙁䅁睒時䕁䅍睢瑂䡁䅁兙畂䡁䅫睘䱂䝁䅕入呂䡁䅑兙あ䡁䅍睘㉂䑁䅅睘䝂䝁䅫杢桂䝁䅷杌㑂䝁䅷督瑂䙁䄰䅕求䝁䄴督灂䝁䄸杢瑁䕁䄸䅕䙂䕁䅉睊桁䍁䅑睑歁䑁䅣䅁潃䅃䅁权䅁䕁䅅兑兂䕁䅷䅁牃䅃䅁李䅁䕁䅅䅣睂䝁䅷党杁䕁䅫杢橂䍁䄴䅉潁䕁䄴兑呂䕁䅑兑剂䕁䅣睕㙁䕁䅅兑兂䕁䅷克䅁䭁䥷䅁歁䅁䅁睕兂䙁䄸兑䍂䙁䅍睘兂䕁䅕杕䩂䕁䄸䅒時䕁䅕睕啂䅁䅁䅳䅧䅁䄴䅁祁䑁䅁杍㑁䕁䅙兗䅁䱁䥅䅁佁䅁䅁杍睁䑁䅉李䝂䙁䅫䅁祃䅃䅁䅅䅁䑁䅉䅍祁䑁䅙杒剂䑁䅅䅁ぃ䅃䅁权䅁䕁䅙兕牁䑁䅉䅁ㅃ䅃䅁䅅䅁䑁䅉䅍祁䑁䅙杒剂䑁䅉䅁㉃䅃䅁权䅁䕁䅙兕牁䑁䅍䅁㍃䅃䅁杂䅁䙁䅅免䅁䱁䥯䅁佁䅁䅁杍睁䑁䅉兎䝂䙁䅫䅁㝃䅃䅁䅅䅁䑁䅉䅍祁䑁䅕杒剂䑁䅑䅁㡃䅃䅁䅮䅍䅁杷允䅁䅁䅙䅁䑁䅁䅷䅁䭁䥁䝣䅁䭁䝁䝅䅁䭁䅁䅅䅁䙁䅁䅁䅁权⭐䅚权婂杂䅁允䅁䅁䅅䅁䙁䙁䐶癶㉔穘䅨䍄䉁䅁䅁睂䅁䅁䅍䅄䅁䅁䅯睨䅙䅁䅯䅗䅙䅁䅯允䅁䅁䅕䅁䅁䭁⽁欵䙁䅁䅁䅁杁⭓䅚权呄睂䅁允䅁䅁䅅䅁䙁偁汖慡浦橱䅤䍄䉁䅁䅁杂䅁䅁䅍䅄䅁䅁䅯睨䅙䅁䅯兡䅙䅁䅯允䅁䅁䅕䅁䅁䕁瑂欵䭁䙁䝫䅁䉁䅁䅁允䅁䅁䅕婮桹併摐歏䵁䅉䅅䅁䡁䅁䅁睁䵁䅁䅁权䡃杂䅁权楂杂䅁权剂杂䅁兂䅁䅁䅁䑯洯䅑䅕䅁䅁䍁䱂欵䭁乁䡉䅁䉁䅁䅁允䅁䅁䅕兢䨳灋呹䕍䵁䅉䅅䅁䡁䅁䅁睁䵁䅁䅁权䡃杂䅁权浂杂䅁权䉁䅁䅁兂䅁䅁䅁䡷浪䅑䅕䅁䅁䝁㥂欵䭁乁䡑䅁䉁䅁䅁允䅁䅁䅕煍楺捪䑷䕎䵁䅉䅅䅁䡁䅁䅁睁䵁䅁䅁权䡃杂䅁权捂杂䅁权䉁䅁䅁兂䅁䅁䅁䕉浶䅑䅕䅁䅁䝁坂欵䭁乁䡑䅁䉁䅁䅁允䅁䅁䅕っ坷砹㤹歏䵁䅉䅅䅁䡁䅁䅁睁䵁䅁䅁权䡃杂䅁权時杂䅁权剂杂䅁兂䅁䅁䅁䝑洳䅑䅕䅁䅁䵁㑂欵䭁乁䡉䅁䉁䅁䅁允䅁䅁䅕唰祪䵃䕁歍䵁䅉䅅䅁䡁䅁䅁睁䵁䅁䅁权䡃杂䅁权歂杂䅁权䉁䅁䅁兂䅁䅁䅁䝷浈䅑䅕䅁䅁䕁瑂欵䭁乁䡑䅁䉁䅁䅁允䅁䅁䅯免䅁䅁杷允䅁䅁䅣䅁䑁䅁䅷䅁䭁䥁䝣䅁䭁䙁䝑䅁䭁䅁䅅䅁䙁䅁䅁䅁杂畖䅚兂䅁䅁䅁䝷浈䅑䅯䄱䅣䅁䅅䅁䉁䅁䅁兂歂湏㙒琳栰䅑杷允䅁䅁䅣䅁䑁䅁䅷䅁䭁䥁䝣䅁䭁䙁䝕䅁䭁䅁䅅䅁䙁䅁䅁䅁权⭐䅚兂䅁䅁䅁䕉浶䅑䅯朰䅣䅁䅅䅁䉁䅁䅁兂㡄䡇塐灅䑂䅑杷允䅁䅁䅣䅁䑁䅁䅷䅁䭁䥁䝣䅁䭁䝁䝍䅁䭁䅁䅅䅁䙁䅁䅁䅁权⭐䅚兂䅁䅁䅁䕉浶䅑䅯眰䅣䅁䅅䅁䉁䅁䅁兂獄䉯塌呍祉䅑杷允䅁䅁䅙䅁䑁䅁䅷䅁䭁䥁䝣䅁䭁䙁䝑䅁䭁䅁䅅䅁䙁䅁䅁䅁杁低䅚权婂杂䅁允䅁䅁䅅䅁䙁䍁瑔桒稯剕䅴䍄䉁䅁䅁睂䅁䅁䅍䅄䅁䅁䅯睨䅙䅁䅯兖䅙䅁䅯允䅁䅁䅕䅁䅁䵁桂欵䙁䅁䅁䅁䅂敢䅚权卄睂䅁允䅁䅁䅅䅁䙁䥁晖甶乤な䅤䍄䉁䅁䅁睂䅁䅁䅍䅄䅁䅁䅯睨䅙䅁䅯杘䅙䅁䅯兕䅙䅁䅕䅁䅁䍁䱂欵䙁䅁䅁䅁杂畖䅚权剄睂䅁允䅁䅁䅅䅁䙁䱁䕳卹䍲⭬⽧䍄䉁䅁䅁杂䅁䅁䅍䅄䅁䅁䅯睨䅙䅁䅯杗䅙䅁䅯兕䅙䅁䅕䅁䅁䭁⽁欵䭁䙁䝫䅁䉁䅁䅁允䅁䅁䅕瑤䅷儵䭥啎䵁䅉䅅䅁䝁䅁䅁睁䵁䅁䅁权䡃杂䅁权煂杂䅁权㥁䅁䅁兂䅁䅁䅁䝑洳䅑䅯兗䅙䅁䅅䅁䉁䅁䅁兂䱃剮洰杙桁䅑杷允䅁䅁䅙䅁䑁䅁䅷䅁䭁䥁䝣䅁䭁䙁䜸䅁䭁䙁䝅䅁䙁䅁䅁䅁杂畖䅚权婂杂䅁允䅁䅁䅅䅁䙁䱁偕慢渫䑂䅂䍄䉁䅁䅁杂䅁䅁䅍䅄䅁䅁䅯睨䅙䅁䅯杘䅙䅁䅯兕䅙䅁䅕䅁䅁䭁⽁欵䭁䙁䝫䅁䉁䅁䅁允䅁䅁䅕杤畤䵭慥啅䵁䅉䅅䅁䡁䅁䅁睁䵁䅁䅁权䡃杂䅁权兂杂䅁权剂杂䅁兂䅁䅁䅁䙙浢䅑䅕䅁䅁䵁桂欵䭁乁䡍䅁䉁䅁䅁允䅁䅁䅕穉乍㔸漲歄䵁䅉䅅䅁䡁䅁䅁睁䵁䅁䅁权䡃杂䅁权奂杂䅁权䉁䅁䅁兂䅁䅁䅁䕉浶䅑䅕䅁䅁䝁坂欵䭁乁䡁䅁䉁䅁䅁允䅁䅁䅕佩兏歎㘸䕐䵁䅉䅅䅁䡁䅁䅁睁䵁䅁䅁权䡃杂䅁权浂杂䅁权䉁䅁䅁兂䅁䅁䅁䑯洯䅑䅕䅁䅁䍁䱂欵䭁乁䡅䅁䉁䅁䅁允䅁䅁䅕歰歓穰䍌吴䴸䅉䅅䅁䡁䅁䅁睁䵁䅁䅁权䡃杂䅁权捂杂䅁权䉁䅁䅁兂䅁䅁䅁䝷浈䅑䅕䅁䅁䕁瑂欵䭁乁䡉䅁䉁䅁䅁允䅁䅁䅕䕪⽬㑌䑘く䵁䅉䅅䅁䡁䅁䅁睁䵁䅁䅁权䡃杂䅁权奂杂䅁权䉁䅁䅁兂䅁䅁䅁䑯洯䅑䅕䅁䅁䍁䱂欵䭁乁䡁䅁䉁䅁䅁允䅁䅁䅕⽅癇摐匱問䵁䅉䅅䅁䡁䅁䅁睁䵁䅁䅁权䡃杂䅁权歂杂䅁权䉁䅁䅁兂䅁䅁䅁䕉浶䅑䅕䅁䅁䝁坂欵䭁乁䡑䅁䉁䅁䅁允䅁䅁䅯免䅁䅁杷允䅁䅁䅣䅁䑁䅁䅷䅁䭁䥁䝣䅁䭁䝁䝫䅁䭁䅁䅅䅁䙁䅁䅁䅁杂畖䅚兂䅁䅁䅁䝷浈䅑䅯䄱䅣䅁䅅䅁䉁䅁䅁兂剂煶䙃䥂㕑䅑杷允䅁䅁䅣䅁䑁䅁䅷䅁䭁䥁䝣䅁䭁䙁䜰䅁䭁䅁䅅䅁䙁䅁䅁䅁权⭐䅚兂䅁䅁䅁䕉浶䅑䅯䄱䅣䅁䅅䅁䉁䅁䅁兂歂唶塍䠱䭣䅑杷允䅁䅁䅣䅁䑁䅁䅷䅁䭁䥁䝣䅁䭁䙁䜴䅁䭁䙁䝅䅁䙁䅁䅁䅁䅄教䅚兂䅁䅁䅁䝑洳䅑䅯䄱䅣䅁䅅䅁䉁䅁䅁兂䩃䉶番㉪䭷䅑杷允䅁䅁䅣䅁䑁䅁䅷䅁䭁䥁䝣䅁䭁䙁䝯䅁䭁䙁䝅䅁䙁䅁䅁䅁杁⭓䅚兂䅁䅁䅁䙙浢䅑䅯䄱䅣䅁䅅䅁䉁䅁䅁兂⭁浚兕䜲㈰䅑杷允䅁䅁䅣䅁䑁䅁䅷䅁䭁䥁䝣䅁䭁䙁䜸䅁䭁䙁䝅䅁䙁䅁䅁䅁杁⭓䅚兂䅁䅁䅁䙙浢䅑䅯䄰䅣䅁䅅䅁䉁䅁䅁兂硂獶猵ㅚ瘸䅑杷允䅁䅁䅣䅁䑁䅁䅷䅁䭁䥁䝣䅁䭁䝁䝙䅁䭁䅁䅅䅁䙁䅁䅁䅁杁⭓䅚兂䅁䅁䅁䙙浢䅑䅯䄱䅣䅁䅅䅁䉁䅁䅁兂桃晶㑰䄶穣䅑杷允䅁䅁䅣䅁䑁䅁䅷䅁䭁䥁䝣䅁䭁䝁䝍䅁䭁䅁䅅䅁䙁䅁䅁䅁䅄佋䅚兂䅁䅁䅁䑉浔䅑䅯䄱䅣䅁䅅䅁䉁䅁䅁兂潃硕搷䙃獍䅑杷允䅁䅁䅣䅁䑁䅁䅷䅁䭁䥁䝣䅁䭁䙁䝧䅁䭁䅁䅅䅁䙁䅁䅁䅁权⭐䅚兂䅁䅁䅁䕉浶䅑䅯朰䅣䅁䅅䅁䉁䅁䅁兂硂䅹卢晸㙙䅑杷允䅁䅁䅣䅁䑁䅁䅷䅁䭁䥁䝣䅁䭁䝁䝅䅁䭁䅁䅅䅁䙁䅁䅁䅁䅄佥䅚兂䅁䅁䅁䡙洳䅑䅯眰䅣䅁䅅䅁䉁䅁䅁兂祁噤㉤敷㕑䅑杷允䅁䅁䅣䅁䑁䅁䅷䅁䭁䥁䝣䅁䭁䝁䝷䅁䭁䙁䝅䅁䙁䅁䅁䅁䅄教䅚兂䅁䅁䅁䝑洳䅑䅯䄱䅣䅁䅅䅁䉁䅁䅁兂䥃䝙敖䅓䵷䅑杷允䅁䅁䅙䅁䑁䅁䅷䅁䭁䥁䝣䅁䭁䝁䝉䅁䭁䙁䝅䅁䙁䅁䅁䅁杂敦䅚权婂杂䅁允䅁䅁䅅䅁䭁䑁䅅䅁䵁䅉䅅䅁䡁䅁䅁睁䵁䅁䅁权䡃杂䅁权灂杂䅁权䉁䅁䅁兂䅁䅁䅁䝷浈䅑䅕䅁䅁䕁瑂欵䭁乁䡉䅁䉁䅁䅁允䅁䅁䅕歱䙩女捕啐䵁䅉䅅䅁䡁䅁䅁睁䵁䅁䅁权䡃杂䅁权桂杂䅁权䉁䅁䅁兂䅁䅁䅁䙙浢䅑䅕䅁䅁䵁桂欵䭁乁䡅䅁䉁䅁䅁允䅁䅁䅕䙄畱㝨娰歅䵁䅉䅅䅁䑁䅁䅁睁䵁䅁䅁权䡃杂䅁权橁䅁䅁允䅁䅁䅅䅁䭁䡁䝕䅁䵁䅉䅅䅁䡁䅁䅁睁䵁䅁䅁权䡃杂䅁权慂杂䅁权剂杂䅁兂䅁䅁䅁䑉浔䅑䅕䅁䅁䭁⽁欵䭁乁䡉䅁䉁䅁䅁允䅁䅁䅕㔯䍧低潭啎䵁䅉䅅䅁䡁䅁䅁睁䵁䅁䅁权䡃杂䅁权噂杂䅁权䉁䅁䅁兂䅁䅁䅁䝑洳䅑䅕䅁䅁䵁㑂欵䭁乁䡁䅁䉁䅁䅁允䅁䅁䅕慄佲䝃楳歒䵁䅉䅅䅁䡁䅁䅁睁䵁䅁䅁权䡃杂䅁权橂杂䅁权䉁䅁䅁兂䅁䅁䅁䝷浈䅑䅕䅁䅁䕁瑂欵䭁乁䡁䅁䉁䅁䅁允䅁䅁䅕䡪杖㜷塑き䵁䅉䅅䅁䝁䅁䅁睁䵁䅁䅁权䡃杂䅁权敂杂䅁权剂杂䅁兂䅁䅁䅁䝑洳䅑䅯兗䅙䅁䅅䅁䉁䅁䅁兂䉃㉸扴倸䬸䅑杷允䅁䅁䅣䅁䑁䅁䅷䅁䭁䥁䝣䅁䭁䙁䝑䅁䭁䅁䅅䅁䙁䅁䅁䅁䅄教䅚兂䅁䅁䅁䝑洳䅑䅯儰䅣䅁䅅䅁䉁䅁䅁兂汁ㅇ䑆ㅵ浺睐杷允䅁䅁䅣䅁䑁䅁䅷䅁䭁䥁䝣䅁䭁䙁䝙䅁䭁䅁䅅䅁䙁䅁䅁䅁杁⭓䅚兂䅁䅁䅁䙙浢䅑䅯䄰䅣䅁䅅䅁䉁䅁䅁兂䍃䉉唲ぇ剕䅑杷允䅁䅁䅣䅁䑁䅁䅷䅁䭁䥁䝣䅁䭁䙁䜴䅁䭁䙁䝅䅁䙁䅁䅁䅁权⭐䅚兂䅁䅁䅁䕉浶䅑䅯䄱䅣䅁䅅䅁䉁䅁䅁兂汄儯煕乸剉䅑杷允䅁䅁䅣䅁䑁䅁䅷䅁䭁䥁䝣䅁䭁䝁䝷䅁䭁䙁䝅䅁䙁䅁䅁䅁权⭐䅚兂䅁䅁䅁䕉浶䅑䅯眰䅣䅁䅅䅁䉁䅁䅁兂㡁卪䅲塍䡷䅑杷允䅁䅁䅣䅁䑁䅁䅷䅁䭁䥁䝣䅁䭁䝁䝅䅁䭁䅁䅅䅁䙁䅁䅁䅁䅄教䅚兂䅁䅁䅁䝑洳䅑䅯眰䅣䅁䅅䅁䉁䅁䅁兂杄㉌䱚癖䌹䅑杷允䅁䅁䅣䅁䑁䅁䅷䅁䭁䥁䝣䅁䭁䝁䝉䅁䭁䙁䝅䅁䙁䅁䅁䅁杁⭓䅚兂䅁䅁䅁䙙浢䅑䅯䄰䅣䅁䅅䅁䉁䅁䅁兂呂呑噮湥睙䅑杷允䅁䅁䅣䅁䑁䅁䅷䅁䭁䥁䝣䅁䭁䙁䝁䅁䭁䙁䝅䅁䙁䅁䅁䅁䅄佋䅚兂䅁䅁䅁䑉浔䅑䅯朰䅣䅁䅅䅁䉁䅁䅁兂婃䑅捤䴲䱯䅑杷允䅁䅁䅣䅁䑁䅁䅷䅁䭁䥁䝣䅁䭁䙁䝁䅁䭁䙁䝅䅁䙁䅁䅁䅁䅄佋䅚兂䅁䅁䅁䑉浔䅑䅯䄱䅣䅁䅅䅁䉁䅁䅁兂㙂坍ぃ䕙䩳䅑杷允䅁䅁䅣䅁䑁䅁䅷䅁䭁䥁䝣䅁䭁䝁䝧䅁䭁䙁䝅䅁䙁䅁䅁䅁杂畖䅚兂䅁䅁䅁䝷浈䅑䅯儰䅣䅁䅅䅁䉁䅁䅁兂㥁⼵ㅡ䅂㑌睐杷允䅁䅁䅣䅁䑁䅁䅷䅁䭁䥁䝣䅁䭁䙁䝁䅁䭁䙁䝅䅁䙁䅁䅁䅁杁⭓䅚兂䅁䅁䅁䙙浢䅑䅯儰䅣䅁䅅䅁䉁䅁䅁兂噂卺䥭䡢䥦睐杷允䅁䅁䅣䅁䑁䅁䅷䅁䭁䥁䝣䅁䭁䙁䜸䅁䭁䙁䝅䅁䙁䅁䅁䅁䅄佥䅚兂䅁䅁䅁䡙洳䅑䅯眰䅣䅁䅅䅁䉁䅁䅁兂灁䵴⽍䉶瘰䅑杷允䅁䅁䅣䅁䑁䅁䅷䅁䭁䥁䝣䅁䭁䙁䝑䅁䭁䅁䅅䅁䙁䅁䅁䅁䅄佥䅚兂䅁䅁䅁䡙洳䅑䅯䄰䅣䅁䅅䅁䉁䅁䅁兂硃匰呧呢樰䅑杷允䅁䅁䅣䅁䑁䅁䅷䅁䭁䥁䝣䅁䭁䙁䝕䅁䭁䅁䅅䅁䙁䅁䅁䅁杂畖䅚兂䅁䅁䅁䝷浈䅑䅯眰䅣䅁䅅䅁䉁䅁䅁兂⭁昷塄䑚䍎䅑杷允䅁䅁䅣䅁䑁䅁䅷䅁䭁䥁䝣䅁䭁䙁䝕䅁䭁䅁䅅䅁䙁䅁䅁䅁杁低䅚兂䅁䅁䅁䑯洯䅑䅯䄱䅣䅁䅅䅁䉁䅁䅁兂㉃扮䝚䑂⼸䅑杷允䅁䅁䅣䅁䑁䅁䅷䅁䭁䥁䝣䅁䭁䝁䝫䅁䭁䅁䅅䅁䙁䅁䅁䅁权⭐䅚兂䅁䅁䅁䕉浶䅑䅯朰䅣䅁䅅䅁䉁䅁䅁兂呄票漶穢㑫䅑杷允䅁䅁䅣䅁䑁䅁䅷䅁䭁䥁䝣䅁䭁䙁䜴䅁䭁䙁䝅䅁䙁䅁䅁䅁杂畖䅚兂䅁䅁䅁䝷浈䅑䅯䄰䅣䅁䅅䅁䉁䅁䅁兂畄極材牂䭷䅑杷允䅁䅁䅣䅁䑁䅁䅷䅁䭁䥁䝣䅁䭁䙁䝙䅁䭁䅁䅅䅁䙁䅁䅁䅁杂畖䅚兂䅁䅁䅁䝷浈䅑䅯儰䅣䅁䅅䅁䉁䅁䅁兂㍃潌乩癰呔睐杷允䅁䅁䅣䅁䑁䅁䅷䅁䭁䥁䝣䅁䭁䝁䝧䅁䭁䙁䝅䅁䙁䅁䅁䅁杂畖䅚兂䅁䅁䅁䝷浈䅑䅯眰䅣䅁䅅䅁䉁䅁䅁兂歄䤯䍰慦ぁ䅑杷允䅁䅁䅙䅁䑁䅁䅷䅁䭁䥁䝣䅁䭁䙁䜴䅁䭁䙁䝅䅁䙁䅁䅁䅁䅄教䅚权婂杂䅁允䅁䅁䅅䅁䙁䥁⬰䅱癗杬䄵䍄䉁䅁䅁睂䅁䅁䅍䅄䅁䅁䅯睨䅙䅁䅯睘䅙䅁䅯兕䅙䅁䅕䅁䅁䵁桂欵䙁䅁䅁䅁䅂敢䅚权剄睂䅁允䅁䅁䅅䅁䙁䑁塊灱唲晦⽅䍄䉁䅁䅁睂䅁䅁䅍䅄䅁䅁䅯睨䅙䅁䅯䅡䅙䅁䅯兕䅙䅁䅕䅁䅁䍁ぁ欵䙁䅁䅁䅁权⭐䅚权呄睂䅁允䅁䅁䅅䅁䙁䑁剐歷異橰䅆䍄䉁䅁䅁杂䅁䅁䅍䅄䅁䅁䅯睨䅙䅁䅯䅚䅙䅁䅯允䅁䅁䅕䅁䅁䕁瑂欵䭁䙁䝫䅁䉁䅁䅁允䅁䅁䅯党䅙䅁杷允䅁䅁䅣䅁䑁䅁䅷䅁䭁䥁䝣䅁䭁䙁䝕䅁䭁䅁䅅䅁䙁䅁䅁䅁杁低䅚兂䅁䅁䅁䑯洯䅑䅯䄰䅣䅁䅅䅁䉁䅁䅁兂灃㝤摧獏⽕䅑杷允䅁䅁䅣䅁䑁䅁䅷䅁䭁䥁䝣䅁䭁䙁䜸䅁䭁䙁䝅䅁䙁䅁䅁䅁杂畖䅚兂䅁䅁䅁䝷浈䅑䅯䄰䅣䅁䅅䅁䉁䅁䅁兂乃扭䭴歃睉䅑杷允䅁䅁䅣䅁䑁䅁䅷䅁䭁䥁䝣䅁䭁䝁䝫䅁䭁䅁䅅䅁䙁䅁䅁䅁杁⭓䅚兂䅁䅁䅁䙙浢䅑䅯䄰䅣䅁䅅䅁䉁䅁䅁兂祃㍋㉌李㕙䅑杷允䅁䅁䅣䅁䑁䅁䅷䅁䭁䥁䝣䅁䭁䙁䜰䅁䭁䅁䅅䅁䙁䅁䅁䅁杁⭓䅚兂䅁䅁䅁䙙浢䅑䅯儰䅣䅁䅅䅁䉁䅁䅁兂䡃㑔癨其丯睐杷允䅁䅁䅙䅁䑁䅁䅷䅁䭁䥁䝣䅁䭁䙁䝯䅁䭁䙁䝅䅁䙁䅁䅁䅁杁低䅚权婂杂䅁允䅁䅁䅅䅁䙁䭁㕸兹橴穕䅆䍄䉁䅁䅁杂䅁䅁䅍䅄䅁䅁䅯睨䅙䅁䅯杙䅙䅁䅯兕䅙䅁䅕䅁䅁䍁䱂欵䭁䙁䝫䅁䉁䅁䅁允䅁䅁䅕䔷匴癋摏歌䵁䅉䅅䅁䡁䅁䅁睁䵁䅁䅁权䡃杂䅁权坂杂䅁权䉁䅁䅁兂䅁䅁䅁䕉浶䅑䅕䅁䅁䝁坂欵䭁乁䡑䅁䉁䅁䅁允䅁䅁䅕搹䉫砱䑗啅䵁䅉䅅䅁䝁䅁䅁睁䵁䅁䅁权䡃杂䅁权摂杂䅁权䉁䅁䅁兂䅁䅁䅁䝷浈䅑䅯兗䅙䅁䅅䅁䉁䅁䅁兂㕄㙯穧㌹剁䅑杷允䅁䅁䅣䅁䑁䅁䅷䅁䭁䥁䝣䅁䭁䙁䜴䅁䭁䙁䝅䅁䙁䅁䅁䅁杁低䅚兂䅁䅁䅁䑯洯䅑䅯眰䅣䅁䅅䅁䉁䅁䅁兂杂䕅湹䘲乑䅑杷允䅁䅁䅣䅁䑁䅁䅷䅁䭁䥁䝣䅁䭁䝁䝯䅁䭁䑁䄰䅁䙁䅁䅁䅁权⭐䅚兂䅁䅁䅁䕉浶䅑䅯䄱䅣䅁䅅䅁䉁䅁䅁兂煃䡄㍦牂晧䅑杷允䅁䅁䅣䅁䑁䅁䅷䅁䭁䥁䝣䅁䭁䙁䝧䅁䭁䅁䅅䅁䙁䅁䅁䅁杂畖䅚兂䅁䅁䅁䝷浈䅑䅯䄱䅣䅁䅅䅁䉁䅁䅁兂摃杓䅡煋㡉䅑杷允䅁䅁䅣䅁䑁䅁䅷䅁䭁䥁䝣䅁䭁䝁䝯䅁䭁䑁䄰䅁䙁䅁䅁䅁杁低䅚兂䅁䅁䅁䑯洯䅑䅯䄱䅣䅁䅅䅁䉁䅁䅁兂坄㡅塮潰慳䅑杷允䅁䅁䅣䅁䑁䅁䅷䅁䭁䥁䝣䅁䭁䝁䝯䅁䭁䑁䄰䅁䙁䅁䅁䅁䅄教䅚兂䅁䅁䅁䝑洳䅑䅯朰䅣䅁䅅䅁䉁䅁䅁兂剂〵䉹奚桫䅑杷允䅁䅁䅣䅁䑁䅁䅷䅁䭁䥁䝣䅁䭁䙁䝷䅁䭁䅁䅅䅁䙁䅁䅁䅁杂畖䅚兂䅁䅁䅁䝷浈䅑䅯儰䅣䅁䅅䅁䉁䅁䅁兂⭂䨱摦⬴穈睐杷允䅁䅁䅣䅁䑁䅁䅷䅁䭁䥁䝣䅁䭁䝁䝙䅁䭁䅁䅅䅁䙁䅁䅁䅁杁⭓䅚兂䅁䅁䅁䙙浢䅑䅯䄰䅣䅁䅅䅁䉁䅁䅁兂敄坯煦噋礴䅑杷允䅁䅁䅙䅁䑁䅁䅷䅁䭁䥁䝣䅁䭁䝁䝯䅁䭁䑁䄰䅁䙁䅁䅁䅁䅄教䅚权婂杂䅁允䅁䅁䅅䅁䙁䙁湈䥔汆卩䅆䍄䉁䅁䅁睂䅁䅁䅍䅄䅁䅁䅯睨䅙䅁䅯兖䅙䅁䅯允䅁䅁䅕䅁䅁䵁桂欵䙁䅁䅁䅁䅂敢䅚权剄睂䅁允䅁䅁䅅䅁䙁䥁㑅汲㥒䅦䅴䍄䉁䅁䅁睂䅁䅁䅍䅄䅁䅁䅯睨䅙䅁䅯杚䅙䅁䅯允䅁䅁䅕䅁䅁䕁瑂欵䙁䅁䅁䅁䅄佥䅚权卄睂䅁允䅁䅁䅅䅁䙁䡁灤㉷灆䑋䅖䍄䉁䅁䅁睂䅁䅁䅍䅄䅁䅁䅯睨䅙䅁䅯䅡䅙䅁䅯兕䅙䅁䅕䅁䅁䭁⽁欵䙁䅁䅁䅁杁⭓䅚权啄睂䅁允䅁䅁䅅䅁䙁䉁橣剁晁䑳䅖䍄䉁䅁䅁睂䅁䅁䅍䅄䅁䅁䅯睨䅙䅁䅯䅢䅙䅁䅯兕䅙䅁䅕䅁䅁䭁⽁欵䙁䅁䅁䅁杁⭓䅚权啄睂䅁允䅁䅁䅅䅁䙁䭁儷啥潍東䅬䍄䉁䅁䅁睂䅁䅁䅍䅄䅁䅁䅯睨䅙䅁䅯杗䅙䅁䅯兕䅙䅁䅕䅁䅁䝁坂欵䙁䅁䅁䅁䅄教䅚权啄睂䅁允䅁䅁䅅䅁䙁䉁⭌䡰䉘呱䅖䍄䉁䅁䅁杂䅁䅁䅍䅄䅁䅁䅯睨䅙䅁䅯杗䅙䅁䅯兕䅙䅁䅕䅁䅁䝁坂欵䭁䙁䝫䅁䉁䅁䅁允䅁䅁䅕乢児䱁眹歎䵁䅉䅅䅁䝁䅁䅁睁䵁䅁䅁权䡃杂䅁权捂杂䅁权䉁䅁䅁兂䅁䅁䅁䝑洳䅑䅯兗䅙䅁䅅䅁䉁䅁䅁兂塂穐䩢睪ㅑ䅑杷允䅁䅁䅣䅁䑁䅁䅷䅁䭁䥁䝣䅁䭁䙁䝙䅁䭁䅁䅅䅁䙁䅁䅁䅁䅄教䅚兂䅁䅁䅁䝑洳䅑䅯儰䅣䅁䅅䅁䉁䅁䅁兂偃畁ぺ票午睐杷允䅁䅁䅣䅁䑁䅁䅷䅁䭁䥁䝣䅁䭁䙁䜰䅁䭁䅁䅅䅁䙁䅁䅁䅁䅄佋䅚兂䅁䅁䅁䑉浔䅑䅯朰䅣䅁䅅䅁䉁䅁䅁兂婁㥣卣焸䝅䅑杷允䅁䅁䅣䅁䑁䅁䅷䅁䭁䥁䝣䅁䭁䝁䝑䅁䭁䅁䅅䅁䙁䅁䅁䅁权⭐䅚兂䅁䅁䅁䕉浶䅑䅯眰䅣䅁䅅䅁䉁䅁䅁权硁䅁䅁䍄䉁䅁䅁睂䅁䅁䅍䅄䅁䅁䅯睨䅙䅁䅯条䅙䅁䅯児䅁䅁䅕䅁䅁䍁ぁ欵䙁䅁䅁䅁权⭐䅚权卄睂䅁允䅁䅁䅅䅁䙁䉁娰䝢㡭砹䄵䍄䉁䅁䅁睂䅁䅁䅍䅄䅁䅁䅯睨䅙䅁䅯兖䅙䅁䅯允䅁䅁䅕䅁䅁䍁ぁ欵䙁䅁䅁䅁权⭐䅚权卄睂䅁允䅁䅁䅅䅁䙁䕁癕ㅯ畨啅䅊䍄䉁䅁䅁睂䅁䅁䅍䅄䅁䅁䅯睨䅙䅁䅯䅘䅙䅁䅯允䅁䅁䅕䅁䅁䍁ぁ欵䙁䅁䅁䅁权⭐䅚权兄睂䅁允䅁䅁䅅䅁䙁䅁㕯⼷吸䑄䅤䍄䉁䅁䅁睂䅁䅁䅍䅄䅁䅁䅯睨䅙䅁䅯䅡䅙䅁䅯兕䅙䅁䅕䅁䅁䭁⽁欵䙁䅁䅁䅁杁⭓䅚权卄睂䅁允䅁䅁䅅䅁䙁䩁穬䉨⬴穑䅤䍄䉁䅁䅁睂䅁䅁䅍䅄䅁䅁䅯睨䅙䅁䅯䅖䅙䅁䅯允䅁䅁䅕䅁䅁䵁潁欵䙁䅁䅁䅁杁低䅚权啄睂䅁允䅁䅁䅅䅁䙁佁癷祵偣砲䅰䍄䉁䅁䅁睂䅁䅁䅍䅄䅁䅁䅯睨䅙䅁䅯杗䅙䅁䅯兕䅙䅁䅕䅁䅁䵁潁欵䙁䅁䅁䅁杁低䅚权兄睂䅁允䅁䅁䅅䅁䙁乁㍹留匰穏䅆䍄䉁䅁䅁睂䅁䅁䅍䅄䅁䅁䅯睨䅙䅁䅯䅕䅙䅁䅯兕䅙䅁䅕䅁䅁䭁⽁欵䙁䅁䅁䅁杁⭓䅚权兄睂䅁允䅁䅁䅅䅁䙁䵁䉌摭匹䅕䄹䍄䉁䅁䅁睂䅁䅁䅍䅄䅁䅁䅯睨䅙䅁䅯杗䅙䅁䅯兕䅙䅁䅕䅁䅁䭁⽁欵䙁䅁䅁䅁杁⭓䅚权卄睂䅁允䅁䅁䅅䅁䙁䭁⽮奤㙹穱䅚䍄䉁䅁䅁睂䅁䅁䅍䅄䅁䅁䅯睨䅙䅁䅯䅗䅙䅁䅯允䅁䅁䅕䅁䅁䍁䱂欵䙁䅁䅁䅁杂畖䅚权呄睂䅁允䅁䅁䅅䅁䙁䭁獅䡦琲稰䅨䍄䉁䅁䅁睂䅁䅁䅍䅄䅁䅁䅯睨䅙䅁䅯睘䅙䅁䅯兕䅙䅁䅕䅁䅁䍁ぁ欵䙁䅁䅁䅁权⭐䅚权呄睂䅁允䅁䅁䅅䅁䙁䥁䱷睩䥹䌱䅨䍄䉁䅁䅁睂䅁䅁䅍䅄䅁䅁䅯睨䅙䅁䅯兡䅙䅁䅯允䅁䅁䅕䅁䅁䭁⽁欵䙁䅁䅁䅁杁⭓䅚权啄睂䅁允䅁䅁䅅䅁䙁䑁午㥩㥲橵䅚䍄䉁䅁䅁睂䅁䅁䅍䅄䅁䅁䅯睨䅙䅁䅯杙䅙䅁䅯兕䅙䅁䅕䅁䅁䍁䱂欵䙁䅁䅁䅁杂畖䅚权卄睂䅁允䅁䅁䅅䅁䙁䱁硉慭㥹味䅆䍄䉁䅁䅁杂䅁䅁䅍䅄䅁䅁䅯睨䅙䅁䅯杖䅙䅁䅯允䅁䅁䅕䅁䅁䍁ぁ欵䭁䙁䝫䅁䉁䅁䅁允䅁䅁䅕灐㥐稸村歃䵁䅉䅅䅁䡁䅁䅁睁䵁䅁䅁权䡃杂䅁权潂杂䅁权剂杂䅁兂䅁䅁䅁䝷浈䅑䅕䅁䅁䕁瑂欵䭁乁䡍䅁䉁䅁䅁允䅁䅁䅕㡄獯䠴瑑䕎䵁䅉䅅䅁䡁䅁䅁睁䵁䅁䅁权䡃杂䅁权楂杂䅁权剂杂䅁兂䅁䅁䅁䑉浔䅑䅕䅁䅁䭁⽁欵䭁乁䡍䅁䉁䅁䅁允䅁䅁䅕敇䱆㑳楬䕋䵁䅉䅅䅁䡁䅁䅁睁䵁䅁䅁权䡃杂䅁权歂杂䅁权䉁䅁䅁兂䅁䅁䅁䕉浶䅑䅕䅁䅁䝁坂欵䭁乁䡍䅁䉁䅁䅁允䅁䅁䅯免䅁䅁杷允䅁䅁䅙䅁䑁䅁䅷䅁䭁䥁䝣䅁䭁䝁䝧䅁䭁䙁䝅䅁䙁䅁䅁䅁杁低䅚权婂杂䅁允䅁䅁䅅䅁䙁䑁剐歷異橰䅆䍄䉁䅁䅁睂䅁䅁䅍䅄䅁䅁䅯睨䅙䅁䅯兡䅙䅁䅯允䅁䅁䅕䅁䅁䵁潁欵䙁䅁䅁䅁杁低䅚权兄睂䅁允䅁䅁䅅䅁䙁䅁晎態乇䑬䅆䍄䉁䅁䅁睂䅁䅁䅍䅄䅁䅁䅯睨䅙䅁䅯杖䅙䅁䅯允䅁䅁䅕䅁䅁䵁潁欵䙁䅁䅁䅁杁低䅚权呄睂䅁允䅁䅁䅅䅁䙁偁䵐㉹㍈先䅬䍄䉁䅁䅁睂䅁䅁䅍䅄䅁䅁䅯睨䅙䅁䅯兖䅙䅁䅯允䅁䅁䅕䅁䅁䕁瑂欵䙁䅁䅁䅁䅄佥䅚权啄睂䅁允䅁䅁䅅䅁䙁䝁敲奣佱䕏䅚䍄䉁䅁䅁睂䅁䅁䅍䅄䅁䅁䅯睨䅙䅁䅯杚䅙䅁䅯允䅁䅁䅕䅁䅁䭁⽁欵䙁䅁䅁䅁杁⭓䅚权啄睂䅁允䅁䅁䅅䅁䙁䙁牯栲湺橨䅂䍄䉁䅁䅁睂䅁䅁䅍䅄䅁䅁䅯睨䅙䅁䅯兙䅙䅁䅯允䅁䅁䅕䅁䅁䍁䱂欵䙁䅁䅁䅁杂畖䅚权卄睂䅁允䅁䅁䅅䅁䙁䵁稯㑰焳歬䅒䍄䉁䅁䅁睂䅁䅁䅍䅄䅁䅁䅯睨䅙䅁䅯杗䅙䅁䅯兕䅙䅁䅕䅁䅁䵁桂欵䙁䅁䅁䅁䅂敢䅚权剄睂䅁允䅁䅁䅅䅁䙁䝁䵍噰呂⽯⽯䍄䉁䅁䅁杂䅁䅁䅍䅄䅁䅁䅯睨䅙䅁䅯睙䅙䅁䅯允䅁䅁䅕䅁䅁䍁ぁ欵䭁䙁䝫䅁䉁䅁䅁允䅁䅁䅕㉙穌坣儳䕌䵁䅉䅅䅁䡁䅁䅁睁䵁䅁䅁权䡃杂䅁权桂杂䅁权䉁䅁䅁兂䅁䅁䅁䙙浢䅑䅕䅁䅁䵁桂欵䭁乁䡑䅁䉁䅁䅁允䅁䅁䅕桘卐潇獍歒䵁䅉䅅䅁䡁䅁䅁睁䵁䅁䅁权䡃杂䅁权桂杂䅁权䉁䅁䅁兂䅁䅁䅁䝑洳䅑䅕䅁䅁䵁㑂欵䭁乁䡁䅁䉁䅁䅁允䅁䅁䅕䉴睐浱敬け䵁䅉䅅䅁䡁䅁䅁睁䵁䅁䅁权䡃杂䅁权獂杂䅁权剂杂䅁兂䅁䅁䅁䍷浪䅑䅕䅁䅁䍁ぁ欵䭁乁䡉䅁䉁䅁䅁允䅁䅁䅕⽰佹牢稯啂䵁䅉䅅䅁䝁䅁䅁睁䵁䅁䅁权䡃杂䅁权橂杂䅁权䉁䅁䅁兂䅁䅁䅁䡙洳䅑䅯兗䅙䅁䅅䅁䉁䅁䅁兂乂圹⭔吰ㅣ䅑杷允䅁䅁䅣䅁䑁䅁䅷䅁䭁䥁䝣䅁䭁䙁䜴䅁䭁䙁䝅䅁䙁䅁䅁䅁杂畖䅚兂䅁䅁䅁䝷浈䅑䅯朰䅣䅁䅅䅁䉁䅁䅁兂乃煐䙧㕲余䅑杷允䅁䅁䅕䅁䑁䅁䅷䅁䭁䥁䝣䅁䭁䩁䡣䅁䙁䅁䅁䅁杁佣䅚权扃䅃䅁允䅁䅁䅅䅁啁䉁䈰䅁䅁䅁䅁䍄䉁䅁䅁睂䅁䅁䅍䅄䅁䅁䅯睨䅙䅁䅯杙䅙䅁䅯兕䅙䅁䅕䅁䅁䝁坂欵䙁䅁䅁䅁䅄教䅚权卄睂䅁允䅁䅁䅅䅁䙁䡁さ敩剃樯䅊䍄䉁䅁䅁睂䅁䅁䅍䅄䅁䅁䅯睨䅙䅁䅯睙䅙䅁䅯允䅁䅁䅕䅁䅁䵁潁欵䙁䅁䅁䅁杁低䅚权卄睂䅁允䅁䅁䅅䅁䙁䙁桔⽺浂呌䅂䍄䉁䅁䅁睂䅁䅁䅍䅄䅁䅁䅯睨䅙䅁䅯䅕䅙䅁䅯兕䅙䅁䅕䅁䅁䝁坂欵䙁䅁䅁䅁䅄教䅚权卄睂䅁允䅁䅁䅅䅁䙁䉁摑䴰偅桔䅎䍄䉁䅁䅁睂䅁䅁䅍䅄䅁䅁䅯睨䅙䅁䅯杗䅙䅁䅯兕䅙䅁䅕䅁䅁䕁瑂欵䙁䅁䅁䅁䅄佥䅚权剄睂䅁允䅁䅁䅅䅁䙁䥁偡㕨奌⭁⽉䍄䉁䅁䅁杂䅁䅁䅍䅄䅁䅁䅯睨䅙䅁䅯睘䅙䅁䅯兕䅙䅁䅕䅁䅁䍁䱂欵䭁䙁䝫䅁䉁䅁䅁允䅁䅁䅕啎商祫㘫䕌䵁䅉䅅䅁䡁䅁䅁睁䵁䅁䅁权䡃杂䅁权時杂䅁权剂杂䅁兂䅁䅁䅁䕉浶䅑䅕䅁䅁䝁坂欵䭁乁䡑䅁䉁䅁䅁允䅁䅁䅕睬搶偃䭅䕍䵁䅉䅅䅁䡁䅁䅁睁䵁䅁䅁权䡃杂䅁权煂杂䅁权㥁䅁䅁兂䅁䅁䅁䙙浢䅑䅕䅁䅁䵁桂欵䭁乁䡑䅁䉁䅁䅁允䅁䅁䅕䩓䝌桦䙔歈䵁䅉䅅䅁䡁䅁䅁睁䵁䅁䅁权䡃杂䅁权敂杂䅁权剂杂䅁兂䅁䅁䅁䝷浈䅑䅕䅁䅁䕁瑂欵䭁乁䡅䅁䉁䅁䅁允䅁䅁䅕奂⼰牔洷樱䴸䅉䅅䅁䡁䅁䅁睁䵁䅁䅁权䡃杂䅁权桂杂䅁权䉁䅁䅁兂䅁䅁䅁䡷浪䅑䅕䅁䅁䝁㥂欵䭁乁䡅䅁䉁䅁䅁允䅁䅁䅕䙩䱺昴桡䕅䵁䅉䅅䅁䡁䅁䅁睁䵁䅁䅁权䡃杂䅁权敂杂䅁权剂杂䅁兂䅁䅁䅁䑯洯䅑䅕䅁䅁䍁䱂欵䭁乁䡁䅁䉁䅁䅁允䅁䅁䅕洴㉌噱⭌啅䵁䅉䅅䅁䡁䅁䅁睁䵁䅁䅁权䡃杂䅁权歂杂䅁权䉁䅁䅁兂䅁䅁䅁䍷浪䅑䅕䅁䅁䍁ぁ欵䭁乁䡁䅁䉁䅁䅁允䅁䅁䅯免䅁䅁杷允䅁䅁䅣䅁䑁䅁䅷䅁䭁䥁䝣䅁䭁䝁䝙䅁䭁䅁䅅䅁䙁䅁䅁䅁䅄教䅚兂䅁䅁䅁䝑洳䅑䅯眰䅣䅁䅅䅁䉁䅁䅁兂杂獫啯㍣硷䅑杷允䅁䅁䅙䅁䑁䅁䅷䅁䭁䥁䝣䅁䭁䝁䝯䅁䭁䑁䄰䅁䙁䅁䅁䅁杂畖䅚权婂杂䅁允䅁䅁䅅䅁䙁䅁婳卺济桭䄱䍄䉁䅁䅁睂䅁䅁䅍䅄䅁䅁䅯睨䅙䅁䅯杖䅙䅁䅯允䅁䅁䅕䅁䅁䍁䱂欵䙁䅁䅁䅁杂畖䅚权剄睂䅁允䅁䅁䅅䅁䙁䙁杈捎㝄㡴⽯䍄䉁䅁䅁睂䅁䅁䅍䅄䅁䅁䅯睨䅙䅁䅯䅖䅙䅁䅯允䅁䅁䅕䅁䅁䵁桂欵䙁䅁䅁䅁䅂敢䅚权兄睂䅁允䅁䅁䅅䅁䙁偁㉲案䙌䌳䅆䍄䉁䅁䅁睂䅁䅁䅍䅄䅁䅁䅯睨䅙䅁䅯杗䅙䅁䅯兕䅙䅁䅕䅁䅁䍁ぁ欵䙁䅁䅁䅁权⭐䅚权兄睂䅁允䅁䅁䅅䅁䙁偁歧硧慕穖䅎䍄䉁䅁䅁睂䅁䅁䅍䅄䅁䅁䅯睨䅙䅁䅯䅡䅙䅁䅯兕䅙䅁䅕䅁䅁䍁ぁ欵䙁䅁䅁䅁权⭐䅚权啄睂䅁允䅁䅁䅅䅁䙁䅁敖䜯䭅䑍䅎䍄䉁䅁䅁睂䅁䅁䅍䅄䅁䅁䅯睨䅙䅁䅯䅕䅙䅁䅯兕䅙䅁䅕䅁䅁䍁ぁ欵䙁䅁䅁䅁权⭐䅚权卄睂䅁允䅁䅁䅅䅁䙁䙁㘯㍇䅱兣䄹䍄䉁䅁䅁睂䅁䅁䅍䅄䅁䅁䅯睨䅙䅁䅯䅗䅙䅁䅯允䅁䅁䅕䅁䅁䵁潁欵䙁䅁䅁䅁杁低䅚权兄睂䅁允䅁䅁䅅䅁䙁佁婥㜷歡穬䅒䍄䉁䅁䅁睂䅁䅁䅍䅄䅁䅁䅯睨䅙䅁䅯䅢䅙䅁䅯兕䅙䅁䅕䅁䅁䍁䱂欵䙁䅁䅁䅁杂畖䅚权剄睂䅁允䅁䅁䅅䅁䙁䭁晴眫焲㡃⽳䍄䉁䅁䅁睂䅁䅁䅍䅄䅁䅁䅯睨䅙䅁䅯兖䅙䅁䅯允䅁䅁䅕䅁䅁䵁潁欵䙁䅁䅁䅁杁低䅚权兄睂䅁允䅁䅁䅅䅁䙁偁牐䉁穩橖䅸䍄䉁䅁䅁睂䅁䅁䅍䅄䅁䅁䅯睨䅙䅁䅯兡䅙䅁䅯允䅁䅁䅕䅁䅁䝁坂欵䙁䅁䅁䅁䅄教䅚权兄睂䅁允䅁䅁䅅䅁䙁䅁獰䕷奄穮䅬䍄䉁䅁䅁睂䅁䅁䅍䅄䅁䅁䅯睨䅙䅁䅯䅚䅙䅁䅯允䅁䅁䅕䅁䅁䭁⽁欵䙁䅁䅁䅁杁⭓䅚权剄睂䅁允䅁䅁䅅䅁䭁䑁䅅䅁䵁䅉䅅䅁䡁䅁䅁睁䵁䅁䅁权䡃杂䅁权浂杂䅁权䉁䅁䅁兂䅁䅁䅁䑯洯䅑䅕䅁䅁䍁䱂欵䭁乁䡁䅁䉁䅁䅁允䅁䅁䅕串塥㡁㑬䕍䵁䅉䅅䅁䡁䅁䅁睁䵁䅁䅁权䡃杂䅁权獂杂䅁权剂杂䅁兂䅁䅁䅁䍷浪䅑䅕䅁䅁䍁ぁ欵䭁乁䡑䅁䉁䅁䅁允䅁䅁䅕䝂䙢婺䉄ぁ䵁䅉䅅䅁䡁䅁䅁睁䵁䅁䅁权䡃杂䅁权獂杂䅁权剂杂䅁兂䅁䅁䅁䑉浔䅑䅕䅁䅁䭁⽁欵䭁乁䡉䅁䉁䅁䅁允䅁䅁䅕㕃㙷祹琲啃䵁䅉䅅䅁䡁䅁䅁睁䵁䅁䅁权䡃杂䅁权敂杂䅁权剂杂䅁兂䅁䅁䅁䕉浶䅑䅕䅁䅁䝁坂欵䭁乁䡁䅁䉁䅁䅁允䅁䅁䅕癒眱㡊牸歄䵁䅉䅅䅁䡁䅁䅁睁䵁䅁䅁权䡃杂䅁权潂杂䅁权剂杂䅁兂䅁䅁䅁䙙浢䅑䅕䅁䅁䵁桂欵䭁乁䡁䅁䉁䅁䅁允䅁䅁䅕剖㔱汷䩒ぎ䵁䅉䅅䅁䝁䅁䅁睁䵁䅁䅁权䡃杂䅁权橂杂䅁权䉁䅁䅁兂䅁䅁䅁䡷浪䅑䅯兗䅙䅁䅅䅁䉁䅁䅁兂䥃砹奸潪㍷䅑杷允䅁䅁䅣䅁䑁䅁䅷䅁䭁䥁䝣䅁䭁䝁䝫䅁䭁䅁䅅䅁䙁䅁䅁䅁䅄佋䅚兂䅁䅁䅁䑉浔䅑䅯朰䅣䅁䅅䅁䉁䅁䅁兂敃䙘杍穳積䅑杷允䅁䅁䅣䅁䑁䅁䅷䅁䭁䥁䝣䅁䭁䙁䝷䅁䭁䅁䅅䅁䙁䅁䅁䅁䅄教䅚兂䅁䅁䅁䝑洳䅑䅯䄱䅣䅁䅅䅁䉁䅁䅁兂䑃乩こ㕩穕䅑杷允䅁䅁䅣䅁䑁䅁䅷䅁䭁䥁䝣䅁䭁䙁䝑䅁䭁䅁䅅䅁䙁䅁䅁䅁䅂敢䅚兂䅁䅁䅁䡷浪䅑䅯朰䅣䅁䅅䅁䉁䅁䅁兂坃䙃⽔䉉汯䅑杷允䅁䅁䅣䅁䑁䅁䅷䅁䭁䥁䝣䅁䭁䙁䝧䅁䭁䅁䅅䅁䙁䅁䅁䅁杂畖䅚兂䅁䅁䅁䝷浈䅑䅯䄰䅣䅁䅅䅁䉁䅁䅁兂塂娰樰婳㠴䅑杷允䅁䅁䅙䅁䑁䅁䅷䅁䭁䥁䝣䅁䭁䝁䝯䅁䭁䑁䄰䅁䙁䅁䅁䅁权⭐䅚权婂杂䅁允䅁䅁䅅䅁䙁䙁丸䠰慖䉰䄵䍄䉁䅁䅁睂䅁䅁䅍䅄䅁䅁䅯睨䅙䅁䅯睘䅙䅁䅯兕䅙䅁䅕䅁䅁䵁潁欵䙁䅁䅁䅁杁低䅚权卄睂䅁允䅁䅁䅅䅁䙁乁塎湫瑘匰䅴䍄䉁䅁䅁睂䅁䅁䅍䅄䅁䅁䅯睨䅙䅁䅯䅚䅙䅁䅯允䅁䅁䅕䅁䅁䝁坂欵䙁䅁䅁䅁䅄教䅚权卄睂䅁允䅁䅁䅅䅁䭁䑁䅅䅁䵁䅉䅅䅁䡁䅁䅁睁䵁䅁䅁权䡃杂䅁权桂杂䅁权䉁䅁䅁兂䅁䅁䅁䍷浪䅑䅕䅁䅁䍁ぁ欵䭁乁䡑䅁䉁䅁䅁允䅁䅁䅕倫戲祆⭣き䵁䅉䅅䅁䡁䅁䅁睁䵁䅁䅁权䡃杂䅁权煂杂䅁权㥁䅁䅁兂䅁䅁䅁䕉浶䅑䅕䅁䅁䝁坂欵䭁乁䡑䅁䉁䅁䅁允䅁䅁䅕乍破楡琷歈䵁䅉䅅䅁䡁䅁䅁睁䵁䅁䅁权䡃杂䅁权楂杂䅁权剂杂䅁兂䅁䅁䅁䑉浔䅑䅕䅁䅁䭁⽁欵䭁乁䡑䅁䉁䅁䅁允䅁䅁䅕慊決䱒塙か䵁䅉䅅䅁䡁䅁䅁睁䵁䅁䅁权䡃杂䅁权噂杂䅁权䉁䅁䅁兂䅁䅁䅁䑉浔䅑䅕䅁䅁䭁⽁欵䭁乁䡅䅁䉁䅁䅁允䅁䅁䅕扆㍑慒䱉啁䵁䅉䅅䅁䡁䅁䅁睁䵁䅁䅁权䡃杂䅁权坂杂䅁权䉁䅁䅁兂䅁䅁䅁䑉浔䅑䅕䅁䅁䭁⽁欵䭁乁䡅䅁䉁䅁䅁允䅁䅁䅕か癢䝂㠯橹䴸䅉䅅䅁䝁䅁䅁睁䵁䅁䅁权䡃杂䅁权㑃睂䅁权⭃睂䅁兂䅁䅁䅁䡙洳䅑䅯䅶䅣䅁䅅䅁䉁䅁䅁睂䅁䅁䅁䡉浄䅑杷允䅁䅁䅣䅁䑁䅁䅷䅁䭁䥁䝣䅁䭁䝁䝙䅁䭁䅁䅅䅁䙁䅁䅁䅁䅄教䅚兂䅁䅁䅁䝑洳䅑䅯朰䅣䅁䅅䅁䉁䅁䅁兂㍄硏䙑椫㉧䅑杷允䅁䅁䅙䅁䑁䅁䅷䅁䭁䥁䝣䅁䭁䙁䜸䅁䭁䙁䝅䅁䙁䅁䅁䅁䅂敢䅚权婂杂䅁允䅁䅁䅅䅁䙁䑁⽇䭩乢橁䅆䍄䉁䅁䅁睂䅁䅁䅍䅄䅁䅁䅯睨䅙䅁䅯䅕䅙䅁䅯兕䅙䅁䅕䅁䅁䵁桂欵䙁䅁䅁䅁䅂敢䅚权兄睂䅁允䅁䅁䅅䅁䙁䕁䭨䙈摹剙䅆䍄䉁䅁䅁杂䅁䅁䅍䅄䅁䅁䅯睨䅙䅁䅯䅖䅙䅁䅯允䅁䅁䅕䅁䅁䍁䱂欵䭁䙁䝫䅁䉁䅁䅁允䅁䅁䅕湏党敩杵䕉䵁䅉䅅䅁䡁䅁䅁睁䵁䅁䅁权䡃杂䅁权坂杂䅁权䉁䅁䅁兂䅁䅁䅁䝑洳䅑䅕䅁䅁䵁㑂欵䭁乁䡑䅁䉁䅁䅁允䅁䅁䅕䜶煦奤䅵䕆䵁䅉䅅䅁䡁䅁䅁睁䵁䅁䅁权䡃杂䅁权摂杂䅁权䉁䅁䅁兂䅁䅁䅁䝷浈䅑䅕䅁䅁䕁瑂欵䭁乁䡑䅁䉁䅁䅁允䅁䅁䅕㌫卙晅水歄䵁䅉䅅䅁䝁䅁䅁睁䵁䅁䅁权䡃杂䅁权煂杂䅁权㥁䅁䅁兂䅁䅁䅁䙙浢䅑䅯儰䅣䅁䅅䅁䉁䅁䅁兂祄呔桴兖牌睐杷允䅁䅁䅣䅁䑁䅁䅷䅁䭁䥁䝣䅁䭁䝁䝉䅁䭁䙁䝅䅁䙁䅁䅁䅁权⭐䅚兂䅁䅁䅁䕉浶䅑䅯儰䅣䅁䅅䅁䉁䅁䅁兂䉄堯佘敚決睐杷允䅁䅁䅣䅁䑁䅁䅷䅁䭁䥁䝣䅁䭁䝁䝙䅁䭁䅁䅅䅁䙁䅁䅁䅁䅂敢䅚兂䅁䅁䅁䡷浪䅑䅯眰䅣䅁䅅䅁䉁䅁䅁兂摁圵㉁塁穉䅑杷允䅁䅁䅣䅁䑁䅁䅷䅁䭁䥁䝣䅁䭁䙁䜰䅁䭁䅁䅅䅁䙁䅁䅁䅁杁低䅚兂䅁䅁䅁䑯洯䅑䅯䄱䅣䅁䅅䅁䉁䅁䅁兂䉃呺㑬瑊䝑䅑杷允䅁䅁䅣䅁䑁䅁䅷䅁䭁䥁䝣䅁䭁䝁䝅䅁䭁䅁䅅䅁䙁䅁䅁䅁权⭐䅚兂䅁䅁䅁䕉浶䅑䅯眰䅣䅁䅅䅁䉁䅁䅁兂䅁噣癥楉㐸䅑杷允䅁䅁䅣䅁䑁䅁䅷䅁䭁䥁䝣䅁䭁䝁䝙䅁䭁䅁䅅䅁䙁䅁䅁䅁杁低䅚兂䅁䅁䅁䑯洯䅑䅯䄰䅣䅁䅅䅁䉁䅁䅁兂佂奔㍉䰵瑫䅑杷允䅁䅁䅣䅁䑁䅁䅷䅁䭁䥁䝣䅁䭁䙁䝧䅁䭁䅁䅅䅁䙁䅁䅁䅁䅄教䅚兂䅁䅁䅁䝑洳䅑䅯眰䅣䅁䅅䅁䉁䅁䅁兂佄摸㈯佂㐰䅑杷允䅁䅁䅣䅁䑁䅁䅷䅁䭁䥁䝣䅁䭁䝁䝍䅁䭁䅁䅅䅁䙁䅁䅁䅁杁⭓䅚兂䅁䅁䅁䙙浢䅑䅯䄰䅣䅁䅅䅁䉁䅁䅁兂䝁祔桧瑺㍉䅑杷允䅁䅁䅣䅁䑁䅁䅷䅁䭁䥁䝣䅁䭁䙁䝧䅁䭁䅁䅅䅁䙁䅁䅁䅁杁低䅚兂䅁䅁䅁䑯洯䅑䅯朰䅣䅁䅅䅁䉁䅁䅁兂䑄⭚杶䑙㕣䅑杷允䅁䅁䅣䅁䑁䅁䅷䅁䭁䥁䝣䅁䭁䝁䝍䅁䭁䅁䅅䅁䙁䅁䅁䅁䅄佥䅚兂䅁䅁䅁䡙洳䅑䅯眰䅣䅁䅅䅁䉁䅁䅁兂桂灱ㅭ䍆ㅧ䅑杷允䅁䅁䅣䅁䑁䅁䅷䅁䭁䥁䝣䅁䭁䙁䝁䅁䭁䙁䝅䅁䙁䅁䅁䅁杁⭓䅚兂䅁䅁䅁䙙浢䅑䅯朰䅣䅁䅅䅁䉁䅁䅁兂楄慈瑬捵剁䅑杷允䅁䅁䅣䅁䑁䅁䅷䅁䭁䥁䝣䅁䭁䝁䝅䅁䭁䅁䅅䅁䙁䅁䅁䅁杂畖䅚兂䅁䅁䅁䝷浈䅑䅯眰䅣䅁䅅䅁䉁䅁䅁兂湁剷卶䑱䉂䅑杷允䅁䅁䅣䅁䑁䅁䅷䅁䭁䥁䝣䅁䭁䝁䝯䅁䭁䑁䄰䅁䙁䅁䅁䅁䅂敢䅚兂䅁䅁䅁䡷浪䅑䅯䄱䅣䅁䅅䅁䉁䅁䅁兂流扷㙯㙖楣䅑杷允䅁䅁䅕䅁䑁䅁䅷䅁䭁䥁䝣䅁䭁䩁䡣䅁䙁䅁䅁䅁杂⭑䅚权扃䅃䅁允䅁䅁䅅䅁䙁䵁䴳䵺䵺䝮䅬䍄䉁䅁䅁杂䅁䅁䅍䅄䅁䅁䅯睨䅙䅁䅯䅚䅙䅁䅯允䅁䅁䅕䅁䅁䭁⽁欵䭁䙁䝫䅁䉁䅁䅁允䅁䅁䅯党䅙䅁杷允䅁䅁䅣䅁䑁䅁䅷䅁䭁䥁䝣䅁䭁䝁䝙䅁䭁䅁䅅䅁䙁䅁䅁䅁杁⭓䅚兂䅁䅁䅁䙙浢䅑䅯朰䅣䅁䅅䅁䉁䅁䅁兂煁潣㑩协〰䅑杷允䅁䅁䅣䅁䑁䅁䅷䅁䭁䥁䝣䅁䭁䝁䝉䅁䭁䙁䝅䅁䙁䅁䅁䅁䅄教䅚兂䅁䅁䅁䝑洳䅑䅯儰䅣䅁䅅䅁䉁䅁䅁兂偄潱楱摍㍄睐杷允䅁䅁䅕䅁䑁䅁䅷䅁䭁䥁䝣䅁䭁䡁䝙䅁䭁䉁䄸䅁䙁䅁䅁䅁杂敦䅚允䅁䅁䅅䅁䭁䡁䝣䅁䵁䅉䅅䅁䡁䅁䅁睁䵁䅁䅁权䡃杂䅁权噂杂䅁权䉁䅁䅁兂䅁䅁䅁䕉浶䅑䅕䅁䅁䝁坂欵䭁乁䡉䅁䉁䅁䅁允䅁䅁䅕㍓塦娲偂歒䵁䅉䅅䅁䝁䅁䅁睁䵁䅁䅁权䡃杂䅁权浂杂䅁权䉁䅁䅁兂䅁䅁䅁䝷浈䅑䅯兗䅙䅁䅅䅁䉁䅁䅁兂㍄硏䙑椫㉧䅑杷允䅁䅁䅣䅁䑁䅁䅷䅁䭁䥁䝣䅁䭁䙁䜸䅁䭁䙁䝅䅁䙁䅁䅁䅁杂畖䅚兂䅁䅁䅁䝷浈䅑䅯朰䅣䅁䅅䅁䉁䅁䅁兂䕂兒䈳剕祑䅑杷允䅁䅁䅣䅁䑁䅁䅷䅁䭁䥁䝣䅁䭁䝁䝧䅁䭁䙁䝅䅁䙁䅁䅁䅁杁⭓䅚兂䅁䅁䅁䙙浢䅑䅯䄰䅣䅁䅅䅁䉁䅁䅁兂卄㡕䩨畐㈸䅑杷允䅁䅁䅣䅁䑁䅁䅷䅁䭁䥁䝣䅁䭁䙁䝑䅁䭁䅁䅅䅁䙁䅁䅁䅁杁低䅚兂䅁䅁䅁䑯洯䅑䅯儰䅣䅁䅅䅁䉁䅁䅁兂婄硇䍵硓效睐杷允䅁䅁䅣䅁䑁䅁䅷䅁䭁䥁䝣䅁䭁䙁䜴䅁䭁䙁䝅䅁䙁䅁䅁䅁䅄教䅚兂䅁䅁䅁䝑洳䅑䅯䄰䅣䅁䅅䅁䉁䅁䅁兂塁灬煗䉏䭕䅑杷允䅁䅁䅣䅁䑁䅁䅷䅁䭁䥁䝣䅁䭁䙁䝑䅁䭁䅁䅅䅁䙁䅁䅁䅁权⭐䅚兂䅁䅁䅁䕉浶䅑䅯䄰䅣䅁䅅䅁䉁䅁䅁兂坁䙓湔⭳杣䅑杷允䅁䅁䅣䅁䑁䅁䅷䅁䭁䥁䝣䅁䭁䙁䝯䅁䭁䙁䝅䅁䙁䅁䅁䅁杂畖䅚兂䅁䅁䅁䝷浈䅑䅯䄰䅣䅁䅅䅁䉁䅁䅁兂奃㔸儵⭎ㅯ䅑杷允䅁䅁䅣䅁䑁䅁䅷䅁䭁䥁䝣䅁䭁䙁䝷䅁䭁䅁䅅䅁䙁䅁䅁䅁杂畖䅚兂䅁䅁䅁䝷浈䅑䅯䄱䅣䅁䅅䅁䉁䅁䅁兂䅃⬸䕌㉖㕣䅑杷允䅁䅁䅙䅁䑁䅁䅷䅁䭁䥁䝣䅁䭁䙁䝙䅁䭁䅁䅅䅁䙁䅁䅁䅁杁⭓䅚权婂杂䅁允䅁䅁䅅䅁䙁䉁奖䙁䝍朷䄹䍄䉁䅁䅁睂䅁䅁䅍䅄䅁䅁䅯睨䅙䅁䅯䅕䅙䅁䅯兕䅙䅁䅕䅁䅁䵁㑂欵䙁䅁䅁䅁杂敦䅚权兄睂䅁允䅁䅁䅅䅁䙁䕁癚ふ汏栫䅊䍄䉁䅁䅁睂䅁䅁䅍䅄䅁䅁䅯睨䅙䅁䅯䅡䅙䅁䅯兕䅙䅁䅕䅁䅁䵁㑂欵䙁䅁䅁䅁杂敦䅚权啄睂䅁允䅁䅁䅅䅁䙁佁稴䰶䅔䑯䅨䍄䉁䅁䅁睂䅁䅁䅍䅄䅁䅁䅯睨䅙䅁䅯䅕䅙䅁䅯兕䅙䅁䅕䅁䅁䕁瑂欵䙁䅁䅁䅁䅄佥䅚权卄睂䅁允䅁䅁䅅䅁䙁䭁䭰摓㑇砹䅎䍄䉁䅁䅁睂䅁䅁䅍䅄䅁䅁䅯睨䅙䅁䅯兖䅙䅁䅯允䅁䅁䅕䅁䅁䵁桂欵䙁䅁䅁䅁䅂敢䅚权呄睂䅁允䅁䅁䅅䅁䙁䵁乣㕶畴啈䅊䍄䉁䅁䅁杂䅁䅁䅍䅄䅁䅁䅯睨䅙䅁䅯杗䅙䅁䅯兕䅙䅁䅕䅁䅁䵁桂欵䭁䙁䝫䅁䉁䅁䅁允䅁䅁䅕積敖䱮祒䕏䵁䅉䅅䅁䝁䅁䅁睁䵁䅁䅁权䡃杂䅁权橂杂䅁权䉁䅁䅁兂䅁䅁䅁䙙浢䅑䅯兗䅙䅁䅅䅁䉁䅁䅁兂䕂穯䥵扮㑫䅑杷允䅁䅁䅣䅁䑁䅁䅷䅁䭁䥁䝣䅁䭁䝁䝙䅁䭁䅁䅅䅁䙁䅁䅁䅁䅄佋䅚兂䅁䅁䅁䑉浔䅑䅯眰䅣䅁䅅䅁䉁䅁䅁兂獂啐㑍癚灅䅑杷允䅁䅁䅣䅁䑁䅁䅷䅁䭁䥁䝣䅁䭁䙁䝷䅁䭁䅁䅅䅁䙁䅁䅁䅁䅄佋䅚兂䅁䅁䅁䑉浔䅑䅯䄰䅣䅁䅅䅁䉁䅁䅁兂㡂䡘砲杒硍䅑杷允䅁䅁䅣䅁䑁䅁䅷䅁䭁䥁䝣䅁䭁䙁䝷䅁䭁䅁䅅䅁䙁䅁䅁䅁䅄教䅚兂䅁䅁䅁䝑洳䅑䅯眰䅣䅁䅅䅁䉁䅁䅁兂坁兩煬䈫祉䅑杷允䅁䅁䅣䅁䑁䅁䅷䅁䭁䥁䝣䅁䭁䝁䝙䅁䭁䅁䅅䅁䙁䅁䅁䅁䅄佋䅚兂䅁䅁䅁䑉浔䅑䅯䄱䅣䅁䅅䅁䉁䅁䅁兂橄㥍⽫㙔煳䅑杷允䅁䅁䅣䅁䑁䅁䅷䅁䭁䥁䝣䅁䭁䙁䝁䅁䭁䙁䝅䅁䙁䅁䅁䅁䅄教䅚兂䅁䅁䅁䝑洳䅑䅯眰䅣䅁䅅䅁䉁䅁䅁兂捃則是牸偧䅑杷允䅁䅁䅙䅁䑁䅁䅷䅁䭁䥁䝣䅁䭁䙁䝕䅁䭁䅁䅅䅁䙁䅁䅁䅁䅄教䅚权婂杂䅁允䅁䅁䅅䅁䙁䥁晖甶乤な䅤䍄䉁䅁䅁睂䅁䅁䅍䅄䅁䅁䅯睨䅙䅁䅯杙䅙䅁䅯兕䅙䅁䅕䅁䅁䍁ぁ欵䙁䅁䅁䅁权⭐䅚权卄睂䅁允䅁䅁䅅䅁䙁䥁捔啭刴䍥䄹䍄䉁䅁䅁睂䅁䅁䅍䅄䅁䅁䅯睨䅙䅁䅯䅕䅙䅁䅯兕䅙䅁䅕䅁䅁䍁䱂欵䙁䅁䅁䅁杂畖䅚权兄睂䅁允䅁䅁䅅䅁䙁偁卄㙂業䉲䅂䍄䉁䅁䅁睂䅁䅁䅍䅄䅁䅁䅯睨䅙䅁䅯兘䅙䅁䅯允䅁䅁䅕䅁䅁䭁⽁欵䙁䅁䅁䅁杁⭓䅚权兄睂䅁允䅁䅁䅅䅁䙁䝁⼶桎橄睔䅰䍄䉁䅁䅁杂䅁䅁䅍䅄䅁䅁䅯睨䅙䅁䅯杚䅙䅁䅯允䅁䅁䅕䅁䅁䍁ぁ欵䭁䙁䝫䅁䉁䅁䅁允䅁䅁䅕汩慱祗㡈歋䵁䅉䅅䅁䡁䅁䅁睁䵁䅁䅁权䡃杂䅁权啂杂䅁权䉁䅁䅁兂䅁䅁䅁䑯洯䅑䅕䅁䅁䍁䱂欵䭁乁䡉䅁䉁䅁䅁允䅁䅁䅕潍制䈷䭅歉䵁䅉䅅䅁䡁䅁䅁睁䵁䅁䅁权䡃杂䅁权歂杂䅁权䉁䅁䅁兂䅁䅁䅁䍷浪䅑䅕䅁䅁䍁ぁ欵䭁乁䡑䅁䉁䅁䅁允䅁䅁䅯免䅁䅁杷允䅁䅁䅣䅁䑁䅁䅷䅁䭁䥁䝣䅁䭁䙁䜸䅁䭁䙁䝅䅁䙁䅁䅁䅁䅄佋䅚兂䅁䅁䅁䑉浔䅑䅯䄰䅣䅁䅅䅁䉁䅁䅁兂婄塑祒礹灣䅑杷允䅁䅁䅣䅁䑁䅁䅷䅁䭁䥁䝣䅁䭁䝁䝅䅁䭁䅁䅅䅁䙁䅁䅁䅁杁低䅚兂䅁䅁䅁䑯洯䅑䅯眰䅣䅁䅅䅁䉁䅁䅁兂䝁扯偹㥯穅䅑杷允䅁䅁䅙䅁䑁䅁䅷䅁䭁䥁䝣䅁䭁䙁䝧䅁䭁䅁䅅䅁䙁䅁䅁䅁杂敦䅚权婂杂䅁允䅁䅁䅅䅁䙁䍁汋吲佷穕䅴䍄䉁䅁䅁睂䅁䅁䅍䅄䅁䅁䅯睨䅙䅁䅯䅖䅙䅁䅯允䅁䅁䅕䅁䅁䝁坂欵䙁䅁䅁䅁䅄教䅚权兄睂䅁允䅁䅁䅅䅁䙁䱁㍣橊䥍極䅆䍄䉁䅁䅁睂䅁䅁䅍䅄䅁䅁䅯睨䅙䅁䅯䅗䅙䅁䅯允䅁䅁䅕䅁䅁䝁坂欵䙁䅁䅁䅁䅄教䅚权卄睂䅁允䅁䅁䅅䅁䙁䱁㍏偬䙐樫䄹䍄䉁䅁䅁睂䅁䅁䅍䅄䅁䅁䅯睨䅙䅁䅯睙䅙䅁䅯允䅁䅁䅕䅁䅁䍁ぁ欵䙁䅁䅁䅁权⭐䅚权卄睂䅁允䅁䅁䅅䅁䙁䉁即ㄹ㙪䐯䅨䍄䉁䅁䅁睂䅁䅁䅍䅄䅁䅁䅯睨䅙䅁䅯兘䅙䅁䅯允䅁䅁䅕䅁䅁䍁䱂欵䙁䅁䅁䅁杂畖䅚权兄睂䅁允䅁䅁䅅䅁䙁䉁㑸䙨晚眱䅸䍄䉁䅁䅁杂䅁䅁䅍䅄䅁䅁䅯睨䅙䅁䅯䅵䅣䅁䅯兵䅣䅁䅕䅁䅁䝁㥂欵䭁䱁䡷䅁䉁䅁䅁允䅁䅁䅣䅁䅁䝁䑂欵䵁䅉䅅䅁䡁䅁䅁睁䵁䅁䅁权䡃杂䅁权坂杂䅁权䉁䅁䅁兂䅁䅁䅁䙙浢䅑䅕䅁䅁䵁桂欵䭁乁䡁䅁䉁䅁䅁允䅁䅁䅕支煏祮䭒歅䵁䅉䅅䅁䝁䅁䅁睁䵁䅁䅁权䡃杂䅁权奂杂䅁权䉁䅁䅁兂䅁䅁䅁䕉浶䅑䅯兗䅙䅁䅅䅁䉁䅁䅁兂敂猱䍑睘㔰䅑杷允䅁䅁䅣䅁䑁䅁䅷䅁䭁䥁䝣䅁䭁䝁䝑䅁䭁䅁䅅䅁䙁䅁䅁䅁䅄教䅚兂䅁䅁䅁䝑洳䅑䅯䄰䅣䅁䅅䅁䉁䅁䅁权硁䅁䅁䍄䉁䅁䅁杂䅁䅁䅍䅄䅁䅁䅯睨䅙䅁䅯杖䅙䅁䅯允䅁䅁䅕䅁䅁䵁桂欵䭁䙁䝫䅁䉁䅁䅁允䅁䅁䅕㕮敐㝎圶䕆䵁䅉䅅䅁䡁䅁䅁睁䵁䅁䅁权䡃杂䅁权時杂䅁权剂杂䅁兂䅁䅁䅁䑉浔䅑䅕䅁䅁䭁⽁欵䭁乁䡁䅁䉁䅁䅁允䅁䅁䅕噗祇塴牃か䵁䅉䅅䅁䡁䅁䅁睁䵁䅁䅁权䡃杂䅁权坂杂䅁权䉁䅁䅁兂䅁䅁䅁䙙浢䅑䅕䅁䅁䵁桂欵䭁乁䡍䅁䉁䅁䅁允䅁䅁䅕搲乄欯㕃い䵁䅉䅅䅁䡁䅁䅁睁䵁䅁䅁权䡃杂䅁权歂杂䅁权䉁䅁䅁兂䅁䅁䅁䍷浪䅑䅕䅁䅁䍁ぁ欵䭁乁䡉䅁䉁䅁䅁允䅁䅁䅯免䅁䅁杷允䅁䅁䅙䅁䑁䅁䅷䅁䭁䥁䝣䅁䭁䝁䝧䅁䭁䙁䝅䅁䙁䅁䅁䅁䅂敢䅚权婂杂䅁允䅁䅁䅅䅁䙁䅁ぬ䙖㉹橋䅨䍄䉁䅁䅁睂䅁䅁䅍䅄䅁䅁䅯睨䅙䅁䅯䅘䅙䅁䅯允䅁䅁䅕䅁䅁䍁䱂欵䙁䅁䅁䅁杂畖䅚权剄睂䅁允䅁䅁䅅䅁䙁䍁䅃㙂歒儹䅎䍄䉁䅁䅁睂䅁䅁䅍䅄䅁䅁䅯睨䅙䅁䅯䅖䅙䅁䅯允䅁䅁䅕䅁䅁䵁桂欵䙁䅁䅁䅁䅂敢䅚权卄睂䅁允䅁䅁䅅䅁䙁䩁浌㉪瑬楙䅒䍄䉁䅁䅁睂䅁䅁䅍䅄䅁䅁䅯睨䅙䅁䅯䅗䅙䅁䅯允䅁䅁䅕䅁䅁䵁桂欵䙁䅁䅁䅁䅂敢䅚权卄睂䅁允䅁䅁䅅䅁䙁䱁㍏偬䙐樫䄹䍄䉁䅁䅁睂䅁䅁䅍䅄䅁䅁䅯睨䅙䅁䅯䅘䅙䅁䅯允䅁䅁䅕䅁䅁䍁ぁ欵䙁䅁䅁䅁权⭐䅚权啄睂䅁允䅁䅁䅅䅁䙁䡁坹㠵摈告䅨䍄䉁䅁䅁睂䅁䅁䅍䅄䅁䅁䅯睨䅙䅁䅯兡䅙䅁䅯允䅁䅁䅕䅁䅁䵁桂欵䙁䅁䅁䅁䅂敢䅚权啄睂䅁允䅁䅁䅅䅁䙁䡁婯塸䱊穱䅨䍄䉁䅁䅁兂䅁䅁䅍䅄䅁䅁䅯睨䅙䅁䅯杤䅙䅁䅯䅥䅙䅁䅕䅁䅁䝁㥂欵䉁䅁䅁允䅁䅁䅯兲䅧䅁杷允䅁䅁䅣䅁䑁䅁䅷䅁䭁䥁䝣䅁䭁䙁䝙䅁䭁䅁䅅䅁䙁䅁䅁䅁䅄佥䅚兂䅁䅁䅁䡙洳䅑䅯䄰䅣䅁䅅䅁䉁䅁䅁兂䝁⭍䱁硆啉䅑杷允䅁䅁䅣䅁䑁䅁䅷䅁䭁䥁䝣䅁䭁䙁䝧䅁䭁䅁䅅䅁䙁䅁䅁䅁杁低䅚兂䅁䅁䅁䑯洯䅑䅯䄱䅣䅁䅅䅁䉁䅁䅁兂煁䩇啘坃㈴䅑杷允䅁䅁䅣䅁䑁䅁䅷䅁䭁䥁䝣䅁䭁䝁䝉䅁䭁䙁䝅䅁䙁䅁䅁䅁权⭐䅚兂䅁䅁䅁䕉浶䅑䅯眰䅣䅁䅅䅁䉁䅁䅁兂乄硉票䥯獫䅑杷允䅁䅁䅣䅁䑁䅁䅷䅁䭁䥁䝣䅁䭁䝁䝫䅁䭁䅁䅅䅁䙁䅁䅁䅁权⭐䅚兂䅁䅁䅁䕉浶䅑䅯眰䅣䅁䅅䅁䉁䅁䅁兂畃㡴唱䩩〸䅑杷允䅁䅁䅣䅁䑁䅁䅷䅁䭁䥁䝣䅁䭁䙁䝯䅁䭁䙁䝅䅁䙁䅁䅁䅁䅂敢䅚兂䅁䅁䅁䡷浪䅑䅯眰䅣䅁䅅䅁䉁䅁䅁兂㕃䑢佭呮㉙䅑杷允䅁䅁䅣䅁䑁䅁䅷䅁䭁䥁䝣䅁䭁䝁䝍䅁䭁䅁䅅䅁䙁䅁䅁䅁杁⭓䅚兂䅁䅁䅁䙙浢䅑䅯眰䅣䅁䅅䅁䉁䅁䅁兂呂牑煃歘稴䅑杷允䅁䅁䅣䅁䑁䅁䅷䅁䭁䥁䝣䅁䭁䝁䝫䅁䭁䅁䅅䅁䙁䅁䅁䅁䅄佥䅚兂䅁䅁䅁䡙洳䅑䅯䄱䅣䅁䅅䅁䉁䅁䅁兂汁瑁⽕䱩㙷䅑杷允䅁䅁䅣䅁䑁䅁䅷䅁䭁䥁䝣䅁䭁䝁䝷䅁䭁䙁䝅䅁䙁䅁䅁䅁杁⭓䅚兂䅁䅁䅁䙙浢䅑䅯䄰䅣䅁䅅䅁䉁䅁䅁兂扁㌶牪㤫䱍䅑杷允䅁䅁䅣䅁䑁䅁䅷䅁䭁䥁䝣䅁䭁䝁䝫䅁䭁䅁䅅䅁䙁䅁䅁䅁杂畖䅚兂䅁䅁䅁䝷浈䅑䅯眰䅣䅁䅅䅁䉁䅁䅁兂䡂杏橍㑌㉍䅑杷允䅁䅁䅙䅁䑁䅁䅷䅁䭁䥁䝣䅁䭁䙁䜸䅁䭁䙁䝅䅁䙁䅁䅁䅁䅄教䅚权婂杂䅁允䅁䅁䅅䅁䙁䕁䙒捄剆䑆䅊䍄䉁䅁䅁睂䅁䅁䅍䅄䅁䅁䅯睨䅙䅁䅯䅖䅙䅁䅯允䅁䅁䅕䅁䅁䍁䱂欵䙁䅁䅁䅁杂畖䅚权呄睂䅁允䅁䅁䅅䅁䙁偁穱祈楫硁䄹䍄䉁䅁䅁杂䅁䅁䅍䅄䅁䅁䅯睨䅙䅁䅯䅢䅙䅁䅯兕䅙䅁䅕䅁䅁䵁㑂欵䭁䙁䝫䅁䉁䅁䅁允䅁䅁䅕汶摈乮汪い䵁䅉䅅䅁䡁䅁䅁睁䵁䅁䅁权䡃杂䅁权奂杂䅁权䉁䅁䅁兂䅁䅁䅁䝷浈䅑䅕䅁䅁䕁瑂欵䭁乁䡅䅁䉁䅁䅁允䅁䅁䅕㝍䑃睩甸歁䵁䅉䅅䅁䡁䅁䅁睁䵁䅁䅁权䡃杂䅁权浂杂䅁权䉁䅁䅁兂䅁䅁䅁䡷浪䅑䅕䅁䅁䝁㥂欵䭁乁䡅䅁䉁䅁䅁允䅁䅁䅕䥳桓㉭湵稷䴸䅉䅅䅁䝁䅁䅁睁䵁䅁䅁权䡃杂䅁权煂杂䅁权㥁䅁䅁兂䅁䅁䅁䡙洳䅑䅯兗䅙䅁䅅䅁䉁䅁䅁权硁䅁䅁䍄䉁䅁䅁睂䅁䅁䅍䅄䅁䅁䅯睨䅙䅁䅯兘䅙䅁䅯允䅁䅁䅕䅁䅁䭁⽁欵䙁䅁䅁䅁杁⭓䅚权呄睂䅁允䅁䅁䅅䅁䙁䕁塷癙䡖䅏䅨䍄䉁䅁䅁睂䅁䅁䅍䅄䅁䅁䅯睨䅙䅁䅯䅘䅙䅁䅯允䅁䅁䅕䅁䅁䵁桂欵䙁䅁䅁䅁䅂敢䅚权兄睂䅁允䅁䅁䅅䅁䙁䩁砯㍆ㅄ橎䅖䍄䉁䅁䅁睂䅁䅁䅍䅄䅁䅁䅯睨䅙䅁䅯杙䅙䅁䅯兕䅙䅁䅕䅁䅁䕁瑂欵䙁䅁䅁䅁䅄佥䅚权卄睂䅁允䅁䅁䅅䅁䙁䅁稵㉖㤱呭䅊䍄䉁䅁䅁睂䅁䅁䅍䅄䅁䅁䅯睨䅙䅁䅯䅚䅙䅁䅯允䅁䅁䅕䅁䅁䭁⽁欵䙁䅁䅁䅁杁⭓䅚权兄睂䅁允䅁䅁䅅䅁䭁䑁䅅䅁䵁䅉䅅䅁䝁䅁䅁睁䵁䅁䅁权䡃杂䅁权兂杂䅁权剂杂䅁兂䅁䅁䅁䑯洯䅑䅯兗䅙䅁䅅䅁䉁䅁䅁兂卂坣こ卪倴䅑杷允䅁䅁䅣䅁䑁䅁䅷䅁䭁䥁䝣䅁䭁䙁䝕䅁䭁䅁䅅䅁䙁䅁䅁䅁䅄佋䅚兂䅁䅁䅁䑉浔䅑䅯䄱䅣䅁䅅䅁䉁䅁䅁兂湃摑㡅乧㝕䅑杷允䅁䅁䅣䅁䑁䅁䅷䅁䭁䥁䝣䅁䭁䙁䜸䅁䭁䙁䝅䅁䙁䅁䅁䅁䅄佋䅚兂䅁䅁䅁䑉浔䅑䅯䄱䅣䅁䅅䅁䉁䅁䅁兂奂は䑎㑋潕䅑杷允䅁䅁䅣䅁䑁䅁䅷䅁䭁䥁䝣䅁䭁䝁䝍䅁䭁䅁䅅䅁䙁䅁䅁䅁权⭐䅚兂䅁䅁䅁䕉浶䅑䅯䄱䅣䅁䅅䅁䉁䅁䅁兂ㅃ䭰捍䍺す䅑杷允䅁䅁䅙䅁䑁䅁䅷䅁䭁䥁䝣䅁䭁䝁䝍䅁䭁䅁䅅䅁䙁䅁䅁䅁䅄教䅚权婂杂䅁允䅁䅁䅅䅁䙁佁㑣睴㍮樷䅬䍄䉁䅁䅁睂䅁䅁䅍䅄䅁䅁䅯睨䅙䅁䅯䅡䅙䅁䅯兕䅙䅁䅕䅁䅁䭁⽁欵䙁䅁䅁䅁杁⭓䅚权兄睂䅁允䅁䅁䅅䅁䙁䉁䙥䅩偗䑫䅖䍄䉁䅁䅁睂䅁䅁䅍䅄䅁䅁䅯睨䅙䅁䅯杖䅙䅁䅯允䅁䅁䅕䅁䅁䍁ぁ欵䙁䅁䅁䅁权⭐䅚权兄睂䅁允䅁䅁䅅䅁䙁䥁㙤末㡪䅃䄱䍄䉁䅁䅁睂䅁䅁䅍䅄䅁䅁䅯睨䅙䅁䅯䅘䅙䅁䅯允䅁䅁䅕䅁䅁䵁㑂欵䙁䅁䅁䅁杂敦䅚权啄睂䅁允䅁䅁䅅䅁䙁佁睴䩤畘橕䅬䍄䉁䅁䅁睂䅁䅁䅍䅄䅁䅁䅯睨䅙䅁䅯睘䅙䅁䅯兕䅙䅁䅕䅁䅁䝁坂欵䙁䅁䅁䅁䅄教䅚权啄睂䅁允䅁䅁䅅䅁䙁䭁偁㍵㡳積䅂䍄䉁䅁䅁杂䅁䅁䅍䅄䅁䅁䅯睨䅙䅁䅯条䅙䅁䅯児䅁䅁䅕䅁䅁䍁ぁ欵䭁䙁䝫䅁䉁䅁䅁允䅁䅁䅕剡䅔乂潙䕇䵁䅉䅅䅁䡁䅁䅁睁䵁䅁䅁权䡃杂䅁权噂杂䅁权䉁䅁䅁兂䅁䅁䅁䙙浢䅑䅕䅁䅁䵁桂欵䭁乁䡑䅁䉁䅁䅁允䅁䅁䅕㝸乬䙵浥䕒䵁䅉䅅䅁䙁䅁䅁睁䵁䅁䅁权䡃杂䅁权塃睂䅁兂䅁䅁䅁䡙洳䅑䅯杖䅧䅁䅅䅁䉁䅁䅁兂䭁㘱睎剐礵䅑杷允䅁䅁䅣䅁䑁䅁䅷䅁䭁䥁䝣䅁䭁䙁䝑䅁䭁䅁䅅䅁䙁䅁䅁䅁权⭐䅚兂䅁䅁䅁䕉浶䅑䅯儰䅣䅁䅅䅁䉁䅁䅁兂睂瑰⽅䑤奌睐杷允䅁䅁䅣䅁䑁䅁䅷䅁䭁䥁䝣䅁䭁䙁䝧䅁䭁䅁䅅䅁䙁䅁䅁䅁杁⭓䅚兂䅁䅁䅁䙙浢䅑䅯䄱䅣䅁䅅䅁䉁䅁䅁兂い嘴䍭䍪㡧䅑杷允䅁䅁䅣䅁䑁䅁䅷䅁䭁䥁䝣䅁䭁䙁䝯䅁䭁䙁䝅䅁䙁䅁䅁䅁权⭐䅚兂䅁䅁䅁䕉浶䅑䅯儰䅣䅁䅅䅁䉁䅁䅁兂㝁䭉卮晚癐睐杷允䅁䅁䅣䅁䑁䅁䅷䅁䭁䥁䝣䅁䭁䙁䝯䅁䭁䙁䝅䅁䙁䅁䅁䅁杁⭓䅚兂䅁䅁䅁䙙浢䅑䅯朰䅣䅁䅅䅁䉁䅁䅁兂桄氯が䥈㍍䅑杷允䅁䅁䅙䅁䑁䅁䅷䅁䭁䥁䝣䅁䭁䝁䝯䅁䭁䑁䄰䅁䙁䅁䅁䅁杁⭓䅚权婂杂䅁允䅁䅁䅅䅁䙁䙁杩睳琫剒䄹䍄䉁䅁䅁睂䅁䅁䅍䅄䅁䅁䅯睨䅙䅁䅯兡䅙䅁䅯允䅁䅁䅕䅁䅁䵁桂欵䙁䅁䅁䅁䅂敢䅚权兄睂䅁允䅁䅁䅅䅁䙁佁扑㑪䝙穏䅬䍄䉁䅁䅁睂䅁䅁䅍䅄䅁䅁䅯睨䅙䅁䅯䅢䅙䅁䅯兕䅙䅁䅕䅁䅁䝁坂欵䙁䅁䅁䅁䅄教䅚权兄睂䅁允䅁䅁䅅䅁䙁䙁捋杨㙘睶䅸䍄䉁䅁䅁睂䅁䅁䅍䅄䅁䅁䅯睨䅙䅁䅯䅗䅙䅁䅯允䅁䅁䅕䅁䅁䵁桂欵䙁䅁䅁䅁䅂敢䅚权兄睂䅁允䅁䅁䅅䅁䙁䅁扡⬲㡰呶䅴䍄䉁䅁䅁兂䅁䅁䅍䅄䅁䅁䅯睨䅙䅁䅯䅳䅧䅁䅯杲䅧䅁䅕䅁䅁䝁㥂欵䉁䅁䅁允䅁䅁䅯睳䅧䅁杷允䅁䅁䅣䅁䑁䅁䅷䅁䭁䥁䝣䅁䭁䙁䝧䅁䭁䅁䅅䅁䙁䅁䅁䅁䅄佋䅚兂䅁䅁䅁䑉浔䅑䅯朰䅣䅁䅅䅁䉁䅁䅁兂㥄兌㑈㉰㉑䅑杷允䅁䅁䅣䅁䑁䅁䅷䅁䭁䥁䝣䅁䭁䝁䝫䅁䭁䅁䅅䅁䙁䅁䅁䅁䅄佥䅚兂䅁䅁䅁䡙洳䅑䅯眰䅣䅁䅅䅁䉁䅁䅁兂䝃乏䙢卢㙧䅑杷允䅁䅁䅙䅁䑁䅁䅷䅁䭁䥁䝣䅁䭁䙁䝁䅁䭁䙁䝅䅁䙁䅁䅁䅁䅄佥䅚权婂杂䅁允䅁䅁䅅䅁䙁䍁㌰匹䔷样䅊䍄䉁䅁䅁杂䅁䅁䅍䅄䅁䅁䅯睨䅙䅁䅯兘䅙䅁䅯允䅁䅁䅕䅁䅁䵁㑂欵䭁䙁䝫䅁䉁䅁䅁允䅁䅁䅕汩婤砲癔䕅䵁䅉䅅䅁䡁䅁䅁睁䵁䅁䅁权䡃杂䅁权楂杂䅁权剂杂䅁兂䅁䅁䅁䕉浶䅑䅕䅁䅁䝁坂欵䭁乁䡍䅁䉁䅁䅁允䅁䅁䅕瀶湊湇商啌䵁䅉䅅䅁䝁䅁䅁睁䵁䅁䅁权䡃杂䅁权慂杂䅁权剂杂䅁兂䅁䅁䅁䕉浶䅑䅯兗䅙䅁䅅䅁䉁䅁䅁兂千儸㌴䙏け䅑杷允䅁䅁䅣䅁䑁䅁䅷䅁䭁䥁䝣䅁䭁䝁䝙䅁䭁䅁䅅䅁䙁䅁䅁䅁杁⭓䅚兂䅁䅁䅁䙙浢䅑䅯儰䅣䅁䅅䅁䉁䅁䅁兂扁䱁婱䝺ㅈ睐杷允䅁䅁䅣䅁䑁䅁䅷䅁䭁䥁䝣䅁䭁䙁䝕䅁䭁䅁䅅䅁䙁䅁䅁䅁杂畖䅚兂䅁䅁䅁䝷浈䅑䅯䄰䅣䅁䅅䅁䉁䅁䅁兂ぁ硓䍒扷䕴䅑杷允䅁䅁䅕䅁䑁䅁䅷䅁䭁䥁䝣䅁䭁䱁䥁䅁䭁䑁䄰䅁䙁䅁䅁䅁杂敦䅚允䅁䅁䅅䅁䭁䱁䥉䅁䵁䅉䅅䅁䝁䅁䅁睁䵁䅁䅁权䡃杂䅁权潂杂䅁权剂杂䅁兂䅁䅁䅁䙙浢䅑䅯兗䅙䅁䅅䅁䉁䅁䅁兂䑂橦㥱橫㍍䅑杷允䅁䅁䅣䅁䑁䅁䅷䅁䭁䥁䝣䅁䭁䝁䝫䅁䭁䅁䅅䅁䙁䅁䅁䅁杁低䅚兂䅁䅁䅁䑯洯䅑䅯眰䅣䅁䅅䅁䉁䅁䅁兂睄橨煑䵣硙䅑杷允䅁䅁䅙䅁䑁䅁䅷䅁䭁䥁䝣䅁䭁䙁䝙䅁䭁䅁䅅䅁䙁䅁䅁䅁杂畖䅚权婂杂䅁允䅁䅁䅅䅁䙁佁求潨礲桦䅆䍄䉁䅁䅁睂䅁䅁䅍䅄䅁䅁䅯睨䅙䅁䅯兙䅙䅁䅯允䅁䅁䅕䅁䅁䵁潁欵䙁䅁䅁䅁杁低䅚权呄睂䅁允䅁䅁䅅䅁䙁乁浕畔㌵䑮䅊䍄䉁䅁䅁睂䅁䅁䅍䅄䅁䅁䅯睨䅙䅁䅯兙䅙䅁䅯允䅁䅁䅕䅁䅁䍁䱂欵䙁䅁䅁䅁杂畖䅚权剄睂䅁允䅁䅁䅅䅁䙁䍁呸払ㅒ儰䅰䍄䉁䅁䅁睂䅁䅁䅍䅄䅁䅁䅯睨䅙䅁䅯䅚䅙䅁䅯允䅁䅁䅕䅁䅁䍁ぁ欵䙁䅁䅁䅁权⭐䅚权剄睂䅁允䅁䅁䅅䅁䭁䑁䅅䅁䵁䅉䅅䅁䝁䅁䅁睁䵁䅁䅁权䡃杂䅁权桂杂䅁权䉁䅁䅁兂䅁䅁䅁䝑洳䅑䅯兗䅙䅁䅅䅁䉁䅁䅁兂乁奇匹摃䝖䅑杷允䅁䅁䅣䅁䑁䅁䅷䅁䭁䥁䝣䅁䭁䙁䝷䅁䭁䅁䅅䅁䙁䅁䅁䅁杁⭓䅚兂䅁䅁䅁䙙浢䅑䅯䄰䅣䅁䅅䅁䉁䅁䅁兂湂灬灙婴㔴䅑杷允䅁䅁䅣䅁䑁䅁䅷䅁䭁䥁䝣䅁䭁䝁䝯䅁䭁䑁䄰䅁䙁䅁䅁䅁䅄佋䅚兂䅁䅁䅁䑉浔䅑䅯眰䅣䅁䅅䅁䉁䅁䅁兂剂㥯䭔灣坳䅑杷允䅁䅁䅣䅁䑁䅁䅷䅁䭁䥁䝣䅁䭁䙁䜴䅁䭁䙁䝅䅁䙁䅁䅁䅁权⭐䅚兂䅁䅁䅁䕉浶䅑䅯眰䅣䅁䅅䅁䉁䅁䅁兂扃祏桔攳偣䅑杷允䅁䅁䅣䅁䑁䅁䅷䅁䭁䥁䝣䅁䭁䙁䝕䅁䭁䅁䅅䅁䙁䅁䅁䅁杂畖䅚兂䅁䅁䅁䝷浈䅑䅯儰䅣䅁䅅䅁䉁䅁䅁兂ㅂ䙒⭲湳䝙䅑杷允䅁䅁䅣䅁䑁䅁䅷䅁䭁䥁䝣䅁䭁䙁䝙䅁䭁䅁䅅䅁䙁䅁䅁䅁䅄佋䅚兂䅁䅁䅁䑉浔䅑䅯朰䅣䅁䅅䅁䉁䅁䅁兂敂晓捊㘳䵣䅑杷允䅁䅁䅣䅁䑁䅁䅷䅁䭁䥁䝣䅁䭁䙁䝙䅁䭁䅁䅅䅁䙁䅁䅁䅁杁⭓䅚兂䅁䅁䅁䙙浢䅑䅯朰䅣䅁䅅䅁䉁䅁䅁兂䱁呙块䝳卙䅑杷允䅁䅁䅣䅁䑁䅁䅷䅁䭁䥁䝣䅁䭁䝁䝑䅁䭁䅁䅅䅁䙁䅁䅁䅁杂畖䅚兂䅁䅁䅁䝷浈䅑䅯儰䅣䅁䅅䅁䉁䅁䅁权硁䅁䅁䍄䉁䅁䅁杂䅁䅁䅍䅄䅁䅁䅯睨䅙䅁䅯䅢䅙䅁䅯兕䅙䅁䅕䅁䅁䵁桂欵䭁䙁䝫䅁䉁䅁䅁允䅁䅁䅕㉢啫潏慨䕅䵁䅉䅅䅁䡁䅁䅁睁䵁䅁䅁权䡃杂䅁权噂杂䅁权䉁䅁䅁兂䅁䅁䅁䕉浶䅑䅕䅁䅁䝁坂欵䭁乁䡑䅁䉁䅁䅁允䅁䅁䅕䍶㑌〳佱䕒䵁䅉䅅䅁䡁䅁䅁睁䵁䅁䅁权䡃杂䅁权奂杂䅁权䉁䅁䅁兂䅁䅁䅁䝑洳䅑䅕䅁䅁䵁㑂欵䭁乁䡑䅁䉁䅁䅁允䅁䅁䅕䭱兲䍑穷啐䵁䅉䅅䅁䡁䅁䅁睁䵁䅁䅁权䡃杂䅁权敂杂䅁权剂杂䅁兂䅁䅁䅁䙙浢䅑䅕䅁䅁䵁桂欵䭁乁䡅䅁䉁䅁䅁允䅁䅁䅕畖灵祗䔱吰䴸䅉䅅䅁䡁䅁䅁睁䵁䅁䅁权䡃杂䅁权啂杂䅁权䉁䅁䅁兂䅁䅁䅁䑉浔䅑䅕䅁䅁䭁⽁欵䭁乁䡁䅁䉁䅁䅁允䅁䅁䅕摎潑䩊䝬歈䵁䅉䅅䅁䡁䅁䅁睁䵁䅁䅁权䡃杂䅁权橂
A6: 杂䅁权䉁䅁䅁兂䅁䅁䅁䍷浪䅑䅕䅁䅁䍁ぁ欵䭁乁䡍䅁䉁䅁䅁允䅁䅁䅕㕳䑬杕汴か䵁䅉䅅䅁䝁䅁䅁睁䵁䅁䅁权䡃杂䅁权啂杂䅁权䉁䅁䅁兂䅁䅁䅁䝷浈䅑䅯兗䅙䅁䅅䅁䉁䅁䅁兂千漵瀹坢歉䅑杷允䅁䅁䅣䅁䑁䅁䅷䅁䭁䥁䝣䅁䭁䝁䝍䅁䭁䅁䅅䅁䙁䅁䅁䅁杂畖䅚兂䅁䅁䅁䝷浈䅑䅯眰䅣䅁䅅䅁䉁䅁䅁兂佃䉂獰椶ぷ䅑杷允䅁䅁䅙䅁䑁䅁䅷䅁䭁䥁䝣䅁䭁䙁䜰䅁䭁䅁䅅䅁䙁䅁䅁䅁䅂敢䅚权婂杂䅁允䅁䅁䅅䅁䙁乁兄㡐䙈桡䅂䍄䉁䅁䅁睂䅁䅁䅍䅄䅁䅁䅯睨䅙䅁䅯杗䅙䅁䅯兕䅙䅁䅕䅁䅁䭁⽁欵䙁䅁䅁䅁杁⭓䅚权啄睂䅁允䅁䅁䅅䅁䙁䵁䡶橓夫呺䅒䍄䉁䅁䅁睂䅁䅁䅍䅄䅁䅁䅯睨䅙䅁䅯䅗䅙䅁䅯允䅁䅁䅕䅁䅁䝁坂欵䙁䅁䅁䅁䅄教䅚权剄睂䅁允䅁䅁䅅䅁䙁䕁破卍偐偙⽳䍄䉁䅁䅁睂䅁䅁䅍䅄䅁䅁䅯睨䅙䅁䅯兘䅙䅁䅯允䅁䅁䅕䅁䅁䍁ぁ欵䙁䅁䅁䅁权⭐䅚权呄睂䅁允䅁䅁䅅䅁䙁䝁䌫㕢⭯睵䅒䍄䉁䅁䅁睂䅁䅁䅍䅄䅁䅁䅯睨䅙䅁䅯䅕䅙䅁䅯兕䅙䅁䅕䅁䅁䍁ぁ欵䙁䅁䅁䅁权⭐䅚权呄睂䅁允䅁䅁䅅䅁䙁䥁啸漯㔴六䅬䍄䉁䅁䅁睂䅁䅁䅍䅄䅁䅁䅯睨䅙䅁䅯杙䅙䅁䅯兕䅙䅁䅕䅁䅁䝁坂欵䙁䅁䅁䅁䅄教䅚权兄睂䅁允䅁䅁䅅䅁䙁䩁渷䅁䕭䑲䅂䍄䉁䅁䅁睂䅁䅁䅍䅄䅁䅁䅯睨䅙䅁䅯䅚䅙䅁䅯允䅁䅁䅕䅁䅁䍁ぁ欵䙁䅁䅁䅁权⭐䅚权兄睂䅁允䅁䅁䅅䅁䭁䑁䅅䅁䵁䅉䅅䅁䡁䅁䅁睁䵁䅁䅁权䡃杂䅁权兂杂䅁权剂杂䅁兂䅁䅁䅁䍷浪䅑䅕䅁䅁䍁ぁ欵䭁乁䡍䅁䉁䅁䅁允䅁䅁䅕桂䙓㤫唶䕃䵁䅉䅅䅁䡁䅁䅁睁䵁䅁䅁权䡃杂䅁权時杂䅁权剂杂䅁兂䅁䅁䅁䑯洯䅑䅕䅁䅁䍁䱂欵䭁乁䡉䅁䉁䅁䅁允䅁䅁䅕㕴ㄲ㍗奣䕍䵁䅉䅅䅁䝁䅁䅁睁䵁䅁䅁权䡃杂䅁权橂杂䅁权䉁䅁䅁兂䅁䅁䅁䕉浶䅑䅯兗䅙䅁䅅䅁䉁䅁䅁兂⽁朵䍍奮穕䅑杷允䅁䅁䅣䅁䑁䅁䅷䅁䭁䥁䝣䅁䭁䙁䜰䅁䭁䅁䅅䅁䙁䅁䅁䅁杂畖䅚兂䅁䅁䅁䝷浈䅑䅯眰䅣䅁䅅䅁䉁䅁䅁兂䕁㉸捘䌱䭁䅑杷允䅁䅁䅙䅁䑁䅁䅷䅁䭁䥁䝣䅁䭁䝁䝉䅁䭁䙁䝅䅁䙁䅁䅁䅁杁低䅚权婂杂䅁允䅁䅁䅅䅁䙁䉁桮㝓䩏楙䅨䍄䉁䅁䅁杂䅁䅁䅍䅄䅁䅁䅯睨䅙䅁䅯䅡䅙䅁䅯兕䅙䅁䅕䅁䅁䭁⽁欵䭁䙁䝫䅁䉁䅁䅁允䅁䅁䅕噶獏⭇扮啎䵁䅉䅅䅁䡁䅁䅁睁䵁䅁䅁权䡃杂䅁权桂杂䅁权䉁䅁䅁兂䅁䅁䅁䝷浈䅑䅕䅁䅁䕁瑂欵䭁乁䡉䅁䉁䅁䅁允䅁䅁䅕婎扣䡄䵖啓䵁䅉䅅䅁䡁䅁䅁睁䵁䅁䅁权䡃杂䅁权楂杂䅁权剂杂䅁兂䅁䅁䅁䙙浢䅑䅕䅁䅁䵁桂欵䭁乁䡍䅁䉁䅁䅁允䅁䅁䅕橘⬲㝡䱡啌䵁䅉䅅䅁䡁䅁䅁睁䵁䅁䅁权䡃杂䅁权桂杂䅁权䉁䅁䅁兂䅁䅁䅁䑯洯䅑䅕䅁䅁䍁䱂欵䭁乁䡑䅁䉁䅁䅁允䅁䅁䅕潸慯䵔潍ぐ䵁䅉䅅䅁䡁䅁䅁睁䵁䅁䅁权䡃杂䅁权浂杂䅁权䉁䅁䅁兂䅁䅁䅁䙙浢䅑䅕䅁䅁䵁桂欵䭁乁䡑䅁䉁䅁䅁允䅁䅁䅕樰⭢䝒塘き䵁䅉䅅䅁䡁䅁䅁睁䵁䅁䅁权䡃杂䅁权慂杂䅁权剂杂䅁兂䅁䅁䅁䍷浪䅑䅕䅁䅁䍁ぁ欵䭁乁䡉䅁䉁䅁䅁允䅁䅁䅕渶敬扆䉧き䵁䅉䅅䅁䡁䅁䅁睁䵁䅁䅁权䡃杂䅁权煂杂䅁权㥁䅁䅁兂䅁䅁䅁䍷浪䅑䅕䅁䅁䍁ぁ欵䭁乁䡑䅁䉁䅁䅁允䅁䅁䅕䭧噖汮䝄う䵁䅉䅅䅁䡁䅁䅁睁䵁䅁䅁权䡃杂䅁权摂杂䅁权䉁䅁䅁兂䅁䅁䅁䙙浢䅑䅕䅁䅁䵁桂欵䭁乁䡑䅁䉁䅁䅁允䅁䅁䅕敢㝦晱升歄䵁䅉䅅䅁䡁䅁䅁睁䵁䅁䅁权䡃杂䅁权獂杂䅁权剂杂䅁兂䅁䅁䅁䝑洳䅑䅕䅁䅁䵁㑂欵䭁乁䡉䅁䉁䅁䅁允䅁䅁䅕慗歂癐㙌䕅䵁䅉䅅䅁䡁䅁䅁睁䵁䅁䅁权䡃杂䅁权時杂䅁权剂杂䅁兂䅁䅁䅁䕉浶䅑䅕䅁䅁䝁坂欵䭁乁䡉䅁䉁䅁䅁允䅁䅁䅕㕦䍷睃栳䕍䵁䅉䅅䅁䡁䅁䅁睁䵁䅁䅁权䡃杂䅁权啂杂䅁权䉁䅁䅁兂䅁䅁䅁䝑洳䅑䅕䅁䅁䵁㑂欵䭁乁䡍䅁䉁䅁䅁允䅁䅁䅕䅵㉡牓睃歉䵁䅉䅅䅁䡁䅁䅁睁䵁䅁䅁权䡃杂䅁权慂杂䅁权剂杂䅁兂䅁䅁䅁䍷浪䅑䅕䅁䅁䍁ぁ欵䭁乁䡑䅁䉁䅁䅁允䅁䅁䅕䙈猵电䱔䕍䵁䅉䅅䅁䡁䅁䅁睁䵁䅁䅁权䡃杂䅁权浂杂䅁权䉁䅁䅁兂䅁䅁䅁䑯洯䅑䅕䅁䅁䍁䱂欵䭁乁䡉䅁䉁䅁䅁允䅁䅁䅕扁眱㠵杊啍䵁䅉䅅䅁䡁䅁䅁睁䵁䅁䅁权䡃杂䅁权慂杂䅁权剂杂䅁兂䅁䅁䅁䑉浔䅑䅕䅁䅁䭁⽁欵䭁乁䡅䅁䉁䅁䅁允䅁䅁䅕䅎湰煒㑤稸䴸䅉䅅䅁䝁䅁䅁睁䵁䅁䅁权䡃杂䅁权獂杂䅁权剂杂䅁兂䅁䅁䅁䑉浔䅑䅯兗䅙䅁䅅䅁䉁䅁䅁兂䝁䠵⽉䉓䕁䅑杷允䅁䅁䅣䅁䑁䅁䅷䅁䭁䥁䝣䅁䭁䝁䝙䅁䭁䅁䅅䅁䙁䅁䅁䅁杂畖䅚兂䅁䅁䅁䝷浈䅑䅯眰䅣䅁䅅䅁䉁䅁䅁兂偄杔䡚她硣䅑杷允䅁䅁䅣䅁䑁䅁䅷䅁䭁䥁䝣䅁䭁䙁䝙䅁䭁䅁䅅䅁䙁䅁䅁䅁权⭐䅚兂䅁䅁䅁䕉浶䅑䅯儰䅣䅁䅅䅁䉁䅁䅁兂橂祡䬵㕚䉶睐杷允䅁䅁䅣䅁䑁䅁䅷䅁䭁䥁䝣䅁䭁䙁䝙䅁䭁䅁䅅䅁䙁䅁䅁䅁䅂敢䅚兂䅁䅁䅁䡷浪䅑䅯䄰䅣䅁䅅䅁䉁䅁䅁兂硃㝢祱汨唴䅑杷允䅁䅁䅣䅁䑁䅁䅷䅁䭁䥁䝣䅁䭁䝁䝉䅁䭁䙁䝅䅁䙁䅁䅁䅁䅄佥䅚兂䅁䅁䅁䡙洳䅑䅯眰䅣䅁䅅䅁䉁䅁䅁兂䭂奵硁啹眰䅑杷允䅁䅁䅣䅁䑁䅁䅷䅁䭁䥁䝣䅁䭁䝁䝍䅁䭁䅁䅅䅁䙁䅁䅁䅁杂畖䅚兂䅁䅁䅁䝷浈䅑䅯䄰䅣䅁䅅䅁䉁䅁䅁兂䅁㉌䑥噣㍣䅑杷允䅁䅁䅣䅁䑁䅁䅷䅁䭁䥁䝣䅁䭁䙁䝑䅁䭁䅁䅅䅁䙁䅁䅁䅁杁⭓䅚兂䅁䅁䅁䙙浢䅑䅯䄱䅣䅁䅅䅁䉁䅁䅁兂乃䙦砷倱杳䅑杷允䅁䅁䅣䅁䑁䅁䅷䅁䭁䥁䝣䅁䭁䙁䝕䅁䭁䅁䅅䅁䙁䅁䅁䅁权⭐䅚兂䅁䅁䅁䕉浶䅑䅯儰䅣䅁䅅䅁䉁䅁䅁兂䉁獕䑍楥㑪睐杷允䅁䅁䅣䅁䑁䅁䅷䅁䭁䥁䝣䅁䭁䙁䝷䅁䭁䅁䅅䅁䙁䅁䅁䅁杁低䅚兂䅁䅁䅁䑯洯䅑䅯朰䅣䅁䅅䅁䉁䅁䅁兂䡄瑅䝢䌲㝕䅑杷允䅁䅁䅣䅁䑁䅁䅷䅁䭁䥁䝣䅁䭁䝁䝍䅁䭁䅁䅅䅁䙁䅁䅁䅁䅄佥䅚兂䅁䅁䅁䡙洳䅑䅯䄰䅣䅁䅅䅁䉁䅁䅁兂畁攰婚啸㍉䅑杷允䅁䅁䅣䅁䑁䅁䅷䅁䭁䥁䝣䅁䭁䙁䜴䅁䭁䙁䝅䅁䙁䅁䅁䅁杁低䅚兂䅁䅁䅁䑯洯䅑䅯䄱䅣䅁䅅䅁䉁䅁䅁兂癄ㅓ獬焱倴䅑杷允䅁䅁䅣䅁䑁䅁䅷䅁䭁䥁䝣䅁䭁䝁䝙䅁䭁䅁䅅䅁䙁䅁䅁䅁䅄佋䅚兂䅁䅁䅁䑉浔䅑䅯䄰䅣䅁䅅䅁䉁䅁䅁兂坃㙏䅷穷牳䅑杷允䅁䅁䅣䅁䑁䅁䅷䅁䭁䥁䝣䅁䭁䙁䝧䅁䭁䅁䅅䅁䙁䅁䅁䅁权⭐䅚兂䅁䅁䅁䕉浶䅑䅯䄱䅣䅁䅅䅁䉁䅁䅁兂䕁慖塎㍁㕑䅑杷允䅁䅁䅣䅁䑁䅁䅷䅁䭁䥁䝣䅁䭁䙁䝯䅁䭁䙁䝅䅁䙁䅁䅁䅁杁⭓䅚兂䅁䅁䅁䙙浢䅑䅯䄰䅣䅁䅅䅁䉁䅁䅁兂婁噋啧公㈰䅑杷允䅁䅁䅙䅁䑁䅁䅷䅁䭁䥁䝣䅁䭁䙁䝑䅁䭁䅁䅅䅁䙁䅁䅁䅁杂敦䅚权婂杂䅁允䅁䅁䅅䅁䙁䙁儴婫㉰卯䅂䍄䉁䅁䅁杂䅁䅁䅍䅄䅁䅁䅯睨䅙䅁䅯䅢䅙䅁䅯兕䅙䅁䅕䅁䅁䝁坂欵䭁䙁䝫䅁䉁䅁䅁允䅁䅁䅕啚煯䙗汖䕄䵁䅉䅅䅁䡁䅁䅁睁䵁䅁䅁权䡃杂䅁权灂杂䅁权䉁䅁䅁兂䅁䅁䅁䑯洯䅑䅕䅁䅁䍁䱂欵䭁乁䡅䅁䉁䅁䅁允䅁䅁䅕元甲䱋湍樷䴸䅉䅅䅁䡁䅁䅁睁䵁䅁䅁权䡃杂䅁权兂杂䅁权剂杂䅁兂䅁䅁䅁䝷浈䅑䅕䅁䅁䕁瑂欵䭁乁䡑䅁䉁䅁䅁允䅁䅁䅕䉤栫䭷噅啅䵁䅉䅅䅁䡁䅁䅁睁䵁䅁䅁权䡃杂䅁权捂杂䅁权䉁䅁䅁兂䅁䅁䅁䍷浪䅑䅕䅁䅁䍁ぁ欵䭁乁䡉䅁䉁䅁䅁允䅁䅁䅕材䉧别⭋歍䵁䅉䅅䅁䝁䅁䅁睁䵁䅁䅁权䡃杂䅁权捂杂䅁权䉁䅁䅁兂䅁䅁䅁䝷浈䅑䅯兗䅙䅁䅅䅁䉁䅁䅁兂䵃塓瘸捨㝍䅑杷允䅁䅁䅣䅁䑁䅁䅷䅁䭁䥁䝣䅁䭁䙁䝕䅁䭁䅁䅅䅁䙁䅁䅁䅁杁⭓䅚兂䅁䅁䅁䙙浢䅑䅯眰䅣䅁䅅䅁䉁䅁䅁兂杄琱㠰搱䈱䅑杷允䅁䅁䅕䅁䑁䅁䅷䅁䭁䥁䝣䅁䭁䉁䅙䅁䙁䅁䅁䅁杁佣䅚权婂杂䅁允䅁䅁䅅䅁啁䝁瑢橴䅣䅁䅁䍄䉁䅁䅁杂䅁䅁䅍䅄䅁䅁䅯睨䅙䅁䅯杙䅙䅁䅯兕䅙䅁䅕䅁䅁䵁桂欵䭁䙁䝫䅁䉁䅁䅁允䅁䅁䅕呤䩓䨴⭈歍䵁䅉䅅䅁䡁䅁䅁睁䵁䅁䅁权䡃杂䅁权時杂䅁权剂杂䅁兂䅁䅁䅁䑯洯䅑䅕䅁䅁䍁䱂欵䭁乁䡅䅁䉁䅁䅁允䅁䅁䅕呎⼰䝢䘰䐶䴸䅉䅅䅁䝁䅁䅁睁䵁䅁䅁权䡃杂䅁权摂杂䅁权䉁䅁䅁兂䅁䅁䅁䑉浔䅑䅯兗䅙䅁䅅䅁䉁䅁䅁兂䝄ㅯ䍔㍅䕯䅑杷允䅁䅁䅙䅁䑁䅁䅷䅁䭁䥁䝣䅁䭁䝁䝷䅁䭁䙁䝅䅁䙁䅁䅁䅁杁⭓䅚权婂杂䅁允䅁䅁䅅䅁䙁䕁㕦㍹洸杍䅬䍄䉁䅁䅁睂䅁䅁䅍䅄䅁䅁䅯睨䅙䅁䅯䅢䅙䅁䅯兕䅙䅁䅕䅁䅁䝁坂欵䙁䅁䅁䅁䅄教䅚权啄睂䅁允䅁䅁䅅䅁䙁偁ㅊ㔲䍈睵䅸䍄䉁䅁䅁睂䅁䅁䅍䅄䅁䅁䅯睨䅙䅁䅯䅗䅙䅁䅯允䅁䅁䅕䅁䅁䵁潁欵䙁䅁䅁䅁杁低䅚权呄睂䅁允䅁䅁䅅䅁䙁䵁㙲捺げ呯䅎䍄䉁䅁䅁睂䅁䅁䅍䅄䅁䅁䅯睨䅙䅁䅯睘䅙䅁䅯兕䅙䅁䅕䅁䅁䝁坂欵䙁䅁䅁䅁䅄教䅚权呄睂䅁允䅁䅁䅅䅁䙁䑁特别晓半䄱䍄䉁䅁䅁杂䅁䅁䅍䅄䅁䅁䅯睨䅙䅁䅯䅘䅙䅁䅯允䅁䅁䅕䅁䅁䍁䱂欵䭁䙁䝫䅁䉁䅁䅁允䅁䅁䅕卐⭲㐷䝪啎䵁䅉䅅䅁䡁䅁䅁睁䵁䅁䅁权䡃杂䅁权浂杂䅁权䉁䅁䅁兂䅁䅁䅁䡷浪䅑䅕䅁䅁䝁㥂欵䭁乁䡍䅁䉁䅁䅁允䅁䅁䅕㑬㔴㥺㍩啍䵁䅉䅅䅁䡁䅁䅁睁䵁䅁䅁权䡃杂䅁权奂杂䅁权䉁䅁䅁兂䅁䅁䅁䝑洳䅑䅕䅁䅁䵁㑂欵䭁乁䡍䅁䉁䅁䅁允䅁䅁䅕奔㑖䙊攴く䵁䅉䅅䅁䡁䅁䅁睁䵁䅁䅁权䡃杂䅁权楂杂䅁权剂杂䅁兂䅁䅁䅁䑯洯䅑䅕䅁䅁䍁䱂欵䭁乁䡁䅁䉁䅁䅁允䅁䅁䅕浨佧奷晫が䵁䅉䅅䅁䡁䅁䅁睁䵁䅁䅁权䡃杂䅁权潂杂䅁权剂杂䅁兂䅁䅁䅁䝑洳䅑䅕䅁䅁䵁㑂欵䭁乁䡍䅁䉁䅁䅁允䅁䅁䅕稷据敷婋ぎ䵁䅉䅅䅁䝁䅁䅁睁䵁䅁䅁权䡃杂䅁权敂杂䅁权剂杂䅁兂䅁䅁䅁䕉浶䅑䅯兗䅙䅁䅅䅁䉁䅁䅁兂㙂䥒奁樰呁䅑杷允䅁䅁䅙䅁䑁䅁䅷䅁䭁䥁䝣䅁䭁䝁䝫䅁䭁䅁䅅䅁䙁䅁䅁䅁杂畖䅚权婂杂䅁允䅁䅁䅅䅁䙁䑁㑉汓搶穕䅬䍄䉁䅁䅁睂䅁䅁䅍䅄䅁䅁䅯睨䅙䅁䅯兘䅙䅁䅯允䅁䅁䅕䅁䅁䵁桂欵䙁䅁䅁䅁䅂敢䅚权呄睂䅁允䅁䅁䅅䅁䙁偁焱桄䵄兕䅴䍄䉁䅁䅁睂䅁䅁䅍䅄䅁䅁䅯睨䅙䅁䅯䅚䅙䅁䅯允䅁䅁䅕䅁䅁䍁ぁ欵䙁䅁䅁䅁权⭐䅚权啄睂䅁允䅁䅁䅅䅁䭁䑁䅅䅁䵁䅉䅅䅁䡁䅁䅁睁䵁䅁䅁权䡃杂䅁权潂杂䅁权剂杂䅁兂䅁䅁䅁䑯洯䅑䅕䅁䅁䍁䱂欵䭁乁䡍䅁䉁䅁䅁允䅁䅁䅕杹䵲桱畋き䵁䅉䅅䅁䝁䅁䅁睁䵁䅁䅁权䡃杂䅁权浂杂䅁权䉁䅁䅁兂䅁䅁䅁䙙浢䅑䅯兗䅙䅁䅅䅁䉁䅁䅁兂䭁癡坧氱穕䅑杷允䅁䅁䅙䅁䑁䅁䅷䅁䭁䥁䝣䅁䭁䙁䝙䅁䭁䅁䅅䅁䙁䅁䅁䅁䅂敢䅚权婂杂䅁允䅁䅁䅅䅁䙁䅁橷慶摪硲䅎䍄䉁䅁䅁杂䅁䅁䅍䅄䅁䅁䅯睨䅙䅁䅯杚䅙䅁䅯允䅁䅁䅕䅁䅁䭁⽁欵䭁䙁䝫䅁䉁䅁䅁允䅁䅁䅕偕男呈慖䕍䵁䅉䅅䅁䡁䅁䅁睁䵁䅁䅁权䡃杂䅁权獂杂䅁权剂杂䅁兂䅁䅁䅁䝷浈䅑䅕䅁䅁䕁瑂欵䭁乁䡍䅁䉁䅁䅁允䅁䅁䅕搯䭑歋奩啃䵁䅉䅅䅁䡁䅁䅁睁䵁䅁䅁权䡃杂䅁权獂杂䅁权剂杂䅁兂䅁䅁䅁䍷浪䅑䅕䅁䅁䍁ぁ欵䭁乁䡁䅁䉁䅁䅁允䅁䅁䅕䥔睊欱嘸䕂䵁䅉䅅䅁䝁䅁䅁睁䵁䅁䅁权䡃杂䅁权兂杂䅁权剂杂䅁兂䅁䅁䅁䝷浈䅑䅯兗䅙䅁䅅䅁䉁䅁䅁兂啁摈䉄い吴䅑杷允䅁䅁䅙䅁䑁䅁䅷䅁䭁䥁䝣䅁䭁䙁䝑䅁䭁䅁䅅䅁䙁䅁䅁䅁权⭐䅚权婂杂䅁允䅁䅁䅅䅁䙁䩁䵹獋㑏礸䅂䍄䉁䅁䅁杂䅁䅁䅍䅄䅁䅁䅯睨䅙䅁䅯杖䅙䅁䅯允䅁䅁䅕䅁䅁䝁㥂欵䭁䙁䝫䅁䉁䅁䅁允䅁䅁䅕书ぐ儲䡅ぅ䵁䅉䅅䅁䡁䅁䅁睁䵁䅁䅁权䡃杂䅁权煂杂䅁权㥁䅁䅁兂䅁䅁䅁䑉浔䅑䅕䅁䅁䭁⽁欵䭁乁䡁䅁䉁䅁䅁允䅁䅁䅕捸乔橁晁ぇ䵁䅉䅅䅁䡁䅁䅁睁䵁䅁䅁权䡃杂䅁权啂杂䅁权䉁䅁䅁兂䅁䅁䅁䍷浪䅑䅕䅁䅁䍁ぁ欵䭁乁䡍䅁䉁䅁䅁允䅁䅁䅕桂⭁䝬㕪啇䵁䅉䅅䅁䡁䅁䅁睁䵁䅁䅁权䡃杂䅁权噂杂䅁权䉁䅁䅁兂䅁䅁䅁䝷浈䅑䅕䅁䅁䕁瑂欵䭁乁䡑䅁䉁䅁䅁允䅁䅁䅕䙮敊㙋㥈け䵁䅉䅅䅁䡁䅁䅁睁䵁䅁䅁权䡃杂䅁权灂杂䅁权䉁䅁䅁兂䅁䅁䅁䝑洳䅑䅕䅁䅁䵁㑂欵䭁乁䡉䅁䉁䅁䅁允䅁䅁䅕猫愫㍈根䕐䵁䅉䅅䅁䡁䅁䅁睁䵁䅁䅁权䡃杂䅁权浂杂䅁权䉁䅁䅁兂䅁䅁䅁䑉浔䅑䅕䅁䅁䭁⽁欵䭁乁䡅䅁䉁䅁䅁允䅁䅁䅕䉢睊㡢夷吶䴸䅉䅅䅁䡁䅁䅁睁䵁䅁䅁权䡃杂䅁权煂杂䅁权㥁䅁䅁兂䅁䅁䅁䍷浪䅑䅕䅁䅁䍁ぁ欵䭁乁䡁䅁䉁䅁䅁允䅁䅁䅕慦剕桒⽅䕇䵁䅉䅅䅁䡁䅁䅁睁䵁䅁䅁权䡃杂䅁权楂杂䅁权剂杂䅁兂䅁䅁䅁䑉浔䅑䅕䅁䅁䭁⽁欵䭁乁䡅䅁䉁䅁䅁允䅁䅁䅕挱㑉止㑭樷䴸䅉䅅䅁䝁䅁䅁睁䵁䅁䅁权䡃杂䅁权浂杂䅁权䉁䅁䅁兂䅁䅁䅁䡷浪䅑䅯兗䅙䅁䅅䅁䉁䅁䅁兂呄煌婡样さ䅑杷允䅁䅁䅣䅁䑁䅁䅷䅁䭁䥁䝣䅁䭁䙁䜰䅁䭁䅁䅅䅁䙁䅁䅁䅁䅂敢䅚兂䅁䅁䅁䡷浪䅑䅯儰䅣䅁䅅䅁䉁䅁䅁兂䅁畂䙎啁䉐睐杷允䅁䅁䅣䅁䑁䅁䅷䅁䭁䥁䝣䅁䭁䝁䝅䅁䭁䅁䅅䅁䙁䅁䅁䅁䅄教䅚兂䅁䅁䅁䝑洳䅑䅯䄰䅣䅁䅅䅁䉁䅁䅁兂桂礶畲婩䙆䅑杷允䅁䅁䅙䅁䑁䅁䅷䅁䭁䥁䝣䅁䭁䙁䝧䅁䭁䅁䅅䅁䙁䅁䅁䅁䅄教䅚权婂杂䅁允䅁䅁䅅䅁䙁䱁㍏偬䙐樫䄹䍄䉁䅁䅁杂䅁䅁䅍䅄䅁䅁䅯睨䅙䅁䅯睘䅙䅁䅯兕䅙䅁䅕䅁䅁䵁㑂欵䭁䙁䝫䅁䉁䅁䅁允䅁䅁䅕汒㑯癈愸啍䵁䅉䅅䅁䡁䅁䅁睁䵁䅁䅁权䡃杂䅁权捂杂䅁权䉁䅁䅁兂䅁䅁䅁䍷浪䅑䅕䅁䅁䍁ぁ欵䭁乁䡑䅁䉁䅁䅁允䅁䅁䅕杬呕硦剓䕍䵁䅉䅅䅁䡁䅁䅁睁䵁䅁䅁权䡃杂䅁权桂杂䅁权䉁䅁䅁兂䅁䅁䅁䑯洯䅑䅕䅁䅁䍁䱂欵䭁乁䡁䅁䉁䅁䅁允䅁䅁䅕䩶兒䵥圱歐䵁䅉䅅䅁䙁䅁䅁睁䵁䅁䅁权䡃杂䅁权坁䅁䅁兂䅁䅁䅁䙉浌䅑䅯兗䅙䅁䅅䅁䉁䅁䅁䅆䵂欷㍑䅁䅁䅁杷允䅁䅁䅙䅁䑁䅁䅷䅁䭁䥁䝣䅁䭁䝁䝷䅁䭁䙁䝅䅁䙁䅁䅁䅁䅂敢䅚权婂杂䅁允䅁䅁䅅䅁䙁偁㍑歘佊睵䄵䍄䉁䅁䅁睂䅁䅁䅍䅄䅁䅁䅯睨䅙䅁䅯杘䅙䅁䅯兕䅙䅁䅕䅁䅁䵁㑂欵䙁䅁䅁䅁杂敦䅚权兄睂䅁允䅁䅁䅅䅁䙁䩁楥砲杅兣䅰䍄䉁䅁䅁睂䅁䅁䅍䅄䅁䅁䅯睨䅙䅁䅯杚䅙䅁䅯允䅁䅁䅕䅁䅁䵁桂欵䙁䅁䅁䅁䅂敢䅚权啄睂䅁允䅁䅁䅅䅁䙁佁攸偯祴樸䅊䍄䉁䅁䅁兂䅁䅁䅍䅄䅁䅁䅯睨䅙䅁䅯杆䅁䅁䅕䅁䅁䵁歂欵䭁䙁䝫䅁䉁䅁䅁允䅁䉁䅑瑃䙵睎䅁䅁䵁䅉䅅䅁䡁䅁䅁睁䵁䅁䅁权䡃杂䅁权煂杂䅁权㥁䅁䅁兂䅁䅁䅁䕉浶䅑䅕䅁䅁䝁坂欵䭁乁䡍䅁䉁䅁䅁允䅁䅁䅕楦㈳桥楯䕈䵁䅉䅅䅁䝁䅁䅁睁䵁䅁䅁权䡃杂䅁权坂杂䅁权䉁䅁䅁兂䅁䅁䅁䑯洯䅑䅯兗䅙䅁䅅䅁䉁䅁䅁兂湁晡夶朱兙䅑杷允䅁䅁䅙䅁䑁䅁䅷䅁䭁䥁䝣䅁䭁䙁䝯䅁䭁䙁䝅䅁䙁䅁䅁䅁䅂敢䅚权婂杂䅁允䅁䅁䅅䅁䙁乁㍶桒樷呮䅚䍄䉁䅁䅁睂䅁䅁䅍䅄䅁䅁䅯睨䅙䅁䅯杘䅙䅁䅯兕䅙䅁䅕䅁䅁䵁㑂欵䙁䅁䅁䅁杂敦䅚权呄睂䅁允䅁䅁䅅䅁䙁䡁䥉橬卯杸䅨䍄䉁䅁䅁睂䅁䅁䅍䅄䅁䅁䅯睨䅙䅁䅯睘䅙䅁䅯兕䅙䅁䅕䅁䅁䵁桂欵䙁䅁䅁䅁䅂敢䅚权兄睂䅁允䅁䅁䅅䅁䙁䱁㕸爲塄呇䅂䍄䉁䅁䅁睂䅁䅁䅍䅄䅁䅁䅯睨䅙䅁䅯杗䅙䅁䅯兕䅙䅁䅕䅁䅁䍁ぁ欵䙁䅁䅁䅁权⭐䅚权呄睂䅁允䅁䅁䅅䅁䙁䭁㕸兹橴穕䅆䍄䉁䅁䅁睂䅁䅁䅍䅄䅁䅁䅯睨䅙䅁䅯杖䅙䅁䅯允䅁䅁䅕䅁䅁䍁ぁ欵䙁䅁䅁䅁权⭐䅚权卄睂䅁允䅁䅁䅅䅁䙁䩁䩐婱栱桋䅂䍄䉁䅁䅁睂䅁䅁䅍䅄䅁䅁䅯睨䅙䅁䅯兙䅙䅁䅯允䅁䅁䅕䅁䅁䵁潁欵䙁䅁䅁䅁杁低䅚权卄睂䅁允䅁䅁䅅䅁䙁䝁晁扮祲呤䅤䍄䉁䅁䅁睂䅁䅁䅍䅄䅁䅁䅯睨䅙䅁䅯睙䅙䅁䅯允䅁䅁䅕䅁䅁䍁䱂欵䙁䅁䅁䅁杂畖䅚权剄睂䅁允䅁䅁䅅䅁䙁䵁䙣卐祱兔䅚䍄䉁䅁䅁睂䅁䅁䅍䅄䅁䅁䅯睨䅙䅁䅯睙䅙䅁䅯允䅁䅁䅕䅁䅁䵁桂欵䙁䅁䅁䅁䅂敢䅚权卄睂䅁允䅁䅁䅅䅁䙁佁㑣睴㍮樷䅬䍄䉁䅁䅁睂䅁䅁䅍䅄䅁䅁䅯睨䅙䅁䅯睙䅙䅁䅯允䅁䅁䅕䅁䅁䕁瑂欵䙁䅁䅁䅁䅄佥䅚权剄睂䅁允䅁䅁䅅䅁䙁䝁琯䭏⬲䅑䅊䍄䉁䅁䅁睂䅁䅁䅍䅄䅁䅁䅯睨䅙䅁䅯杗䅙䅁䅯兕䅙䅁䅕䅁䅁䍁䱂欵䙁䅁䅁䅁杂畖䅚权呄睂䅁允䅁䅁䅅䅁䙁䱁㡶欰湬告䅒䍄䉁䅁䅁睂䅁䅁䅍䅄䅁䅁䅯睨䅙䅁䅯杚䅙䅁䅯允䅁䅁䅕䅁䅁䍁ぁ欵䙁䅁䅁䅁权⭐䅚权啄睂䅁允䅁䅁䅅䅁䙁䵁䝸⼵啷祚䄱䍄䉁䅁䅁杂䅁䅁䅍䅄䅁䅁䅯睨䅙䅁䅯䅕䅙䅁䅯兕䅙䅁䅕䅁䅁䍁ぁ欵䭁䙁䝫䅁䉁䅁䅁允䅁䅁䅕䙪⭔橪婭啃䵁䅉䅅䅁䡁䅁䅁睁䵁䅁䅁权䡃杂䅁权灂杂䅁权䉁䅁䅁兂䅁䅁䅁䑉浔䅑䅕䅁䅁䭁⽁欵䭁乁䡅䅁䉁䅁䅁允䅁䅁䅕到え浊䰴吹䴸䅉䅅䅁䡁䅁䅁睁䵁䅁䅁权䡃杂䅁权啂杂䅁权䉁䅁䅁兂䅁䅁䅁䍷浪䅑䅕䅁䅁䍁ぁ欵䭁乁䡁䅁䉁䅁䅁允䅁䅁䅕䨲䬸剢物ぇ䵁䅉䅅䅁䝁䅁䅁睁䵁䅁䅁权䡃杂䅁权兂杂䅁权剂杂䅁兂䅁䅁䅁䕉浶䅑䅯兗䅙䅁䅅䅁䉁䅁䅁兂䡁⭈ㅢ昶何䅑杷允䅁䅁䅙䅁䑁䅁䅷䅁䭁䥁䝣䅁䭁䙁䝁䅁䭁䙁䝅䅁䙁䅁䅁䅁杂畖䅚权婂杂䅁允䅁䅁䅅䅁䙁䕁奰摦䰫栵䅂䍄䉁䅁䅁睂䅁䅁䅍䅄䅁䅁䅯睨䅙䅁䅯䅢䅙䅁䅯兕䅙䅁䅕䅁䅁䝁坂欵䙁䅁䅁䅁䅄教䅚权卄睂䅁允䅁䅁䅅䅁䙁䝁瀹䑆䥱桗䅂䍄䉁䅁䅁杂䅁䅁䅍䅄䅁䅁䅯睨䅙䅁䅯䅕䅙䅁䅯兕䅙䅁䅕䅁䅁䕁瑂欵䭁䙁䝫䅁䉁䅁䅁允䅁䅁䅕䩰摋楳瑒歅䵁䅉䅅䅁䝁䅁䅁睁䵁䅁䅁权䡃杂䅁权煂杂䅁权㥁䅁䅁兂䅁䅁䅁䑯洯䅑䅯儰䅣䅁䅅䅁䉁䅁䅁兂䥃摯歹婲湔睐杷允䅁䅁䅙䅁䑁䅁䅷䅁䭁䥁䝣䅁䭁䝁䝙䅁䭁䅁䅅䅁䙁䅁䅁䅁杁⭓䅚权婂杂䅁允䅁䅁䅅䅁䙁䅁圯稯䵮穒䅂䍄䉁䅁䅁睂䅁䅁䅍䅄䅁䅁䅯睨䅙䅁䅯䅕䅙䅁䅯兕䅙䅁䅕䅁䅁䍁ぁ欵䙁䅁䅁䅁权⭐䅚权啄睂䅁允䅁䅁䅅䅁䙁䭁獚䈯摏睂䅸䍄䉁䅁䅁杂䅁䅁䅍䅄䅁䅁䅯睨䅙䅁䅯兖䅙䅁䅯允䅁䅁䅕䅁䅁䍁ぁ欵䭁䙁䝫䅁䉁䅁䅁允䅁䅁䅕㘱扔牅公䕐䵁䅉䅅䅁䡁䅁䅁睁䵁䅁䅁权䡃杂䅁权橂杂䅁权䉁䅁䅁兂䅁䅁䅁䕉浶䅑䅕䅁䅁䝁坂欵䭁乁䡉䅁䉁䅁䅁允䅁䅁䅕䴹穒潴潁く䵁䅉䅅䅁䡁䅁䅁睁䵁䅁䅁权䡃杂䅁权啂杂䅁权䉁䅁䅁兂䅁䅁䅁䕉浶䅑䅕䅁䅁䝁坂欵䭁乁䡁䅁䉁䅁䅁允䅁䅁䅕㠷睉瑮呉啉䵁䅉䅅䅁䡁䅁䅁睁䵁䅁䅁权䡃杂䅁权潂杂䅁权剂杂䅁兂䅁䅁䅁䝷浈䅑䅕䅁䅁䕁瑂欵䭁乁䡁䅁䉁䅁䅁允䅁䅁䅕㤰攫䭤䡢歎䵁䅉䅅䅁䝁䅁䅁睁䵁䅁䅁权䡃杂䅁权浂杂䅁权䉁䅁䅁兂䅁䅁䅁䝑洳䅑䅯兗䅙䅁䅅䅁䉁䅁䅁兂牄坈䠶汨さ䅑杷允䅁䅁䅣䅁䑁䅁䅷䅁䭁䥁䝣䅁䭁䙁䝧䅁䭁䅁䅅䅁䙁䅁䅁䅁䅂敢䅚兂䅁䅁䅁䡷浪䅑䅯儰䅣䅁䅅䅁䉁䅁䅁兂⽁儶何䑓楌睐杷允䅁䅁䅣䅁䑁䅁䅷䅁䭁䥁䝣䅁䭁䝁䝍䅁䭁䅁䅅䅁䙁䅁䅁䅁杁低䅚兂䅁䅁䅁䑯洯䅑䅯䄰䅣䅁䅅䅁䉁䅁䅁兂㥂楁䝨煨ぉ䅑杷允䅁䅁䅙䅁䑁䅁䅷䅁䭁䥁䝣䅁䭁䙁䜸䅁䭁䙁䝅䅁䙁䅁䅁䅁杁低䅚权婂杂䅁允䅁䅁䅅䅁䙁䥁䱷睩䥹䌱䅨䍄䉁䅁䅁杂䅁䅁䅍䅄䅁䅁䅯睨䅙䅁䅯睘䅙䅁䅯兕䅙䅁䅕䅁䅁䭁⽁欵䭁䙁䝫䅁䉁䅁䅁允䅁䅁䅕穨扎㡍啇歌䵁䅉䅅䅁䝁䅁䅁睁䵁䅁䅁权䡃杂䅁权奂杂䅁权䉁䅁䅁兂䅁䅁䅁䙙浢䅑䅯兗䅙䅁䅅䅁䉁䅁䅁兂婄穲摶入㡯䅑杷允䅁䅁䅙䅁䑁䅁䅷䅁䭁䥁䝣䅁䭁䙁䝧䅁䭁䅁䅅䅁䙁䅁䅁䅁杁低䅚权婂杂䅁允䅁䅁䅅䅁䙁佁䑙灁䨱穡䅒䍄䉁䅁䅁杂䅁䅁䅍䅄䅁䅁䅯睨䅙䅁䅯䅗䅙䅁䅯允䅁䅁䅕䅁䅁䭁⽁欵䭁䙁䝫䅁䉁䅁䅁允䅁䅁䅕汓䤸敏⼯䕏䵁䅉䅅䅁䡁䅁䅁睁䵁䅁䅁权䡃杂䅁权坂杂䅁权䉁䅁䅁兂䅁䅁䅁䝷浈䅑䅕䅁䅁䕁瑂欵䭁乁䡁䅁䉁䅁䅁允䅁䅁䅕坥㉋䝌刲歅䵁䅉䅅䅁䝁䅁䅁睁䵁䅁䅁权䡃杂䅁权奂杂䅁权䉁䅁䅁兂䅁䅁䅁䝑洳䅑䅯兗䅙䅁䅅䅁䉁䅁䅁兂灂䡹啩癓㡷䅑杷允䅁䅁䅙䅁䑁䅁䅷䅁䭁䥁䝣䅁䭁䝁䝯䅁䭁䑁䄰䅁䙁䅁䅁䅁䅄佥䅚权剄睂䅁允䅁䅁䅅䅁䙁䥁が呓䕄⬳⽧䍄䉁䅁䅁睂䅁䅁䅍䅄䅁䅁䅯睨䅙䅁䅯兙䅙䅁䅯允䅁䅁䅕䅁䅁䍁ぁ欵䙁䅁䅁䅁权⭐䅚权卄睂䅁允䅁䅁䅅䅁䙁䩁䨴剔䱊橯䅨䍄䉁䅁䅁睂䅁䅁䅍䅄䅁䅁䅯睨䅙䅁䅯睙䅙䅁䅯允䅁䅁䅕䅁䅁䵁㑂欵䙁䅁䅁䅁杂敦䅚权剄睂䅁允䅁䅁䅅䅁䙁䵁䉰灭割癉⽁䍄䉁䅁䅁杂䅁䅁䅍䅄䅁䅁䅯睨䅙䅁䅯兖䅙䅁䅯允䅁䅁䅕䅁䅁䕁瑂欵䭁䙁䝫䅁䉁䅁䅁允䅁䅁䅕浇䄷㐵䙦啒䵁䅉䅅䅁䡁䅁䅁睁䵁䅁䅁权䡃杂䅁权兂杂䅁权剂杂䅁兂䅁䅁䅁䑉浔䅑䅕䅁䅁䭁⽁欵䭁乁䡅䅁䉁䅁䅁允䅁䅁䅕兏䡉㍙㝴呹䴸䅉䅅䅁䝁䅁䅁睁䵁䅁䅁权䡃杂䅁权桂杂䅁权䉁䅁䅁兂䅁䅁䅁䑉浔䅑䅯兗䅙䅁䅅䅁䉁䅁䅁兂㝃告杬㕖積䅑杷允䅁䅁䅣䅁䑁䅁䅷䅁䭁䥁䝣䅁䭁䙁䝑䅁䭁䅁䅅䅁䙁䅁䅁䅁杁低䅚兂䅁䅁䅁䑯洯䅑䅯朰䅣䅁䅅䅁䉁䅁䅁兂呁书ぐ匲桅䅑杷允䅁䅁䅣䅁䑁䅁䅷䅁䭁䥁䝣䅁䭁䝁䝷䅁䭁䙁䝅䅁䙁䅁䅁䅁权⭐䅚兂䅁䅁䅁䕉浶䅑䅯䄰䅣䅁䅅䅁䉁䅁䅁兂捂偧啌奤䩷䅑杷允䅁䅁䅙䅁䑁䅁䅷䅁䭁䥁䝣䅁䭁䝁䝅䅁䭁䅁䅅䅁䙁䅁䅁䅁杁⭓䅚权婂杂䅁允䅁䅁䅅䅁䙁䝁⭋䅶㝄歂䅂䍄䉁䅁䅁睂䅁䅁䅍䅄䅁䅁䅯睨䅙䅁䅯兙䅙䅁䅯允䅁䅁䅕䅁䅁䵁桂欵䙁䅁䅁䅁䅂敢䅚权剄睂䅁允䅁䅁䅅䅁䙁䩁偙㝰桋䉆䅂䍄䉁䅁䅁睂䅁䅁䅍䅄䅁䅁䅯睨䅙䅁䅯兡䅙䅁䅯允䅁䅁䅕䅁䅁䝁坂欵䙁䅁䅁䅁䅄教䅚权卄睂䅁允䅁䅁䅅䅁䙁䭁䥰扨䙇䑈䄱䍄䉁䅁䅁睂䅁䅁䅍䅄䅁䅁䅯睨䅙䅁䅯杘䅙䅁䅯兕䅙䅁䅕䅁䅁䍁ぁ欵䙁䅁䅁䅁权⭐䅚权兄睂䅁允䅁䅁䅅䅁䙁䥁浇塐㍒硄䅂䍄䉁䅁䅁杂䅁䅁䅍䅄䅁䅁䅯睨䅙䅁䅯兙䅙䅁䅯允䅁䅁䅕䅁䅁䵁桂欵䭁䙁䝫䅁䉁䅁䅁允䅁䅁䅕婎扣䡄䵖啓䵁䅉䅅䅁䡁䅁䅁睁䵁䅁䅁权䡃杂䅁权煂杂䅁权㥁䅁䅁兂䅁䅁䅁䕉浶䅑䅕䅁䅁䝁坂欵䭁乁䡁䅁䉁䅁䅁允䅁䅁䅕㉗含㡺浏歈䵁䅉䅅䅁䝁䅁䅁睁䵁䅁䅁权䡃杂䅁权桂杂䅁权䉁䅁䅁兂䅁䅁䅁䙙浢䅑䅯兗䅙䅁䅅䅁䉁䅁䅁兂䉁卩党䙸䑚䅑杷允䅁䅁䅙䅁䑁䅁䅷䅁䭁䥁䝣䅁䭁䝁䝧䅁䭁䙁䝅䅁䙁䅁䅁䅁杁⭓䅚权婂杂䅁允䅁䅁䅅䅁䙁䡁煄䕉兎橈䅖䍄䉁䅁䅁杂䅁䅁䅍䅄䅁䅁䅯睨䅙䅁䅯䅡䅙䅁䅯兕䅙䅁䅕䅁䅁䵁桂欵䭁䙁䝫䅁䉁䅁䅁允䅁䅁䅕㈹⽗潘橂歏䵁䅉䅅䅁䡁䅁䅁睁䵁䅁䅁权䡃杂䅁权浂杂䅁权䉁䅁䅁兂䅁䅁䅁䙙浢䅑䅕䅁䅁䵁桂欵䭁乁䡉䅁䉁䅁䅁允䅁䅁䅕稹啳時潯歎䵁䅉䅅䅁䡁䅁䅁睁䵁䅁䅁权䡃杂䅁权慂杂䅁权剂杂䅁兂䅁䅁䅁䙙浢䅑䅕䅁䅁䵁桂欵䭁乁䡅䅁䉁䅁䅁允䅁䅁䅕乺癤慂桘䐸䴸䅉䅅䅁䡁䅁䅁睁䵁䅁䅁权䡃杂䅁权煂杂䅁权㥁䅁䅁兂䅁䅁䅁䝑洳䅑䅕䅁䅁䵁㑂欵䭁乁䡍䅁䉁䅁䅁允䅁䅁䅕㥧睩氳晹䕉䵁䅉䅅䅁䡁䅁䅁睁䵁䅁䅁权䡃杂䅁权時杂䅁权剂杂䅁兂䅁䅁䅁䙙浢䅑䅕䅁䅁䵁桂欵䭁乁䡅䅁䉁䅁䅁允䅁䅁䅕佰䘳牘瑅䐷䴸䅉䅅䅁䡁䅁䅁睁䵁䅁䅁权䡃杂䅁权歂杂䅁权䉁䅁䅁兂䅁䅁䅁䙙浢䅑䅕䅁䅁䵁桂欵䭁乁䡑䅁䉁䅁䅁允䅁䅁䅯免䅁䅁杷允䅁䅁䅣䅁䑁䅁䅷䅁䭁䥁䝣䅁䭁䙁䝙䅁䭁䅁䅅䅁䙁䅁䅁䅁杁低䅚兂䅁䅁䅁䑯洯䅑䅯䄱䅣䅁䅅䅁䉁䅁䅁兂摂睷乹㡊䵉䅑杷允䅁䅁䅣䅁䑁䅁䅷䅁䭁䥁䝣䅁䭁䙁䝧䅁䭁䅁䅅䅁䙁䅁䅁䅁䅄佋䅚兂䅁䅁䅁䑉浔䅑䅯䄱䅣䅁䅅䅁䉁䅁䅁兂㕃䩪慳䍡〴䅑杷允䅁䅁䅣䅁䑁䅁䅷䅁䭁䥁䝣䅁䭁䙁䝷䅁䭁䅁䅅䅁䙁䅁䅁䅁杁低䅚兂䅁䅁䅁䑯洯䅑䅯儰䅣䅁䅅䅁䉁䅁䅁兂牃楊割㙧䱉䅑杷允䅁䅁䅙䅁䑁䅁䅷䅁䭁䥁䝣䅁䭁䙁䝕䅁䭁䅁䅅䅁䙁䅁䅁䅁杂畖䅚权婂杂䅁允䅁䅁䅅䅁䙁䍁敂礱夯啥䅒䍄䉁䅁䅁杂䅁䅁䅍䅄䅁䅁䅯睨䅙䅁䅯兖䅙䅁䅯允䅁䅁䅕䅁䅁䭁⽁欵䭁䙁䝫䅁䉁䅁䅁允䅁䅁䅕慹穴䵄杪啑䵁䅉䅅䅁䡁䅁䅁睁䵁䅁䅁权䡃杂䅁权捂杂䅁权䉁䅁䅁兂䅁䅁䅁䕉浶䅑䅕䅁䅁䝁坂欵䭁乁䡉䅁䉁䅁䅁允䅁䅁䅕乸煄䄵桹䕐䵁䅉䅅䅁䡁䅁䅁睁䵁䅁䅁权䡃杂䅁权歂杂䅁权䉁䅁䅁兂䅁䅁䅁䑉浔䅑䅕䅁䅁䭁⽁欵䭁乁䡍䅁䉁䅁䅁允䅁䅁䅯免䅁䅁杷允䅁䅁䅙䅁䑁䅁䅷䅁䭁䥁䝣䅁䭁䙁䝕䅁䭁䅁䅅䅁䙁䅁䅁䅁杁⭓䅚权婂杂䅁允䅁䅁䅅䅁䙁䉁ぅ桚ㅌ䕅䅊䍄䉁䅁䅁睂䅁䅁䅍䅄䅁䅁䅯睨䅙䅁䅯䅢䅙䅁䅯兕䅙䅁䅕䅁䅁䝁坂欵䙁䅁䅁䅁䅄教䅚权呄睂䅁允䅁䅁䅅䅁䙁䙁乷ㅗ䥒䅑䅬䍄䉁䅁䅁睂䅁䅁䅍䅄䅁䅁䅯睨䅙䅁䅯杖䅙䅁䅯允䅁䅁䅕䅁䅁䵁桂欵䙁䅁䅁䅁䅂敢䅚权呄睂䅁允䅁䅁䅅䅁䙁䱁䡱佨㤯刷䅂䍄䉁䅁䅁杂䅁䅁䅍䅄䅁䅁䅯睨䅙䅁䅯䅖䅙䅁䅯允䅁䅁䅕䅁䅁䝁坂欵䭁䙁䝫䅁䉁䅁䅁允䅁䅁䅕⽊汖慡敦䕉䵁䅉䅅䅁䝁䅁䅁睁䵁䅁䅁权䡃杂䅁权啂杂䅁权䉁䅁䅁兂䅁䅁䅁䝑洳䅑䅯兗䅙䅁䅅䅁䉁䅁䅁兂㕄樲䱎桁橷䅑杷允䅁䅁䅙䅁䑁䅁䅷䅁䭁䥁䝣䅁䭁䝁䝑䅁䭁䅁䅅䅁䙁䅁䅁䅁杁⭓䅚权婂杂䅁允䅁䅁䅅䅁䭁䝁䝕䅁䵁䅉䅅䅁䡁䅁䅁睁䵁䅁䅁权䡃杂䅁权奂杂䅁权䉁䅁䅁兂䅁䅁䅁䑉浔䅑䅕䅁䅁䭁⽁欵䭁乁䡍䅁䉁䅁䅁允䅁䅁䅕塍瘲呉敩䕎䵁䅉䅅䅁䡁䅁䅁睁䵁䅁䅁权䡃杂䅁权橂杂䅁权䉁䅁䅁兂䅁䅁䅁䝷浈䅑䅕䅁䅁䕁瑂欵䭁乁䡅䅁䉁䅁䅁允䅁䅁䅕㥎瘫㍧奍啄䵁䅉䅅䅁䝁䅁䅁睁䵁䅁䅁权䡃杂䅁权摂杂䅁权䉁䅁䅁兂䅁䅁䅁䕉浶䅑䅯兗䅙䅁䅅䅁䉁䅁䅁兂剂㐲剚偅䩷䅑杷允䅁䅁䅣䅁䑁䅁䅷䅁䭁䥁䝣䅁䭁䙁䝷䅁䭁䅁䅅䅁䙁䅁䅁䅁䅂敢䅚兂䅁䅁䅁䡷浪䅑䅯朰䅣䅁䅅䅁䉁䅁䅁兂慁潨䤫捋㙕䅑杷允䅁䅁䅣䅁䑁䅁䅷䅁䭁䥁䝣䅁䭁䝁䝍䅁䭁䅁䅅䅁䙁䅁䅁䅁䅄佋䅚兂䅁䅁䅁䑉浔䅑䅯䄰䅣䅁䅅䅁䉁䅁䅁兂㡁乙卄别瑫䅑杷允䅁䅁䅙䅁䑁䅁䅷䅁䭁䥁䝣䅁䭁䝁䝑䅁䭁䅁䅅䅁䙁䅁䅁䅁杁低䅚权婂杂䅁允䅁䅁䅅䅁䭁䝁䝕䅁䵁䅉䅅䅁䝁䅁䅁睁䵁䅁䅁权䡃杂䅁权歂杂䅁权䉁䅁䅁兂䅁䅁䅁䙙浢䅑䅯兗䅙䅁䅅䅁䉁䅁䅁权求杂䅁䍄䉁䅁䅁睂䅁䅁䅍䅄䅁䅁䅯睨䅙䅁䅯兘䅙䅁䅯允䅁䅁䅕䅁䅁䝁坂欵䙁䅁䅁䅁䅄教䅚权兄睂䅁允䅁䅁䅅䅁䙁䭁㙐䵌㕯杤䄵䍄䉁䅁䅁杂䅁䅁䅍䅄䅁䅁䅯睨䅙䅁䅯䅚䅙䅁䅯允䅁䅁䅕䅁䅁䵁桂欵䭁䙁䝫䅁䉁䅁䅁允䅁䅁䅯党䅙䅁杷允䅁䅁䅣䅁䑁䅁䅷䅁䭁䥁䝣䅁䭁䙁䜴䅁䭁䙁䝅䅁䙁䅁䅁䅁权⭐䅚兂䅁䅁䅁䕉浶䅑䅯朰䅣䅁䅅䅁䉁䅁䅁兂䩄䩡捃䵱啙䅑杷允䅁䅁䅙䅁䑁䅁䅷䅁䭁䥁䝣䅁䭁䝁䝉䅁䭁䙁䝅䅁䙁䅁䅁䅁权⭐䅚权婂杂䅁允䅁䅁䅅䅁䙁䍁䥈㥚噂祉䄹䍄䉁䅁䅁杂䅁䅁䅍䅄䅁䅁䅯睨䅙䅁䅯杙䅙䅁䅯兕䅙䅁䅕䅁䅁䝁坂欵䭁䙁䝫䅁䉁䅁䅁允䅁䅁䅕祭䙰灆敹䕍䵁䅉䅅䅁䡁䅁䅁睁䵁䅁䅁权䡃杂䅁权楂杂䅁权剂杂䅁兂䅁䅁䅁䝷浈䅑䅕䅁䅁䕁瑂欵䭁乁䡁䅁䉁䅁䅁允䅁䅁䅕歚佯畊す䕍䵁䅉䅅䅁䝁䅁䅁睁䵁䅁䅁权䡃杂䅁权楂杂䅁权剂杂䅁兂䅁䅁䅁䝑洳䅑䅯兗䅙䅁䅅䅁䉁䅁䅁兂㍃父砫䑘硕䅑杷允䅁䅁䅣䅁䑁䅁䅷䅁䭁䥁䝣䅁䭁䝁䝧䅁䭁䙁䝅䅁䙁䅁䅁䅁䅄佋䅚兂䅁䅁䅁䑉浔䅑䅯䄰䅣䅁䅅䅁䉁䅁䅁兂䅃䱦兪奇硍䅑杷允䅁䅁䅙䅁䑁䅁䅷䅁䭁䥁䝣䅁䭁䙁䜴䅁䭁䙁䝅䅁䙁䅁䅁䅁杂畖䅚权婂杂䅁允䅁䅁䅅䅁䙁䥁朸⬳乥睹䅨䍄䉁䅁䅁杂䅁䅁䅍䅄䅁䅁䅯睨䅙䅁䅯䅘䅙䅁䅯允䅁䅁䅕䅁䅁䍁ぁ欵䭁䙁䝫䅁䉁䅁䅁允䅁䅁䅕畇䍃䙢䭮䕍䵁䅉䅅䅁䡁䅁䅁睁䵁䅁䅁权䡃杂䅁权噂杂䅁权䉁䅁䅁兂䅁䅁䅁䍷浪䅑䅕䅁䅁䍁ぁ欵䭁乁䡉䅁䉁䅁䅁允䅁䅁䅕䡕䡋坔浔歐䵁䅉䅅䅁䝁䅁䅁睁䵁䅁䅁权䡃杂䅁权捂杂䅁权䉁䅁䅁兂䅁䅁䅁䑯洯䅑䅯兗䅙䅁䅅䅁䉁䅁䅁兂䅃敭术⭊㙯䅑杷允䅁䅁䅣䅁䑁䅁䅷䅁䭁䥁䝣䅁䭁䝁䝙䅁䭁䅁䅅䅁䙁䅁䅁䅁䅂敢䅚兂䅁䅁䅁䡷浪䅑䅯儰䅣䅁䅅䅁䉁䅁䅁兂癄䵘偱灶奌睐杷允䅁䅁䅙䅁䑁䅁䅷䅁䭁䥁䝣䅁䭁䙁䝷䅁䭁䅁䅅䅁䙁䅁䅁䅁杂畖䅚权婂杂䅁允䅁䅁䅅䅁䙁䝁祐灂㕪橚䅰䍄䉁䅁䅁睂䅁䅁䅍䅄䅁䅁䅯睨䅙䅁䅯杚䅙䅁䅯允䅁䅁䅕䅁䅁䵁潁欵䙁䅁䅁䅁杁低䅚权卄睂䅁允䅁䅁䅅䅁䙁䵁硺歃偒楳䄱䍄䉁䅁䅁睂䅁䅁䅍䅄䅁䅁䅯睨䅙䅁䅯兘䅙䅁䅯允䅁䅁䅕䅁䅁䍁ぁ欵䙁䅁䅁䅁权⭐䅚权卄睂䅁允䅁䅁䅅䅁䙁䕁摭䍧䍢杚䅰䍄䉁䅁䅁睂䅁䅁䅍䅄䅁䅁䅯睨䅙䅁䅯䅡䅙䅁䅯兕䅙䅁䅕䅁䅁䍁ぁ欵䙁䅁䅁䅁权⭐䅚权兄睂䅁允䅁䅁䅅䅁䙁䕁椴㑳獈呩䅎䍄䉁䅁䅁杂䅁䅁䅍䅄䅁䅁䅯睨䅙䅁䅯睙䅙䅁䅯允䅁䅁䅕䅁䅁䭁⽁欵䭁䙁䝫䅁䉁䅁䅁允䅁䅁䅕㉷䅡㝃㕋䕏䵁䅉䅅䅁䡁䅁䅁睁䵁䅁䅁权䡃杂䅁权捂杂䅁权䉁䅁䅁兂䅁䅁䅁䡷浪䅑䅕䅁䅁䝁㥂欵䭁乁䡉䅁䉁䅁䅁允䅁䅁䅕䵖灔䙊創歏䵁䅉䅅䅁䝁䅁䅁睁䵁䅁䅁权䡃杂䅁权橂杂䅁权䉁䅁䅁兂䅁䅁䅁䝑洳䅑䅯兗䅙䅁䅅䅁䉁䅁䅁兂婁䱹䱐⽴祙䅑杷允䅁䅁䅣䅁䑁䅁䅷䅁䭁䥁䝣䅁䭁䙁䜰䅁䭁䅁䅅䅁䙁䅁䅁䅁杁⭓䅚兂䅁䅁䅁䙙浢䅑䅯䄱䅣䅁䅅䅁䉁䅁䅁兂噁灱䱵㉶丰䅑杷允䅁䅁䅣䅁䑁䅁䅷䅁䭁䥁䝣䅁䭁䙁䝧䅁䭁䅁䅅䅁䙁䅁䅁䅁䅂敢䅚兂䅁䅁䅁䡷浪䅑䅯朰䅣䅁䅅䅁䉁䅁䅁兂硃㍡㝵兊⭕䅑杷允䅁䅁䅣䅁䑁䅁䅷䅁䭁䥁䝣䅁䭁䙁䜰䅁䭁䅁䅅䅁䙁䅁䅁䅁䅄佋䅚兂䅁䅁䅁䑉浔䅑䅯䄰䅣䅁䅅䅁䉁䅁䅁兂煄睧捷瀳䕍䅑杷允䅁䅁䅣䅁䑁䅁䅷䅁䭁䥁䝣䅁䭁䙁䜰䅁䭁䅁䅅䅁䙁䅁䅁䅁䅄佥䅚兂䅁䅁䅁䡙洳䅑䅯䄰䅣䅁䅅䅁䉁䅁䅁兂摁䕐䘱癲兑䅑杷允䅁䅁䅣䅁䑁䅁䅷䅁䭁䥁䝣䅁䭁䙁䝙䅁䭁䅁䅅䅁䙁䅁䅁䅁䅄佋䅚兂䅁䅁䅁䑉浔䅑䅯䄰䅣䅁䅅䅁䉁䅁䅁兂兂ㅚ杮ㄱ䭍䅑杷允䅁䅁䅣䅁䑁䅁䅷䅁䭁䥁䝣䅁䭁䙁䝁䅁䭁䙁䝅䅁䙁䅁䅁䅁䅄教䅚兂䅁䅁䅁䝑洳䅑䅯儰䅣䅁䅅䅁䉁䅁䅁兂佃硹㥦卯剄睐杷允䅁䅁䅣䅁䑁䅁䅷䅁䭁䥁䝣䅁䭁䝁䝙䅁䭁䅁䅅䅁䙁䅁䅁䅁杂畖䅚兂䅁䅁䅁䝷浈䅑䅯䄰䅣䅁䅅䅁䉁䅁䅁兂㉁偳䕨獋稸䅑杷允䅁䅁䅣䅁䑁䅁䅷䅁䭁䥁䝣䅁䭁䙁䝁䅁䭁䙁䝅䅁䙁䅁䅁䅁杂畖䅚兂䅁䅁䅁䝷浈䅑䅯䄱䅣䅁䅅䅁䉁䅁䅁兂䕃嘱慂汣剉䅑杷允䅁䅁䅣䅁䑁䅁䅷䅁䭁䥁䝣䅁䭁䙁䜸䅁䭁䙁䝅䅁䙁䅁䅁䅁䅄佋䅚兂䅁䅁䅁䑉浔䅑䅯眰䅣䅁䅅䅁䉁䅁䅁兂汄㉑眰摇游䅑杷允䅁䅁䅙䅁䑁䅁䅷䅁䭁䥁䝣䅁䭁䙁䜰䅁䭁䅁䅅䅁䙁䅁䅁䅁杂畖䅚权婂杂䅁允䅁䅁䅅䅁䙁佁䉺偰㑪䅚䄱䍄䉁䅁䅁睂䅁䅁䅍䅄䅁䅁䅯睨䅙䅁䅯䅗䅙䅁䅯允䅁䅁䅕䅁䅁䵁㑂欵䙁䅁䅁䅁杂敦䅚权呄睂䅁允䅁䅁䅅䅁䙁䱁⼶塑ㅶ呑䅴䍄䉁䅁䅁睂䅁䅁䅍䅄䅁䅁䅯睨䅙䅁䅯䅖䅙䅁䅯允䅁䅁䅕䅁䅁䍁䱂欵䙁䅁䅁䅁杂畖䅚权卄睂䅁允䅁䅁䅅䅁䙁䵁攰䅡䝗䌹䅆䍄䉁䅁䅁睂䅁䅁䅍䅄䅁䅁䅯睨䅙䅁䅯䅘䅙䅁䅯允䅁䅁䅕䅁䅁䝁坂欵䙁䅁䅁䅁䅄教䅚权兄睂䅁允䅁䅁䅅䅁䙁䩁䩆奊浉呗䅬䍄䉁䅁䅁杂䅁䅁䅍䅄䅁䅁䅯睨䅙䅁䅯杖䅙䅁䅯允䅁䅁䅕䅁䅁䵁㑂欵䭁䙁䝫䅁䉁䅁䅁允䅁䅁䅕畧摓硑慫䕆䵁䅉䅅䅁䝁䅁䅁睁䵁䅁䅁权䡃杂䅁权摂杂䅁权䉁䅁䅁兂䅁䅁䅁䑯洯䅑䅯兗䅙䅁䅅䅁䉁䅁䅁兂祂䌳摫䉲䬸䅑杷允䅁䅁䅣䅁䑁䅁䅷䅁䭁䥁䝣䅁䭁䙁䝁䅁䭁䙁䝅䅁䙁䅁䅁䅁杁低䅚兂䅁䅁䅁䑯洯䅑䅯䄰䅣䅁䅅䅁䉁䅁䅁兂穃䠳健䕭䵑䅑杷允䅁䅁䅙䅁䑁䅁䅷䅁䭁䥁䝣䅁䭁䙁䝕䅁䭁䅁䅅䅁䙁䅁䅁䅁䅄佥䅚权婂杂䅁允䅁䅁䅅䅁䙁䡁摢㕗奇䕮䅖䍄䉁䅁䅁杂䅁䅁䅍䅄䅁䅁䅯睨䅙䅁䅯䅢䅙䅁䅯兕䅙䅁䅕䅁䅁䭁⽁欵䭁䙁䝫䅁䉁䅁䅁允䅁䅁䅕癏剨㥢灎啃䵁䅉䅅䅁䡁䅁䅁睁䵁䅁䅁权䡃杂䅁权噂杂䅁权䉁䅁䅁兂䅁䅁䅁䑯洯䅑䅕䅁䅁䍁䱂欵䭁乁䡑䅁䉁䅁䅁允䅁䅁䅕灂汹䑚扬歑䵁䅉䅅䅁䡁䅁䅁睁䵁䅁䅁权䡃杂䅁权楂杂䅁权剂杂䅁兂䅁䅁䅁䑉浔䅑䅕䅁䅁䭁⽁欵䭁乁䡁䅁䉁䅁䅁允䅁䅁䅕桄硴刷㝸か䵁䅉䅅䅁䝁䅁䅁睁䵁䅁䅁权䡃杂䅁权灂杂䅁权䉁䅁䅁兂䅁䅁䅁䝷浈䅑䅯兗䅙䅁䅅䅁䉁䅁䅁兂煃䥓硗剨㥷䅑杷允䅁䅁䅣䅁䑁䅁䅷䅁䭁䥁䝣䅁䭁䙁䜸䅁䭁䙁䝅䅁䙁䅁䅁䅁䅄教䅚兂䅁䅁䅁䝑洳䅑䅯朰䅣䅁䅅䅁䉁䅁䅁兂䕂兒䈳剕祑䅑杷允䅁䅁䅙䅁䑁䅁䅷䅁䭁䥁䝣䅁䭁䝁䝫䅁䭁䅁䅅䅁䙁䅁䅁䅁杁低䅚权婂杂䅁允䅁䅁䅅䅁䙁䱁坂娷共橪䅆䍄䉁䅁䅁睂䅁䅁䅍䅄䅁䅁䅯睨䅙䅁䅯䅖䅙䅁䅯允䅁䅁䅕䅁䅁䵁潁欵䙁䅁䅁䅁杁低䅚权卄睂䅁允䅁䅁䅅䅁䙁䙁猱楗䕫桁䄹䍄䉁䅁䅁杂䅁䅁䅍䅄䅁䅁䅯睨䅙䅁䅯兡䅙䅁䅯允䅁䅁䅕䅁䅁䭁⽁欵䭁䙁䝫䅁䉁䅁䅁允䅁䅁䅕䐵䑅晬橅歎䵁䅉䅅䅁䡁䅁䅁睁䵁䅁䅁权䡃杂䅁权桂杂䅁权䉁䅁䅁兂䅁䅁䅁䕉浶䅑䅕䅁䅁䝁坂欵䭁乁䡍䅁䉁䅁䅁允䅁䅁䅕䥒䅦啫穃ぐ䵁䅉䅅䅁䝁䅁䅁睁䵁䅁䅁权䡃杂䅁权灂杂䅁权䉁䅁䅁兂䅁䅁䅁䕉浶䅑䅯兗䅙䅁䅅䅁䉁䅁䅁兂ㅃ华奉ㅂ㈸䅑杷允䅁䅁䅙䅁䑁䅁䅷䅁䭁䥁䝣䅁䭁䙁䜴䅁䭁䙁䝅䅁䙁䅁䅁䅁杁低䅚权婂杂䅁允䅁䅁䅅䅁䙁䕁㍚䥂兡睵䄵䍄䉁䅁䅁睂䅁䅁䅍䅄䅁䅁䅯睨䅙䅁䅯䅕䅙䅁䅯兕䅙䅁䅕䅁䅁䵁㑂欵䙁䅁䅁䅁杂敦䅚权呄睂䅁允䅁䅁䅅䅁䙁䥁戶㡓偉桁䅊䍄䉁䅁䅁睂䅁䅁䅍䅄䅁䅁䅯睨䅙䅁䅯䅘䅙䅁䅯允䅁䅁䅕䅁䅁䭁⽁欵䙁䅁䅁䅁杁⭓䅚权兄睂䅁允䅁䅁䅅䅁䙁䱁䌱癑椲穕䅤䍄䉁䅁䅁睂䅁䅁䅍䅄䅁䅁䅯睨䅙䅁䅯条䅙䅁䅯児䅁䅁䅕䅁䅁䵁桂欵䙁䅁䅁䅁䅂敢䅚权呄睂䅁允䅁䅁䅅䅁䙁䅁睲坄䑮桓䅸䍄䉁䅁䅁睂䅁䅁䅍䅄䅁䅁䅯睨䅙䅁䅯杗䅙䅁䅯兕䅙䅁䅕䅁䅁䍁ぁ欵䙁䅁䅁䅁权⭐䅚权啄睂䅁允䅁䅁䅅䅁䙁䉁临䱺捊橉䅎䍄䉁䅁䅁睂䅁䅁䅍䅄䅁䅁䅯睨䅙䅁䅯兡䅙䅁䅯允䅁䅁䅕䅁䅁䍁䱂欵䙁䅁䅁䅁杂畖䅚权呄睂䅁允䅁䅁䅅䅁䙁䙁摱䭮㑇穈䅚䍄䉁䅁䅁睂䅁䅁䅍䅄䅁䅁䅯睨䅙䅁䅯䅖䅙䅁䅯允䅁䅁䅕䅁䅁䍁ぁ欵䙁䅁䅁䅁权⭐䅚权啄睂䅁允䅁䅁䅅䅁䙁乁杩㝌㤳剱䄱䍄䉁䅁䅁睂䅁䅁䅍䅄䅁䅁䅯睨䅙䅁䅯䅡䅙䅁䅯兕䅙䅁䅕䅁䅁䵁潁欵䙁䅁䅁䅁杁低䅚权啄睂䅁允䅁䅁䅅䅁䙁䅁䩣刳甶䑔䅆䍄䉁䅁䅁杂䅁䅁䅍䅄䅁䅁䅯睨䅙䅁䅯兖䅙䅁䅯允䅁䅁䅕䅁䅁䝁㥂欵䭁䙁䝫䅁䉁䅁䅁允䅁䅁䅕䤴獊扗䴵啒䵁䅉䅅䅁䡁䅁䅁睁䵁䅁䅁权䡃杂䅁权敂杂䅁权剂杂䅁兂䅁䅁䅁䑉浔䅑䅕䅁䅁䭁⽁欵䭁乁䡉䅁䉁䅁䅁允䅁䅁䅕䵴灯か䥈啅䵁䅉䅅䅁䡁䅁䅁睁䵁䅁䅁权䡃杂䅁权潂杂䅁权剂杂䅁兂䅁䅁䅁䑯洯䅑䅕䅁䅁䍁䱂欵䭁乁䡅䅁䉁䅁䅁允䅁䅁䅕慑⽨啘㥥䐸䴸䅉䅅䅁䡁䅁䅁睁䵁䅁䅁权䡃杂䅁权兂杂䅁权剂杂䅁兂䅁䅁䅁䡷浪䅑䅕䅁䅁䝁㥂欵䭁乁䡅䅁䉁䅁䅁允䅁䅁䅕⼫晦牅つ橵䴸䅉䅅䅁䡁䅁䅁睁䵁䅁䅁权䡃杂䅁权灂杂䅁权䉁䅁䅁兂䅁䅁䅁䑯洯䅑䅕䅁䅁䍁䱂欵䭁乁䡁䅁䉁䅁䅁允䅁䅁䅕歺敨㉁䅗歎䵁䅉䅅䅁䡁䅁䅁睁䵁䅁䅁权䡃杂䅁权噂杂䅁权䉁䅁䅁兂䅁䅁䅁䝷浈䅑䅕䅁䅁䕁瑂欵䭁乁䡁䅁䉁䅁䅁允䅁䅁䅕婄䱍坭睰䕒䵁䅉䅅䅁䡁䅁䅁睁䵁䅁䅁权䡃杂䅁权奂杂䅁权䉁䅁䅁兂䅁䅁䅁䝑洳䅑䅕䅁䅁䵁㑂欵䭁乁䡁䅁䉁䅁䅁允䅁䅁䅕ㅉ余㉏楷啐䵁䅉䅅䅁䡁䅁䅁睁䵁䅁䅁权䡃杂䅁权噂杂䅁权䉁䅁䅁兂䅁䅁䅁䕉浶䅑䅕䅁䅁䝁坂欵䭁乁䡁䅁䉁䅁䅁允䅁䅁䅕硄䱆䨹⭫䕒䵁䅉䅅䅁䡁䅁䅁睁䵁䅁䅁权䡃杂䅁权浂杂䅁权䉁䅁䅁兂䅁䅁䅁䡷浪䅑䅕䅁䅁䝁㥂欵䭁乁䡁䅁䉁䅁䅁允䅁䅁䅕䭄歪牗硹き䵁䅉䅅䅁䡁䅁䅁睁䵁䅁䅁权䡃杂䅁权坂杂䅁权䉁䅁䅁兂䅁䅁䅁䑯洯䅑䅕䅁䅁䍁䱂欵䭁乁䡁䅁䉁䅁䅁允䅁䅁䅕水䅍䝪杣䕅䵁䅉䅅䅁䡁䅁䅁睁䵁䅁䅁权䡃杂䅁权慂杂䅁权剂杂䅁兂䅁䅁䅁䑯洯䅑䅕䅁䅁䍁䱂欵䭁乁䡁䅁䉁䅁䅁允䅁䅁䅕硕㑎㍍啲䕎䵁䅉䅅䅁䡁䅁䅁睁䵁䅁䅁权䡃杂䅁权兂杂䅁权剂杂䅁兂䅁䅁䅁䍷浪䅑䅕䅁䅁䍁ぁ欵䭁乁䡁䅁䉁䅁䅁允䅁䅁䅕剄畋挵祱啃䵁䅉䅅䅁䡁䅁䅁睁䵁䅁䅁权䡃杂䅁权煂杂䅁权㥁䅁䅁兂䅁䅁䅁䝷浈䅑䅕䅁䅁䕁瑂欵䭁乁䡁䅁䉁䅁䅁允䅁䅁䅕祅杤偤ㅂえ䵁䅉䅅䅁䝁䅁䅁睁䵁䅁䅁权䡃杂䅁权捂杂䅁权䉁䅁䅁兂䅁䅁䅁䡷浪䅑䅯兗䅙䅁䅅䅁䉁䅁䅁兂ぁ潧爳㈳㕫䅑杷允䅁䅁䅣䅁䑁䅁䅷䅁䭁䥁䝣䅁䭁䙁䝧䅁䭁䅁䅅䅁䙁䅁䅁䅁杁低䅚兂䅁䅁䅁䑯洯䅑䅯䄰䅣䅁䅅䅁䉁䅁䅁兂晄䕨䕉䭢㉫䅑杷允䅁䅁䅣䅁䑁䅁䅷䅁䭁䥁䝣䅁䭁䝁䝯䅁䭁䑁䄰䅁䙁䅁䅁䅁权⭐䅚兂䅁䅁䅁䕉浶䅑䅯䄰䅣䅁䅅䅁䉁䅁䅁兂䍄娶煐湖晑䅑杷允䅁䅁䅣䅁䑁䅁䅷䅁䭁䥁䝣䅁䭁䙁䝁䅁䭁䙁䝅䅁䙁䅁䅁䅁杂畖䅚兂䅁䅁䅁䝷浈䅑䅯䄰䅣䅁䅅䅁䉁䅁䅁兂呃湖橥歋剑䅑杷允䅁䅁䅣䅁䑁䅁䅷䅁䭁䥁䝣䅁䭁䝁䝙䅁䭁䅁䅅䅁䙁䅁䅁䅁䅄教䅚兂䅁䅁䅁䝑洳䅑䅯䄰䅣䅁䅅䅁䉁䅁䅁兂㉁䵧偅䝎穕䅑杷允䅁䅁䅣䅁䑁䅁䅷䅁䭁䥁䝣䅁䭁䙁䜸䅁䭁䙁䝅䅁䙁䅁䅁䅁权⭐䅚兂䅁䅁䅁䕉浶䅑䅯䄰䅣䅁䅅䅁䉁䅁䅁兂啂㥍瀴渰瑷䅑杷允䅁䅁䅣䅁䑁䅁䅷䅁䭁䥁䝣䅁䭁䝁䝷䅁䭁䙁䝅䅁䙁䅁䅁䅁䅂敢䅚兂䅁䅁䅁䡷浪䅑䅯䄱䅣䅁䅅䅁䉁䅁䅁兂灃慆捍䘹儸䅑杷允䅁䅁䅙䅁䑁䅁䅷䅁䭁䥁䝣䅁䭁䝁䝅䅁䭁䅁䅅䅁䙁䅁䅁䅁䅄佥䅚权婂杂䅁允䅁䅁䅅䅁䙁䑁㉳癁㙇歴䅆䍄䉁䅁䅁睂䅁䅁䅍䅄䅁䅁䅯睨䅙䅁䅯杖䅙䅁䅯允䅁䅁䅕䅁䅁䝁坂欵䙁䅁䅁䅁䅄教䅚权卄睂䅁允䅁䅁䅅䅁䙁䩁含樳⭥桬䅒䍄䉁䅁䅁睂䅁䅁䅍䅄䅁䅁䅯睨䅙䅁䅯杖䅙䅁䅯允䅁䅁䅕䅁䅁䵁桂欵䙁䅁䅁䅁䅂敢䅚权卄睂䅁允䅁䅁䅅䅁䙁䩁含樳⭥桬䅒䍄䉁䅁䅁睂䅁䅁䅍䅄䅁䅁䅯睨䅙䅁䅯杘䅙䅁䅯兕䅙䅁䅕䅁䅁䍁䱂欵䙁䅁䅁䅁杂畖䅚权啄睂䅁允䅁䅁䅅䅁䙁䩁奓㡶䙚杇䅰䍄䉁䅁䅁睂䅁䅁䅍䅄䅁䅁䅯睨䅙䅁䅯杗䅙䅁䅯兕䅙䅁䅕䅁䅁䵁桂欵䙁䅁䅁䅁䅂敢䅚权兄睂䅁允䅁䅁䅅䅁䙁䵁慇杕楤䑪䅖䍄䉁䅁䅁杂䅁䅁䅍䅄䅁䅁䅯睨䅙䅁䅯䅘䅙䅁䅯允䅁䅁䅕䅁䅁䝁㥂欵䭁䙁䝫䅁䉁䅁䅁允䅁䅁䅕䑰睍爸㙌歎䵁䅉䅅䅁䡁䅁䅁睁䵁䅁䅁权䡃杂䅁权歂杂䅁权䉁䅁䅁兂䅁䅁䅁䑯洯䅑䅕䅁䅁䍁䱂欵䭁乁䡉䅁䉁䅁䅁允䅁䅁䅯免䅁䅁杷允䅁䅁䅣䅁䑁䅁䅷䅁䭁䥁䝣䅁䭁䝁䝯䅁䭁䑁䄰䅁䙁䅁䅁䅁䅄佥䅚兂䅁䅁䅁䡙洳䅑䅯䄱䅣䅁䅅䅁䉁䅁䅁兂䍁牬㥖桱楣䅑杷允䅁䅁䅣䅁䑁䅁䅷䅁䭁䥁䝣䅁䭁䙁䝕䅁䭁䅁䅅䅁䙁䅁䅁䅁权⭐䅚兂䅁䅁䅁䕉浶䅑䅯䄰䅣䅁䅅䅁䉁䅁䅁兂硁潡楚祃䌱䅑杷允䅁䅁䅣䅁䑁䅁䅷䅁䭁䥁䝣䅁䭁䝁䝧䅁䭁䙁䝅䅁䙁䅁䅁䅁䅄佋䅚兂䅁䅁䅁䑉浔䅑䅯眰䅣䅁䅅䅁䉁䅁䅁兂䡄浏㝎䰰睅䅑杷允䅁䅁䅣䅁䑁䅁䅷䅁䭁䥁䝣䅁䭁䝁䝫䅁䭁䅁䅅䅁䙁䅁䅁䅁杁低䅚兂䅁䅁䅁䑯洯䅑䅯䄰䅣䅁䅅䅁䉁䅁䅁兂㡁䡊発㘷穷䅑杷允䅁䅁䅣䅁䑁䅁䅷䅁䭁䥁䝣䅁䭁䝁䝷䅁䭁䙁䝅䅁䙁䅁䅁䅁杁低䅚兂䅁䅁䅁䑯洯䅑䅯眰䅣䅁䅅䅁䉁䅁䅁兂䝁䠵⽉䉓䕁䅑杷允䅁䅁䅣䅁䑁䅁䅷䅁䭁䥁䝣䅁䭁䝁䝙䅁䭁䅁䅅䅁䙁䅁䅁䅁权⭐䅚兂䅁䅁䅁䕉浶䅑䅯眰䅣䅁䅅䅁䉁䅁䅁兂䑁䅳剅猴畉䅑杷允䅁䅁䅣䅁䑁䅁䅷䅁䭁䥁䝣䅁䭁䝁䝯䅁䭁䑁䄰䅁䙁䅁䅁䅁杂畖䅚兂䅁䅁䅁䝷浈䅑䅯䄰䅣䅁䅅䅁䉁䅁䅁兂佂は砰䨯散䅑杷允䅁䅁䅣䅁䑁䅁䅷䅁䭁䥁䝣䅁䭁䝁䝑䅁䭁䅁䅅䅁䙁䅁䅁䅁杁⭓䅚兂䅁䅁䅁䙙浢䅑䅯䄰䅣䅁䅅䅁䉁䅁䅁权硁䅁䅁䍄䉁䅁䅁睂䅁䅁䅍䅄䅁䅁䅯睨䅙䅁䅯䅚䅙䅁䅯允䅁䅁䅕䅁䅁䝁坂欵䙁䅁䅁䅁䅄教䅚权兄睂䅁允䅁䅁䅅䅁䭁䑁䅅䅁䵁䅉䅅䅁䡁䅁䅁睁䵁䅁䅁权䡃杂䅁权慂杂䅁权剂杂䅁兂䅁䅁䅁䡷浪䅑䅕䅁䅁䝁㥂欵䭁乁䡅䅁䉁䅁䅁允䅁䅁䅕晧㝢剰䭋䐴䴸䅉䅅䅁䡁䅁䅁睁䵁䅁䅁权䡃杂䅁权楂杂䅁权剂杂䅁兂䅁䅁䅁䍷浪䅑䅕䅁䅁䍁ぁ欵䭁乁䡁䅁䉁䅁䅁允䅁䅁䅕瑏硘爰婂䕋䵁䅉䅅䅁䡁䅁䅁睁䵁䅁䅁权䡃杂䅁权楂杂䅁权剂杂䅁兂䅁䅁䅁䙙浢䅑䅕䅁䅁䵁桂欵䭁乁䡅䅁䉁䅁䅁允䅁䅁䅕才煰杬摬樸䴸䅉䅅䅁䡁䅁䅁睁䵁䅁䅁权䡃杂䅁权橂杂䅁权䉁䅁䅁兂䅁䅁䅁䑯洯䅑䅕䅁䅁䍁䱂欵䭁乁䡁䅁䉁䅁䅁允䅁䅁䅕䅳爵扯敧啎䵁䅉䅅䅁䡁䅁䅁睁䵁䅁䅁权䡃杂䅁权摂杂䅁权䉁䅁䅁兂䅁䅁䅁䑉浔䅑䅕䅁䅁䭁⽁欵䭁乁䡁䅁䉁䅁䅁允䅁䅁䅕䔹䘴倳獍あ䵁䅉䅅䅁䡁䅁䅁睁䵁䅁䅁权䡃杂䅁权坂杂䅁权䉁䅁䅁兂䅁䅁䅁䡷浪䅑䅕䅁䅁䝁㥂欵䭁乁䡑䅁䉁䅁䅁允䅁䅁䅕畧摓硑慫䕆䵁䅉䅅䅁䡁䅁䅁睁䵁䅁䅁权䡃杂䅁权摂杂䅁权䉁䅁䅁兂䅁䅁䅁䝷浈䅑䅕䅁䅁䕁瑂欵䭁乁䡁䅁䉁䅁䅁允䅁䅁䅕潡䑏副潗歄䵁䅉䅅䅁䡁䅁䅁睁䵁䅁䅁权䡃杂䅁权獂杂䅁权剂杂䅁兂䅁䅁䅁䡷浪䅑䅕䅁䅁䝁㥂欵䭁乁䡅䅁䉁䅁䅁允䅁䅁䅕䕴扴奋佢䑵䴸䅉䅅䅁䡁䅁䅁睁䵁䅁䅁权䡃杂䅁权奂杂䅁权䉁䅁䅁兂䅁䅁䅁䡷浪䅑䅕䅁䅁䝁㥂欵䭁乁䡁䅁䉁䅁䅁允䅁䅁䅕浹敧确体䕐䵁䅉䅅䅁䡁䅁䅁睁䵁䅁䅁权䡃杂䅁权楂杂䅁权剂杂䅁兂䅁䅁䅁䡷浪䅑䅕䅁䅁䝁㥂欵䭁乁䡉䅁䉁䅁䅁允䅁䅁䅕䑡䥖䍴癬歍䵁䅉䅅䅁䡁䅁䅁睁䵁䅁䅁权䡃杂䅁权獂杂䅁权剂杂䅁兂䅁䅁䅁䑉浔䅑䅕䅁䅁䭁⽁欵䭁乁䡁䅁䉁䅁䅁允䅁䅁䅕䍗樹㙯偏歂䵁䅉䅅䅁䡁䅁䅁睁䵁䅁䅁权䡃杂䅁权獂杂䅁权剂杂䅁兂䅁䅁䅁䝷浈䅑䅕䅁䅁䕁瑂欵䭁乁䡁䅁䉁䅁䅁允䅁䅁䅕䕲婎欴硏䕄䵁䅉䅅䅁䡁䅁䅁睁䵁䅁䅁权䡃杂䅁权奂杂䅁权䉁䅁䅁兂䅁䅁䅁䡷浪䅑䅕䅁䅁䝁㥂欵䭁乁䡉䅁䉁䅁䅁允䅁䅁䅕䍵硉兑䰳啐䵁䅉䅅䅁䡁䅁䅁睁䵁䅁䅁权䡃杂䅁权敂杂䅁权剂杂䅁兂䅁䅁䅁䍷浪䅑䅕䅁䅁䍁ぁ欵䭁乁䡁䅁䉁䅁䅁允䅁䅁䅕㍲愫偦敬い䵁䅉䅅䅁䡁䅁䅁睁䵁䅁䅁权䡃杂䅁权時杂䅁权剂杂䅁兂䅁䅁䅁䝷浈䅑䅕䅁䅁䕁瑂欵䭁乁䡍䅁䉁䅁䅁允䅁䅁䅕婥㑢獤䉆啌䵁䅉䅅䅁䡁䅁䅁睁䵁䅁䅁权䡃杂䅁权坂杂䅁权䉁䅁䅁兂䅁䅁䅁䑉浔䅑䅕䅁䅁䭁⽁欵䭁乁䡍䅁䉁䅁䅁允䅁䅁䅕戴杔噒根歃䵁䅉䅅䅁䡁䅁䅁睁䵁䅁䅁权䡃杂䅁权坂杂䅁权䉁䅁䅁兂䅁䅁䅁䕉浶䅑䅕䅁䅁䝁坂欵䭁乁䡍䅁䉁䅁䅁允䅁䅁䅕晵硱塓欶い䵁䅉䅅䅁䡁䅁䅁睁䵁䅁䅁权䡃杂䅁权奂杂䅁权䉁䅁䅁兂䅁䅁䅁䕉浶䅑䅕䅁䅁䝁坂欵䭁乁䡅䅁䉁䅁䅁允䅁䅁䅕乚关啦卌歁䵁䅉䅅䅁䡁䅁䅁睁䵁䅁䅁权䡃杂䅁权敂杂䅁权剂杂䅁兂䅁䅁䅁䍷浪䅑䅕䅁䅁䍁ぁ欵䭁乁䡑䅁䉁䅁䅁允䅁䅁䅕湒䕣灨㝃歄䵁䅉䅅䅁䡁䅁䅁睁䵁䅁䅁权䡃杂䅁权坂杂䅁权䉁䅁䅁兂䅁䅁䅁䑯洯䅑䅕䅁䅁䍁䱂欵䭁乁䡉䅁䉁䅁䅁允䅁䅁䅕㥲祆䥯䭣啅䵁䅉䅅䅁䡁䅁䅁睁䵁䅁䅁权䡃杂䅁权潂杂䅁权剂杂䅁兂䅁䅁䅁䝷浈䅑䅕䅁䅁䕁瑂欵䭁乁䡑䅁䉁䅁䅁允䅁䅁䅕獰䠵䝂执歎䵁䅉䅅䅁䡁䅁䅁睁䵁䅁䅁权䡃杂䅁权啂杂䅁权䉁䅁䅁兂䅁䅁䅁䑉浔䅑䅕䅁䅁䭁⽁欵䭁乁䡍䅁䉁䅁䅁允䅁䅁䅕㝣塵⬫潓ぇ䵁䅉䅅䅁䡁䅁䅁睁䵁䅁䅁权䡃杂䅁权噂杂䅁权䉁䅁䅁兂䅁䅁䅁䑉浔䅑䅕䅁䅁䭁⽁欵䭁乁䡍䅁䉁䅁䅁允䅁䅁䅕佶噚摮煗䕐䵁䅉䅅䅁䡁䅁䅁睁䵁䅁䅁权䡃杂䅁权敂杂䅁权剂杂䅁兂䅁䅁䅁䡷浪䅑䅕䅁䅁䝁㥂欵䭁乁䡅䅁䉁䅁䅁允䅁䅁䅕㝗⼹扸ㅦ䑹䴸䅉䅅䅁䡁䅁䅁睁䵁䅁䅁权䡃杂䅁权橂杂䅁权䉁䅁䅁兂䅁䅁䅁䑉浔䅑䅕䅁䅁䭁⽁欵䭁乁䡍䅁䉁䅁䅁允䅁䅁䅕䵷㐫䍣獁啌䵁䅉䅅䅁䡁䅁䅁睁䵁䅁䅁权䡃杂䅁权獂杂䅁权剂杂䅁兂䅁䅁䅁䕉浶䅑䅕䅁䅁䝁坂欵䭁乁䡍䅁䉁䅁䅁允䅁䅁䅕䄱⭦啬ひ䕃䵁䅉䅅䅁䡁䅁䅁睁䵁䅁䅁权䡃杂䅁权敂杂䅁权剂杂䅁兂䅁䅁䅁䝷浈䅑䅕䅁䅁䕁瑂欵䭁乁䡉䅁䉁䅁䅁允䅁䅁䅕呪漶慂圫歄䵁䅉䅅䅁䡁䅁䅁睁䵁䅁䅁权䡃杂䅁权楂杂䅁权剂杂䅁兂䅁䅁䅁䝷浈䅑䅕䅁䅁䕁瑂欵䭁乁䡍䅁䉁䅁䅁允䅁䅁䅕兲汚敵楹䕌䵁䅉䅅䅁䡁䅁䅁睁䵁䅁䅁权䡃杂䅁权煂杂䅁权㥁䅁䅁兂䅁䅁䅁䡷浪䅑䅕䅁䅁䝁㥂欵䭁乁䡍䅁䉁䅁䅁允䅁䅁䅕套湗塏杒䕈䵁䅉䅅䅁䡁䅁䅁睁䵁䅁䅁权䡃杂䅁权奂杂䅁权䉁䅁䅁兂䅁䅁䅁䕉浶䅑䅕䅁䅁䝁坂欵䭁乁䡉䅁䉁䅁䅁允䅁䅁䅕慇乶㘯祶ぐ䵁䅉䅅䅁䡁䅁䅁睁䵁䅁䅁权䡃杂䅁权摂杂䅁权䉁䅁䅁兂䅁䅁䅁䍷浪䅑䅕䅁䅁䍁ぁ欵䭁乁䡍䅁䉁䅁䅁允䅁䅁䅕䩧慰瑴㍚ぁ䵁䅉䅅䅁䡁䅁䅁睁䵁䅁䅁权䡃杂䅁权坂杂䅁权䉁䅁䅁兂䅁䅁䅁䑯洯䅑䅕䅁䅁䍁䱂欵䭁乁䡍䅁䉁䅁䅁允䅁䅁䅕䩅扔樹焰歄䵁䅉䅅䅁䡁䅁䅁睁䵁䅁䅁权䡃杂䅁权摂杂䅁权䉁䅁䅁兂䅁䅁䅁䡷浪䅑䅕䅁䅁䝁㥂欵䭁乁䡍䅁䉁䅁䅁允䅁䅁䅕渷啶㙘䄸䕅䵁䅉䅅䅁䡁䅁䅁睁䵁䅁䅁权䡃杂䅁权摂杂䅁权䉁䅁䅁兂䅁䅁䅁䙙浢䅑䅕䅁䅁䵁桂欵䭁乁䡉䅁䉁䅁䅁允䅁䅁䅕愫潏⽍睤啅䵁䅉䅅䅁䡁䅁䅁睁䵁䅁䅁权䡃杂䅁权桂杂䅁权䉁䅁䅁兂䅁䅁䅁䝑洳䅑䅕䅁䅁䵁㑂欵䭁乁䡍䅁䉁䅁䅁允䅁䅁䅕桨挫硔䰰啑䵁䅉䅅䅁䡁䅁䅁睁䵁䅁䅁权䡃杂䅁权坂杂䅁权䉁䅁䅁兂䅁䅁䅁䝷浈䅑䅕䅁䅁䕁瑂欵䭁乁䡑䅁䉁䅁䅁允䅁䅁䅕煎焯䉲奚歅䵁䅉䅅䅁䡁䅁䅁睁䵁䅁䅁权䡃杂䅁权歂杂䅁权䉁䅁䅁兂䅁䅁䅁䝑洳䅑䅕䅁䅁䵁㑂欵䭁乁䡅䅁䉁䅁䅁允䅁䅁䅯免䅁䅁杷允䅁䅁䅣䅁䑁䅁䅷䅁䭁䥁䝣䅁䭁䙁䝁䅁䭁䙁䝅䅁䙁䅁䅁䅁权⭐䅚兂䅁䅁䅁䕉浶䅑䅯朰䅣䅁䅅䅁䉁䅁䅁兂㝁畸ㅮ䥍兙䅑杷允䅁䅁䅣䅁䑁䅁䅷䅁䭁䥁䝣䅁䭁䙁䝙䅁䭁䅁䅅䅁䙁䅁䅁䅁䅄佋䅚兂䅁䅁䅁䑉浔䅑䅯䄱䅣䅁䅅䅁䉁䅁䅁兂穄坣漲䵇䩣䅑杷允䅁䅁䅣䅁䑁䅁䅷䅁䭁䥁䝣䅁䭁䙁䝷䅁䭁䅁䅅䅁䙁䅁䅁䅁权⭐䅚兂䅁䅁䅁䕉浶䅑䅯䄱䅣䅁䅅䅁䉁䅁䅁兂慂扌䡄䙒㉉䅑杷允䅁䅁䅣䅁䑁䅁䅷䅁䭁䥁䝣䅁䭁䝁䝯䅁䭁䑁䄰䅁䙁䅁䅁䅁杂畖䅚兂䅁䅁䅁䝷浈䅑䅯眰䅣䅁䅅䅁䉁䅁䅁兂橁楧奏噗慧䅑杷允䅁䅁䅙䅁䑁䅁䅷䅁䭁䥁䝣䅁䭁䝁䝙䅁䭁䅁䅅䅁䙁䅁䅁䅁杂敦䅚权婂杂䅁允䅁䅁䅅䅁䙁偁塮猸ㅲ橷䅆䍄䉁䅁䅁睂䅁䅁䅍䅄䅁䅁䅯睨䅙䅁䅯杖䅙䅁䅯允䅁䅁䅕䅁䅁䭁⽁欵䙁䅁䅁䅁杁⭓䅚权啄睂䅁允䅁䅁䅅䅁䙁䉁穓杘決䉎䅂䍄䉁䅁䅁睂䅁䅁䅍䅄䅁䅁䅯睨䅙䅁䅯杖䅙䅁䅯允䅁䅁䅕䅁䅁䝁坂欵䙁䅁䅁䅁䅄教䅚权啄睂䅁允䅁䅁䅅䅁䙁䙁橺㥍⽫硢䅊䍄䉁䅁䅁睂䅁䅁䅍䅄䅁䅁䅯睨䅙䅁䅯睘䅙䅁䅯兕䅙䅁䅕䅁䅁䭁⽁欵䙁䅁䅁䅁杁⭓䅚权呄睂䅁允䅁䅁䅅䅁䙁䝁え坵㍏祉䅴䍄䉁䅁䅁兂䅁䅁䅍䅄䅁䅁䅯睨䅙䅁䅯兦䅙䅁䅯䅄䅁䅁䅕䅁䅁䝁㥂欵䉁䅁䅁允䅁䅁䅣䅁䅁䵁㑂欵䵁䅉䅅䅁䡁䅁䅁睁䵁䅁䅁权䡃杂䅁权兂杂䅁权剂杂䅁兂䅁䅁䅁䝷浈䅑䅕䅁䅁䕁瑂欵䭁乁䡉䅁䉁䅁䅁允䅁䅁䅕䉆儳具伹ぅ䵁䅉䅅䅁䡁䅁䅁睁䵁䅁䅁权䡃杂䅁权奂杂䅁权䉁䅁䅁兂䅁䅁䅁䙙浢䅑䅕䅁䅁䵁桂欵䭁乁䡍䅁䉁䅁䅁允䅁䅁䅕䍘䉂圸獎問䵁䅉䅅䅁䡁䅁䅁睁䵁䅁䅁权䡃杂䅁权煂杂䅁权㥁䅁䅁兂䅁䅁䅁䑉浔䅑䅕䅁䅁䭁⽁欵䭁乁䡍䅁䉁䅁䅁允䅁䅁䅕剡䅔乂潙䕇䵁䅉䅅䅁䡁䅁䅁睁䵁䅁䅁权䡃杂䅁权兂杂䅁权剂杂䅁兂䅁䅁䅁䑯洯䅑䅕䅁䅁䍁䱂欵䭁乁䡍䅁䉁䅁䅁允䅁䅁䅕桢䉳癕⽷啄䵁䅉䅅䅁䡁䅁䅁睁䵁䅁䅁权䡃杂䅁权兂杂䅁权剂杂䅁兂䅁䅁䅁䕉浶䅑䅕䅁䅁䝁坂欵䭁乁䡍䅁䉁䅁䅁允䅁䅁䅕睒卬橍㘲歄䵁䅉䅅䅁䡁䅁䅁睁䵁䅁䅁权䡃杂䅁权噂杂䅁权䉁䅁䅁兂䅁䅁䅁䙙浢䅑䅕䅁䅁䵁桂欵䭁乁䡉䅁䉁䅁䅁允䅁䅁䅕器焯〵倲げ䵁䅉䅅䅁䡁䅁䅁睁䵁䅁䅁权䡃杂䅁权歂杂䅁权䉁䅁䅁兂䅁䅁䅁䑯洯䅑䅕䅁䅁䍁䱂欵䭁乁䡑䅁䉁䅁䅁允䅁䅁䅯免䅁䅁杷允䅁䅁䅣䅁䑁䅁䅷䅁䭁䥁䝣䅁䭁䙁䜰䅁䭁䅁䅅䅁䙁䅁䅁䅁䅄佋䅚兂䅁䅁䅁䑉浔䅑䅯䄱䅣䅁䅅䅁䉁䅁䅁兂㝂獧㉒礹䕁䅑杷允䅁䅁䅣䅁䑁䅁䅷䅁䭁䥁䝣䅁䭁䙁䜰䅁䭁䅁䅅䅁䙁䅁䅁䅁䅄佥䅚兂䅁䅁䅁䡙洳䅑䅯儰䅣䅁䅅䅁䉁䅁䅁兂䝁灶㝵兘⭭睐杷允䅁䅁䅣䅁䑁䅁䅷䅁䭁䥁䝣䅁䭁䝁䝍䅁䭁䅁䅅䅁䙁䅁䅁䅁䅂敢䅚兂䅁䅁䅁䡷浪䅑䅯眰䅣䅁䅅䅁䉁䅁䅁兂㍁橢⽅㑎祷䅑杷允䅁䅁䅣䅁䑁䅁䅷䅁䭁䥁䝣䅁䭁䝁䝉䅁䭁䙁䝅䅁䙁䅁䅁䅁杁⭓䅚兂䅁䅁䅁䙙浢䅑䅯儰䅣䅁䅅䅁䉁䅁䅁兂䅂䔴杕啒灔睐杷允䅁䅁䅣䅁䑁䅁䅷䅁䭁䥁䝣䅁䭁䝁䝙䅁䭁䅁䅅䅁䙁䅁䅁䅁杁⭓䅚兂䅁䅁䅁䙙浢䅑䅯眰䅣䅁䅅䅁䉁䅁䅁兂⽂䅩地楔睉䅑杷允䅁䅁䅣䅁䑁䅁䅷䅁䭁䥁䝣䅁䭁䙁䝯䅁䭁䙁䝅䅁䙁䅁䅁䅁䅂敢䅚兂䅁䅁䅁䡷浪䅑䅯朰䅣䅁䅅䅁䉁䅁䅁兂穃橪慍㑏㐴䅑杷允䅁䅁䅣䅁䑁䅁䅷䅁䭁䥁䝣䅁䭁䝁䝙䅁䭁䅁䅅䅁䙁䅁䅁䅁杁低䅚兂䅁䅁䅁䑯洯䅑䅯朰䅣䅁䅅䅁䉁䅁䅁兂穁稫䝸塥眴䅑杷允䅁䅁䅣䅁䑁䅁䅷䅁䭁䥁䝣䅁䭁䝁䝧䅁䭁䙁䝅䅁䙁䅁䅁䅁䅄教䅚兂䅁䅁䅁䝑洳䅑䅯朰䅣䅁䅅䅁䉁䅁䅁兂㍄扚改䝧㙍䅑杷允䅁䅁䅣䅁䑁䅁䅷䅁䭁䥁䝣䅁䭁䝁䝍䅁䭁䅁䅅䅁䙁䅁䅁䅁杂畖䅚兂䅁䅁䅁䝷浈䅑䅯儰䅣䅁䅅䅁䉁䅁䅁兂乄剔䵑䈯㉢睐杷允䅁䅁䅣䅁䑁䅁䅷䅁䭁䥁䝣䅁䭁䝁䝉䅁䭁䙁䝅䅁䙁䅁䅁䅁权⭐䅚兂䅁䅁䅁䕉浶䅑䅯䄱䅣䅁䅅䅁䉁䅁䅁兂㉂硄㍚ぐ癅䅑杷允䅁䅁䅣䅁䑁䅁䅷䅁䭁䥁䝣䅁䭁䙁䝁䅁䭁䙁䝅䅁䙁䅁䅁䅁权⭐䅚兂䅁䅁䅁䕉浶䅑䅯䄱䅣䅁䅅䅁䉁䅁䅁兂睁婭㕏㈶倰䅑杷允䅁䅁䅣䅁䑁䅁䅷䅁䭁䥁䝣䅁䭁䙁䜰䅁䭁䅁䅅䅁䙁䅁䅁䅁权⭐䅚兂䅁䅁䅁䕉浶䅑䅯儰䅣䅁䅅䅁䉁䅁䅁兂塁穑㐵煂䉦睐杷允䅁䅁䅣䅁䑁䅁䅷䅁䭁䥁䝣䅁䭁䝁䝯䅁䭁䑁䄰䅁䙁䅁䅁䅁䅄佋䅚兂䅁䅁䅁䑉浔䅑䅯朰䅣䅁䅅䅁䉁䅁䅁兂䍄橐㉸䵅慣䅑杷允䅁䅁䅣䅁䑁䅁䅷䅁䭁䥁䝣䅁䭁䙁䝁䅁䭁䙁䝅䅁䙁䅁䅁䅁杁⭓䅚兂䅁䅁䅁䙙浢䅑䅯䄱䅣䅁䅅䅁䉁䅁䅁兂啃⽂穙⭭免䅑杷允䅁䅁䅣䅁䑁䅁䅷䅁䭁䥁䝣䅁䭁䙁䝁䅁䭁䙁䝅䅁䙁䅁䅁䅁权⭐䅚兂䅁䅁䅁䕉浶䅑䅯儰䅣䅁䅅䅁䉁䅁䅁兂睄㍩塵䙧䉺睐杷允䅁䅁䅣䅁䑁䅁䅷䅁䭁䥁䝣䅁䭁䝁䝉䅁䭁䙁䝅䅁䙁䅁䅁䅁䅄佋䅚兂䅁䅁䅁䑉浔䅑䅯眰䅣䅁䅅䅁䉁䅁䅁兂桄㝇坤祁游䅑杷允䅁䅁䅣䅁䑁䅁䅷䅁䭁䥁䝣䅁䭁䙁䝁䅁䭁䙁䝅䅁䙁䅁䅁䅁杂畖䅚兂䅁䅁䅁䝷浈䅑䅯儰䅣䅁䅅䅁䉁䅁䅁兂潂浄䵧塪兲睐杷允䅁䅁䅣䅁䑁䅁䅷䅁䭁䥁䝣䅁䭁䙁䜰䅁䭁䅁䅅䅁䙁䅁䅁䅁䅄佥䅚兂䅁䅁䅁䡙洳䅑䅯䄱䅣䅁䅅䅁䉁䅁䅁兂剁浈挰晳兙䅑杷允䅁䅁䅣䅁䑁䅁䅷䅁䭁䥁䝣䅁䭁䝁䝍䅁䭁䅁䅅䅁䙁䅁䅁䅁䅄教䅚兂䅁䅁䅁䝑洳䅑䅯䄱䅣䅁䅅䅁䉁䅁䅁兂䅃娱橅坮硫䅑杷允䅁䅁䅕䅁䑁䅁䅷䅁䭁䥁䝣䅁䭁䉁䅙䅁䙁䅁䅁䅁杂敦䅚权婂杂䅁允䅁䅁䅅䅁啁䝁瑢橴䅣䅁䅁䍄䉁䅁䅁睂䅁䅁䅍䅄䅁䅁䅯睨䅙䅁䅯睙䅙䅁䅯允䅁䅁䅕䅁䅁䍁ぁ欵䙁䅁䅁䅁权⭐䅚权啄睂䅁允䅁䅁䅅䅁䙁䕁权㉍呬穭䅖䍄䉁䅁䅁睂䅁䅁䅍䅄䅁䅁䅯睨䅙䅁䅯杚䅙䅁䅯允䅁䅁䅕䅁䅁䝁坂欵䙁䅁䅁䅁䅄教䅚权剄睂䅁允䅁䅁䅅䅁䙁䅁⭤灺慧偖⽍䍄䉁䅁䅁睂䅁䅁䅍䅄䅁䅁䅯睨䅙䅁䅯杚䅙䅁䅯允䅁䅁䅕䅁䅁䍁ぁ欵䙁䅁䅁䅁权⭐䅚权呄睂䅁允䅁䅁䅅䅁䙁䍁晹堵睬祐䅴䍄䉁䅁䅁睂䅁䅁䅍䅄䅁䅁䅯睨䅙䅁䅯睘䅙䅁䅯兕䅙䅁䅕䅁䅁䍁ぁ欵䙁䅁䅁䅁权⭐䅚权卄睂䅁允䅁䅁䅅䅁䙁䵁浰慌吲䌲䄵䍄䉁䅁䅁睂䅁䅁䅍䅄䅁䅁䅯睨䅙䅁䅯䅢䅙䅁䅯兕䅙䅁䅕䅁䅁䭁⽁欵䙁䅁䅁䅁杁⭓䅚权卄睂䅁允䅁䅁䅅䅁䙁䭁捋䘯塭䅓䅴䍄䉁䅁䅁睂䅁䅁䅍䅄䅁䅁䅯睨䅙䅁䅯睘䅙䅁䅯兕䅙䅁䅕䅁䅁䵁㑂欵䙁䅁䅁䅁杂敦䅚权剄睂䅁允䅁䅁䅅䅁䙁䱁㡮奯䑱㥵⽷䍄䉁䅁䅁睂䅁䅁䅍䅄䅁䅁䅯睨䅙䅁䅯杙䅙䅁䅯兕䅙䅁䅕䅁䅁䝁坂欵䙁䅁䅁䅁䅄教䅚权啄睂䅁允䅁䅁䅅䅁䙁佁㙭桓䉨橱䅂䍄䉁䅁䅁睂䅁䅁䅍䅄䅁䅁䅯睨䅙䅁䅯䅗䅙䅁䅯允䅁䅁䅕䅁䅁䭁⽁欵䙁䅁䅁䅁杁⭓䅚权剄睂䅁允䅁䅁䅅䅁䙁䵁䡱晓婮⭩⽯䍄䉁䅁䅁睂䅁䅁䅍䅄䅁䅁䅯睨䅙䅁䅯杘䅙䅁䅯兕䅙䅁䅕䅁䅁䕁瑂欵䙁䅁䅁䅁䅄佥䅚权兄睂䅁允䅁䅁䅅䅁䙁䥁䉚煵牓睧䅴䍄䉁䅁䅁睂䅁䅁䅍䅄䅁䅁䅯睨䅙䅁䅯兙䅙䅁䅯允䅁䅁䅕䅁䅁䵁潁欵䙁䅁䅁䅁杁低䅚权兄睂䅁允䅁䅁䅅䅁䙁䑁啧浫獅穊䅒䍄䉁䅁䅁睂䅁䅁䅍䅄䅁䅁䅯睨䅙䅁䅯杚䅙䅁䅯允䅁䅁䅕䅁䅁䵁桂欵䙁䅁䅁䅁䅂敢䅚权剄睂䅁允䅁䅁䅅䅁䙁偁浒䝐ひ倳⽣䍄䉁䅁䅁兂䅁䅁䅍䅄䅁䅁䅯睨䅙䅁䅯睬䅣䅁䅕䅁䅁䵁歂欵䭁䩁䥳䅁䉁䅁䅁允䅁䅁䅕䥘䌯匹䥨䕣䵁䅉䅅䅁䡁䅁䅁睁䵁䅁䅁权䡃杂䅁权楂杂䅁权剂杂䅁兂䅁䅁䅁䍷浪䅑䅕䅁䅁䍁ぁ欵䭁乁䡉䅁䉁䅁䅁允䅁䅁䅕㝘摸渹欲歋䵁䅉䅅䅁䡁䅁䅁睁䵁䅁䅁权䡃杂䅁权煂杂䅁权㥁䅁䅁兂䅁䅁䅁䕉浶䅑䅕䅁䅁䝁坂欵䭁乁䡉䅁䉁䅁䅁允䅁䅁䅕呴乎歫唴䕉䵁䅉䅅䅁䡁䅁䅁睁䵁䅁䅁权䡃杂䅁权時杂䅁权剂杂䅁兂䅁䅁䅁䕉浶䅑䅕䅁䅁䝁坂欵䭁乁䡍䅁䉁䅁䅁允䅁䅁䅕煅挹塊硧䕌䵁䅉䅅䅁䡁䅁䅁睁䵁䅁䅁权䡃杂䅁权灂杂䅁权䉁䅁䅁兂䅁䅁䅁䑉浔䅑䅕䅁䅁䭁⽁欵䭁乁䡉䅁䉁䅁䅁允䅁䅁䅕䥎楅橆杆歎䵁䅉䅅䅁䡁䅁䅁睁䵁䅁䅁权䡃杂䅁权捂杂䅁权䉁䅁䅁兂䅁䅁䅁䙙浢䅑䅕䅁䅁䵁桂欵䭁乁䡉䅁䉁䅁䅁允䅁䅁䅕䕪⽬㑌䑘く䵁䅉䅅䅁䡁䅁䅁睁䵁䅁䅁权䡃杂䅁权時杂䅁权剂杂䅁兂䅁䅁䅁䑉浔䅑䅕䅁䅁䭁⽁欵䭁乁䡑䅁䉁䅁䅁允䅁䅁䅕䍸㉪琸䅹か䵁䅉䅅䅁䡁䅁䅁睁䵁䅁䅁权䡃杂䅁权歂杂䅁权䉁䅁䅁兂䅁䅁䅁䝑洳䅑䅕䅁䅁䵁㑂欵䭁乁䡍䅁䉁䅁䅁允䅁䅁䅯免䅁䅁杷允䅁䅁䅣䅁䑁䅁䅷䅁䭁䥁䝣䅁䭁䙁䝙䅁䭁䅁䅅䅁䙁䅁䅁䅁䅂敢䅚兂䅁䅁䅁䡷浪䅑䅯眰䅣䅁䅅䅁䉁䅁䅁兂䉄扲㕴汱呍䅑杷允䅁䅁䅣䅁䑁䅁䅷䅁䭁䥁䝣䅁䭁䙁䜴䅁䭁䙁䝅䅁䙁䅁䅁䅁䅄佥䅚兂䅁䅁䅁䡙洳䅑䅯朰䅣䅁䅅䅁䉁䅁䅁兂䡁㝒婫奦佑䅑杷允䅁䅁䅣䅁䑁䅁䅷䅁䭁䥁䝣䅁䭁䙁䜸䅁䭁䙁䝅䅁䙁䅁䅁䅁权⭐䅚兂䅁䅁䅁䕉浶䅑䅯䄱䅣䅁䅅䅁䉁䅁䅁兂㥁塮啣䝴瑕䅑杷允䅁䅁䅣䅁䑁䅁䅷䅁䭁䥁䝣䅁䭁䝁䝑䅁䭁䅁䅅䅁䙁䅁䅁䅁䅂敢䅚兂䅁䅁䅁䡷浪䅑䅯䄰䅣䅁䅅䅁䉁䅁䅁权硁䅁䅁䍄䉁䅁䅁睂䅁䅁䅍䅄䅁䅁䅯睨䅙䅁䅯睘䅙䅁䅯兕䅙䅁䅕䅁䅁䵁桂欵䙁䅁䅁䅁䅂敢䅚权啄睂䅁允䅁䅁䅅䅁䙁䱁祪穣扊祩䄹䍄䉁䅁䅁睂䅁䅁䅍䅄䅁䅁䅯睨䅙䅁䅯睘䅙䅁䅯兕䅙䅁䅕䅁䅁䍁ぁ欵䙁䅁䅁䅁权⭐䅚权剄睂䅁允䅁䅁䅅䅁䙁䭁㤵晏䍑⭑⽯䍄䉁䅁䅁睂䅁䅁䅍䅄䅁䅁䅯睨䅙䅁䅯睘䅙䅁䅯兕䅙䅁䅕䅁䅁䍁䱂欵䙁䅁䅁䅁杂畖䅚权剄睂䅁允䅁䅁䅅䅁䙁佁婦夷慇⭢⼴䍄䉁䅁䅁睂䅁䅁䅍䅄䅁䅁䅯睨䅙䅁䅯兖䅙䅁䅯允䅁䅁䅕䅁䅁䍁䱂欵䙁䅁䅁䅁杂畖䅚权剄睂䅁允䅁䅁䅅䅁䙁䕁穉摙佗末䅚䍄䉁䅁䅁睂䅁䅁䅍䅄䅁䅁䅯睨䅙䅁䅯䅚䅙䅁䅯允䅁䅁䅕䅁䅁䵁桂欵䙁䅁䅁䅁䅂敢䅚权呄睂䅁允䅁䅁䅅䅁䭁䑁䅅䅁䵁䅉䅅䅁䡁䅁䅁睁䵁䅁䅁权䡃杂䅁权噂杂䅁权䉁䅁䅁兂䅁䅁䅁䑯洯䅑䅕䅁䅁䍁䱂欵䭁乁䡍䅁䉁䅁䅁允䅁䅁䅕剱㙈塭㍱䕑䵁䅉䅅䅁䡁䅁䅁睁䵁䅁䅁权䡃杂䅁权敂杂䅁权剂杂䅁兂䅁䅁䅁䝑洳䅑䅕䅁䅁䵁㑂欵䭁乁䡑䅁䉁䅁䅁允䅁䅁䅕慬䥓ㅍㅈ歃䵁䅉䅅䅁䡁䅁䅁睁䵁䅁䅁权䡃杂䅁权獂杂䅁权剂杂䅁兂䅁䅁䅁䍷浪䅑䅕䅁䅁䍁ぁ欵䭁乁䡍䅁䉁䅁䅁允䅁䅁䅕卂琹㕥乍ぁ䵁䅉䅅䅁䡁䅁䅁睁䵁䅁䅁权䡃杂䅁权慂杂䅁权剂杂䅁兂䅁䅁䅁䝷浈䅑䅕䅁䅁䕁瑂欵䭁乁䡍䅁䉁䅁䅁允䅁䅁䅕䕮䙩⽣祤き䵁䅉䅅䅁䡁䅁䅁睁䵁䅁䅁权䡃杂䅁权潂杂䅁权剂杂䅁兂䅁䅁䅁䙙浢䅑䅕䅁䅁䵁桂欵䭁乁䡉䅁䉁䅁䅁允䅁䅁䅕㈹⽗潘橂歏䵁䅉䅅䅁䡁䅁䅁睁䵁䅁䅁权䡃杂䅁权灂杂䅁权䉁䅁䅁兂䅁䅁䅁䝷浈䅑䅕䅁䅁䕁瑂欵䭁乁䡍䅁䉁䅁䅁允䅁䅁䅕捇穩㝹慤歎䵁䅉䅅䅁䡁䅁䅁睁䵁䅁䅁权䡃杂䅁权奂杂䅁权䉁䅁䅁兂䅁䅁䅁䝷浈䅑䅕䅁䅁䕁瑂欵䭁乁䡑䅁䉁䅁䅁允䅁䅁䅕〲䙹䍥䍑く䵁䅉䅅䅁䡁䅁䅁睁䵁䅁䅁权䡃杂䅁权奂杂䅁权䉁䅁䅁兂䅁䅁䅁䑉浔䅑䅕䅁䅁䭁⽁欵䭁乁䡅䅁䉁䅁䅁允䅁䅁䅕啩摢坲乮䐹䴸䅉䅅䅁䡁䅁䅁睁䵁䅁䅁权䡃杂䅁权楂杂䅁权剂杂䅁兂䅁䅁䅁䝷浈䅑䅕䅁䅁䕁瑂欵䭁乁䡉䅁䉁䅁䅁允䅁䅁䅕呤䩓䨴⭈歍䵁䅉䅅䅁䡁䅁䅁睁䵁䅁䅁权䡃杂䅁权潂杂䅁权剂杂䅁兂䅁䅁䅁䑉浔䅑䅕䅁䅁䭁⽁欵䭁乁䡉䅁䉁䅁䅁允䅁䅁䅕歬䕶浃啁歎䵁䅉䅅䅁䡁䅁䅁睁䵁䅁䅁权䡃杂䅁权慂杂䅁权剂杂䅁兂䅁䅁䅁䙙浢䅑䅕䅁䅁䵁桂欵䭁乁䡉䅁䉁䅁䅁允䅁䅁䅕積敖䱮祒䕏䵁䅉䅅䅁䡁䅁䅁睁䵁䅁䅁权䡃杂䅁权慂杂䅁权剂杂䅁兂䅁䅁䅁䡷浪䅑䅕䅁䅁䝁㥂欵䭁乁䡁䅁䉁䅁䅁允䅁䅁䅕硙䄴⭍䌹ぎ䵁䅉䅅䅁䡁䅁䅁睁䵁䅁䅁权䡃杂䅁权歂杂䅁权䉁䅁䅁兂䅁䅁䅁䡷浪䅑䅕䅁䅁䝁㥂欵䭁乁䡑䅁䉁䅁䅁允䅁䅁䅯免䅁䅁杷允䅁䅁䅣䅁䑁䅁䅷䅁䭁䥁䝣䅁䭁䝁䝉䅁䭁䙁䝅䅁䙁䅁䅁䅁䅂敢䅚兂䅁䅁䅁䡷浪䅑䅯儰䅣䅁䅅䅁䉁䅁䅁兂硂婫湰䉲摮睐杷允䅁䅁䅣䅁䑁䅁䅷䅁䭁䥁䝣䅁䭁䝁䝫䅁䭁䅁䅅䅁䙁䅁䅁䅁䅄佋䅚兂䅁䅁䅁䑉浔䅑䅯䄱䅣䅁䅅䅁䉁䅁䅁兂癃唶䉆啋硉䅑杷允䅁䅁䅣䅁䑁䅁䅷䅁䭁䥁䝣䅁䭁䙁䝯䅁䭁䙁䝅䅁䙁䅁䅁䅁䅄教䅚兂䅁䅁䅁䝑洳䅑䅯朰䅣䅁䅅䅁䉁䅁䅁兂穁噎挶䡴㑉䅑杷允䅁䅁䅣䅁䑁䅁䅷䅁䭁䥁䝣䅁䭁䙁䝯䅁䭁䙁䝅䅁䙁䅁䅁䅁䅄佋䅚兂䅁䅁䅁䑉浔䅑䅯眰䅣䅁䅅䅁䉁䅁䅁兂ぃ娹䥱汉睯䅑杷允䅁䅁䅣䅁䑁䅁䅷䅁䭁䥁䝣䅁䭁䙁䝯䅁䭁䙁䝅䅁䙁䅁䅁䅁权⭐䅚兂䅁䅁䅁䕉浶䅑䅯眰䅣䅁䅅䅁䉁䅁䅁兂䍁䕱甹䑬穑䅑杷允䅁䅁䅣䅁䑁䅁䅷䅁䭁䥁䝣䅁䭁䙁䝯䅁䭁䙁䝅䅁䙁䅁䅁䅁杂畖䅚兂䅁䅁䅁䝷浈䅑䅯眰䅣䅁䅅䅁䉁䅁䅁兂捁㌸䄰攴稰䅑杷允䅁䅁䅣䅁䑁䅁䅷䅁䭁䥁䝣䅁䭁䝁䝅䅁䭁䅁䅅䅁䙁䅁䅁䅁权⭐䅚兂䅁䅁䅁䕉浶䅑䅯朰䅣䅁䅅䅁䉁䅁䅁兂⭂丵歡ㄲ䉰䅑杷允䅁䅁䅣䅁䑁䅁䅷䅁䭁䥁䝣䅁䭁䝁䝅䅁䭁䅁䅅䅁䙁䅁䅁䅁杂畖䅚兂䅁䅁䅁䝷浈䅑䅯朰䅣䅁䅅䅁䉁䅁䅁兂ㅁ硬䵳啤䩸䅑杷允䅁䅁䅣䅁䑁䅁䅷䅁䭁䥁䝣䅁䭁䝁䝷䅁䭁䙁䝅䅁䙁䅁䅁䅁权⭐䅚兂䅁䅁䅁䕉浶䅑䅯儰䅣䅁䅅䅁䉁䅁䅁兂佄捕䭭噋䉶睐杷允䅁䅁䅣䅁䑁䅁䅷䅁䭁䥁䝣䅁䭁䙁䝯䅁䭁䙁䝅䅁䙁䅁䅁䅁䅄教䅚兂䅁䅁䅁䝑洳䅑䅯䄱䅣䅁䅅䅁䉁䅁䅁兂㕄桎橗晑で䅑杷允䅁䅁䅣䅁䑁䅁䅷䅁䭁䥁䝣䅁䭁䙁䝯䅁䭁䙁䝅䅁䙁䅁䅁䅁杁⭓䅚兂䅁䅁䅁䙙浢䅑䅯儰䅣䅁䅅䅁䉁䅁䅁兂䵃㄰啌圱硪睐杷允䅁䅁䅣䅁䑁䅁䅷䅁䭁䥁䝣䅁䭁䝁䝷䅁䭁䙁䝅䅁䙁䅁䅁䅁䅄教䅚兂䅁䅁䅁䝑洳䅑䅯儰䅣䅁䅅䅁䉁䅁䅁兂䍁奺⽌捃剢睐杷允䅁䅁䅣䅁䑁䅁䅷䅁䭁䥁䝣䅁䭁䝁䝫䅁䭁䅁䅅䅁䙁䅁䅁䅁杁⭓䅚兂䅁䅁䅁䙙浢䅑䅯儰䅣䅁䅅䅁䉁䅁䅁兂䝂㌴到㥬㜳睐杷允䅁䅁䅣䅁䑁䅁䅷䅁䭁䥁䝣䅁䭁䝁䝅䅁䭁䅁䅅䅁䙁䅁䅁䅁杁低䅚兂䅁䅁䅁䑯洯䅑䅯䄰䅣䅁䅅䅁䉁䅁䅁兂权穓な獆ㅁ䅑杷允䅁䅁䅣䅁䑁䅁䅷䅁䭁䥁䝣䅁䭁䝁䝅䅁䭁䅁䅅䅁䙁䅁䅁䅁杁⭓䅚兂䅁䅁䅁䙙浢䅑䅯䄰䅣䅁䅅䅁䉁䅁䅁兂敁橰杩慐䍸䅑杷允䅁䅁䅣䅁䑁䅁䅷䅁䭁䥁䝣䅁䭁䝁䝅䅁䭁䅁䅅䅁䙁䅁䅁䅁杂畖䅚兂䅁䅁䅁䝷浈䅑䅯䄰䅣䅁䅅䅁䉁䅁䅁兂䉃䝎䥷㔶䙸䅑杷允䅁䅁䅣䅁䑁䅁䅷䅁䭁䥁䝣䅁䭁䝁䝉䅁䭁䙁䝅䅁䙁䅁䅁䅁䅂敢䅚兂䅁䅁䅁䡷浪䅑䅯眰䅣䅁䅅䅁䉁䅁䅁兂橁欱䰷摓睑䅑杷允䅁䅁䅣䅁䑁䅁䅷䅁䭁䥁䝣䅁䭁䝁䝧䅁䭁䙁䝅䅁䙁䅁䅁䅁杁⭓䅚兂䅁䅁䅁䙙浢䅑䅯眰䅣䅁䅅䅁䉁䅁䅁兂慁坧敗支き䅑杷允䅁䅁䅣䅁䑁䅁䅷䅁䭁䥁䝣䅁䭁䝁䝧䅁䭁䙁䝅䅁䙁䅁䅁䅁杂畖䅚兂䅁䅁䅁䝷浈䅑䅯䄱䅣䅁䅅䅁䉁䅁䅁兂慄䕗⽆半㍷䅑杷允䅁䅁䅣䅁䑁䅁䅷䅁䭁䥁䝣䅁䭁䙁䜰䅁䭁䅁䅅䅁䙁䅁䅁䅁杁⭓䅚兂䅁䅁䅁䙙浢䅑䅯眰䅣䅁䅅䅁䉁䅁䅁兂㉄呦䥨䱩䩉䅑杷允䅁䅁䅣䅁䑁䅁䅷䅁䭁䥁䝣䅁䭁䙁䜰䅁䭁䅁䅅䅁䙁䅁䅁䅁䅂敢䅚兂䅁䅁䅁䡷浪䅑䅯䄱䅣䅁䅅䅁䉁䅁䅁兂睄焲乕ㅨ剕䅑杷允䅁䅁䅣䅁䑁䅁䅷䅁䭁䥁䝣䅁䭁䝁䝧䅁䭁䙁䝅䅁䙁䅁䅁䅁䅄教䅚兂䅁䅁䅁䝑洳䅑䅯儰䅣䅁䅅䅁䉁䅁䅁兂奂湨何㝖⽦睐杷允䅁䅁䅣䅁䑁䅁䅷䅁䭁䥁䝣䅁䭁䝁䝅䅁䭁䅁䅅䅁䙁䅁䅁䅁杁低䅚兂䅁䅁䅁䑯洯䅑䅯䄱䅣䅁䅅䅁䉁䅁䅁兂浃䥙稲唶ㅷ䅑杷允䅁䅁䅣䅁䑁䅁䅷䅁䭁䥁䝣䅁䭁䝁䝯䅁䭁䑁䄰䅁䙁䅁䅁䅁䅄佥䅚兂䅁䅁䅁䡙洳䅑䅯朰䅣䅁䅅䅁䉁䅁䅁兂穁敏癸椵橕䅑杷允䅁䅁䅣䅁䑁䅁䅷䅁䭁䥁䝣䅁䭁䝁䝷䅁䭁䙁䝅䅁䙁䅁䅁䅁杁低䅚兂䅁䅁䅁䑯洯䅑䅯儰䅣䅁䅅䅁䉁䅁䅁兂䱁牱呴坎䥘睐杷允䅁䅁䅣䅁䑁䅁䅷䅁䭁䥁䝣䅁䭁䝁䝅䅁䭁䅁䅅䅁䙁䅁䅁䅁杁⭓䅚兂䅁䅁䅁䙙浢䅑䅯䄱䅣䅁䅅䅁䉁䅁䅁兂呂杂漵圶䑊䅑杷允䅁䅁䅣䅁䑁䅁䅷䅁䭁䥁䝣䅁䭁䝁䝅䅁䭁䅁䅅䅁䙁䅁䅁䅁䅄教䅚兂䅁䅁䅁䝑洳䅑䅯䄱䅣䅁䅅䅁䉁䅁䅁兂乃䥮㥕昷䕚䅑杷允䅁䅁䅙䅁䑁䅁䅷䅁䭁䥁䝣䅁䭁䝁䝫䅁䭁䅁䅅䅁䙁䅁䅁䅁䅄佥䅚权婂杂䅁允䅁䅁䅅䅁䙁䙁卒㙊䩃䑳䅰䍄䉁䅁䅁睂䅁䅁䅍䅄䅁䅁䅯睨䅙䅁䅯兙䅙䅁䅯允䅁䅁䅕䅁䅁䍁ぁ欵䙁䅁䅁䅁权⭐䅚权剄睂䅁允䅁䅁䅅䅁䙁䭁敯坕慡昳⽕䍄䉁䅁䅁睂䅁䅁䅍䅄䅁䅁䅯睨䅙䅁䅯䅘䅙䅁䅯允䅁䅁䅕䅁䅁䝁坂欵䙁䅁䅁䅁䅄教䅚权呄睂䅁允䅁䅁䅅䅁䙁䥁⼴摕睭橩䅚䍄䉁䅁䅁睂䅁䅁䅍䅄䅁䅁䅯睨䅙䅁䅯兙䅙䅁䅯允䅁䅁䅕䅁䅁䭁⽁欵䙁䅁䅁䅁杁⭓䅚权剄睂䅁允䅁䅁䅅䅁䙁䉁䡘桥㡚睋䅰䍄䉁䅁䅁睂䅁䅁䅍䅄䅁䅁䅯睨䅙䅁䅯兘䅙䅁䅯允䅁䅁䅕䅁䅁䍁䱂欵䙁䅁䅁䅁杂畖䅚权卄睂䅁允䅁䅁䅅䅁䙁䕁㑇杁ㅲ䅎䄹䍄䉁䅁䅁睂䅁䅁䅍䅄䅁䅁䅯睨䅙䅁䅯睙䅙䅁䅯允䅁䅁䅕䅁䅁䍁䱂欵䙁䅁䅁䅁杂畖䅚权啄睂䅁允䅁䅁䅅䅁䙁䕁坎㍴佰樰䅨䍄䉁䅁䅁睂䅁䅁䅍䅄䅁䅁䅯睨䅙䅁䅯䅡䅙䅁䅯兕䅙䅁䅕䅁䅁䵁潁欵䙁䅁䅁䅁杁低䅚权卄睂䅁允䅁䅁䅅䅁䙁偁坫晉塦稵䅊䍄䉁䅁䅁睂䅁䅁䅍䅄䅁䅁䅯睨䅙䅁䅯䅡䅙䅁䅯兕䅙䅁䅕䅁䅁䍁䱂欵䙁䅁䅁䅁杂畖䅚权卄睂䅁允䅁䅁䅅䅁䙁乁奍䙕佤味䅨䍄䉁䅁䅁睂䅁䅁䅍䅄䅁䅁䅯睨䅙䅁䅯兘䅙䅁䅯允䅁䅁䅕䅁䅁䭁⽁欵䙁䅁䅁䅁杁⭓䅚权卄睂䅁允䅁䅁䅅䅁䙁䩁樯㡯婕睉䅸䍄䉁䅁䅁睂䅁䅁䅍䅄䅁䅁䅯睨䅙䅁䅯杚䅙䅁䅯允䅁䅁䅕䅁䅁䵁㑂欵䙁䅁䅁䅁杂敦䅚权卄睂䅁允䅁䅁䅅䅁䙁䉁睙噧㍴稯䅒䍄䉁䅁䅁睂䅁䅁䅍䅄䅁䅁䅯睨䅙䅁䅯䅡䅙䅁䅯兕䅙䅁䅕䅁䅁䍁䱂欵䙁䅁䅁䅁杂畖䅚权啄睂䅁允䅁䅁䅅䅁䙁䕁⭎牏匲積䅤䍄䉁䅁䅁睂䅁䅁䅍䅄䅁䅁䅯睨䅙䅁䅯䅡䅙䅁䅯兕䅙䅁䅕䅁䅁䍁ぁ欵䙁䅁䅁䅁权⭐䅚权剄睂䅁允䅁䅁䅅䅁䙁䝁乕晲扺⽂⽍䍄䉁䅁䅁睂䅁䅁䅍䅄䅁䅁䅯睨䅙䅁䅯䅡䅙䅁䅯兕䅙䅁䅕䅁䅁䍁䱂欵䙁䅁䅁䅁杂畖䅚权剄睂䅁允䅁䅁䅅䅁䙁䡁晗あ乂瘷⽉䍄䉁䅁䅁睂䅁䅁䅍䅄䅁䅁䅯睨䅙䅁䅯䅡䅙䅁䅯兕䅙䅁䅕䅁䅁䵁㑂欵䙁䅁䅁䅁杂敦䅚权卄睂䅁允䅁䅁䅅䅁䙁䩁⽌ㅊ⽅稰䅬䍄䉁䅁䅁睂䅁䅁䅍䅄䅁䅁䅯睨䅙䅁䅯杙䅙䅁䅯兕䅙䅁䅕䅁䅁䍁䱂欵䙁䅁䅁䅁杂畖䅚权啄睂䅁允䅁䅁䅅䅁䙁䩁硷塍昴穮䅂䍄䉁䅁䅁睂䅁䅁䅍䅄䅁䅁䅯睨䅙䅁䅯䅖䅙䅁䅯允䅁䅁䅕䅁䅁䵁桂欵䙁䅁䅁䅁䅂敢䅚权啄睂䅁允䅁䅁䅅䅁䙁䅁䰲摕慦祩䅆䍄䉁䅁䅁杂䅁䅁䅍䅄䅁䅁䅯睨䅙䅁䅯条䅙䅁䅯児䅁䅁䅕䅁䅁䵁㑂欵䭁䙁䝫䅁䉁䅁䅁允䅁䅁䅕杋䵧䌯牉歉䵁䅉䅅䅁䡁䅁䅁睁䵁䅁䅁权䡃杂䅁权噂杂䅁权䉁䅁䅁兂䅁䅁䅁䍷浪䅑䅕䅁䅁䍁ぁ欵䭁乁䡍䅁䉁䅁䅁允䅁䅁䅕穈㙆煢版歏䵁䅉䅅䅁䡁䅁䅁睁䵁䅁䅁权䡃杂䅁权啂杂䅁权䉁䅁䅁兂䅁䅁䅁䙙浢䅑䅕䅁䅁䵁桂欵䭁乁䡉䅁䉁䅁䅁允䅁䅁䅕畫偡坡椱䕊䵁䅉䅅䅁䡁䅁䅁睁䵁䅁䅁权䡃杂䅁权啂杂䅁权䉁䅁䅁兂䅁䅁䅁䑯洯䅑䅕䅁䅁䍁䱂欵䭁乁䡍䅁䉁䅁䅁允䅁䅁䅕塺婌䨶⽺歈䵁䅉䅅䅁䡁䅁䅁睁䵁䅁䅁权䡃杂䅁权啂杂䅁权䉁䅁䅁兂䅁䅁䅁䙙浢䅑䅕䅁䅁䵁桂欵䭁乁䡍䅁䉁䅁䅁允䅁䅁䅕䥰伶㕱㥈啈䵁䅉䅅䅁䡁䅁䅁睁䵁䅁䅁权䡃杂䅁权啂杂䅁权䉁䅁䅁兂䅁䅁䅁䝷浈䅑䅕䅁䅁䕁瑂欵䭁乁䡍䅁䉁䅁䅁允䅁䅁䅕橷㍖䰹䴯え䵁䅉䅅䅁䡁䅁䅁睁䵁䅁䅁权䡃杂䅁权獂杂䅁权剂杂䅁兂䅁䅁䅁䙙浢䅑䅕䅁䅁䵁桂欵䭁乁䡅䅁䉁䅁䅁允䅁䅁䅕䝈坔兦佑空䴸䅉䅅䅁䡁䅁䅁睁䵁䅁䅁权䡃杂䅁权敂杂䅁权剂杂䅁兂䅁䅁䅁䡷浪䅑䅕䅁䅁䝁㥂欵䭁乁䡑䅁䉁䅁䅁允䅁䅁䅕䭳啸㑴扢啃䵁䅉䅅䅁䡁䅁䅁睁䵁䅁䅁权䡃杂䅁权灂杂䅁权䉁䅁䅁兂䅁䅁䅁䙙浢䅑䅕䅁䅁䵁桂欵䭁乁䡅䅁䉁䅁䅁允䅁䅁䅕歪汐堹畩稫䴸䅉䅅䅁䡁䅁䅁睁䵁䅁䅁权䡃杂䅁权摂杂䅁权䉁䅁䅁兂䅁䅁䅁䑉浔䅑䅕䅁䅁䭁⽁欵䭁乁䡅䅁䉁䅁䅁允䅁䅁䅕匹剁匶獭呹䴸䅉䅅䅁䡁䅁䅁睁䵁䅁䅁权䡃杂䅁权敂杂䅁权剂杂䅁兂䅁䅁䅁䍷浪䅑䅕䅁䅁䍁ぁ欵䭁乁䡉䅁䉁䅁䅁允䅁䅁䅕敏畤䩮㍷歅䵁䅉䅅䅁䙁䅁䅁睁䵁䅁䅁权䡃杂䅁权㥂杂䅁权晁䅁䅁兂䅁䅁䅁䡙洳䅑䅅䅁䉁䅁䅁睂䅁䅁䅁䕉浶䅑杷允䅁䅁䅣䅁䑁䅁䅷䅁䭁䥁䝣䅁䭁䝁䝍䅁䭁䅁䅅䅁䙁䅁䅁䅁杂畖䅚兂䅁䅁䅁䝷浈䅑䅯朰䅣䅁䅅䅁䉁䅁䅁兂湄䱏䩣⬹㔴䅑杷允䅁䅁䅣䅁䑁䅁䅷䅁䭁䥁䝣䅁䭁䙁䝑䅁䭁䅁䅅䅁䙁䅁䅁䅁权⭐䅚兂䅁䅁䅁䕉浶䅑䅯䄱䅣䅁䅅䅁䉁䅁䅁兂ㅂ祗塉偮杫䅑杷允䅁䅁䅣䅁䑁䅁䅷䅁䭁䥁䝣䅁䭁䝁䝷䅁䭁䙁䝅䅁䙁䅁䅁䅁䅂敢䅚兂䅁䅁䅁䡷浪䅑䅯儰䅣䅁䅅䅁䉁䅁䅁兂权渵⭣䱁䅘睐杷允䅁䅁䅣䅁䑁䅁䅷䅁䭁䥁䝣䅁䭁䝁䝍䅁䭁䅁䅅䅁䙁䅁䅁䅁权⭐䅚兂䅁䅁䅁䕉浶䅑䅯朰䅣䅁䅅䅁䉁䅁䅁兂䥂場啯歲㘸䅑杷允䅁䅁䅣䅁䑁䅁䅷䅁䭁䥁䝣䅁䭁䙁䝑䅁䭁䅁䅅䅁䙁䅁䅁䅁杁⭓䅚兂䅁䅁䅁䙙浢䅑䅯儰䅣䅁䅅䅁䉁䅁䅁兂婂䙩杸橅乪睐杷允䅁䅁䅣䅁䑁䅁䅷䅁䭁䥁䝣䅁䭁䙁䝑䅁䭁䅁䅅䅁䙁䅁䅁䅁杂畖䅚兂䅁䅁䅁䝷浈䅑䅯儰䅣䅁䅅䅁䉁䅁䅁兂权ㅑ穳獱浌睐杷允䅁䅁䅣䅁䑁䅁䅷䅁䭁䥁䝣䅁䭁䝁䝯䅁䭁䑁䄰䅁䙁䅁䅁䅁权⭐䅚兂䅁䅁䅁䕉浶䅑䅯朰䅣䅁䅅䅁䉁䅁䅁兂㕂奂䥓⭡朴䅑杷允䅁䅁䅣䅁䑁䅁䅷䅁䭁䥁䝣䅁䭁䝁䝯䅁䭁䑁䄰䅁䙁䅁䅁䅁杂畖䅚兂䅁䅁䅁䝷浈䅑䅯朰䅣䅁䅅䅁䉁䅁䅁兂剂〵䉹奚桫䅑杷允䅁䅁䅣䅁䑁䅁䅷䅁䭁䥁䝣䅁䭁䙁䜰䅁䭁䅁䅅䅁䙁䅁䅁䅁䅂敢䅚兂䅁䅁䅁䡷浪䅑䅯朰䅣䅁䅅䅁䉁䅁䅁兂噄㑐歨䅹卅䅑杷允䅁䅁䅣䅁䑁䅁䅷䅁䭁䥁䝣䅁䭁䝁䝯䅁䭁䑁䄰䅁䙁䅁䅁䅁权⭐䅚兂䅁䅁䅁䕉浶䅑䅯眰䅣䅁䅅䅁䉁䅁䅁兂䵁乕煷椹摕䅑杷允䅁䅁䅣䅁䑁䅁䅷䅁䭁䥁䝣䅁䭁䝁䝯䅁䭁䑁䄰䅁䙁䅁䅁䅁䅄教䅚兂䅁䅁䅁䝑洳䅑䅯䄱䅣䅁䅅䅁䉁䅁䅁兂浄䥶䍱䅮晧䅑杷允䅁䅁䅙䅁䑁䅁䅷䅁䭁䥁䝣䅁䭁䝁䝯䅁䭁䑁䄰䅁䙁䅁䅁䅁杁⭓䅚权剄睂䅁允䅁䅁䅅䅁䙁䭁て䥰漫敢⽫䍄䉁䅁䅁杂䅁䅁䅍䅄䅁䅁䅯睨䅙䅁䅯条䅙䅁䅯児䅁䅁䅕䅁䅁䵁桂欵䭁乁䡅䅁䉁䅁䅁允䅁䅁䅕㝑䴱㠶㘱吶䴸䅉䅅䅁䝁䅁䅁睁䵁䅁䅁权䡃杂䅁权煂杂䅁权㥁䅁䅁兂䅁䅁䅁䝑洳䅑䅯儰䅣䅁䅅䅁䉁䅁䅁兂煃䤰呙乃栯睐杷允䅁䅁䅣䅁䑁䅁䅷䅁䭁䥁䝣䅁䭁䝁䝫䅁䭁䅁䅅䅁䙁䅁䅁䅁䅄佋䅚兂䅁䅁䅁䑉浔䅑䅯眰䅣䅁䅅䅁䉁䅁䅁兂㑄う橆牊睅䅑杷允䅁䅁䅣䅁䑁䅁䅷䅁䭁䥁䝣䅁䭁䝁䝑䅁䭁䅁䅅䅁䙁䅁䅁䅁䅄教䅚兂䅁䅁䅁䝑洳䅑䅯朰䅣䅁䅅䅁䉁䅁䅁权硁䅁䅁䍄䉁䅁䅁睂䅁䅁䅍䅄䅁䅁䅯睨䅙䅁䅯杘䅙䅁䅯兕䅙䅁䅕䅁䅁䭁⽁欵䙁䅁䅁䅁杁⭓䅚权剄睂䅁允䅁䅁䅅䅁䙁䑁楋楒䵦摪⽙䍄䉁䅁䅁睂䅁䅁䅍䅄䅁䅁䅯睨䅙䅁䅯䅚䅙䅁䅯允䅁䅁䅕䅁䅁䍁ぁ欵䙁䅁䅁䅁权⭐䅚权卄睂䅁允䅁䅁䅅䅁䭁䑁䅅䅁䵁䅉䅅䅁䡁䅁䅁睁䵁䅁䅁权䡃杂䅁权歂杂䅁权䉁䅁䅁兂䅁䅁䅁䕉浶䅑䅕䅁䅁䝁坂欵䭁乁䡉䅁䉁䅁䅁允䅁䅁䅯免䅁䅁杷允䅁䅁䅣䅁䑁䅁䅷䅁䭁䥁䝣䅁䭁䝁䝑䅁䭁䅁䅅䅁䙁䅁䅁䅁䅄佋䅚兂䅁䅁䅁䑉浔䅑䅯眰䅣䅁䅅䅁䉁䅁䅁权硁䅁䅁䍄䉁䅁䅁睂䅁䅁䅍䅄䅁䅁䅯睨䅙䅁䅯䅚䅙䅁䅯允䅁䅁䅕䅁䅁䝁坂欵䙁䅁䅁䅁䅄教䅚权呄睂䅁允䅁䅁䅅䅁䭁䑁䅅䅁䵁䅉䅅䅁䡁䅁䅁睁䵁䅁䅁权䡃杂䅁权歂杂䅁权䉁䅁䅁兂䅁䅁䅁䕉浶䅑䅕䅁䅁䝁坂欵䭁乁䡅䅁䉁䅁䅁允䅁䅁䅯免䅁䅁杷允䅁䅁䅣䅁䑁䅁䅷䅁䭁䥁䝣䅁䭁䝁䝑䅁䭁䅁䅅䅁䙁䅁䅁䅁䅄教䅚兂䅁䅁䅁䝑洳䅑䅯儰䅣䅁䅅䅁䉁䅁䅁权硁䅁䅁䍄䉁䅁䅁睂䅁䅁䅍䅄䅁䅁䅯睨䅙䅁䅯睙䅙䅁䅯允䅁䅁䅕䅁䅁䵁桂欵䙁䅁䅁䅁䅂敢䅚权呄睂䅁允䅁䅁䅅䅁䙁䉁扢䭰硋楪䄹䍄䉁䅁䅁睂䅁䅁䅍䅄䅁䅁䅯睨䅙䅁䅯杙䅙䅁䅯兕䅙䅁䅕䅁䅁䵁潁欵䙁䅁䅁䅁杁低䅚权啄睂䅁允䅁䅁䅅䅁䙁偁㡳⼰头礯䅤䍄䉁䅁䅁睂䅁䅁䅍䅄䅁䅁䅯睨䅙䅁䅯杙䅙䅁䅯兕䅙䅁䅕䅁䅁䵁桂欵䙁䅁䅁䅁䅂敢䅚权啄睂䅁允䅁䅁䅅䅁䙁䩁㕱摲儱卡䄹䍄䉁䅁䅁睂䅁䅁䅍䅄䅁䅁䅯睨䅙䅁䅯䅢䅙䅁䅯兕䅙䅁䅕䅁䅁䵁桂欵䙁䅁䅁䅁䅂敢䅚权卄睂䅁允䅁䅁䅅䅁䙁䝁瀹䑆䥱桗䅂䍄䉁䅁䅁睂䅁䅁䅍䅄䅁䅁䅯睨䅙䅁䅯䅘䅙䅁䅯允䅁䅁䅕䅁䅁䭁⽁欵䙁䅁䅁䅁杁⭓䅚权卄睂䅁允䅁䅁䅅䅁䙁䥁瘳ど噴橕䅸䍄䉁䅁䅁睂䅁䅁䅍䅄䅁䅁䅯睨䅙䅁䅯䅘䅙䅁䅯允䅁䅁䅕䅁䅁䵁潁欵䙁䅁䅁䅁杁低䅚权呄睂䅁允䅁䅁䅅䅁䙁䍁儳瀷楂䑊䅂䍄䉁䅁䅁睂䅁䅁䅍䅄䅁䅁䅯睨䅙䅁䅯䅘䅙䅁䅯允䅁䅁䅕䅁䅁䍁ぁ欵䙁䅁䅁䅁权⭐䅚权呄睂䅁允䅁䅁䅅䅁䙁䱁栶丸㙫䐹䅂䍄䉁䅁䅁睂䅁䅁䅍䅄䅁䅁䅯睨䅙䅁䅯䅘䅙䅁䅯允䅁䅁䅕䅁䅁䭁⽁欵䙁䅁䅁䅁杁⭓䅚权呄睂䅁允䅁䅁䅅䅁䙁佁框樲㍦穪䅒䍄䉁䅁䅁睂䅁䅁䅍䅄䅁䅁䅯睨䅙䅁䅯䅘䅙䅁䅯允䅁䅁䅕䅁䅁䍁䱂欵䙁䅁䅁䅁杂畖䅚权呄睂䅁允䅁䅁䅅䅁䙁䡁㡒䑴橨䑬䅖䍄䉁䅁䅁睂䅁䅁䅍䅄䅁䅁䅯睨䅙䅁䅯兘䅙䅁䅯允䅁䅁䅕䅁䅁䵁桂欵䙁䅁䅁䅁䅂敢䅚权剄睂䅁允䅁䅁䅅䅁䙁䙁䴶當噫丰⽉䍄䉁䅁䅁睂䅁䅁䅍䅄䅁䅁䅯睨䅙䅁䅯杘䅙䅁䅯兕䅙䅁䅕䅁䅁䍁ぁ欵䙁䅁䅁䅁权⭐䅚权剄睂䅁允䅁䅁䅅䅁䙁䥁器堵煭捶⽧䍄䉁䅁䅁睂䅁䅁䅍䅄䅁䅁䅯睨䅙䅁䅯䅘䅙䅁䅯允䅁䅁䅕䅁䅁䭁⽁欵䙁䅁䅁䅁杁⭓䅚权剄睂䅁允䅁䅁䅅䅁䙁䥁橙⽳䝷儲䅖䍄䉁䅁䅁睂䅁䅁䅍䅄䅁䅁䅯睨䅙䅁䅯䅘䅙䅁䅯允䅁䅁䅕䅁䅁䵁桂欵䙁䅁䅁䅁䅂敢䅚权剄睂䅁允䅁䅁䅅䅁䙁䩁併婉灧朹䅴䍄䉁䅁䅁睂䅁䅁䅍䅄䅁䅁䅯睨䅙䅁䅯睙䅙䅁䅯允䅁䅁䅕䅁䅁䝁坂欵䙁䅁䅁䅁䅄教䅚权啄睂䅁允䅁䅁䅅䅁䙁䩁琰䱉救橡䅤䍄䉁䅁䅁睂䅁䅁䅍䅄䅁䅁䅯睨䅙䅁䅯睙䅙䅁䅯允䅁䅁䅕䅁䅁䍁ぁ欵䙁䅁䅁䅁权⭐䅚权剄睂䅁允䅁䅁䅅䅁䙁䩁䥳敇琫公䅴䍄䉁䅁䅁睂䅁䅁䅍䅄䅁䅁䅯睨䅙䅁䅯睙䅙䅁䅯允䅁䅁䅕䅁䅁䭁⽁欵䙁䅁䅁䅁杁⭓䅚权剄睂䅁允䅁䅁䅅䅁䙁䕁剤湊䍧睪䅚䍄䉁䅁䅁睂䅁䅁䅍䅄䅁䅁䅯睨䅙䅁䅯兘䅙䅁䅯允䅁䅁䅕䅁䅁䵁桂欵䙁䅁䅁䅁䅂敢䅚权卄睂䅁允䅁䅁䅅䅁䙁偁橭䑱㍐䉣䅆䍄䉁䅁䅁睂䅁䅁䅍䅄䅁䅁䅯睨䅙䅁䅯兘䅙䅁䅯允䅁䅁䅕䅁䅁䝁坂欵䙁䅁䅁䅁䅄教䅚权剄睂䅁允䅁䅁䅅䅁䙁䕁潺嘴敊摘⽉䍄䉁䅁䅁睂䅁䅁䅍䅄䅁䅁䅯睨䅙䅁䅯䅢䅙䅁䅯兕䅙䅁䅕䅁䅁䍁䱂欵䙁䅁䅁䅁杂畖䅚权卄睂䅁允䅁䅁䅅䅁䙁䱁汈䙵⭂睇䄵䍄䉁䅁䅁睂䅁䅁䅍䅄䅁䅁䅯睨䅙䅁䅯䅢䅙䅁䅯兕䅙䅁䅕䅁䅁䍁ぁ欵䙁䅁䅁䅁权⭐䅚权啄睂䅁允䅁䅁䅅䅁䙁䥁婲獂敵睑䅚䍄䉁䅁䅁睂䅁䅁䅍䅄䅁䅁䅯睨䅙䅁䅯䅢䅙䅁䅯兕䅙䅁䅕䅁䅁䍁䱂欵䙁䅁䅁䅁杂畖䅚权啄睂䅁允䅁䅁䅅䅁䙁䵁䩖浶灖睘䅸䍄䉁䅁䅁睂䅁䅁䅍䅄䅁䅁䅯睨䅙䅁䅯兡䅙䅁䅯允䅁䅁䅕䅁䅁䍁䱂欵䙁䅁䅁䅁杂畖䅚权卄睂䅁允䅁䅁䅅䅁䙁䵁牗䝲䬲穧䅴䍄䉁䅁䅁睂䅁䅁䅍䅄䅁䅁䅯睨䅙䅁䅯兡䅙䅁䅯允䅁䅁䅕䅁䅁䍁ぁ欵䙁䅁䅁䅁权⭐䅚权啄睂䅁允䅁䅁䅅䅁䙁偁㕰㕕䭅呗䅎䍄䉁䅁䅁睂䅁䅁䅍䅄䅁䅁䅯睨䅙䅁䅯兡䅙䅁䅯允䅁䅁䅕䅁䅁䍁䱂欵䙁䅁䅁䅁杂畖䅚权啄睂䅁允䅁䅁䅅䅁䙁䩁灕椵潄䑢䅬䍄䉁䅁䅁睂䅁䅁䅍䅄䅁䅁䅯睨䅙䅁䅯兡䅙䅁䅯允䅁䅁䅕䅁䅁䵁桂欵䙁䅁䅁䅁䅂敢䅚权剄睂䅁允䅁䅁䅅䅁䙁䩁㡶㡷癷睄䅆䍄䉁䅁䅁睂䅁䅁䅍䅄䅁䅁䅯睨䅙䅁䅯杘䅙䅁䅯兕䅙䅁䅕䅁䅁䍁䱂欵䙁䅁䅁䅁杂畖䅚权卄睂䅁允䅁䅁䅅䅁䙁䉁晦䕖硄䉖䅒䍄䉁䅁䅁睂䅁䅁䅍䅄䅁䅁䅯睨䅙䅁䅯杘䅙䅁䅯兕䅙䅁䅕䅁䅁䵁潁欵䙁䅁䅁䅁杁低䅚权呄睂䅁允䅁䅁䅅䅁䙁䱁㍳㙉〵睕䅸䍄䉁䅁䅁睂䅁䅁䅍䅄䅁䅁䅯睨䅙䅁䅯杘䅙䅁䅯兕䅙䅁䅕䅁䅁䍁䱂欵䙁䅁䅁䅁杂畖䅚权呄睂䅁允䅁䅁䅅䅁䙁䑁呩灢䡱睑䅨䍄䉁䅁䅁睂䅁䅁䅍䅄䅁䅁䅯睨䅙䅁䅯䅘䅙䅁䅯允䅁䅁䅕䅁䅁䵁㑂欵䙁䅁䅁䅁杂敦䅚权剄睂䅁允䅁䅁䅅䅁䙁偁硶䉄㕃癯⽁䍄䉁䅁䅁睂䅁䅁䅍䅄䅁䅁䅯睨䅙䅁䅯杘䅙䅁䅯兕䅙䅁䅕䅁䅁䝁坂欵䙁䅁䅁䅁䅄教䅚权呄睂䅁允䅁䅁䅅䅁䙁䵁瘹䩑瑋杅䅚䍄䉁䅁䅁睂䅁䅁䅍䅄䅁䅁䅯睨䅙䅁䅯杘䅙䅁䅯兕䅙䅁䅕䅁䅁䵁桂欵䙁䅁䅁䅁䅂敢䅚权呄睂䅁允䅁䅁䅅䅁䙁䑁䔶失浵兗䅖䍄䉁䅁䅁睂䅁䅁䅍䅄䅁䅁䅯睨䅙䅁䅯杘䅙䅁䅯兕䅙䅁䅕䅁䅁䝁坂欵䙁䅁䅁䅁䅄教䅚权啄睂䅁允䅁䅁䅅䅁䙁䍁䙙睡㑹眵䅰䍄䉁䅁䅁睂䅁䅁䅍䅄䅁䅁䅯睨䅙䅁䅯䅕䅙䅁䅯兕䅙䅁䅕䅁䅁䕁瑂欵䙁䅁䅁䅁䅄佥䅚权啄睂䅁允䅁䅁䅅䅁䙁䥁䝃晋䰳硗䅎䍄䉁䅁䅁睂䅁䅁䅍䅄䅁䅁䅯睨䅙䅁䅯杖䅙䅁䅯允䅁䅁䅕䅁䅁䕁瑂欵䙁䅁䅁䅁䅄佥䅚权卄睂䅁允䅁䅁䅅䅁䙁䙁牃䄶丯䉌䅖䍄䉁䅁䅁睂䅁䅁䅍䅄䅁䅁䅯睨䅙䅁䅯䅚䅙䅁䅯允䅁䅁䅕䅁䅁䕁瑂欵䙁䅁䅁䅁䅄佥䅚权卄睂䅁允䅁䅁䅅䅁䭁䑁䅅䅁䵁䅉䅅䅁䡁䅁䅁睁䵁䅁䅁权䡃杂䅁权潂杂䅁权剂杂䅁兂䅁䅁䅁䝑洳䅑䅕䅁䅁䵁㑂欵䭁乁䡉䅁䉁䅁䅁允䅁䅁䅕祪䑒敵愰歏䵁䅉䅅䅁䡁䅁䅁睁䵁䅁䅁权䡃杂䅁权捂杂䅁权䉁䅁䅁兂䅁䅁䅁䝑洳䅑䅕䅁䅁䵁㑂欵䭁乁䡅䅁䉁䅁䅁允䅁䅁䅕楯䭹偦戵啁䵁䅉䅅䅁䝁䅁䅁睁䵁䅁䅁权䡃杂䅁权煂杂䅁权㥁䅁䅁兂䅁䅁䅁䡙洳䅑䅯儰䅣䅁䅅䅁䉁䅁䅁权硁䅁䅁䍄䉁䅁䅁睂䅁䅁䅍䅄䅁䅁䅯睨䅙䅁䅯杚䅙䅁䅯允䅁䅁䅕䅁䅁䕁瑂欵䙁䅁䅁䅁䅄佥䅚权啄睂䅁允䅁䅁䅅䅁䙁偁晪湓獚䑬䅒䍄䉁䅁䅁杂䅁䅁䅍䅄䅁䅁䅯睨䅙䅁䅯杙䅙䅁䅯兕䅙䅁䅕䅁䅁䵁㑂欵䭁䙁䝫䅁䉁䅁䅁允䅁䅁䅕㈴⭰牙㤹啍䵁䅉䅅䅁䡁䅁䅁睁䵁䅁䅁权䡃杂䅁权坂杂䅁权䉁䅁䅁兂䅁䅁䅁䝑洳䅑䅕䅁䅁䵁㑂欵䭁乁䡅䅁䉁䅁䅁允䅁䅁䅕䵉硩㌵䥎䑷䴸䅉䅅䅁䡁䅁䅁睁䵁䅁䅁权䡃杂䅁权時杂䅁权剂杂䅁兂䅁䅁䅁䝑洳䅑䅕䅁䅁䵁㑂欵䭁乁䡅䅁䉁䅁䅁允䅁䅁䅕猶昷晏儴樱䴸䅉䅅䅁䡁䅁䅁睁䵁䅁䅁权䡃杂䅁权啂杂䅁权䉁䅁䅁兂䅁䅁䅁䝑洳䅑䅕䅁䅁䵁㑂欵䭁乁䡁䅁䉁䅁䅁允䅁䅁䅕偈䥎乮夰䕊䵁䅉䅅䅁䡁䅁䅁睁䵁䅁䅁权䡃杂䅁权兂杂䅁权剂杂䅁兂䅁䅁䅁䝑洳䅑䅕䅁䅁䵁㑂欵䭁乁䡁䅁䉁䅁䅁允䅁䅁䅕慬慙圶癑ぅ䵁䅉䅅䅁䡁䅁䅁睁䵁䅁䅁权䡃杂䅁权時杂䅁权剂杂䅁兂䅁䅁䅁䝑洳䅑䅕䅁䅁䵁㑂欵䭁乁䡁䅁䉁䅁䅁允䅁䅁䅕久捌呶灒啍䵁䅉䅅䅁䡁䅁䅁睁䵁䅁䅁权䡃杂䅁权兂杂䅁权剂杂䅁兂䅁䅁䅁䝑洳䅑䅕䅁䅁䵁㑂欵䭁乁䡍䅁䉁䅁䅁允䅁䅁䅕稳氹䠳婫歅䵁䅉䅅䅁䡁䅁䅁睁䵁䅁䅁权䡃杂䅁权橂杂䅁权䉁䅁䅁兂䅁䅁䅁䡷浪䅑䅕䅁䅁䝁㥂欵䭁乁䡉䅁䉁䅁䅁允䅁䅁䅕摓㑶㕅剘䕏䵁䅉䅅䅁䡁䅁䅁睁䵁䅁䅁权䡃杂䅁权捂杂䅁权䉁䅁䅁兂䅁䅁䅁䝑洳䅑䅕䅁䅁䵁㑂欵䭁乁䡑䅁䉁䅁䅁允䅁䅁䅕乒礵圹牐問䵁䅉䅅䅁䡁䅁䅁睁䵁䅁䅁权䡃杂䅁权兂杂䅁权剂杂䅁兂䅁䅁䅁䝑洳䅑䅕䅁䅁䵁㑂欵䭁乁䡅䅁䉁䅁䅁允䅁䅁䅕瑡爫坸䑶究䴸䅉䅅䅁䝁䅁䅁睁䵁䅁䅁权䡃杂䅁权歂杂䅁权䉁䅁䅁兂䅁䅁䅁䡷浪䅑䅯兗䅙䅁䅅䅁䉁䅁䅁权求杂䅁䍄䉁䅁䅁睂䅁䅁䅍䅄䅁䅁䅯睨䅙䅁䅯䅡䅙䅁䅯兕䅙䅁䅕䅁䅁䵁㑂欵䙁䅁䅁䅁杂敦䅚权兄睂䅁允䅁䅁䅅䅁䙁䡁䬹硬椹橭䅨䍄䉁䅁䅁睂䅁䅁䅍䅄䅁䅁䅯睨䅙䅁䅯杚䅙䅁䅯允䅁䅁䅕䅁䅁䕁瑂欵䙁䅁䅁䅁䅄佥䅚权兄睂䅁允䅁䅁䅅䅁䙁䱁㥚塅㕁䑨䅒䍄䉁䅁䅁睂䅁䅁䅍䅄䅁䅁䅯睨䅙䅁䅯兖䅙䅁䅯允䅁䅁䅕䅁䅁䕁瑂欵䙁䅁䅁䅁䅄佥䅚权剄睂䅁允䅁䅁䅅䅁䙁䱁灷䑩䑱⬯⼴䍄䉁䅁䅁睂䅁䅁䅍䅄䅁䅁䅯睨䅙䅁䅯䅘䅙䅁䅯允䅁䅁䅕䅁䅁䕁瑂欵䙁䅁䅁䅁䅄佥䅚权呄睂䅁允䅁䅁䅅䅁䙁䩁䥙偖朸橯䅒䍄䉁䅁䅁睂䅁䅁䅍䅄䅁䅁䅯睨䅙䅁䅯䅖䅙䅁䅯允䅁䅁䅕䅁䅁䕁瑂欵䙁䅁䅁䅁䅄佥䅚权啄睂䅁允䅁䅁䅅䅁䙁䝁敁畍䑖䍕䅒䍄䉁䅁䅁睂䅁䅁䅍䅄䅁䅁䅯睨䅙䅁䅯条䅙䅁䅯児䅁䅁䅕䅁䅁䕁瑂欵䙁䅁䅁䅁䅄佥䅚权卄睂䅁允䅁䅁䅅䅁䙁䑁奎婲䨸䍕䅎䍄䉁䅁䅁睂䅁䅁䅍䅄䅁䅁䅯睨䅙䅁䅯条䅙䅁䅯児䅁䅁䅕䅁䅁䵁潁欵䙁䅁䅁䅁杁低䅚权剄睂䅁允䅁䅁䅅䅁䙁䕁啁は㥋瑰⽉䍄䉁䅁䅁睂䅁䅁䅍䅄䅁䅁䅯睨䅙䅁䅯睘䅙䅁䅯兕䅙䅁䅕䅁䅁䕁瑂欵䙁䅁䅁䅁䅄佥䅚权呄睂䅁允䅁䅁䅅䅁䙁佁桅畫䭩呩䅂䍄䉁䅁䅁睂䅁䅁䅍䅄䅁䅁䅯睨䅙䅁䅯兡䅙䅁䅯允䅁䅁䅕䅁䅁䕁瑂欵䙁䅁䅁䅁䅄佥䅚权呄睂䅁允䅁䅁䅅䅁䙁䕁扚啬㉔呲䅬䍄䉁䅁䅁睂䅁䅁䅍䅄䅁䅁䅯睨䅙䅁䅯睘䅙䅁䅯兕䅙䅁䅕䅁䅁䕁瑂欵䙁䅁䅁䅁䅄佥䅚权啄睂䅁允䅁䅁䅅䅁䙁䉁⭪㥄㡔呧䅆䍄䉁䅁䅁睂䅁䅁䅍䅄䅁䅁䅯睨䅙䅁䅯兙䅙䅁䅯允䅁䅁䅕䅁䅁䕁瑂欵䙁䅁䅁䅁䅄佥䅚权剄睂䅁允䅁䅁䅅䅁䙁䡁塶㕬䑹砳䅂䍄䉁䅁䅁杂䅁䅁䅍䅄䅁䅁䅯睨䅙䅁䅯䅗䅙䅁䅯允䅁䅁䅕䅁䅁䵁㑂欵䭁䙁䝫䅁䉁䅁䅁允䅁䅁䅕㑥睚䱺⽊䕐䵁䅉䅅䅁䝁䅁䅁睁䵁䅁䅁权䡃杂䅁权敂杂䅁权剂杂䅁兂䅁䅁䅁䡷浪䅑䅯兗䅙䅁䅅䅁䉁䅁䅁兂乂畔䅥橸䩯䅑杷允䅁䅁䅣䅁䑁䅁䅷䅁䭁䥁䝣䅁䭁䙁䝯䅁䭁䙁䝅䅁䙁䅁䅁䅁䅂敢䅚兂䅁䅁䅁䡷浪䅑䅯䄰䅣䅁䅅䅁䉁䅁䅁兂䕁整獂奋㍯䅑杷允䅁䅁䅣䅁䑁䅁䅷䅁䭁䥁䝣䅁䭁䙁䜴䅁䭁䙁䝅䅁䙁䅁䅁䅁䅂敢䅚兂䅁䅁䅁䡷浪䅑䅯儰䅣䅁䅅䅁䉁䅁䅁兂敃癙晇位䩌睐杷允䅁䅁䅣䅁䑁䅁䅷䅁䭁䥁䝣䅁䭁䙁䝯䅁䭁䙁䝅䅁䙁䅁䅁䅁䅂敢䅚兂䅁䅁䅁䡷浪䅑䅯䄱䅣䅁䅅䅁䉁䅁䅁兂楁穗塡䭉㍕䅑杷允䅁䅁䅣䅁䑁䅁䅷䅁䭁䥁䝣䅁䭁䙁䝕䅁䭁䅁䅅䅁䙁䅁䅁䅁䅂敢䅚兂䅁䅁䅁䡷浪䅑䅯朰䅣䅁䅅䅁䉁䅁䅁兂⽃煮娹癌䝴䅑杷允䅁䅁䅣䅁䑁䅁䅷䅁䭁䥁䝣䅁䭁䝁䝷䅁䭁䙁䝅䅁䙁䅁䅁䅁䅂敢䅚兂䅁䅁䅁䡷浪䅑䅯眰䅣䅁䅅䅁䉁䅁䅁兂偃噕䄵样位䅑杷允䅁䅁䅙䅁䑁䅁䅷䅁䭁䥁䝣䅁䭁䙁䝯䅁䭁䙁䝅䅁䙁䅁䅁䅁䅄佥䅚权婂杂䅁允䅁䅁䅅䅁䙁䍁楸塷ぐ穈䅤䍄䉁䅁䅁睂䅁䅁䅍䅄䅁䅁䅯睨䅙䅁䅯䅖䅙䅁䅯允䅁䅁䅕䅁䅁䵁㑂欵䙁䅁䅁䅁杂敦䅚权呄睂䅁允䅁䅁䅅䅁䙁乁剧㉨杷卬䅂䍄䉁䅁䅁睂䅁䅁䅍䅄䅁䅁䅯睨䅙䅁䅯䅡䅙䅁䅯兕䅙䅁䅕䅁䅁䕁瑂欵䙁䅁䅁䅁䅄佥䅚权剄睂䅁允䅁䅁䅅䅁䙁䩁兴䝋慂敊⽑䍄䉁䅁䅁睂䅁䅁䅍䅄䅁䅁䅯睨䅙䅁䅯兙䅙䅁䅯允䅁䅁䅕䅁䅁䕁瑂欵䙁䅁䅁䅁䅄佥䅚权卄睂䅁允䅁䅁䅅䅁䙁䵁礱攲捩へ䅤䍄䉁䅁䅁睂䅁䅁䅍䅄䅁䅁䅯睨䅙䅁䅯兙䅙䅁䅯允䅁䅁䅕䅁䅁䕁瑂欵䙁䅁䅁䅁䅄佥䅚权啄睂䅁允䅁䅁䅅䅁䙁䱁䩔娴低歡䅊䍄䉁䅁䅁睂䅁䅁䅍䅄䅁䅁䅯睨䅙䅁䅯䅡䅙䅁䅯兕䅙䅁䅕䅁䅁䕁瑂欵䙁䅁䅁䅁䅄佥䅚权兄睂䅁允䅁䅁䅅䅁䙁䅁䱍浣づ樯䅨䍄䉁䅁䅁杂䅁䅁䅍䅄䅁䅁䅯睨䅙䅁䅯䅡䅙䅁䅯兕䅙䅁䅕䅁䅁䵁㑂欵䭁䙁䝫䅁䉁䅁䅁允䅁䅁䅕橱䉚卆⽸䕏䵁䅉䅅䅁䡁䅁䅁睁䵁䅁䅁权䡃杂䅁权灂杂䅁权䉁䅁䅁兂䅁䅁䅁䝑洳䅑䅕䅁䅁䵁㑂欵䭁乁䡑䅁䉁䅁䅁允䅁䅁䅕癰䱅祲硒く䵁䅉䅅䅁䡁䅁䅁睁䵁䅁䅁权䡃杂䅁权潂杂䅁权剂杂䅁兂䅁䅁䅁䝑洳䅑䅕䅁䅁䵁㑂欵䭁乁䡑䅁䉁䅁䅁允䅁䅁䅕捣漸桭爰問䵁䅉䅅䅁䡁䅁䅁睁䵁䅁䅁权䡃杂䅁权歂杂䅁权䉁䅁䅁兂䅁䅁䅁䝑洳䅑䅕䅁䅁䵁㑂欵䭁乁䡑䅁䉁䅁䅁允䅁䅁䅯免䅁䅁杷允䅁䅁䅣䅁䑁䅁䅷䅁䭁䥁䝣䅁䭁䙁䝕䅁䭁䅁䅅䅁䙁䅁䅁䅁䅂敢䅚兂䅁䅁䅁䡷浪䅑䅯眰䅣䅁䅅䅁䉁䅁䅁兂䅄祉啰㡎䕴䅑杷允䅁䅁䅙䅁䑁䅁䅷䅁䭁䥁䝣䅁䭁䙁䝑䅁䭁䅁䅅䅁䙁䅁䅁䅁䅄佥䅚权婂杂䅁允䅁䅁䅅䅁䙁䅁敧㤳ㄴ䌲䅎䍄䉁䅁䅁睂䅁䅁䅍䅄䅁䅁䅯睨䅙䅁䅯䅖䅙䅁䅯允䅁䅁䅕䅁䅁䕁瑂欵䙁䅁䅁䅁䅄佥䅚权剄睂䅁允䅁䅁䅅䅁䙁䍁奕湍䙃㥧⽕䍄䉁䅁䅁兂䅁䅁䅍䅄䅁䅁䅯睨䅙䅁䅯杤䅙䅁䅯䅄䅁䅁䅕䅁䅁䝁㥂欵䉁䅁䅁允䅁䅁䅯儲䅣䅁杷允䅁䅁䅣䅁䑁䅁䅷䅁䭁䥁䝣䅁䭁䝁䝯䅁䭁䑁䄰䅁䙁䅁䅁䅁䅂敢䅚兂䅁䅁䅁䡷浪䅑䅯䄰䅣䅁䅅䅁䉁䅁䅁兂浂挹乎は楷䅑杷允䅁䅁䅣䅁䑁䅁䅷䅁䭁䥁䝣䅁䭁䝁䝉䅁䭁䙁䝅䅁䙁䅁䅁䅁䅂敢䅚兂䅁䅁䅁䡷浪䅑䅯䄰䅣䅁䅅䅁䉁䅁䅁兂汃潌含瑣硍䅑杷允䅁䅁䅣䅁䑁䅁䅷䅁䭁䥁䝣䅁䭁䝁䝉䅁䭁䙁䝅䅁䙁䅁䅁䅁䅂敢䅚兂䅁䅁䅁䡷浪䅑䅯䄱䅣䅁䅅䅁䉁䅁䅁兂䥄䕮乬癕硕䅑杷允䅁䅁䅣䅁䑁䅁䅷䅁䭁䥁䝣䅁䭁䝁䝍䅁䭁䅁䅅䅁䙁䅁䅁䅁䅂敢䅚兂䅁䅁䅁䡷浪䅑䅯䄱䅣䅁䅅䅁䉁䅁䅁兂汄儷湩剂㑳䅑杷允䅁䅁䅣䅁䑁䅁䅷䅁䭁䥁䝣䅁䭁䙁䝷䅁䭁䅁䅅䅁䙁䅁䅁䅁䅂敢䅚兂䅁䅁䅁䡷浪䅑䅯䄰䅣䅁䅅䅁䉁䅁䅁兂奁⭮䤱捓㑯䅑杷允䅁䅁䅣䅁䑁䅁䅷䅁䭁䥁䝣䅁䭁䝁䝍䅁䭁䅁䅅䅁䙁䅁䅁䅁䅂敢䅚兂䅁䅁䅁䡷浪䅑䅯䄰䅣䅁䅅䅁䉁䅁䅁兂䵁䭗㥲敶㉷䅑杷允䅁䅁䅣䅁䑁䅁䅷䅁䭁䥁䝣䅁䭁䝁䝍䅁䭁䅁䅅䅁䙁䅁䅁䅁䅂敢䅚兂䅁䅁䅁䡷浪䅑䅯朰䅣䅁䅅䅁䉁䅁䅁兂扁娲块八㕯䅑杷允䅁䅁䅣䅁䑁䅁䅷䅁䭁䥁䝣䅁䭁䝁䝫䅁䭁䅁䅅䅁䙁䅁䅁䅁䅂敢䅚兂䅁䅁䅁䡷浪䅑䅯䄰䅣䅁䅅䅁䉁䅁䅁兂剃㕶㝥汊㝑䅑杷允䅁䅁䅣䅁䑁䅁䅷䅁䭁䥁䝣䅁䭁䙁䜰䅁䭁䅁䅅䅁䙁䅁䅁䅁䅂敢䅚兂䅁䅁䅁䡷浪䅑䅯䄰䅣䅁䅅䅁䉁䅁䅁兂䵁湵塍祆到䅑杷允䅁䅁䅣䅁䑁䅁䅷䅁䭁䥁䝣䅁䭁䙁䜰䅁䭁䅁䅅䅁䙁䅁䅁䅁䅂敢䅚兂䅁䅁䅁䡷浪䅑䅯眰䅣䅁䅅䅁䉁䅁䅁兂䙃穗匶杫儴䅑杷允䅁䅁䅣䅁䑁䅁䅷䅁䭁䥁䝣䅁䭁䝁䝷䅁䭁䙁䝅䅁䙁䅁䅁䅁䅂敢䅚兂䅁䅁䅁䡷浪䅑䅯䄰䅣䅁䅅䅁䉁䅁䅁兂㍂捐收祦儴䅑杷允䅁䅁䅣䅁䑁䅁䅷䅁䭁䥁䝣䅁䭁䙁䜴䅁䭁䙁䝅䅁䙁䅁䅁䅁䅂敢䅚兂䅁䅁䅁䡷浪䅑䅯朰䅣䅁䅅䅁䉁䅁䅁兂㕂祚晘煬佣䅑杷允䅁䅁䅣䅁䑁䅁䅷䅁䭁䥁䝣䅁䭁䝁䝫䅁䭁䅁䅅䅁䙁䅁䅁䅁䅂敢䅚兂䅁䅁䅁䡷浪䅑䅯儰䅣䅁䅅䅁䉁䅁䅁兂䕂㝉坦っ橢睐杷允䅁䅁䅣䅁䑁䅁䅷䅁䭁䥁䝣䅁䭁䙁䜴䅁䭁䙁䝅䅁䙁䅁䅁䅁䅂敢䅚兂䅁䅁䅁䡷浪䅑䅯眰䅣䅁䅅䅁䉁䅁䅁兂乂畔䅥橸䩯䅑杷允䅁䅁䅙䅁䑁䅁䅷䅁䭁䥁䝣䅁䭁䙁䝯䅁䭁䙁䝅䅁䙁䅁䅁䅁杂敦䅚权婂杂䅁允䅁䅁䅅䅁䭁䑁䅅䅁䵁䅉䅅䅁䙁䅁䅁睁䵁䅁䅁权䡃杂䅁权塃睂䅁兂䅁䅁䅁䙉浌䅑䅯睭䅧䅁䅅䅁䉁䅁䅁兂䅁䅁䅁䉁睸䅑杷允䅁䅁䅕䅁䑁䅁䅷䅁䭁䥁䝣䅁䭁䩁䡣䅁䙁䅁䅁䅁杂敗䅚权扃䅃䅁允䅁䅁䅅䅁䙁䵁ㅐ䙋偹浱䅸䍄䉁䅁䅁兂䅁䅁䅍䅄䅁䅁䅯睨䅙䅁䅯杆䅁䅁䅕䅁䅁䝁䑂欵䭁䙁䝫䅁䉁䅁䅁允䅁䉁䅑偉捣睎䅁䅁䵁䅉䅅䅁䙁䅁䅁睁䵁䅁䅁权䡃杂䅁权坁䅁䅁兂䅁䅁䅁䙙浮䅑䅯兗䅙䅁䅅䅁䉁䅁䅁䅆時㉤㍕䅁䅁䅁杷允䅁䅁䅣䅁䑁䅁䅷䅁䭁䥁䝣䅁䭁䝁䝅䅁䭁䅁䅅䅁䙁䅁䅁䅁䅄佥䅚兂䅁䅁䅁䡙洳䅑䅯䄱䅣䅁䅅䅁䉁䅁䅁兂祄㜰㍧㙶䉎䅑杷允䅁䅁䅣䅁䑁䅁䅷䅁䭁䥁䝣䅁䭁䝁䝑䅁䭁䅁䅅䅁䙁䅁䅁䅁䅄佥䅚兂䅁䅁䅁䡙洳䅑䅯䄰䅣䅁䅅䅁䉁䅁䅁权硁䅁䅁䍄䉁䅁䅁杂䅁䅁䅍䅄䅁䅁䅯睨䅙䅁䅯兘䅙䅁䅯允䅁䅁䅕䅁䅁䝁㥂欵䭁䙁䝫䅁䉁䅁䅁允䅁䅁䅕塩塹灕䵣䕅䵁䅉䅅䅁䡁䅁䅁睁䵁䅁䅁权䡃杂䅁权潂杂䅁权剂杂䅁兂䅁䅁䅁䡷浪䅑䅕䅁䅁䝁㥂欵䭁乁䡍䅁䉁䅁䅁允䅁䅁䅕呍㔱煓䥊ぎ䵁䅉䅅䅁䡁䅁䅁睁䵁䅁䅁权䡃杂䅁权桂杂䅁权䉁䅁䅁兂䅁䅁䅁䡷浪䅑䅕䅁䅁䝁㥂欵䭁乁䡁䅁䉁䅁䅁允䅁䅁䅕⽵癰慌楹䕑䵁䅉䅅䅁䝁䅁䅁睁䵁䅁䅁权䡃杂䅁权㑃睂䅁权㙃睂䅁兂䅁䅁䅁䡙洳䅑䅯䅶䅣䅁䅅䅁䉁䅁䅁睂䅁䅁䅁䙉浌䅑杷允䅁䅁䅕䅁䑁䅁䅷䅁䭁䥁䝣䅁䭁䉁䅙䅁䭁䍁䅅䅁䭁䙁䝫䅁䉁䅁䅁允䅁䉁䅑畚㈲睎䅁䅁䵁䅉䅅䅁䙁䅁䅁睁䵁䅁䅁权䡃杂䅁权塃睂䅁权桁䅁䅁权扃䅃䅁允䅁䅁䅅䅁䙁䅁塲㍯㥁湈䅊䍄䉁䅁䅁睂䅁䅁䅍䅄䅁䅁䅯睨䅙䅁䅯睘䅙䅁䅯兕䅙䅁䅕䅁䅁䵁㑂欵䙁䅁䅁䅁杂敦䅚权卄睂䅁允䅁䅁䅅䅁䙁偁吶牑獯呰䅆䍄䉁䅁䅁兂䅁䅁䅍䅄䅁䅁䅯睨䅙䅁䅯䅳䅧䅁䅯睲䅧䅁䅕䅁䅁䝁㥂欵䉁䅁䅁允䅁䅁䅯关䅧䅁杷允䅁䅁䅣䅁䑁䅁䅷䅁䭁䥁䝣䅁䭁䙁䝙䅁䭁䅁䅅䅁䙁䅁䅁䅁䅄佥䅚兂䅁䅁䅁䡙洳䅑䅯朰䅣䅁䅅䅁䉁䅁䅁兂い坱噏朰噍䅑杷允䅁䅁䅣䅁䑁䅁䅷䅁䭁䥁䝣䅁䭁䙁䝧䅁䭁䅁䅅䅁䙁䅁䅁䅁䅄佥䅚兂䅁䅁䅁䡙洳䅑䅯䄱䅣䅁䅅䅁䉁䅁䅁兂婁穎兘䥦㡯䅑杷允䅁䅁䅣䅁䑁䅁䅷䅁䭁䥁䝣䅁䭁䙁䝙䅁䭁䅁䅅䅁䙁䅁䅁䅁䅄佥䅚兂䅁䅁䅁䡙洳䅑䅯眰䅣䅁䅅䅁䉁䅁䅁兂歂啳焰癇即䅑杷允䅁䅁䅣䅁䑁䅁䅷䅁䭁䥁䝣䅁䭁䙁䝙䅁䭁䅁䅅䅁䙁䅁䅁䅁䅄佥䅚兂䅁䅁䅁䡙洳䅑䅯儰䅣䅁䅅䅁䉁䅁䅁兂慄䑊䭌䩖䅄睐杷允䅁䅁䅣䅁䑁䅁䅷䅁䭁䥁䝣䅁䭁䙁䝁䅁䭁䙁䝅䅁䙁䅁䅁䅁䅄佥䅚兂䅁䅁䅁䡙洳䅑䅯朰䅣䅁䅅䅁䉁䅁䅁兂剄浧坆䴸呷䅑杷允䅁䅁䅙䅁䑁䅁䅷䅁䭁䥁䝣䅁䭁䙁䝁䅁䭁䙁䝅䅁䙁䅁䅁䅁杂敦䅚权婂杂䅁允䅁䅁䅅䅁䭁䑁䅅䅁䵁䅉䅅䅁䡁䅁䅁睁䵁䅁䅁权䡃杂䅁权兂杂䅁权剂杂䅁兂䅁䅁䅁䡷浪䅑䅕䅁䅁䝁㥂欵䭁乁䡑䅁䉁䅁䅁允䅁䅁䅕湕㙁昲畺歅䵁䅉䅅䅁䡁䅁䅁睁䵁䅁䅁权䡃杂䅁权時杂䅁权剂杂䅁兂䅁䅁䅁䡷浪䅑䅕䅁䅁䝁㥂欵䭁乁䡁䅁䉁䅁䅁允䅁䅁䅕䥳呚䵦穈䕍䵁䅉䅅䅁䝁䅁䅁睁䵁䅁䅁权䡃杂䅁权時杂䅁权剂杂䅁兂䅁䅁䅁䡙洳䅑䅯兗䅙䅁䅅䅁䉁䅁䅁权硁䅁䅁䍄䉁䅁䅁睂䅁䅁䅍䅄䅁䅁䅯睨䅙䅁䅯睘䅙䅁䅯兕䅙䅁䅕䅁䅁䵁㑂欵䙁䅁䅁䅁杂敦䅚权啄睂䅁允䅁䅁䅅䅁䙁䡁癋戹扨䐫䅂䍄䉁䅁䅁睂䅁䅁䅍䅄䅁䅁䅯睨䅙䅁䅯杗䅙䅁䅯兕䅙䅁䅕䅁䅁䵁㑂欵䙁䅁䅁䅁杂敦䅚权卄睂䅁允䅁䅁䅅䅁䙁䕁睩䉁穙穑䅨䍄䉁䅁䅁睂䅁䅁䅍䅄䅁䅁䅯睨䅙䅁䅯䅗䅙䅁䅯允䅁䅁䅕䅁䅁䵁㑂欵䙁䅁䅁䅁杂敦䅚权剄睂䅁允䅁䅁䅅䅁䙁乁䵌㄰㥦⭸⽑䍄䉁䅁䅁睂䅁䅁䅍䅄䅁䅁䅯睨䅙䅁䅯杗䅙䅁䅯兕䅙䅁䅕䅁䅁䵁㑂欵䙁䅁䅁䅁杂敦䅚权呄睂䅁允䅁䅁䅅䅁䙁䉁敐煲癊樯䅖䍄䉁䅁䅁睂䅁䅁䅍䅄䅁䅁䅯睨䅙䅁䅯杗䅙䅁䅯兕䅙䅁䅕䅁䅁䵁㑂欵䙁䅁䅁䅁杂敦䅚权啄睂䅁允䅁䅁䅅䅁䙁䍁潁䵸摉橉䅤䍄䉁䅁䅁睂䅁䅁䅍䅄䅁䅁䅯睨䅙䅁䅯兙䅙䅁䅯允䅁䅁䅕䅁䅁䵁㑂欵䙁䅁䅁䅁杂敦䅚权卄睂䅁允䅁䅁䅅䅁䙁䙁瑖㡎㍅ぱ䅊䍄䉁䅁䅁杂䅁䅁䅍䅄䅁䅁䅯睨䅙䅁䅯兙䅙䅁䅯允䅁䅁䅕䅁䅁䝁㥂欵䭁䙁䝫䅁䉁䅁䅁允䅁䅁䅕潴前眫㑔問䵁䅉䅅䅁䝁䅁䅁睁䵁䅁䅁权䡃杂䅁权潂杂䅁权剂杂䅁兂䅁䅁䅁䡙洳䅑䅯兗䅙䅁䅅䅁䉁䅁䅁权硁䅁䅁䍄䉁䅁䅁睂䅁䅁䅍䅄䅁䅁䅯睨䅙䅁䅯睙䅙䅁䅯允䅁䅁䅕䅁䅁䵁㑂欵䙁䅁䅁䅁杂敦䅚权啄睂䅁允䅁䅁䅅䅁䙁䉁⬷煭剸穣䅤䍄䉁䅁䅁睂䅁䅁䅍䅄䅁䅁䅯睨䅙䅁䅯䅡䅙䅁䅯兕䅙䅁䅕䅁䅁䵁㑂欵䙁䅁䅁䅁杂敦䅚权剄睂䅁允䅁䅁䅅䅁䙁乁䕇剡䉗界⽍䍄䉁䅁䅁睂䅁䅁䅍䅄䅁䅁䅯睨䅙䅁䅯兖䅙䅁䅯允䅁䅁䅕䅁䅁䵁㑂欵䙁䅁䅁䅁杂敦䅚权兄睂䅁允䅁䅁䅅䅁䙁䱁楯㍙佴䔴䅖䍄䉁䅁䅁睂䅁䅁䅍䅄䅁䅁䅯睨䅙䅁䅯兖䅙䅁䅯允䅁䅁䅕䅁䅁䵁㑂欵䙁䅁䅁䅁杂敦䅚权卄睂䅁允䅁䅁䅅䅁䙁䑁䌸⽦㕪え䅤䍄䉁䅁䅁睂䅁䅁䅍䅄䅁䅁䅯睨䅙䅁䅯兖䅙䅁䅯允䅁䅁䅕䅁䅁䵁㑂欵䙁䅁䅁䅁杂敦䅚权呄睂䅁允䅁䅁䅅䅁䙁䙁㡴潃硄䕐䅖䍄䉁䅁䅁睂䅁䅁䅍䅄䅁䅁䅯睨䅙䅁䅯兘䅙䅁䅯允䅁䅁䅕䅁䅁䵁㑂欵䙁䅁䅁䅁杂敦䅚权卄睂䅁允䅁䅁䅅䅁䙁䡁⭫⭁乲䈲䅆䍄䉁䅁䅁睂䅁䅁䅍䅄䅁䅁䅯睨䅙䅁䅯兖䅙䅁䅯允䅁䅁䅕䅁䅁䵁㑂欵䙁䅁䅁䅁杂敦䅚权剄睂䅁允䅁䅁䅅䅁䙁乁穔㙡坖偓⽅䍄䉁䅁䅁睂䅁䅁䅍䅄䅁䅁䅯睨䅙䅁䅯兖䅙䅁䅯允䅁䅁䅕䅁䅁䵁㑂欵䙁䅁䅁䅁杂敦䅚权啄睂䅁允䅁䅁䅅䅁䙁䡁塩⽩佨歰䅖䍄䉁䅁䅁睂䅁䅁䅍䅄䅁䅁䅯睨䅙䅁䅯䅖䅙䅁䅯允䅁䅁䅕䅁䅁䵁㑂欵䙁䅁䅁䅁杂敦䅚权卄睂䅁允䅁䅁䅅䅁䙁䩁奮䙦扷椶䅒䍄䉁䅁䅁睂䅁䅁䅍䅄䅁䅁䅯睨䅙䅁䅯䅖䅙䅁䅯允䅁䅁䅕䅁䅁䵁㑂欵䙁䅁䅁䅁杂敦䅚权剄睂䅁允䅁䅁䅅䅁䙁䉁奓噘煘佄⽙䍄䉁䅁䅁睂䅁䅁䅍䅄䅁䅁䅯睨䅙䅁䅯䅖䅙䅁䅯允䅁䅁䅕䅁䅁䵁㑂欵䙁䅁䅁䅁杂敦䅚权啄睂䅁允䅁䅁䅅䅁䙁䍁㑶奢硪楷䅎䍄䉁䅁䅁睂䅁䅁䅍䅄䅁䅁䅯睨䅙䅁䅯条䅙䅁䅯児䅁䅁䅕䅁䅁䵁㑂欵䙁䅁䅁䅁杂敦䅚权兄睂䅁允䅁䅁䅅䅁䙁䩁䝰睴䕫䍧䅆䍄䉁䅁䅁睂䅁䅁䅍䅄䅁䅁䅯睨䅙䅁䅯䅚䅙䅁䅯允䅁䅁䅕䅁䅁䵁㑂欵䙁䅁䅁䅁杂敦䅚权卄睂䅁允䅁䅁䅅䅁䭁䑁䅅䅁䵁䅉䅅䅁䡁䅁䅁睁䵁䅁䅁权䡃杂䅁权歂杂䅁权䉁䅁䅁兂䅁䅁䅁䡷浪䅑䅕䅁䅁䝁㥂欵䭁乁䡍䅁䉁䅁䅁允䅁䅁䅯免䅁䅁杷允䅁䅁䅙䅁䑁䅁䅷䅁䭁䥁䝣䅁䭁䝁䝑䅁䭁䅁䅅䅁䙁䅁䅁䅁杂敦䅚权婂杂䅁允䅁䅁䅅䅁䭁䝁䝕䅁䵁䅉䅅䅁䡁䅁䅁睁䵁䅁䅁权䡃杂䅁权歂杂䅁权䉁䅁䅁兂䅁䅁䅁䡷浪䅑䅕䅁䅁䝁㥂欵䭁乁䡅䅁䉁䅁䅁允䅁䅁䅯免䅁䅁杷允䅁䅁䅣䅁䑁䅁䅷䅁䭁䥁䝣䅁䭁䝁䝉䅁䭁䙁䝅䅁䙁䅁䅁䅁䅄佥䅚兂䅁䅁䅁䡙洳䅑䅯䄰䅣䅁䅅䅁䉁䅁䅁兂千㍍猹塵硫䅑杷允䅁䅁䅣䅁䑁䅁䅷䅁䭁䥁䝣䅁䭁䝁䝉䅁䭁䙁䝅䅁䙁䅁䅁䅁䅄佥䅚兂䅁䅁䅁䡙洳䅑䅯䄱䅣䅁䅅䅁䉁䅁䅁兂畂乗㍱䡓硷䅑杷允䅁䅁䅣䅁䑁䅁䅷䅁䭁䥁䝣䅁䭁䝁䝉䅁䭁䙁䝅䅁䙁䅁䅁䅁䅄佥䅚兂䅁䅁䅁䡙洳䅑䅯儰䅣䅁䅅䅁䉁䅁䅁兂癄䨲㝶⼷摔睐杷允䅁䅁䅣䅁䑁䅁䅷䅁䭁䥁䝣䅁䭁䙁䝷䅁䭁䅁䅅䅁䙁䅁䅁䅁䅄佥䅚兂䅁䅁䅁䡙洳䅑䅯䄰䅣䅁䅅䅁䉁䅁䅁兂呄啭摇桢㕁䅑杷允䅁䅁䅣䅁䑁䅁䅷䅁䭁䥁䝣䅁䭁䙁䝷䅁䭁䅁䅅䅁䙁䅁䅁䅁䅄佥䅚兂䅁䅁䅁䡙洳䅑䅯眰䅣䅁䅅䅁䉁䅁䅁兂㝁愯畁畕㉷䅑杷允䅁䅁䅣䅁䑁䅁䅷䅁䭁䥁䝣䅁䭁䝁䝷䅁䭁䙁䝅䅁䙁䅁䅁䅁䅄佥䅚兂䅁䅁䅁䡙洳䅑䅯䄰䅣䅁䅅䅁䉁䅁䅁兂䥁㡐伸兯內䅑杷允䅁䅁䅣䅁䑁䅁䅷䅁䭁䥁䝣䅁䭁䝁䝷䅁䭁䙁䝅䅁䙁䅁䅁䅁䅄佥䅚兂䅁䅁䅁䡙洳䅑䅯朰䅣䅁䅅䅁䉁䅁䅁兂兄慅啱摹允䅑杷允䅁䅁䅣䅁䑁䅁䅷䅁䭁䥁䝣䅁䭁䝁䝷䅁䭁䙁䝅䅁䙁䅁䅁䅁䅄佥䅚兂䅁䅁䅁䡙洳䅑䅯䄱䅣䅁䅅䅁䉁䅁䅁兂畃浬桇杴兙䅑杷允䅁䅁䅣䅁䑁䅁䅷䅁䭁䥁䝣䅁䭁䝁䝷䅁䭁䙁䝅䅁䙁䅁䅁䅁䅄佥䅚兂䅁䅁䅁䡙洳䅑䅯眰䅣䅁䅅䅁䉁䅁䅁兂㥄硬䭷噣估䅑杷允䅁䅁䅙䅁䑁䅁䅷䅁䭁䥁䝣䅁䭁䝁䝷䅁䭁䙁䝅䅁䙁䅁䅁䅁杂敦䅚权婂杂䅁允䅁䅁䅅䅁䭁䑁䅅䅁䵁䅉䅅䅁䡁䅁䅁睁䵁䅁䅁权䡃杂䅁权灂杂䅁权䉁䅁䅁兂䅁䅁䅁䡷浪䅑䅕䅁䅁䝁㥂欵䭁乁䡉䅁䉁䅁䅁允䅁䅁䅕癋䔲ㅳ㝴䕐䵁䅉䅅䅁䡁䅁䅁睁䵁䅁䅁权䡃杂䅁权灂杂䅁权䉁䅁䅁兂䅁䅁䅁䡷浪䅑䅕䅁䅁䝁㥂欵䭁乁䡁䅁䉁䅁䅁允䅁䅁䅕㤱㑅伱⬯歏䵁䅉䅅䅁䝁䅁䅁睁䵁䅁䅁权䡃杂䅁权灂杂䅁权䉁䅁䅁兂䅁䅁䅁䡙洳䅑䅯兗䅙䅁䅅䅁䉁䅁䅁兂獁塋晥稴㙳䅑杷允䅁䅁䅣䅁䑁䅁䅷䅁䭁䥁䝣䅁䭁䝁䝫䅁䭁䅁䅅䅁䙁䅁䅁䅁䅄佥䅚兂䅁䅁䅁䡙洳䅑䅯儰䅣䅁䅅䅁䉁䅁䅁兂偁䉵摎楏汪睐杷允䅁䅁䅙䅁䑁䅁䅷䅁䭁䥁䝣䅁䭁䙁䜴䅁䭁䙁䝅䅁䙁䅁䅁䅁杂敦䅚权婂杂䅁允䅁䅁䅅䅁䭁䑁䅅䅁䵁䅉䅅䅁䝁䅁䅁睁䵁䅁䅁权䡃杂䅁权㑃睂䅁权㝃睂䅁兂䅁䅁䅁䡙洳䅑䅯䅶䅣䅁䅅䅁䉁䅁䅁睂䅁䅁䅁䙙浮䅑杷允䅁䅁䅙䅁䑁䅁䅷䅁䭁䥁䝣䅁䭁䱁䡧䅁䭁䱁䠰䅁䙁䅁䅁䅁杂敦䅚权㡃睂䅁允䅁䅁䅅䅁䡁䅁䅁䅁䅄佚䅚䍄䉁䅁䅁杂䅁䅁䅍䅄䅁䅁䅯睨䅙䅁䅯䅵䅣䅁䅯䅥䅙䅁䅕䅁䅁䝁㥂欵䭁䱁䡷䅁䉁䅁䅁允䅁䅁䅯光䅁䅁杷允䅁䅁䅕䅁䑁䅁䅷䅁䭁䥁䝣䅁䭁䡁䜰䅁䭁䡁䝧䅁䙁䅁䅁䅁杂敦䅚允䅁䅁䅅䅁䡁䅁䅁䅁䅄佥䅚

Sheet Key_Stats
F2: Key Stats - Standard
B3: Settings: | H3: Contact:
B4: 1) Select S&P Capital IQ Pro Add-In manual refresh option. | H4: Please contact S&P Capital IQ Pro support with any questions or comments:
B5: 2) Enable macros while opening the template. | H5: email: | I5: support.CapIQPro@spglobal.com
B6: 3) For best performance, save this file to your computer, close and then reopen.
B8: Instructions:
B9: Step 1: Enter Ticker-Exchange or Entity ID. | F9: NYSE:IBM | H9: Disclaimer:
B10: Ticker-Exchange Format: AKR-US or NYSE:AKR | H10: Copyright © 2026 S&P Global Market Intelligence LLC (and its affiliates as applicable) – All rights reserved.
B11: Step 2: Enter required Period Format. | F11: FY0 | H11: This model and/or any data in it are provided subject to the written agreement of S&P Global Market | T11: =IF($F$11="FY0","Fiscal Year Ended,","Fiscal Quarter Ended,") -> Fiscal Year Ended,
B12: Format: FY0, FQ0 | H12: Intelligence LLC governing the subscription service to which this model is applied.
T13: $F$11 Format | U13: Current | V13: Previous | W13: Next
B15: Step 3: Enter Valuation Date. | F15: 46059 | T15: Fiscal Year | U15: FY0 | V15: FY-1 | W15: FY+1
T16: Fiscal Quarter | U16: FQ0 | V16: FQ-1 | W16: FQ+1
F17: Currency | H17: Magnitude | I17: Conversion Method | T17: Last Twelve Months | U17: LTM | V17: LTM-1
B18: Step 4: Select Currency, Magnitude & Conversion Method. | F18: U.S. Dollar | H18: Millions | I18: Historical
B20: Step 5: Hit "REFRESH" button.
B25: SPGTable | E25: =$F$9 -> NYSE:IBM | F25: =$F$9 -> NYSE:IBM | G25: =$F$9 -> NYSE:IBM | H25: =$F$9 -> NYSE:IBM | I25: =$F$9 -> NYSE:IBM | J25: =$F$9 -> NYSE:IBM | K25: =$F$9 -> NYSE:IBM | L25: =$F$9 -> NYSE:IBM | ... P25: =$F$9 -> NYSE:IBM
B26: SPGTable | E26: =LEFT(F26,LEN(F26)-1)&RIGHT(F26,1)+1 -> FY-4 | F26: =LEFT(G26,LEN(G26)-1)&RIGHT(G26,1)+1 -> FY-3 | G26: =LEFT(H26,LEN(H26)-1)&RIGHT(H26,1)+1 -> FY-2 | H26: =VLOOKUP($F$11,FormatTable,2,FALSE) -> FY-1 | I26: =$F$11 -> FY0 | J26: LTM | K26: =IF($F$11="LTM","FY0",IF(MID($F$11,2,1)="Q",LEFT($F$11,1)&"Q-3",$F$11)) -> FY0 | L26: =IF(K26="FY0","",LEFT(K26,3)&RIGHT(K26,1)-1) | M26: =IF(K26="FY0","",LEFT(L26,3)&RIGHT(L26,1)-1) | N26: =IF($F$11="LTM","FY+1",VLOOKUP($F$11,FormatTable,3,FALSE)) -> FY+1 | O26: =LEFT(N26,3)&RIGHT(N26,1)+1 -> FY+2 | P26: =LEFT(O26,3)&RIGHT(O26,1)+1 -> FY+3
E27: =IF($F$15="","",$F$15) -> 46059 | F27: =IF($F$15="","",$F$15) -> 46059 | G27: =IF($F$15="","",$F$15) -> 46059 | H27: =IF($F$15="","",$F$15) -> 46059 | I27: =IF($F$15="","",$F$15) -> 46059 | J27: =IF($F$15="","",$F$15) -> 46059 | K27: =IF($F$15="","",$F$15) -> 46059 | L27: =IF($F$15="","",$F$15) -> 46059 | ... P27: =IF($F$15="","",$F$15) -> 46059
C28: IQ_PERIOD_END | D28: SP_REV_DATE_EST | E28: 44561 | F28: 44926 | G28: 45291 | H28: 45657 | I28: 46022 | J28: 46022 | N28: 46387 | O28: 46752 | P28: 47118
E29: =$T$11 -> Fiscal Year Ended, | P29: Source: S&P Capital IQ Pro
B30: KEY FINANCIALS | E30: Actuals | J30: LTM | N30: Estimates
B31: Period Ended | E31: =IF(E28="","",E28) -> 44561 | F31: =IF(F28="","",F28) -> 44926 | G31: =IF(G28="","",G28) -> 45291 | H31: =IF(H28="","",H28) -> 45657 | I31: =IF(I28="","",I28) -> 46022 | J31: =IF(J28="","",J28) -> 46022 | N31: =IF(N28="","",N28) -> 46387 | O31: =IF(O28="","",O28) -> 46752 | P31: =IF(P28="","",P28) -> 47118
B33: Total Revenue | C33: IQ_TOTAL_REV | D33: SP_REV_EST | E33: 57351 | F33: 60530 | G33: 61860 | H33: 62753 | I33: 67535 | J33: 67535 | N33: 71183.312 | O33: 74255.149 | P33: 78520.452
B34: Total Revenues, 1 Year Growth (%) | C34: IQ_TOTAL_REV_1YR_ANN_GROWTH | E34: 3.936 | F34: 5.543 | G34: 2.197 | H34: 1.444 | I34: 7.62 | J34: 7.62 | N34: =IFERROR((N33/K33-1)*100,"-") -> - | O34: =IFERROR(IF($L$26="",(O33/N33-1)*100,(O33/L33-1)*100),"-") -> 4.3153897 | P34: =IFERROR(IF($M$26="",(P33/O33-1)*100,(P33/M33-1)*100),"-") -> 5.7441177
B36: Gross Profit | C36: IQ_GP | E36: 31486 | F36: 32688 | G36: 34300 | H36: 35552 | I36: 39297 | J36: 39297 | N36: =IFERROR((N33*N37)/100,"-") -> 42803.401 | O36: =IFERROR((O33*O37)/100,"-") -> 44966.579 | P36: =IFERROR((P33*P37)/100,"-") -> 47873.975
